Workbook

Sheet Cover
B2: PT Metro Healthcare Indonesia Tbk (CARE) - Model data fundamental 6 tahun & proyeksi ilustratif
B3: Historis FY2020-FY2025 (laporan keuangan konsolidasian audited) | proyeksi ilustratif FY2026-FY2030 | Format: PRO
B5: Penting - sifat dokumen
B6: Bukan rekomendasi | C6: Dokumen ini hanya ringkasan informasi dan analisis data fundamental yang bersumber dari laporan keuangan publik (audited) PT Metro Healthcare Indonesia Tbk. Dokumen ini BUKAN saran atau rekomendasi investasi, bukan ajakan membeli, menjual, atau menahan efek apa pun, dan tidak memuat target atau penilaian nilai wajar. Proyeksi bersifat ilustratif dan dapat berbeda jauh dari realisasi. Data dapat mengandung kesalahan ekstraksi; selalu cek ke laporan asli. Dokumen ini disusun dengan bantuan kecerdasan buatan (AI) dari laporan keuangan publik; kemungkinan kesalahan tetap ada, harap verifikasi ke sumber.
B7: Proyeksi | C7: Angka FY..E adalah proyeksi ILUSTRATIF berbasis asumsi transparan di sheet Asumsi (Base/Bull/Bear), dikalibrasi dari tren FY2022-2025. Tidak ada target, nilai wajar, atau kesimpulan nilai per saham.
B8: Sumber data | C8: Laporan keuangan konsolidasian audited PT Metro Healthcare Indonesia Tbk FY2021-FY2025. Kolom 2021 dari komparatif LK FY2022 (disilangkan ke LK FY2021); kolom 2020 dari komparatif LK FY2021 (ringkasan XBRL IDX tidak dapat diunduh, HTTP 403), tanpa CALK. Lihat Data_Log & Temuan.
B10: Hak cipta & lisensi
B11: Hak cipta | C11: © 2026 Ryant Gabein Pasaribu. Kompilasi, struktur, metodologi, kode akun standar, dan analisis dalam file ini adalah ciptaan Ryant Gabein Pasaribu. Dilisensikan di bawah Creative Commons Atribusi 4.0 Internasional (CC BY 4.0): bebas digunakan dan dibagikan dengan wajib mencantumkan atribusi "Ryant Gabein Pasaribu" dan menyertakan tautan lisensi https://creativecommons.org/licenses/by/4.0/deed.id. Data laporan keuangan bersumber dari laporan publik emiten.
B12: Versi | C12: v1.0
B13: Tanggal terbit | C13: 2026-10-25
B14: ID file | C14: CARE-FY2025-v1.0-21844D70
B16: Format
B17: Data terbuka | C17: Data dan model ini terbuka dan gratis untuk semua orang.
B18: Format output | C18: Tiga format (bukan tingkatan akses, semuanya gratis): Ritel (PDF ringkasan 4 halaman), Akademik (Excel data historis, rasio, rekonsiliasi), Pro (Excel model penuh dengan proyeksi ilustratif & template DCF kosong).
B20: Informasi model
B21: Emiten | C21: PT Metro Healthcare Indonesia Tbk dan Entitas Anaknya (kode CARE) - rumah sakit swasta
B22: Satuan | C22: Rupiah penuh (Ringkasan/Dashboard: Rp miliar); beban & arus kas keluar negatif (kurung)
B23: Tahun historis | C23: FY2020, FY2021, FY2022, FY2023, FY2024, FY2025
B24: Status rekonsiliasi | C24: =Rekonsiliasi!$C$3 -> SEMUA 354 CEK SESUAI EKSPEKTASI
B25: Skenario aktif | C25: =Asumsi!C4 -> Base
B26: Dibangun | C26: 25-10-2026 oleh /workspace/emiten/common/build_model.py --ticker CARE
B28: Daftar sheet
B29: Cover | C29: Sifat dokumen, lisensi, keterangan warna
B30: Panduan | C30: Cara memakai model ini
B31: Ringkasan | C31: Ringkasan siap cetak/PDF (A4): highlights, indikator utama, grafik, tanda perhatian
B32: Dashboard | C32: Indikator & grafik historis + proyeksi ilustratif
B33: Asumsi | C33: Selektor skenario Base/Bull/Bear & driver per tahun, dengan dasar kalibrasi FY2022-2025
B34: IS_Proj | C34: Proyeksi laba rugi (pendapatan per layanan, EBITDA, laba)
B35: BS_Proj | C35: Proyeksi neraca agregat; kas = penyeimbang; cek balance
B36: CF_Proj | C36: Proyeksi arus kas tidak langsung; FCF
B37: Schedules_Proj | C37: Aset tetap, aset takberwujud, sewa, utang, modal kerja
B38: DCF_Template | C38: Kalkulator DCF opsional dengan input KOSONG (tanpa kesimpulan)
B39: Peer | C39: Tabel pembanding fundamental (input kosong, tanpa kelipatan pasar)
B40: IS | C40: Laba rugi & OCI FY2020-2025
... B48: Data_Log | C48: Sumber per tahun, pemetaan akun, override

Sheet Panduan
A1: Panduan pemakaian
A2: Format PRO (model penuh) - gratis & terbuka; bukan rekomendasi investasi
B4: Langkah
B5: 1. Mulai | C5: Baca Cover (sifat dokumen) lalu Ringkasan (siap cetak A4: File > Print/Export PDF untuk sheet Ringkasan).
B6: 2. Data historis | C6: IS, BS, CF berisi angka laporan (biru) dan subtotal rumus (hitam). Baris 3 menyebut sumber tiap kolom; kolom FY2020 berlatar oranye = kolom pertama, dari komparatif LK FY2021 (Temuan C2); FY2021 dari komparatif LK FY2022 (C1).
B7: 3. Rincian & rasio | C7: Schedules memuat rincian catatan (CALK) FY2021-2025; bagian A merangkum angka yang dipakai Rasio. Rasio memakai rumus hidup dan kolom rata-rata FY2022-25.
B8: 4. Cek kualitas | C8: Rekonsiliasi: kolom "Sesuai ekspektasi?" harus ✔ untuk semua baris. ❌ yang diharapkan adalah selisih di laporan sumber dan dijelaskan di kolom Penjelasan / sheet Temuan.
B9: 5. Proyeksi ilustratif | C9: Pilih skenario di Asumsi!C4 (Base/Bull/Bear). Ubah sel biru di blok skenario untuk mencoba asumsi sendiri; IS_Proj, BS_Proj, CF_Proj ikut berubah. Cek BS_Proj baris "Cek" harus 0.
B10: 6. Template DCF (opsional) | C10: Isi sendiri sel kuning (Rf, ERP, beta, Kd, pajak, bobot utang, g / kelipatan). Tanpa input, template tidak menghitung apa pun. Hasil adalah keluaran rumus atas input Anda, bukan nilai wajar atau rekomendasi.
B11: 7. Peer | C11: Isi data fundamental pembanding dari laporan publik masing-masing emiten beserta sumbernya. Tidak ada angka pembanding yang dikarang di file ini.
B13: Keterangan warna
B14: Biru | C14: Input / angka dari laporan (bisa diubah)
B15: Hitam | C15: Rumus di sheet yang sama
B16: Hijau | C16: Rumus yang merujuk sheet lain
B17: Kuning | C17: Sel yang perlu diisi/diverifikasi pengguna atau angka yang dikoreksi (ada komentar sel)
B18: Oranye | C18: Kolom FY2020 (kolom pertama) dari komparatif LK FY2021
B19: Biru muda | C19: Kolom tahun proyeksi (E) - ilustratif
B21: Definisi penting
B22: EBITDA | C22: Laba (rugi) usaha (laba bruto + beban usaha; pendapatan/beban lain disajikan di bawahnya) + penyusutan aset tetap (Cat 21).
B23: Utang | C23: Utang berbunga: pinjaman bank jangka pendek & panjang, pinjaman lembaga keuangan, wesel bayar/sukuk. Utang neto = utang - kas. CARE tidak memiliki liabilitas sewa.
B24: EPS | C24: EPS tercetak memakai saham rata-rata tertimbang (CALK); Rasio juga menyajikan laba induk / saham tercatat (Temuan C3).
B25: Satuan | C25: Rupiah penuh kecuali disebut (Ringkasan/Dashboard: Rp miliar). Beban & arus kas keluar bertanda negatif.
B27: Daftar sheet (format ini)
B28: Cover | C28: Sifat dokumen, lisensi, keterangan warna
B29: Panduan | C29: Cara memakai model ini
B30: Ringkasan | C30: Ringkasan siap cetak/PDF (A4): highlights, indikator utama, grafik, tanda perhatian
B31: Dashboard | C31: Indikator & grafik historis + proyeksi ilustratif
B32: Asumsi | C32: Selektor skenario Base/Bull/Bear & driver per tahun, dengan dasar kalibrasi FY2022-2025
B33: IS_Proj | C33: Proyeksi laba rugi (pendapatan per layanan, EBITDA, laba)
B34: BS_Proj | C34: Proyeksi neraca agregat; kas = penyeimbang; cek balance
B35: CF_Proj | C35: Proyeksi arus kas tidak langsung; FCF
B36: Schedules_Proj | C36: Aset tetap, aset takberwujud, sewa, utang, modal kerja
B37: DCF_Template | C37: Kalkulator DCF opsional dengan input KOSONG (tanpa kesimpulan)
B38: Peer | C38: Tabel pembanding fundamental (input kosong, tanpa kelipatan pasar)
B39: IS | C39: Laba rugi & OCI FY2020-2025
... B47: Data_Log | C47: Sumber per tahun, pemetaan akun, override
B49: Batasan
B50: Data | C50: Angka diekstrak dari PDF dan dapat mengandung kesalahan; cek ke laporan asli sebelum dipakai.
B51: Proyeksi | C51: Asumsi sederhana: pos neraca lain konstan (termasuk investasi jk pendek), utang konstan, beban keuangan = suku bunga x utang, tanpa OCI baru, tanpa pendanaan baru. Hasil sangat sensitif terhadap asumsi.
B52: Bukan saran | C52: Dokumen ini hanya ringkasan informasi dan analisis data fundamental yang bersumber dari laporan keuangan publik (audited) PT Metro Healthcare Indonesia Tbk. Dokumen ini BUKAN saran atau rekomendasi investasi, bukan ajakan membeli, menjual, atau menahan efek apa pun, dan tidak memuat target atau penilaian nilai wajar. Proyeksi bersifat ilustratif dan dapat berbeda jauh dari realisasi. Data dapat mengandung kesalahan ekstraksi; selalu cek ke laporan asli. Dokumen ini disusun dengan bantuan kecerdasan buatan (AI) dari laporan keuangan publik; kemungkinan kesalahan tetap ada, harap verifikasi ke sumber.

Sheet Ringkasan
B1: Metro Healthcare Indonesia (CARE) | Ringkasan FY2020-FY2025
B2: Rumah sakit swasta (Cinere, Ciputat, Cibitung & lainnya) | sumber: laporan keuangan konsolidasian audited | gratis & terbuka | BUKAN rekomendasi investasi
B4: Penting: Dokumen ini hanya ringkasan informasi dan analisis data fundamental yang bersumber dari laporan keuangan publik (audited) PT Metro Healthcare Indonesia Tbk. Dokumen ini BUKAN saran atau rekomendasi investasi, bukan ajakan membeli, menjual, atau menahan efek apa pun, dan tidak memuat target atau penilaian nilai wajar. Proyeksi bersifat ilustratif dan dapat berbeda jauh dari realisasi. Data dapat mengandung kesalahan ekstraksi; selalu cek ke laporan asli. Dokumen ini disusun dengan bantuan kecerdasan buatan (AI) dari laporan keuangan publik; kemungkinan kesalahan tetap ada, harap verifikasi ke sumber.
B6: Ringkasan Eksekutif / Highlights
B7: • Pendapatan neto FY2025 Rp440 miliar (+37,8% vs FY2024), termasuk pendapatan investasi Rp97,8 miliar; pendapatan rumah sakit (rawat inap + rawat jalan) Rp342 miliar.
B8: • Rawat inap tumbuh 16,2% per tahun dan rawat jalan 25,1% per tahun FY2023-2025; porsi rawat jalan 30,2% pendapatan RS FY2025.
B9: • Laba pemilik induk FY2025 Rp5,0 miliar (EPS Rp0,15) setelah rugi tiga tahun (FY2022-2024 total Rp-285 miliar).
B10: • Utang berbunga Rp1.084 miliar vs kas Rp420 miliar (FY2025); beban keuangan Rp80 miliar melebihi EBITDA rumah sakit. Tidak ada dividen FY2020-FY2025.
B11: • Data 6 tahun direkonsiliasi dengan 354 cek; 3 selisih di laporan sumber sudah diperkirakan dan dijelaskan (lihat tanda perhatian & sheet Temuan).
B13: Indikator utama (Rp miliar, kecuali disebut lain) - rumus hidup dari sheet IS/BS/CF/Rasio
B14: Indikator | C14: FY2020A | D14: FY2021A | E14: FY2022A | F14: FY2023A | G14: FY2024A | H14: FY2025A
B15: Pendapatan neto | C15: =IS!C6/1000000000 -> 216.2961 | D15: =IS!D6/1000000000 -> 290.93436 | E15: =IS!E6/1000000000 -> 233.97072 | F15: =IS!F6/1000000000 -> 242.6808 | G15: =IS!G6/1000000000 -> 319.02241 | H15: =IS!H6/1000000000 -> 439.75161
B16: Pertumbuhan | D16: =Rasio!D6 -> 0.34507447 | E16: =Rasio!E6 -> -0.19579548 | F16: =Rasio!F6 -> 0.037227198 | G16: =Rasio!G6 -> 0.31457623 | H16: =Rasio!H6 -> 0.37843484
B17: Porsi rawat jalan | C17: n/a | D17: =Rasio!D25 -> 0.30082755 | E17: =Rasio!E25 -> 0.33346319 | F17: =Rasio!F25 -> 0.27231421 | G17: =Rasio!G25 -> 0.27701089 | H17: =Rasio!H25 -> 0.30223216
B18: EBITDA | C18: n/a | D18: =Rasio!D15/1000000000 -> 31.395271 | E18: =Rasio!E15/1000000000 -> -37.713752 | F18: =Rasio!F15/1000000000 -> -14.553809 | G18: =Rasio!G15/1000000000 -> -4.4118705 | H18: =Rasio!H15/1000000000 -> 96.341924
B19: Margin EBITDA | C19: n/a | D19: =Rasio!D16 -> 0.10791187 | E19: =Rasio!E16 -> -0.16119005 | F19: =Rasio!F16 -> -0.059970996 | G19: =Rasio!G16 -> -0.013829344 | H19: =Rasio!H16 -> 0.2190826
B20: Laba tahun berjalan | C20: =IS!C17/1000000000 -> 14.167951 | D20: =IS!D17/1000000000 -> 6.1736248 | E20: =IS!E17/1000000000 -> -93.604422 | F20: =IS!F17/1000000000 -> -110.68886 | G20: =IS!G17/1000000000 -> -79.91722 | H20: =IS!H17/1000000000 -> 5.1455661
B21: Laba pemilik entitas induk | C21: =IS!C24/1000000000 -> 14.312843 | D21: =IS!D24/1000000000 -> 6.0991939 | E21: =IS!E24/1000000000 -> -93.543897 | F21: =IS!F24/1000000000 -> -110.91979 | G21: =IS!G24/1000000000 -> -80.309181 | H21: =IS!H24/1000000000 -> 4.9527183
B22: Porsi laba ke NCI | C22: =Rasio!C22 -> -0.010226703 | D22: =Rasio!D22 -> 0.012056273 | E22: =Rasio!E22 -> 0.00064660741 | F22: =Rasio!F22 -> -0.0020862705 | G22: =Rasio!G22 -> -0.0049045902 | H22: =Rasio!H22 -> 0.037478444
B23: ROE (rata-rata ekuitas induk) | D23: =Rasio!D19 -> 0.0018518641 | E23: =Rasio!E19 -> -0.028768755 | F23: =Rasio!F19 -> -0.03519918 | G23: =Rasio!G19 -> -0.026273737 | H23: =Rasio!H19 -> 0.001640296
B24: Arus kas operasi | C24: =CF!C14/1000000000 -> 50.302794 | D24: =CF!D14/1000000000 -> 47.12909 | E24: =CF!E14/1000000000 -> -48.836369 | F24: =CF!F14/1000000000 -> -83.033264 | G24: =CF!G14/1000000000 -> -113.01118 | H24: =CF!H14/1000000000 -> 45.886905
B25: Capex | C25: =Rasio!C39/1000000000 -> 522.26812 | D25: =Rasio!D39/1000000000 -> 310.40494 | E25: =Rasio!E39/1000000000 -> 290.45364 | F25: =Rasio!F39/1000000000 -> 12.562011 | G25: =Rasio!G39/1000000000 -> 226.92998 | H25: =Rasio!H39/1000000000 -> 210.75646
B26: Utang neto (utang berbunga - kas) | C26: =Rasio!C34/1000000000 -> -409.31695 | D26: =Rasio!D34/1000000000 -> 301.66334 | E26: =Rasio!E34/1000000000 -> 423.82926 | F26: =Rasio!F34/1000000000 -> 428.75124 | G26: =Rasio!G34/1000000000 -> 495.39694 | H26: =Rasio!H34/1000000000 -> 663.43093
B27: Utang neto / EBITDA (x) | C27: n/a | D27: =Rasio!D36 -> 9.6085597 | E27: =Rasio!E36 -> -11.238056 | F27: =Rasio!F36 -> -29.459727 | G27: =Rasio!G36 -> -112.28728 | H27: =Rasio!H36 -> 6.8862123
B28: DSO piutang (hari) | C28: =Rasio!C27 -> 78.157702 | D28: =Rasio!D27 -> 54.471996 | E28: =Rasio!E27 -> 30.410991 | F28: =Rasio!F27 -> 44.764498 | G28: =Rasio!G27 -> 44.949167 | H28: =Rasio!H27 -> 26.904669
B29: Tarif pajak efektif | C29: =Rasio!C21 -> -0.027198489 | D29: =Rasio!D21 -> 0.051166078 | E29: =Rasio!E21 -> -0.0030912546 | F29: =Rasio!F21 -> -0.043025819 | G29: =Rasio!G21 -> -0.054817048 | H29: =Rasio!H21 -> 0.36248885
B30: Catatan: kolom FY2021 dari komparatif LK FY2022, FY2020 dari komparatif LK FY2021 (EBITDA 2020 tidak dihitung: CALK 2020 tidak dimuat). EBITDA = laba (rugi) usaha + penyusutan aset tetap. Utang = bank + lembaga keuangan + wesel/sukuk.
B32: Tren 6 tahun
B50: Batang = pendapatan RS per layanan (Cat 20, tanpa pendapatan investasi 2025 & diskon); garis putus-putus = porsi rawat jalan (sumbu kanan).
B68: Kiri: margin terhadap pendapatan neto. Kanan: arus kas operasi (abu-abu), capex (arsir), dan sisanya (garis).
B86: Tanda perhatian dari laporan keuangan (bahasa sederhana)
B87: 1. Beban bunga besar - Utang bank, pinjaman lembaga keuangan dan sukuk sekitar Rp1 triliun; bunganya lebih besar dari EBITDA rumah sakit, sehingga laba sangat bergantung pada pendapatan nonoperasi. (Temuan C6)
B88: 2. Pendapatan 2025 termasuk pendapatan investasi - Laba 2025 kembali positif terutama karena pendapatan investasi dicatat di dalam pendapatan; pos ini tidak diasumsikan berulang. (Temuan C5)
B89: 3. Penyajian ulang 2022 - LK 2023 mengubah pendapatan & beban pokok 2022 menjadi bruto (diskon dipindah ke beban pokok); model memakai angka asli, sehingga 2021-2022 vs 2023+ tidak sebanding penuh. (Temuan C4)
B90: 4. Sumber 2020-2021 - Angka 2021 dari kolom pembanding LK 2022 (dicocokkan ke LK 2021); angka 2020 dari kolom pembanding LK 2021 karena ringkasan XBRL BEI tidak dapat diunduh. (Temuan C1, C2)
B91: 5. Kas proyeksi - Pada skenario Base kas dapat menipis/negatif karena rugi dan capex; artinya butuh pendanaan tambahan, yang tidak dimodelkan. (Temuan C7)
B92: Detail lengkap ada di sheet Temuan dan Rekonsiliasi. Tanda perhatian bukan tuduhan kecurangan; ini daftar hal yang perlu dicek ulang ke laporan asli.
B94: Lisensi & format
... B102: Dokumen ini hanya ringkasan informasi dan analisis data fundamental yang bersumber dari laporan keuangan publik (audited) PT Metro Healthcare Indonesia Tbk. Dokumen ini BUKAN saran atau rekomendasi investasi, bukan ajakan membeli, menjual, atau menahan efek apa pun, dan tidak memuat target atau penilaian nilai wajar. Proyeksi bersifat ilustratif dan dapat berbeda jauh dari realisasi. Data dapat mengandung kesalahan ekstraksi; selalu cek ke laporan asli. Dokumen ini disusun dengan bantuan kecerdasan buatan (AI) dari laporan keuangan publik; kemungkinan kesalahan tetap ada, harap verifikasi ke sumber. Penyusun tidak bertanggung jawab atas keputusan apa pun yang diambil berdasarkan dokumen ini. Dokumen ini disusun pada 25-10-2026.

Sheet Dashboard
A1: Dashboard - historis FY2020-FY2025 & proyeksi ilustratif FY2026-FY2030 (skenario aktif)
A2: Rp miliar. Kolom E = Proyeksi ILUSTRATIF berbasis asumsi transparan - bukan rekomendasi investasi, bukan target, bukan nilai wajar. Tidak ada nilai per saham/target di sheet ini.
B3: Skenario aktif: | C3: =Asumsi!C4 -> Base
B4: Indikator | C4: FY2020A | D4: FY2021A | E4: FY2022A | F4: FY2023A | G4: FY2024A | H4: FY2025A | I4: FY2026E | J4: FY2027E | K4: FY2028E | L4: FY2029E | M4: FY2030E | N4: Catatan
B5: Pendapatan neto | C5: =IS_Proj!C9/1000000000 -> 216.2961 | D5: =IS_Proj!D9/1000000000 -> 290.93436 | E5: =IS_Proj!E9/1000000000 -> 233.97072 | F5: =IS_Proj!F9/1000000000 -> 242.6808 | G5: =IS_Proj!G9/1000000000 -> 319.02241 | H5: =IS_Proj!H9/1000000000 -> 439.75161 | I5: =IS_Proj!I9/1000000000 -> 386.08626 | J5: =IS_Proj!J9/1000000000 -> 435.98215 | ... M5: =IS_Proj!M9/1000000000 -> 628.37101
B6: Pertumbuhan pendapatan | D6: =IS_Proj!D10 -> 0.34507447 | E6: =IS_Proj!E10 -> -0.19579548 | F6: =IS_Proj!F10 -> 0.037227198 | G6: =IS_Proj!G10 -> 0.31457623 | H6: =IS_Proj!H10 -> 0.37843484 | I6: =IS_Proj!I10 -> -0.12203558 | J6: =IS_Proj!J10 -> 0.12923507 | K6: =IS_Proj!K10 -> 0.12940489 | ... M6: =IS_Proj!M10 -> 0.12974954
B7: EBITDA | D7: =IS_Proj!D15/1000000000 -> 31.395271 | E7: =IS_Proj!E15/1000000000 -> -37.713752 | F7: =IS_Proj!F15/1000000000 -> -14.553809 | G7: =IS_Proj!G15/1000000000 -> -4.4118705 | H7: =IS_Proj!H15/1000000000 -> 96.341924 | I7: =IS_Proj!I15/1000000000 -> 19.304313 | J7: =IS_Proj!J15/1000000000 -> 21.799107 | K7: =IS_Proj!K15/1000000000 -> 24.620018 | ... M7: =IS_Proj!M15/1000000000 -> 31.418551
B8: Margin EBITDA | D8: =IS_Proj!D29 -> 0.10791187 | E8: =IS_Proj!E29 -> -0.16119005 | F8: =IS_Proj!F29 -> -0.059970996 | G8: =IS_Proj!G29 -> -0.013829344 | H8: =IS_Proj!H29 -> 0.2190826 | I8: =IS_Proj!I29 -> 0.05 | J8: =IS_Proj!J29 -> 0.05 | K8: =IS_Proj!K29 -> 0.05 | ... M8: =IS_Proj!M29 -> 0.05
B9: Laba tahun berjalan | C9: =IS_Proj!C23/1000000000 -> 14.167951 | D9: =IS_Proj!D23/1000000000 -> 6.1736248 | E9: =IS_Proj!E23/1000000000 -> -93.604422 | F9: =IS_Proj!F23/1000000000 -> -110.68886 | G9: =IS_Proj!G23/1000000000 -> -79.91722 | H9: =IS_Proj!H23/1000000000 -> 5.1455661 | I9: =IS_Proj!I23/1000000000 -> -81.870694 | J9: =IS_Proj!J23/1000000000 -> -81.013145 | ... M9: =IS_Proj!M23/1000000000 -> -76.542648
B10: Laba pemilik entitas induk | C10: =IS_Proj!C25/1000000000 -> 14.312843 | D10: =IS_Proj!D25/1000000000 -> 6.0991939 | E10: =IS_Proj!E25/1000000000 -> -93.543897 | F10: =IS_Proj!F25/1000000000 -> -110.91979 | G10: =IS_Proj!G25/1000000000 -> -80.309181 | H10: =IS_Proj!H25/1000000000 -> 4.9527183 | I10: =IS_Proj!I25/1000000000 -> -78.841479 | J10: =IS_Proj!J25/1000000000 -> -78.015659 | ... M10: =IS_Proj!M25/1000000000 -> -73.71057
B11: Arus kas operasi | C11: =CF_Proj!C11/1000000000 -> 50.302794 | D11: =CF_Proj!D11/1000000000 -> 47.12909 | E11: =CF_Proj!E11/1000000000 -> -48.836369 | F11: =CF_Proj!F11/1000000000 -> -83.033264 | G11: =CF_Proj!G11/1000000000 -> -113.01118 | H11: =CF_Proj!H11/1000000000 -> 45.886905 | I11: =CF_Proj!I11/1000000000 -> -62.856401 | J11: =CF_Proj!J11/1000000000 -> -59.565383 | ... M11: =CF_Proj!M11/1000000000 -> -56.01489
B12: Capex | C12: =CF_Proj!C13/1000000000 -> -522.26812 | D12: =CF_Proj!D13/1000000000 -> -310.40494 | E12: =CF_Proj!E13/1000000000 -> -290.45364 | F12: =CF_Proj!F13/1000000000 -> -12.562011 | G12: =CF_Proj!G13/1000000000 -> -226.92998 | H12: =CF_Proj!H13/1000000000 -> -210.75646 | I12: =CF_Proj!I13/1000000000 -> -30.886901 | J12: =CF_Proj!J13/1000000000 -> -34.878572 | ... M12: =CF_Proj!M13/1000000000 -> -50.269681
B13: FCF setelah sewa | C13: =CF_Proj!C27/1000000000 -> -471.96533 | D13: =CF_Proj!D27/1000000000 -> -263.27585 | E13: =CF_Proj!E27/1000000000 -> -339.29001 | F13: =CF_Proj!F27/1000000000 -> -95.595275 | G13: =CF_Proj!G27/1000000000 -> -339.94117 | H13: =CF_Proj!H27/1000000000 -> -164.86956 | I13: =CF_Proj!I27/1000000000 -> -93.743302 | J13: =CF_Proj!J27/1000000000 -> -94.443954 | ... M13: =CF_Proj!M27/1000000000 -> -106.28457
B14: Kas akhir | C14: =BS_Proj!C6/1000000000 -> 525.47969 | D14: =BS_Proj!D6/1000000000 -> 542.40048 | E14: =BS_Proj!E6/1000000000 -> 533.20803 | F14: =BS_Proj!F6/1000000000 -> 525.76295 | G14: =BS_Proj!G6/1000000000 -> 449.06966 | H14: =BS_Proj!H6/1000000000 -> 420.20409 | I14: =BS_Proj!I6/1000000000 -> 326.46079 | J14: =BS_Proj!J6/1000000000 -> 232.01684 | ... M14: =BS_Proj!M6/1000000000 -> -74.350241
B15: Utang neto (utang + sewa - kas) | C15: =BS_Proj!C31/1000000000 -> -409.31695 | D15: =BS_Proj!D31/1000000000 -> 301.66334 | E15: =BS_Proj!E31/1000000000 -> 423.82926 | F15: =BS_Proj!F31/1000000000 -> 428.75124 | G15: =BS_Proj!G31/1000000000 -> 495.39694 | H15: =BS_Proj!H31/1000000000 -> 663.43093 | I15: =BS_Proj!I31/1000000000 -> 757.17424 | J15: =BS_Proj!J31/1000000000 -> 851.61819 | ... M15: =BS_Proj!M31/1000000000 -> 1157.9853
B16: Utang neto / EBITDA | D16: =BS_Proj!D33 -> 9.6085597 | E16: =BS_Proj!E33 -> -11.238056 | F16: =BS_Proj!F33 -> -29.459727 | G16: =BS_Proj!G33 -> -112.28728 | H16: =BS_Proj!H33 -> 6.8862123 | I16: =BS_Proj!I33 -> 39.22306 | J16: =BS_Proj!J33 -> 39.066654 | K16: =BS_Proj!K33 -> 38.573983 | ... M16: =BS_Proj!M33 -> 36.856737
B17: ROE | D17: =BS_Proj!D32 -> 0.0018518641 | E17: =BS_Proj!E32 -> -0.028768755 | F17: =BS_Proj!F32 -> -0.03519918 | G17: =BS_Proj!G32 -> -0.026273737 | H17: =BS_Proj!H32 -> 0.001640296 | I17: =BS_Proj!I32 -> -0.026433611 | J17: =BS_Proj!J32 -> -0.026863104 | K17: =BS_Proj!K32 -> -0.027199395 | ... M17: =BS_Proj!M32 -> -0.027545259
B18: Cek balance BS_Proj (harus 0) | C18: =BS_Proj!C30 -> 0 | D18: =BS_Proj!D30 -> 0 | E18: =BS_Proj!E30 -> 0 | F18: =BS_Proj!F30 -> 0 | G18: =BS_Proj!G30 -> 0 | H18: =BS_Proj!H30 -> 0 | I18: =BS_Proj!I30 -> 0 | J18: =BS_Proj!J30 -> 0 | ... M18: =BS_Proj!M30 -> 0
B19: Status rekonsiliasi | C19: =Rekonsiliasi!$C$3 -> SEMUA 354 CEK SESUAI EKSPEKTASI

Sheet Asumsi
A1: Asumsi proyeksi ilustratif FY2026E-FY2030E (Base / Bull / Bear)
A2: Proyeksi ILUSTRATIF berbasis asumsi transparan - bukan rekomendasi investasi, bukan target, bukan nilai wajar.
A4: Skenario aktif | C4: Base | D4: =IF(C4="Bull",2,IF(C4="Bear",3,1)) -> 1 | E4: <- pilih Base / Bull / Bear. Kolom historis = aktual (rumus dari IS/BS/CF/Schedules); kolom E = asumsi skenario aktif.
A5: Kalibrasi | C5: Asumsi dikalibrasi dari FY2023-FY2025 (RS mulai beroperasi penuh). FY2020-2022 (masa IPO/COVID, basis pendapatan berbeda) tidak dipakai sebagai patokan.
A7: Kunci | B7: Driver | C7: FY2020A | D7: FY2021A | E7: FY2022A | F7: FY2023A | G7: FY2024A | H7: FY2025A | I7: FY2026E | J7: FY2027E | K7: FY2028E | L7: FY2029E | M7: FY2030E | N7: Dasar asumsi (kalibrasi FY2022-FY2025)
B8: ASUMSI AKTIF - kolom historis = aktual (rumus), kolom E = skenario terpilih
B9: PENDAPATAN (per jenis layanan, Cat 20)
A10: g_inpat | B10: Pertumbuhan pendapatan rawat inap | D10: =IFERROR(Schedules!D6/Schedules!C6-1,"") | E10: =IFERROR(Schedules!E6/Schedules!D6-1,"") -> -0.23780263 | F10: =IFERROR(Schedules!F6/Schedules!E6-1,"") -> 0.017350281 | G10: =IFERROR(Schedules!G6/Schedules!F6-1,"") -> 0.3060916 | H10: =IFERROR(Schedules!H6/Schedules!G6-1,"") -> 0.034481309 | I10: =CHOOSE(Asumsi!$D$4,I36,I61,I86) -> 0.12 | J10: =CHOOSE(Asumsi!$D$4,J36,J61,J86) -> 0.12 | K10: =CHOOSE(Asumsi!$D$4,K36,K61,K86) -> 0.12 | L10: =CHOOSE(Asumsi!$D$4,L36,L61,L86) -> 0.12 | M10: =CHOOSE(Asumsi!$D$4,M36,M61,M86) -> 0.12 | N10: Pendapatan: 2022 174 M, 2023 177 M, 2024 231 M, 2025 239 M. CAGR 2023-25 16,2% (fase ramp-up RS baru). Base 12%; Bull 16%; Bear 7%.
A11: g_outpat | B11: Pertumbuhan pendapatan rawat jalan | D11: =IFERROR(Schedules!D7/Schedules!C7-1,"") | E11: =IFERROR(Schedules!E7/Schedules!D7-1,"") -> -0.11374661 | F11: =IFERROR(Schedules!F7/Schedules!E7-1,"") -> -0.23902013 | G11: =IFERROR(Schedules!G7/Schedules!F7-1,"") -> 0.3372491 | H11: =IFERROR(Schedules!H7/Schedules!G7-1,"") -> 0.16946515 | I11: =CHOOSE(Asumsi!$D$4,I37,I62,I87) -> 0.15 | J11: =CHOOSE(Asumsi!$D$4,J37,J62,J87) -> 0.15 | K11: =CHOOSE(Asumsi!$D$4,K37,K62,K87) -> 0.15 | L11: =CHOOSE(Asumsi!$D$4,L37,L62,L87) -> 0.15 | M11: =CHOOSE(Asumsi!$D$4,M37,M62,M87) -> 0.15 | N11: Pendapatan: 2022 87 M, 2023 66 M, 2024 88 M, 2025 103 M. CAGR 2023-25 25,1%. Base 15%; Bull 20%; Bear 9%.
B12: MARGIN & BIAYA (% pendapatan neto)
A13: cogs | B13: Beban pokok di luar penyusutan | C13: =IFERROR(-(IS!C7+Schedules!C12)/IS!C6,"") -> 0.52430277 | D13: =IFERROR(-(IS!D7+Schedules!D12)/IS!D6,"") -> 0.43894136 | E13: =IFERROR(-(IS!E7+Schedules!E12)/IS!E6,"") -> 0.49091966 | F13: =IFERROR(-(IS!F7+Schedules!F12)/IS!F6,"") -> 0.54162322 | G13: =IFERROR(-(IS!G7+Schedules!G12)/IS!G6,"") -> 0.59218078 | H13: =IFERROR(-(IS!H7+Schedules!H12)/IS!H6,"") -> 0.45086354 | I13: =CHOOSE(Asumsi!$D$4,I39,I64,I89) -> 0.57 | J13: =CHOOSE(Asumsi!$D$4,J39,J64,J89) -> 0.57 | K13: =CHOOSE(Asumsi!$D$4,K39,K64,K89) -> 0.57 | L13: =CHOOSE(Asumsi!$D$4,L39,L64,L89) -> 0.57 | M13: =CHOOSE(Asumsi!$D$4,M39,M64,M89) -> 0.57 | N13: Historis: 2022 49,1%, 2023 54,2%, 2024 59,2%, 2025 45,1% (2025 diturunkan oleh pendapatan investasi 97,8 M di pendapatan; Temuan C5). Atas pendapatan RS saja 2025 ±57%. Base 57%; Bull 55%; Bear 60%.
A14: opex | B14: Beban usaha di luar penyusutan | C14: =IFERROR(-(IS!C9+Schedules!C13+Schedules!C16+Schedules!C17)/IS!C6,"") -> 0.54743769 | D14: =IFERROR(-(IS!D9+Schedules!D13+Schedules!D16+Schedules!D17)/IS!D6,"") -> 0.45314676 | E14: =IFERROR(-(IS!E9+Schedules!E13+Schedules!E16+Schedules!E17)/IS!E6,"") -> 0.67027038 | F14: =IFERROR(-(IS!F9+Schedules!F13+Schedules!F16+Schedules!F17)/IS!F6,"") -> 0.51834778 | G14: =IFERROR(-(IS!G9+Schedules!G13+Schedules!G16+Schedules!G17)/IS!G6,"") -> 0.42164856 | H14: =IFERROR(-(IS!H9+Schedules!H13+Schedules!H16+Schedules!H17)/IS!H6,"") -> 0.33005387 | I14: =CHOOSE(Asumsi!$D$4,I40,I65,I90) -> 0.38 | J14: =CHOOSE(Asumsi!$D$4,J40,J65,J90) -> 0.38 | K14: =CHOOSE(Asumsi!$D$4,K40,K65,K90) -> 0.38 | L14: =CHOOSE(Asumsi!$D$4,L40,L65,L90) -> 0.38 | M14: =CHOOSE(Asumsi!$D$4,M40,M65,M90) -> 0.38 | N14: Historis: 2022 67,0%, 2023 51,8%, 2024 42,2%, 2025 33,0%. Atas pendapatan RS saja 2025 ±42%; skala operasi menurunkan rasio. Base 38%; Bull 35%; Bear 42%.
A15: other_op | B15: Pendapatan (beban) lain neto (di bawah laba usaha) | C15: =IFERROR(IS!C12/IS!C6,"") -> 0.0024631428 | D15: =IFERROR(IS!D12/IS!D6,"") -> 0.0084739653 | E15: =IFERROR(IS!E12/IS!E6,"") -> 0.10957279 | F15: =IFERROR(IS!F12/IS!F6,"") -> 0.0010315002 | G15: =IFERROR(IS!G12/IS!G6,"") -> 0.079103768 | H15: =IFERROR(IS!H12/IS!H6,"") -> 0.0064969318 | I15: =CHOOSE(Asumsi!$D$4,I41,I66,I91) -> 0.005 | J15: =CHOOSE(Asumsi!$D$4,J41,J66,J91) -> 0.005 | K15: =CHOOSE(Asumsi!$D$4,K41,K66,K91) -> 0.005 | L15: =CHOOSE(Asumsi!$D$4,L41,L66,L91) -> 0.005 | M15: =CHOOSE(Asumsi!$D$4,M41,M66,M91) -> 0.005 | N15: Historis: 2022 0,0%, 2023 0,0%, 2024 0,0%, 2025 0,0% (2022 & 2024 memuat pos tidak berulang). Base 0,5%; Bull 0,8%; Bear 0,3%.
B16: INVESTASI & ASET
A17: capex | B17: Capex aset tetap + uang muka aset tetap (% pendapatan) | C17: =IFERROR(-(CF!C22+CF!C21)/IS!C6,"") -> 2.414598 | D17: =IFERROR(-(CF!D22+CF!D21)/IS!D6,"") -> 1.0669243 | E17: =IFERROR(-(CF!E22+CF!E21)/IS!E6,"") -> 1.2414102 | F17: =IFERROR(-(CF!F22+CF!F21)/IS!F6,"") -> 0.051763514 | G17: =IFERROR(-(CF!G22+CF!G21)/IS!G6,"") -> 0.71132929 | H17: =IFERROR(-(CF!H22+CF!H21)/IS!H6,"") -> 0.47926252 | I17: =CHOOSE(Asumsi!$D$4,I43,I68,I93) -> 0.08 | J17: =CHOOSE(Asumsi!$D$4,J43,J68,J93) -> 0.08 | K17: =CHOOSE(Asumsi!$D$4,K43,K68,K93) -> 0.08 | L17: =CHOOSE(Asumsi!$D$4,L43,L68,L93) -> 0.08 | M17: =CHOOSE(Asumsi!$D$4,M43,M68,M93) -> 0.08 | N17: Historis kas: 2022 124,1%, 2023 5,2%, 2024 71,1%, 2025 47,9% (pembangunan RS selesai). Base 8%; Bull 6%; Bear 12%.
A18: lease_pd | B18: Penambahan sewa dikapitalisasi (% pendapatan; CARE: tidak ada) | C18: =0 -> 0 | D18: =0 -> 0 | E18: =0 -> 0 | F18: =0 -> 0 | G18: =0 -> 0 | H18: =0 -> 0 | I18: =CHOOSE(Asumsi!$D$4,I44,I69,I94) -> 0 | J18: =CHOOSE(Asumsi!$D$4,J44,J69,J94) -> 0 | K18: =CHOOSE(Asumsi!$D$4,K44,K69,K94) -> 0 | L18: =CHOOSE(Asumsi!$D$4,L44,L69,L94) -> 0 | M18: =CHOOSE(Asumsi!$D$4,M44,M69,M94) -> 0 | N18: CARE tidak memiliki liabilitas sewa; 0 di semua skenario.
A19: dep | B19: Penyusutan aset tetap (% aset tetap neto awal) | D19: =IFERROR(Schedules!D14/BS!C16,"") -> 0.0079516282 | E19: =IFERROR(Schedules!E14/BS!D16,"") -> 0.0078461143 | F19: =IFERROR(Schedules!F14/BS!E16,"") -> 0.0064676906 | G19: =IFERROR(Schedules!G14/BS!F16,"") -> 0.0076614698 | H19: =IFERROR(Schedules!H14/BS!G16,"") -> 0.0080818592 | I19: =CHOOSE(Asumsi!$D$4,I45,I70,I95) -> 0.0074 | J19: =CHOOSE(Asumsi!$D$4,J45,J70,J95) -> 0.0074 | K19: =CHOOSE(Asumsi!$D$4,K45,K70,K95) -> 0.0074 | L19: =CHOOSE(Asumsi!$D$4,L45,L70,L95) -> 0.0074 | M19: =CHOOSE(Asumsi!$D$4,M45,M70,M95) -> 0.0074 | N19: Historis: 2022 0,8%, 2023 0,6%, 2024 0,8%, 2025 0,8% (porsi besar aset tetap = tanah & bangunan dalam penyelesaian). Base/Bull/Bear = rata-rata 2023-25.
A20: sw | B20: Amortisasi aset takberwujud (CARE: goodwill, tidak diamortisasi) | C20: =0 -> 0 | D20: =0 -> 0 | E20: =0 -> 0 | F20: =0 -> 0 | G20: =0 -> 0 | H20: =0 -> 0 | I20: =CHOOSE(Asumsi!$D$4,I46,I71,I96) -> 0 | J20: =CHOOSE(Asumsi!$D$4,J46,J71,J96) -> 0 | K20: =CHOOSE(Asumsi!$D$4,K46,K71,K96) -> 0 | L20: =CHOOSE(Asumsi!$D$4,L46,L71,L96) -> 0 | M20: =CHOOSE(Asumsi!$D$4,M46,M71,M96) -> 0 | N20: Goodwill tidak diamortisasi; 0.
B21: MODAL KERJA (hari, saldo akhir, basis 365)
A22: dso | B22: DSO piutang usaha / pendapatan | C22: =IFERROR(BS!C8/IS!C6*365,"") -> 78.157702 | D22: =IFERROR(BS!D8/IS!D6*365,"") -> 54.471996 | E22: =IFERROR(BS!E8/IS!E6*365,"") -> 30.410991 | F22: =IFERROR(BS!F8/IS!F6*365,"") -> 44.764498 | G22: =IFERROR(BS!G8/IS!G6*365,"") -> 44.949167 | H22: =IFERROR(BS!H8/IS!H6*365,"") -> 26.904669 | I22: =CHOOSE(Asumsi!$D$4,I48,I73,I98) -> 40 | J22: =CHOOSE(Asumsi!$D$4,J48,J73,J98) -> 40 | K22: =CHOOSE(Asumsi!$D$4,K48,K73,K98) -> 40 | L22: =CHOOSE(Asumsi!$D$4,L48,L73,L98) -> 40 | M22: =CHOOSE(Asumsi!$D$4,M48,M73,M98) -> 40 | N22: Historis: 2022 30,4, 2023 44,8, 2024 44,9, 2025 26,9. Base 40; Bull 35; Bear 45.
A23: dio | B23: DIO persediaan / beban pokok di luar penyusutan | C23: =IFERROR(BS!C10/-(IS!C7+Schedules!C12)*365,"") -> 22.105991 | D23: =IFERROR(BS!D10/-(IS!D7+Schedules!D12)*365,"") -> 17.517856 | E23: =IFERROR(BS!E10/-(IS!E7+Schedules!E12)*365,"") -> 12.107786 | F23: =IFERROR(BS!F10/-(IS!F7+Schedules!F12)*365,"") -> 13.269195 | G23: =IFERROR(BS!G10/-(IS!G7+Schedules!G12)*365,"") -> 12.110239 | H23: =IFERROR(BS!H10/-(IS!H7+Schedules!H12)*365,"") -> 9.8392559 | I23: =CHOOSE(Asumsi!$D$4,I49,I74,I99) -> 11 | J23: =CHOOSE(Asumsi!$D$4,J49,J74,J99) -> 11 | K23: =CHOOSE(Asumsi!$D$4,K49,K74,K99) -> 11 | L23: =CHOOSE(Asumsi!$D$4,L49,L74,L99) -> 11 | M23: =CHOOSE(Asumsi!$D$4,M49,M74,M99) -> 11 | N23: Historis: 2022 12,1, 2023 13,3, 2024 12,1, 2025 9,8. Base 11; Bull 10; Bear 12.
A24: dpo | B24: DPO utang usaha / beban pokok di luar penyusutan | C24: =IFERROR(BS!C24/-(IS!C7+Schedules!C12)*365,"") -> 34.831007 | D24: =IFERROR(BS!D24/-(IS!D7+Schedules!D12)*365,"") -> 41.891802 | E24: =IFERROR(BS!E24/-(IS!E7+Schedules!E12)*365,"") -> 85.404129 | F24: =IFERROR(BS!F24/-(IS!F7+Schedules!F12)*365,"") -> 118.10956 | G24: =IFERROR(BS!G24/-(IS!G7+Schedules!G12)*365,"") -> 48.535333 | H24: =IFERROR(BS!H24/-(IS!H7+Schedules!H12)*365,"") -> 38.937891 | I24: =CHOOSE(Asumsi!$D$4,I50,I75,I100) -> 45 | J24: =CHOOSE(Asumsi!$D$4,J50,J75,J100) -> 45 | K24: =CHOOSE(Asumsi!$D$4,K50,K75,K100) -> 45 | L24: =CHOOSE(Asumsi!$D$4,L50,L75,L100) -> 45 | M24: =CHOOSE(Asumsi!$D$4,M50,M75,M100) -> 45 | N24: Historis: 2022 85,4, 2023 118,1, 2024 48,5, 2025 38,9. Base 45; Bull 50; Bear 40.
B25: PAJAK, PENDANAAN, DISTRIBUSI
A26: tax | B26: Tarif pajak (% laba sebelum pajak positif; rugi = 0) | C26: =IFERROR(-IS!C16/IS!C15,"") -> -0.027198489 | D26: =IFERROR(-IS!D16/IS!D15,"") -> 0.051166078 | E26: =IFERROR(-IS!E16/IS!E15,"") -> -0.0030912546 | F26: =IFERROR(-IS!F16/IS!F15,"") -> -0.043025819 | G26: =IFERROR(-IS!G16/IS!G15,"") -> -0.054817048 | H26: =IFERROR(-IS!H16/IS!H15,"") -> 0.36248885 | I26: =CHOOSE(Asumsi!$D$4,I52,I77,I102) -> 0.22 | J26: =CHOOSE(Asumsi!$D$4,J52,J77,J102) -> 0.22 | K26: =CHOOSE(Asumsi!$D$4,K52,K77,K102) -> 0.22 | L26: =CHOOSE(Asumsi!$D$4,L52,L77,L102) -> 0.22 | M26: =CHOOSE(Asumsi!$D$4,M52,M77,M102) -> 0.22 | N26: Historis tarif efektif: 2022 -0,3%, 2023 -4,3%, 2024 -5,5%, 2025 36,2% (tidak bermakna saat rugi; pajak tangguhan). Tarif badan 22% hanya pada laba positif.
A27: fin_cost | B27: Suku bunga efektif (beban keuangan / rata-rata utang berbunga) | D27: =IFERROR(-IS!D14/AVERAGE((BS!D23+BS!D30+BS!D34+BS!D31+BS!D35+BS!D32+BS!D36),(BS!C23+BS!C30+BS!C34+BS!C31+BS!C35+BS!C32+BS!C36)),"") -> 0.053817975 | E27: =IFERROR(-IS!E14/AVERAGE((BS!E23+BS!E30+BS!E34+BS!E31+BS!E35+BS!E32+BS!E36),(BS!D23+BS!D30+BS!D34+BS!D31+BS!D35+BS!D32+BS!D36)),"") -> 0.10010136 | F27: =IFERROR(-IS!F14/AVERAGE((BS!F23+BS!F30+BS!F34+BS!F31+BS!F35+BS!F32+BS!F36),(BS!E23+BS!E30+BS!E34+BS!E31+BS!E35+BS!E32+BS!E36)),"") -> 0.080413901 | G27: =IFERROR(-IS!G14/AVERAGE((BS!G23+BS!G30+BS!G34+BS!G31+BS!G35+BS!G32+BS!G36),(BS!F23+BS!F30+BS!F34+BS!F31+BS!F35+BS!F32+BS!F36)),"") -> 0.081427908 | H27: =IFERROR(-IS!H14/AVERAGE((BS!H23+BS!H30+BS!H34+BS!H31+BS!H35+BS!H32+BS!H36),(BS!G23+BS!G30+BS!G34+BS!G31+BS!G35+BS!G32+BS!G36)),"") -> 0.079243528 | I27: =CHOOSE(Asumsi!$D$4,I53,I78,I103) -> 0.0804 | J27: =CHOOSE(Asumsi!$D$4,J53,J78,J103) -> 0.0804 | K27: =CHOOSE(Asumsi!$D$4,K53,K78,K103) -> 0.0804 | L27: =CHOOSE(Asumsi!$D$4,L53,L78,L103) -> 0.0804 | M27: =CHOOSE(Asumsi!$D$4,M53,M78,M103) -> 0.0804 | N27: Historis: 2023 8,04%, 2024 8,14%, 2025 7,92%. Base = rata-rata 2023-25; Bull x0,9; Bear x1,1. Beban = suku bunga x rata-rata utang (Temuan C6).
A28: yld | B28: Imbal hasil kas (penghasilan keuangan / kas awal) | D28: =IFERROR(IS!D13/BS!C6,"") -> 0.030033394 | E28: =IFERROR(IS!E13/BS!D6,"") -> 0.058600482 | F28: =IFERROR(IS!F13/BS!E6,"") -> 0.012421559 | G28: =IFERROR(IS!G13/BS!F6,"") -> 0.011873623 | H28: =IFERROR(IS!H13/BS!G6,"") -> 0.03463915 | I28: =CHOOSE(Asumsi!$D$4,I54,I79,I104) -> 0.0196 | J28: =CHOOSE(Asumsi!$D$4,J54,J79,J104) -> 0.0196 | K28: =CHOOSE(Asumsi!$D$4,K54,K79,K104) -> 0.0196 | L28: =CHOOSE(Asumsi!$D$4,L54,L79,L104) -> 0.0196 | M28: =CHOOSE(Asumsi!$D$4,M54,M79,M104) -> 0.0196 | N28: Historis: 2022 5,86%, 2023 1,24%, 2024 1,19%, 2025 3,46%. Base = rata-rata 2023-25; Bear x0,8; tanpa circular reference.
A29: debt_chg | B29: Perubahan neto utang (Rp; + = tambah) | D29: =(BS!D23+BS!D30+BS!D34+BS!D31+BS!D35+BS!D32+BS!D36)-(BS!C23+BS!C30+BS!C34+BS!C31+BS!C35+BS!C32+BS!C36) -> 727901075220 | E29: =(BS!E23+BS!E30+BS!E34+BS!E31+BS!E35+BS!E32+BS!E36)-(BS!D23+BS!D30+BS!D34+BS!D31+BS!D35+BS!D32+BS!D36) -> 112973480557 | F29: =(BS!F23+BS!F30+BS!F34+BS!F31+BS!F35+BS!F32+BS!F36)-(BS!E23+BS!E30+BS!E34+BS!E31+BS!E35+BS!E32+BS!E36) -> -2523103518 | G29: =(BS!G23+BS!G30+BS!G34+BS!G31+BS!G35+BS!G32+BS!G36)-(BS!F23+BS!F30+BS!F34+BS!F31+BS!F35+BS!F32+BS!F36) -> -10047593917 | H29: =(BS!H23+BS!H30+BS!H34+BS!H31+BS!H35+BS!H32+BS!H36)-(BS!G23+BS!G30+BS!G34+BS!G31+BS!G35+BS!G32+BS!G36) -> 139168430360 | I29: =CHOOSE(Asumsi!$D$4,I55,I80,I105) -> 0 | J29: =CHOOSE(Asumsi!$D$4,J55,J80,J105) -> 0 | K29: =CHOOSE(Asumsi!$D$4,K55,K80,K105) -> 0 | L29: =CHOOSE(Asumsi!$D$4,L55,L80,L105) -> 0 | M29: =CHOOSE(Asumsi!$D$4,M55,M80,M105) -> 0 | N29: Historis utang berbunga: 2022 957 M, 2023 955 M, 2024 944 M, 2025 1.084 M. Semua skenario 0 (kas = penyeimbang; refinancing tidak dimodelkan).
A30: payout | B30: Payout dividen (% laba induk tahun lalu) | C30: =0 -> 0 | D30: =0 -> 0 | E30: =0 -> 0 | F30: =0 -> 0 | G30: =0 -> 0 | H30: =0 -> 0 | I30: =CHOOSE(Asumsi!$D$4,I56,I81,I106) -> 0 | J30: =CHOOSE(Asumsi!$D$4,J56,J81,J106) -> 0 | K30: =CHOOSE(Asumsi!$D$4,K56,K81,K106) -> 0 | L30: =CHOOSE(Asumsi!$D$4,L56,L81,L106) -> 0 | M30: =CHOOSE(Asumsi!$D$4,M56,M81,M106) -> 0 | N30: CARE tidak membagi dividen FY2020-2025 dan masih defisit; 0 di semua skenario.
A31: nci_share | B31: Porsi laba ke NCI (% laba tahun berjalan) | C31: =IFERROR(IS!C25/IS!C17,"") -> -0.010226703 | D31: =IFERROR(IS!D25/IS!D17,"") -> 0.012056273 | E31: =IFERROR(IS!E25/IS!E17,"") -> 0.00064660741 | F31: =IFERROR(IS!F25/IS!F17,"") -> -0.0020862705 | G31: =IFERROR(IS!G25/IS!G17,"") -> -0.0049045902 | H31: =IFERROR(IS!H25/IS!H17,"") -> 0.037478444 | I31: =CHOOSE(Asumsi!$D$4,I57,I82,I107) -> 0.037 | J31: =CHOOSE(Asumsi!$D$4,J57,J82,J107) -> 0.037 | K31: =CHOOSE(Asumsi!$D$4,K57,K82,K107) -> 0.037 | L31: =CHOOSE(Asumsi!$D$4,L57,L82,L107) -> 0.037 | M31: =CHOOSE(Asumsi!$D$4,M57,M82,M107) -> 0.037 | N31: Historis: 2022 0,1%, 2023 -0,2%, 2024 -0,5%, 2025 3,7%. 3,7% semua skenario.
B34: SKENARIO BASE - input biru per tahun (boleh diubah pengguna)
B35: PENDAPATAN (per jenis layanan, Cat 20)
A36: Base.g_inpat | B36: Pertumbuhan pendapatan rawat inap | I36: 0.12 | J36: 0.12 | K36: 0.12 | L36: 0.12 | M36: 0.12
A37: Base.g_outpat | B37: Pertumbuhan pendapatan rawat jalan | I37: 0.15 | J37: 0.15 | K37: 0.15 | L37: 0.15 | M37: 0.15
B38: MARGIN & BIAYA (% pendapatan neto)
A39: Base.cogs | B39: Beban pokok di luar penyusutan | I39: 0.57 | J39: 0.57 | K39: 0.57 | L39: 0.57 | M39: 0.57
A40: Base.opex | B40: Beban usaha di luar penyusutan | I40: 0.38 | J40: 0.38 | K40: 0.38 | L40: 0.38 | M40: 0.38
A41: Base.other_op | B41: Pendapatan (beban) lain neto (di bawah laba usaha) | I41: 0.005 | J41: 0.005 | K41: 0.005 | L41: 0.005 | M41: 0.005
B42: INVESTASI & ASET
A43: Base.capex | B43: Capex aset tetap + uang muka aset tetap (% pendapatan) | I43: 0.08 | J43: 0.08 | K43: 0.08 | L43: 0.08 | M43: 0.08
A44: Base.lease_pd | B44: Penambahan sewa dikapitalisasi (% pendapatan; CARE: tidak ada) | I44: 0 | J44: 0 | K44: 0 | L44: 0 | M44: 0
A45: Base.dep | B45: Penyusutan aset tetap (% aset tetap neto awal) | I45: 0.0074 | J45: 0.0074 | K45: 0.0074 | L45: 0.0074 | M45: 0.0074
A46: Base.sw | B46: Amortisasi aset takberwujud (CARE: goodwill, tidak diamortisasi) | I46: 0 | J46: 0 | K46: 0 | L46: 0 | M46: 0
B47: MODAL KERJA (hari, saldo akhir, basis 365)
A48: Base.dso | B48: DSO piutang usaha / pendapatan | I48: 40 | J48: 40 | K48: 40 | L48: 40 | M48: 40
A49: Base.dio | B49: DIO persediaan / beban pokok di luar penyusutan | I49: 11 | J49: 11 | K49: 11 | L49: 11 | M49: 11
A50: Base.dpo | B50: DPO utang usaha / beban pokok di luar penyusutan | I50: 45 | J50: 45 | K50: 45 | L50: 45 | M50: 45
B51: PAJAK, PENDANAAN, DISTRIBUSI
A52: Base.tax | B52: Tarif pajak (% laba sebelum pajak positif; rugi = 0) | I52: 0.22 | J52: 0.22 | K52: 0.22 | L52: 0.22 | M52: 0.22
A53: Base.fin_cost | B53: Suku bunga efektif (beban keuangan / rata-rata utang berbunga) | I53: 0.0804 | J53: 0.0804 | K53: 0.0804 | L53: 0.0804 | M53: 0.0804
A54: Base.yld | B54: Imbal hasil kas (penghasilan keuangan / kas awal) | I54: 0.0196 | J54: 0.0196 | K54: 0.0196 | L54: 0.0196 | M54: 0.0196
A55: Base.debt_chg | B55: Perubahan neto utang (Rp; + = tambah) | I55: 0 | J55: 0 | K55: 0 | L55: 0 | M55: 0
A56: Base.payout | B56: Payout dividen (% laba induk tahun lalu) | I56: 0 | J56: 0 | K56: 0 | L56: 0 | M56: 0
A57: Base.nci_share | B57: Porsi laba ke NCI (% laba tahun berjalan) | I57: 0.037 | J57: 0.037 | K57: 0.037 | L57: 0.037 | M57: 0.037
B59: SKENARIO BULL - input biru per tahun (boleh diubah pengguna)
B60: PENDAPATAN (per jenis layanan, Cat 20)
A61: Bull.g_inpat | B61: Pertumbuhan pendapatan rawat inap | I61: 0.16 | J61: 0.16 | K61: 0.16 | L61: 0.16 | M61: 0.16
A62: Bull.g_outpat | B62: Pertumbuhan pendapatan rawat jalan | I62: 0.2 | J62: 0.2 | K62: 0.2 | L62: 0.2 | M62: 0.2
B63: MARGIN & BIAYA (% pendapatan neto)
A64: Bull.cogs | B64: Beban pokok di luar penyusutan | I64: 0.55 | J64: 0.55 | K64: 0.55 | L64: 0.55 | M64: 0.55
A65: Bull.opex | B65: Beban usaha di luar penyusutan | I65: 0.35 | J65: 0.35 | K65: 0.35 | L65: 0.35 | M65: 0.35
A66: Bull.other_op | B66: Pendapatan (beban) lain neto (di bawah laba usaha) | I66: 0.008 | J66: 0.008 | K66: 0.008 | L66: 0.008 | M66: 0.008
B67: INVESTASI & ASET
A68: Bull.capex | B68: Capex aset tetap + uang muka aset tetap (% pendapatan) | I68: 0.06 | J68: 0.06 | K68: 0.06 | L68: 0.06 | M68: 0.06
A69: Bull.lease_pd | B69: Penambahan sewa dikapitalisasi (% pendapatan; CARE: tidak ada) | I69: 0 | J69: 0 | K69: 0 | L69: 0 | M69: 0
A70: Bull.dep | B70: Penyusutan aset tetap (% aset tetap neto awal) | I70: 0.0074 | J70: 0.0074 | K70: 0.0074 | L70: 0.0074 | M70: 0.0074
A71: Bull.sw | B71: Amortisasi aset takberwujud (CARE: goodwill, tidak diamortisasi) | I71: 0 | J71: 0 | K71: 0 | L71: 0 | M71: 0
B72: MODAL KERJA (hari, saldo akhir, basis 365)
A73: Bull.dso | B73: DSO piutang usaha / pendapatan | I73: 35 | J73: 35 | K73: 35 | L73: 35 | M73: 35
A74: Bull.dio | B74: DIO persediaan / beban pokok di luar penyusutan | I74: 10 | J74: 10 | K74: 10 | L74: 10 | M74: 10
A75: Bull.dpo | B75: DPO utang usaha / beban pokok di luar penyusutan | I75: 50 | J75: 50 | K75: 50 | L75: 50 | M75: 50
B76: PAJAK, PENDANAAN, DISTRIBUSI
A77: Bull.tax | B77: Tarif pajak (% laba sebelum pajak positif; rugi = 0) | I77: 0.22 | J77: 0.22 | K77: 0.22 | L77: 0.22 | M77: 0.22
A78: Bull.fin_cost | B78: Suku bunga efektif (beban keuangan / rata-rata utang berbunga) | I78: 0.0724 | J78: 0.0724 | K78: 0.0724 | L78: 0.0724 | M78: 0.0724
A79: Bull.yld | B79: Imbal hasil kas (penghasilan keuangan / kas awal) | I79: 0.0196 | J79: 0.0196 | K79: 0.0196 | L79: 0.0196 | M79: 0.0196
A80: Bull.debt_chg | B80: Perubahan neto utang (Rp; + = tambah) | I80: 0 | J80: 0 | K80: 0 | L80: 0 | M80: 0
A81: Bull.payout | B81: Payout dividen (% laba induk tahun lalu) | I81: 0 | J81: 0 | K81: 0 | L81: 0 | M81: 0
A82: Bull.nci_share | B82: Porsi laba ke NCI (% laba tahun berjalan) | I82: 0.037 | J82: 0.037 | K82: 0.037 | L82: 0.037 | M82: 0.037
B84: SKENARIO BEAR - input biru per tahun (boleh diubah pengguna)
B85: PENDAPATAN (per jenis layanan, Cat 20)
A86: Bear.g_inpat | B86: Pertumbuhan pendapatan rawat inap | I86: 0.07 | J86: 0.07 | K86: 0.07 | L86: 0.07 | M86: 0.07
A87: Bear.g_outpat | B87: Pertumbuhan pendapatan rawat jalan | I87: 0.09 | J87: 0.09 | K87: 0.09 | L87: 0.09 | M87: 0.09
B88: MARGIN & BIAYA (% pendapatan neto)
A89: Bear.cogs | B89: Beban pokok di luar penyusutan | I89: 0.6 | J89: 0.6 | K89: 0.6 | L89: 0.6 | M89: 0.6
A90: Bear.opex | B90: Beban usaha di luar penyusutan | I90: 0.42 | J90: 0.42 | K90: 0.42 | L90: 0.42 | M90: 0.42
A91: Bear.other_op | B91: Pendapatan (beban) lain neto (di bawah laba usaha) | I91: 0.003 | J91: 0.003 | K91: 0.003 | L91: 0.003 | M91: 0.003
B92: INVESTASI & ASET
A93: Bear.capex | B93: Capex aset tetap + uang muka aset tetap (% pendapatan) | I93: 0.12 | J93: 0.12 | K93: 0.12 | L93: 0.12 | M93: 0.12
A94: Bear.lease_pd | B94: Penambahan sewa dikapitalisasi (% pendapatan; CARE: tidak ada) | I94: 0 | J94: 0 | K94: 0 | L94: 0 | M94: 0
A95: Bear.dep | B95: Penyusutan aset tetap (% aset tetap neto awal) | I95: 0.0074 | J95: 0.0074 | K95: 0.0074 | L95: 0.0074 | M95: 0.0074
A96: Bear.sw | B96: Amortisasi aset takberwujud (CARE: goodwill, tidak diamortisasi) | I96: 0 | J96: 0 | K96: 0 | L96: 0 | M96: 0
B97: MODAL KERJA (hari, saldo akhir, basis 365)
A98: Bear.dso | B98: DSO piutang usaha / pendapatan | I98: 45 | J98: 45 | K98: 45 | L98: 45 | M98: 45
A99: Bear.dio | B99: DIO persediaan / beban pokok di luar penyusutan | I99: 12 | J99: 12 | K99: 12 | L99: 12 | M99: 12
A100: Bear.dpo | B100: DPO utang usaha / beban pokok di luar penyusutan | I100: 40 | J100: 40 | K100: 40 | L100: 40 | M100: 40
B101: PAJAK, PENDANAAN, DISTRIBUSI
A102: Bear.tax | B102: Tarif pajak (% laba sebelum pajak positif; rugi = 0) | I102: 0.22 | J102: 0.22 | K102: 0.22 | L102: 0.22 | M102: 0.22
A103: Bear.fin_cost | B103: Suku bunga efektif (beban keuangan / rata-rata utang berbunga) | I103: 0.0884 | J103: 0.0884 | K103: 0.0884 | L103: 0.0884 | M103: 0.0884
A104: Bear.yld | B104: Imbal hasil kas (penghasilan keuangan / kas awal) | I104: 0.0157 | J104: 0.0157 | K104: 0.0157 | L104: 0.0157 | M104: 0.0157
A105: Bear.debt_chg | B105: Perubahan neto utang (Rp; + = tambah) | I105: 0 | J105: 0 | K105: 0 | L105: 0 | M105: 0
A106: Bear.payout | B106: Payout dividen (% laba induk tahun lalu) | I106: 0 | J106: 0 | K106: 0 | L106: 0 | M106: 0
...

Sheet IS_Proj
A1: Proyeksi laba rugi (ilustratif)
A2: Rp penuh | kolom A = aktual (link ke IS/BS/CF/Schedules), kolom E = proyeksi | Proyeksi ILUSTRATIF berbasis asumsi transparan - bukan rekomendasi investasi, bukan target, bukan nilai wajar.
A3: Skenario aktif: | C3: =Asumsi!C4 -> Base | I3: ilustratif | J3: ilustratif | K3: ilustratif | L3: ilustratif | M3: ilustratif
A4: Kode | B4: Akun | C4: FY2020A | D4: FY2021A | E4: FY2022A | F4: FY2023A | G4: FY2024A | H4: FY2025A | I4: FY2026E | J4: FY2027E | K4: FY2028E | L4: FY2029E | M4: FY2030E | N4: Catatan / sumber
B5: PENDAPATAN (per jenis layanan)
A6: P.REV_INPAT | B6: Rawat inap | D6: =Schedules!D6 -> 227741067451 | E6: =Schedules!E6 -> 173583642926 | F6: =Schedules!F6 -> 176595367941 | G6: =Schedules!G6 -> 230649727444 | H6: =Schedules!H6 -> 238602832073 | I6: =H6*(1+Asumsi!I10) -> 2.6723517e+11 | J6: =I6*(1+Asumsi!J10) -> 2.9930339e+11 | K6: =J6*(1+Asumsi!K10) -> 3.352198e+11 | L6: =K6*(1+Asumsi!L10) -> 3.7544618e+11 | M6: =L6*(1+Asumsi!M10) -> 4.2049972e+11
A7: P.REV_OUTPAT | B7: Rawat jalan | D7: =Schedules!D7 -> 97988396120 | E7: =Schedules!E7 -> 86842548252 | F7: =Schedules!F7 -> 66085431242 | G7: =Schedules!G7 -> 88372683358 | H7: =Schedules!H7 -> 103348773155 | I7: =H7*(1+Asumsi!I11) -> 1.1885109e+11 | J7: =I7*(1+Asumsi!J11) -> 1.3667875e+11 | K7: =J7*(1+Asumsi!K11) -> 1.5718057e+11 | L7: =K7*(1+Asumsi!L11) -> 1.8075765e+11 | M7: =L7*(1+Asumsi!M11) -> 2.078713e+11
A8: P.REV_OTHER | B8: Lainnya (pendapatan investasi 2025) & diskon (2021-22) | D8: =Schedules!D8+Schedules!D9 -> -34795107445 | E8: =Schedules!E8+Schedules!E9 -> -26455466569 | F8: =Schedules!F8+Schedules!F9 -> 0 | G8: =Schedules!G8+Schedules!G9 -> 0 | H8: =Schedules!H8+Schedules!H9 -> 97800000000 | I8: =0 -> 0 | J8: =0 -> 0 | K8: =0 -> 0 | L8: =0 -> 0 | M8: =0 -> 0 | N8: E: 0 (tidak berulang; Temuan C4-C5)
A9: P.REVENUE | B9: Pendapatan neto | C9: =IS!C6 -> 216296095571 | D9: =IS!D6 -> 290934356126 | E9: =IS!E6 -> 233970724609 | F9: =IS!F6 -> 242680799183 | G9: =IS!G6 -> 319022410802 | H9: =IS!H6 -> 439751605228 | I9: =I6+I7+I8 -> 3.8608626e+11 | J9: =J6+J7+J8 -> 4.3598215e+11 | K9: =K6+K7+K8 -> 4.9240037e+11 | L9: =L6+L7+L8 -> 5.5620383e+11 | M9: =M6+M7+M8 -> 6.2837101e+11
A10: P.REV_GROWTH | B10: Pertumbuhan pendapatan neto | D10: =D9/C9-1 -> 0.34507447 | E10: =E9/D9-1 -> -0.19579548 | F10: =F9/E9-1 -> 0.037227198 | G10: =G9/F9-1 -> 0.31457623 | H10: =H9/G9-1 -> 0.37843484 | I10: =I9/H9-1 -> -0.12203558 | J10: =J9/I9-1 -> 0.12923507 | K10: =K9/J9-1 -> 0.12940489 | ... M10: =M9/L9-1 -> 0.12974954
B11: BIAYA & EBITDA
A12: P.COGS_X | B12: Beban pokok di luar penyusutan | D12: =IS!D7+Schedules!D12 -> -127703122398 | E12: =IS!E7+Schedules!E12 -> -114860829484 | F12: =IS!F7+Schedules!F12 -> -131441555891 | G12: =IS!G7+Schedules!G12 -> -188918940570 | H12: =IS!H7+Schedules!H12 -> -198267964153 | I12: =-I9*Asumsi!I13 -> -2.2006917e+11 | J12: =-J9*Asumsi!J13 -> -2.4850982e+11 | K12: =-K9*Asumsi!K13 -> -2.8066821e+11 | L12: =-L9*Asumsi!L13 -> -3.1703618e+11 | M12: =-M9*Asumsi!M13 -> -3.5817148e+11
A13: P.GP_X | B13: Laba bruto sebelum penyusutan | D13: =D9+D12 -> 163231233728 | E13: =E9+E12 -> 119109895125 | F13: =F9+F12 -> 111239243292 | G13: =G9+G12 -> 130103470232 | H13: =H9+H12 -> 241483641075 | I13: =I9+I12 -> 1.6601709e+11 | J13: =J9+J12 -> 1.8747232e+11 | K13: =K9+K12 -> 2.1173216e+11 | ... M13: =M9+M12 -> 2.7019954e+11
A14: P.OPEX_X | B14: Beban usaha di luar penyusutan & amortisasi | D14: =IS!D9+Schedules!D13+Schedules!D16+Schedules!D17 -> -131835962281 | E14: =IS!E9+Schedules!E13+Schedules!E16+Schedules!E17 -> -156823647433 | F14: =IS!F9+Schedules!F13+Schedules!F16+Schedules!F17 -> -125793052442 | G14: =IS!G9+Schedules!G13+Schedules!G16+Schedules!G17 -> -134515340769 | H14: =IS!H9+Schedules!H13+Schedules!H16+Schedules!H17 -> -145141717485 | I14: =-I9*Asumsi!I14 -> -1.4671278e+11 | J14: =-J9*Asumsi!J14 -> -1.6567322e+11 | K14: =-K9*Asumsi!K14 -> -1.8711214e+11 | L14: =-L9*Asumsi!L14 -> -2.1135745e+11 | M14: =-M9*Asumsi!M14 -> -2.3878099e+11
A15: P.EBITDA | B15: EBITDA | D15: =D13+D14 -> 31395271447 | E15: =E13+E14 -> -37713752308 | F15: =F13+F14 -> -14553809150 | G15: =G13+G14 -> -4411870537 | H15: =H13+H14 -> 96341923590 | I15: =I13+I14 -> 1.9304313e+10 | J15: =J13+J14 -> 2.1799107e+10 | K15: =K13+K14 -> 2.4620018e+10 | ... M15: =M13+M14 -> 3.1418551e+10 | N15: laba (rugi) usaha + penyusutan aset tetap (FY2020 kosong: Temuan C2)
A16: P.DA | B16: Penyusutan & amortisasi | D16: =-Schedules!D18 -> -17297314280 | E16: =-Schedules!E18 -> -22877629559 | F16: =-Schedules!F18 -> -21584974350 | G16: =-Schedules!G18 -> -25515756073 | H16: =-Schedules!H18 -> -26326052136 | I16: =-(Schedules_Proj!I9+Schedules_Proj!I13) -> -2.4217183e+10 | J16: =-(Schedules_Proj!J9+Schedules_Proj!J13) -> -2.4266539e+10 | K16: =-(Schedules_Proj!K9+Schedules_Proj!K13) -> -2.4345068e+10 | L16: =-(Schedules_Proj!L9+Schedules_Proj!L13) -> -2.4456415e+10 | M16: =-(Schedules_Proj!M9+Schedules_Proj!M13) -> -2.460471e+10
A17: P.EBIT | B17: Laba (rugi) usaha (EBIT) | C17: =IS!C10 -> -15517181073 | D17: =D15+D16 -> 14097957167 | E17: =E15+E16 -> -60591381867 | F17: =F15+F16 -> -36138783500 | G17: =G15+G16 -> -29927626610 | H17: =H15+H16 -> 70015871454 | I17: =I15+I16 -> -4.9128696e+09 | J17: =J15+J16 -> -2.4674313e+09 | K17: =K15+K16 -> 2.7495068e+08 | ... M17: =M15+M16 -> 6.8138404e+09 | N17: historis: = laba usaha IS (cek di Rekonsiliasi)
A18: P.OTHER_OP | B18: Pendapatan (beban) lain neto | C18: =IS!C12 -> 532768164 | D18: =IS!D12 -> 2465367652 | E18: =IS!E12 -> 25636825732 | F18: =IS!F12 -> 250325287 | G18: =IS!G12 -> 25235874672 | H18: =IS!H12 -> 2857036197 | I18: =I9*Asumsi!I15 -> 1.9304313e+09 | J18: =J9*Asumsi!J15 -> 2.1799107e+09 | K18: =K9*Asumsi!K15 -> 2.4620018e+09 | L18: =L9*Asumsi!L15 -> 2.7810191e+09 | M18: =M9*Asumsi!M15 -> 3.1418551e+09
A19: P.FIN_INC | B19: Penghasilan keuangan | C19: =IS!C13 -> 40428301431 | D19: =IS!D13 -> 15781938577 | E19: =IS!E13 -> 31784929332 | F19: =IS!F13 -> 6623274915 | G19: =IS!G13 -> 6242710845 | H19: =IS!H13 -> 15555391585 | I19: =BS_Proj!H6*Asumsi!I28 -> 8.2360003e+09 | J19: =BS_Proj!I6*Asumsi!J28 -> 6.3986315e+09 | K19: =BS_Proj!J6*Asumsi!K28 -> 4.54753e+09 | L19: =BS_Proj!K6*Asumsi!L28 -> 2.6252801e+09 | M19: =BS_Proj!L6*Asumsi!M28 -> 6.2591287e+08 | N19: E: imbal hasil x kas awal
A20: P.FIN_COST | B20: Beban keuangan | C20: =IS!C14 -> -11651080910 | D20: =IS!D14 -> -25838724542 | E20: =IS!E14 -> -90146332117 | F20: =IS!F14 -> -76857656488 | G20: =IS!G14 -> -77315017008 | H20: =IS!H14 -> -80356964083 | I20: =-Schedules_Proj!I24*Asumsi!I27 -> -8.7124256e+10 | J20: =-Schedules_Proj!J24*Asumsi!J27 -> -8.7124256e+10 | K20: =-Schedules_Proj!K24*Asumsi!K27 -> -8.7124256e+10 | L20: =-Schedules_Proj!L24*Asumsi!L27 -> -8.7124256e+10 | M20: =-Schedules_Proj!M24*Asumsi!M27 -> -8.7124256e+10 | N20: E: suku bunga x rata-rata utang (Temuan C6)
A21: P.PBT | B21: Laba sebelum pajak | C21: =C17+C18+C19+C20 -> 13792807612 | D21: =D17+D18+D19+D20 -> 6506538854 | E21: =E17+E18+E19+E20 -> -93315958920 | F21: =F17+F18+F19+F20 -> -106122839786 | G21: =G17+G18+G19+G20 -> -75764058101 | H21: =H17+H18+H19+H20 -> 8071335153 | I21: =I17+I18+I19+I20 -> -8.1870694e+10 | J21: =J17+J18+J19+J20 -> -8.1013145e+10 | ... M21: =M17+M18+M19+M20 -> -7.6542648e+10
A22: P.TAX | B22: Beban pajak | C22: =IS!C16 -> 375143524 | D22: =IS!D16 -> -332914077 | E22: =IS!E16 -> -288463386 | F22: =IS!F16 -> -4566022109 | G22: =IS!G16 -> -4153162003 | H22: =IS!H16 -> -2925769032 | I22: =-MAX(I21,0)*Asumsi!I26 -> 0 | J22: =-MAX(J21,0)*Asumsi!J26 -> 0 | K22: =-MAX(K21,0)*Asumsi!K26 -> 0 | L22: =-MAX(L21,0)*Asumsi!L26 -> 0 | M22: =-MAX(M21,0)*Asumsi!M26 -> 0
A23: P.NI | B23: Laba tahun berjalan | C23: =C21+C22 -> 14167951136 | D23: =D21+D22 -> 6173624777 | E23: =E21+E22 -> -93604422306 | F23: =F21+F22 -> -110688861895 | G23: =G21+G22 -> -79917220104 | H23: =H21+H22 -> 5145566121 | I23: =I21+I22 -> -8.1870694e+10 | J23: =J21+J22 -> -8.1013145e+10 | ... M23: =M21+M22 -> -7.6542648e+10
A24: P.NI_NCI | B24: Diatribusikan ke NCI | C24: =IS!C25 -> -144891428 | D24: =IS!D25 -> 74430906 | E24: =IS!E25 -> -60525313 | F24: =IS!F25 -> 230926912 | G24: =IS!G25 -> 391961217 | H24: =IS!H25 -> 192847813 | I24: =I23*Asumsi!I31 -> -3.0292157e+09 | J24: =J23*Asumsi!J31 -> -2.9974864e+09 | K24: =K23*Asumsi!K31 -> -2.9540716e+09 | L24: =L23*Asumsi!L31 -> -2.8994747e+09 | M24: =M23*Asumsi!M31 -> -2.832078e+09
A25: P.NI_PARENT | B25: Diatribusikan ke pemilik entitas induk | C25: =C23-C24 -> 14312842564 | D25: =D23-D24 -> 6099193871 | E25: =E23-E24 -> -93543896993 | F25: =F23-F24 -> -110919788807 | G25: =G23-G24 -> -80309181321 | H25: =H23-H24 -> 4952718308 | I25: =I23-I24 -> -7.8841479e+10 | J25: =J23-J24 -> -7.8015659e+10 | ... M25: =M23-M24 -> -7.371057e+10
A26: P.EPS | B26: Laba induk per saham (Rp; / 33.250.000.000 saham) | C26: =C25/Asumsi!$C$110 -> 0.43046143 | D26: =D25/Asumsi!$C$110 -> 0.1834344 | E26: =E25/Asumsi!$C$110 -> -2.8133503 | F26: =F25/Asumsi!$C$110 -> -3.3359335 | G26: =G25/Asumsi!$C$110 -> -2.4153137 | H26: =H25/Asumsi!$C$110 -> 0.14895393 | I26: =I25/Asumsi!$C$110 -> -2.3711723 | J26: =J25/Asumsi!$C$110 -> -2.3463356 | ... M26: =M25/Asumsi!$C$110 -> -2.2168592 | N26: saham tetap sejak IPO
B27: MARGIN
A28: P.GM_X | B28: Margin laba bruto sebelum penyusutan | D28: =D13/D9 -> 0.56105864 | E28: =E13/E9 -> 0.50908034 | F28: =F13/F9 -> 0.45837678 | G28: =G13/G9 -> 0.40781922 | H28: =H13/H9 -> 0.54913646 | I28: =I13/I9 -> 0.43 | J28: =J13/J9 -> 0.43 | K28: =K13/K9 -> 0.43 | ... M28: =M13/M9 -> 0.43
A29: P.EBITDA_M | B29: Margin EBITDA | D29: =D15/D9 -> 0.10791187 | E29: =E15/E9 -> -0.16119005 | F29: =F15/F9 -> -0.059970996 | G29: =G15/G9 -> -0.013829344 | H29: =H15/H9 -> 0.2190826 | I29: =I15/I9 -> 0.05 | J29: =J15/J9 -> 0.05 | K29: =K15/K9 -> 0.05 | ... M29: =M15/M9 -> 0.05
A30: P.EBIT_M | B30: Margin EBIT | C30: =C17/C9 -> -0.071740459 | D30: =D17/D9 -> 0.048457519 | E30: =E17/E9 -> -0.25896993 | F30: =F17/F9 -> -0.14891489 | G30: =G17/G9 -> -0.093810421 | H30: =H17/H9 -> 0.15921686 | I30: =I17/I9 -> -0.012724798 | J30: =J17/J9 -> -0.0056594778 | ... M30: =M17/M9 -> 0.010843658
A31: P.NI_M | B31: Margin laba bersih | C31: =C23/C9 -> 0.065502575 | D31: =D23/D9 -> 0.021219992 | E31: =E23/E9 -> -0.40006895 | F31: =F23/F9 -> -0.45610886 | G31: =G23/G9 -> -0.2505066 | H31: =H23/H9 -> 0.011701074 | I31: =I23/I9 -> -0.21205286 | J31: =J23/J9 -> -0.18581758 | ... M31: =M23/M9 -> -0.12181123

Sheet BS_Proj
A1: Proyeksi posisi keuangan agregat (ilustratif)
A2: Rp penuh | kolom A = aktual (link ke IS/BS/CF/Schedules), kolom E = proyeksi | Proyeksi ILUSTRATIF berbasis asumsi transparan - bukan rekomendasi investasi, bukan target, bukan nilai wajar.
A3: Skenario aktif: | C3: =Asumsi!C4 -> Base | I3: ilustratif | J3: ilustratif | K3: ilustratif | L3: ilustratif | M3: ilustratif
A4: Kode | B4: Akun | C4: FY2020A | D4: FY2021A | E4: FY2022A | F4: FY2023A | G4: FY2024A | H4: FY2025A | I4: FY2026E | J4: FY2027E | K4: FY2028E | L4: FY2029E | M4: FY2030E | N4: Catatan / sumber
B5: ASET
A6: PB.CASH | B6: Kas dan setara kas | C6: =BS!C6 -> 525479693804 | D6: =BS!D6 -> 542400475238 | E6: =BS!E6 -> 533208033479 | F6: =BS!F6 -> 525762948837 | G6: =BS!G6 -> 449069663731 | H6: =BS!H6 -> 420204094763 | I6: =CF_Proj!I24 -> 3.2646079e+11 | J6: =CF_Proj!J24 -> 2.3201684e+11 | K6: =CF_Proj!K24 -> 1.3394286e+11 | L6: =CF_Proj!L24 -> 3.193433e+10 | M6: =CF_Proj!M24 -> -7.4350241e+10 | N6: E: penyeimbang dari CF_Proj
A7: PB.AR | B7: Piutang usaha | C7: =BS!C8 -> 46315632063 | D7: =BS!D8 -> 43418562083 | E7: =BS!E8 -> 19493922195 | F7: =BS!F8 -> 29762970115 | G7: =BS!G8 -> 39287099946 | H7: =BS!H8 -> 32414715751 | I7: =Schedules_Proj!I26 -> 4.2310823e+10 | J7: =Schedules_Proj!J26 -> 4.7778865e+10 | K7: =Schedules_Proj!K26 -> 5.3961684e+10 | L7: =Schedules_Proj!L26 -> 6.0953844e+10 | M7: =Schedules_Proj!M26 -> 6.8862577e+10
A8: PB.INV | B8: Persediaan | C8: =BS!C10 -> 6868279382 | D8: =BS!D10 -> 6128999612 | E8: =BS!E10 -> 3810165323 | F8: =BS!F10 -> 4778420963 | G8: =BS!G10 -> 6268091785 | H8: =BS!H10 -> 5344682837 | I8: =Schedules_Proj!I27 -> 6.6322215e+09 | J8: =Schedules_Proj!J27 -> 7.4893371e+09 | K8: =Schedules_Proj!K27 -> 8.4584939e+09 | L8: =Schedules_Proj!L27 -> 9.554515e+09 | M8: =Schedules_Proj!M27 -> 1.0794209e+10
A9: PB.OCA | B9: Aset lancar lainnya | C9: =BS!C15-BS!C6-BS!C8-BS!C10 -> 203189597426 | D9: =BS!D15-BS!D6-BS!D8-BS!D10 -> 662313009876 | E9: =BS!E15-BS!E6-BS!E8-BS!E10 -> 325110362505 | F9: =BS!F15-BS!F6-BS!F8-BS!F10 -> 234215132667 | G9: =BS!G15-BS!G6-BS!G8-BS!G10 -> 48691384911 | H9: =BS!H15-BS!H6-BS!H8-BS!H10 -> 55953490668 | I9: =H9 -> 55953490668 | J9: =I9 -> 55953490668 | K9: =J9 -> 55953490668 | L9: =K9 -> 55953490668 | M9: =L9 -> 55953490668 | N9: termasuk investasi jk pendek; E: konstan
A10: PB.TCA | B10: Jumlah aset lancar | C10: =C6+C7+C8+C9 -> 781853202675 | D10: =D6+D7+D8+D9 -> 1254261046809 | E10: =E6+E7+E8+E9 -> 881622483502 | F10: =F6+F7+F8+F9 -> 794519472582 | G10: =G6+G7+G8+G9 -> 543316240373 | H10: =H6+H7+H8+H9 -> 513916984019 | I10: =I6+I7+I8+I9 -> 4.3135733e+11 | J10: =J6+J7+J8+J9 -> 3.4323853e+11 | ... M10: =M6+M7+M8+M9 -> 6.1260036e+10
A11: PB.PPE | B11: Aset tetap - neto | C11: =BS!C16 -> 2175317280881 | D11: =BS!D16 -> 2915791008035 | E11: =BS!E16 -> 3337354211724 | F11: =BS!F16 -> 3330399614118 | G11: =BS!G16 -> 3257425244004 | H11: =BS!H16 -> 3272592245462 | I11: =Schedules_Proj!I10 -> 3.279262e+12 | J11: =Schedules_Proj!J10 -> 3.289874e+12 | K11: =Schedules_Proj!K10 -> 3.304921e+12 | L11: =Schedules_Proj!L10 -> 3.3249608e+12 | M11: =Schedules_Proj!M10 -> 3.3506258e+12
A12: PB.INTANG | B12: Goodwill | C12: =BS!C17 -> 7024470936 | D12: =BS!D17 -> 6971681464 | E12: =BS!E17 -> 6971681464 | F12: =BS!F17 -> 6971681464 | G12: =BS!G17 -> 0 | H12: =BS!H17 -> 0 | I12: =Schedules_Proj!I15 -> 0 | J12: =Schedules_Proj!J15 -> 0 | K12: =Schedules_Proj!K15 -> 0 | L12: =Schedules_Proj!L15 -> 0 | M12: =Schedules_Proj!M15 -> 0
A13: PB.ONCA | B13: Aset tidak lancar lainnya | C13: =BS!C20-BS!C16-BS!C17 -> 481476309661 | D13: =BS!D20-BS!D16-BS!D17 -> 34188065950 | E13: =BS!E20-BS!E16-BS!E17 -> 8672755722 | F13: =BS!F20-BS!F16-BS!F17 -> 5115489549 | G13: =BS!G20-BS!G16-BS!G17 -> 220363928007 | H13: =BS!H20-BS!H16-BS!H17 -> 389419701284 | I13: =H13 -> 389419701284 | J13: =I13 -> 389419701284 | K13: =J13 -> 389419701284 | L13: =K13 -> 389419701284 | M13: =L13 -> 389419701284 | N13: E: konstan
A14: PB.TNCA | B14: Jumlah aset tidak lancar | C14: =C11+C12+C13 -> 2663818061478 | D14: =D11+D12+D13 -> 2956950755449 | E14: =E11+E12+E13 -> 3352998648910 | F14: =F11+F12+F13 -> 3342486785131 | G14: =G11+G12+G13 -> 3477789172011 | H14: =H11+H12+H13 -> 3662011946746 | I14: =I11+I12+I13 -> 3.6686817e+12 | J14: =J11+J12+J13 -> 3.6792937e+12 | ... M14: =M11+M12+M13 -> 3.7400455e+12
A15: PB.TA | B15: JUMLAH ASET | C15: =C10+C14 -> 3445671264153 | D15: =D10+D14 -> 4211211802258 | E15: =E10+E14 -> 4234621132412 | F15: =F10+F14 -> 4137006257713 | G15: =G10+G14 -> 4021105412384 | H15: =H10+H14 -> 4175928930765 | I15: =I10+I14 -> 4.100039e+12 | J15: =J10+J14 -> 4.0225322e+12 | ... M15: =M10+M14 -> 3.8013056e+12
B16: LIABILITAS
A17: PB.AP | B17: Utang usaha | C17: =BS!C24 -> 10821912088 | D17: =BS!D24 -> 14656750351 | E17: =BS!E24 -> 26875586517 | F17: =BS!F24 -> 42532889111 | G17: =BS!G24 -> 25121215698 | H17: =BS!H24 -> 21151058333 | I17: =Schedules_Proj!I28 -> 2.7131815e+10 | J17: =Schedules_Proj!J28 -> 3.0638197e+10 | K17: =Schedules_Proj!K28 -> 3.460293e+10 | L17: =Schedules_Proj!L28 -> 3.9086652e+10 | M17: =Schedules_Proj!M28 -> 4.4158127e+10
A18: PB.DEBT | B18: Utang berbunga (bank, lembaga keuangan, wesel/sukuk) | C18: =(BS!C23+BS!C30+BS!C34+BS!C31+BS!C35+BS!C32+BS!C36) -> 116162740870 | D18: =(BS!D23+BS!D30+BS!D34+BS!D31+BS!D35+BS!D32+BS!D36) -> 844063816090 | E18: =(BS!E23+BS!E30+BS!E34+BS!E31+BS!E35+BS!E32+BS!E36) -> 957037296647 | F18: =(BS!F23+BS!F30+BS!F34+BS!F31+BS!F35+BS!F32+BS!F36) -> 954514193129 | G18: =(BS!G23+BS!G30+BS!G34+BS!G31+BS!G35+BS!G32+BS!G36) -> 944466599212 | H18: =(BS!H23+BS!H30+BS!H34+BS!H31+BS!H35+BS!H32+BS!H36) -> 1083635029572 | I18: =Schedules_Proj!I23 -> 1083635029572 | J18: =Schedules_Proj!J23 -> 1083635029572 | K18: =Schedules_Proj!K23 -> 1083635029572 | L18: =Schedules_Proj!L23 -> 1083635029572 | M18: =Schedules_Proj!M23 -> 1083635029572
A19: PB.LEASE | B19: Liabilitas sewa (tidak ada) | C19: =0 -> 0 | D19: =0 -> 0 | E19: =0 -> 0 | F19: =0 -> 0 | G19: =0 -> 0 | H19: =0 -> 0 | I19: =Schedules_Proj!I18 -> 0 | J19: =Schedules_Proj!J18 -> 0 | K19: =Schedules_Proj!K18 -> 0 | L19: =Schedules_Proj!L18 -> 0 | M19: =Schedules_Proj!M18 -> 0
A20: PB.OL | B20: Liabilitas lainnya | C20: =BS!C40-BS!C24-(BS!C23+BS!C30+BS!C34+BS!C31+BS!C35+BS!C32+BS!C36) -> 27929171939 | D20: =BS!D40-BS!D24-(BS!D23+BS!D30+BS!D34+BS!D31+BS!D35+BS!D32+BS!D36) -> 54223391980 | E20: =BS!E40-BS!E24-(BS!E23+BS!E30+BS!E34+BS!E31+BS!E35+BS!E32+BS!E36) -> 43816446726 | F20: =BS!F40-BS!F24-(BS!F23+BS!F30+BS!F34+BS!F31+BS!F35+BS!F32+BS!F36) -> 42235167472 | G20: =BS!G40-BS!G24-(BS!G23+BS!G30+BS!G34+BS!G31+BS!G35+BS!G32+BS!G36) -> 33130760746 | H20: =BS!H40-BS!H24-(BS!H23+BS!H30+BS!H34+BS!H31+BS!H35+BS!H32+BS!H36) -> 47287331752 | I20: =H20 -> 47287331752 | J20: =I20 -> 47287331752 | K20: =J20 -> 47287331752 | L20: =K20 -> 47287331752 | M20: =L20 -> 47287331752 | N20: akrual, utang lain, pajak, imbalan kerja, dll; E: konstan
A21: PB.TL | B21: JUMLAH LIABILITAS | C21: =C17+C18+C19+C20 -> 154913824897 | D21: =D17+D18+D19+D20 -> 912943958421 | E21: =E17+E18+E19+E20 -> 1027729329890 | F21: =F17+F18+F19+F20 -> 1039282249712 | G21: =G17+G18+G19+G20 -> 1002718575656 | H21: =H17+H18+H19+H20 -> 1152073419657 | I21: =I17+I18+I19+I20 -> 1.1580542e+12 | J21: =J17+J18+J19+J20 -> 1.1615606e+12 | ... M21: =M17+M18+M19+M20 -> 1.1750805e+12
B22: EKUITAS
A23: PB.EQ_OTHER | B23: Modal & cadangan (selain saldo laba) | C23: =BS!C45-BS!C44 -> 3328284159332 | D23: =BS!D45-BS!D44 -> 3328284159332 | E23: =BS!E45-BS!E44 -> 3328284159332 | F23: =BS!F45-BS!F44 -> 3328284159332 | G23: =BS!G45-BS!G44 -> 3328284159332 | H23: =BS!H45-BS!H44 -> 3328284159332 | I23: =H23 -> 3328284159332 | J23: =I23 -> 3328284159332 | K23: =J23 -> 3328284159332 | L23: =K23 -> 3328284159332 | M23: =L23 -> 3328284159332 | N23: E: konstan
A24: PB.RE | B24: Saldo laba | C24: =BS!C44 -> -38449339396 | D24: =BS!D44 -> -31033031403 | E24: =BS!E44 -> -122376092871 | F24: =BS!F44 -> -231784665472 | G24: =BS!G44 -> -311516892081 | H24: =BS!H44 -> -306241065514 | I24: =H24+IS_Proj!I25+CF_Proj!I19 -> -3.8508254e+11 | J24: =I24+IS_Proj!J25+CF_Proj!J19 -> -4.630982e+11 | K24: =J24+IS_Proj!K25+CF_Proj!K19 -> -5.3998391e+11 | L24: =K24+IS_Proj!L25+CF_Proj!L19 -> -6.1544861e+11 | M24: =L24+IS_Proj!M25+CF_Proj!M19 -> -6.8915918e+11
A25: PB.EQ_PARENT | B25: Ekuitas pemilik entitas induk | C25: =C23+C24 -> 3289834819936 | D25: =D23+D24 -> 3297251127929 | E25: =E23+E24 -> 3205908066461 | F25: =F23+F24 -> 3096499493860 | G25: =G23+G24 -> 3016767267251 | H25: =H23+H24 -> 3022043093818 | I25: =I23+I24 -> 2.9432016e+12 | J25: =J23+J24 -> 2.865186e+12 | ... M25: =M23+M24 -> 2.639125e+12
A26: PB.NCI | B26: Kepentingan nonpengendali | C26: =BS!C46 -> 922619320 | D26: =BS!D46 -> 1016715908 | E26: =BS!E46 -> 983736061 | F26: =BS!F46 -> 1224514141 | G26: =BS!G46 -> 1619569477 | H26: =BS!H46 -> 1812417290 | I26: =H26+IS_Proj!I24 -> -1.2167984e+09 | J26: =I26+IS_Proj!J24 -> -4.2142848e+09 | K26: =J26+IS_Proj!K24 -> -7.1683564e+09 | L26: =K26+IS_Proj!L24 -> -1.0067831e+10 | M26: =L26+IS_Proj!M24 -> -1.2899909e+10 | N26: E: tanpa dividen ke NCI (ilustratif)
A27: PB.TE | B27: JUMLAH EKUITAS | C27: =C25+C26 -> 3290757439256 | D27: =D25+D26 -> 3298267843837 | E27: =E25+E26 -> 3206891802522 | F27: =F25+F26 -> 3097724008001 | G27: =G25+G26 -> 3018386836728 | H27: =H25+H26 -> 3023855511108 | I27: =I25+I26 -> 2.9419848e+12 | J27: =J25+J26 -> 2.8609717e+12 | ... M27: =M25+M26 -> 2.6262251e+12
A28: PB.TLE | B28: JUMLAH LIABILITAS DAN EKUITAS | C28: =C21+C27 -> 3445671264153 | D28: =D21+D27 -> 4211211802258 | E28: =E21+E27 -> 4234621132412 | F28: =F21+F27 -> 4137006257713 | G28: =G21+G27 -> 4021105412384 | H28: =H21+H27 -> 4175928930765 | I28: =I21+I27 -> 4.100039e+12 | J28: =J21+J27 -> 4.0225322e+12 | ... M28: =M21+M27 -> 3.8013056e+12
A30: PB.CHECK | B30: Cek: aset - (liabilitas + ekuitas), harus 0 | C30: =ROUND(C15-C28,0) -> 0 | D30: =ROUND(D15-D28,0) -> 0 | E30: =ROUND(E15-E28,0) -> 0 | F30: =ROUND(F15-F28,0) -> 0 | G30: =ROUND(G15-G28,0) -> 0 | H30: =ROUND(H15-H28,0) -> 0 | I30: =ROUND(I15-I28,0) -> 0 | J30: =ROUND(J15-J28,0) -> 0 | ... M30: =ROUND(M15-M28,0) -> 0
A31: PB.NETDEBT | B31: Memo: utang neto (utang berbunga - kas) | C31: =C18+C19-C6 -> -409316952934 | D31: =D18+D19-D6 -> 301663340852 | E31: =E18+E19-E6 -> 423829263168 | F31: =F18+F19-F6 -> 428751244292 | G31: =G18+G19-G6 -> 495396935481 | H31: =H18+H19-H6 -> 663430934809 | I31: =I18+I19-I6 -> 7.5717424e+11 | J31: =J18+J19-J6 -> 8.5161819e+11 | ... M31: =M18+M19-M6 -> 1.1579853e+12
A32: PB.ROE | B32: Memo: ROE (laba induk / rata-rata ekuitas induk) | D32: =IS_Proj!D25/AVERAGE(C25,D25) -> 0.0018518641 | E32: =IS_Proj!E25/AVERAGE(D25,E25) -> -0.028768755 | F32: =IS_Proj!F25/AVERAGE(E25,F25) -> -0.03519918 | G32: =IS_Proj!G25/AVERAGE(F25,G25) -> -0.026273737 | H32: =IS_Proj!H25/AVERAGE(G25,H25) -> 0.001640296 | I32: =IS_Proj!I25/AVERAGE(H25,I25) -> -0.026433611 | J32: =IS_Proj!J25/AVERAGE(I25,J25) -> -0.026863104 | K32: =IS_Proj!K25/AVERAGE(J25,K25) -> -0.027199395 | ... M32: =IS_Proj!M25/AVERAGE(L25,M25) -> -0.027545259
A33: PB.ND_EBITDA | B33: Memo: utang neto / EBITDA | D33: =D31/IS_Proj!D15 -> 9.6085597 | E33: =E31/IS_Proj!E15 -> -11.238056 | F33: =F31/IS_Proj!F15 -> -29.459727 | G33: =G31/IS_Proj!G15 -> -112.28728 | H33: =H31/IS_Proj!H15 -> 6.8862123 | I33: =I31/IS_Proj!I15 -> 39.22306 | J33: =J31/IS_Proj!J15 -> 39.066654 | K33: =K31/IS_Proj!K15 -> 38.573983 | ... M33: =M31/IS_Proj!M15 -> 36.856737

Sheet CF_Proj
A1: Proyeksi arus kas (metode tidak langsung untuk tahun E)
A2: Rp penuh | kolom A = aktual (link ke IS/BS/CF/Schedules), kolom E = proyeksi | Proyeksi ILUSTRATIF berbasis asumsi transparan - bukan rekomendasi investasi, bukan target, bukan nilai wajar.
A3: Skenario aktif: | C3: =Asumsi!C4 -> Base | I3: ilustratif | J3: ilustratif | K3: ilustratif | L3: ilustratif | M3: ilustratif
A4: Kode | B4: Akun | C4: FY2020A | D4: FY2021A | E4: FY2022A | F4: FY2023A | G4: FY2024A | H4: FY2025A | I4: FY2026E | J4: FY2027E | K4: FY2028E | L4: FY2029E | M4: FY2030E | N4: Catatan / sumber
B5: ARUS KAS OPERASI
A6: PC.NI | B6: Laba tahun berjalan | C6: =IS_Proj!C23 -> 14167951136 | D6: =IS_Proj!D23 -> 6173624777 | E6: =IS_Proj!E23 -> -93604422306 | F6: =IS_Proj!F23 -> -110688861895 | G6: =IS_Proj!G23 -> -79917220104 | H6: =IS_Proj!H23 -> 5145566121 | I6: =IS_Proj!I23 -> -8.1870694e+10 | J6: =IS_Proj!J23 -> -8.1013145e+10 | ... M6: =IS_Proj!M23 -> -7.6542648e+10
A7: PC.DA | B7: Penyusutan & amortisasi (nonkas) | I7: =-IS_Proj!I16 -> 2.4217183e+10 | J7: =-IS_Proj!J16 -> 2.4266539e+10 | K7: =-IS_Proj!K16 -> 2.4345068e+10 | L7: =-IS_Proj!L16 -> 2.4456415e+10 | M7: =-IS_Proj!M16 -> 2.460471e+10
A8: PC.D_AR | B8: (Kenaikan) piutang usaha | I8: =BS_Proj!H7-BS_Proj!I7 -> -9.8961074e+09 | J8: =BS_Proj!I7-BS_Proj!J7 -> -5.4680421e+09 | K8: =BS_Proj!J7-BS_Proj!K7 -> -6.1828186e+09 | L8: =BS_Proj!K7-BS_Proj!L7 -> -6.9921601e+09 | M8: =BS_Proj!L7-BS_Proj!M7 -> -7.908733e+09
A9: PC.D_INV | B9: (Kenaikan) persediaan | I9: =BS_Proj!H8-BS_Proj!I8 -> -1.2875387e+09 | J9: =BS_Proj!I8-BS_Proj!J8 -> -8.571156e+08 | K9: =BS_Proj!J8-BS_Proj!K8 -> -9.6915682e+08 | L9: =BS_Proj!K8-BS_Proj!L8 -> -1.0960211e+09 | M9: =BS_Proj!L8-BS_Proj!M8 -> -1.2396939e+09
A10: PC.D_AP | B10: Kenaikan utang usaha | I10: =BS_Proj!I17-BS_Proj!H17 -> 5.980757e+09 | J10: =BS_Proj!J17-BS_Proj!I17 -> 3.506382e+09 | K10: =BS_Proj!K17-BS_Proj!J17 -> 3.9647324e+09 | L10: =BS_Proj!L17-BS_Proj!K17 -> 4.4837227e+09 | M10: =BS_Proj!M17-BS_Proj!L17 -> 5.071475e+09
A11: PC.CFO | B11: Arus kas operasi | C11: =CF!C14 -> 50302794090 | D11: =CF!D14 -> 47129089642 | E11: =CF!E14 -> -48836369112 | F11: =CF!F14 -> -83033264168 | G11: =CF!G14 -> -113011184320 | H11: =CF!H14 -> 45886904636 | I11: =I6+I7+I8+I9+I10 -> -6.2856401e+10 | J11: =J6+J7+J8+J9+J10 -> -5.9565383e+10 | K11: =K6+K7+K8+K9+K10 -> -5.8681949e+10 | L11: =L6+L7+L8+L9+L10 -> -5.7512224e+10 | M11: =M6+M7+M8+M9+M10 -> -5.601489e+10 | N11: historis: laporan (metode langsung); E: tidak langsung
B12: ARUS KAS INVESTASI
A13: PC.CAPEX | B13: Capex aset tetap + uang muka | C13: =CF!C22+CF!C21 -> -522268123814 | D13: =CF!D22+CF!D21 -> -310404936909 | E13: =CF!E22+CF!E21 -> -290453639673 | F13: =CF!F22+CF!F21 -> -12562010950 | G13: =CF!G22+CF!G21 -> -226929983578 | H13: =CF!H22+CF!H21 -> -210756461260 | I13: =-Schedules_Proj!I7 -> -3.0886901e+10 | J13: =-Schedules_Proj!J7 -> -3.4878572e+10 | K13: =-Schedules_Proj!K7 -> -3.9392029e+10 | L13: =-Schedules_Proj!L7 -> -4.4496306e+10 | M13: =-Schedules_Proj!M7 -> -5.0269681e+10
A14: PC.SW | B14: Capex aset takberwujud (tidak ada) | C14: =0 -> 0 | D14: =0 -> 0 | E14: =0 -> 0 | F14: =0 -> 0 | G14: =0 -> 0 | H14: =0 -> 0 | I14: =-Schedules_Proj!I14 -> 0 | J14: =-Schedules_Proj!J14 -> 0 | K14: =-Schedules_Proj!K14 -> 0 | L14: =-Schedules_Proj!L14 -> 0 | M14: =-Schedules_Proj!M14 -> 0
A15: PC.CFI | B15: Arus kas investasi | C15: =CF!C23 -> -502268123814 | D15: =CF!D23 -> -760313339809 | E15: =CF!E23 -> 39827160327 | F15: =CF!F23 -> 78509989050 | G15: =CF!G23 -> 42526142886 | H15: =CF!H23 -> -218206301905 | I15: =I13+I14 -> -3.0886901e+10 | J15: =J13+J14 -> -3.4878572e+10 | K15: =K13+K14 -> -3.9392029e+10 | L15: =L13+L14 -> -4.4496306e+10 | M15: =M13+M14 -> -5.0269681e+10 | N15: historis: total laporan (termasuk penempatan/pencairan deposito & akuisisi)
B16: ARUS KAS PENDANAAN
A17: PC.DEBT | B17: Perubahan neto utang berbunga (kas) | C17: =(CF!C25+CF!C26+CF!C27+CF!C28+CF!C29+CF!C30+CF!C31+CF!C32+CF!C33) -> -16561701376 | D17: =(CF!D25+CF!D26+CF!D27+CF!D28+CF!D29+CF!D30+CF!D31+CF!D32+CF!D33) -> 727901075221 | E17: =(CF!E25+CF!E26+CF!E27+CF!E28+CF!E29+CF!E30+CF!E31+CF!E32+CF!E33) -> -243121219 | F17: =(CF!F25+CF!F26+CF!F27+CF!F28+CF!F29+CF!F30+CF!F31+CF!F32+CF!F33) -> -3317513427 | G17: =(CF!G25+CF!G26+CF!G27+CF!G28+CF!G29+CF!G30+CF!G31+CF!G32+CF!G33) -> -5763124276 | H17: =(CF!H25+CF!H26+CF!H27+CF!H28+CF!H29+CF!H30+CF!H31+CF!H32+CF!H33) -> 142165771092 | I17: =Asumsi!I29 -> 0 | J17: =Asumsi!J29 -> 0 | K17: =Asumsi!K29 -> 0 | L17: =Asumsi!L29 -> 0 | M17: =Asumsi!M29 -> 0
A18: PC.LEASE | B18: Pembayaran sewa (tidak ada) | C18: =0 -> 0 | D18: =0 -> 0 | E18: =0 -> 0 | F18: =0 -> 0 | G18: =0 -> 0 | H18: =0 -> 0 | I18: =-Schedules_Proj!I8 -> 0 | J18: =-Schedules_Proj!J8 -> 0 | K18: =-Schedules_Proj!K8 -> 0 | L18: =-Schedules_Proj!L8 -> 0 | M18: =-Schedules_Proj!M8 -> 0
A19: PC.DIV | B19: Dividen dibayar | C19: =CF!C38 -> 0 | D19: =CF!D38 -> 0 | E19: =CF!E38 -> 0 | F19: =CF!F38 -> 0 | G19: =CF!G38 -> 0 | H19: =CF!H38 -> 0 | I19: =-Asumsi!I30*MAX(IS_Proj!H25,0) -> 0 | J19: =-Asumsi!J30*MAX(IS_Proj!I25,0) -> 0 | K19: =-Asumsi!K30*MAX(IS_Proj!J25,0) -> 0 | L19: =-Asumsi!L30*MAX(IS_Proj!K25,0) -> 0 | M19: =-Asumsi!M30*MAX(IS_Proj!L25,0) -> 0
A20: PC.CFF | B20: Arus kas pendanaan | C20: =CF!C39 -> 970495601854 | D20: =CF!D39 -> 727451787424 | E20: =CF!E39 -> 249408214 | F20: =CF!F39 -> -2921809524 | G20: =CF!G39 -> -6208243672 | H20: =CF!H39 -> 143453828301 | I20: =I17+I18+I19 -> 0 | J20: =J17+J18+J19 -> 0 | K20: =K17+K18+K19 -> 0 | L20: =L17+L18+L19 -> 0 | M20: =M17+M18+M19 -> 0 | N20: historis: total laporan
A22: PC.NET | B22: Kenaikan (penurunan) neto kas | C22: =C11+C15+C20 -> 518530272130 | D22: =D11+D15+D20 -> 14267537257 | E22: =E11+E15+E20 -> -8759800571 | F22: =F11+F15+F20 -> -7445084642 | G22: =G11+G15+G20 -> -76693285106 | H22: =H11+H15+H20 -> -28865568968 | I22: =I11+I15+I20 -> -9.3743302e+10 | J22: =J11+J15+J20 -> -9.4443954e+10 | ... M22: =M11+M15+M20 -> -1.0628457e+11
A23: PC.CASH_BEGIN | B23: Kas awal tahun | C23: =CF!C41 -> 6949421674 | D23: =CF!D41 -> 525479693804 | E23: =CF!E41 -> 542400475238 | F23: =CF!F41 -> 533208033479 | G23: =CF!G41 -> 525762948837 | H23: =CF!H41 -> 449069663731 | I23: =BS_Proj!H6 -> 420204094763 | J23: =BS_Proj!I6 -> 3.2646079e+11 | K23: =BS_Proj!J6 -> 2.3201684e+11 | L23: =BS_Proj!K6 -> 1.3394286e+11 | M23: =BS_Proj!L6 -> 3.193433e+10 | N23: E: kas neraca
A24: PC.CASH_END | B24: Kas akhir tahun | C24: =C23+C22 -> 525479693804 | D24: =D23+D22 -> 539747231061 | E24: =E23+E22 -> 533640674667 | F24: =F23+F22 -> 525762948837 | G24: =G23+G22 -> 449069663731 | H24: =H23+H22 -> 420204094763 | I24: =I23+I22 -> 3.2646079e+11 | J24: =J23+J22 -> 2.3201684e+11 | ... M24: =M23+M22 -> -7.4350241e+10
B25: MEMO: ARUS KAS BEBAS
A26: PC.FCF | B26: FCF = arus kas operasi + capex | C26: =C11+C13+N(C14) -> -471965329724 | D26: =D11+D13+N(D14) -> -263275847267 | E26: =E11+E13+N(E14) -> -339290008785 | F26: =F11+F13+N(F14) -> -95595275118 | G26: =G11+G13+N(G14) -> -339941167898 | H26: =H11+H13+N(H14) -> -164869556624 | I26: =I11+I13+I14 -> -9.3743302e+10 | J26: =J11+J13+J14 -> -9.4443954e+10 | K26: =K11+K13+K14 -> -9.8073978e+10 | L26: =L11+L13+L14 -> -1.0200853e+11 | M26: =M11+M13+M14 -> -1.0628457e+11
A27: PC.FCF_L | B27: FCF setelah pembayaran sewa | C27: =C26+C18 -> -471965329724 | D27: =D26+D18 -> -263275847267 | E27: =E26+E18 -> -339290008785 | F27: =F26+F18 -> -95595275118 | G27: =G26+G18 -> -339941167898 | H27: =H26+H18 -> -164869556624 | I27: =I26+I18 -> -9.3743302e+10 | J27: =J26+J18 -> -9.4443954e+10 | ... M27: =M26+M18 -> -1.0628457e+11

Sheet Schedules_Proj
A1: Schedule proyeksi: aset tetap, ROU & sewa, utang, modal kerja
A2: Rp penuh | kolom A = aktual (link ke IS/BS/CF/Schedules), kolom E = proyeksi | Proyeksi ILUSTRATIF berbasis asumsi transparan - bukan rekomendasi investasi, bukan target, bukan nilai wajar.
A3: Skenario aktif: | C3: =Asumsi!C4 -> Base | I3: ilustratif | J3: ilustratif | K3: ilustratif | L3: ilustratif | M3: ilustratif
A4: Kode | B4: Akun | C4: FY2020A | D4: FY2021A | E4: FY2022A | F4: FY2023A | G4: FY2024A | H4: FY2025A | I4: FY2026E | J4: FY2027E | K4: FY2028E | L4: FY2029E | M4: FY2030E | N4: Catatan / sumber
B5: ASET TETAP
A6: S.PPE_BEG | B6: Aset tetap neto awal | I6: =BS_Proj!H11 -> 3272592245462 | J6: =BS_Proj!I11 -> 3.279262e+12 | K6: =BS_Proj!J11 -> 3.289874e+12 | L6: =BS_Proj!K11 -> 3.304921e+12 | M6: =BS_Proj!L11 -> 3.3249608e+12
A7: S.CAPEX | B7: Capex (kas) | C7: =-(CF!C22+CF!C21) -> 522268123814 | D7: =-(CF!D22+CF!D21) -> 310404936909 | E7: =-(CF!E22+CF!E21) -> 290453639673 | F7: =-(CF!F22+CF!F21) -> 12562010950 | G7: =-(CF!G22+CF!G21) -> 226929983578 | H7: =-(CF!H22+CF!H21) -> 210756461260 | I7: =Asumsi!I17*IS_Proj!I9 -> 3.0886901e+10 | J7: =Asumsi!J17*IS_Proj!J9 -> 3.4878572e+10 | K7: =Asumsi!K17*IS_Proj!K9 -> 3.9392029e+10 | L7: =Asumsi!L17*IS_Proj!L9 -> 4.4496306e+10 | M7: =Asumsi!M17*IS_Proj!M9 -> 5.0269681e+10
A8: S.LEASE_PD | B8: Sewa dikapitalisasi (CARE: 0) | C8: =0 -> 0 | D8: =0 -> 0 | E8: =0 -> 0 | F8: =0 -> 0 | G8: =0 -> 0 | H8: =0 -> 0 | I8: =Asumsi!I18*IS_Proj!I9 -> 0 | J8: =Asumsi!J18*IS_Proj!J9 -> 0 | K8: =Asumsi!K18*IS_Proj!K9 -> 0 | L8: =Asumsi!L18*IS_Proj!L9 -> 0 | M8: =Asumsi!M18*IS_Proj!M9 -> 0
A9: S.DEP | B9: Penyusutan aset tetap | D9: =Schedules!D14 -> 17297314280 | E9: =Schedules!E14 -> 22877629559 | F9: =Schedules!F14 -> 21584974350 | G9: =Schedules!G14 -> 25515756073 | H9: =Schedules!H14 -> 26326052136 | I9: =I6*Asumsi!I19 -> 2.4217183e+10 | J9: =J6*Asumsi!J19 -> 2.4266539e+10 | K9: =K6*Asumsi!K19 -> 2.4345068e+10 | L9: =L6*Asumsi!L19 -> 2.4456415e+10 | M9: =M6*Asumsi!M19 -> 2.460471e+10
A10: S.PPE_END | B10: Aset tetap neto akhir | C10: =BS!C16 -> 2175317280881 | D10: =BS!D16 -> 2915791008035 | E10: =BS!E16 -> 3337354211724 | F10: =BS!F16 -> 3330399614118 | G10: =BS!G16 -> 3257425244004 | H10: =BS!H16 -> 3272592245462 | I10: =I6+I7+I8-I9 -> 3.279262e+12 | J10: =J6+J7+J8-J9 -> 3.289874e+12 | K10: =K6+K7+K8-K9 -> 3.304921e+12 | L10: =L6+L7+L8-L9 -> 3.3249608e+12 | M10: =M6+M7+M8-M9 -> 3.3506258e+12 | N10: historis: neraca (memuat penambahan nonkas, pelepasan, penurunan nilai)
B11: GOODWILL (konstan)
A12: S.INT_BEG | B12: Aset takberwujud awal | I12: =BS_Proj!H12 -> 0 | J12: =BS_Proj!I12 -> 0 | K12: =BS_Proj!J12 -> 0 | L12: =BS_Proj!K12 -> 0 | M12: =BS_Proj!L12 -> 0
A13: S.SW_AMORT | B13: Amortisasi aset takberwujud | D13: =Schedules!D17 -> 0 | E13: =Schedules!E17 -> 0 | F13: =Schedules!F17 -> 0 | G13: =Schedules!G17 -> 0 | H13: =Schedules!H17 -> 0 | I13: =I12*Asumsi!I20 -> 0 | J13: =J12*Asumsi!J20 -> 0 | K13: =K12*Asumsi!K20 -> 0 | L13: =L12*Asumsi!L20 -> 0 | M13: =M12*Asumsi!M20 -> 0
A14: S.SW_CAPEX | B14: Capex aset takberwujud (= amortisasi) | I14: =I13 -> 0 | J14: =J13 -> 0 | K14: =K13 -> 0 | L14: =L13 -> 0 | M14: =M13 -> 0
A15: S.INT_END | B15: Aset takberwujud akhir | C15: =BS!C17 -> 7024470936 | D15: =BS!D17 -> 6971681464 | E15: =BS!E17 -> 6971681464 | F15: =BS!F17 -> 6971681464 | G15: =BS!G17 -> 0 | H15: =BS!H17 -> 0 | I15: =I12+I14-I13 -> 0 | J15: =J12+J14-J13 -> 0 | K15: =K12+K14-K13 -> 0 | L15: =L12+L14-L13 -> 0 | M15: =M12+M14-M13 -> 0
B16: LIABILITAS SEWA
A17: S.LEASE_BEG | B17: Liabilitas sewa awal | I17: =BS_Proj!H19 -> 0 | J17: =BS_Proj!I19 -> 0 | K17: =BS_Proj!J19 -> 0 | L17: =BS_Proj!K19 -> 0 | M17: =BS_Proj!L19 -> 0
A18: S.LEASE_END | B18: Liabilitas sewa akhir | C18: =0 -> 0 | D18: =0 -> 0 | E18: =0 -> 0 | F18: =0 -> 0 | G18: =0 -> 0 | H18: =0 -> 0 | I18: =I17 -> 0 | J18: =J17 -> 0 | K18: =K17 -> 0 | L18: =L17 -> 0 | M18: =M17 -> 0 | N18: CARE tidak memiliki liabilitas sewa
A19: S.LEASE_AVG | B19: Rata-rata liabilitas sewa | D19: =AVERAGE(0,D18) -> 0 | E19: =AVERAGE(0,E18) -> 0 | F19: =AVERAGE(0,F18) -> 0 | G19: =AVERAGE(0,G18) -> 0 | H19: =AVERAGE(0,H18) -> 0 | I19: =AVERAGE(I17,I18) -> 0 | J19: =AVERAGE(J17,J18) -> 0 | K19: =AVERAGE(K17,K18) -> 0 | L19: =AVERAGE(L17,L18) -> 0 | M19: =AVERAGE(M17,M18) -> 0
B20: UTANG BERBUNGA
A21: S.DEBT_BEG | B21: Utang awal | I21: =BS_Proj!H18 -> 1083635029572 | J21: =BS_Proj!I18 -> 1083635029572 | K21: =BS_Proj!J18 -> 1083635029572 | L21: =BS_Proj!K18 -> 1083635029572 | M21: =BS_Proj!L18 -> 1083635029572
A22: S.DEBT_CHG | B22: Perubahan neto (tarik / (bayar)) | I22: =Asumsi!I29 -> 0 | J22: =Asumsi!J29 -> 0 | K22: =Asumsi!K29 -> 0 | L22: =Asumsi!L29 -> 0 | M22: =Asumsi!M29 -> 0
A23: S.DEBT_END | B23: Utang akhir | C23: =(BS!C23+BS!C30+BS!C34+BS!C31+BS!C35+BS!C32+BS!C36) -> 116162740870 | D23: =(BS!D23+BS!D30+BS!D34+BS!D31+BS!D35+BS!D32+BS!D36) -> 844063816090 | E23: =(BS!E23+BS!E30+BS!E34+BS!E31+BS!E35+BS!E32+BS!E36) -> 957037296647 | F23: =(BS!F23+BS!F30+BS!F34+BS!F31+BS!F35+BS!F32+BS!F36) -> 954514193129 | G23: =(BS!G23+BS!G30+BS!G34+BS!G31+BS!G35+BS!G32+BS!G36) -> 944466599212 | H23: =(BS!H23+BS!H30+BS!H34+BS!H31+BS!H35+BS!H32+BS!H36) -> 1083635029572 | I23: =I21+I22 -> 1083635029572 | J23: =J21+J22 -> 1083635029572 | K23: =K21+K22 -> 1083635029572 | L23: =L21+L22 -> 1083635029572 | M23: =M21+M22 -> 1083635029572
A24: S.DEBT_AVG | B24: Rata-rata utang | D24: =AVERAGE((BS!C23+BS!C30+BS!C34+BS!C31+BS!C35+BS!C32+BS!C36),D23) -> 480113278480 | E24: =AVERAGE((BS!D23+BS!D30+BS!D34+BS!D31+BS!D35+BS!D32+BS!D36),E23) -> 9.0055056e+11 | F24: =AVERAGE((BS!E23+BS!E30+BS!E34+BS!E31+BS!E35+BS!E32+BS!E36),F23) -> 955775744888 | G24: =AVERAGE((BS!F23+BS!F30+BS!F34+BS!F31+BS!F35+BS!F32+BS!F36),G23) -> 9.494904e+11 | H24: =AVERAGE((BS!G23+BS!G30+BS!G34+BS!G31+BS!G35+BS!G32+BS!G36),H23) -> 1014050814392 | I24: =AVERAGE(I21,I23) -> 1083635029572 | J24: =AVERAGE(J21,J23) -> 1083635029572 | K24: =AVERAGE(K21,K23) -> 1083635029572 | L24: =AVERAGE(L21,L23) -> 1083635029572 | M24: =AVERAGE(M21,M23) -> 1083635029572
B25: MODAL KERJA
A26: S.AR | B26: Piutang usaha (DSO x pendapatan / 365) | C26: =BS!C8 -> 46315632063 | D26: =BS!D8 -> 43418562083 | E26: =BS!E8 -> 19493922195 | F26: =BS!F8 -> 29762970115 | G26: =BS!G8 -> 39287099946 | H26: =BS!H8 -> 32414715751 | I26: =IS_Proj!I9*Asumsi!I22/365 -> 4.2310823e+10 | J26: =IS_Proj!J9*Asumsi!J22/365 -> 4.7778865e+10 | K26: =IS_Proj!K9*Asumsi!K22/365 -> 5.3961684e+10 | L26: =IS_Proj!L9*Asumsi!L22/365 -> 6.0953844e+10 | M26: =IS_Proj!M9*Asumsi!M22/365 -> 6.8862577e+10
A27: S.INV | B27: Persediaan (DIO x beban pokok / 365) | C27: =BS!C10 -> 6868279382 | D27: =BS!D10 -> 6128999612 | E27: =BS!E10 -> 3810165323 | F27: =BS!F10 -> 4778420963 | G27: =BS!G10 -> 6268091785 | H27: =BS!H10 -> 5344682837 | I27: =-IS_Proj!I12*Asumsi!I23/365 -> 6.6322215e+09 | J27: =-IS_Proj!J12*Asumsi!J23/365 -> 7.4893371e+09 | K27: =-IS_Proj!K12*Asumsi!K23/365 -> 8.4584939e+09 | L27: =-IS_Proj!L12*Asumsi!L23/365 -> 9.554515e+09 | M27: =-IS_Proj!M12*Asumsi!M23/365 -> 1.0794209e+10
A28: S.AP | B28: Utang usaha (DPO x beban pokok / 365) | C28: =BS!C24 -> 10821912088 | D28: =BS!D24 -> 14656750351 | E28: =BS!E24 -> 26875586517 | F28: =BS!F24 -> 42532889111 | G28: =BS!G24 -> 25121215698 | H28: =BS!H24 -> 21151058333 | I28: =-IS_Proj!I12*Asumsi!I24/365 -> 2.7131815e+10 | J28: =-IS_Proj!J12*Asumsi!J24/365 -> 3.0638197e+10 | K28: =-IS_Proj!K12*Asumsi!K24/365 -> 3.460293e+10 | L28: =-IS_Proj!L12*Asumsi!L24/365 -> 3.9086652e+10 | M28: =-IS_Proj!M12*Asumsi!M24/365 -> 4.4158127e+10
A29: S.NWC | B29: Modal kerja usaha neto | C29: =C26+C27-C28 -> 42361999357 | D29: =D26+D27-D28 -> 34890811344 | E29: =E26+E27-E28 -> -3571498999 | F29: =F26+F27-F28 -> -7991498033 | G29: =G26+G27-G28 -> 20433976033 | H29: =H26+H27-H28 -> 16608340255 | I29: =I26+I27-I28 -> 2.1811229e+10 | J29: =J26+J27-J28 -> 2.4630005e+10 | ... M29: =M26+M27-M28 -> 3.5498658e+10
A30: S.D_NWC | B30: (Kenaikan) modal kerja | D30: =C29-D29 -> 7471188013 | E30: =D29-E29 -> 38462310343 | F30: =E29-F29 -> 4419999034 | G30: =F29-G29 -> -28425474066 | H30: =G29-H29 -> 3825635778 | I30: =H29-I29 -> -5.2028891e+09 | J30: =I29-J29 -> -2.8187757e+09 | K30: =J29-K29 -> -3.187243e+09 | ... M30: =L29-M29 -> -4.0769519e+09

Sheet DCF_Template
A1: Template DCF opsional - kalkulator untuk pengguna (input KOSONG)
A2: Sel kuning diisi sendiri oleh pengguna dan perlu diverifikasi. Hasil sepenuhnya bergantung pada input pengguna; BUKAN nilai wajar, target, atau rekomendasi dari penyusun.
B4: INPUT (kosong = template tidak menghitung)
B5: Suku bunga bebas risiko (Rf) | D5: perlu diisi/diverifikasi: mis. imbal hasil SUN 10 tahun; catat sumber & tanggal
B6: Equity risk premium (ERP) | D6: perlu diisi/diverifikasi: catat sumber
B7: Beta (levered) | D7: perlu diisi/diverifikasi: metode, periode & indeks acuan
B8: Premi tambahan (ukuran/spesifik), opsional | D8: perlu diisi/diverifikasi: isi 0 bila tidak dipakai
B9: Biaya utang sebelum pajak (Kd) | D9: perlu diisi/diverifikasi
B10: Tarif pajak untuk perisai bunga | D10: perlu diisi/diverifikasi: tarif PPh badan berlaku
B11: Bobot utang D/(D+E) target | D11: perlu diisi/diverifikasi
B12: Pertumbuhan terminal (g) - metode Gordon | D12: perlu diisi/diverifikasi
B13: Kelipatan EV/EBITDA terminal - metode exit multiple | D13: perlu diisi/diverifikasi: dokumentasikan sumber
B14: Aset non-operasi ditambahkan (Rp), mis. investasi saham | D14: perlu diisi/diverifikasi: isi 0 bila tidak dipakai
B15: Input inti lengkap? (Rf, ERP, beta, Kd, pajak, bobot utang) | C15: =COUNT($C$5,$C$6,$C$7,$C$9,$C$10,$C$11)=6 -> FALSE
B16: Siap hitung metode Gordon? | C16: =AND($C$15,COUNT($C$12)=1) -> FALSE
B17: Siap hitung metode exit multiple? | C17: =AND($C$15,COUNT($C$13)=1) -> FALSE
B19: WACC
B20: Biaya ekuitas Ke = Rf + beta x ERP + premi | C20: =IF($C$15,$C$5+$C$7*$C$6+N($C$8),"")
B21: Biaya utang setelah pajak | C21: =IF($C$15,$C$9*(1-$C$10),"")
B22: WACC | C22: =IF($C$15,$C$20*(1-$C$11)+$C$21*$C$11,"")
B24: FCFF (mengikuti skenario aktif di Asumsi)
I25: FY2026E | J25: FY2027E | K25: FY2028E | L25: FY2029E | M25: FY2030E
B26: Periode diskonto (tahun, akhir periode) | I26: 1 | J26: 2 | K26: 3 | L26: 4 | M26: 5
B27: EBIT | I27: =IS_Proj!I17 -> -4.9128696e+09 | J27: =IS_Proj!J17 -> -2.4674313e+09 | K27: =IS_Proj!K17 -> 2.7495068e+08 | L27: =IS_Proj!L17 -> 3.3537762e+09 | M27: =IS_Proj!M17 -> 6.8138404e+09
B28: Pajak atas EBIT (tarif dari Asumsi) | I28: =-MAX(I27,0)*Asumsi!I26 -> 0 | J28: =-MAX(J27,0)*Asumsi!J26 -> 0 | K28: =-MAX(K27,0)*Asumsi!K26 -> -60489149 | L28: =-MAX(L27,0)*Asumsi!L26 -> -7.3783076e+08 | M28: =-MAX(M27,0)*Asumsi!M26 -> -1.4990449e+09
B29: NOPAT | I29: =I27+I28 -> -4.9128696e+09 | J29: =J27+J28 -> -2.4674313e+09 | K29: =K27+K28 -> 2.1446153e+08 | L29: =L27+L28 -> 2.6159454e+09 | M29: =M27+M28 -> 5.3147955e+09
B30: + D&A | I30: =-IS_Proj!I16 -> 2.4217183e+10 | J30: =-IS_Proj!J16 -> 2.4266539e+10 | K30: =-IS_Proj!K16 -> 2.4345068e+10 | L30: =-IS_Proj!L16 -> 2.4456415e+10 | M30: =-IS_Proj!M16 -> 2.460471e+10
B31: - Capex | I31: =CF_Proj!I13 -> -3.0886901e+10 | J31: =CF_Proj!J13 -> -3.4878572e+10 | K31: =CF_Proj!K13 -> -3.9392029e+10 | L31: =CF_Proj!L13 -> -4.4496306e+10 | M31: =CF_Proj!M13 -> -5.0269681e+10
B32: - Kenaikan modal kerja | I32: =Schedules_Proj!I30 -> -5.2028891e+09 | J32: =Schedules_Proj!J30 -> -2.8187757e+09 | K32: =Schedules_Proj!K30 -> -3.187243e+09 | L32: =Schedules_Proj!L30 -> -3.6044585e+09 | M32: =Schedules_Proj!M30 -> -4.0769519e+09
B33: FCFF | I33: =SUM(I29:I32) -> -1.6785477e+10 | J33: =SUM(J29:J32) -> -1.589824e+10 | K33: =SUM(K29:K32) -> -1.8019743e+10 | L33: =SUM(L29:L32) -> -2.1028404e+10 | M33: =SUM(M29:M32) -> -2.4427127e+10
B34: Faktor diskonto | I34: =IF($C$15,1/(1+$C$22)^I26,"") | J34: =IF($C$15,1/(1+$C$22)^J26,"") | K34: =IF($C$15,1/(1+$C$22)^K26,"") | L34: =IF($C$15,1/(1+$C$22)^L26,"") | M34: =IF($C$15,1/(1+$C$22)^M26,"")
B35: PV FCFF | I35: =IF($C$15,I33*I34,"") | J35: =IF($C$15,J33*J34,"") | K35: =IF($C$15,K33*K34,"") | L35: =IF($C$15,L33*L34,"") | M35: =IF($C$15,M33*M34,"")
B36: Catatan IFRS 16: FCFF sebelum pembayaran sewa, sehingga liabilitas sewa diperlakukan sebagai utang di jembatan ekuitas.
B38: NILAI PERUSAHAAN & JEMBATAN EKUITAS (hasil kalkulator) | C38: Gordon | D38: Exit multiple
B39: Σ PV FCFF | C39: =IF($C$16,SUMPRODUCT($I$33:$M$33/(1+$C$22)^$I$26:$M$26),"") | D39: =IF($C$17,SUMPRODUCT($I$33:$M$33/(1+$C$22)^$I$26:$M$26),"")
B40: Nilai terminal (akhir FY2030E) | C40: =IF($C$16,IF($C$22>$C$12,$M$33*(1+$C$12)/($C$22-$C$12),"WACC<=g"),"") | D40: =IF($C$17,IS_Proj!$M$15*$C$13,"")
B41: PV nilai terminal | C41: =IFERROR(C40/(1+$C$22)^5,"") | D41: =IFERROR(D40/(1+$C$22)^5,"")
B42: Nilai perusahaan (EV) | C42: =IFERROR(C39+C41,"") | D42: =IFERROR(D39+D41,"")
B43: (-) Utang bank FY2025A | C43: =-BS_Proj!H18 -> -1083635029572 | D43: =-BS_Proj!H18 -> -1083635029572
B44: (-) Liabilitas sewa FY2025A | C44: =-BS_Proj!H19 -> 0 | D44: =-BS_Proj!H19 -> 0
B45: (+) Kas FY2025A | C45: =BS_Proj!H6 -> 420204094763 | D45: =BS_Proj!H6 -> 420204094763
B46: (-) Kepentingan nonpengendali (nilai buku FY2025A) | C46: =-BS_Proj!H26 -> -1812417290 | D46: =-BS_Proj!H26 -> -1812417290
B47: (+) Aset non-operasi (input) | C47: =N($C$14) -> 0 | D47: =N($C$14) -> 0
B48: Nilai ekuitas | C48: =IFERROR(C42+SUM(C43:C47),"") | D48: =IFERROR(D42+SUM(D43:D47),"")
B49: Nilai ekuitas per saham (Rp) | C49: =IFERROR(C48/Asumsi!$C$110,"") | D49: =IFERROR(D48/Asumsi!$C$110,"")
B50: Hanya keluaran rumus atas input pengguna; bukan target, bukan nilai wajar, bukan rekomendasi. NCI dikurangkan pada nilai buku (penyederhanaan).
B52: SENSITIVITAS nilai ekuitas per saham (Gordon): WACC (baris) x g (kolom)
B53: WACC \ g | C53: =IF($C$16,$C$12+(-0.01),"") | D53: =IF($C$16,$C$12+(-0.005),"") | E53: =IF($C$16,$C$12+(0),"") | F53: =IF($C$16,$C$12+(0.005),"") | G53: =IF($C$16,$C$12+(0.01),"")
B54: =IF($C$16,$C$22+(-0.02),"") | C54: =IF($C$16,IFERROR(IF($B54>C$53,(SUMPRODUCT($I$33:$M$33/(1+$B54)^$I$26:$M$26)+$M$33*(1+C$53)/($B54-C$53)/(1+$B54)^5+SUM($C$43:$C$47))/Asumsi!$C$110,"n/a"),""),"") | D54: =IF($C$16,IFERROR(IF($B54>D$53,(SUMPRODUCT($I$33:$M$33/(1+$B54)^$I$26:$M$26)+$M$33*(1+D$53)/($B54-D$53)/(1+$B54)^5+SUM($C$43:$C$47))/Asumsi!$C$110,"n/a"),""),"") | E54: =IF($C$16,IFERROR(IF($B54>E$53,(SUMPRODUCT($I$33:$M$33/(1+$B54)^$I$26:$M$26)+$M$33*(1+E$53)/($B54-E$53)/(1+$B54)^5+SUM($C$43:$C$47))/Asumsi!$C$110,"n/a"),""),"") | F54: =IF($C$16,IFERROR(IF($B54>F$53,(SUMPRODUCT($I$33:$M$33/(1+$B54)^$I$26:$M$26)+$M$33*(1+F$53)/($B54-F$53)/(1+$B54)^5+SUM($C$43:$C$47))/Asumsi!$C$110,"n/a"),""),"") | G54: =IF($C$16,IFERROR(IF($B54>G$53,(SUMPRODUCT($I$33:$M$33/(1+$B54)^$I$26:$M$26)+$M$33*(1+G$53)/($B54-G$53)/(1+$B54)^5+SUM($C$43:$C$47))/Asumsi!$C$110,"n/a"),""),"")
B55: =IF($C$16,$C$22+(-0.01),"") | C55: =IF($C$16,IFERROR(IF($B55>C$53,(SUMPRODUCT($I$33:$M$33/(1+$B55)^$I$26:$M$26)+$M$33*(1+C$53)/($B55-C$53)/(1+$B55)^5+SUM($C$43:$C$47))/Asumsi!$C$110,"n/a"),""),"") | D55: =IF($C$16,IFERROR(IF($B55>D$53,(SUMPRODUCT($I$33:$M$33/(1+$B55)^$I$26:$M$26)+$M$33*(1+D$53)/($B55-D$53)/(1+$B55)^5+SUM($C$43:$C$47))/Asumsi!$C$110,"n/a"),""),"") | E55: =IF($C$16,IFERROR(IF($B55>E$53,(SUMPRODUCT($I$33:$M$33/(1+$B55)^$I$26:$M$26)+$M$33*(1+E$53)/($B55-E$53)/(1+$B55)^5+SUM($C$43:$C$47))/Asumsi!$C$110,"n/a"),""),"") | F55: =IF($C$16,IFERROR(IF($B55>F$53,(SUMPRODUCT($I$33:$M$33/(1+$B55)^$I$26:$M$26)+$M$33*(1+F$53)/($B55-F$53)/(1+$B55)^5+SUM($C$43:$C$47))/Asumsi!$C$110,"n/a"),""),"") | G55: =IF($C$16,IFERROR(IF($B55>G$53,(SUMPRODUCT($I$33:$M$33/(1+$B55)^$I$26:$M$26)+$M$33*(1+G$53)/($B55-G$53)/(1+$B55)^5+SUM($C$43:$C$47))/Asumsi!$C$110,"n/a"),""),"")
B56: =IF($C$16,$C$22+(0),"") | C56: =IF($C$16,IFERROR(IF($B56>C$53,(SUMPRODUCT($I$33:$M$33/(1+$B56)^$I$26:$M$26)+$M$33*(1+C$53)/($B56-C$53)/(1+$B56)^5+SUM($C$43:$C$47))/Asumsi!$C$110,"n/a"),""),"") | D56: =IF($C$16,IFERROR(IF($B56>D$53,(SUMPRODUCT($I$33:$M$33/(1+$B56)^$I$26:$M$26)+$M$33*(1+D$53)/($B56-D$53)/(1+$B56)^5+SUM($C$43:$C$47))/Asumsi!$C$110,"n/a"),""),"") | E56: =IF($C$16,IFERROR(IF($B56>E$53,(SUMPRODUCT($I$33:$M$33/(1+$B56)^$I$26:$M$26)+$M$33*(1+E$53)/($B56-E$53)/(1+$B56)^5+SUM($C$43:$C$47))/Asumsi!$C$110,"n/a"),""),"") | F56: =IF($C$16,IFERROR(IF($B56>F$53,(SUMPRODUCT($I$33:$M$33/(1+$B56)^$I$26:$M$26)+$M$33*(1+F$53)/($B56-F$53)/(1+$B56)^5+SUM($C$43:$C$47))/Asumsi!$C$110,"n/a"),""),"") | G56: =IF($C$16,IFERROR(IF($B56>G$53,(SUMPRODUCT($I$33:$M$33/(1+$B56)^$I$26:$M$26)+$M$33*(1+G$53)/($B56-G$53)/(1+$B56)^5+SUM($C$43:$C$47))/Asumsi!$C$110,"n/a"),""),"")
B57: =IF($C$16,$C$22+(0.01),"") | C57: =IF($C$16,IFERROR(IF($B57>C$53,(SUMPRODUCT($I$33:$M$33/(1+$B57)^$I$26:$M$26)+$M$33*(1+C$53)/($B57-C$53)/(1+$B57)^5+SUM($C$43:$C$47))/Asumsi!$C$110,"n/a"),""),"") | D57: =IF($C$16,IFERROR(IF($B57>D$53,(SUMPRODUCT($I$33:$M$33/(1+$B57)^$I$26:$M$26)+$M$33*(1+D$53)/($B57-D$53)/(1+$B57)^5+SUM($C$43:$C$47))/Asumsi!$C$110,"n/a"),""),"") | E57: =IF($C$16,IFERROR(IF($B57>E$53,(SUMPRODUCT($I$33:$M$33/(1+$B57)^$I$26:$M$26)+$M$33*(1+E$53)/($B57-E$53)/(1+$B57)^5+SUM($C$43:$C$47))/Asumsi!$C$110,"n/a"),""),"") | F57: =IF($C$16,IFERROR(IF($B57>F$53,(SUMPRODUCT($I$33:$M$33/(1+$B57)^$I$26:$M$26)+$M$33*(1+F$53)/($B57-F$53)/(1+$B57)^5+SUM($C$43:$C$47))/Asumsi!$C$110,"n/a"),""),"") | G57: =IF($C$16,IFERROR(IF($B57>G$53,(SUMPRODUCT($I$33:$M$33/(1+$B57)^$I$26:$M$26)+$M$33*(1+G$53)/($B57-G$53)/(1+$B57)^5+SUM($C$43:$C$47))/Asumsi!$C$110,"n/a"),""),"")
B58: =IF($C$16,$C$22+(0.02),"") | C58: =IF($C$16,IFERROR(IF($B58>C$53,(SUMPRODUCT($I$33:$M$33/(1+$B58)^$I$26:$M$26)+$M$33*(1+C$53)/($B58-C$53)/(1+$B58)^5+SUM($C$43:$C$47))/Asumsi!$C$110,"n/a"),""),"") | D58: =IF($C$16,IFERROR(IF($B58>D$53,(SUMPRODUCT($I$33:$M$33/(1+$B58)^$I$26:$M$26)+$M$33*(1+D$53)/($B58-D$53)/(1+$B58)^5+SUM($C$43:$C$47))/Asumsi!$C$110,"n/a"),""),"") | E58: =IF($C$16,IFERROR(IF($B58>E$53,(SUMPRODUCT($I$33:$M$33/(1+$B58)^$I$26:$M$26)+$M$33*(1+E$53)/($B58-E$53)/(1+$B58)^5+SUM($C$43:$C$47))/Asumsi!$C$110,"n/a"),""),"") | F58: =IF($C$16,IFERROR(IF($B58>F$53,(SUMPRODUCT($I$33:$M$33/(1+$B58)^$I$26:$M$26)+$M$33*(1+F$53)/($B58-F$53)/(1+$B58)^5+SUM($C$43:$C$47))/Asumsi!$C$110,"n/a"),""),"") | G58: =IF($C$16,IFERROR(IF($B58>G$53,(SUMPRODUCT($I$33:$M$33/(1+$B58)^$I$26:$M$26)+$M$33*(1+G$53)/($B58-G$53)/(1+$B58)^5+SUM($C$43:$C$47))/Asumsi!$C$110,"n/a"),""),"")
B60: Template ini sengaja tidak memuat perbandingan dengan data pasar. Pengguna bertanggung jawab penuh atas input dan interpretasinya.

Sheet Peer
A1: Tabel pembanding - data FUNDAMENTAL saja (baris pembanding kosong)
A2: Isi hanya dengan data terverifikasi dari laporan keuangan publik tiap emiten; cantumkan sumber & tanggal akses. Tidak ada angka yang dikarang.
A4: Kode | B4: Nama emiten | C4: Fokus usaha | D4: Tahun buku | E4: Pendapatan (Rp miliar) | F4: Pertumbuhan pendapatan | G4: Margin EBITDA | H4: Margin laba bersih | I4: ROE | J4: ROA | K4: Utang / ekuitas | L4: Utang neto / EBITDA | M4: Jumlah RS | N4: Jumlah tempat tidur | O4: Porsi pendapatan rawat jalan | P4: Sumber (laporan, halaman) | Q4: Tanggal akses
A5: CARE | B5: PT Metro Healthcare Indonesia Tbk | C5: Jaringan rumah sakit swasta | D5: 2025 | E5: =IS_Proj!H9/1000000000 -> 439.75161 | F5: =IS_Proj!H10 -> 0.37843484 | G5: =IS_Proj!H29 -> 0.2190826 | H5: =IS_Proj!H31 -> 0.011701074 | I5: =BS_Proj!H32 -> 0.001640296 | J5: =IS_Proj!H23/BS_Proj!H15 -> 0.0012321968 | K5: =BS_Proj!H18/BS_Proj!H27 -> 0.35836204 | L5: =BS_Proj!H33 -> 6.8862123 | O5: =IS_Proj!H7/(IS_Proj!H6+IS_Proj!H7) -> 0.30223216 | P5: Model ini (laporan audited FY2025)
B14: Median pembanding (tanpa CARE) | E14: =IF(COUNT(E6:E13)=0,"",MEDIAN(E6:E13)) | F14: =IF(COUNT(F6:F13)=0,"",MEDIAN(F6:F13)) | G14: =IF(COUNT(G6:G13)=0,"",MEDIAN(G6:G13)) | H14: =IF(COUNT(H6:H13)=0,"",MEDIAN(H6:H13)) | I14: =IF(COUNT(I6:I13)=0,"",MEDIAN(I6:I13)) | J14: =IF(COUNT(J6:J13)=0,"",MEDIAN(J6:J13)) | K14: =IF(COUNT(K6:K13)=0,"",MEDIAN(K6:K13)) | L14: =IF(COUNT(L6:L13)=0,"",MEDIAN(L6:L13)) | ... O14: =IF(COUNT(O6:O13)=0,"",MEDIAN(O6:O13))
B15: Rata-rata pembanding (tanpa CARE) | E15: =IF(COUNT(E6:E13)=0,"",AVERAGE(E6:E13)) | F15: =IF(COUNT(F6:F13)=0,"",AVERAGE(F6:F13)) | G15: =IF(COUNT(G6:G13)=0,"",AVERAGE(G6:G13)) | H15: =IF(COUNT(H6:H13)=0,"",AVERAGE(H6:H13)) | I15: =IF(COUNT(I6:I13)=0,"",AVERAGE(I6:I13)) | J15: =IF(COUNT(J6:J13)=0,"",AVERAGE(J6:J13)) | K15: =IF(COUNT(K6:K13)=0,"",AVERAGE(K6:K13)) | L15: =IF(COUNT(L6:L13)=0,"",AVERAGE(L6:L13)) | ... O15: =IF(COUNT(O6:O13)=0,"",AVERAGE(O6:O13))
B17: Tabel ini sengaja tidak memuat kelipatan pasar (P/E, P/BV, EV/EBITDA): isinya ringkasan data fundamental, bukan penilaian.

Sheet IS
A1: Laporan Laba Rugi & OCI - historis FY2020A-FY2025A
A2: Rp penuh. Biru = input dari CARE_seri_2020_2025.json (LK audited, Rupiah penuh), hitam = rumus. Kolom 2021 dari komparatif LK FY2022 (disilang ke LK FY2021); kolom 2020 dari komparatif LK audited FY2021 (ringkasan XBRL IDX terblokir).
B3: Sumber kolom | C3: LK FY2021 (komparatif) | D3: LK FY2022 (komparatif) | E3: LK FY2022 | F3: LK FY2023 | G3: LK FY2024 | H3: LK FY2025 | I3: Catatan sumber: CARE tercatat di BEI sejak IPO efektif 28 Feb 2020. Ringkasan XBRL IDX FS-2020/2021 terblokir (HTTP 403); kolom 2020 diambil dari LK konsolidasian audited FY2021 (kompara
A4: Kode | B4: Akun | C4: FY2020A | D4: FY2021A | E4: FY2022A | F4: FY2023A | G4: FY2024A | H4: FY2025A | I4: Catatan / sumber
B5: LABA RUGI
A6: IS.REVENUE | B6: Pendapatan neto (Cat 20) | C6: 216296095571 | D6: 290934356126 | E6: 233970724609 | F6: 242680799183 | G6: 319022410802 | H6: 439751605228 | I6: kunci JSON: pendapatan_neto
A7: IS.COGS | B7: Beban pokok pendapatan (Cat 21) | C7: -113404642135 | D7: -145000436678 | E7: -137738459043 | F7: -153026530241 | G7: -214434696643 | H7: -224594016289 | I7: kunci JSON: beban_pokok
A8: IS.GROSS_PROFIT | B8: Laba bruto | C8: =C6+C7 -> 102891453436 | D8: =D6+D7 -> 145933919448 | E8: =E6+E7 -> 96232265566 | F8: =F6+F7 -> 89654268942 | G8: =G6+G7 -> 104587714159 | H8: =H6+H7 -> 215157588939
A9: IS.OPEX_TOTAL | B9: Beban usaha (umum & administrasi, Cat 22) | C9: -118408634509 | D9: -131835962281 | E9: -156823647433 | F9: -125793052442 | G9: -134515340769 | H9: -145141717485 | I9: kunci JSON: beban_usaha
A10: IS.OPER_PROFIT | B10: Laba (rugi) usaha | C10: =C8+C9 -> -15517181073 | D10: =D8+D9 -> 14097957167 | E10: =E8+E9 -> -60591381867 | F10: =F8+F9 -> -36138783500 | G10: =G8+G9 -> -29927626610 | H10: =H8+H9 -> 70015871454
A11: IS.OTHER_INCOME | B11: Pendapatan (beban) lain-lain - neto (Cat 25; di bawah laba usaha) | C11: 532768164 | D11: 2465367652 | E11: 25636825732 | F11: 250325287 | G11: 25235874672 | H11: 2857036197 | I11: kunci JSON: pendapatan_lain
A12: IS.OTHER_OPER_NET | B12: Pendapatan (beban) lain-lain - neto (memo rumus) | C12: =C11 -> 532768164 | D12: =D11 -> 2465367652 | E12: =E11 -> 25636825732 | F12: =F11 -> 250325287 | G12: =G11 -> 25235874672 | H12: =H11 -> 2857036197
A13: IS.FIN_INCOME | B13: Penghasilan keuangan (Cat 23) | C13: 40428301431 | D13: 15781938577 | E13: 31784929332 | F13: 6623274915 | G13: 6242710845 | H13: 15555391585 | I13: kunci JSON: penghasilan_keuangan
A14: IS.FIN_COST | B14: Beban keuangan (Cat 24) | C14: -11651080910 | D14: -25838724542 | E14: -90146332117 | F14: -76857656488 | G14: -77315017008 | H14: -80356964083 | I14: kunci JSON: beban_keuangan
A15: IS.PBT | B15: Laba (rugi) sebelum pajak | C15: =C10+C11+C13+C14 -> 13792807612 | D15: =D10+D11+D13+D14 -> 6506538854 | E15: =E10+E11+E13+E14 -> -93315958920 | F15: =F10+F11+F13+F14 -> -106122839786 | G15: =G10+G11+G13+G14 -> -75764058101 | H15: =H10+H11+H13+H14 -> 8071335153
A16: IS.TAX_TOTAL | B16: Beban pajak penghasilan | C16: 375143524 | D16: -332914077 | E16: -288463386 | F16: -4566022109 | G16: -4153162003 | H16: -2925769032 | I16: kunci JSON: beban_pajak
A17: IS.NET_INCOME | B17: Laba tahun berjalan | C17: =C15+C16 -> 14167951136 | D17: =D15+D16 -> 6173624777 | E17: =E15+E16 -> -93604422306 | F17: =F15+F16 -> -110688861895 | G17: =G15+G16 -> -79917220104 | H17: =H15+H16 -> 5145566121
B18: PENGHASILAN KOMPREHENSIF LAIN (OCI)
A19: IS.OCI_REMEASURE | B19: Pengukuran kembali program imbalan pasti | C19: 212586100 | D19: 1713820262 | E19: 2856898707 | F19: 1950086378 | G19: 743652348 | H19: 414241358 | I19: kunci JSON: oci_remeasurement
A20: IS.OCI_TAX | B20: Pajak terkait | C20: -46768943 | D20: -377040458 | E20: -628517716 | F20: -429019004 | G20: -163603517 | H20: -91133099 | I20: kunci JSON: oci_pajak_terkait
A21: IS.OCI_TOTAL | B21: Jumlah OCI | C21: =C19+C20 -> 165817157 | D21: =D19+D20 -> 1336779804 | E21: =E19+E20 -> 2228380991 | F21: =F19+F20 -> 1521067374 | G21: =G19+G20 -> 580048831 | H21: =H19+H20 -> 323108259
A22: IS.TCI | B22: Jumlah laba komprehensif | C22: =C17+C21 -> 14333768293 | D22: =D17+D21 -> 7510404581 | E22: =E17+E21 -> -91376041315 | F22: =F17+F21 -> -109167794521 | G22: =G17+G21 -> -79337171273 | H22: =H17+H21 -> 5468674380
B23: ATRIBUSI & PER SAHAM
A24: IS.NI_PARENT | B24: Laba diatribusikan ke pemilik entitas induk | C24: 14312842564 | D24: 6099193871 | E24: -93543896993 | F24: -110919788807 | G24: -80309181321 | H24: 4952718308 | I24: kunci JSON: laba_induk
A25: IS.NI_NCI | B25: Laba diatribusikan ke kepentingan nonpengendali (NCI) | C25: -144891428 | D25: 74430906 | E25: -60525313 | F25: 230926912 | G25: 391961217 | H25: 192847813 | I25: kunci JSON: laba_nci
A26: IS.TCI_PARENT | B26: Laba komprehensif - pemilik entitas induk | C26: 14481079666 | D26: 7416307993 | E26: -91343061468 | F26: -109408572601 | G26: -79732226609 | H26: 5275826567 | I26: kunci JSON: tci_induk
A27: IS.TCI_NCI | B27: Laba komprehensif - NCI | C27: -147311373 | D27: 94096588 | E27: -32979847 | F27: 240778080 | G27: 395055336 | H27: 192847813 | I27: kunci JSON: tci_nci
A28: IS.EPS_BASIC | B28: Laba per saham dasar tercetak (Rp, penuh) | C28: 0.51 | D28: 0.18 | E28: -2.81 | F28: -3.34 | G28: -2.42 | H28: 0.15 | I28: kunci JSON: eps_dasar
A29: IS.EPS_DILUTED | B29: Laba per saham dilusian tercetak (Rp, penuh) | C29: 0.51 | D29: 0.18 | E29: -2.81 | F29: -3.34 | G29: -2.42 | H29: 0.15 | I29: kunci JSON: eps_dilusian
B30: MEMO: RINCIAN PAJAK (tidak dipakai rumus)
A31: IS.TAX_CURRENT | B31: Pajak kini | C31: -1173268664 | D31: -4712708186 | E31: -1015824357 | F31: -3947518609 | G31: -4906863060 | H31: -3588173160 | I31: kunci JSON: pajak_kini
A32: IS.TAX_DEFERRED | B32: Pajak tangguhan | C32: 1548412188 | D32: 4379794109 | E32: 727360971 | F32: -618503500 | G32: 753701057 | H32: 662404128 | I32: kunci JSON: pajak_tangguhan
B33: MEMO: SUBTOTAL TERCETAK DI LK (untuk Rekonsiliasi)
A34: IS.GROSS_PROFIT_PRINTED | B34: Laba bruto (tercetak) | C34: 102891453436 | D34: 145933919448 | E34: 96232265566 | F34: 89654268942 | G34: 104587714159 | H34: 215157588939 | I34: kunci JSON: laba_bruto
A35: IS.OPER_PROFIT_PRINTED | B35: Laba (rugi) usaha (tercetak) | C35: -15517181073 | D35: 14097957167 | E35: -60591381867 | F35: -36138783500 | G35: -29927626610 | H35: 70015871454 | I35: kunci JSON: laba_usaha
A36: IS.PBT_PRINTED | B36: Laba sebelum pajak (tercetak) | C36: 13792807612 | D36: 6506538854 | E36: -93315958920 | F36: -106122839786 | G36: -75764058101 | H36: 8071335153 | I36: kunci JSON: laba_sebelum_pajak
A37: IS.NET_INCOME_PRINTED | B37: Laba tahun berjalan (tercetak) | C37: 14167951136 | D37: 6173624777 | E37: -93604422306 | F37: -110688861895 | G37: -79917220104 | H37: 5145566121 | I37: kunci JSON: laba_tahun_berjalan
A38: IS.OCI_TOTAL_PRINTED | B38: Jumlah OCI (tercetak) | C38: 165817157 | D38: 1336779804 | E38: 2228380991 | F38: 1521067374 | G38: 580048831 | H38: 323108259 | I38: kunci JSON: oci_total
A39: IS.TCI_PRINTED | B39: Laba komprehensif (tercetak) | C39: 14333768293 | D39: 7510404581 | E39: -91376041315 | F39: -109167794521 | G39: -79337171273 | H39: 5468674380 | I39: kunci JSON: total_laba_komprehensif

Sheet BS
A1: Laporan Posisi Keuangan - historis FY2020A-FY2025A
A2: Rp penuh. Biru = input dari CARE_seri_2020_2025.json (LK audited, Rupiah penuh), hitam = rumus. Kolom 2021 dari komparatif LK FY2022 (disilang ke LK FY2021); kolom 2020 dari komparatif LK audited FY2021 (ringkasan XBRL IDX terblokir).
B3: Sumber kolom | C3: LK FY2021 (komparatif) | D3: LK FY2022 (komparatif) | E3: LK FY2022 | F3: LK FY2023 | G3: LK FY2024 | H3: LK FY2025 | I3: Catatan sumber: CARE tercatat di BEI sejak IPO efektif 28 Feb 2020. Ringkasan XBRL IDX FS-2020/2021 terblokir (HTTP 403); kolom 2020 diambil dari LK konsolidasian audited FY2021 (kompara
A4: Kode | B4: Akun | C4: FY2020A | D4: FY2021A | E4: FY2022A | F4: FY2023A | G4: FY2024A | H4: FY2025A | I4: Catatan / sumber
B5: ASET
A6: BS.CASH | B6: Kas dan setara kas | C6: 525479693804 | D6: 542400475238 | E6: 533208033479 | F6: 525762948837 | G6: 449069663731 | H6: 420204094763 | I6: kunci JSON: kas
A7: BS.ST_INVEST | B7: Investasi jangka pendek (deposito > 3 bulan) | C7: 200000000000 | D7: 650000000000 | E7: 320000000000 | F7: 229000000000 | G7: 43000000000 | H7: 50500000000 | I7: kunci JSON: invest_jp
A8: BS.TRADE_REC | B8: Piutang usaha - neto | C8: 46315632063 | D8: 43418562083 | E8: 19493922195 | F8: 29762970115 | G8: 39287099946 | H8: 32414715751 | I8: kunci JSON: piutang_usaha_pk3
A9: BS.OTHER_REC | B9: Piutang lain-lain | C9: 17731873 | D9: 7668632882 | E9: 340953590 | F9: 433676044 | G9: 224662236 | H9: 85820156 | I9: kunci JSON: piutang_lain_pk3
A10: BS.INVENTORY | B10: Persediaan | C10: 6868279382 | D10: 6128999612 | E10: 3810165323 | F10: 4778420963 | G10: 6268091785 | H10: 5344682837 | I10: kunci JSON: persediaan
A11: BS.PREPAID_TAX | B11: Pajak dibayar dimuka | C11: 1182138238 | D11: 1754631182 | E11: 2084307178 | F11: 2986519826 | G11: 3851470413 | H11: 5159594606 | I11: kunci JSON: pajak_dimuka
A12: BS.PREPAID_ADV | B12: Biaya dibayar dimuka (2020: dalam aset lancar lainnya) | D12: 1118956971 | E12: 1406842329 | F12: 912381292 | G12: 287577361 | H12: 168458214 | I12: kunci JSON: biaya_dimuka
A13: BS.RESTRICTED_CASH | B13: Kas yang dibatasi penggunaannya (2020: dalam aset lancar lainnya) | D13: 1770788841 | E13: 1278259408 | F13: 882555505 | G13: 1327674901 | H13: 39617692 | I13: kunci JSON: kas_dibatasi
A14: BS.OTHER_CA | B14: Aset lancar lainnya | C14: 1989727315 | I14: kunci JSON: aset_lancar_lain
A15: BS.TOTAL_CA | B15: Jumlah aset lancar | C15: =C6+C7+C8+C9+C10+C11+C12+C13+C14 -> 781853202675 | D15: =D6+D7+D8+D9+D10+D11+D12+D13+D14 -> 1254261046809 | E15: =E6+E7+E8+E9+E10+E11+E12+E13+E14 -> 881622483502 | F15: =F6+F7+F8+F9+F10+F11+F12+F13+F14 -> 794519472582 | G15: =G6+G7+G8+G9+G10+G11+G12+G13+G14 -> 543316240373 | H15: =H6+H7+H8+H9+H10+H11+H12+H13+H14 -> 513916984019
A16: BS.PPE | B16: Aset tetap - neto | C16: 2175317280881 | D16: 2915791008035 | E16: 3337354211724 | F16: 3330399614118 | G16: 3257425244004 | H16: 3272592245462 | I16: kunci JSON: aset_tetap
A17: BS.INTANGIBLES | B17: Goodwill | C17: 7024470936 | D17: 6971681464 | E17: 6971681464 | F17: 6971681464 | G17: 0 | I17: kunci JSON: goodwill
A18: BS.DTA | B18: Aset pajak tangguhan | C18: 1969259816 | D18: 6097463738 | E18: 2251911265 | F18: 1365138297 | G18: 1153962483 | H18: 1313984823 | I18: kunci JSON: aset_pajak_tangguhan
A19: BS.OTHER_NCA | B19: Aset tidak lancar lainnya (terutama uang muka pembelian aset tetap/tanah) | C19: 479507049845 | D19: 28090602212 | E19: 6420844457 | F19: 3750351252 | G19: 219209965524 | H19: 388105716461 | I19: kunci JSON: aset_tl_lain
A20: BS.TOTAL_NCA | B20: Jumlah aset tidak lancar | C20: =C16+C17+C18+C19 -> 2663818061478 | D20: =D16+D17+D18+D19 -> 2956950755449 | E20: =E16+E17+E18+E19 -> 3352998648910 | F20: =F16+F17+F18+F19 -> 3342486785131 | G20: =G16+G17+G18+G19 -> 3477789172011 | H20: =H16+H17+H18+H19 -> 3662011946746
A21: BS.TOTAL_ASSETS | B21: JUMLAH ASET | C21: =C15+C20 -> 3445671264153 | D21: =D15+D20 -> 4211211802258 | E21: =E15+E20 -> 4234621132412 | F21: =F15+F20 -> 4137006257713 | G21: =G15+G20 -> 4021105412384 | H21: =H15+H20 -> 4175928930765
B22: LIABILITAS
A23: BS.ST_BANK | B23: Pinjaman bank jangka pendek | C23: 12963780723 | D23: 2991703325 | E23: 129665344429 | F23: 141562028547 | G23: 784583691204 | H23: 14999351279 | I23: kunci JSON: pinjaman_bank_jp
A24: BS.TRADE_PAY | B24: Utang usaha | C24: 10821912088 | D24: 14656750351 | E24: 26875586517 | F24: 42532889111 | G24: 25121215698 | H24: 21151058333 | I24: kunci JSON: utang_usaha_pk3
A25: BS.OTHER_PAY | B25: Utang lain-lain | C25: 1054065771 | D25: 13910668126 | E25: 118942040 | F25: 101870631 | G25: 110965776 | H25: 165705249 | I25: kunci JSON: utang_lain_pk3
A26: BS.TAX_PAY | B26: Utang pajak | C26: 5582268383 | D26: 8348663320 | E26: 3984780507 | F26: 7415860622 | G26: 5076025035 | H26: 4047417382 | I26: kunci JSON: utang_pajak
A27: BS.ACCRUALS | B27: Beban akrual (2020: termasuk pendapatan diterima dimuka) | C27: 10505015865 | D27: 20900956080 | E27: 30291824799 | F27: 25368291439 | G27: 19281565827 | H27: 33642337482 | I27: kunci JSON: beban_akrual
A28: BS.UNEARNED_REV | B28: Pendapatan diterima dimuka | D28: 225567741 | E28: 923705000 | F28: 765095206 | G28: 474503141 | H28: 317960517 | I28: kunci JSON: pendapatan_dimuka
A29: BS.EMPLOYEE_BENEFIT_CUR | B29: Liabilitas imbalan kerja - jangka pendek | D29: 1242431381 | E29: 1470305253 | F29: 2607723880 | G29: 1761006332 | H29: 1435919928 | I29: kunci JSON: imbalan_kerja_jt1
A30: BS.LT_BANK_CUR | B30: Utang bank jangka panjang - jatuh tempo 1 tahun | C30: 7502028558 | D30: 8275268737 | E30: 4356691244 | F30: 6804272871 | G30: 9363311221 | H30: 17208650114 | I30: kunci JSON: utang_bank_jt1
A31: BS.FINLOAN_CUR | B31: Pinjaman lembaga keuangan - jatuh tempo 1 tahun | D31: 7107214914 | E31: 15315140959 | F31: 27060733465 | G31: 28284448216 | H31: 21804949777 | I31: kunci JSON: pinjaman_lk_jt1
A32: BS.NOTES_CUR | B32: Wesel bayar / sukuk - jatuh tempo 1 tahun | F32: 649428474637 | G32: 0 | H32: 499148560875 | I32: kunci JSON: utang_obligasi_jt1
A33: BS.TOTAL_CL | B33: Jumlah liabilitas jangka pendek | C33: =C23+C24+C25+C26+C27+C28+C29+C30+C31+C32 -> 48429071388 | D33: =D23+D24+D25+D26+D27+D28+D29+D30+D31+D32 -> 77659223975 | E33: =E23+E24+E25+E26+E27+E28+E29+E30+E31+E32 -> 213002320748 | F33: =F23+F24+F25+F26+F27+F28+F29+F30+F31+F32 -> 903647240409 | G33: =G23+G24+G25+G26+G27+G28+G29+G30+G31+G32 -> 874056732450 | H33: =H23+H24+H25+H26+H27+H28+H29+H30+H31+H32 -> 613921910936
A34: BS.LT_BANK_NC | B34: Utang bank jangka panjang - setelah 1 tahun | C34: 95696931589 | D34: 87421662853 | E34: 84205352315 | F34: 82192016943 | G34: 73084588828 | H34: 279437460767 | I34: kunci JSON: utang_bank_jp
A35: BS.FINLOAN_NC | B35: Pinjaman lembaga keuangan - setelah 1 tahun | D35: 90042541090 | E35: 74727400131 | F35: 47466666666 | G35: 49150559743 | H35: 1330269852 | I35: kunci JSON: pinjaman_lk_jp
A36: BS.NOTES_NC | B36: Wesel bayar / sukuk - setelah 1 tahun | D36: 648225425171 | E36: 648767367569 | F36: 0 | H36: 249705786908 | I36: kunci JSON: utang_obligasi_jp
A37: BS.EMPLOYEE_BENEFIT | B37: Liabilitas imbalan kerja | C37: 10787821920 | D37: 9595105332 | E37: 6625105384 | F37: 5413792415 | G37: 5316132909 | H37: 6978678157 | I37: kunci JSON: imbalan_kerja
A38: BS.DTL | B38: Liabilitas pajak tangguhan | D38: 0 | E38: 401783743 | F38: 562533279 | G38: 1110561726 | H38: 699313037 | I38: kunci JSON: liab_pajak_tangguhan
A39: BS.TOTAL_NCL | B39: Jumlah liabilitas jangka panjang | C39: =C34+C35+C36+C37+C38 -> 106484753509 | D39: =D34+D35+D36+D37+D38 -> 835284734446 | E39: =E34+E35+E36+E37+E38 -> 814727009142 | F39: =F34+F35+F36+F37+F38 -> 135635009303 | G39: =G34+G35+G36+G37+G38 -> 128661843206 | H39: =H34+H35+H36+H37+H38 -> 538151508721
A40: BS.TOTAL_LIAB | B40: JUMLAH LIABILITAS | C40: =C33+C39 -> 154913824897 | D40: =D33+D39 -> 912943958421 | E40: =E33+E39 -> 1027729329890 | F40: =F33+F39 -> 1039282249712 | G40: =G33+G39 -> 1002718575656 | H40: =H33+H39 -> 1152073419657
B41: EKUITAS
A42: BS.SHARE_CAPITAL | B42: Modal saham | C42: 3325000000000 | D42: 3325000000000 | E42: 3325000000000 | F42: 3325000000000 | G42: 3325000000000 | H42: 3325000000000 | I42: kunci JSON: modal_saham
A43: BS.APIC | B43: Tambahan modal disetor | C43: 3284159332 | D43: 3284159332 | E43: 3284159332 | F43: 3284159332 | G43: 3284159332 | H43: 3284159332 | I43: kunci JSON: tambahan_modal
A44: BS.RETAINED_EARN | B44: Saldo laba (defisit) | C44: -38449339396 | D44: -31033031403 | E44: -122376092871 | F44: -231784665472 | G44: -311516892081 | H44: -306241065514 | I44: kunci JSON: saldo_laba
A45: BS.EQUITY_PARENT | B45: Ekuitas pemilik entitas induk | C45: =C42+C43+C44 -> 3289834819936 | D45: =D42+D43+D44 -> 3297251127929 | E45: =E42+E43+E44 -> 3205908066461 | F45: =F42+F43+F44 -> 3096499493860 | G45: =G42+G43+G44 -> 3016767267251 | H45: =H42+H43+H44 -> 3022043093818
A46: BS.NCI | B46: Kepentingan nonpengendali | C46: 922619320 | D46: 1016715908 | E46: 983736061 | F46: 1224514141 | G46: 1619569477 | H46: 1812417290 | I46: kunci JSON: nci
A47: BS.TOTAL_EQUITY | B47: JUMLAH EKUITAS | C47: =C45+C46 -> 3290757439256 | D47: =D45+D46 -> 3298267843837 | E47: =E45+E46 -> 3206891802522 | F47: =F45+F46 -> 3097724008001 | G47: =G45+G46 -> 3018386836728 | H47: =H45+H46 -> 3023855511108
A48: BS.TOTAL_LIAB_EQUITY | B48: JUMLAH LIABILITAS DAN EKUITAS | C48: =C40+C47 -> 3445671264153 | D48: =D40+D47 -> 4211211802258 | E48: =E40+E47 -> 4234621132412 | F48: =F40+F47 -> 4137006257713 | G48: =G40+G47 -> 4021105412384 | H48: =H40+H47 -> 4175928930765
B49: MEMO: SUBTOTAL TERCETAK DI LK
A50: BS.TOTAL_CA_PRINTED | B50: Jumlah aset lancar (tercetak) | C50: 781853202675 | D50: 1254261046809 | E50: 881622483502 | F50: 794519472582 | G50: 543316240373 | H50: 513916984019 | I50: kunci JSON: TOTAL_ASET_LANCAR
A51: BS.TOTAL_NCA_PRINTED | B51: Jumlah aset tidak lancar (tercetak) | C51: 2663818061478 | D51: 2956950755449 | E51: 3352998648910 | F51: 3342486785131 | G51: 3477789172011 | H51: 3662011946746 | I51: kunci JSON: TOTAL_ASET_TIDAK_LANCAR
A52: BS.TOTAL_ASSETS_PRINTED | B52: Jumlah aset (tercetak) | C52: 3445671264153 | D52: 4211211802258 | E52: 4234621132412 | F52: 4137006257713 | G52: 4021105412384 | H52: 4175928930765 | I52: kunci JSON: TOTAL_ASET
A53: BS.TOTAL_CL_PRINTED | B53: Liabilitas jangka pendek (tercetak) | C53: 48429071388 | D53: 77659223975 | E53: 213002320748 | F53: 903647240409 | G53: 874056732450 | H53: 613921910936 | I53: kunci JSON: TOTAL_LIAB_PENDEK
A54: BS.TOTAL_NCL_PRINTED | B54: Liabilitas jangka panjang (tercetak) | C54: 106484753509 | D54: 835284734446 | E54: 814727009142 | F54: 135635009303 | G54: 128661843206 | H54: 538151508721 | I54: kunci JSON: TOTAL_LIAB_PANJANG
A55: BS.TOTAL_LIAB_PRINTED | B55: Jumlah liabilitas (tercetak) | C55: 154913824897 | D55: 912943958421 | E55: 1027729329890 | F55: 1039282249712 | G55: 1002718575656 | H55: 1152073419657 | I55: kunci JSON: TOTAL_LIABILITAS
A56: BS.EQUITY_PARENT_PRINTED | B56: Ekuitas induk (tercetak) | C56: 3289834819936 | D56: 3297251127929 | E56: 3205908066461 | F56: 3096499493860 | G56: 3016767267251 | H56: 3022043093818 | I56: kunci JSON: EKUITAS_INDUK
A57: BS.TOTAL_EQUITY_PRINTED | B57: Jumlah ekuitas (tercetak) | C57: 3290757439256 | D57: 3298267843837 | E57: 3206891802522 | F57: 3097724008001 | G57: 3018386836728 | H57: 3023855511108 | I57: kunci JSON: TOTAL_EKUITAS
A58: BS.TOTAL_LIAB_EQUITY_PRINTED | B58: Jumlah liabilitas & ekuitas (tercetak) | C58: 3445671264153 | D58: 4211211802258 | E58: 4234621132412 | F58: 4137006257713 | G58: 4021105412384 | H58: 4175928930765 | I58: kunci JSON: TOTAL_LIAB_EKUITAS
B59: CEK
A60: BS.CHECK | B60: Aset - (liabilitas + ekuitas) = 0 | C60: =C21-C48 -> 0 | D60: =D21-D48 -> 0 | E60: =E21-E48 -> 0 | F60: =F21-F48 -> 0 | G60: =G21-G48 -> 0 | H60: =H21-H48 -> 0

Sheet CF
A1: Laporan Arus Kas - historis FY2020A-FY2025A
A2: Rp penuh. Biru = input dari CARE_seri_2020_2025.json (LK audited, Rupiah penuh), hitam = rumus. Kolom 2021 dari komparatif LK FY2022 (disilang ke LK FY2021); kolom 2020 dari komparatif LK audited FY2021 (ringkasan XBRL IDX terblokir).
B3: Sumber kolom | C3: LK FY2021 (komparatif) | D3: LK FY2022 (komparatif) | E3: LK FY2022 | F3: LK FY2023 | G3: LK FY2024 | H3: LK FY2025 | I3: Catatan sumber: CARE tercatat di BEI sejak IPO efektif 28 Feb 2020. Ringkasan XBRL IDX FS-2020/2021 terblokir (HTTP 403); kolom 2020 diambil dari LK konsolidasian audited FY2021 (kompara
A4: Kode | B4: Akun | C4: FY2020A | D4: FY2021A | E4: FY2022A | F4: FY2023A | G4: FY2024A | H4: FY2025A | I4: Catatan / sumber
B5: ARUS KAS OPERASI
A6: CF.CASH_FROM_CUSTOMERS | B6: Penerimaan kas dari pelanggan | C6: 224592214488 | D6: 292751864402 | E6: 253841095105 | F6: 232326431071 | G6: 308225530263 | H6: 446447611927 | I6: kunci JSON: terima_pelanggan
A7: CF.CASH_TO_SUPPLIERS | B7: Pembayaran kas kepada pemasok | C7: -54249030622 | D7: -123129004365 | E7: -109811205924 | F7: -116752508937 | G7: -211751066528 | H7: -199202830638 | I7: kunci JSON: bayar_pemasok
A8: CF.CASH_TO_EMPLOYEES | B8: Pembayaran kas kepada karyawan | C8: -132743418321 | D8: -84054771676 | E8: -100269540230 | F8: -81620584124 | G8: -91189172580 | H8: -93665214277 | I8: kunci JSON: bayar_karyawan
A9: CF.CASH_OTHER_OPEX | B9: Pembayaran beban operasional lainnya | C9: -16158312467 | D9: -27083325288 | E9: -43600635995 | F9: -40146098673 | G9: -39779078019 | H9: -48300245415 | I9: kunci JSON: bayar_opex_lain
A10: CF.CASH_GEN | B10: Kas yang dihasilkan dari operasi | C10: =C6+C7+C8+C9 -> 21441453078 | D10: =D6+D7+D8+D9 -> 58484763073 | E10: =E6+E7+E8+E9 -> 159712956 | F10: =F6+F7+F8+F9 -> -6192760663 | G10: =G6+G7+G8+G9 -> -34493786864 | H10: =H6+H7+H8+H9 -> 105279321597
A11: CF.FIN_INCOME_RECEIVED | B11: Penerimaan penghasilan keuangan | C11: 40428301431 | D11: 8573719399 | E11: 39138613754 | F11: 6623274915 | G11: 6242710845 | H11: 15555391585 | I11: kunci JSON: terima_penghasilan_keu
A12: CF.FIN_COST_PAID | B12: Pembayaran beban keuangan | C12: -11305994267 | D12: -18028301010 | E12: -85574763730 | F12: -82138957516 | G12: -80360564102 | H12: -70273454714 | I12: kunci JSON: bayar_beban_keu
A13: CF.TAX_PAID | B13: Pembayaran pajak penghasilan | C13: -260966152 | D13: -1901091820 | E13: -2559932092 | F13: -1324820904 | G13: -4399544199 | H13: -4674353832 | I13: kunci JSON: bayar_pajak
A14: CF.CFO | B14: Kas neto dari aktivitas operasi | C14: =C10+C11+C12+C13 -> 50302794090 | D14: =D10+D11+D12+D13 -> 47129089642 | E14: =E10+E11+E12+E13 -> -48836369112 | F14: =F10+F11+F12+F13 -> -83033264168 | G14: =G10+G11+G12+G13 -> -113011184320 | H14: =H10+H11+H12+H13 -> 45886904636
B15: ARUS KAS INVESTASI
A16: CF.SUBS_DIVEST | B16: Hasil divestasi entitas anak | D16: 0 | E16: 225800000 | F16: 0 | G16: 178083594007 | H16: 50159355 | I16: kunci JSON: divestasi_anak
A17: CF.SUBS_ACQ | B17: Akuisisi entitas anak | G17: -94627467543 | H17: 0 | I17: kunci JSON: akuisisi_anak
A18: CF.PPE_DISPOSAL_PROCEEDS | B18: Hasil penjualan aset tetap | C18: 0 | D18: 91597100 | E18: 55000000 | F18: 72000000 | G18: 0 | I18: kunci JSON: jual_aset_tetap
A19: CF.ST_INVEST_DRAW | B19: Pencairan investasi jangka pendek | C19: 20000000000 | D19: 200000000000 | E19: 650000000000 | F19: 100000000000 | G19: 229000000000 | H19: 43000000000 | I19: kunci JSON: investasi_jp_draw
A20: CF.ST_INVEST_PLACE | B20: Penempatan investasi jangka pendek | C20: 0 | D20: -650000000000 | E20: -320000000000 | F20: -9000000000 | G20: -43000000000 | H20: -50500000000 | I20: kunci JSON: investasi_jp_place
A21: CF.PPE_ADVANCES | B21: Uang muka pembelian aset tetap | C21: -479146160590 | D21: -26276036375 | E21: -3656599877 | F21: -1732920358 | G21: -216458917563 | H21: -202413407666 | I21: kunci JSON: uang_muka_aset_tetap
A22: CF.CAPEX_PPE | B22: Perolehan aset tetap | C22: -43121963224 | D22: -284128900534 | E22: -286797039796 | F22: -10829090592 | G22: -10471066015 | H22: -8343053594 | I22: kunci JSON: perolehan_aset_tetap
A23: CF.CFI | B23: Kas neto untuk aktivitas investasi | C23: =C16+C17+C18+C19+C20+C21+C22 -> -502268123814 | D23: =D16+D17+D18+D19+D20+D21+D22 -> -760313339809 | E23: =E16+E17+E18+E19+E20+E21+E22 -> 39827160327 | F23: =F16+F17+F18+F19+F20+F21+F22 -> 78509989050 | G23: =G16+G17+G18+G19+G20+G21+G22 -> 42526142886 | H23: =H16+H17+H18+H19+H20+H21+H22 -> -218206301905
B24: ARUS KAS PENDANAAN
A25: CF.ST_BANK_DRAW | B25: Penerimaan pinjaman bank jangka pendek | C25: 122406267224 | D25: 94430428219 | E25: 57611347026 | F25: 81109637645 | G25: 820261571890 | H25: 27073838533 | I25: kunci JSON: pinjaman_bank_pendek_draw
A26: CF.ST_BANK_REPAY | B26: Pembayaran pinjaman bank jangka pendek | C26: -132166928747 | D26: -104402505616 | E26: -44937705922 | F26: -69212953527 | G26: -172242638206 | H26: -796658178458 | I26: kunci JSON: pinjaman_bank_pendek_repay
A27: CF.LT_BANK_DRAW | B27: Penerimaan utang bank jangka panjang | D27: 748387819796 | E27: 91799881715 | F27: 4995000000 | G27: 0 | H27: 321589326771 | I27: kunci JSON: pinjaman_bank_panjang_draw
A28: CF.LT_BANK_REPAY | B28: Pembayaran utang bank jangka panjang | C28: -6801039853 | D28: -8740092349 | E28: -97609429124 | F28: -4694056586 | G28: -6804272871 | H28: -102577989515 | I28: kunci JSON: pinjaman_bank_panjang_repay
A29: CF.FINLOAN_DRAW | B29: Penerimaan pinjaman lembaga keuangan | G29: 57235000000 | H29: 2672706546 | I29: kunci JSON: pinjaman_lk_draw
A30: CF.FINLOAN_REPAY | B30: Pembayaran pinjaman lembaga keuangan | D30: 0 | E30: -7107214914 | F30: -15515140959 | G30: -54212785089 | H30: -56967748164 | I30: kunci JSON: pinjaman_lk_repay
A31: CF.SUKUK_ISSUE | B31: Penerimaan sukuk | H31: 750000000000 | I31: kunci JSON: terima_sukuk
A32: CF.NOTES_REPAY | B32: Pembayaran wesel bayar | G32: -650000000000 | H32: 0 | I32: kunci JSON: bayar_wesel
A33: CF.LOAN_COSTS | B33: Biaya transaksi pinjaman | D33: -1774574829 | E33: 0 | H33: -2966184621 | I33: kunci JSON: biaya_transaksi_pinjaman
A34: CF.RESTRICTED_NET | B34: Kas yang dibatasi penggunaannya - neto | C34: 1392705481 | D34: -449287797 | E34: 492529433 | F34: 395703903 | G34: -445119396 | H34: 1288057209 | I34: kunci JSON: kas_dibatasi_neto
A35: CF.RP_PAID | B35: Pembayaran kepada pihak berelasi | C35: -17619561583 | I35: kunci JSON: bayar_pihak_berelasi
A36: CF.IPO_PROCEEDS | B36: Penerimaan dari penawaran umum saham | C36: 1030000000000 | I36: kunci JSON: terima_ipo
A37: CF.IPO_COSTS | B37: Biaya emisi saham | C37: -26715840668 | I37: kunci JSON: biaya_emisi
A38: CF.DIVIDENDS_PAID | B38: Pembayaran dividen tunai (tidak ada FY2020-FY2025) | I38: kunci JSON: -
A39: CF.CFF | B39: Kas neto untuk aktivitas pendanaan | C39: =C25+C26+C27+C28+C29+C30+C31+C32+C33+C34+C35+C36+C37+C38 -> 970495601854 | D39: =D25+D26+D27+D28+D29+D30+D31+D32+D33+D34+D35+D36+D37+D38 -> 727451787424 | E39: =E25+E26+E27+E28+E29+E30+E31+E32+E33+E34+E35+E36+E37+E38 -> 249408214 | F39: =F25+F26+F27+F28+F29+F30+F31+F32+F33+F34+F35+F36+F37+F38 -> -2921809524 | G39: =G25+G26+G27+G28+G29+G30+G31+G32+G33+G34+G35+G36+G37+G38 -> -6208243672 | H39: =H25+H26+H27+H28+H29+H30+H31+H32+H33+H34+H35+H36+H37+H38 -> 143453828301
A40: CF.NET_CHANGE | B40: Kenaikan (penurunan) neto kas | C40: =C14+C23+C39 -> 518530272130 | D40: =D14+D23+D39 -> 14267537257 | E40: =E14+E23+E39 -> -8759800571 | F40: =F14+F23+F39 -> -7445084642 | G40: =G14+G23+G39 -> -76693285106 | H40: =H14+H23+H39 -> -28865568968
A41: CF.CASH_BEGIN | B41: Kas awal tahun | C41: 6949421674 | D41: 525479693804 | E41: 542400475238 | F41: 533208033479 | G41: 525762948837 | H41: 449069663731 | I41: kunci JSON: KAS_AWAL
A42: CF.SUBS_CASH | B42: Kas entitas anak yang diakuisisi / (dilepas) | C42: 0 | D42: 2653244177 | E42: -432641188 | F42: 0 | I42: kunci JSON: kas_anak_akuisisi
A43: CF.CASH_END | B43: Kas akhir tahun | C43: =C40+C41+C42 -> 525479693804 | D43: =D40+D41+D42 -> 542400475238 | E43: =E40+E41+E42 -> 533208033479 | F43: =F40+F41+F42 -> 525762948837 | G43: =G40+G41+G42 -> 449069663731 | H43: =H40+H41+H42 -> 420204094763
B44: MEMO: SUBTOTAL TERCETAK DI LK
A45: CF.CASH_GEN_PRINTED | B45: Kas yang dihasilkan dari operasi (tercetak) | F45: -6192760663 | G45: -34493786864 | H45: 105279321597 | I45: kunci JSON: KAS_DARI_OPERASI
A46: CF.CFO_PRINTED | B46: Kas neto operasi (tercetak) | C46: 50302794090 | D46: 47129089642 | E46: -48836369112 | F46: -83033264168 | G46: -113011184320 | H46: 45886904636 | I46: kunci JSON: NET_OPERASI
A47: CF.CFI_PRINTED | B47: Kas neto investasi (tercetak) | C47: -502268123814 | D47: -760313339809 | E47: 39827160327 | F47: 78509989050 | G47: 42526142886 | H47: -218206301905 | I47: kunci JSON: NET_INVESTASI
A48: CF.CFF_PRINTED | B48: Kas neto pendanaan (tercetak) | C48: 970495601854 | D48: 727451787424 | E48: 249408214 | F48: -2921809524 | G48: -6208243672 | H48: 143453828301 | I48: kunci JSON: NET_PENDANAAN
A49: CF.NET_CHANGE_PRINTED | B49: Kenaikan neto kas (tercetak) | C49: 518530272130 | D49: 14267537257 | E49: -8759800571 | F49: -7445084642 | G49: -76693285106 | H49: -28865568968 | I49: kunci JSON: KENAIKAN_NETO
A50: CF.CASH_END_PRINTED | B50: Kas akhir (tercetak) | C50: 525479693804 | D50: 542400475238 | E50: 533208033479 | F50: 525762948837 | G50: 449069663731 | H50: 420204094763 | I50: kunci JSON: KAS_AKHIR

Sheet Schedules
A1: Schedules CALK FY2020A-FY2025A
A2: Rincian catatan atas LK (tahapD per tahun, Rp penuh). Bagian A = ringkasan yang dipakai Rasio/Asumsi; bagian B-C = rincian lengkap. Kosong = tidak diungkap tahun itu; kolom FY2020 kosong (CALK 2020 tidak dimuat; Temuan C2). Kolom FY2021 dari komparatif CALK LK FY2022. Tiap tahun memakai CALK LK tahun itu sendiri; komparatif yang disajikan kembali dibuang (Temuan C4).
B3: Sumber kolom | C3: LK FY2021 (komparatif) | D3: LK FY2022 (komparatif) | E3: LK FY2022 | F3: LK FY2023 | G3: LK FY2024 | H3: LK FY2025
A4: Kode | B4: Akun | C4: FY2020A | D4: FY2021A | E4: FY2022A | F4: FY2023A | G4: FY2024A | H4: FY2025A | I4: Catatan / sumber
B5: A. RINGKASAN UNTUK MODEL (rumus dari bagian B-C)
A6: REV.INPAT | B6: Pendapatan - rawat inap (Σ rincian) | D6: =N(D48)+N(D49)+N(D50)+N(D51)+N(D52) -> 227741067451 | E6: =N(E48)+N(E49)+N(E50)+N(E51)+N(E52) -> 173583642926 | F6: =N(F48)+N(F49)+N(F50)+N(F51)+N(F52) -> 176595367941 | G6: =N(G48)+N(G49)+N(G50)+N(G51)+N(G52) -> 230649727444 | H6: =N(H48)+N(H49)+N(H50)+N(H51)+N(H52) -> 238602832073 | I6: Cat 20
A7: REV.OUTPAT | B7: Pendapatan - rawat jalan (Σ rincian) | D7: =N(D54)+N(D55)+N(D56)+N(D57)+N(D58) -> 97988396120 | E7: =N(E54)+N(E55)+N(E56)+N(E57)+N(E58) -> 86842548252 | F7: =N(F54)+N(F55)+N(F56)+N(F57)+N(F58) -> 66085431242 | G7: =N(G54)+N(G55)+N(G56)+N(G57)+N(G58) -> 88372683358 | H7: =N(H54)+N(H55)+N(H56)+N(H57)+N(H58) -> 103348773155 | I7: Cat 20
A8: REV.OTHER | B8: Pendapatan lainnya (pendapatan investasi, 2025) | D8: =N(D60) -> 0 | E8: =N(E60) -> 0 | F8: =N(F60) -> 0 | G8: =N(G60) -> 0 | H8: =N(H60) -> 97800000000 | I8: Cat 20; Temuan C5
A9: REV.DISC | B9: Diskon / selisih tarif (pengurang, 2021-2022) | D9: =N(D64) -> -34795107445 | E9: =N(E64) -> -26455466569 | F9: =N(F64) -> 0 | G9: =N(G64) -> 0 | H9: =N(H64) -> 0 | I9: Cat 20; Temuan C4
A10: REV.NET | B10: Pendapatan neto (rumus) | D10: =D6+D7+D8+D9 -> 290934356126 | E10: =E6+E7+E8+E9 -> 233970724609 | F10: =F6+F7+F8+F9 -> 242680799183 | G10: =G6+G7+G8+G9 -> 319022410802 | H10: =H6+H7+H8+H9 -> 439751605228
A11: REV.OUT_SH | B11: Porsi rawat jalan % pendapatan rumah sakit (inap + jalan) | D11: =IFERROR(D7/(D6+D7),0) -> 0.30082755 | E11: =IFERROR(E7/(E6+E7),0) -> 0.33346319 | F11: =IFERROR(F7/(F6+F7),0) -> 0.27231421 | G11: =IFERROR(G7/(G6+G7),0) -> 0.27701089 | H11: =IFERROR(H7/(H6+H7),0) -> 0.30223216
A12: DA.DEP_IN_COGS | B12: Penyusutan aset tetap di beban pokok (Cat 21) | D12: =N(D70) -> 17297314280 | E12: =N(E70) -> 22877629559 | F12: =N(F70) -> 21584974350 | G12: =N(G70) -> 25515756073 | H12: =N(H70) -> 26326052136 | I12: Cat 21
A13: DA.IN_OPEX | B13: Penyusutan di beban usaha (tidak diungkap terpisah; 0) | D13: =0 -> 0 | E13: =0 -> 0 | F13: =0 -> 0 | G13: =0 -> 0 | H13: =0 -> 0 | I13: Cat 22
A14: DA.PPE | B14: Penyusutan aset tetap (Cat 21) | D14: =D12+D13 -> 17297314280 | E14: =E12+E13 -> 22877629559 | F14: =F12+F13 -> 21584974350 | G14: =G12+G13 -> 25515756073 | H14: =H12+H13 -> 26326052136
A15: DA.MUT | B15: Penyusutan menurut mutasi Cat 9 (akumulasi: penambahan) | D15: =D39 -> 17297314280 | E15: =E39 -> 22877629559 | F15: =F39 -> 21584974350 | G15: =G39 -> 25515756073 | H15: =H39 -> 26326052136
A16: DA.ROU | B16: Penyusutan aset hak guna (tidak ada) | D16: =0 -> 0 | E16: =0 -> 0 | F16: =0 -> 0 | G16: =0 -> 0 | H16: =0 -> 0
A17: DA.SOFTWARE | B17: Amortisasi aset takberwujud (tidak ada; goodwill tidak diamortisasi) | D17: =0 -> 0 | E17: =0 -> 0 | F17: =0 -> 0 | G17: =0 -> 0 | H17: =0 -> 0
A18: DA.TOTAL | B18: Total D&A (untuk EBITDA) | D18: =D14+D16+D17 -> 17297314280 | E18: =E14+E16+E17 -> 22877629559 | F18: =F14+F16+F17 -> 21584974350 | G18: =G14+G16+G17 -> 25515756073 | H18: =H14+H16+H17 -> 26326052136
A19: PPE.ADDITIONS | B19: Penambahan aset tetap (biaya perolehan, kas + nonkas) | D19: =D31 -> 95695632413 | E19: =E31 -> 53237485863 | F19: =F31 -> 14630376744 | G19: =G31 -> 11678249547 | H19: =H31 -> 41493053594
A20: EPS.WSH | B20: Rata-rata tertimbang saham beredar - dasar (lembar) | D20: =D133 -> 33250000000 | E20: =E133 -> 33250000000 | F20: =F133 -> 33250000000 | G20: =G133 -> 33250000000 | H20: =H133 -> 33250000000 | I20: Cat laba per saham
B27: B. MUTASI ASET TETAP (Cat 9, baris JUMLAH tabel mutasi)
B28: Cat 9 Aset tetap - biaya perolehan (JUMLAH)
A29: MUT.COST_T.saldo_awal | B29: Saldo awal | D29: 2240626968829 | E29: 3037021081863 | F29: 3467630763681 | G29: 3482029090425 | H29: 3432215639882 | I29: mutasi_aset (biaya perolehan)
A30: MUT.COST_T.akuisisi | B30: Akuisisi entitas anak | D30: 700939207168 | E30: 377484118288 | F30: 0 | G30: -60970485090 | H30: 0
A31: MUT.COST_T.penambahan | B31: Penambahan | D31: 95695632413 | E31: 53237485863 | F31: 14630376744 | G31: 11678249547 | H31: 41493053594
A32: MUT.COST_T.pengurangan | B32: Pengurangan (tercatat negatif) | D32: -240726547 | E32: -111922333 | F32: -232050000 | G32: -521215000 | H32: -314989194
A33: MUT.COST_T.reklasifikasi | B33: Reklasifikasi | D33: 0 | E33: 0 | F33: 0 | G33: 0 | H33: 0
A34: MUT.COST_T.saldo_akhir | B34: Saldo akhir (tercetak) | D34: 3037021081863 | E34: 3467630763681 | F34: 3482029090425 | G34: 3432215639882 | H34: 3473393704282
A35: MUT.COST_T.END | B35: Saldo akhir (rumus: awal + akuisisi + penambahan + pengurangan + reklas) | D35: =D29+N(D30)+D31+D32+D33 -> 3037021081863 | E35: =E29+N(E30)+E31+E32+E33 -> 3467630763681 | F35: =F29+N(F30)+F31+F32+F33 -> 3482029090425 | G35: =G29+N(G30)+G31+G32+G33 -> 3432215639882 | H35: =H29+N(H30)+H31+H32+H33 -> 3473393704282
B36: Cat 9 Aset tetap - akumulasi penyusutan (JUMLAH)
A37: MUT.AD_T.saldo_awal | B37: Saldo awal | D37: 65309687948 | E37: 121230073828 | F37: 130276551957 | G37: 151629476307 | H37: 174790395878 | I37: mutasi_aset (akumulasi penyusutan)
A38: MUT.AD_T.akuisisi | B38: Akuisisi entitas anak | D38: 38788051552 | E38: -13751885347 | F38: 0 | G38: -1833621502 | H38: 0
A39: MUT.AD_T.penambahan | B39: Penambahan | D39: 17297314280 | E39: 22877629559 | F39: 21584974350 | G39: 25515756073 | H39: 26326052136
A40: MUT.AD_T.pengurangan | B40: Pengurangan (tercatat negatif) | D40: -164979952 | E40: -79266083 | F40: -232050000 | G40: -521215000 | H40: -314989194
A41: MUT.AD_T.reklasifikasi | B41: Reklasifikasi | D41: 0 | E41: 0 | F41: 0 | G41: 0 | H41: 0
A42: MUT.AD_T.saldo_akhir | B42: Saldo akhir (tercetak) | D42: 121230073828 | E42: 130276551957 | F42: 151629476307 | G42: 174790395878 | H42: 200801458820
A43: MUT.AD_T.END | B43: Saldo akhir (rumus: awal + akuisisi + penambahan + pengurangan + reklas) | D43: =D37+N(D38)+D39+D40+D41 -> 121230073828 | E43: =E37+N(E38)+E39+E40+E41 -> 130276551957 | F43: =F37+N(F38)+F39+F40+F41 -> 151629476307 | G43: =G37+N(G38)+G39+G40+G41 -> 174790395878 | H43: =H37+N(H38)+H39+H40+H41 -> 200801458820
A44: PPE.NBV | B44: Nilai tercatat aset tetap (biaya - akumulasi) | D44: =D34-D42 -> 2915791008035 | E44: =E34-E42 -> 3337354211724 | F44: =F34-F42 -> 3330399614118 | G44: =G34-G42 -> 3257425244004 | H44: =H34-H42 -> 3272592245462
B46: C. RINCIAN CATATAN (urut catatan LK)
B47: Cat 20 - Rawat inap
A48: CK001 | B48: Kamar rawat inap | D48: 85561084222 | E48: 59522584951 | F48: 62769144873 | G48: 79971978451 | H48: 94961869556 | I48: hal PDF 65,67,76
A49: CK002 | B49: Jasa medis | D49: 57817012718 | E49: 48425092048 | F49: 47312041259 | G49: 65218414029 | H49: 56392997716 | I49: hal PDF 65,67,76
A50: CK003 | B50: Obat dan perlengkapan medis | D50: 30071123526 | E50: 31296284192 | F50: 33594554794 | G50: 42736234133 | H50: 46510425397 | I50: hal PDF 65,67,76
A51: CK004 | B51: Jasa penunjang medis | D51: 44975023114 | E51: 26325975238 | F51: 25620273578 | G51: 31989346647 | H51: 28716987760 | I51: hal PDF 65,67,76
A52: CK005 | B52: Pendapatan administrasi dan lainnya | D52: 9316823871 | E52: 8013706497 | F52: 7299353437 | G52: 10733754184 | H52: 12020551644 | I52: hal PDF 65,67,76
B53: Cat 20 - Rawat jalan
A54: CK006 | B54: Obat dan perlengkapan medis | D54: 21371214441 | E54: 28948975992 | F54: 22454208393 | G54: 29796942473 | H54: 39818018139 | I54: hal PDF 65,67,76
A55: CK007 | B55: Jasa medis | D55: 23746436531 | E55: 25714454586 | F55: 23340671793 | G55: 28927667098 | H55: 32511984256 | I55: hal PDF 65,67,76
A56: CK008 | B56: Jasa penunjang medis | D56: 43452183356 | E56: 21708000186 | F56: 11830465265 | G56: 16622572369 | H56: 15273486238 | I56: hal PDF 65,67,76
A57: CK009 | B57: Jasa instalasi gawat darurat | D57: 5714685941 | E57: 5640831403 | F57: 4835372702 | G57: 7017350222 | H57: 8764830069 | I57: hal PDF 65,67,76
A58: CK010 | B58: Pendapatan administrasi dan lainnya | D58: 3703875851 | E58: 4830286085 | F58: 3624713089 | G58: 6008151196 | H58: 6980454453 | I58: hal PDF 65,67,76
B59: Cat 20 - Lainnya
A60: CK011 | B60: Pendapatan investasi | H60: 97800000000 | I60: hal PDF 76
B61: Cat 20 - Jumlah
A62: CK012 | B62: JUMLAH (lapor) | D62: 290934356126 | E62: 233970724609 | F62: 242680799183 | G62: 319022410802 | H62: 439751605228 | I62: hal PDF 65,67,76
A63: CK013 | B63: Total bruto | D63: 325729463571 | E63: 260426191178 | I63: hal PDF 76
A64: CK014 | B64: Diskon | D64: -34795107445 | E64: -26455466569 | I64: hal PDF 76
A65: SK001 | B65: Σ rincian (rumus) | D65: =N(D48)+N(D49)+N(D50)+N(D51)+N(D52)+N(D54)+N(D55)+N(D56)+N(D57)+N(D58)+N(D60)+N(D64) -> 290934356126 | E65: =N(E48)+N(E49)+N(E50)+N(E51)+N(E52)+N(E54)+N(E55)+N(E56)+N(E57)+N(E58)+N(E60)+N(E64) -> 233970724609 | F65: =N(F48)+N(F49)+N(F50)+N(F51)+N(F52)+N(F54)+N(F55)+N(F56)+N(F57)+N(F58)+N(F60)+N(F64) -> 242680799183 | G65: =N(G48)+N(G49)+N(G50)+N(G51)+N(G52)+N(G54)+N(G55)+N(G56)+N(G57)+N(G58)+N(G60)+N(G64) -> 319022410802 | H65: =N(H48)+N(H49)+N(H50)+N(H51)+N(H52)+N(H54)+N(H55)+N(H56)+N(H57)+N(H58)+N(H60)+N(H64) -> 439751605228
B66: Cat 21 - Jumlah
A67: CK015 | B67: Jasa tenaga ahli medis | F67: 53752817033 | G67: 56136910913 | H67: 63395778416 | I67: hal PDF 65,67,76
A68: CK016 | B68: Biaya selisih tarif klaim | F68: 29196274360 | G68: 69246864317 | H68: 57975226027 | I68: hal PDF 65,67,76
A69: CK017 | B69: Obat dan perlengkapan medis | D69: 47583755931 | E69: 41597478556 | F69: 36214766736 | G69: 46011351956 | H69: 56179311287 | I69: hal PDF 65,67,76
A70: CK018 | B70: Penyusutan | D70: 17297314280 | E70: 22877629559 | F70: 21584974350 | G70: 25515756073 | H70: 26326052136 | I70: hal PDF 65,67,76
A71: CK019 | B71: Makanan dan minuman | D71: 7279969949 | E71: 5033270720 | F71: 3883308486 | G71: 5515498100 | H71: 6750975538 | I71: hal PDF 65,67,76
A72: CK020 | B72: Jasa penunjang medis | D72: 3354135472 | E72: 3081837214 | F72: 4211795765 | G72: 4574711448 | H72: 5698895075 | I72: hal PDF 65,67,76
A73: CK021 | B73: Rujukan | D73: 15555449947 | E73: 4698230515 | F73: 2706916304 | G73: 3606914936 | H73: 3639480216 | I73: hal PDF 65,67,76
A74: CK022 | B74: Gaji dan tunjangan karyawan | F74: 939064484 | G74: 1647697571 | H74: 2111881932 | I74: hal PDF 65,67,76
A75: CK023 | B75: Lain-lain (masing-masing di bawah Rp 200.000.000) | F75: 536612723 | G75: 2178991329 | H75: 2516415662 | I75: hal PDF 65,67,76
A76: CK024 | B76: JUMLAH (lapor) | D76: 145000436678 | E76: 137738459043 | F76: 153026530241 | G76: 214434696643 | H76: 224594016289 | I76: hal PDF 65,67,76
A77: CK025 | B77: Jasa tenaga ahli, gaji dan tunjangan | D77: 53094153182 | E77: 59635290511 | I77: hal PDF 76
A78: CK026 | B78: Perbaikan dan pemeliharaan | D78: 125139592 | E78: 246526587 | I78: hal PDF 76
A79: CK027 | B79: Lain-lain (masing-masing dibawah Rp 200.000.000) | D79: 710518325 | E79: 568195381 | I79: hal PDF 76
A80: SK002 | B80: Σ rincian (rumus) | D80: =N(D67)+N(D68)+N(D69)+N(D70)+N(D71)+N(D72)+N(D73)+N(D74)+N(D75)+N(D77)+N(D78)+N(D79) -> 145000436678 | E80: =N(E67)+N(E68)+N(E69)+N(E70)+N(E71)+N(E72)+N(E73)+N(E74)+N(E75)+N(E77)+N(E78)+N(E79) -> 137738459043 | F80: =N(F67)+N(F68)+N(F69)+N(F70)+N(F71)+N(F72)+N(F73)+N(F74)+N(F75)+N(F77)+N(F78)+N(F79) -> 153026530241 | G80: =N(G67)+N(G68)+N(G69)+N(G70)+N(G71)+N(G72)+N(G73)+N(G74)+N(G75)+N(G77)+N(G78)+N(G79) -> 214434696643 | H80: =N(H67)+N(H68)+N(H69)+N(H70)+N(H71)+N(H72)+N(H73)+N(H74)+N(H75)+N(H77)+N(H78)+N(H79) -> 224594016289
B81: Cat 22 - Jumlah
A82: CK028 | B82: Gaji dan tunjangan | D82: 85818306730 | E82: 99952397980 | F82: 81959240386 | G82: 85978960899 | H82: 92658718016 | I82: hal PDF 66,68,77
A83: CK029 | B83: Honorarium tenaga ahli | D83: 9763891570 | E83: 11421360978 | F83: 8370960501 | G83: 9558630021 | H83: 10208488621 | I83: hal PDF 66,68,77
A84: CK030 | B84: Pajak dan perijinan | D84: 5942785615 | E84: 6025579971 | F84: 6553903145 | G84: 5145841539 | H84: 8684458803 | I84: hal PDF 66,68,77
A85: CK031 | B85: Listrik dan air | D85: 4507042360 | E85: 6162518826 | F85: 5197077888 | G85: 6317435530 | H85: 6877384908 | I85: hal PDF 66,68,77
A86: CK032 | B86: Peralatan kantor | D86: 4369026112 | E86: 6484828864 | F86: 4278404472 | G86: 5623125960 | H86: 5498673319 | I86: hal PDF 66,68,77
A87: CK033 | B87: Jasa kebersihan | G87: 5338785775 | H87: 5216750945 | I87: hal PDF 66,77
A88: CK034 | B88: Keamanan | D88: 3926176298 | E88: 4669071950 | F88: 3758102796 | G88: 3933612468 | H88: 3453516677 | I88: hal PDF 66,68,77
A89: CK035 | B89: Sewa | D89: 2658729317 | E89: 4642857471 | F89: 4005700364 | G89: 3702882279 | H89: 3422715022 | I89: hal PDF 66,68,77
A90: CK036 | B90: Perbaikan dan pemeliharaan | D90: 1480282020 | E90: 2339545176 | F90: 1689185119 | G90: 1882522806 | H90: 2251420455 | I90: hal PDF 66,68,77
A91: CK037 | B91: Imbalan pascakerja | D91: 1275741550 | E91: 2922718460 | F91: 2358340776 | G91: 1931654349 | H91: 2098802874 | I91: hal PDF 66,68,77
A92: CK038 | B92: Transportasi | D92: 1225017764 | E92: 1632638548 | F92: 878382827 | G92: 993820632 | H92: 1206169626 | I92: hal PDF 66,68,77
A93: CK039 | B93: Lingkungan | D93: 1176299941 | E93: 1004755712 | F93: 574501190 | G93: 693852475 | H93: 935215228 | I93: hal PDF 66,68,77
A94: CK040 | B94: Pelatihan | D94: 251119287 | E94: 1060810675 | F94: 223192023 | G94: 374235696 | H94: 589380671 | I94: hal PDF 66,68,77
A95: CK041 | B95: Iklan dan promosi | D95: 204179634 | E95: 621096579 | F95: 332356815 | G95: 490319995 | H95: 556438151 | I95: hal PDF 66,68,77
A96: CK042 | B96: Asuransi | D96: 357160147 | E96: 532625844 | F96: 384759532 | G96: 408055398 | H96: 420312052 | I96: hal PDF 66,68,77
A97: CK043 | B97: Kerugian penurunan nilai piutang usaha | F97: 382896083 | G97: 1278126523 | H97: 20739873 | I97: hal PDF 66,68,77
A98: CK044 | B98: Lain-lain (masing-masing di bawah Rp 200.000.000) | D98: 2805427454 | E98: 1632304955 | F98: 653342618 | G98: 672536043 | H98: 1042532244 | I98: hal PDF 66,68,77
A99: CK045 | B99: JUMLAH (lapor) | D99: 131835962281 | E99: 156823647433 | F99: 125793052442 | G99: 134515340769 | H99: 145141717485 | I99: hal PDF 66,68,77
A100: CK046 | B100: Komunikasi | D100: 262662138 | E100: 289257091 | F100: 175441235 | G100: 190942381 | I100: hal PDF 66,68,77
A101: CK047 | B101: Cleaning services | D101: 4506984899 | E101: 5225360381 | F101: 4017264672 | I101: hal PDF 68,77
A102: CK048 | B102: Cadangan kerugian piutang | D102: 1305129445 | E102: 203917972 | I102: hal PDF 77
A103: SK003 | B103: Σ rincian (rumus) | D103: =N(D82)+N(D83)+N(D84)+N(D85)+N(D86)+N(D87)+N(D88)+N(D89)+N(D90)+N(D91)+N(D92)+N(D93)+N(D94)+N(D95)+N(D96)+N(D97)+N(D98)+N(D100)+N(D101)+N(D102) -> 131835962281 | E103: =N(E82)+N(E83)+N(E84)+N(E85)+N(E86)+N(E87)+N(E88)+N(E89)+N(E90)+N(E91)+N(E92)+N(E93)+N(E94)+N(E95)+N(E96)+N(E97)+N(E98)+N(E100)+N(E101)+N(E102) -> 156823647433 | F103: =N(F82)+N(F83)+N(F84)+N(F85)+N(F86)+N(F87)+N(F88)+N(F89)+N(F90)+N(F91)+N(F92)+N(F93)+N(F94)+N(F95)+N(F96)+N(F97)+N(F98)+N(F100)+N(F101)+N(F102) -> 125793052442 | G103: =N(G82)+N(G83)+N(G84)+N(G85)+N(G86)+N(G87)+N(G88)+N(G89)+N(G90)+N(G91)+N(G92)+N(G93)+N(G94)+N(G95)+N(G96)+N(G97)+N(G98)+N(G100)+N(G101)+N(G102) -> 134515340769 | H103: =N(H82)+N(H83)+N(H84)+N(H85)+N(H86)+N(H87)+N(H88)+N(H89)+N(H90)+N(H91)+N(H92)+N(H93)+N(H94)+N(H95)+N(H96)+N(H97)+N(H98)+N(H100)+N(H101)+N(H102) -> 145141717485
B104: Cat 23 - Jumlah
A105: CK049 | B105: Bunga bank | D105: 6204209122 | E105: 1560967442 | F105: 1520809153 | G105: 2852619973 | H105: 7772297007 | I105: hal PDF 66,68,77
A106: CK050 | B106: Bunga promissory note | H106: 5500000000 | I106: hal PDF 77
A107: CK051 | B107: Bunga deposito berjangka | D107: 2369510277 | E107: 8130811205 | F107: 5102465762 | G107: 3390090872 | H107: 2283094578 | I107: hal PDF 66,68,77
...

Sheet Rasio
A1: Rasio keuangan FY2020A-FY2025A
A2: Rumus dari IS/BS/CF/Schedules. Rata-rata saldo & pertumbuhan mulai 2021; rasio berbasis CALK (EBITDA, D&A) kosong untuk 2020. Kolom rata-rata = FY2022-FY2025.
A4: Kode | B4: Akun | C4: FY2020A | D4: FY2021A | E4: FY2022A | F4: FY2023A | G4: FY2024A | H4: FY2025A | I4: Rata-rata FY2022-25 | J4: Definisi / catatan
B5: PERTUMBUHAN (yoy)
A6: R.G_REV | B6: Pendapatan neto | D6: =IFERROR(IS!D6/IS!C6-1,0) -> 0.34507447 | E6: =IFERROR(IS!E6/IS!D6-1,0) -> -0.19579548 | F6: =IFERROR(IS!F6/IS!E6-1,0) -> 0.037227198 | G6: =IFERROR(IS!G6/IS!F6-1,0) -> 0.31457623 | H6: =IFERROR(IS!H6/IS!G6-1,0) -> 0.37843484 | I6: =AVERAGE(E6:H6) -> 0.1336107
A7: R.G_INPAT | B7: Rawat inap | E7: =IFERROR(Schedules!E6/Schedules!D6-1,0) -> -0.23780263 | F7: =IFERROR(Schedules!F6/Schedules!E6-1,0) -> 0.017350281 | G7: =IFERROR(Schedules!G6/Schedules!F6-1,0) -> 0.3060916 | H7: =IFERROR(Schedules!H6/Schedules!G6-1,0) -> 0.034481309 | I7: =AVERAGE(E7:H7) -> 0.030030142
A8: R.G_OUTPAT | B8: Rawat jalan | E8: =IFERROR(Schedules!E7/Schedules!D7-1,0) -> -0.11374661 | F8: =IFERROR(Schedules!F7/Schedules!E7-1,0) -> -0.23902013 | G8: =IFERROR(Schedules!G7/Schedules!F7-1,0) -> 0.3372491 | H8: =IFERROR(Schedules!H7/Schedules!G7-1,0) -> 0.16946515 | I8: =AVERAGE(E8:H8) -> 0.038486877
A9: R.G_EBITDA | B9: EBITDA | E9: =IFERROR((IS!E10+Schedules!E18)/(IS!D10+Schedules!D18)-1,0) -> -2.2012558 | F9: =IFERROR((IS!F10+Schedules!F18)/(IS!E10+Schedules!E18)-1,0) -> -0.61409809 | G9: =IFERROR((IS!G10+Schedules!G18)/(IS!F10+Schedules!F18)-1,0) -> -0.69685802 | H9: =IFERROR((IS!H10+Schedules!H18)/(IS!G10+Schedules!G18)-1,0) -> -22.836979 | I9: =AVERAGE(E9:H9) -> -6.5872977
A10: R.G_NI | B10: Laba tahun berjalan | D10: =IFERROR(IS!D17/IS!C17-1,0) -> -0.56425423 | E10: =IFERROR(IS!E17/IS!D17-1,0) -> -16.161988 | F10: =IFERROR(IS!F17/IS!E17-1,0) -> 0.18251744 | G10: =IFERROR(IS!G17/IS!F17-1,0) -> -0.27800125 | H10: =IFERROR(IS!H17/IS!G17-1,0) -> -1.0643862 | I10: =AVERAGE(E10:H10) -> -4.3304644
A11: R.G_NIP | B11: Laba pemilik entitas induk | D11: =IFERROR(IS!D24/IS!C24-1,0) -> -0.57386565 | E11: =IFERROR(IS!E24/IS!D24-1,0) -> -16.337092 | F11: =IFERROR(IS!F24/IS!E24-1,0) -> 0.18575121 | G11: =IFERROR(IS!G24/IS!F24-1,0) -> -0.27597066 | H11: =IFERROR(IS!H24/IS!G24-1,0) -> -1.0616706 | I11: =AVERAGE(E11:H11) -> -4.3722455
B12: PROFITABILITAS
A13: R.GM | B13: Margin laba bruto | C13: =IFERROR(IS!C8/IS!C6,0) -> 0.47569723 | D13: =IFERROR(IS!D8/IS!D6,0) -> 0.50160428 | E13: =IFERROR(IS!E8/IS!E6,0) -> 0.41130046 | F13: =IFERROR(IS!F8/IS!F6,0) -> 0.36943289 | G13: =IFERROR(IS!G8/IS!G6,0) -> 0.32783814 | H13: =IFERROR(IS!H8/IS!H6,0) -> 0.48927073 | I13: =AVERAGE(E13:H13) -> 0.39946055
A14: R.OPM | B14: Margin laba usaha | C14: =IFERROR(IS!C10/IS!C6,0) -> -0.071740459 | D14: =IFERROR(IS!D10/IS!D6,0) -> 0.048457519 | E14: =IFERROR(IS!E10/IS!E6,0) -> -0.25896993 | F14: =IFERROR(IS!F10/IS!F6,0) -> -0.14891489 | G14: =IFERROR(IS!G10/IS!G6,0) -> -0.093810421 | H14: =IFERROR(IS!H10/IS!H6,0) -> 0.15921686 | I14: =AVERAGE(E14:H14) -> -0.085619593
A15: R.EBITDA | B15: EBITDA (Rp) | D15: =(IS!D10+Schedules!D18) -> 31395271447 | E15: =(IS!E10+Schedules!E18) -> -37713752308 | F15: =(IS!F10+Schedules!F18) -> -14553809150 | G15: =(IS!G10+Schedules!G18) -> -4411870537 | H15: =(IS!H10+Schedules!H18) -> 96341923590 | I15: =AVERAGE(E15:H15) -> 9.9156229e+09 | J15: laba (rugi) usaha + penyusutan aset tetap (Cat 21); tanpa pendapatan lain-lain
A16: R.EBITDA_M | B16: Margin EBITDA | D16: =IFERROR((IS!D10+Schedules!D18)/IS!D6,0) -> 0.10791187 | E16: =IFERROR((IS!E10+Schedules!E18)/IS!E6,0) -> -0.16119005 | F16: =IFERROR((IS!F10+Schedules!F18)/IS!F6,0) -> -0.059970996 | G16: =IFERROR((IS!G10+Schedules!G18)/IS!G6,0) -> -0.013829344 | H16: =IFERROR((IS!H10+Schedules!H18)/IS!H6,0) -> 0.2190826 | I16: =AVERAGE(E16:H16) -> -0.0039769476
A17: R.NM | B17: Margin laba bersih | C17: =IFERROR(IS!C17/IS!C6,0) -> 0.065502575 | D17: =IFERROR(IS!D17/IS!D6,0) -> 0.021219992 | E17: =IFERROR(IS!E17/IS!E6,0) -> -0.40006895 | F17: =IFERROR(IS!F17/IS!F6,0) -> -0.45610886 | G17: =IFERROR(IS!G17/IS!G6,0) -> -0.2505066 | H17: =IFERROR(IS!H17/IS!H6,0) -> 0.011701074 | I17: =AVERAGE(E17:H17) -> -0.27374583
A18: R.NMP | B18: Margin laba induk | C18: =IFERROR(IS!C24/IS!C6,0) -> 0.06617245 | D18: =IFERROR(IS!D24/IS!D6,0) -> 0.020964158 | E18: =IFERROR(IS!E24/IS!E6,0) -> -0.39981026 | F18: =IFERROR(IS!F24/IS!F6,0) -> -0.45706042 | G18: =IFERROR(IS!G24/IS!G6,0) -> -0.25173523 | H18: =IFERROR(IS!H24/IS!H6,0) -> 0.011262536 | I18: =AVERAGE(E18:H18) -> -0.27433585
A19: R.ROE | B19: ROE (laba induk / rata-rata ekuitas induk) | D19: =IFERROR(IS!D24/((BS!D45+BS!C45)/2),0) -> 0.0018518641 | E19: =IFERROR(IS!E24/((BS!E45+BS!D45)/2),0) -> -0.028768755 | F19: =IFERROR(IS!F24/((BS!F45+BS!E45)/2),0) -> -0.03519918 | G19: =IFERROR(IS!G24/((BS!G45+BS!F45)/2),0) -> -0.026273737 | H19: =IFERROR(IS!H24/((BS!H45+BS!G45)/2),0) -> 0.001640296 | I19: =AVERAGE(E19:H19) -> -0.022150344
A20: R.ROA | B20: ROA (laba / rata-rata aset) | D20: =IFERROR(IS!D17/((BS!D21+BS!C21)/2),0) -> 0.0016125686 | E20: =IFERROR(IS!E17/((BS!E21+BS!D21)/2),0) -> -0.022165824 | F20: =IFERROR(IS!F17/((BS!F21+BS!E21)/2),0) -> -0.02644381 | G20: =IFERROR(IS!G17/((BS!G21+BS!F21)/2),0) -> -0.019592088 | H20: =IFERROR(IS!H17/((BS!H21+BS!G21)/2),0) -> 0.0012554702 | I20: =AVERAGE(E20:H20) -> -0.016736563
A21: R.ETR | B21: Tarif pajak efektif | C21: =IFERROR(-IS!C16/IS!C15,0) -> -0.027198489 | D21: =IFERROR(-IS!D16/IS!D15,0) -> 0.051166078 | E21: =IFERROR(-IS!E16/IS!E15,0) -> -0.0030912546 | F21: =IFERROR(-IS!F16/IS!F15,0) -> -0.043025819 | G21: =IFERROR(-IS!G16/IS!G15,0) -> -0.054817048 | H21: =IFERROR(-IS!H16/IS!H15,0) -> 0.36248885 | I21: =AVERAGE(E21:H21) -> 0.065388683
A22: R.NCI_SH | B22: Porsi laba ke NCI | C22: =IFERROR(IS!C25/IS!C17,0) -> -0.010226703 | D22: =IFERROR(IS!D25/IS!D17,0) -> 0.012056273 | E22: =IFERROR(IS!E25/IS!E17,0) -> 0.00064660741 | F22: =IFERROR(IS!F25/IS!F17,0) -> -0.0020862705 | G22: =IFERROR(IS!G25/IS!G17,0) -> -0.0049045902 | H22: =IFERROR(IS!H25/IS!H17,0) -> 0.037478444 | I22: =AVERAGE(E22:H22) -> 0.0077835477
A23: R.OTH | B23: Pendapatan (beban) lain neto % pendapatan | C23: =IFERROR(IS!C12/IS!C6,0) -> 0.0024631428 | D23: =IFERROR(IS!D12/IS!D6,0) -> 0.0084739653 | E23: =IFERROR(IS!E12/IS!E6,0) -> 0.10957279 | F23: =IFERROR(IS!F12/IS!F6,0) -> 0.0010315002 | G23: =IFERROR(IS!G12/IS!G6,0) -> 0.079103768 | H23: =IFERROR(IS!H12/IS!H6,0) -> 0.0064969318 | I23: =AVERAGE(E23:H23) -> 0.049051248 | J23: Cat 25 (di bawah laba usaha)
B24: PENDAPATAN
A25: R.SH_OUTPAT | B25: Porsi rawat jalan (% pendapatan RS) | D25: =Schedules!D11 -> 0.30082755 | E25: =Schedules!E11 -> 0.33346319 | F25: =Schedules!F11 -> 0.27231421 | G25: =Schedules!G11 -> 0.27701089 | H25: =Schedules!H11 -> 0.30223216 | I25: =AVERAGE(E25:H25) -> 0.29625512
B26: MODAL KERJA (hari, saldo akhir)
A27: R.DSO | B27: DSO piutang usaha (hari) | C27: =IFERROR(BS!C8/IS!C6*365,0) -> 78.157702 | D27: =IFERROR(BS!D8/IS!D6*365,0) -> 54.471996 | E27: =IFERROR(BS!E8/IS!E6*365,0) -> 30.410991 | F27: =IFERROR(BS!F8/IS!F6*365,0) -> 44.764498 | G27: =IFERROR(BS!G8/IS!G6*365,0) -> 44.949167 | H27: =IFERROR(BS!H8/IS!H6*365,0) -> 26.904669 | I27: =AVERAGE(E27:H27) -> 36.757331
A28: R.DIO | B28: DIO persediaan (hari, atas beban pokok) | C28: =IFERROR(BS!C10/-IS!C7*365,0) -> 22.105991 | D28: =IFERROR(BS!D10/-IS!D7*365,0) -> 15.428125 | E28: =IFERROR(BS!E10/-IS!E7*365,0) -> 10.096747 | F28: =IFERROR(BS!F10/-IS!F7*365,0) -> 11.397525 | G28: =IFERROR(BS!G10/-IS!G7*365,0) -> 10.669232 | H28: =IFERROR(BS!H10/-IS!H7*365,0) -> 8.6859359 | I28: =AVERAGE(E28:H28) -> 10.21236
A29: R.DPO | B29: DPO utang usaha (hari, atas beban pokok) | C29: =IFERROR(BS!C24/-IS!C7*365,0) -> 34.831007 | D29: =IFERROR(BS!D24/-IS!D7*365,0) -> 36.894467 | E29: =IFERROR(BS!E24/-IS!E7*365,0) -> 71.218955 | F29: =IFERROR(BS!F24/-IS!F7*365,0) -> 101.44976 | G29: =IFERROR(BS!G24/-IS!G7*365,0) -> 42.760075 | H29: =IFERROR(BS!H24/-IS!H7*365,0) -> 34.37374 | I29: =AVERAGE(E29:H29) -> 62.450632
B30: LIKUIDITAS & SOLVABILITAS
A31: R.CR | B31: Current ratio | C31: =IFERROR(BS!C15/BS!C33,0) -> 16.144295 | D31: =IFERROR(BS!D15/BS!D33,0) -> 16.150832 | E31: =IFERROR(BS!E15/BS!E33,0) -> 4.1390276 | F31: =IFERROR(BS!F15/BS!F33,0) -> 0.87923632 | G31: =IFERROR(BS!G15/BS!G33,0) -> 0.62160295 | H31: =IFERROR(BS!H15/BS!H33,0) -> 0.83710481 | I31: =AVERAGE(E31:H31) -> 1.6192429
A32: R.DEBT | B32: Utang berbunga: bank + lembaga keuangan + wesel/sukuk (Rp) | C32: =(BS!C23+BS!C30+BS!C34+BS!C31+BS!C35+BS!C32+BS!C36) -> 116162740870 | D32: =(BS!D23+BS!D30+BS!D34+BS!D31+BS!D35+BS!D32+BS!D36) -> 844063816090 | E32: =(BS!E23+BS!E30+BS!E34+BS!E31+BS!E35+BS!E32+BS!E36) -> 957037296647 | F32: =(BS!F23+BS!F30+BS!F34+BS!F31+BS!F35+BS!F32+BS!F36) -> 954514193129 | G32: =(BS!G23+BS!G30+BS!G34+BS!G31+BS!G35+BS!G32+BS!G36) -> 944466599212 | H32: =(BS!H23+BS!H30+BS!H34+BS!H31+BS!H35+BS!H32+BS!H36) -> 1083635029572 | I32: =AVERAGE(E32:H32) -> 984913279640 | J32: Temuan C6
A33: R.CASHINV | B33: Kas + investasi jk pendek (Rp) | C33: =(BS!C6+BS!C7) -> 725479693804 | D33: =(BS!D6+BS!D7) -> 1192400475238 | E33: =(BS!E6+BS!E7) -> 853208033479 | F33: =(BS!F6+BS!F7) -> 754762948837 | G33: =(BS!G6+BS!G7) -> 492069663731 | H33: =(BS!H6+BS!H7) -> 470704094763 | I33: =AVERAGE(E33:H33) -> 6.4268619e+11 | J33: Temuan C6
A34: R.ND | B34: Utang neto (utang berbunga - kas) (Rp) | C34: =(BS!C23+BS!C30+BS!C34+BS!C31+BS!C35+BS!C32+BS!C36)+0-BS!C6 -> -409316952934 | D34: =(BS!D23+BS!D30+BS!D34+BS!D31+BS!D35+BS!D32+BS!D36)+0-BS!D6 -> 301663340852 | E34: =(BS!E23+BS!E30+BS!E34+BS!E31+BS!E35+BS!E32+BS!E36)+0-BS!E6 -> 423829263168 | F34: =(BS!F23+BS!F30+BS!F34+BS!F31+BS!F35+BS!F32+BS!F36)+0-BS!F6 -> 428751244292 | G34: =(BS!G23+BS!G30+BS!G34+BS!G31+BS!G35+BS!G32+BS!G36)+0-BS!G6 -> 495396935481 | H34: =(BS!H23+BS!H30+BS!H34+BS!H31+BS!H35+BS!H32+BS!H36)+0-BS!H6 -> 663430934809 | I34: =AVERAGE(E34:H34) -> 5.0285209e+11 | J34: negatif = kas neto
A35: R.DE | B35: Utang / ekuitas | C35: =IFERROR((BS!C23+BS!C30+BS!C34+BS!C31+BS!C35+BS!C32+BS!C36)/BS!C47,0) -> 0.035299697 | D35: =IFERROR((BS!D23+BS!D30+BS!D34+BS!D31+BS!D35+BS!D32+BS!D36)/BS!D47,0) -> 0.25591124 | E35: =IFERROR((BS!E23+BS!E30+BS!E34+BS!E31+BS!E35+BS!E32+BS!E36)/BS!E47,0) -> 0.29843143 | F35: =IFERROR((BS!F23+BS!F30+BS!F34+BS!F31+BS!F35+BS!F32+BS!F36)/BS!F47,0) -> 0.30813403 | G35: =IFERROR((BS!G23+BS!G30+BS!G34+BS!G31+BS!G35+BS!G32+BS!G36)/BS!G47,0) -> 0.31290443 | H35: =IFERROR((BS!H23+BS!H30+BS!H34+BS!H31+BS!H35+BS!H32+BS!H36)/BS!H47,0) -> 0.35836204 | I35: =AVERAGE(E35:H35) -> 0.31945798
A36: R.NDE | B36: Utang neto / EBITDA | D36: =IFERROR(((BS!D23+BS!D30+BS!D34+BS!D31+BS!D35+BS!D32+BS!D36)+0-BS!D6)/(IS!D10+Schedules!D18),0) -> 9.6085597 | E36: =IFERROR(((BS!E23+BS!E30+BS!E34+BS!E31+BS!E35+BS!E32+BS!E36)+0-BS!E6)/(IS!E10+Schedules!E18),0) -> -11.238056 | F36: =IFERROR(((BS!F23+BS!F30+BS!F34+BS!F31+BS!F35+BS!F32+BS!F36)+0-BS!F6)/(IS!F10+Schedules!F18),0) -> -29.459727 | G36: =IFERROR(((BS!G23+BS!G30+BS!G34+BS!G31+BS!G35+BS!G32+BS!G36)+0-BS!G6)/(IS!G10+Schedules!G18),0) -> -112.28728 | H36: =IFERROR(((BS!H23+BS!H30+BS!H34+BS!H31+BS!H35+BS!H32+BS!H36)+0-BS!H6)/(IS!H10+Schedules!H18),0) -> 6.8862123 | I36: =AVERAGE(E36:H36) -> -36.524712
A37: R.ICR | B37: EBITDA / beban keuangan | D37: =IFERROR((IS!D10+Schedules!D18)/-IS!D14,0) -> 1.2150473 | E37: =IFERROR((IS!E10+Schedules!E18)/-IS!E14,0) -> -0.41836147 | F37: =IFERROR((IS!F10+Schedules!F18)/-IS!F14,0) -> -0.18936056 | G37: =IFERROR((IS!G10+Schedules!G18)/-IS!G14,0) -> -0.057063565 | H37: =IFERROR((IS!H10+Schedules!H18)/-IS!H14,0) -> 1.1989244 | I37: =AVERAGE(E37:H37) -> 0.1335347
B38: ARUS KAS
A39: R.CAPEX | B39: Capex (perolehan aset tetap + uang muka aset tetap) (Rp) | C39: =-(CF!C22+CF!C21) -> 522268123814 | D39: =-(CF!D22+CF!D21) -> 310404936909 | E39: =-(CF!E22+CF!E21) -> 290453639673 | F39: =-(CF!F22+CF!F21) -> 12562010950 | G39: =-(CF!G22+CF!G21) -> 226929983578 | H39: =-(CF!H22+CF!H21) -> 210756461260 | I39: =AVERAGE(E39:H39) -> 1.8517552e+11
A40: R.CAPEX_R | B40: Capex % pendapatan | C40: =IFERROR(-(CF!C22+CF!C21)/IS!C6,0) -> 2.414598 | D40: =IFERROR(-(CF!D22+CF!D21)/IS!D6,0) -> 1.0669243 | E40: =IFERROR(-(CF!E22+CF!E21)/IS!E6,0) -> 1.2414102 | F40: =IFERROR(-(CF!F22+CF!F21)/IS!F6,0) -> 0.051763514 | G40: =IFERROR(-(CF!G22+CF!G21)/IS!G6,0) -> 0.71132929 | H40: =IFERROR(-(CF!H22+CF!H21)/IS!H6,0) -> 0.47926252 | I40: =AVERAGE(E40:H40) -> 0.62094137
A41: R.FCF | B41: Arus kas bebas sederhana (CFO - capex) (Rp) | C41: =CF!C14--(CF!C22+CF!C21) -> -471965329724 | D41: =CF!D14--(CF!D22+CF!D21) -> -263275847267 | E41: =CF!E14--(CF!E22+CF!E21) -> -339290008785 | F41: =CF!F14--(CF!F22+CF!F21) -> -95595275118 | G41: =CF!G14--(CF!G22+CF!G21) -> -339941167898 | H41: =CF!H14--(CF!H22+CF!H21) -> -164869556624 | I41: =AVERAGE(E41:H41) -> -2.34924e+11
A42: R.CCONV | B42: CFO / laba tahun berjalan | C42: =IFERROR(CF!C14/IS!C17,0) -> 3.5504636 | D42: =IFERROR(CF!D14/IS!D17,0) -> 7.6339414 | E42: =IFERROR(CF!E14/IS!E17,0) -> 0.52173143 | F42: =IFERROR(CF!F14/IS!F17,0) -> 0.75015013 | G42: =IFERROR(CF!G14/IS!G17,0) -> 1.414103 | H42: =IFERROR(CF!H14/IS!H17,0) -> 8.9177563 | I42: =AVERAGE(E42:H42) -> 2.9009352
B43: PER SAHAM (informasi, bukan penilaian)
A44: R.EPS | B44: Laba induk / 33,250,000,000 saham tercatat (Rp) | C44: =IFERROR(IS!C24/33250000000,0) -> 0.43046143 | D44: =IFERROR(IS!D24/33250000000,0) -> 0.1834344 | E44: =IFERROR(IS!E24/33250000000,0) -> -2.8133503 | F44: =IFERROR(IS!F24/33250000000,0) -> -3.3359335 | G44: =IFERROR(IS!G24/33250000000,0) -> -2.4153137 | H44: =IFERROR(IS!H24/33250000000,0) -> 0.14895393 | I44: =AVERAGE(E44:H44) -> -2.1039109 | J44: saham tercatat akhir 2025
A45: R.EPS_W | B45: Laba induk / saham rata-rata tertimbang CALK (Rp) | D45: =IFERROR(IS!D24/Schedules!D20,0) -> 0.1834344 | E45: =IFERROR(IS!E24/Schedules!E20,0) -> -2.8133503 | F45: =IFERROR(IS!F24/Schedules!F20,0) -> -3.3359335 | G45: =IFERROR(IS!G24/Schedules!G20,0) -> -2.4153137 | H45: =IFERROR(IS!H24/Schedules!H20,0) -> 0.14895393 | I45: =AVERAGE(E45:H45) -> -2.1039109
A46: R.EPS_P | B46: EPS dasar tercetak (Rp) | C46: =IS!C28 -> 0.51 | D46: =IS!D28 -> 0.18 | E46: =IS!E28 -> -2.81 | F46: =IS!F28 -> -3.34 | G46: =IS!G28 -> -2.42 | H46: =IS!H28 -> 0.15 | I46: =AVERAGE(E46:H46) -> -2.105 | J46: LK (2 desimal)
A47: R.BVPS | B47: Ekuitas induk per saham (Rp) | C47: =IFERROR(BS!C45/33250000000,0) -> 98.942401 | D47: =IFERROR(BS!D45/33250000000,0) -> 99.165447 | E47: =IFERROR(BS!E45/33250000000,0) -> 96.418288 | F47: =IFERROR(BS!F45/33250000000,0) -> 93.127804 | G47: =IFERROR(BS!G45/33250000000,0) -> 90.729843 | H47: =IFERROR(BS!H45/33250000000,0) -> 90.888514 | I47: =AVERAGE(E47:H47) -> 92.791112
A48: R.DIV | B48: Dividen tunai dibayar (Rp) | C48: =-CF!C38 -> 0 | D48: =-CF!D38 -> 0 | E48: =-CF!E38 -> 0 | F48: =-CF!F38 -> 0 | G48: =-CF!G38 -> 0 | H48: =-CF!H38 -> 0 | J48: CARE tidak membagi dividen FY2020-2025

Sheet Rekonsiliasi
A1: Rekonsiliasi & cek integritas (354 cek)
A2: Status = hasil rumus saat ini; Ekspektasi = hasil yang diharapkan dari data sumber (dihitung saat build). Semua ❌ yang diharapkan dijelaskan dan ditautkan ke Temuan.
B3: Ringkasan | C3: =IF(COUNTIF(K7:K360,"✖*")=0,"SEMUA 354 CEK SESUAI EKSPEKTASI","ADA "&COUNTIF(K7:K360,"✖*")&" CEK TIDAK SESUAI EKSPEKTASI") -> SEMUA 354 CEK SESUAI EKSPEKTASI
C4: ="OK: "&COUNTIF(I7:I360,"OK")&" | ❌ (diharapkan, dijelaskan di Temuan): "&COUNTIF(I7:I360,"❌")&" | N/A/INFO: "&(COUNTIF(I7:I360,"N/A")+COUNTIF(I7:I360,"INFO")) -> OK: 347 | ❌ (diharapkan, dijelaskan di Temuan): 3 | N/A/INFO: 4
A6: No | B6: Kategori | C6: Cek | D6: Tahun | E6: Nilai A | F6: Nilai B | G6: Selisih A-B | H6: Toleransi | I6: Status | J6: Ekspektasi | K6: Sesuai ekspektasi? | L6: Penjelasan / Temuan
A7: 1 | B7: Subtotal rumus vs tercetak | C7: IS: GROSS_PROFIT rumus = tercetak | D7: 2020 | E7: =IS!C8 -> 102891453436 | F7: =IS!C34 -> 102891453436 | G7: =IF(COUNT(E7:F7)=2,E7-F7,"") -> 0 | H7: 1 | I7: =IF(COUNT(E7:F7)<2,"N/A",IF(ABS(G7)<=H7,"OK","❌")) -> OK | J7: OK | K7: =IF(I7=J7,"✔ sesuai","✖ TIDAK sesuai") -> ✔ sesuai
A8: 2 | B8: Subtotal rumus vs tercetak | C8: IS: OPER_PROFIT rumus = tercetak | D8: 2020 | E8: =IS!C10 -> -15517181073 | F8: =IS!C35 -> -15517181073 | G8: =IF(COUNT(E8:F8)=2,E8-F8,"") -> 0 | H8: 1 | I8: =IF(COUNT(E8:F8)<2,"N/A",IF(ABS(G8)<=H8,"OK","❌")) -> OK | J8: OK | K8: =IF(I8=J8,"✔ sesuai","✖ TIDAK sesuai") -> ✔ sesuai
A9: 3 | B9: Subtotal rumus vs tercetak | C9: IS: PBT rumus = tercetak | D9: 2020 | E9: =IS!C15 -> 13792807612 | F9: =IS!C36 -> 13792807612 | G9: =IF(COUNT(E9:F9)=2,E9-F9,"") -> 0 | H9: 1 | I9: =IF(COUNT(E9:F9)<2,"N/A",IF(ABS(G9)<=H9,"OK","❌")) -> OK | J9: OK | K9: =IF(I9=J9,"✔ sesuai","✖ TIDAK sesuai") -> ✔ sesuai
A10: 4 | B10: Subtotal rumus vs tercetak | C10: IS: NET_INCOME rumus = tercetak | D10: 2020 | E10: =IS!C17 -> 14167951136 | F10: =IS!C37 -> 14167951136 | G10: =IF(COUNT(E10:F10)=2,E10-F10,"") -> 0 | H10: 1 | I10: =IF(COUNT(E10:F10)<2,"N/A",IF(ABS(G10)<=H10,"OK","❌")) -> OK | J10: OK | K10: =IF(I10=J10,"✔ sesuai","✖ TIDAK sesuai") -> ✔ sesuai
A11: 5 | B11: Subtotal rumus vs tercetak | C11: IS: OCI_TOTAL rumus = tercetak | D11: 2020 | E11: =IS!C21 -> 165817157 | F11: =IS!C38 -> 165817157 | G11: =IF(COUNT(E11:F11)=2,E11-F11,"") -> 0 | H11: 1 | I11: =IF(COUNT(E11:F11)<2,"N/A",IF(ABS(G11)<=H11,"OK","❌")) -> OK | J11: OK | K11: =IF(I11=J11,"✔ sesuai","✖ TIDAK sesuai") -> ✔ sesuai
A12: 6 | B12: Subtotal rumus vs tercetak | C12: IS: TCI rumus = tercetak | D12: 2020 | E12: =IS!C22 -> 14333768293 | F12: =IS!C39 -> 14333768293 | G12: =IF(COUNT(E12:F12)=2,E12-F12,"") -> 0 | H12: 1 | I12: =IF(COUNT(E12:F12)<2,"N/A",IF(ABS(G12)<=H12,"OK","❌")) -> OK | J12: OK | K12: =IF(I12=J12,"✔ sesuai","✖ TIDAK sesuai") -> ✔ sesuai
A13: 7 | B13: Subtotal rumus vs tercetak | C13: BS: TOTAL_CA rumus = tercetak | D13: 2020 | E13: =BS!C15 -> 781853202675 | F13: =BS!C50 -> 781853202675 | G13: =IF(COUNT(E13:F13)=2,E13-F13,"") -> 0 | H13: 1 | I13: =IF(COUNT(E13:F13)<2,"N/A",IF(ABS(G13)<=H13,"OK","❌")) -> OK | J13: OK | K13: =IF(I13=J13,"✔ sesuai","✖ TIDAK sesuai") -> ✔ sesuai
A14: 8 | B14: Subtotal rumus vs tercetak | C14: BS: TOTAL_NCA rumus = tercetak | D14: 2020 | E14: =BS!C20 -> 2663818061478 | F14: =BS!C51 -> 2663818061478 | G14: =IF(COUNT(E14:F14)=2,E14-F14,"") -> 0 | H14: 1 | I14: =IF(COUNT(E14:F14)<2,"N/A",IF(ABS(G14)<=H14,"OK","❌")) -> OK | J14: OK | K14: =IF(I14=J14,"✔ sesuai","✖ TIDAK sesuai") -> ✔ sesuai
A15: 9 | B15: Subtotal rumus vs tercetak | C15: BS: TOTAL_ASSETS rumus = tercetak | D15: 2020 | E15: =BS!C21 -> 3445671264153 | F15: =BS!C52 -> 3445671264153 | G15: =IF(COUNT(E15:F15)=2,E15-F15,"") -> 0 | H15: 1 | I15: =IF(COUNT(E15:F15)<2,"N/A",IF(ABS(G15)<=H15,"OK","❌")) -> OK | J15: OK | K15: =IF(I15=J15,"✔ sesuai","✖ TIDAK sesuai") -> ✔ sesuai
A16: 10 | B16: Subtotal rumus vs tercetak | C16: BS: TOTAL_CL rumus = tercetak | D16: 2020 | E16: =BS!C33 -> 48429071388 | F16: =BS!C53 -> 48429071388 | G16: =IF(COUNT(E16:F16)=2,E16-F16,"") -> 0 | H16: 1 | I16: =IF(COUNT(E16:F16)<2,"N/A",IF(ABS(G16)<=H16,"OK","❌")) -> OK | J16: OK | K16: =IF(I16=J16,"✔ sesuai","✖ TIDAK sesuai") -> ✔ sesuai
A17: 11 | B17: Subtotal rumus vs tercetak | C17: BS: TOTAL_NCL rumus = tercetak | D17: 2020 | E17: =BS!C39 -> 106484753509 | F17: =BS!C54 -> 106484753509 | G17: =IF(COUNT(E17:F17)=2,E17-F17,"") -> 0 | H17: 1 | I17: =IF(COUNT(E17:F17)<2,"N/A",IF(ABS(G17)<=H17,"OK","❌")) -> OK | J17: OK | K17: =IF(I17=J17,"✔ sesuai","✖ TIDAK sesuai") -> ✔ sesuai
A18: 12 | B18: Subtotal rumus vs tercetak | C18: BS: TOTAL_LIAB rumus = tercetak | D18: 2020 | E18: =BS!C40 -> 154913824897 | F18: =BS!C55 -> 154913824897 | G18: =IF(COUNT(E18:F18)=2,E18-F18,"") -> 0 | H18: 1 | I18: =IF(COUNT(E18:F18)<2,"N/A",IF(ABS(G18)<=H18,"OK","❌")) -> OK | J18: OK | K18: =IF(I18=J18,"✔ sesuai","✖ TIDAK sesuai") -> ✔ sesuai
A19: 13 | B19: Subtotal rumus vs tercetak | C19: BS: EQUITY_PARENT rumus = tercetak | D19: 2020 | E19: =BS!C45 -> 3289834819936 | F19: =BS!C56 -> 3289834819936 | G19: =IF(COUNT(E19:F19)=2,E19-F19,"") -> 0 | H19: 1 | I19: =IF(COUNT(E19:F19)<2,"N/A",IF(ABS(G19)<=H19,"OK","❌")) -> OK | J19: OK | K19: =IF(I19=J19,"✔ sesuai","✖ TIDAK sesuai") -> ✔ sesuai
A20: 14 | B20: Subtotal rumus vs tercetak | C20: BS: TOTAL_EQUITY rumus = tercetak | D20: 2020 | E20: =BS!C47 -> 3290757439256 | F20: =BS!C57 -> 3290757439256 | G20: =IF(COUNT(E20:F20)=2,E20-F20,"") -> 0 | H20: 1 | I20: =IF(COUNT(E20:F20)<2,"N/A",IF(ABS(G20)<=H20,"OK","❌")) -> OK | J20: OK | K20: =IF(I20=J20,"✔ sesuai","✖ TIDAK sesuai") -> ✔ sesuai
A21: 15 | B21: Subtotal rumus vs tercetak | C21: BS: TOTAL_LIAB_EQUITY rumus = tercetak | D21: 2020 | E21: =BS!C48 -> 3445671264153 | F21: =BS!C58 -> 3445671264153 | G21: =IF(COUNT(E21:F21)=2,E21-F21,"") -> 0 | H21: 1 | I21: =IF(COUNT(E21:F21)<2,"N/A",IF(ABS(G21)<=H21,"OK","❌")) -> OK | J21: OK | K21: =IF(I21=J21,"✔ sesuai","✖ TIDAK sesuai") -> ✔ sesuai
A22: 16 | B22: Subtotal rumus vs tercetak | C22: CF: CASH_GEN rumus = tercetak | D22: 2020 | E22: =CF!C10 -> 21441453078 | F22: =CF!C45 -> 0 | G22: =IF(COUNT(E22:F22)=2,E22-F22,"") -> 21441453078 | H22: 1 | I22: =IF(COUNT(E22:F22)<2,"N/A",IF(ABS(G22)<=H22,"OK","❌")) -> ❌ | J22: ❌ | K22: =IF(I22=J22,"✔ sesuai","✖ TIDAK sesuai") -> ✔ sesuai | L22: LK FY2021 (dan komparatifnya) tidak mencetak subtotal "kas dihasilkan dari operasi" sebelum bunga/pajak (baru disajikan sejak LK FY2023); sel tercetak kosong, bukan selisih angka. Total arus kas operasi ber-tie.
A23: 17 | B23: Subtotal rumus vs tercetak | C23: CF: CFO rumus = tercetak | D23: 2020 | E23: =CF!C14 -> 50302794090 | F23: =CF!C46 -> 50302794090 | G23: =IF(COUNT(E23:F23)=2,E23-F23,"") -> 0 | H23: 1 | I23: =IF(COUNT(E23:F23)<2,"N/A",IF(ABS(G23)<=H23,"OK","❌")) -> OK | J23: OK | K23: =IF(I23=J23,"✔ sesuai","✖ TIDAK sesuai") -> ✔ sesuai
A24: 18 | B24: Subtotal rumus vs tercetak | C24: CF: CFI rumus = tercetak | D24: 2020 | E24: =CF!C23 -> -502268123814 | F24: =CF!C47 -> -502268123814 | G24: =IF(COUNT(E24:F24)=2,E24-F24,"") -> 0 | H24: 1 | I24: =IF(COUNT(E24:F24)<2,"N/A",IF(ABS(G24)<=H24,"OK","❌")) -> OK | J24: OK | K24: =IF(I24=J24,"✔ sesuai","✖ TIDAK sesuai") -> ✔ sesuai
A25: 19 | B25: Subtotal rumus vs tercetak | C25: CF: CFF rumus = tercetak | D25: 2020 | E25: =CF!C39 -> 970495601854 | F25: =CF!C48 -> 970495601854 | G25: =IF(COUNT(E25:F25)=2,E25-F25,"") -> 0 | H25: 1 | I25: =IF(COUNT(E25:F25)<2,"N/A",IF(ABS(G25)<=H25,"OK","❌")) -> OK | J25: OK | K25: =IF(I25=J25,"✔ sesuai","✖ TIDAK sesuai") -> ✔ sesuai
A26: 20 | B26: Subtotal rumus vs tercetak | C26: CF: NET_CHANGE rumus = tercetak | D26: 2020 | E26: =CF!C40 -> 518530272130 | F26: =CF!C49 -> 518530272130 | G26: =IF(COUNT(E26:F26)=2,E26-F26,"") -> 0 | H26: 1 | I26: =IF(COUNT(E26:F26)<2,"N/A",IF(ABS(G26)<=H26,"OK","❌")) -> OK | J26: OK | K26: =IF(I26=J26,"✔ sesuai","✖ TIDAK sesuai") -> ✔ sesuai
A27: 21 | B27: Subtotal rumus vs tercetak | C27: CF: CASH_END rumus = tercetak | D27: 2020 | E27: =CF!C43 -> 525479693804 | F27: =CF!C50 -> 525479693804 | G27: =IF(COUNT(E27:F27)=2,E27-F27,"") -> 0 | H27: 1 | I27: =IF(COUNT(E27:F27)<2,"N/A",IF(ABS(G27)<=H27,"OK","❌")) -> OK | J27: OK | K27: =IF(I27=J27,"✔ sesuai","✖ TIDAK sesuai") -> ✔ sesuai
A28: 22 | B28: Integritas laporan | C28: BS: aset = liabilitas + ekuitas | D28: 2020 | E28: =BS!C21 -> 3445671264153 | F28: =BS!C48 -> 3445671264153 | G28: =IF(COUNT(E28:F28)=2,E28-F28,"") -> 0 | H28: 1 | I28: =IF(COUNT(E28:F28)<2,"N/A",IF(ABS(G28)<=H28,"OK","❌")) -> OK | J28: OK | K28: =IF(I28=J28,"✔ sesuai","✖ TIDAK sesuai") -> ✔ sesuai
A29: 23 | B29: Integritas laporan | C29: IS: laba = induk + NCI | D29: 2020 | E29: =IS!C17 -> 14167951136 | F29: =IS!C24+IS!C25 -> 14167951136 | G29: =IF(COUNT(E29:F29)=2,E29-F29,"") -> 0 | H29: 1 | I29: =IF(COUNT(E29:F29)<2,"N/A",IF(ABS(G29)<=H29,"OK","❌")) -> OK | J29: OK | K29: =IF(I29=J29,"✔ sesuai","✖ TIDAK sesuai") -> ✔ sesuai
A30: 24 | B30: Integritas laporan | C30: IS: laba komprehensif = induk + NCI | D30: 2020 | E30: =IS!C22 -> 14333768293 | F30: =IS!C26+IS!C27 -> 14333768293 | G30: =IF(COUNT(E30:F30)=2,E30-F30,"") -> 0 | H30: 1 | I30: =IF(COUNT(E30:F30)<2,"N/A",IF(ABS(G30)<=H30,"OK","❌")) -> OK | J30: OK | K30: =IF(I30=J30,"✔ sesuai","✖ TIDAK sesuai") -> ✔ sesuai
A31: 25 | B31: Integritas laporan | C31: CF: kas akhir = kas neraca (tanpa cerukan) | D31: 2020 | E31: =CF!C43 -> 525479693804 | F31: =BS!C6 -> 525479693804 | G31: =IF(COUNT(E31:F31)=2,E31-F31,"") -> 0 | H31: 1 | I31: =IF(COUNT(E31:F31)<2,"N/A",IF(ABS(G31)<=H31,"OK","❌")) -> OK | J31: OK | K31: =IF(I31=J31,"✔ sesuai","✖ TIDAK sesuai") -> ✔ sesuai
A32: 26 | B32: Integritas laporan | C32: LPE: dividen ke pemilik induk = dividen dibayar (CF) | D32: 2020 | E32: 0 | F32: =CF!C38 -> 0 | G32: =IF(COUNT(E32:F32)=2,E32-F32,"") -> 0 | H32: 1 | I32: =IF(COUNT(E32:F32)<2,"N/A",IF(ABS(G32)<=H32,"OK","❌")) -> OK | J32: OK | K32: =IF(I32=J32,"✔ sesuai","✖ TIDAK sesuai") -> ✔ sesuai | L32: LPE: LPE: seluruh laba komprehensif induk (laba + pengukuran kembali imbalan kerja) dibukukan ke defisit; tidak ada dividen / pergerakan lain
A33: 27 | B33: CALK vs laporan | C33: CALK FY2020 tidak dimuat: tie-out CALK, D&A/EBITDA & EPS tertimbang tidak dilakukan (Temuan C2) | D33: 2020 | G33: =IF(COUNT(E33:F33)=2,E33-F33,"") | H33: 1 | I33: =IF(COUNT(E33:F33)<2,"N/A",IF(ABS(G33)<=H33,"OK","N/A")) -> N/A | J33: N/A | K33: =IF(I33=J33,"✔ sesuai","✖ TIDAK sesuai") -> ✔ sesuai
A34: 28 | B34: Per saham | C34: EPS tercetak vs laba induk / saham ditempatkan akhir tahun (modal saham / Rp100) (toleransi Rp1) | D34: 2020 | E34: =IS!C28 -> 0.51 | F34: =ROUND(IS!C24/(BS!C42/100),2) -> 0.43 | G34: =IF(COUNT(E34:F34)=2,E34-F34,"") -> 0.08 | H34: 1 | I34: =IF(COUNT(E34:F34)<2,"N/A",IF(ABS(G34)<=H34,"OK","❌")) -> OK | J34: OK | K34: =IF(I34=J34,"✔ sesuai","✖ TIDAK sesuai") -> ✔ sesuai | L34: EPS 2020 tercetak memakai rata-rata tertimbang (IPO Feb 2020), sehingga sedikit di atas laba / saham akhir tahun (Temuan C3)
A35: 29 | B35: Subtotal rumus vs tercetak | C35: IS: GROSS_PROFIT rumus = tercetak | D35: 2021 | E35: =IS!D8 -> 145933919448 | F35: =IS!D34 -> 145933919448 | G35: =IF(COUNT(E35:F35)=2,E35-F35,"") -> 0 | H35: 1 | I35: =IF(COUNT(E35:F35)<2,"N/A",IF(ABS(G35)<=H35,"OK","❌")) -> OK | J35: OK | K35: =IF(I35=J35,"✔ sesuai","✖ TIDAK sesuai") -> ✔ sesuai
A36: 30 | B36: Subtotal rumus vs tercetak | C36: IS: OPER_PROFIT rumus = tercetak | D36: 2021 | E36: =IS!D10 -> 14097957167 | F36: =IS!D35 -> 14097957167 | G36: =IF(COUNT(E36:F36)=2,E36-F36,"") -> 0 | H36: 1 | I36: =IF(COUNT(E36:F36)<2,"N/A",IF(ABS(G36)<=H36,"OK","❌")) -> OK | J36: OK | K36: =IF(I36=J36,"✔ sesuai","✖ TIDAK sesuai") -> ✔ sesuai
A37: 31 | B37: Subtotal rumus vs tercetak | C37: IS: PBT rumus = tercetak | D37: 2021 | E37: =IS!D15 -> 6506538854 | F37: =IS!D36 -> 6506538854 | G37: =IF(COUNT(E37:F37)=2,E37-F37,"") -> 0 | H37: 1 | I37: =IF(COUNT(E37:F37)<2,"N/A",IF(ABS(G37)<=H37,"OK","❌")) -> OK | J37: OK | K37: =IF(I37=J37,"✔ sesuai","✖ TIDAK sesuai") -> ✔ sesuai
A38: 32 | B38: Subtotal rumus vs tercetak | C38: IS: NET_INCOME rumus = tercetak | D38: 2021 | E38: =IS!D17 -> 6173624777 | F38: =IS!D37 -> 6173624777 | G38: =IF(COUNT(E38:F38)=2,E38-F38,"") -> 0 | H38: 1 | I38: =IF(COUNT(E38:F38)<2,"N/A",IF(ABS(G38)<=H38,"OK","❌")) -> OK | J38: OK | K38: =IF(I38=J38,"✔ sesuai","✖ TIDAK sesuai") -> ✔ sesuai
A39: 33 | B39: Subtotal rumus vs tercetak | C39: IS: OCI_TOTAL rumus = tercetak | D39: 2021 | E39: =IS!D21 -> 1336779804 | F39: =IS!D38 -> 1336779804 | G39: =IF(COUNT(E39:F39)=2,E39-F39,"") -> 0 | H39: 1 | I39: =IF(COUNT(E39:F39)<2,"N/A",IF(ABS(G39)<=H39,"OK","❌")) -> OK | J39: OK | K39: =IF(I39=J39,"✔ sesuai","✖ TIDAK sesuai") -> ✔ sesuai
A40: 34 | B40: Subtotal rumus vs tercetak | C40: IS: TCI rumus = tercetak | D40: 2021 | E40: =IS!D22 -> 7510404581 | F40: =IS!D39 -> 7510404581 | G40: =IF(COUNT(E40:F40)=2,E40-F40,"") -> 0 | H40: 1 | I40: =IF(COUNT(E40:F40)<2,"N/A",IF(ABS(G40)<=H40,"OK","❌")) -> OK | J40: OK | K40: =IF(I40=J40,"✔ sesuai","✖ TIDAK sesuai") -> ✔ sesuai
A41: 35 | B41: Subtotal rumus vs tercetak | C41: BS: TOTAL_CA rumus = tercetak | D41: 2021 | E41: =BS!D15 -> 1254261046809 | F41: =BS!D50 -> 1254261046809 | G41: =IF(COUNT(E41:F41)=2,E41-F41,"") -> 0 | H41: 1 | I41: =IF(COUNT(E41:F41)<2,"N/A",IF(ABS(G41)<=H41,"OK","❌")) -> OK | J41: OK | K41: =IF(I41=J41,"✔ sesuai","✖ TIDAK sesuai") -> ✔ sesuai
A42: 36 | B42: Subtotal rumus vs tercetak | C42: BS: TOTAL_NCA rumus = tercetak | D42: 2021 | E42: =BS!D20 -> 2956950755449 | F42: =BS!D51 -> 2956950755449 | G42: =IF(COUNT(E42:F42)=2,E42-F42,"") -> 0 | H42: 1 | I42: =IF(COUNT(E42:F42)<2,"N/A",IF(ABS(G42)<=H42,"OK","❌")) -> OK | J42: OK | K42: =IF(I42=J42,"✔ sesuai","✖ TIDAK sesuai") -> ✔ sesuai
A43: 37 | B43: Subtotal rumus vs tercetak | C43: BS: TOTAL_ASSETS rumus = tercetak | D43: 2021 | E43: =BS!D21 -> 4211211802258 | F43: =BS!D52 -> 4211211802258 | G43: =IF(COUNT(E43:F43)=2,E43-F43,"") -> 0 | H43: 1 | I43: =IF(COUNT(E43:F43)<2,"N/A",IF(ABS(G43)<=H43,"OK","❌")) -> OK | J43: OK | K43: =IF(I43=J43,"✔ sesuai","✖ TIDAK sesuai") -> ✔ sesuai
A44: 38 | B44: Subtotal rumus vs tercetak | C44: BS: TOTAL_CL rumus = tercetak | D44: 2021 | E44: =BS!D33 -> 77659223975 | F44: =BS!D53 -> 77659223975 | G44: =IF(COUNT(E44:F44)=2,E44-F44,"") -> 0 | H44: 1 | I44: =IF(COUNT(E44:F44)<2,"N/A",IF(ABS(G44)<=H44,"OK","❌")) -> OK | J44: OK | K44: =IF(I44=J44,"✔ sesuai","✖ TIDAK sesuai") -> ✔ sesuai
A45: 39 | B45: Subtotal rumus vs tercetak | C45: BS: TOTAL_NCL rumus = tercetak | D45: 2021 | E45: =BS!D39 -> 835284734446 | F45: =BS!D54 -> 835284734446 | G45: =IF(COUNT(E45:F45)=2,E45-F45,"") -> 0 | H45: 1 | I45: =IF(COUNT(E45:F45)<2,"N/A",IF(ABS(G45)<=H45,"OK","❌")) -> OK | J45: OK | K45: =IF(I45=J45,"✔ sesuai","✖ TIDAK sesuai") -> ✔ sesuai
A46: 40 | B46: Subtotal rumus vs tercetak | C46: BS: TOTAL_LIAB rumus = tercetak | D46: 2021 | E46: =BS!D40 -> 912943958421 | F46: =BS!D55 -> 912943958421 | G46: =IF(COUNT(E46:F46)=2,E46-F46,"") -> 0 | H46: 1 | I46: =IF(COUNT(E46:F46)<2,"N/A",IF(ABS(G46)<=H46,"OK","❌")) -> OK | J46: OK | K46: =IF(I46=J46,"✔ sesuai","✖ TIDAK sesuai") -> ✔ sesuai
A47: 41 | B47: Subtotal rumus vs tercetak | C47: BS: EQUITY_PARENT rumus = tercetak | D47: 2021 | E47: =BS!D45 -> 3297251127929 | F47: =BS!D56 -> 3297251127929 | G47: =IF(COUNT(E47:F47)=2,E47-F47,"") -> 0 | H47: 1 | I47: =IF(COUNT(E47:F47)<2,"N/A",IF(ABS(G47)<=H47,"OK","❌")) -> OK | J47: OK | K47: =IF(I47=J47,"✔ sesuai","✖ TIDAK sesuai") -> ✔ sesuai
A48: 42 | B48: Subtotal rumus vs tercetak | C48: BS: TOTAL_EQUITY rumus = tercetak | D48: 2021 | E48: =BS!D47 -> 3298267843837 | F48: =BS!D57 -> 3298267843837 | G48: =IF(COUNT(E48:F48)=2,E48-F48,"") -> 0 | H48: 1 | I48: =IF(COUNT(E48:F48)<2,"N/A",IF(ABS(G48)<=H48,"OK","❌")) -> OK | J48: OK | K48: =IF(I48=J48,"✔ sesuai","✖ TIDAK sesuai") -> ✔ sesuai
A49: 43 | B49: Subtotal rumus vs tercetak | C49: BS: TOTAL_LIAB_EQUITY rumus = tercetak | D49: 2021 | E49: =BS!D48 -> 4211211802258 | F49: =BS!D58 -> 4211211802258 | G49: =IF(COUNT(E49:F49)=2,E49-F49,"") -> 0 | H49: 1 | I49: =IF(COUNT(E49:F49)<2,"N/A",IF(ABS(G49)<=H49,"OK","❌")) -> OK | J49: OK | K49: =IF(I49=J49,"✔ sesuai","✖ TIDAK sesuai") -> ✔ sesuai
A50: 44 | B50: Subtotal rumus vs tercetak | C50: CF: CASH_GEN rumus = tercetak | D50: 2021 | E50: =CF!D10 -> 58484763073 | F50: =CF!D45 -> 0 | G50: =IF(COUNT(E50:F50)=2,E50-F50,"") -> 58484763073 | H50: 1 | I50: =IF(COUNT(E50:F50)<2,"N/A",IF(ABS(G50)<=H50,"OK","❌")) -> ❌ | J50: ❌ | K50: =IF(I50=J50,"✔ sesuai","✖ TIDAK sesuai") -> ✔ sesuai | L50: LK FY2022 (dan komparatifnya) tidak mencetak subtotal "kas dihasilkan dari operasi" sebelum bunga/pajak (baru disajikan sejak LK FY2023); sel tercetak kosong, bukan selisih angka. Total arus kas operasi ber-tie.
A51: 45 | B51: Subtotal rumus vs tercetak | C51: CF: CFO rumus = tercetak | D51: 2021 | E51: =CF!D14 -> 47129089642 | F51: =CF!D46 -> 47129089642 | G51: =IF(COUNT(E51:F51)=2,E51-F51,"") -> 0 | H51: 1 | I51: =IF(COUNT(E51:F51)<2,"N/A",IF(ABS(G51)<=H51,"OK","❌")) -> OK | J51: OK | K51: =IF(I51=J51,"✔ sesuai","✖ TIDAK sesuai") -> ✔ sesuai
A52: 46 | B52: Subtotal rumus vs tercetak | C52: CF: CFI rumus = tercetak | D52: 2021 | E52: =CF!D23 -> -760313339809 | F52: =CF!D47 -> -760313339809 | G52: =IF(COUNT(E52:F52)=2,E52-F52,"") -> 0 | H52: 1 | I52: =IF(COUNT(E52:F52)<2,"N/A",IF(ABS(G52)<=H52,"OK","❌")) -> OK | J52: OK | K52: =IF(I52=J52,"✔ sesuai","✖ TIDAK sesuai") -> ✔ sesuai
A53: 47 | B53: Subtotal rumus vs tercetak | C53: CF: CFF rumus = tercetak | D53: 2021 | E53: =CF!D39 -> 727451787424 | F53: =CF!D48 -> 727451787424 | G53: =IF(COUNT(E53:F53)=2,E53-F53,"") -> 0 | H53: 1 | I53: =IF(COUNT(E53:F53)<2,"N/A",IF(ABS(G53)<=H53,"OK","❌")) -> OK | J53: OK | K53: =IF(I53=J53,"✔ sesuai","✖ TIDAK sesuai") -> ✔ sesuai
A54: 48 | B54: Subtotal rumus vs tercetak | C54: CF: NET_CHANGE rumus = tercetak | D54: 2021 | E54: =CF!D40 -> 14267537257 | F54: =CF!D49 -> 14267537257 | G54: =IF(COUNT(E54:F54)=2,E54-F54,"") -> 0 | H54: 1 | I54: =IF(COUNT(E54:F54)<2,"N/A",IF(ABS(G54)<=H54,"OK","❌")) -> OK | J54: OK | K54: =IF(I54=J54,"✔ sesuai","✖ TIDAK sesuai") -> ✔ sesuai
A55: 49 | B55: Subtotal rumus vs tercetak | C55: CF: CASH_END rumus = tercetak | D55: 2021 | E55: =CF!D43 -> 542400475238 | F55: =CF!D50 -> 542400475238 | G55: =IF(COUNT(E55:F55)=2,E55-F55,"") -> 0 | H55: 1 | I55: =IF(COUNT(E55:F55)<2,"N/A",IF(ABS(G55)<=H55,"OK","❌")) -> OK | J55: OK | K55: =IF(I55=J55,"✔ sesuai","✖ TIDAK sesuai") -> ✔ sesuai
A56: 50 | B56: Integritas laporan | C56: BS: aset = liabilitas + ekuitas | D56: 2021 | E56: =BS!D21 -> 4211211802258 | F56: =BS!D48 -> 4211211802258 | G56: =IF(COUNT(E56:F56)=2,E56-F56,"") -> 0 | H56: 1 | I56: =IF(COUNT(E56:F56)<2,"N/A",IF(ABS(G56)<=H56,"OK","❌")) -> OK | J56: OK | K56: =IF(I56=J56,"✔ sesuai","✖ TIDAK sesuai") -> ✔ sesuai
A57: 51 | B57: Integritas laporan | C57: IS: laba = induk + NCI | D57: 2021 | E57: =IS!D17 -> 6173624777 | F57: =IS!D24+IS!D25 -> 6173624777 | G57: =IF(COUNT(E57:F57)=2,E57-F57,"") -> 0 | H57: 1 | I57: =IF(COUNT(E57:F57)<2,"N/A",IF(ABS(G57)<=H57,"OK","❌")) -> OK | J57: OK | K57: =IF(I57=J57,"✔ sesuai","✖ TIDAK sesuai") -> ✔ sesuai
A58: 52 | B58: Integritas laporan | C58: IS: laba komprehensif = induk + NCI | D58: 2021 | E58: =IS!D22 -> 7510404581 | F58: =IS!D26+IS!D27 -> 7510404581 | G58: =IF(COUNT(E58:F58)=2,E58-F58,"") -> 0 | H58: 1 | I58: =IF(COUNT(E58:F58)<2,"N/A",IF(ABS(G58)<=H58,"OK","❌")) -> OK | J58: OK | K58: =IF(I58=J58,"✔ sesuai","✖ TIDAK sesuai") -> ✔ sesuai
A59: 53 | B59: Integritas laporan | C59: CF: kas akhir = kas neraca (tanpa cerukan) | D59: 2021 | E59: =CF!D43 -> 542400475238 | F59: =BS!D6 -> 542400475238 | G59: =IF(COUNT(E59:F59)=2,E59-F59,"") -> 0 | H59: 1 | I59: =IF(COUNT(E59:F59)<2,"N/A",IF(ABS(G59)<=H59,"OK","❌")) -> OK | J59: OK | K59: =IF(I59=J59,"✔ sesuai","✖ TIDAK sesuai") -> ✔ sesuai
A60: 54 | B60: Integritas laporan | C60: LPE: dividen ke pemilik induk = dividen dibayar (CF) | D60: 2021 | E60: 0 | F60: =CF!D38 -> 0 | G60: =IF(COUNT(E60:F60)=2,E60-F60,"") -> 0 | H60: 1 | I60: =IF(COUNT(E60:F60)<2,"N/A",IF(ABS(G60)<=H60,"OK","❌")) -> OK | J60: OK | K60: =IF(I60=J60,"✔ sesuai","✖ TIDAK sesuai") -> ✔ sesuai | L60: LPE: LPE: seluruh laba komprehensif induk (laba + pengukuran kembali imbalan kerja) dibukukan ke defisit; tidak ada dividen / pergerakan lain
A61: 55 | B61: Antar tahun | C61: CF: kas awal = kas neraca tahun lalu | D61: 2021 | E61: =CF!D41 -> 525479693804 | F61: =BS!C6 -> 525479693804 | G61: =IF(COUNT(E61:F61)=2,E61-F61,"") -> 0 | H61: 1 | I61: =IF(COUNT(E61:F61)<2,"N/A",IF(ABS(G61)<=H61,"OK","❌")) -> OK | J61: OK | K61: =IF(I61=J61,"✔ sesuai","✖ TIDAK sesuai") -> ✔ sesuai
A62: 56 | B62: Antar tahun | C62: Saldo laba: awal + laba komprehensif ke saldo laba (LPE) + dividen (CF) + lainnya (LPE) = akhir | D62: 2021 | E62: =BS!C44+7416307993+CF!D38+0 -> -31033031403 | F62: =BS!D44 -> -31033031403 | G62: =IF(COUNT(E62:F62)=2,E62-F62,"") -> 0 | H62: 1 | I62: =IF(COUNT(E62:F62)<2,"N/A",IF(ABS(G62)<=H62,"OK","❌")) -> OK | J62: OK | K62: =IF(I62=J62,"✔ sesuai","✖ TIDAK sesuai") -> ✔ sesuai | L62: laba komprehensif ke saldo laba (defisit) = laba induk + pengukuran kembali imbalan kerja (neto pajak, porsi induk). Angka statis LPE dari CARE_cek_silang.json
A63: 57 | B63: CALK vs laporan | C63: Cat 20: rawat inap + rawat jalan + lainnya + diskon = pendapatan neto IS | D63: 2021 | E63: =Schedules!D10 -> 290934356126 | F63: =IS!D6 -> 290934356126 | G63: =IF(COUNT(E63:F63)=2,E63-F63,"") -> 0 | H63: 1 | I63: =IF(COUNT(E63:F63)<2,"N/A",IF(ABS(G63)<=H63,"OK","❌")) -> OK | J63: OK | K63: =IF(I63=J63,"✔ sesuai","✖ TIDAK sesuai") -> ✔ sesuai
A64: 58 | B64: CALK vs laporan | C64: Cat 20: jumlah pendapatan neto tercetak = IS | D64: 2021 | E64: =Schedules!D62 -> 290934356126 | F64: =IS!D6 -> 290934356126 | G64: =IF(COUNT(E64:F64)=2,E64-F64,"") -> 0 | H64: 1 | I64: =IF(COUNT(E64:F64)<2,"N/A",IF(ABS(G64)<=H64,"OK","❌")) -> OK | J64: OK | K64: =IF(I64=J64,"✔ sesuai","✖ TIDAK sesuai") -> ✔ sesuai
A65: 59 | B65: CALK vs laporan | C65: Cat 21: jumlah beban pokok tercetak = IS | D65: 2021 | E65: =Schedules!D76 -> 145000436678 | F65: =-IS!D7 -> 145000436678 | G65: =IF(COUNT(E65:F65)=2,E65-F65,"") -> 0 | H65: 1 | I65: =IF(COUNT(E65:F65)<2,"N/A",IF(ABS(G65)<=H65,"OK","❌")) -> OK | J65: OK | K65: =IF(I65=J65,"✔ sesuai","✖ TIDAK sesuai") -> ✔ sesuai
A66: 60 | B66: CALK vs laporan | C66: Cat 22: jumlah beban usaha tercetak = IS | D66: 2021 | E66: =Schedules!D99 -> 131835962281 | F66: =-IS!D9 -> 131835962281 | G66: =IF(COUNT(E66:F66)=2,E66-F66,"") -> 0 | H66: 1 | I66: =IF(COUNT(E66:F66)<2,"N/A",IF(ABS(G66)<=H66,"OK","❌")) -> OK | J66: OK | K66: =IF(I66=J66,"✔ sesuai","✖ TIDAK sesuai") -> ✔ sesuai
A67: 61 | B67: CALK vs laporan | C67: Cat 23: jumlah penghasilan keuangan tercetak = IS | D67: 2021 | E67: =Schedules!D108 -> 15781938577 | F67: =IS!D13 -> 15781938577 | G67: =IF(COUNT(E67:F67)=2,E67-F67,"") -> 0 | H67: 1 | I67: =IF(COUNT(E67:F67)<2,"N/A",IF(ABS(G67)<=H67,"OK","❌")) -> OK | J67: OK | K67: =IF(I67=J67,"✔ sesuai","✖ TIDAK sesuai") -> ✔ sesuai
A68: 62 | B68: CALK vs laporan | C68: Cat 24: jumlah beban keuangan tercetak = IS | D68: 2021 | E68: =Schedules!D117 -> 25838724542 | F68: =-IS!D14 -> 25838724542 | G68: =IF(COUNT(E68:F68)=2,E68-F68,"") -> 0 | H68: 1 | I68: =IF(COUNT(E68:F68)<2,"N/A",IF(ABS(G68)<=H68,"OK","❌")) -> OK | J68: OK | K68: =IF(I68=J68,"✔ sesuai","✖ TIDAK sesuai") -> ✔ sesuai
A69: 63 | B69: CALK vs laporan | C69: Cat 25: jumlah pendapatan (beban) lain neto tercetak = IS | D69: 2021 | E69: =Schedules!D123 -> 2465367652 | F69: =IS!D11 -> 2465367652 | G69: =IF(COUNT(E69:F69)=2,E69-F69,"") -> 0 | H69: 1 | I69: =IF(COUNT(E69:F69)<2,"N/A",IF(ABS(G69)<=H69,"OK","❌")) -> OK | J69: OK | K69: =IF(I69=J69,"✔ sesuai","✖ TIDAK sesuai") -> ✔ sesuai
A70: 64 | B70: CALK vs laporan | C70: Cat 9: nilai tercatat aset tetap (biaya - akumulasi) = BS | D70: 2021 | E70: =Schedules!D44 -> 2915791008035 | F70: =BS!D16 -> 2915791008035 | G70: =IF(COUNT(E70:F70)=2,E70-F70,"") -> 0 | H70: 1 | I70: =IF(COUNT(E70:F70)<2,"N/A",IF(ABS(G70)<=H70,"OK","❌")) -> OK | J70: OK | K70: =IF(I70=J70,"✔ sesuai","✖ TIDAK sesuai") -> ✔ sesuai
A71: 65 | B71: CALK internal | C71: Cat 21: penyusutan aset tetap di laba rugi = penambahan akumulasi Cat 9 | D71: 2021 | E71: =Schedules!D14 -> 17297314280 | F71: =Schedules!D15 -> 17297314280 | G71: =IF(COUNT(E71:F71)=2,E71-F71,"") -> 0 | H71: 1 | I71: =IF(COUNT(E71:F71)<2,"N/A",IF(ABS(G71)<=H71,"OK","❌")) -> OK | J71: OK | K71: =IF(I71=J71,"✔ sesuai","✖ TIDAK sesuai") -> ✔ sesuai
A72: 66 | B72: CALK internal | C72: Cat 9 Aset tetap - biaya perolehan: awal + mutasi = akhir | D72: 2021 | E72: =Schedules!D35 -> 3037021081863 | F72: =Schedules!D34 -> 3037021081863 | G72: =IF(COUNT(E72:F72)=2,E72-F72,"") -> 0 | H72: 1 | I72: =IF(COUNT(E72:F72)<2,"N/A",IF(ABS(G72)<=H72,"OK","❌")) -> OK | J72: OK | K72: =IF(I72=J72,"✔ sesuai","✖ TIDAK sesuai") -> ✔ sesuai
A73: 67 | B73: CALK internal | C73: Cat 9 Aset tetap - akumulasi penyusutan: awal + mutasi = akhir | D73: 2021 | E73: =Schedules!D43 -> 121230073828 | F73: =Schedules!D42 -> 121230073828 | G73: =IF(COUNT(E73:F73)=2,E73-F73,"") -> 0 | H73: 1 | I73: =IF(COUNT(E73:F73)<2,"N/A",IF(ABS(G73)<=H73,"OK","❌")) -> OK | J73: OK | K73: =IF(I73=J73,"✔ sesuai","✖ TIDAK sesuai") -> ✔ sesuai
A74: 68 | B74: CALK internal | C74: Cat 20: Σ rincian (rawat inap + rawat jalan + lainnya + diskon) = Jumlah tercetak | D74: 2021 | E74: =Schedules!D65 -> 290934356126 | F74: =Schedules!D62 -> 290934356126 | G74: =IF(COUNT(E74:F74)=2,E74-F74,"") -> 0 | H74: 1 | I74: =IF(COUNT(E74:F74)<2,"N/A",IF(ABS(G74)<=H74,"OK","❌")) -> OK | J74: OK | K74: =IF(I74=J74,"✔ sesuai","✖ TIDAK sesuai") -> ✔ sesuai
A75: 69 | B75: CALK internal | C75: Cat 21: Σ rincian = Jumlah tercetak | D75: 2021 | E75: =Schedules!D80 -> 145000436678 | F75: =Schedules!D76 -> 145000436678 | G75: =IF(COUNT(E75:F75)=2,E75-F75,"") -> 0 | H75: 1 | I75: =IF(COUNT(E75:F75)<2,"N/A",IF(ABS(G75)<=H75,"OK","❌")) -> OK | J75: OK | K75: =IF(I75=J75,"✔ sesuai","✖ TIDAK sesuai") -> ✔ sesuai
A76: 70 | B76: CALK internal | C76: Cat 22: Σ rincian = Jumlah tercetak | D76: 2021 | E76: =Schedules!D103 -> 131835962281 | F76: =Schedules!D99 -> 131835962281 | G76: =IF(COUNT(E76:F76)=2,E76-F76,"") -> 0 | H76: 1 | I76: =IF(COUNT(E76:F76)<2,"N/A",IF(ABS(G76)<=H76,"OK","❌")) -> OK | J76: OK | K76: =IF(I76=J76,"✔ sesuai","✖ TIDAK sesuai") -> ✔ sesuai
A77: 71 | B77: CALK internal | C77: Cat 23: Σ rincian = Jumlah tercetak | D77: 2021 | E77: =Schedules!D110 -> 15781938577 | F77: =Schedules!D108 -> 15781938577 | G77: =IF(COUNT(E77:F77)=2,E77-F77,"") -> 0 | H77: 1 | I77: =IF(COUNT(E77:F77)<2,"N/A",IF(ABS(G77)<=H77,"OK","❌")) -> OK | J77: OK | K77: =IF(I77=J77,"✔ sesuai","✖ TIDAK sesuai") -> ✔ sesuai
A78: 72 | B78: CALK internal | C78: Cat 24: Σ rincian = Jumlah tercetak | D78: 2021 | E78: =Schedules!D118 -> 25838724542 | F78: =Schedules!D117 -> 25838724542 | G78: =IF(COUNT(E78:F78)=2,E78-F78,"") -> 0 | H78: 1 | I78: =IF(COUNT(E78:F78)<2,"N/A",IF(ABS(G78)<=H78,"OK","❌")) -> OK | J78: OK | K78: =IF(I78=J78,"✔ sesuai","✖ TIDAK sesuai") -> ✔ sesuai
A79: 73 | B79: CALK internal | C79: Cat 25: Σ rincian = Jumlah tercetak | D79: 2021 | E79: =Schedules!D130 -> 2465367652 | F79: =Schedules!D123 -> 2465367652 | G79: =IF(COUNT(E79:F79)=2,E79-F79,"") -> 0 | H79: 1 | I79: =IF(COUNT(E79:F79)<2,"N/A",IF(ABS(G79)<=H79,"OK","❌")) -> OK | J79: OK | K79: =IF(I79=J79,"✔ sesuai","✖ TIDAK sesuai") -> ✔ sesuai
A80: 74 | B80: Per saham | C80: EPS tercetak vs laba induk / saham rata-rata tertimbang CALK (toleransi Rp1) | D80: 2021 | E80: =IS!D28 -> 0.18 | F80: =ROUND(IS!D24/Schedules!D20,2) -> 0.18 | G80: =IF(COUNT(E80:F80)=2,E80-F80,"") -> 0 | H80: 1 | I80: =IF(COUNT(E80:F80)<2,"N/A",IF(ABS(G80)<=H80,"OK","❌")) -> OK | J80: OK | K80: =IF(I80=J80,"✔ sesuai","✖ TIDAK sesuai") -> ✔ sesuai
A81: 75 | B81: Subtotal rumus vs tercetak | C81: IS: GROSS_PROFIT rumus = tercetak | D81: 2022 | E81: =IS!E8 -> 96232265566 | F81: =IS!E34 -> 96232265566 | G81: =IF(COUNT(E81:F81)=2,E81-F81,"") -> 0 | H81: 1 | I81: =IF(COUNT(E81:F81)<2,"N/A",IF(ABS(G81)<=H81,"OK","❌")) -> OK | J81: OK | K81: =IF(I81=J81,"✔ sesuai","✖ TIDAK sesuai") -> ✔ sesuai
A82: 76 | B82: Subtotal rumus vs tercetak | C82: IS: OPER_PROFIT rumus = tercetak | D82: 2022 | E82: =IS!E10 -> -60591381867 | F82: =IS!E35 -> -60591381867 | G82: =IF(COUNT(E82:F82)=2,E82-F82,"") -> 0 | H82: 1 | I82: =IF(COUNT(E82:F82)<2,"N/A",IF(ABS(G82)<=H82,"OK","❌")) -> OK | J82: OK | K82: =IF(I82=J82,"✔ sesuai","✖ TIDAK sesuai") -> ✔ sesuai
A83: 77 | B83: Subtotal rumus vs tercetak | C83: IS: PBT rumus = tercetak | D83: 2022 | E83: =IS!E15 -> -93315958920 | F83: =IS!E36 -> -93315958920 | G83: =IF(COUNT(E83:F83)=2,E83-F83,"") -> 0 | H83: 1 | I83: =IF(COUNT(E83:F83)<2,"N/A",IF(ABS(G83)<=H83,"OK","❌")) -> OK | J83: OK | K83: =IF(I83=J83,"✔ sesuai","✖ TIDAK sesuai") -> ✔ sesuai
A84: 78 | B84: Subtotal rumus vs tercetak | C84: IS: NET_INCOME rumus = tercetak | D84: 2022 | E84: =IS!E17 -> -93604422306 | F84: =IS!E37 -> -93604422306 | G84: =IF(COUNT(E84:F84)=2,E84-F84,"") -> 0 | H84: 1 | I84: =IF(COUNT(E84:F84)<2,"N/A",IF(ABS(G84)<=H84,"OK","❌")) -> OK | J84: OK | K84: =IF(I84=J84,"✔ sesuai","✖ TIDAK sesuai") -> ✔ sesuai
A85: 79 | B85: Subtotal rumus vs tercetak | C85: IS: OCI_TOTAL rumus = tercetak | D85: 2022 | E85: =IS!E21 -> 2228380991 | F85: =IS!E38 -> 2228380991 | G85: =IF(COUNT(E85:F85)=2,E85-F85,"") -> 0 | H85: 1 | I85: =IF(COUNT(E85:F85)<2,"N/A",IF(ABS(G85)<=H85,"OK","❌")) -> OK | J85: OK | K85: =IF(I85=J85,"✔ sesuai","✖ TIDAK sesuai") -> ✔ sesuai
A86: 80 | B86: Subtotal rumus vs tercetak | C86: IS: TCI rumus = tercetak | D86: 2022 | E86: =IS!E22 -> -91376041315 | F86: =IS!E39 -> -91376041315 | G86: =IF(COUNT(E86:F86)=2,E86-F86,"") -> 0 | H86: 1 | I86: =IF(COUNT(E86:F86)<2,"N/A",IF(ABS(G86)<=H86,"OK","❌")) -> OK | J86: OK | K86: =IF(I86=J86,"✔ sesuai","✖ TIDAK sesuai") -> ✔ sesuai
A87: 81 | B87: Subtotal rumus vs tercetak | C87: BS: TOTAL_CA rumus = tercetak | D87: 2022 | E87: =BS!E15 -> 881622483502 | F87: =BS!E50 -> 881622483502 | G87: =IF(COUNT(E87:F87)=2,E87-F87,"") -> 0 | H87: 1 | I87: =IF(COUNT(E87:F87)<2,"N/A",IF(ABS(G87)<=H87,"OK","❌")) -> OK | J87: OK | K87: =IF(I87=J87,"✔ sesuai","✖ TIDAK sesuai") -> ✔ sesuai
A88: 82 | B88: Subtotal rumus vs tercetak | C88: BS: TOTAL_NCA rumus = tercetak | D88: 2022 | E88: =BS!E20 -> 3352998648910 | F88: =BS!E51 -> 3352998648910 | G88: =IF(COUNT(E88:F88)=2,E88-F88,"") -> 0 | H88: 1 | I88: =IF(COUNT(E88:F88)<2,"N/A",IF(ABS(G88)<=H88,"OK","❌")) -> OK | J88: OK | K88: =IF(I88=J88,"✔ sesuai","✖ TIDAK sesuai") -> ✔ sesuai
A89: 83 | B89: Subtotal rumus vs tercetak | C89: BS: TOTAL_ASSETS rumus = tercetak | D89: 2022 | E89: =BS!E21 -> 4234621132412 | F89: =BS!E52 -> 4234621132412 | G89: =IF(COUNT(E89:F89)=2,E89-F89,"") -> 0 | H89: 1 | I89: =IF(COUNT(E89:F89)<2,"N/A",IF(ABS(G89)<=H89,"OK","❌")) -> OK | J89: OK | K89: =IF(I89=J89,"✔ sesuai","✖ TIDAK sesuai") -> ✔ sesuai
A90: 84 | B90: Subtotal rumus vs tercetak | C90: BS: TOTAL_CL rumus = tercetak | D90: 2022 | E90: =BS!E33 -> 213002320748 | F90: =BS!E53 -> 213002320748 | G90: =IF(COUNT(E90:F90)=2,E90-F90,"") -> 0 | H90: 1 | I90: =IF(COUNT(E90:F90)<2,"N/A",IF(ABS(G90)<=H90,"OK","❌")) -> OK | J90: OK | K90: =IF(I90=J90,"✔ sesuai","✖ TIDAK sesuai") -> ✔ sesuai
A91: 85 | B91: Subtotal rumus vs tercetak | C91: BS: TOTAL_NCL rumus = tercetak | D91: 2022 | E91: =BS!E39 -> 814727009142 | F91: =BS!E54 -> 814727009142 | G91: =IF(COUNT(E91:F91)=2,E91-F91,"") -> 0 | H91: 1 | I91: =IF(COUNT(E91:F91)<2,"N/A",IF(ABS(G91)<=H91,"OK","❌")) -> OK | J91: OK | K91: =IF(I91=J91,"✔ sesuai","✖ TIDAK sesuai") -> ✔ sesuai
A92: 86 | B92: Subtotal rumus vs tercetak | C92: BS: TOTAL_LIAB rumus = tercetak | D92: 2022 | E92: =BS!E40 -> 1027729329890 | F92: =BS!E55 -> 1027729329890 | G92: =IF(COUNT(E92:F92)=2,E92-F92,"") -> 0 | H92: 1 | I92: =IF(COUNT(E92:F92)<2,"N/A",IF(ABS(G92)<=H92,"OK","❌")) -> OK | J92: OK | K92: =IF(I92=J92,"✔ sesuai","✖ TIDAK sesuai") -> ✔ sesuai
A93: 87 | B93: Subtotal rumus vs tercetak | C93: BS: EQUITY_PARENT rumus = tercetak | D93: 2022 | E93: =BS!E45 -> 3205908066461 | F93: =BS!E56 -> 3205908066461 | G93: =IF(COUNT(E93:F93)=2,E93-F93,"") -> 0 | H93: 1 | I93: =IF(COUNT(E93:F93)<2,"N/A",IF(ABS(G93)<=H93,"OK","❌")) -> OK | J93: OK | K93: =IF(I93=J93,"✔ sesuai","✖ TIDAK sesuai") -> ✔ sesuai
A94: 88 | B94: Subtotal rumus vs tercetak | C94: BS: TOTAL_EQUITY rumus = tercetak | D94: 2022 | E94: =BS!E47 -> 3206891802522 | F94: =BS!E57 -> 3206891802522 | G94: =IF(COUNT(E94:F94)=2,E94-F94,"") -> 0 | H94: 1 | I94: =IF(COUNT(E94:F94)<2,"N/A",IF(ABS(G94)<=H94,"OK","❌")) -> OK | J94: OK | K94: =IF(I94=J94,"✔ sesuai","✖ TIDAK sesuai") -> ✔ sesuai
A95: 89 | B95: Subtotal rumus vs tercetak | C95: BS: TOTAL_LIAB_EQUITY rumus = tercetak | D95: 2022 | E95: =BS!E48 -> 4234621132412 | F95: =BS!E58 -> 4234621132412 | G95: =IF(COUNT(E95:F95)=2,E95-F95,"") -> 0 | H95: 1 | I95: =IF(COUNT(E95:F95)<2,"N/A",IF(ABS(G95)<=H95,"OK","❌")) -> OK | J95: OK | K95: =IF(I95=J95,"✔ sesuai","✖ TIDAK sesuai") -> ✔ sesuai
A96: 90 | B96: Subtotal rumus vs tercetak | C96: CF: CASH_GEN rumus = tercetak | D96: 2022 | E96: =CF!E10 -> 159712956 | F96: =CF!E45 -> 0 | G96: =IF(COUNT(E96:F96)=2,E96-F96,"") -> 159712956 | H96: 1 | I96: =IF(COUNT(E96:F96)<2,"N/A",IF(ABS(G96)<=H96,"OK","❌")) -> ❌ | J96: ❌ | K96: =IF(I96=J96,"✔ sesuai","✖ TIDAK sesuai") -> ✔ sesuai | L96: LK FY2022 (dan komparatifnya) tidak mencetak subtotal "kas dihasilkan dari operasi" sebelum bunga/pajak (baru disajikan sejak LK FY2023); sel tercetak kosong, bukan selisih angka. Total arus kas operasi ber-tie.
A97: 91 | B97: Subtotal rumus vs tercetak | C97: CF: CFO rumus = tercetak | D97: 2022 | E97: =CF!E14 -> -48836369112 | F97: =CF!E46 -> -48836369112 | G97: =IF(COUNT(E97:F97)=2,E97-F97,"") -> 0 | H97: 1 | I97: =IF(COUNT(E97:F97)<2,"N/A",IF(ABS(G97)<=H97,"OK","❌")) -> OK | J97: OK | K97: =IF(I97=J97,"✔ sesuai","✖ TIDAK sesuai") -> ✔ sesuai
A98: 92 | B98: Subtotal rumus vs tercetak | C98: CF: CFI rumus = tercetak | D98: 2022 | E98: =CF!E23 -> 39827160327 | F98: =CF!E47 -> 39827160327 | G98: =IF(COUNT(E98:F98)=2,E98-F98,"") -> 0 | H98: 1 | I98: =IF(COUNT(E98:F98)<2,"N/A",IF(ABS(G98)<=H98,"OK","❌")) -> OK | J98: OK | K98: =IF(I98=J98,"✔ sesuai","✖ TIDAK sesuai") -> ✔ sesuai
A99: 93 | B99: Subtotal rumus vs tercetak | C99: CF: CFF rumus = tercetak | D99: 2022 | E99: =CF!E39 -> 249408214 | F99: =CF!E48 -> 249408214 | G99: =IF(COUNT(E99:F99)=2,E99-F99,"") -> 0 | H99: 1 | I99: =IF(COUNT(E99:F99)<2,"N/A",IF(ABS(G99)<=H99,"OK","❌")) -> OK | J99: OK | K99: =IF(I99=J99,"✔ sesuai","✖ TIDAK sesuai") -> ✔ sesuai
A100: 94 | B100: Subtotal rumus vs tercetak | C100: CF: NET_CHANGE rumus = tercetak | D100: 2022 | E100: =CF!E40 -> -8759800571 | F100: =CF!E49 -> -8759800571 | G100: =IF(COUNT(E100:F100)=2,E100-F100,"") -> 0 | H100: 1 | I100: =IF(COUNT(E100:F100)<2,"N/A",IF(ABS(G100)<=H100,"OK","❌")) -> OK | J100: OK | K100: =IF(I100=J100,"✔ sesuai","✖ TIDAK sesuai") -> ✔ sesuai
A101: 95 | B101: Subtotal rumus vs tercetak | C101: CF: CASH_END rumus = tercetak | D101: 2022 | E101: =CF!E43 -> 533208033479 | F101: =CF!E50 -> 533208033479 | G101: =IF(COUNT(E101:F101)=2,E101-F101,"") -> 0 | H101: 1 | I101: =IF(COUNT(E101:F101)<2,"N/A",IF(ABS(G101)<=H101,"OK","❌")) -> OK | J101: OK | K101: =IF(I101=J101,"✔ sesuai","✖ TIDAK sesuai") -> ✔ sesuai
...

Sheet Temuan
A1: Temuan inkonsistensi & catatan forensik (2020-2025)
A2: Nilai statis dari LK (Rp penuh kecuali jumlah saham/token); selisih = rumus.
A4: Kode | B4: Topik | C4: Nilai A | D4: Nilai B | E4: Selisih A-B | F4: Sumber / hal | G4: Penjelasan | H4: Perlakuan di model
A5: C1 | B5: FY2021 dari komparatif LK FY2022, disilang ke LK FY2021 | C5: 80 | D5: 80 | E5: =C5-D5 -> 0 | F5: LK FY2022 (komparatif) vs LK audited FY2021 (situs emiten) | G5: Silang 80 pos 2021 (IS/BS/CF): 80 sama persis. Perbedaan penyajian hanya pemisahan pos (biaya dibayar dimuka & kas dibatasi dipisah dari aset lancar lainnya; pendapatan diterima dimuka dipisah dari beban akrual), total sama. CALK 2021 (Cat 9, 20-25, laba per saham) dari kolom komparatif LK FY2022. | H5: Kolom 2021 dipakai penuh (termasuk CALK); bukan dasar kalibrasi asumsi.
A6: C2 | B6: FY2020 dari komparatif LK FY2021 (ringkasan XBRL IDX terblokir) | F6: LK konsolidasian audited PT Metro Healthcare Indonesia Tbk 31 Des 2021 (EY, opini 12 Agu 2022), kolom 31 Des 2020; https://www.metrohealthcareindonesia.co.id/download_file/3f9244443f8a1ff58ce147598c85bfffa2a8bde5 | G6: Tidak ada penyajian kembali 2020. Silang: (1) aritmetika internal semua subtotal = 0; (2) LPE 2019->2020 (modal, agio, defisit, NCI) ber-tie; (3) kas awal 2021 di LK FY2022 = kas akhir 2020; (4) pendapatan Rp216,29 M sesuai pemberitaan. Ringkasan XBRL IDX tidak dapat diunduh (403). 2020: aset lancar lainnya 1.989.727.315 tidak dipisah (LK FY2021 menggabung biaya dibayar dimuka & kas dibatasi); beban akrual termasuk pendapatan diterima dimuka. Komparatif 2020 diaudit auditor lain (laporan 28 Mei 2021). | H6: Schedules FY2020 kosong; rasio berbasis CALK 2020 = N/A. URL IDX yang perlu diunduh manual bila ingin silang XBRL: idx.co.id > Laporan Keuangan & Tahunan > CARE > 2020 & 2021 Tahunan (FinancialStatement-2020/2021-Tahunan-CARE).
A7: C3 | B7: EPS & jumlah saham | C7: 0.51 | D7: 0.43 | E7: =C7-D7 -> 0.08 | F7: LK FY2021 (EPS 2020); CALK laba per saham FY2022-25 | G7: Saham ditempatkan 33.250.000.000 (Rp100) sejak IPO Maret 2020; rata-rata tertimbang 2021-2025 = 2021 33,250,000,000, 2022 33,250,000,000, 2023 33,250,000,000, 2024 33,250,000,000, 2025 33,250,000,000. EPS 2020 tercetak Rp0,51 memakai rata-rata tertimbang (lebih sedikit saham sebelum IPO), sedangkan laba induk / saham akhir tahun = Rp0,43; selisih < Rp1. | H7: EPS tercetak dipakai apa adanya; proyeksi memakai 33.250.000.000 saham.
A8: C4 | B8: Penyajian kembali 2022: pendapatan bruto vs neto diskon | C8: 233970724609 | D8: 260426191178 | E8: =C8-D8 -> -26455466569 | F8: LK FY2022 hal 7 vs LK FY2023 hal 7 & 9 | G8: CARE: LK FY2023 menyajikan pendapatan 2022 secara bruto (diskon 26.455.466.569 dipindah dari pengurang pendapatan ke beban pokok "biaya selisih tarif klaim"); laba bruto tidak berubah. Beda kecil arus kas investasi 2022 (divestasi 225,8 jt vs 227,0 jt; uang muka aset tetap) saling hapus. 2021: LK FY2022 memisah biaya dibayar dimuka & kas dibatasi (LK FY2021: aset lancar lainnya) dan pendapatan diterima dimuka (LK FY2021: dalam beban akrual) - total sama. Model memakai angka LK tahun berjalan (asli). CF 2022 ikut disajikan kembali (penerimaan pelanggan & pembayaran pemasok +/- 26,5 M; total CFO tetap). Diskon 2021 (-34,8 M) juga mengurangi pendapatan. Model memakai angka asli LK tahun berjalan (2021-2022 neto diskon, 2023+ bruto), sehingga pertumbuhan pendapatan 2022->2023 dan margin bruto tidak sebanding penuh. CALK: untuk tiap catatan & tahun hanya LK tahun itu sendiri yang dipakai; 21 set komparatif dari LK lebih baru dibuang: Cat 20 2022 (LK FY2023), Cat 20 2023 (LK FY2024), Cat 20 2024 (LK FY2025), Cat 21 2022 (LK FY2023), Cat 21 2023 (LK FY2024), Cat 21 2024 (LK FY2025), Cat 22 2022 (LK FY2023), Cat 22 2023 (LK FY2024), Cat 22 2024 (LK FY2025), Cat 23 2022 (LK FY2023), Cat 23 2023 (LK FY2024), Cat 23 2024 (LK FY2025). | H8: OVERRIDES kosong (angka asli). Baris REV.DISC memisahkan diskon; laba bruto tidak terpengaruh.
A9: C5 | B9: Pendapatan 2025 memuat pendapatan investasi | C9: 97800000000 | D9: 439751605228 | E9: =C9-D9 -> -341951605228 | F9: CALK Cat 20 LK FY2025 | G9: Cat 20 FY2025 menambahkan kelompok "Lainnya" 97,8 M (pendapatan investasi) di dalam pendapatan, sehingga pendapatan naik ke 439,8 M dan laba bruto/laba usaha 2025 positif. Tanpa pos ini pendapatan rumah sakit (rawat inap + rawat jalan) = 342,0 M. | H9: Proyeksi: pos "Lainnya" = 0 (diasumsikan tidak berulang); pertumbuhan hanya dari rawat inap & rawat jalan.
A10: C6 | B10: Utang berbunga besar vs EBITDA | C10: 1083635029572 | D10: 96341923590 | E10: =C10-D10 -> 987293105982 | F10: Neraca & laba rugi FY2025 | G10: Utang berbunga 2025 (bank, lembaga keuangan, wesel/sukuk) 1.083,6 M; beban keuangan 80,4 M; EBITDA 96,3 M (termasuk pendapatan investasi C5). Kas + investasi jk pendek: 2020 725,5 M, 2021 1.192,4 M, 2022 853,2 M, 2023 754,8 M, 2024 492,1 M, 2025 470,7 M. Beban bunga melebihi EBITDA dari operasi rumah sakit; laba 2025 tipis dan bergantung pada pos tidak berulang. | H10: Beban keuangan E = suku bunga efektif x rata-rata utang; utang konstan.
A11: C7 | B11: Kas proyeksi bisa negatif | F11: BS_Proj / CF_Proj | G11: Dengan asumsi Base, rugi sebelum pajak berulang (beban bunga > EBITDA) dan capex menguras kas; kas proyeksi dapat menjadi negatif di tahun-tahun akhir. Model tidak menambah utang secara otomatis (debt_chg = 0). | H11: Cek "Kas proyeksi tidak negatif" berstatus INFO; kas negatif dibaca sebagai kebutuhan pendanaan, bukan kesalahan model.
A12: C8 | B12: Uji ekstraksi ganda & silang komparatif | C12: 935 | D12: 10 | E12: =C12-D12 -> 925 | F12: Ekstraksi A (pdftotext/OCR) vs B (OCR independen 400dpi), LK FY2022-25 | G12: Ekstraksi A: pdftotext-layout (hal. teks) / OCR 300dpi psm6 (hal. gambar), direkonsiliasi (abcM). Ekstraksi B independen: OCR tesseract 400dpi grayscale psm4 untuk SEMUA halaman laporan (4-9). pdfplumber/markitdown gagal membaca text layer (encoding font) -> tidak dipakai. Hasil: 935 nilai sama, 10 berbeda (semua salah baca OCR di B, misal digit 7 ganda; nilai A terbukti oleh aritmetika subtotal & komparatif tahun berikut), 165 tidak terbaca di B (ditelusuri lewat aritmetika). | H12: Lihat Rekonsiliasi (cek silang & ekstraksi).
A13: C9 | B13: Kas entitas anak yang diakuisisi/dilepas | C13: 2653244177 | D13: -432641188 | E13: =C13-D13 -> 3085885365 | F13: LAK LK FY2022-FY2023 | G13: Kas akhir = kenaikan neto + kas awal + kas entitas anak yang diakuisisi (2021) / dilepas (2022); dimuat sebagai baris CF.SUBS_CASH. | H13: Tidak diproyeksikan.

Sheet Database
A1: Database format panjang FY2020-FY2025 (untuk digabung antar emiten)
A2: Nilai statis sesuai sumber, Rp penuh. Kolom basis: komparatif / dilaporkan.
A4: emiten | B4: kode_emiten | C4: periode | D4: laporan | E4: kode_akun | F4: akun | G4: nilai | H4: satuan | I4: catatan | J4: halaman | K4: sumber | L4: basis | M4: keterangan
A5: PT Metro Healthcare Indonesia Tbk | B5: CARE | C5: FY2020 | D5: IS | E5: IS.REVENUE | F5: Pendapatan neto (Cat 20) | G5: 216296095571 | H5: Rp | J5: LK FY2021 audited (komparatif 2020) - laporan laba rugi | K5: LK FY2021 audited (komparatif 2020) | L5: komparatif
A6: PT Metro Healthcare Indonesia Tbk | B6: CARE | C6: FY2021 | D6: IS | E6: IS.REVENUE | F6: Pendapatan neto (Cat 20) | G6: 290934356126 | H6: Rp | J6: LK FY2022 hal 7 | K6: LK FY2022 (komparatif), disilang ke LK FY2021 | L6: komparatif
A7: PT Metro Healthcare Indonesia Tbk | B7: CARE | C7: FY2022 | D7: IS | E7: IS.REVENUE | F7: Pendapatan neto (Cat 20) | G7: 233970724609 | H7: Rp | J7: LK FY2022 hal 7 | K7: LK FY2022 | L7: dilaporkan
A8: PT Metro Healthcare Indonesia Tbk | B8: CARE | C8: FY2023 | D8: IS | E8: IS.REVENUE | F8: Pendapatan neto (Cat 20) | G8: 242680799183 | H8: Rp | J8: LK FY2023 hal 7 | K8: LK FY2023 | L8: dilaporkan
A9: PT Metro Healthcare Indonesia Tbk | B9: CARE | C9: FY2024 | D9: IS | E9: IS.REVENUE | F9: Pendapatan neto (Cat 20) | G9: 319022410802 | H9: Rp | J9: LK FY2024 hal 7 | K9: LK FY2024 | L9: dilaporkan
A10: PT Metro Healthcare Indonesia Tbk | B10: CARE | C10: FY2025 | D10: IS | E10: IS.REVENUE | F10: Pendapatan neto (Cat 20) | G10: 439751605228 | H10: Rp | J10: LK FY2025 hal 7 | K10: LK FY2025 | L10: dilaporkan
A11: PT Metro Healthcare Indonesia Tbk | B11: CARE | C11: FY2020 | D11: IS | E11: IS.COGS | F11: Beban pokok pendapatan (Cat 21) | G11: -113404642135 | H11: Rp | J11: LK FY2021 audited (komparatif 2020) - laporan laba rugi | K11: LK FY2021 audited (komparatif 2020) | L11: komparatif
A12: PT Metro Healthcare Indonesia Tbk | B12: CARE | C12: FY2021 | D12: IS | E12: IS.COGS | F12: Beban pokok pendapatan (Cat 21) | G12: -145000436678 | H12: Rp | J12: LK FY2022 hal 7 | K12: LK FY2022 (komparatif), disilang ke LK FY2021 | L12: komparatif
A13: PT Metro Healthcare Indonesia Tbk | B13: CARE | C13: FY2022 | D13: IS | E13: IS.COGS | F13: Beban pokok pendapatan (Cat 21) | G13: -137738459043 | H13: Rp | J13: LK FY2022 hal 7 | K13: LK FY2022 | L13: dilaporkan
A14: PT Metro Healthcare Indonesia Tbk | B14: CARE | C14: FY2023 | D14: IS | E14: IS.COGS | F14: Beban pokok pendapatan (Cat 21) | G14: -153026530241 | H14: Rp | J14: LK FY2023 hal 7 | K14: LK FY2023 | L14: dilaporkan
A15: PT Metro Healthcare Indonesia Tbk | B15: CARE | C15: FY2024 | D15: IS | E15: IS.COGS | F15: Beban pokok pendapatan (Cat 21) | G15: -214434696643 | H15: Rp | J15: LK FY2024 hal 7 | K15: LK FY2024 | L15: dilaporkan
A16: PT Metro Healthcare Indonesia Tbk | B16: CARE | C16: FY2025 | D16: IS | E16: IS.COGS | F16: Beban pokok pendapatan (Cat 21) | G16: -224594016289 | H16: Rp | J16: LK FY2025 hal 7 | K16: LK FY2025 | L16: dilaporkan
A17: PT Metro Healthcare Indonesia Tbk | B17: CARE | C17: FY2020 | D17: IS | E17: IS.GROSS_PROFIT | F17: Laba bruto | G17: 102891453436 | H17: Rp | K17: LK FY2021 audited (komparatif 2020) | L17: komparatif | M17: subtotal dihitung
A18: PT Metro Healthcare Indonesia Tbk | B18: CARE | C18: FY2021 | D18: IS | E18: IS.GROSS_PROFIT | F18: Laba bruto | G18: 145933919448 | H18: Rp | K18: LK FY2022 (komparatif), disilang ke LK FY2021 | L18: komparatif | M18: subtotal dihitung
A19: PT Metro Healthcare Indonesia Tbk | B19: CARE | C19: FY2022 | D19: IS | E19: IS.GROSS_PROFIT | F19: Laba bruto | G19: 96232265566 | H19: Rp | K19: LK FY2022 | L19: dilaporkan | M19: subtotal dihitung
A20: PT Metro Healthcare Indonesia Tbk | B20: CARE | C20: FY2023 | D20: IS | E20: IS.GROSS_PROFIT | F20: Laba bruto | G20: 89654268942 | H20: Rp | K20: LK FY2023 | L20: dilaporkan | M20: subtotal dihitung
A21: PT Metro Healthcare Indonesia Tbk | B21: CARE | C21: FY2024 | D21: IS | E21: IS.GROSS_PROFIT | F21: Laba bruto | G21: 104587714159 | H21: Rp | K21: LK FY2024 | L21: dilaporkan | M21: subtotal dihitung
