Workbook

Sheet Cover
B2: PT Cipta Sarana Medika Tbk (DKHH) - Model data fundamental 6 tahun & proyeksi ilustratif
B3: Historis FY2022-FY2025 (laporan keuangan konsolidasian audited) | proyeksi ilustratif FY2026-FY2030 | Format: PRO
B5: Penting - sifat dokumen
B6: Bukan rekomendasi | C6: Dokumen ini hanya ringkasan informasi dan analisis data fundamental yang bersumber dari laporan keuangan publik (audited) PT Cipta Sarana Medika Tbk. Dokumen ini BUKAN saran atau rekomendasi investasi, bukan ajakan membeli, menjual, atau menahan efek apa pun, dan tidak memuat target atau penilaian nilai wajar. Proyeksi bersifat ilustratif dan dapat berbeda jauh dari realisasi. Data dapat mengandung kesalahan ekstraksi; selalu cek ke laporan asli. Dokumen ini disusun dengan bantuan kecerdasan buatan (AI) dari laporan keuangan publik; kemungkinan kesalahan tetap ada, harap verifikasi ke sumber.
B7: Proyeksi | C7: Angka FY..E adalah proyeksi ILUSTRATIF berbasis asumsi transparan di sheet Asumsi (Base/Bull/Bear), dikalibrasi dari tren FY2022-2025. Tidak ada target, nilai wajar, atau kesimpulan nilai per saham.
B8: Sumber data | C8: Laporan keuangan konsolidasian audited PT Cipta Sarana Medika Tbk FY2025 (komparatif 2024; diunduh dari IDX; auditor KAP Jonnardi, Jamaludin, Sukimto & Rekan) dan Prospektus IPO 2025 (LK konsolidasian audited 2023 & 2022, auditor KAP Jamaludin, Ardi, Sukimto & Rekan; diunduh dari situs emiten karena salinan IDX ditolak/403). Tahun 2021 tidak disajikan (belum konsolidasi); laporan interim 10 bulan prospektus tidak dipakai. Lihat Data_Log & Temuan.
B10: Hak cipta & lisensi
B11: Hak cipta | C11: © 2026 Ryant Gabein Pasaribu. Kompilasi, struktur, metodologi, kode akun standar, dan analisis dalam file ini adalah ciptaan Ryant Gabein Pasaribu. Dilisensikan di bawah Creative Commons Atribusi 4.0 Internasional (CC BY 4.0): bebas digunakan dan dibagikan dengan wajib mencantumkan atribusi "Ryant Gabein Pasaribu" dan menyertakan tautan lisensi https://creativecommons.org/licenses/by/4.0/deed.id. Data laporan keuangan bersumber dari laporan publik emiten.
B12: Versi | C12: v1.0
B13: Tanggal terbit | C13: 2026-10-25
B14: ID file | C14: DKHH-FY2025-v1.0-36F09546
B16: Format
B17: Data terbuka | C17: Data dan model ini terbuka dan gratis untuk semua orang.
B18: Format output | C18: Tiga format (bukan tingkatan akses, semuanya gratis): Ritel (PDF ringkasan 4 halaman), Akademik (Excel data historis, rasio, rekonsiliasi), Pro (Excel model penuh dengan proyeksi ilustratif & template DCF kosong).
B20: Informasi model
B21: Emiten | C21: PT Cipta Sarana Medika Tbk dan Entitas Anak (kode DKHH) - pengelola rumah sakit tipe C "DKH Hospitals" (Kedungwaringin & Sukatani, Bekasi; Cibadak, Sukabumi)
B22: Satuan | C22: Rupiah penuh (Ringkasan/Dashboard: Rp miliar); beban & arus kas keluar negatif (kurung)
B23: Tahun historis | C23: FY2022, FY2023, FY2024, FY2025
B24: Status rekonsiliasi | C24: =Rekonsiliasi!$C$3 -> SEMUA 225 CEK SESUAI EKSPEKTASI
B25: Skenario aktif | C25: =Asumsi!C4 -> Base
B26: Dibangun | C26: 25-10-2026 oleh /workspace/emiten/common/build_model.py --ticker DKHH
B28: Daftar sheet
B29: Cover | C29: Sifat dokumen, lisensi, keterangan warna
B30: Panduan | C30: Cara memakai model ini
B31: Ringkasan | C31: Ringkasan siap cetak/PDF (A4): highlights, indikator utama, grafik, tanda perhatian
B32: Dashboard | C32: Indikator & grafik historis + proyeksi ilustratif
B33: Asumsi | C33: Selektor skenario Base/Bull/Bear & driver per tahun, dengan dasar kalibrasi FY2023-2025
B34: IS_Proj | C34: Proyeksi laba rugi (pendapatan per kelompok, EBITDA, laba)
B35: BS_Proj | C35: Proyeksi neraca agregat; kas = penyeimbang; cek balance
B36: CF_Proj | C36: Proyeksi arus kas tidak langsung; FCF
B37: Schedules_Proj | C37: Aset tetap, aset takberwujud, sewa, utang, modal kerja
B38: DCF_Template | C38: Kalkulator DCF opsional dengan input KOSONG (tanpa kesimpulan)
B39: Peer | C39: Tabel pembanding fundamental (input kosong, tanpa kelipatan pasar)
B40: IS | C40: Laba rugi & OCI FY2022-2025
... B48: Data_Log | C48: Sumber per tahun, pemetaan akun, override

Sheet Panduan
A1: Panduan pemakaian
A2: Format PRO (model penuh) - gratis & terbuka; bukan rekomendasi investasi
B4: Langkah
B5: 1. Mulai | C5: Baca Cover (sifat dokumen) lalu Ringkasan (siap cetak A4: File > Print/Export PDF untuk sheet Ringkasan).
B6: 2. Data historis | C6: IS, BS, CF berisi angka laporan (biru) dan subtotal rumus (hitam). Baris 3 menyebut sumber tiap kolom; kolom FY2022 berlatar oranye = kolom pertama, dari LK audited dalam prospektus IPO (Temuan D8).
B7: 3. Rincian & rasio | C7: Schedules memuat rincian catatan (CALK) FY2022-2025; bagian A merangkum angka yang dipakai Rasio. Rasio memakai rumus hidup dan kolom rata-rata FY2022-25.
B8: 4. Cek kualitas | C8: Rekonsiliasi: kolom "Sesuai ekspektasi?" harus ✔ untuk semua baris. ❌ yang diharapkan adalah selisih di laporan sumber dan dijelaskan di kolom Penjelasan / sheet Temuan.
B9: 5. Proyeksi ilustratif | C9: Pilih skenario di Asumsi!C4 (Base/Bull/Bear). Ubah sel biru di blok skenario untuk mencoba asumsi sendiri; IS_Proj, BS_Proj, CF_Proj ikut berubah. Cek BS_Proj baris "Cek" harus 0.
B10: 6. Template DCF (opsional) | C10: Isi sendiri sel kuning (Rf, ERP, beta, Kd, pajak, bobot utang, g / kelipatan). Tanpa input, template tidak menghitung apa pun. Hasil adalah keluaran rumus atas input Anda, bukan nilai wajar atau rekomendasi.
B11: 7. Peer | C11: Isi data fundamental pembanding dari laporan publik masing-masing emiten beserta sumbernya. Tidak ada angka pembanding yang dikarang di file ini.
B13: Keterangan warna
B14: Biru | C14: Input / angka dari laporan (bisa diubah)
B15: Hitam | C15: Rumus di sheet yang sama
B16: Hijau | C16: Rumus yang merujuk sheet lain
B17: Kuning | C17: Sel yang perlu diisi/diverifikasi pengguna atau angka yang dikoreksi (ada komentar sel)
B18: Oranye | C18: Kolom FY2022 (kolom pertama) dari LK audited dalam prospektus IPO
B19: Biru muda | C19: Kolom tahun proyeksi (E) - ilustratif
B21: Definisi penting
B22: EBITDA | C22: Laba usaha model (laba bruto - beban usaha + pendapatan lain-lain neto) + penyusutan aset tetap (Cat 26-27) + penyusutan aset hak guna (Cat 26).
B23: Utang | C23: Utang berbunga: utang bank jangka pendek & jangka panjang, pembiayaan konsumen, dan dana syirkah temporer (Temuan D2). Utang neto juga menambahkan liabilitas sewa dan mengurangi kas (negatif = kas neto).
B24: EPS | C24: EPS tercetak memakai saham rata-rata tertimbang (CALK; IPO 2025) dan dibulatkan ke Rupiah penuh 2024-2025 (Temuan D9).
B25: Satuan | C25: Rupiah penuh kecuali disebut (Ringkasan/Dashboard: Rp miliar). Beban & arus kas keluar bertanda negatif.
B27: Daftar sheet (format ini)
B28: Cover | C28: Sifat dokumen, lisensi, keterangan warna
B29: Panduan | C29: Cara memakai model ini
B30: Ringkasan | C30: Ringkasan siap cetak/PDF (A4): highlights, indikator utama, grafik, tanda perhatian
B31: Dashboard | C31: Indikator & grafik historis + proyeksi ilustratif
B32: Asumsi | C32: Selektor skenario Base/Bull/Bear & driver per tahun, dengan dasar kalibrasi FY2023-2025
B33: IS_Proj | C33: Proyeksi laba rugi (pendapatan per kelompok, EBITDA, laba)
B34: BS_Proj | C34: Proyeksi neraca agregat; kas = penyeimbang; cek balance
B35: CF_Proj | C35: Proyeksi arus kas tidak langsung; FCF
B36: Schedules_Proj | C36: Aset tetap, aset takberwujud, sewa, utang, modal kerja
B37: DCF_Template | C37: Kalkulator DCF opsional dengan input KOSONG (tanpa kesimpulan)
B38: Peer | C38: Tabel pembanding fundamental (input kosong, tanpa kelipatan pasar)
B39: IS | C39: Laba rugi & OCI FY2022-2025
... B47: Data_Log | C47: Sumber per tahun, pemetaan akun, override
B49: Batasan
B50: Data | C50: Angka diekstrak dari PDF dan dapat mengandung kesalahan; cek ke laporan asli sebelum dipakai.
B51: Proyeksi | C51: Asumsi sederhana: pos neraca lain konstan, utang & liabilitas sewa konstan (pembayaran sewa dikapitalisasi ke aset tetap), beban keuangan = suku bunga x rata-rata utang, aset hak guna konstan, tanpa OCI/revaluasi/penurunan nilai baru, tanpa penghasilan bunga pihak berelasi, tanpa transaksi saham, akuisisi atau pendanaan baru. Hasil sangat sensitif terhadap asumsi.
B52: Bukan saran | C52: Dokumen ini hanya ringkasan informasi dan analisis data fundamental yang bersumber dari laporan keuangan publik (audited) PT Cipta Sarana Medika Tbk. Dokumen ini BUKAN saran atau rekomendasi investasi, bukan ajakan membeli, menjual, atau menahan efek apa pun, dan tidak memuat target atau penilaian nilai wajar. Proyeksi bersifat ilustratif dan dapat berbeda jauh dari realisasi. Data dapat mengandung kesalahan ekstraksi; selalu cek ke laporan asli. Dokumen ini disusun dengan bantuan kecerdasan buatan (AI) dari laporan keuangan publik; kemungkinan kesalahan tetap ada, harap verifikasi ke sumber.

Sheet Ringkasan
B1: Cipta Sarana Medika (DKHH) | Ringkasan FY2022-FY2025
B2: DKH Hospitals - 3 rumah sakit tipe C di Bekasi & Sukabumi | sumber: LK audited FY2025 & prospektus IPO 2025 | gratis & terbuka | BUKAN rekomendasi investasi
B4: Penting: Dokumen ini hanya ringkasan informasi dan analisis data fundamental yang bersumber dari laporan keuangan publik (audited) PT Cipta Sarana Medika Tbk. Dokumen ini BUKAN saran atau rekomendasi investasi, bukan ajakan membeli, menjual, atau menahan efek apa pun, dan tidak memuat target atau penilaian nilai wajar. Proyeksi bersifat ilustratif dan dapat berbeda jauh dari realisasi. Data dapat mengandung kesalahan ekstraksi; selalu cek ke laporan asli. Dokumen ini disusun dengan bantuan kecerdasan buatan (AI) dari laporan keuangan publik; kemungkinan kesalahan tetap ada, harap verifikasi ke sumber.
B6: Ringkasan Eksekutif / Highlights
B7: • Pendapatan FY2025 Rp144,9 miliar (-4,8% vs FY2024): penunjang medis Rp30,6 miliar, rawat inap Rp74,1 miliar, rawat jalan Rp40,0 miliar, lainnya Rp0,2 miliar.
B8: • Pendapatan tumbuh 13,3% per tahun FY2022-2025 (naik 2023-2024, turun 2025); IPO 2025 dan pelaksanaan waran menghimpun Rp69,2 miliar.
B9: • Laba pemilik induk FY2025 Rp6,0 miliar (EPS tercetak Rp3) vs Rp2,8 miliar FY2024; margin laba bersih 4,2%. Laba 2025 ditopang penghasilan bunga dari pihak berelasi Rp13,2 miliar; laba sebelum pajak 2024 hampir nol.
B10: • Utang berbunga Rp90 miliar (termasuk dana syirkah Rp69 miliar) vs kas Rp4,0 miliar (FY2025); piutang pihak berelasi tidak lancar Rp117 miliar; utang neto / EBITDA 5,7x.
B11: • Data 4 tahun direkonsiliasi dengan 225 cek; 11 selisih di laporan sumber sudah diperkirakan dan dijelaskan (lihat tanda perhatian & sheet Temuan).
B13: Indikator utama (Rp miliar, kecuali disebut lain) - rumus hidup dari sheet IS/BS/CF/Rasio
B14: Indikator | C14: FY2022A | D14: FY2023A | E14: FY2024A | F14: FY2025A
B15: Pendapatan | C15: =IS!C6/1000000000 -> 99.578144 | D15: =IS!D6/1000000000 -> 134.18768 | E15: =IS!E6/1000000000 -> 152.14225 | F15: =IS!F6/1000000000 -> 144.87327
B16: Pertumbuhan | D16: =Rasio!D6 -> 0.34756155 | E16: =Rasio!E6 -> 0.13380193 | F16: =Rasio!F6 -> -0.047777527
B17: Porsi penunjang medis | C17: =Rasio!C26 -> 0.025457106 | D17: =Rasio!D26 -> 0.08856077 | E17: =Rasio!E26 -> 0.30323344 | F17: =Rasio!F26 -> 0.21122146
B18: EBITDA | C18: =Rasio!C16/1000000000 -> 15.15056 | D18: =Rasio!D16/1000000000 -> 17.504402 | E18: =Rasio!E16/1000000000 -> 21.381139 | F18: =Rasio!F16/1000000000 -> 15.3438
B19: Margin EBITDA | C19: =Rasio!C17 -> 0.15214744 | D19: =Rasio!D17 -> 0.13044716 | E19: =Rasio!E17 -> 0.14053387 | F19: =Rasio!F17 -> 0.10591188
B20: Laba tahun berjalan | C20: =IS!C20/1000000000 -> 4.8881658 | D20: =IS!D20/1000000000 -> 3.5397164 | E20: =IS!E20/1000000000 -> 2.8373633 | F20: =IS!F20/1000000000 -> 6.0218975
B21: Laba pemilik entitas induk | C21: =IS!C29/1000000000 -> 4.8881658 | D21: =IS!D29/1000000000 -> 3.5397164 | E21: =IS!E29/1000000000 -> 2.8372318 | F21: =IS!F29/1000000000 -> 6.0216481
B22: Porsi laba ke NCI | C22: =Rasio!C23 -> 0 | D22: =Rasio!D23 -> 0 | E22: =Rasio!E23 -> 4.6327871e-05 | F22: =Rasio!F23 -> 4.1416181e-05
B23: ROE (rata-rata ekuitas induk) | D23: =Rasio!D20 -> 0.039282225 | E23: =Rasio!E20 -> 0.02191938 | F23: =Rasio!F20 -> 0.035818841
B24: Arus kas operasi | C24: =CF!C14/1000000000 -> 7.7341001 | D24: =CF!D14/1000000000 -> 19.735705 | E24: =CF!E14/1000000000 -> 2.9976875 | F24: =CF!F14/1000000000 -> 5.5679514
B25: Capex | C25: =Rasio!C41/1000000000 -> 16.981554 | D25: =Rasio!D41/1000000000 -> 36.146492 | E25: =Rasio!E41/1000000000 -> 24.447662 | F25: =Rasio!F41/1000000000 -> 27.390828
B26: Utang neto (utang + sewa - kas) | C26: =Rasio!C36/1000000000 -> 64.124135 | D26: =Rasio!D36/1000000000 -> 142.65161 | E26: =Rasio!E36/1000000000 -> 111.51054 | F26: =Rasio!F36/1000000000 -> 87.265075
B27: Utang neto / EBITDA (x) | C27: =Rasio!C38 -> 4.2324598 | D27: =Rasio!D38 -> 8.1494706 | E27: =Rasio!E38 -> 5.2153695 | F27: =Rasio!F38 -> 5.6873182
B28: DSO piutang (hari) | C28: =Rasio!C28 -> 44.41957 | D28: =Rasio!D28 -> 45.652804 | E28: =Rasio!E28 -> 60.158756 | F28: =Rasio!F28 -> 47.54806
B29: Tarif pajak efektif | C29: =Rasio!C22 -> 0.25801251 | D29: =Rasio!D22 -> 0.76735139 | E29: =Rasio!E22 -> 6.9116652 | F29: =Rasio!F22 -> -0.058527227
B30: Catatan: kolom FY2022-FY2023 dari LK audited dalam prospektus IPO (proforma restrukturisasi); FY2024 dari komparatif LK FY2025. Laba usaha model = laba usaha tercetak + pendapatan lain-lain neto. EBITDA = laba usaha model + penyusutan aset tetap + penyusutan aset hak guna. Utang = bank + pembiayaan konsumen + dana syirkah temporer.
B32: Tren 4 tahun
B50: Batang = pendapatan per kelompok (Cat 25; lainnya = administrasi & lainnya); garis putus-putus = porsi penunjang medis terhadap pendapatan (sumbu kanan).
B68: Kiri: margin terhadap pendapatan. Kanan: arus kas operasi (abu-abu), capex (arsir), pembayaran sewa (titik), dan sisanya (garis).
B86: Tanda perhatian dari laporan keuangan (bahasa sederhana)
B87: 1. Pihak berelasi - Piutang ke pihak berelasi besar (2025 sekitar sepertiga aset) dan penghasilan bunga 2025 berasal dari pinjaman ke pihak berelasi yang sebagian belum diterima kas. (Temuan D3)
B88: 2. Utang & syirkah - Pembiayaan bank syariah (dana syirkah temporer) diperlakukan sebagai utang; kas akhir tahun kecil dibanding utang. (Temuan D2)
B89: 3. Laba tipis & pajak - Laba sebelum pajak 2024 hampir nol dan 2025 bergantung pada bunga pihak berelasi; tarif pajak efektif ekstrem. (Temuan D3, D11)
B90: 4. Proforma & sumber - Data 2022-2024 memuat laba/ekuitas proforma restrukturisasi; 2022-2023 dari prospektus; LAK prospektus tidak sama dengan kas neraca. (Temuan D1, D6, D8)
B91: 5. Pos tidak berulang - Revaluasi aset 2023, uang muka aset tetap 2025 dan bunga neto positif di arus kas operasi 2025. (Temuan D4, D5, D7)
B92: 6. Proyeksi ilustratif - Skenario Base/Bull/Bear bukan perkiraan; tidak ada target harga atau nilai wajar.
B93: Detail lengkap ada di sheet Temuan dan Rekonsiliasi. Tanda perhatian bukan tuduhan kecurangan; ini daftar hal yang perlu dicek ulang ke laporan asli.
... B103: Dokumen ini hanya ringkasan informasi dan analisis data fundamental yang bersumber dari laporan keuangan publik (audited) PT Cipta Sarana Medika Tbk. Dokumen ini BUKAN saran atau rekomendasi investasi, bukan ajakan membeli, menjual, atau menahan efek apa pun, dan tidak memuat target atau penilaian nilai wajar. Proyeksi bersifat ilustratif dan dapat berbeda jauh dari realisasi. Data dapat mengandung kesalahan ekstraksi; selalu cek ke laporan asli. Dokumen ini disusun dengan bantuan kecerdasan buatan (AI) dari laporan keuangan publik; kemungkinan kesalahan tetap ada, harap verifikasi ke sumber. Penyusun tidak bertanggung jawab atas keputusan apa pun yang diambil berdasarkan dokumen ini. Dokumen ini disusun pada 25-10-2026.

Sheet Dashboard
A1: Dashboard - historis FY2022-FY2025 & proyeksi ilustratif FY2026-FY2030 (skenario aktif)
A2: Rp miliar. Kolom E = Proyeksi ILUSTRATIF berbasis asumsi transparan - bukan rekomendasi investasi, bukan target, bukan nilai wajar. Tidak ada nilai per saham/target di sheet ini.
B3: Skenario aktif: | C3: =Asumsi!C4 -> Base
B4: Indikator | C4: FY2022A | D4: FY2023A | E4: FY2024A | F4: FY2025A | G4: FY2026E | H4: FY2027E | I4: FY2028E | J4: FY2029E | K4: FY2030E | L4: Catatan
B5: Pendapatan neto | C5: =IS_Proj!C10/1000000000 -> 99.578144 | D5: =IS_Proj!D10/1000000000 -> 134.18768 | E5: =IS_Proj!E10/1000000000 -> 152.14225 | F5: =IS_Proj!F10/1000000000 -> 144.87327 | G5: =IS_Proj!G10/1000000000 -> 156.40596 | H5: =IS_Proj!H10/1000000000 -> 168.91843 | I5: =IS_Proj!I10/1000000000 -> 182.43191 | J5: =IS_Proj!J10/1000000000 -> 197.02646 | K5: =IS_Proj!K10/1000000000 -> 212.78858
B6: Pertumbuhan pendapatan | D6: =IS_Proj!D11 -> 0.34756155 | E6: =IS_Proj!E11 -> 0.13380193 | F6: =IS_Proj!F11 -> -0.047777527 | G6: =IS_Proj!G11 -> 0.079605361 | H6: =IS_Proj!H11 -> 0.08 | I6: =IS_Proj!I11 -> 0.08 | J6: =IS_Proj!J11 -> 0.08 | K6: =IS_Proj!K11 -> 0.08
B7: EBITDA | C7: =IS_Proj!C17/1000000000 -> 15.15056 | D7: =IS_Proj!D17/1000000000 -> 17.504402 | E7: =IS_Proj!E17/1000000000 -> 21.381139 | F7: =IS_Proj!F17/1000000000 -> 15.3438 | G7: =IS_Proj!G17/1000000000 -> 20.645586 | H7: =IS_Proj!H17/1000000000 -> 22.297233 | I7: =IS_Proj!I17/1000000000 -> 24.081012 | J7: =IS_Proj!J17/1000000000 -> 26.007493 | K7: =IS_Proj!K17/1000000000 -> 28.088092
B8: Margin EBITDA | C8: =IS_Proj!C31 -> 0.15214744 | D8: =IS_Proj!D31 -> 0.13044716 | E8: =IS_Proj!E31 -> 0.14053387 | F8: =IS_Proj!F31 -> 0.10591188 | G8: =IS_Proj!G31 -> 0.132 | H8: =IS_Proj!H31 -> 0.132 | I8: =IS_Proj!I31 -> 0.132 | J8: =IS_Proj!J31 -> 0.132 | K8: =IS_Proj!K31 -> 0.132
B9: Laba tahun berjalan | C9: =IS_Proj!C25/1000000000 -> 4.8881658 | D9: =IS_Proj!D25/1000000000 -> 3.5397164 | E9: =IS_Proj!E25/1000000000 -> 2.8373633 | F9: =IS_Proj!F25/1000000000 -> 6.0218975 | G9: =IS_Proj!G25/1000000000 -> 0.31465181 | H9: =IS_Proj!H25/1000000000 -> 1.4042458 | I9: =IS_Proj!I25/1000000000 -> 2.5213667 | J9: =IS_Proj!J25/1000000000 -> 3.6740851 | K9: =IS_Proj!K25/1000000000 -> 4.8705401
B10: Laba pemilik entitas induk | C10: =IS_Proj!C27/1000000000 -> 4.8881658 | D10: =IS_Proj!D27/1000000000 -> 3.5397164 | E10: =IS_Proj!E27/1000000000 -> 2.8372318 | F10: =IS_Proj!F27/1000000000 -> 6.0216481 | G10: =IS_Proj!G27/1000000000 -> 0.31465181 | H10: =IS_Proj!H27/1000000000 -> 1.4042458 | I10: =IS_Proj!I27/1000000000 -> 2.5213667 | J10: =IS_Proj!J27/1000000000 -> 3.6740851 | K10: =IS_Proj!K27/1000000000 -> 4.8705401
B11: Arus kas operasi | C11: =CF_Proj!C11/1000000000 -> 7.7341001 | D11: =CF_Proj!D11/1000000000 -> 19.735705 | E11: =CF_Proj!E11/1000000000 -> 2.9976875 | F11: =CF_Proj!F11/1000000000 -> 5.5679514 | G11: =CF_Proj!G11/1000000000 -> 8.5522395 | H11: =CF_Proj!H11/1000000000 -> 12.752114 | I11: =CF_Proj!I11/1000000000 -> 14.048445 | J11: =CF_Proj!J11/1000000000 -> 15.466407 | K11: =CF_Proj!K11/1000000000 -> 17.013966
B12: Capex | C12: =CF_Proj!C13/1000000000 -> -16.981554 | D12: =CF_Proj!D13/1000000000 -> -36.146492 | E12: =CF_Proj!E13/1000000000 -> -24.447662 | F12: =CF_Proj!F13/1000000000 -> -27.390828 | G12: =CF_Proj!G13/1000000000 -> -14.076536 | H12: =CF_Proj!H13/1000000000 -> -15.202659 | I12: =CF_Proj!I13/1000000000 -> -16.418872 | J12: =CF_Proj!J13/1000000000 -> -17.732382 | K12: =CF_Proj!K13/1000000000 -> -19.150972
B13: FCF setelah sewa | C13: =CF_Proj!C27/1000000000 -> -9.410982 | D13: =CF_Proj!D27/1000000000 -> -16.410787 | E13: =CF_Proj!E27/1000000000 -> -21.955612 | F13: =CF_Proj!F27/1000000000 -> -22.821714 | G13: =CF_Proj!G27/1000000000 -> -6.0560769 | H13: =CF_Proj!H27/1000000000 -> -3.024868 | I13: =CF_Proj!I27/1000000000 -> -2.9906952 | J13: =CF_Proj!J27/1000000000 -> -2.9358644 | K13: =CF_Proj!K27/1000000000 -> -2.860487
B14: Kas akhir | C14: =BS_Proj!C6/1000000000 -> 29.547207 | D14: =BS_Proj!D6/1000000000 -> 2.4639738 | E14: =BS_Proj!E6/1000000000 -> 2.6633883 | F14: =BS_Proj!F6/1000000000 -> 4.036507 | G14: =BS_Proj!G6/1000000000 -> -2.0195699 | H14: =BS_Proj!H6/1000000000 -> -5.0444379 | I14: =BS_Proj!I6/1000000000 -> -8.0351331 | J14: =BS_Proj!J6/1000000000 -> -10.970998 | K14: =BS_Proj!K6/1000000000 -> -13.831484
B15: Utang neto (utang + sewa - kas) | C15: =BS_Proj!C31/1000000000 -> 64.124135 | D15: =BS_Proj!D31/1000000000 -> 142.65161 | E15: =BS_Proj!E31/1000000000 -> 111.51054 | F15: =BS_Proj!F31/1000000000 -> 87.265075 | G15: =BS_Proj!G31/1000000000 -> 93.321152 | H15: =BS_Proj!H31/1000000000 -> 96.34602 | I15: =BS_Proj!I31/1000000000 -> 99.336715 | J15: =BS_Proj!J31/1000000000 -> 102.27258 | K15: =BS_Proj!K31/1000000000 -> 105.13307
B16: Utang neto / EBITDA | C16: =BS_Proj!C33 -> 4.2324598 | D16: =BS_Proj!D33 -> 8.1494706 | E16: =BS_Proj!E33 -> 5.2153695 | F16: =BS_Proj!F33 -> 5.6873182 | G16: =BS_Proj!G33 -> 4.5201502 | H16: =BS_Proj!H33 -> 4.3209854 | I16: =BS_Proj!I33 -> 4.1251055 | J16: =BS_Proj!J33 -> 3.9324275 | K16: =BS_Proj!K33 -> 3.7429764
B17: ROE | D17: =BS_Proj!D32 -> 0.039282225 | E17: =BS_Proj!E32 -> 0.02191938 | F17: =BS_Proj!F32 -> 0.035818841 | G17: =BS_Proj!G32 -> 0.0015225618 | H17: =BS_Proj!H32 -> 0.006766833 | I17: =BS_Proj!I32 -> 0.012036213 | J17: =BS_Proj!J32 -> 0.017283351 | K17: =BS_Proj!K32 -> 0.022460229
B18: Cek balance BS_Proj (harus 0) | C18: =BS_Proj!C30 -> 0 | D18: =BS_Proj!D30 -> 0 | E18: =BS_Proj!E30 -> 0 | F18: =BS_Proj!F30 -> 0 | G18: =BS_Proj!G30 -> 0 | H18: =BS_Proj!H30 -> 0 | I18: =BS_Proj!I30 -> 0 | J18: =BS_Proj!J30 -> 0 | K18: =BS_Proj!K30 -> 0
B19: Status rekonsiliasi | C19: =Rekonsiliasi!$C$3 -> SEMUA 225 CEK SESUAI EKSPEKTASI

Sheet Asumsi
A1: Asumsi proyeksi ilustratif FY2026E-FY2030E (Base / Bull / Bear)
A2: Proyeksi ILUSTRATIF berbasis asumsi transparan - bukan rekomendasi investasi, bukan target, bukan nilai wajar.
A4: Skenario aktif | C4: Base | D4: =IF(C4="Bull",2,IF(C4="Bear",3,1)) -> 1 | E4: <- pilih Base / Bull / Bear. Kolom historis = aktual (rumus dari IS/BS/CF/Schedules); kolom E = asumsi skenario aktif.
A5: Kalibrasi | C5: Asumsi dikalibrasi dari FY2022-FY2025 (2022-2023 proforma restrukturisasi; 2025 tahun IPO). Pos tidak berulang (bunga pihak berelasi 2025, uang muka aset 2025, revaluasi 2023) tidak dipakai sebagai patokan.
A7: Kunci | B7: Driver | C7: FY2022A | D7: FY2023A | E7: FY2024A | F7: FY2025A | G7: FY2026E | H7: FY2027E | I7: FY2028E | J7: FY2029E | K7: FY2030E | L7: Dasar asumsi (kalibrasi FY2022-FY2025)
B8: ASUMSI AKTIF - kolom historis = aktual (rumus), kolom E = skenario terpilih
B9: PENDAPATAN (per kelompok, Cat 25)
A10: g_med | B10: Pertumbuhan pendapatan penunjang medis (farmasi, laboratorium, radiologi) | D10: =IFERROR(Schedules!D6/Schedules!C6-1,"") -> 3.6879283 | E10: =IFERROR(Schedules!E6/Schedules!D6-1,"") -> 2.8821553 | F10: =IFERROR(Schedules!F6/Schedules!E6-1,"") -> -0.33671624 | G10: =CHOOSE(Asumsi!$D$4,G38,G65,G92) -> 0.08 | H10: =CHOOSE(Asumsi!$D$4,H38,H65,H92) -> 0.08 | I10: =CHOOSE(Asumsi!$D$4,I38,I65,I92) -> 0.08 | J10: =CHOOSE(Asumsi!$D$4,J38,J65,J92) -> 0.08 | K10: =CHOOSE(Asumsi!$D$4,K38,K65,K92) -> 0.08 | L10: Pendapatan: 2022 3 M, 2023 12 M, 2024 46 M, 2025 31 M. CAGR 2022-25 129,4%; 2025 turun. Base 8%; Bull 12%; Bear 3% (3 RS tipe C, pasien BPJS dominan; tanpa RS baru).
A11: g_inpat | B11: Pertumbuhan pendapatan rawat inap | D11: =IFERROR(Schedules!D7/Schedules!C7-1,"") -> 0.48651982 | E11: =IFERROR(Schedules!E7/Schedules!D7-1,"") -> 0.079676764 | F11: =IFERROR(Schedules!F7/Schedules!E7-1,"") -> -0.13733116 | G11: =CHOOSE(Asumsi!$D$4,G39,G66,G93) -> 0.08 | H11: =CHOOSE(Asumsi!$D$4,H39,H66,H93) -> 0.08 | I11: =CHOOSE(Asumsi!$D$4,I39,I66,I93) -> 0.08 | J11: =CHOOSE(Asumsi!$D$4,J39,J66,J93) -> 0.08 | K11: =CHOOSE(Asumsi!$D$4,K39,K66,K93) -> 0.08 | L11: Pendapatan: 2022 54 M, 2023 80 M, 2024 86 M, 2025 74 M. CAGR 2022-25 11,5%. Base 8%; Bull 12%; Bear 3%.
A12: g_outpat | B12: Pertumbuhan pendapatan rawat jalan | D12: =IFERROR(Schedules!D8/Schedules!C8-1,"") -> -0.015719298 | E12: =IFERROR(Schedules!E8/Schedules!D8-1,"") -> -0.53269619 | F12: =IFERROR(Schedules!F8/Schedules!E8-1,"") -> 1.0053615 | G12: =CHOOSE(Asumsi!$D$4,G40,G67,G94) -> 0.08 | H12: =CHOOSE(Asumsi!$D$4,H40,H67,H94) -> 0.08 | I12: =CHOOSE(Asumsi!$D$4,I40,I67,I94) -> 0.08 | J12: =CHOOSE(Asumsi!$D$4,J40,J67,J94) -> 0.08 | K12: =CHOOSE(Asumsi!$D$4,K40,K67,K94) -> 0.08 | L12: Pendapatan: 2022 43 M, 2023 43 M, 2024 20 M, 2025 40 M. CAGR 2022-25 -2,7% (kategori berbeda antar sumber, Temuan D10). Base 8%; Bull 12%; Bear 3%.
A13: rev_oth | B13: Pendapatan lainnya (% 3 kelompok utama) | C13: =IFERROR(Schedules!C9/(Schedules!C6+Schedules!C7+Schedules!C8),"") -> 0.001775748 | D13: =IFERROR(Schedules!D9/(Schedules!D6+Schedules!D7+Schedules!D8),"") -> 0.00054476377 | E13: =IFERROR(Schedules!E9/(Schedules!E6+Schedules!E7+Schedules!E8),"") -> 0.001029331 | F13: =IFERROR(Schedules!F9/(Schedules!F6+Schedules!F7+Schedules!F8),"") -> 0.0012658688 | G13: =CHOOSE(Asumsi!$D$4,G41,G68,G95) -> 0.0009 | H13: =CHOOSE(Asumsi!$D$4,H41,H68,H95) -> 0.0009 | I13: =CHOOSE(Asumsi!$D$4,I41,I68,I95) -> 0.0009 | J13: =CHOOSE(Asumsi!$D$4,J41,J68,J95) -> 0.0009 | K13: =CHOOSE(Asumsi!$D$4,K41,K68,K95) -> 0.0009 | L13: Historis: 2022 0,2%, 2023 0,1%, 2024 0,1%, 2025 0,1%. Base/Bull/Bear = rata-rata 2023-25.
B14: MARGIN & BIAYA (% pendapatan)
A15: cogs | B15: Beban pokok di luar penyusutan aset tetap & aset hak guna | C15: =IFERROR(-(IS!C7+Schedules!C12+Schedules!C16+Schedules!C17)/IS!C6,"") -> 0.64108649 | D15: =IFERROR(-(IS!D7+Schedules!D12+Schedules!D16+Schedules!D17)/IS!D6,"") -> 0.6348373 | E15: =IFERROR(-(IS!E7+Schedules!E12+Schedules!E16+Schedules!E17)/IS!E6,"") -> 0.65153367 | F15: =IFERROR(-(IS!F7+Schedules!F12+Schedules!F16+Schedules!F17)/IS!F6,"") -> 0.69165664 | G15: =CHOOSE(Asumsi!$D$4,G43,G70,G97) -> 0.67 | H15: =CHOOSE(Asumsi!$D$4,H43,H70,H97) -> 0.67 | I15: =CHOOSE(Asumsi!$D$4,I43,I70,I97) -> 0.67 | J15: =CHOOSE(Asumsi!$D$4,J43,J70,J97) -> 0.67 | K15: =CHOOSE(Asumsi!$D$4,K43,K70,K97) -> 0.67 | L15: Historis: 2022 64,1%, 2023 63,5%, 2024 65,2%, 2025 69,2% (naik 2025). Base 67%; Bull 65%; Bear 69%.
A16: opex | B16: Beban penjualan + umum & administrasi di luar penyusutan | C16: =IFERROR(-(IS!C11+Schedules!C13+Schedules!C18)/IS!C6,"") -> 0.21908196 | D16: =IFERROR(-(IS!D11+Schedules!D13+Schedules!D18)/IS!D6,"") -> 0.23527689 | E16: =IFERROR(-(IS!E11+Schedules!E13+Schedules!E18)/IS!E6,"") -> 0.20999604 | F16: =IFERROR(-(IS!F11+Schedules!F13+Schedules!F18)/IS!F6,"") -> 0.19752974 | G16: =CHOOSE(Asumsi!$D$4,G44,G71,G98) -> 0.2 | H16: =CHOOSE(Asumsi!$D$4,H44,H71,H98) -> 0.2 | I16: =CHOOSE(Asumsi!$D$4,I44,I71,I98) -> 0.2 | J16: =CHOOSE(Asumsi!$D$4,J44,J71,J98) -> 0.2 | K16: =CHOOSE(Asumsi!$D$4,K44,K71,K98) -> 0.2 | L16: Historis: 2022 21,9%, 2023 23,5%, 2024 21,0%, 2025 19,8%. Base 20%; Bull 19%; Bear 21,5%.
A17: other_op | B17: Pendapatan (beban) lain-lain neto (% pendapatan) | C17: =IFERROR(IS!C13/IS!C6,"") -> 0.012315884 | D17: =IFERROR(IS!D13/IS!D6,"") -> 0.00056135103 | E17: =IFERROR(IS!E13/IS!E6,"") -> 0.0020635766 | F17: =IFERROR(IS!F13/IS!F6,"") -> -0.004901745 | G17: =CHOOSE(Asumsi!$D$4,G45,G72,G99) -> 0.002 | H17: =CHOOSE(Asumsi!$D$4,H45,H72,H99) -> 0.002 | I17: =CHOOSE(Asumsi!$D$4,I45,I72,I99) -> 0.002 | J17: =CHOOSE(Asumsi!$D$4,J45,J72,J99) -> 0.002 | K17: =CHOOSE(Asumsi!$D$4,K45,K72,K99) -> 0.002 | L17: Historis: 2022 1,2%, 2023 0,1%, 2024 0,2%, 2025 -0,5% (sewa & lain-lain; 2025 negatif). Base 0,2%; Bull 0,3%; Bear 0%.
B18: INVESTASI & ASET
A19: capex | B19: Capex aset tetap (% pendapatan) | C19: =IFERROR(-(CF!C16+CF!C17)/IS!C6,"") -> 0.17053495 | D19: =IFERROR(-(CF!D16+CF!D17)/IS!D6,"") -> 0.26937266 | E19: =IFERROR(-(CF!E16+CF!E17)/IS!E6,"") -> 0.1606895 | F19: =IFERROR(-(CF!F16+CF!F17)/IS!F6,"") -> 0.18906751 | G19: =CHOOSE(Asumsi!$D$4,G47,G74,G101) -> 0.09 | H19: =CHOOSE(Asumsi!$D$4,H47,H74,H101) -> 0.09 | I19: =CHOOSE(Asumsi!$D$4,I47,I74,I101) -> 0.09 | J19: =CHOOSE(Asumsi!$D$4,J47,J74,J101) -> 0.09 | K19: =CHOOSE(Asumsi!$D$4,K47,K74,K101) -> 0.09 | L19: Historis kas: 2022 17,1%, 2023 26,9%, 2024 16,1%, 2025 18,9% (2023 pembangunan RS; 2025 termasuk uang muka aset tetap 23,5 M, Temuan D4). Base 9% (kira-kira setara penyusutan, tanpa RS baru); Bull 7%; Bear 12%.
A20: lease_pd | B20: Pembayaran sewa dikapitalisasi ke aset tetap (% pendapatan) | C20: =IFERROR(-CF!C40/IS!C6,"") -> 0.0016422116 | D20: =IFERROR(-CF!D40/IS!D6,"") -> 0 | E20: =IFERROR(-CF!E40/IS!E6,"") -> 0.0033234514 | F20: =IFERROR(-CF!F40/IS!F6,"") -> 0.0068945572 | G20: =CHOOSE(Asumsi!$D$4,G48,G75,G102) -> 0.0034 | H20: =CHOOSE(Asumsi!$D$4,H48,H75,H102) -> 0.0034 | I20: =CHOOSE(Asumsi!$D$4,I48,I75,I102) -> 0.0034 | J20: =CHOOSE(Asumsi!$D$4,J48,J75,J102) -> 0.0034 | K20: =CHOOSE(Asumsi!$D$4,K48,K75,K102) -> 0.0034 | L20: Historis: 2022 0,2%, 2023 0,0%, 2024 0,3%, 2025 0,7% (kecil). Base/Bull/Bear = rata-rata 2023-25; liabilitas sewa & aset hak guna konstan.
A21: dep | B21: Penyusutan aset tetap + aset hak guna (% aset tetap neto awal) | D21: =IFERROR((Schedules!D14+Schedules!D16)/BS!C21,"") -> 0.11704763 | E21: =IFERROR((Schedules!E14+Schedules!E16)/BS!D21,"") -> 0.083087474 | F21: =IFERROR((Schedules!F14+Schedules!F16)/BS!E21,"") -> 0.095201334 | G21: =CHOOSE(Asumsi!$D$4,G49,G76,G103) -> 0.0984 | H21: =CHOOSE(Asumsi!$D$4,H49,H76,H103) -> 0.0984 | I21: =CHOOSE(Asumsi!$D$4,I49,I76,I103) -> 0.0984 | J21: =CHOOSE(Asumsi!$D$4,J49,J76,J103) -> 0.0984 | K21: =CHOOSE(Asumsi!$D$4,K49,K76,K103) -> 0.0984 | L21: Historis: 2023 11,7%, 2024 8,3%, 2025 9,5%. Base/Bull/Bear = rata-rata 2023-25.
A22: sw | B22: Amortisasi aset takberwujud (% saldo awal) | D22: =IFERROR(Schedules!D19/BS!C17,"") | E22: =IFERROR(Schedules!E19/BS!D17,"") | F22: =IFERROR(Schedules!F19/BS!E17,"") | G22: =CHOOSE(Asumsi!$D$4,G50,G77,G104) -> 0 | H22: =CHOOSE(Asumsi!$D$4,H50,H77,H104) -> 0 | I22: =CHOOSE(Asumsi!$D$4,I50,I77,I104) -> 0 | J22: =CHOOSE(Asumsi!$D$4,J50,J77,J104) -> 0 | K22: =CHOOSE(Asumsi!$D$4,K50,K77,K104) -> 0 | L22: DKHH tidak memiliki aset takberwujud. Semua skenario 0.
B23: MODAL KERJA (hari, saldo akhir, basis 365)
A24: dso | B24: DSO piutang usaha / pendapatan | C24: =IFERROR((BS!C8+BS!C9)/IS!C6*365,"") -> 44.41957 | D24: =IFERROR((BS!D8+BS!D9)/IS!D6*365,"") -> 45.652804 | E24: =IFERROR((BS!E8+BS!E9)/IS!E6*365,"") -> 60.158756 | F24: =IFERROR((BS!F8+BS!F9)/IS!F6*365,"") -> 47.54806 | G24: =CHOOSE(Asumsi!$D$4,G52,G79,G106) -> 50 | H24: =CHOOSE(Asumsi!$D$4,H52,H79,H106) -> 50 | I24: =CHOOSE(Asumsi!$D$4,I52,I79,I106) -> 50 | J24: =CHOOSE(Asumsi!$D$4,J52,J79,J106) -> 50 | K24: =CHOOSE(Asumsi!$D$4,K52,K79,K106) -> 50 | L24: Historis: 2022 44,4, 2023 45,7, 2024 60,2, 2025 47,5 (piutang BPJS). Base 50; Bull 45; Bear 60.
A25: dio | B25: DIO persediaan / beban pokok di luar penyusutan | C25: =IFERROR(BS!C12/-(IS!C7+Schedules!C12+Schedules!C16+Schedules!C17)*365,"") -> 12.949688 | D25: =IFERROR(BS!D12/-(IS!D7+Schedules!D12+Schedules!D16+Schedules!D17)*365,"") -> 17.293084 | E25: =IFERROR(BS!E12/-(IS!E7+Schedules!E12+Schedules!E16+Schedules!E17)*365,"") -> 15.228132 | F25: =IFERROR(BS!F12/-(IS!F7+Schedules!F12+Schedules!F16+Schedules!F17)*365,"") -> 4.8674244 | G25: =CHOOSE(Asumsi!$D$4,G53,G80,G107) -> 10 | H25: =CHOOSE(Asumsi!$D$4,H53,H80,H107) -> 10 | I25: =CHOOSE(Asumsi!$D$4,I53,I80,I107) -> 10 | J25: =CHOOSE(Asumsi!$D$4,J53,J80,J107) -> 10 | K25: =CHOOSE(Asumsi!$D$4,K53,K80,K107) -> 10 | L25: Historis: 2022 12,9, 2023 17,3, 2024 15,2, 2025 4,9 (2025 turun tajam). Base 10; Bull 8; Bear 14.
A26: dpo | B26: DPO utang usaha / beban pokok di luar penyusutan | C26: =IFERROR((BS!C30+BS!C31)/-(IS!C7+Schedules!C12+Schedules!C16+Schedules!C17)*365,"") -> 11.77416 | D26: =IFERROR((BS!D30+BS!D31)/-(IS!D7+Schedules!D12+Schedules!D16+Schedules!D17)*365,"") -> 20.448875 | E26: =IFERROR((BS!E30+BS!E31)/-(IS!E7+Schedules!E12+Schedules!E16+Schedules!E17)*365,"") -> 20.873114 | F26: =IFERROR((BS!F30+BS!F31)/-(IS!F7+Schedules!F12+Schedules!F16+Schedules!F17)*365,"") -> 23.962173 | G26: =CHOOSE(Asumsi!$D$4,G54,G81,G108) -> 22 | H26: =CHOOSE(Asumsi!$D$4,H54,H81,H108) -> 22 | I26: =CHOOSE(Asumsi!$D$4,I54,I81,I108) -> 22 | J26: =CHOOSE(Asumsi!$D$4,J54,J81,J108) -> 22 | K26: =CHOOSE(Asumsi!$D$4,K54,K81,K108) -> 22 | L26: Historis: 2022 11,8, 2023 20,4, 2024 20,9, 2025 24,0. Base 22; Bull 25; Bear 18.
B27: PAJAK, PENDANAAN, DISTRIBUSI
A28: tax | B28: Tarif pajak efektif (% laba sebelum pajak) | C28: =IFERROR(-IS!C18/IS!C17,"") -> 0.25801251 | D28: =IFERROR(-IS!D18/IS!D17,"") -> 0.76735139 | E28: =IFERROR(-IS!E18/IS!E17,"") -> 6.9116652 | F28: =IFERROR(-IS!F18/IS!F17,"") -> -0.058527227 | G28: =CHOOSE(Asumsi!$D$4,G56,G83,G110) -> 0.25 | H28: =CHOOSE(Asumsi!$D$4,H56,H83,H110) -> 0.25 | I28: =CHOOSE(Asumsi!$D$4,I56,I83,I110) -> 0.25 | J28: =CHOOSE(Asumsi!$D$4,J56,J83,J110) -> 0.25 | K28: =CHOOSE(Asumsi!$D$4,K56,K83,K110) -> 0.25 | L28: Historis: 2022 25,8%, 2023 76,7%, 2024 691,2%, 2025 -5,9% (laba sebelum pajak sangat kecil 2024; 2025 manfaat pajak, Temuan D11). Base 25%; Bull 22% (tarif badan); Bear 30%.
A29: fin_cost | B29: Suku bunga efektif (beban keuangan / rata-rata utang berbunga) | D29: =IFERROR(-IS!D15/AVERAGE((BS!D29+BS!D38+BS!D43+BS!D39+BS!D44+BS!D40+BS!D45+BS!D49+BS!D50),(BS!C29+BS!C38+BS!C43+BS!C39+BS!C44+BS!C40+BS!C45+BS!C49+BS!C50)),"") -> 0.063370183 | E29: =IFERROR(-IS!E15/AVERAGE((BS!E29+BS!E38+BS!E43+BS!E39+BS!E44+BS!E40+BS!E45+BS!E49+BS!E50),(BS!D29+BS!D38+BS!D43+BS!D39+BS!D44+BS!D40+BS!D45+BS!D49+BS!D50)),"") -> 0.089940574 | F29: =IFERROR(-IS!F15/AVERAGE((BS!F29+BS!F38+BS!F43+BS!F39+BS!F44+BS!F40+BS!F45+BS!F49+BS!F50),(BS!E29+BS!E38+BS!E43+BS!E39+BS!E44+BS!E40+BS!E45+BS!E49+BS!E50)),"") -> 0.10149914 | G29: =CHOOSE(Asumsi!$D$4,G57,G84,G111) -> 0.0849 | H29: =CHOOSE(Asumsi!$D$4,H57,H84,H111) -> 0.0849 | I29: =CHOOSE(Asumsi!$D$4,I57,I84,I111) -> 0.0849 | J29: =CHOOSE(Asumsi!$D$4,J57,J84,J111) -> 0.0849 | K29: =CHOOSE(Asumsi!$D$4,K57,K84,K111) -> 0.0849 | L29: Historis: 2023 6,34%, 2024 8,99%, 2025 10,15% (termasuk bagi hasil syirkah & bunga sewa). Base = rata-rata 2023-25; Bull x0,9; Bear x1,1 (Temuan D2).
A30: yld | B30: Imbal hasil kas (penghasilan keuangan / kas awal) | D30: =IFERROR(IS!D16/BS!C6,"") -> 0 | E30: =IFERROR(IS!E16/BS!D6,"") -> 0 | F30: =IFERROR(IS!F16/BS!E6,"") -> 4.9525548 | G30: =CHOOSE(Asumsi!$D$4,G58,G85,G112) -> 0 | H30: =CHOOSE(Asumsi!$D$4,H58,H85,H112) -> 0 | I30: =CHOOSE(Asumsi!$D$4,I58,I85,I112) -> 0 | J30: =CHOOSE(Asumsi!$D$4,J58,J85,J112) -> 0 | K30: =CHOOSE(Asumsi!$D$4,K58,K85,K112) -> 0 | L30: Historis: 2023 0%, 2024 0%, 2025 495%. Penghasilan keuangan 2025 = bunga pinjaman ke pihak berelasi, bukan imbal hasil kas (Temuan D3). Semua skenario 0.
A31: debt_chg | B31: Perubahan neto utang (Rp; + = tambah) | D31: =(BS!D29+BS!D38+BS!D43+BS!D39+BS!D44+BS!D40+BS!D45+BS!D49+BS!D50)-(BS!C29+BS!C38+BS!C43+BS!C39+BS!C44+BS!C40+BS!C45+BS!C49+BS!C50) -> 51444241469 | E31: =(BS!E29+BS!E38+BS!E43+BS!E39+BS!E44+BS!E40+BS!E45+BS!E49+BS!E50)-(BS!D29+BS!D38+BS!D43+BS!D39+BS!D44+BS!D40+BS!D45+BS!D49+BS!D50) -> -33270144518 | F31: =(BS!F29+BS!F38+BS!F43+BS!F39+BS!F44+BS!F40+BS!F45+BS!F49+BS!F50)-(BS!E29+BS!E38+BS!E43+BS!E39+BS!E44+BS!E40+BS!E45+BS!E49+BS!E50) -> -21873507264 | G31: =CHOOSE(Asumsi!$D$4,G59,G86,G113) -> 0 | H31: =CHOOSE(Asumsi!$D$4,H59,H86,H113) -> 0 | I31: =CHOOSE(Asumsi!$D$4,I59,I86,I113) -> 0 | J31: =CHOOSE(Asumsi!$D$4,J59,J86,J113) -> 0 | K31: =CHOOSE(Asumsi!$D$4,K59,K86,K113) -> 0 | L31: Historis utang berbunga (termasuk syirkah): 2022 94 M, 2023 145 M, 2024 112 M, 2025 90 M. Semua skenario 0 (kas = penyeimbang; jadwal pelunasan tidak dimodelkan).
A32: payout | B32: Payout dividen (% laba induk tahun lalu) | D32: =IFERROR(-CF!D41/IS!C29,"") -> 0 | E32: =IFERROR(-CF!E41/IS!D29,"") -> 0 | F32: =IFERROR(-CF!F41/IS!E29,"") -> 0 | G32: =CHOOSE(Asumsi!$D$4,G60,G87,G114) -> 0 | H32: =CHOOSE(Asumsi!$D$4,H60,H87,H114) -> 0 | I32: =CHOOSE(Asumsi!$D$4,I60,I87,I114) -> 0 | J32: =CHOOSE(Asumsi!$D$4,J60,J87,J114) -> 0 | K32: =CHOOSE(Asumsi!$D$4,K60,K87,K114) -> 0 | L32: Tidak ada dividen ke pemilik induk 2022-2025 (Temuan D11). Semua skenario 0%.
A33: nci_share | B33: Porsi laba ke NCI (% laba tahun berjalan) | C33: =IFERROR(IS!C30/IS!C20,"") -> 0 | D33: =IFERROR(IS!D30/IS!D20,"") -> 0 | E33: =IFERROR(IS!E30/IS!E20,"") -> 4.6327871e-05 | F33: =IFERROR(IS!F30/IS!F20,"") -> 4.1416181e-05 | G33: =CHOOSE(Asumsi!$D$4,G61,G88,G115) -> 0 | H33: =CHOOSE(Asumsi!$D$4,H61,H88,H115) -> 0 | I33: =CHOOSE(Asumsi!$D$4,I61,I88,I115) -> 0 | J33: =CHOOSE(Asumsi!$D$4,J61,J88,J115) -> 0 | K33: =CHOOSE(Asumsi!$D$4,K61,K88,K115) -> 0 | L33: Historis: 2022 0,000%, 2023 0,000%, 2024 0,005%, 2025 0,004% (sangat kecil). Semua skenario 0%.
B36: SKENARIO BASE - input biru per tahun (boleh diubah pengguna)
B37: PENDAPATAN (per kelompok, Cat 25)
A38: Base.g_med | B38: Pertumbuhan pendapatan penunjang medis (farmasi, laboratorium, radiologi) | G38: 0.08 | H38: 0.08 | I38: 0.08 | J38: 0.08 | K38: 0.08
A39: Base.g_inpat | B39: Pertumbuhan pendapatan rawat inap | G39: 0.08 | H39: 0.08 | I39: 0.08 | J39: 0.08 | K39: 0.08
A40: Base.g_outpat | B40: Pertumbuhan pendapatan rawat jalan | G40: 0.08 | H40: 0.08 | I40: 0.08 | J40: 0.08 | K40: 0.08
A41: Base.rev_oth | B41: Pendapatan lainnya (% 3 kelompok utama) | G41: 0.0009 | H41: 0.0009 | I41: 0.0009 | J41: 0.0009 | K41: 0.0009
B42: MARGIN & BIAYA (% pendapatan)
A43: Base.cogs | B43: Beban pokok di luar penyusutan aset tetap & aset hak guna | G43: 0.67 | H43: 0.67 | I43: 0.67 | J43: 0.67 | K43: 0.67
A44: Base.opex | B44: Beban penjualan + umum & administrasi di luar penyusutan | G44: 0.2 | H44: 0.2 | I44: 0.2 | J44: 0.2 | K44: 0.2
A45: Base.other_op | B45: Pendapatan (beban) lain-lain neto (% pendapatan) | G45: 0.002 | H45: 0.002 | I45: 0.002 | J45: 0.002 | K45: 0.002
B46: INVESTASI & ASET
A47: Base.capex | B47: Capex aset tetap (% pendapatan) | G47: 0.09 | H47: 0.09 | I47: 0.09 | J47: 0.09 | K47: 0.09
A48: Base.lease_pd | B48: Pembayaran sewa dikapitalisasi ke aset tetap (% pendapatan) | G48: 0.0034 | H48: 0.0034 | I48: 0.0034 | J48: 0.0034 | K48: 0.0034
A49: Base.dep | B49: Penyusutan aset tetap + aset hak guna (% aset tetap neto awal) | G49: 0.0984 | H49: 0.0984 | I49: 0.0984 | J49: 0.0984 | K49: 0.0984
A50: Base.sw | B50: Amortisasi aset takberwujud (% saldo awal) | G50: 0 | H50: 0 | I50: 0 | J50: 0 | K50: 0
B51: MODAL KERJA (hari, saldo akhir, basis 365)
A52: Base.dso | B52: DSO piutang usaha / pendapatan | G52: 50 | H52: 50 | I52: 50 | J52: 50 | K52: 50
A53: Base.dio | B53: DIO persediaan / beban pokok di luar penyusutan | G53: 10 | H53: 10 | I53: 10 | J53: 10 | K53: 10
A54: Base.dpo | B54: DPO utang usaha / beban pokok di luar penyusutan | G54: 22 | H54: 22 | I54: 22 | J54: 22 | K54: 22
B55: PAJAK, PENDANAAN, DISTRIBUSI
A56: Base.tax | B56: Tarif pajak efektif (% laba sebelum pajak) | G56: 0.25 | H56: 0.25 | I56: 0.25 | J56: 0.25 | K56: 0.25
A57: Base.fin_cost | B57: Suku bunga efektif (beban keuangan / rata-rata utang berbunga) | G57: 0.0849 | H57: 0.0849 | I57: 0.0849 | J57: 0.0849 | K57: 0.0849
A58: Base.yld | B58: Imbal hasil kas (penghasilan keuangan / kas awal) | G58: 0 | H58: 0 | I58: 0 | J58: 0 | K58: 0
A59: Base.debt_chg | B59: Perubahan neto utang (Rp; + = tambah) | G59: 0 | H59: 0 | I59: 0 | J59: 0 | K59: 0
A60: Base.payout | B60: Payout dividen (% laba induk tahun lalu) | G60: 0 | H60: 0 | I60: 0 | J60: 0 | K60: 0
A61: Base.nci_share | B61: Porsi laba ke NCI (% laba tahun berjalan) | G61: 0 | H61: 0 | I61: 0 | J61: 0 | K61: 0
B63: SKENARIO BULL - input biru per tahun (boleh diubah pengguna)
B64: PENDAPATAN (per kelompok, Cat 25)
A65: Bull.g_med | B65: Pertumbuhan pendapatan penunjang medis (farmasi, laboratorium, radiologi) | G65: 0.12 | H65: 0.12 | I65: 0.12 | J65: 0.12 | K65: 0.12
A66: Bull.g_inpat | B66: Pertumbuhan pendapatan rawat inap | G66: 0.12 | H66: 0.12 | I66: 0.12 | J66: 0.12 | K66: 0.12
A67: Bull.g_outpat | B67: Pertumbuhan pendapatan rawat jalan | G67: 0.12 | H67: 0.12 | I67: 0.12 | J67: 0.12 | K67: 0.12
A68: Bull.rev_oth | B68: Pendapatan lainnya (% 3 kelompok utama) | G68: 0.0009 | H68: 0.0009 | I68: 0.0009 | J68: 0.0009 | K68: 0.0009
B69: MARGIN & BIAYA (% pendapatan)
A70: Bull.cogs | B70: Beban pokok di luar penyusutan aset tetap & aset hak guna | G70: 0.65 | H70: 0.65 | I70: 0.65 | J70: 0.65 | K70: 0.65
A71: Bull.opex | B71: Beban penjualan + umum & administrasi di luar penyusutan | G71: 0.19 | H71: 0.19 | I71: 0.19 | J71: 0.19 | K71: 0.19
A72: Bull.other_op | B72: Pendapatan (beban) lain-lain neto (% pendapatan) | G72: 0.003 | H72: 0.003 | I72: 0.003 | J72: 0.003 | K72: 0.003
B73: INVESTASI & ASET
A74: Bull.capex | B74: Capex aset tetap (% pendapatan) | G74: 0.07 | H74: 0.07 | I74: 0.07 | J74: 0.07 | K74: 0.07
A75: Bull.lease_pd | B75: Pembayaran sewa dikapitalisasi ke aset tetap (% pendapatan) | G75: 0.0034 | H75: 0.0034 | I75: 0.0034 | J75: 0.0034 | K75: 0.0034
A76: Bull.dep | B76: Penyusutan aset tetap + aset hak guna (% aset tetap neto awal) | G76: 0.0984 | H76: 0.0984 | I76: 0.0984 | J76: 0.0984 | K76: 0.0984
A77: Bull.sw | B77: Amortisasi aset takberwujud (% saldo awal) | G77: 0 | H77: 0 | I77: 0 | J77: 0 | K77: 0
B78: MODAL KERJA (hari, saldo akhir, basis 365)
A79: Bull.dso | B79: DSO piutang usaha / pendapatan | G79: 45 | H79: 45 | I79: 45 | J79: 45 | K79: 45
A80: Bull.dio | B80: DIO persediaan / beban pokok di luar penyusutan | G80: 8 | H80: 8 | I80: 8 | J80: 8 | K80: 8
A81: Bull.dpo | B81: DPO utang usaha / beban pokok di luar penyusutan | G81: 25 | H81: 25 | I81: 25 | J81: 25 | K81: 25
B82: PAJAK, PENDANAAN, DISTRIBUSI
A83: Bull.tax | B83: Tarif pajak efektif (% laba sebelum pajak) | G83: 0.22 | H83: 0.22 | I83: 0.22 | J83: 0.22 | K83: 0.22
A84: Bull.fin_cost | B84: Suku bunga efektif (beban keuangan / rata-rata utang berbunga) | G84: 0.0764 | H84: 0.0764 | I84: 0.0764 | J84: 0.0764 | K84: 0.0764
A85: Bull.yld | B85: Imbal hasil kas (penghasilan keuangan / kas awal) | G85: 0 | H85: 0 | I85: 0 | J85: 0 | K85: 0
A86: Bull.debt_chg | B86: Perubahan neto utang (Rp; + = tambah) | G86: 0 | H86: 0 | I86: 0 | J86: 0 | K86: 0
A87: Bull.payout | B87: Payout dividen (% laba induk tahun lalu) | G87: 0 | H87: 0 | I87: 0 | J87: 0 | K87: 0
A88: Bull.nci_share | B88: Porsi laba ke NCI (% laba tahun berjalan) | G88: 0 | H88: 0 | I88: 0 | J88: 0 | K88: 0
B90: SKENARIO BEAR - input biru per tahun (boleh diubah pengguna)
B91: PENDAPATAN (per kelompok, Cat 25)
A92: Bear.g_med | B92: Pertumbuhan pendapatan penunjang medis (farmasi, laboratorium, radiologi) | G92: 0.03 | H92: 0.03 | I92: 0.03 | J92: 0.03 | K92: 0.03
A93: Bear.g_inpat | B93: Pertumbuhan pendapatan rawat inap | G93: 0.03 | H93: 0.03 | I93: 0.03 | J93: 0.03 | K93: 0.03
A94: Bear.g_outpat | B94: Pertumbuhan pendapatan rawat jalan | G94: 0.03 | H94: 0.03 | I94: 0.03 | J94: 0.03 | K94: 0.03
A95: Bear.rev_oth | B95: Pendapatan lainnya (% 3 kelompok utama) | G95: 0.0009 | H95: 0.0009 | I95: 0.0009 | J95: 0.0009 | K95: 0.0009
B96: MARGIN & BIAYA (% pendapatan)
A97: Bear.cogs | B97: Beban pokok di luar penyusutan aset tetap & aset hak guna | G97: 0.69 | H97: 0.69 | I97: 0.69 | J97: 0.69 | K97: 0.69
A98: Bear.opex | B98: Beban penjualan + umum & administrasi di luar penyusutan | G98: 0.215 | H98: 0.215 | I98: 0.215 | J98: 0.215 | K98: 0.215
A99: Bear.other_op | B99: Pendapatan (beban) lain-lain neto (% pendapatan) | G99: 0 | H99: 0 | I99: 0 | J99: 0 | K99: 0
B100: INVESTASI & ASET
A101: Bear.capex | B101: Capex aset tetap (% pendapatan) | G101: 0.12 | H101: 0.12 | I101: 0.12 | J101: 0.12 | K101: 0.12
A102: Bear.lease_pd | B102: Pembayaran sewa dikapitalisasi ke aset tetap (% pendapatan) | G102: 0.0034 | H102: 0.0034 | I102: 0.0034 | J102: 0.0034 | K102: 0.0034
A103: Bear.dep | B103: Penyusutan aset tetap + aset hak guna (% aset tetap neto awal) | G103: 0.0984 | H103: 0.0984 | I103: 0.0984 | J103: 0.0984 | K103: 0.0984
A104: Bear.sw | B104: Amortisasi aset takberwujud (% saldo awal) | G104: 0 | H104: 0 | I104: 0 | J104: 0 | K104: 0
B105: MODAL KERJA (hari, saldo akhir, basis 365)
A106: Bear.dso | B106: DSO piutang usaha / pendapatan | G106: 60 | H106: 60 | I106: 60 | J106: 60 | K106: 60
...

Sheet IS_Proj
A1: Proyeksi laba rugi (ilustratif)
A2: Rp penuh | kolom A = aktual (link ke IS/BS/CF/Schedules), kolom E = proyeksi | Proyeksi ILUSTRATIF berbasis asumsi transparan - bukan rekomendasi investasi, bukan target, bukan nilai wajar.
A3: Skenario aktif: | C3: =Asumsi!C4 -> Base | G3: ilustratif | H3: ilustratif | I3: ilustratif | J3: ilustratif | K3: ilustratif
A4: Kode | B4: Akun | C4: FY2022A | D4: FY2023A | E4: FY2024A | F4: FY2025A | G4: FY2026E | H4: FY2027E | I4: FY2028E | J4: FY2029E | K4: FY2030E | L4: Catatan / sumber
B5: PENDAPATAN (per kelompok)
A6: P.REV_MED | B6: Penunjang medis | C6: =Schedules!C6 -> 2534971388 | D6: =Schedules!D6 -> 11883764227 | E6: =Schedules!E6 -> 46134618145 | F6: =Schedules!F6 -> 30600343048 | G6: =F6*(1+Asumsi!G10) -> 3.304837e+10 | H6: =G6*(1+Asumsi!H10) -> 3.569224e+10 | I6: =H6*(1+Asumsi!I10) -> 3.8547619e+10 | J6: =I6*(1+Asumsi!J10) -> 4.1631429e+10 | K6: =J6*(1+Asumsi!K10) -> 4.4961943e+10
A7: P.REV_INPAT | B7: Rawat inap | C7: =Schedules!C7 -> 53534000426 | D7: =Schedules!D7 -> 79579352582 | E7: =Schedules!E7 -> 85919977894 | F7: =Schedules!F7 -> 74120487810 | G7: =F7*(1+Asumsi!G11) -> 8.0050127e+10 | H7: =G7*(1+Asumsi!H11) -> 8.6454137e+10 | I7: =H7*(1+Asumsi!I11) -> 9.3370468e+10 | J7: =I7*(1+Asumsi!J11) -> 1.0084011e+11 | K7: =J7*(1+Asumsi!K11) -> 1.0890731e+11
A8: P.REV_OUTPAT | B8: Rawat jalan | C8: =Schedules!C8 -> 43332660354 | D8: =Schedules!D8 -> 42651501335 | E8: =Schedules!E8 -> 19931209046 | F8: =Schedules!F8 -> 39969278831 | G8: =F8*(1+Asumsi!G12) -> 4.3166821e+10 | H8: =G8*(1+Asumsi!H12) -> 4.6620167e+10 | I8: =H8*(1+Asumsi!I12) -> 5.034978e+10 | J8: =I8*(1+Asumsi!J12) -> 5.4377763e+10 | K8: =J8*(1+Asumsi!K12) -> 5.8727984e+10
A9: P.REV_OTHER | B9: Lainnya (administrasi & lainnya) | C9: =Schedules!C9 -> 176512253 | D9: =Schedules!D9 -> 73060785 | E9: =Schedules!E9 -> 156443699 | F9: =Schedules!F9 -> 183158700 | G9: =(G6+G7+G8)*Asumsi!G13 -> 1.4063879e+08 | H9: =(H6+H7+H8)*Asumsi!H13 -> 1.5188989e+08 | I9: =(I6+I7+I8)*Asumsi!I13 -> 1.6404108e+08 | J9: =(J6+J7+J8)*Asumsi!J13 -> 1.7716437e+08 | K9: =(K6+K7+K8)*Asumsi!K13 -> 1.9133752e+08
A10: P.REVENUE | B10: Pendapatan | C10: =IS!C6 -> 99578144421 | D10: =IS!D6 -> 134187678929 | E10: =IS!E6 -> 152142248784 | F10: =IS!F6 -> 144873268389 | G10: =G6+G7+G8+G9 -> 1.5640596e+11 | H10: =H6+H7+H8+H9 -> 1.6891843e+11 | I10: =I6+I7+I8+I9 -> 1.8243191e+11 | J10: =J6+J7+J8+J9 -> 1.9702646e+11 | K10: =K6+K7+K8+K9 -> 2.1278858e+11
A11: P.REV_GROWTH | B11: Pertumbuhan pendapatan | D11: =D10/C10-1 -> 0.34756155 | E11: =E10/D10-1 -> 0.13380193 | F11: =F10/E10-1 -> -0.047777527 | G11: =G10/F10-1 -> 0.079605361 | H11: =H10/G10-1 -> 0.08 | I11: =I10/H10-1 -> 0.08 | J11: =J10/I10-1 -> 0.08 | K11: =K10/J10-1 -> 0.08
B12: BIAYA & EBITDA
A13: P.COGS_X | B13: Beban pokok di luar penyusutan (aset tetap & aset hak guna) | C13: =IS!C7+Schedules!C12+Schedules!C16+Schedules!C17 -> -63838203004 | D13: =IS!D7+Schedules!D12+Schedules!D16+Schedules!D17 -> -85187343300 | E13: =IS!E7+Schedules!E12+Schedules!E16+Schedules!E17 -> -99125797801 | F13: =IS!F7+Schedules!F12+Schedules!F16+Schedules!F17 -> -100202557824 | G13: =-G10*Asumsi!G15 -> -1.0479199e+11 | H13: =-H10*Asumsi!H15 -> -1.1317535e+11 | I13: =-I10*Asumsi!I15 -> -1.2222938e+11 | J13: =-J10*Asumsi!J15 -> -1.3200773e+11 | K13: =-K10*Asumsi!K15 -> -1.4256835e+11
A14: P.GP_X | B14: Laba bruto sebelum penyusutan | C14: =C10+C13 -> 35739941417 | D14: =D10+D13 -> 49000335629 | E14: =E10+E13 -> 53016450983 | F14: =F10+F13 -> 44670710565 | G14: =G10+G13 -> 5.1613966e+10 | H14: =H10+H13 -> 5.5743083e+10 | I14: =I10+I13 -> 6.020253e+10 | J14: =J10+J13 -> 6.5018732e+10 | K14: =K10+K13 -> 7.0220231e+10
A15: P.OPEX_X | B15: Beban usaha di luar penyusutan | C15: =IS!C11+Schedules!C13+Schedules!C18 -> -21815774673 | D15: =IS!D11+Schedules!D13+Schedules!D18 -> -31571259863 | E15: =IS!E11+Schedules!E13+Schedules!E18 -> -31949269543 | F15: =IS!F11+Schedules!F13+Schedules!F18 -> -28616778422 | G15: =-G10*Asumsi!G16 -> -3.1281191e+10 | H15: =-H10*Asumsi!H16 -> -3.3783687e+10 | I15: =-I10*Asumsi!I16 -> -3.6486382e+10 | J15: =-J10*Asumsi!J16 -> -3.9405292e+10 | K15: =-K10*Asumsi!K16 -> -4.2557716e+10
A16: P.OTHER_OP | B16: Pendapatan (beban) lain-lain neto | C16: =IS!C13 -> 1226392843 | D16: =IS!D13 -> 75326392 | E16: =IS!E13 -> 313957191 | F16: =IS!F13 -> -710131821 | G16: =G10*Asumsi!G17 -> 3.1281191e+08 | H16: =H10*Asumsi!H17 -> 3.3783687e+08 | I16: =I10*Asumsi!I17 -> 3.6486382e+08 | J16: =J10*Asumsi!J17 -> 3.9405292e+08 | K16: =K10*Asumsi!K17 -> 4.2557716e+08
A17: P.EBITDA | B17: EBITDA | C17: =C14+C15+C16 -> 15150559587 | D17: =D14+D15+D16 -> 17504402158 | E17: =E14+E15+E16 -> 21381138631 | F17: =F14+F15+F16 -> 15343800322 | G17: =G14+G15+G16 -> 2.0645586e+10 | H17: =H14+H15+H16 -> 2.2297233e+10 | I17: =I14+I15+I16 -> 2.4081012e+10 | J17: =J14+J15+J16 -> 2.6007493e+10 | K17: =K14+K15+K16 -> 2.8088092e+10 | L17: laba usaha model + penyusutan aset tetap + penyusutan aset hak guna
A18: P.DA | B18: Penyusutan & amortisasi | C18: =-Schedules!C20 -> -6778169378 | D18: =-Schedules!D20 -> -7754681103 | E18: =-Schedules!E20 -> -9756026475 | F18: =-Schedules!F20 -> -12603292085 | G18: =-(Schedules_Proj!G9+Schedules_Proj!G13) -> -1.2587434e+10 | H18: =-(Schedules_Proj!H9+Schedules_Proj!H13) -> -1.2786288e+10 | I18: =-(Schedules_Proj!I9+Schedules_Proj!I13) -> -1.3080573e+10 | J18: =-(Schedules_Proj!J9+Schedules_Proj!J13) -> -1.3470096e+10 | K18: =-(Schedules_Proj!K9+Schedules_Proj!K13) -> -1.3955422e+10
A19: P.EBIT | B19: Laba usaha (EBIT) | C19: =C17+C18 -> 8372390209 | D19: =D17+D18 -> 9749721055 | E19: =E17+E18 -> 11625112156 | F19: =F17+F18 -> 2740508237 | G19: =G17+G18 -> 8.0581528e+09 | H19: =H17+H18 -> 9.5109448e+09 | I19: =I17+I18 -> 1.1000439e+10 | J19: =J17+J18 -> 1.2537397e+10 | K19: =K17+K18 -> 1.413267e+10 | L19: historis: = laba usaha model IS (cek di Rekonsiliasi; Temuan D9)
A20: P.FIN_INC | B20: Penghasilan keuangan | C20: =IS!C16 -> 0 | D20: =IS!D16 -> 0 | E20: =IS!E16 -> 0 | F20: =IS!F16 -> 13190576716 | G20: =BS_Proj!F6*Asumsi!G30 -> 0 | H20: =BS_Proj!G6*Asumsi!H30 -> 0 | I20: =BS_Proj!H6*Asumsi!I30 -> 0 | J20: =BS_Proj!I6*Asumsi!J30 -> 0 | K20: =BS_Proj!J6*Asumsi!K30 -> 0 | L20: E: imbal hasil x kas awal (0; Temuan D3)
A21: P.FIN_COST | B21: Beban keuangan | C21: =IS!C15 -> -3643595812 | D21: =IS!D15 -> -7565985614 | E21: =IS!E15 -> -11555610977 | F21: =IS!F15 -> -10242145297 | G21: =-Schedules_Proj!G24*Asumsi!G29 -> -7.638617e+09 | H21: =-Schedules_Proj!H24*Asumsi!H29 -> -7.638617e+09 | I21: =-Schedules_Proj!I24*Asumsi!I29 -> -7.638617e+09 | J21: =-Schedules_Proj!J24*Asumsi!J29 -> -7.638617e+09 | K21: =-Schedules_Proj!K24*Asumsi!K29 -> -7.638617e+09 | L21: E: suku bunga x rata-rata utang berbunga termasuk syirkah (Temuan D2)
A22: P.PBT | B22: Laba sebelum pajak | C22: =C19+C20+C21 -> 4728794397 | D22: =D19+D20+D21 -> 2183735441 | E22: =E19+E20+E21 -> 69501179 | F22: =F19+F20+F21 -> 5688939656 | G22: =G19+G20+G21 -> 4.1953574e+08 | H22: =H19+H20+H21 -> 1.8723278e+09 | I22: =I19+I20+I21 -> 3.3618222e+09 | J22: =J19+J20+J21 -> 4.8987801e+09 | K22: =K19+K20+K21 -> 6.4940535e+09
A23: P.TAX | B23: Beban pajak | C23: =IS!C18 -> -1220088106 | D23: =IS!D18 -> -1675692417 | E23: =IS!E18 -> -480368880 | F23: =IS!F18 -> 332957861 | G23: =-MAX(G22,0)*Asumsi!G28 -> -1.0488394e+08 | H23: =-MAX(H22,0)*Asumsi!H28 -> -4.6808195e+08 | I23: =-MAX(I22,0)*Asumsi!I28 -> -8.4045556e+08 | J23: =-MAX(J22,0)*Asumsi!J28 -> -1.224695e+09 | K23: =-MAX(K22,0)*Asumsi!K28 -> -1.6235134e+09
A24: P.MERGING | B24: Laba proforma entitas anak sebelum restrukturisasi | C24: =IS!C19 -> 1379459473 | D24: =IS!D19 -> 3031673373 | E24: =IS!E19 -> 3248230974 | F24: =IS!F19 -> 0 | G24: =0 -> 0 | H24: =0 -> 0 | I24: =0 -> 0 | J24: =0 -> 0 | K24: =0 -> 0 | L24: E: 0 (restrukturisasi selesai 2024; Temuan D1)
A25: P.NI | B25: Laba tahun berjalan | C25: =C22+C23+C24 -> 4888165764 | D25: =D22+D23+D24 -> 3539716397 | E25: =E22+E23+E24 -> 2837363273 | F25: =F22+F23+F24 -> 6021897517 | G25: =G22+G23+G24 -> 3.1465181e+08 | H25: =H22+H23+H24 -> 1.4042458e+09 | I25: =I22+I23+I24 -> 2.5213667e+09 | J25: =J22+J23+J24 -> 3.6740851e+09 | K25: =K22+K23+K24 -> 4.8705401e+09
A26: P.NI_NCI | B26: Diatribusikan ke NCI | C26: =IS!C30 -> 0 | D26: =IS!D30 -> 0 | E26: =IS!E30 -> 131449 | F26: =IS!F30 -> 249404 | G26: =G25*Asumsi!G33 -> 0 | H26: =H25*Asumsi!H33 -> 0 | I26: =I25*Asumsi!I33 -> 0 | J26: =J25*Asumsi!J33 -> 0 | K26: =K25*Asumsi!K33 -> 0
A27: P.NI_PARENT | B27: Diatribusikan ke pemilik entitas induk | C27: =C25-C26 -> 4888165764 | D27: =D25-D26 -> 3539716397 | E27: =E25-E26 -> 2837231824 | F27: =F25-F26 -> 6021648113 | G27: =G25-G26 -> 3.1465181e+08 | H27: =H25-H26 -> 1.4042458e+09 | I27: =I25-I26 -> 2.5213667e+09 | J27: =J25-J26 -> 3.6740851e+09 | K27: =K25-K26 -> 4.8705401e+09
A28: P.EPS | B28: Laba induk per saham (Rp; / 2.550.078.941 saham) | C28: =C27/Asumsi!$C$118 -> 1.9168684 | D28: =D27/Asumsi!$C$118 -> 1.3880811 | E28: =E27/Asumsi!$C$118 -> 1.1126055 | F28: =F27/Asumsi!$C$118 -> 2.3613575 | G28: =G27/Asumsi!$C$118 -> 0.12338905 | H28: =H27/Asumsi!$C$118 -> 0.55066759 | I28: =I27/Asumsi!$C$118 -> 0.98874063 | J28: =J27/Asumsi!$C$118 -> 1.4407731 | K28: =K27/Asumsi!$C$118 -> 1.9099566 | L28: EPS tercetak memakai saham rata-rata tertimbang (IPO 2025)
B29: MARGIN
A30: P.GM_X | B30: Margin laba bruto sebelum penyusutan | C30: =C14/C10 -> 0.35891351 | D30: =D14/D10 -> 0.3651627 | E30: =E14/E10 -> 0.34846633 | F30: =F14/F10 -> 0.30834336 | G30: =G14/G10 -> 0.33 | H30: =H14/H10 -> 0.33 | I30: =I14/I10 -> 0.33 | J30: =J14/J10 -> 0.33 | K30: =K14/K10 -> 0.33
A31: P.EBITDA_M | B31: Margin EBITDA | C31: =C17/C10 -> 0.15214744 | D31: =D17/D10 -> 0.13044716 | E31: =E17/E10 -> 0.14053387 | F31: =F17/F10 -> 0.10591188 | G31: =G17/G10 -> 0.132 | H31: =H17/H10 -> 0.132 | I31: =I17/I10 -> 0.132 | J31: =J17/J10 -> 0.132 | K31: =K17/K10 -> 0.132
A32: P.EBIT_M | B32: Margin EBIT | C32: =C19/C10 -> 0.084078592 | D32: =D19/D10 -> 0.072657349 | E32: =E19/E10 -> 0.076409493 | F32: =F19/F10 -> 0.01891659 | G32: =G19/G10 -> 0.051520754 | H32: =H19/H10 -> 0.056304955 | I32: =I19/I10 -> 0.060298877 | J32: =J19/J10 -> 0.063633063 | K32: =K19/K10 -> 0.06641649
A33: P.NI_M | B33: Margin laba bersih | C33: =C25/C10 -> 0.049088741 | D33: =D25/D10 -> 0.026378848 | E33: =E25/E10 -> 0.018649411 | F33: =F25/F10 -> 0.041566657 | G33: =G25/G10 -> 0.0020117636 | H33: =H25/H10 -> 0.0083131592 | I33: =I25/I10 -> 0.013820864 | J33: =J25/J10 -> 0.018647673 | K33: =K25/K10 -> 0.022889105

Sheet BS_Proj
A1: Proyeksi posisi keuangan agregat (ilustratif)
A2: Rp penuh | kolom A = aktual (link ke IS/BS/CF/Schedules), kolom E = proyeksi | Proyeksi ILUSTRATIF berbasis asumsi transparan - bukan rekomendasi investasi, bukan target, bukan nilai wajar.
A3: Skenario aktif: | C3: =Asumsi!C4 -> Base | G3: ilustratif | H3: ilustratif | I3: ilustratif | J3: ilustratif | K3: ilustratif
A4: Kode | B4: Akun | C4: FY2022A | D4: FY2023A | E4: FY2024A | F4: FY2025A | G4: FY2026E | H4: FY2027E | I4: FY2028E | J4: FY2029E | K4: FY2030E | L4: Catatan / sumber
B5: ASET
A6: PB.CASH | B6: Kas dan setara kas | C6: =BS!C6 -> 29547207476 | D6: =BS!D6 -> 2463973775 | E6: =BS!E6 -> 2663388349 | F6: =BS!F6 -> 4036506961 | G6: =CF_Proj!G24 -> -2.0195699e+09 | H6: =CF_Proj!H24 -> -5.0444379e+09 | I6: =CF_Proj!I24 -> -8.0351331e+09 | J6: =CF_Proj!J24 -> -1.0970998e+10 | K6: =CF_Proj!K24 -> -1.3831484e+10 | L6: E: penyeimbang dari CF_Proj
A7: PB.AR | B7: Piutang usaha (pihak ketiga + berelasi) | C7: =(BS!C8+BS!C9) -> 12118406500 | D7: =(BS!D8+BS!D9) -> 16783681668 | E7: =(BS!E8+BS!E9) -> 25075858587 | F7: =(BS!F8+BS!F9) -> 18872446355 | G7: =Schedules_Proj!G26 -> 2.1425474e+10 | H7: =Schedules_Proj!H26 -> 2.3139511e+10 | I7: =Schedules_Proj!I26 -> 2.4990672e+10 | J7: =Schedules_Proj!J26 -> 2.6989926e+10 | K7: =Schedules_Proj!K26 -> 2.914912e+10
A8: PB.INV | B8: Persediaan | C8: =BS!C12 -> 2264889867 | D8: =BS!D12 -> 4036032457 | E8: =BS!E12 -> 4135618544 | F8: =BS!F12 -> 1336242114 | G8: =Schedules_Proj!G27 -> 2.8710135e+09 | H8: =Schedules_Proj!H27 -> 3.1006945e+09 | I8: =Schedules_Proj!I27 -> 3.3487501e+09 | J8: =Schedules_Proj!J27 -> 3.6166501e+09 | K8: =Schedules_Proj!K27 -> 3.9059821e+09
A9: PB.OCA | B9: Aset lancar lainnya | C9: =BS!C16-BS!C6-BS!C8-BS!C9-BS!C12 -> 1685855107 | D9: =BS!D16-BS!D6-BS!D8-BS!D9-BS!D12 -> 4616338154 | E9: =BS!E16-BS!E6-BS!E8-BS!E9-BS!E12 -> 3217661624 | F9: =BS!F16-BS!F6-BS!F8-BS!F9-BS!F12 -> 15099657194 | G9: =F9 -> 15099657194 | H9: =G9 -> 15099657194 | I9: =H9 -> 15099657194 | J9: =I9 -> 15099657194 | K9: =J9 -> 15099657194 | L9: E: konstan
A10: PB.TCA | B10: Jumlah aset lancar | C10: =C6+C7+C8+C9 -> 45616358950 | D10: =D6+D7+D8+D9 -> 27900026054 | E10: =E6+E7+E8+E9 -> 35092527104 | F10: =F6+F7+F8+F9 -> 39344852624 | G10: =G6+G7+G8+G9 -> 3.7376574e+10 | H10: =H6+H7+H8+H9 -> 3.6295425e+10 | I10: =I6+I7+I8+I9 -> 3.5403947e+10 | J10: =J6+J7+J8+J9 -> 3.4735236e+10 | K10: =K6+K7+K8+K9 -> 3.4323275e+10
A11: PB.PPE | B11: Aset tetap - neto | C11: =BS!C21 -> 66252356120 | D11: =BS!D21 -> 117418739194 | E11: =BS!E21 -> 132385666764 | F11: =BS!F21 -> 127921073027 | G11: =Schedules_Proj!G10 -> 1.2994196e+11 | H11: =Schedules_Proj!H10 -> 1.3293265e+11 | I11: =Schedules_Proj!I10 -> 1.3689122e+11 | J11: =Schedules_Proj!J10 -> 1.4182339e+11 | K11: =Schedules_Proj!K10 -> 1.4774242e+11
A12: PB.INTANG | B12: Aset takberwujud | C12: =BS!C17 -> 0 | D12: =BS!D17 -> 0 | E12: =BS!E17 -> 0 | F12: =BS!F17 -> 0 | G12: =Schedules_Proj!G15 -> 0 | H12: =Schedules_Proj!H15 -> 0 | I12: =Schedules_Proj!I15 -> 0 | J12: =Schedules_Proj!J15 -> 0 | K12: =Schedules_Proj!K15 -> 0
A13: PB.ONCA | B13: Aset tidak lancar lain (piutang pihak berelasi, uang muka aset, aset hak guna, pajak tangguhan, uang muka investasi 2022-23) | C13: =BS!C26-BS!C21-BS!C17 -> 48124674181 | D13: =BS!D26-BS!D21-BS!D17 -> 155351127589 | E13: =BS!E26-BS!E21-BS!E17 -> 100622046044 | F13: =BS!F26-BS!F21-BS!F17 -> 162946944844 | G13: =F13 -> 162946944844 | H13: =G13 -> 162946944844 | I13: =H13 -> 162946944844 | J13: =I13 -> 162946944844 | K13: =J13 -> 162946944844 | L13: E: konstan
A14: PB.TNCA | B14: Jumlah aset tidak lancar | C14: =C11+C12+C13 -> 114377030301 | D14: =D11+D12+D13 -> 272769866783 | E14: =E11+E12+E13 -> 233007712808 | F14: =F11+F12+F13 -> 290868017871 | G14: =G11+G12+G13 -> 2.928889e+11 | H14: =H11+H12+H13 -> 2.9587959e+11 | I14: =I11+I12+I13 -> 2.9983816e+11 | J14: =J11+J12+J13 -> 3.0477034e+11 | K14: =K11+K12+K13 -> 3.1068937e+11
A15: PB.TA | B15: JUMLAH ASET | C15: =C10+C14 -> 159993389251 | D15: =D10+D14 -> 300669892837 | E15: =E10+E14 -> 268100239912 | F15: =F10+F14 -> 330212870495 | G15: =G10+G14 -> 3.3026548e+11 | H15: =H10+H14 -> 3.3217502e+11 | I15: =I10+I14 -> 3.3524211e+11 | J15: =J10+J14 -> 3.3950557e+11 | K15: =K10+K14 -> 3.4501264e+11
B16: LIABILITAS
A17: PB.AP | B17: Utang usaha (pihak ketiga + berelasi) | C17: =(BS!C30+BS!C31) -> 2059291014 | D17: =(BS!D30+BS!D31) -> 4772562529 | E17: =(BS!E30+BS!E31) -> 5668668826 | F17: =(BS!F30+BS!F31) -> 6578276878 | G17: =Schedules_Proj!G28 -> 6.3162296e+09 | H17: =Schedules_Proj!H28 -> 6.821528e+09 | I17: =Schedules_Proj!I28 -> 7.3672502e+09 | J17: =Schedules_Proj!J28 -> 7.9566302e+09 | K17: =Schedules_Proj!K28 -> 8.5931607e+09
A18: PB.DEBT | B18: Utang berbunga (bank, pembiayaan konsumen, syirkah) | C18: =(BS!C29+BS!C38+BS!C43+BS!C39+BS!C44+BS!C40+BS!C45+BS!C49+BS!C50) -> 93671342320 | D18: =(BS!D29+BS!D38+BS!D43+BS!D39+BS!D44+BS!D40+BS!D45+BS!D49+BS!D50) -> 145115583789 | E18: =(BS!E29+BS!E38+BS!E43+BS!E39+BS!E44+BS!E40+BS!E45+BS!E49+BS!E50) -> 111845439271 | F18: =(BS!F29+BS!F38+BS!F43+BS!F39+BS!F44+BS!F40+BS!F45+BS!F49+BS!F50) -> 89971932007 | G18: =Schedules_Proj!G23 -> 89971932007 | H18: =Schedules_Proj!H23 -> 89971932007 | I18: =Schedules_Proj!I23 -> 89971932007 | J18: =Schedules_Proj!J23 -> 89971932007 | K18: =Schedules_Proj!K23 -> 89971932007
A19: PB.LEASE | B19: Liabilitas sewa | C19: =(BS!C41+BS!C46) -> 0 | D19: =(BS!D41+BS!D46) -> 0 | E19: =(BS!E41+BS!E46) -> 2328487150 | F19: =(BS!F41+BS!F46) -> 1329650108 | G19: =Schedules_Proj!G18 -> 1329650108 | H19: =Schedules_Proj!H18 -> 1329650108 | I19: =Schedules_Proj!I18 -> 1329650108 | J19: =Schedules_Proj!J18 -> 1329650108 | K19: =Schedules_Proj!K18 -> 1329650108
A20: PB.OL | B20: Liabilitas lainnya | C20: =BS!C52-BS!C30-BS!C31-(BS!C29+BS!C38+BS!C43+BS!C39+BS!C44+BS!C40+BS!C45+BS!C49+BS!C50)-BS!C41-BS!C46 -> 13196011190 | D20: =BS!D52-BS!D30-BS!D31-(BS!D29+BS!D38+BS!D43+BS!D39+BS!D44+BS!D40+BS!D45+BS!D49+BS!D50)-BS!D41-BS!D46 -> 21628740131 | E20: =BS!E52-BS!E30-BS!E31-(BS!E29+BS!E38+BS!E43+BS!E39+BS!E44+BS!E40+BS!E45+BS!E49+BS!E50)-BS!E41-BS!E46 -> 18528254195 | F20: =BS!F52-BS!F30-BS!F31-(BS!F29+BS!F38+BS!F43+BS!F39+BS!F44+BS!F40+BS!F45+BS!F49+BS!F50)-BS!F41-BS!F46 -> 25827020582 | G20: =F20 -> 25827020582 | H20: =G20 -> 25827020582 | I20: =H20 -> 25827020582 | J20: =I20 -> 25827020582 | K20: =J20 -> 25827020582 | L20: utang lain, akrual, pajak, liabilitas kontrak, imbalan kerja; E: konstan
A21: PB.TL | B21: JUMLAH LIABILITAS | C21: =C17+C18+C19+C20 -> 108926644524 | D21: =D17+D18+D19+D20 -> 171516886449 | E21: =E17+E18+E19+E20 -> 138370849442 | F21: =F17+F18+F19+F20 -> 123706879575 | G21: =G17+G18+G19+G20 -> 1.2344483e+11 | H21: =H17+H18+H19+H20 -> 1.2395013e+11 | I21: =I17+I18+I19+I20 -> 1.2449585e+11 | J21: =J17+J18+J19+J20 -> 1.2508523e+11 | K21: =K17+K18+K19+K20 -> 1.2572176e+11
B22: EKUITAS
A23: PB.EQ_OTHER | B23: Modal & cadangan (selain saldo laba; termasuk surplus revaluasi & ekuitas proforma) | C23: =BS!C59-BS!C58 -> 31525576875 | D23: =BS!D59-BS!D58 -> 106072122139 | E23: =BS!E59-BS!E58 -> 103807584338 | F23: =BS!F59-BS!F58 -> 174562244493 | G23: =F23 -> 174562244493 | H23: =G23 -> 174562244493 | I23: =H23 -> 174562244493 | J23: =I23 -> 174562244493 | K23: =J23 -> 174562244493 | L23: E: konstan
A24: PB.RE | B24: Saldo laba | C24: =BS!C58 -> 19541167852 | D24: =BS!D58 -> 23080884249 | E24: =BS!E58 -> 25918247522 | F24: =BS!F58 -> 31939895635 | G24: =F24+IS_Proj!G27+CF_Proj!G19 -> 3.2254547e+10 | H24: =G24+IS_Proj!H27+CF_Proj!H19 -> 3.3658793e+10 | I24: =H24+IS_Proj!I27+CF_Proj!I19 -> 3.618016e+10 | J24: =I24+IS_Proj!J27+CF_Proj!J19 -> 3.9854245e+10 | K24: =J24+IS_Proj!K27+CF_Proj!K19 -> 4.4724785e+10
A25: PB.EQ_PARENT | B25: Ekuitas pemilik entitas induk | C25: =C23+C24 -> 51066744727 | D25: =D23+D24 -> 129153006388 | E25: =E23+E24 -> 129725831860 | F25: =F23+F24 -> 206502140128 | G25: =G23+G24 -> 2.0681679e+11 | H25: =H23+H24 -> 2.0822104e+11 | I25: =I23+I24 -> 2.107424e+11 | J25: =J23+J24 -> 2.1441649e+11 | K25: =K23+K24 -> 2.1928703e+11
A26: PB.NCI | B26: Kepentingan nonpengendali | C26: =BS!C60 -> 0 | D26: =BS!D60 -> 0 | E26: =BS!E60 -> 3558610 | F26: =BS!F60 -> 3850792 | G26: =F26+IS_Proj!G26 -> 3850792 | H26: =G26+IS_Proj!H26 -> 3850792 | I26: =H26+IS_Proj!I26 -> 3850792 | J26: =I26+IS_Proj!J26 -> 3850792 | K26: =J26+IS_Proj!K26 -> 3850792 | L26: E: tanpa dividen ke NCI (ilustratif)
A27: PB.TE | B27: JUMLAH EKUITAS | C27: =C25+C26 -> 51066744727 | D27: =D25+D26 -> 129153006388 | E27: =E25+E26 -> 129729390470 | F27: =F25+F26 -> 206505990920 | G27: =G25+G26 -> 2.0682064e+11 | H27: =H25+H26 -> 2.0822489e+11 | I27: =I25+I26 -> 2.1074626e+11 | J27: =J25+J26 -> 2.1442034e+11 | K27: =K25+K26 -> 2.1929088e+11
A28: PB.TLE | B28: JUMLAH LIABILITAS DAN EKUITAS | C28: =C21+C27 -> 159993389251 | D28: =D21+D27 -> 300669892837 | E28: =E21+E27 -> 268100239912 | F28: =F21+F27 -> 330212870495 | G28: =G21+G27 -> 3.3026548e+11 | H28: =H21+H27 -> 3.3217502e+11 | I28: =I21+I27 -> 3.3524211e+11 | J28: =J21+J27 -> 3.3950557e+11 | K28: =K21+K27 -> 3.4501264e+11
A30: PB.CHECK | B30: Cek: aset - (liabilitas + ekuitas), harus 0 | C30: =ROUND(C15-C28,0) -> 0 | D30: =ROUND(D15-D28,0) -> 0 | E30: =ROUND(E15-E28,0) -> 0 | F30: =ROUND(F15-F28,0) -> 0 | G30: =ROUND(G15-G28,0) -> 0 | H30: =ROUND(H15-H28,0) -> 0 | I30: =ROUND(I15-I28,0) -> 0 | J30: =ROUND(J15-J28,0) -> 0 | K30: =ROUND(K15-K28,0) -> 0
A31: PB.NETDEBT | B31: Memo: utang neto (utang + sewa - kas) | C31: =C18+C19-C6 -> 64124134844 | D31: =D18+D19-D6 -> 142651610014 | E31: =E18+E19-E6 -> 111510538072 | F31: =F18+F19-F6 -> 87265075154 | G31: =G18+G19-G6 -> 9.3321152e+10 | H31: =H18+H19-H6 -> 9.634602e+10 | I31: =I18+I19-I6 -> 9.9336715e+10 | J31: =J18+J19-J6 -> 1.0227258e+11 | K31: =K18+K19-K6 -> 1.0513307e+11
A32: PB.ROE | B32: Memo: ROE (laba induk / rata-rata ekuitas induk) | D32: =IS_Proj!D27/AVERAGE(C25,D25) -> 0.039282225 | E32: =IS_Proj!E27/AVERAGE(D25,E25) -> 0.02191938 | F32: =IS_Proj!F27/AVERAGE(E25,F25) -> 0.035818841 | G32: =IS_Proj!G27/AVERAGE(F25,G25) -> 0.0015225618 | H32: =IS_Proj!H27/AVERAGE(G25,H25) -> 0.006766833 | I32: =IS_Proj!I27/AVERAGE(H25,I25) -> 0.012036213 | J32: =IS_Proj!J27/AVERAGE(I25,J25) -> 0.017283351 | K32: =IS_Proj!K27/AVERAGE(J25,K25) -> 0.022460229
A33: PB.ND_EBITDA | B33: Memo: utang neto / EBITDA | C33: =C31/IS_Proj!C17 -> 4.2324598 | D33: =D31/IS_Proj!D17 -> 8.1494706 | E33: =E31/IS_Proj!E17 -> 5.2153695 | F33: =F31/IS_Proj!F17 -> 5.6873182 | G33: =G31/IS_Proj!G17 -> 4.5201502 | H33: =H31/IS_Proj!H17 -> 4.3209854 | I33: =I31/IS_Proj!I17 -> 4.1251055 | J33: =J31/IS_Proj!J17 -> 3.9324275 | K33: =K31/IS_Proj!K17 -> 3.7429764

Sheet CF_Proj
A1: Proyeksi arus kas (metode tidak langsung untuk tahun E)
A2: Rp penuh | kolom A = aktual (link ke IS/BS/CF/Schedules), kolom E = proyeksi | Proyeksi ILUSTRATIF berbasis asumsi transparan - bukan rekomendasi investasi, bukan target, bukan nilai wajar.
A3: Skenario aktif: | C3: =Asumsi!C4 -> Base | G3: ilustratif | H3: ilustratif | I3: ilustratif | J3: ilustratif | K3: ilustratif
A4: Kode | B4: Akun | C4: FY2022A | D4: FY2023A | E4: FY2024A | F4: FY2025A | G4: FY2026E | H4: FY2027E | I4: FY2028E | J4: FY2029E | K4: FY2030E | L4: Catatan / sumber
B5: ARUS KAS OPERASI
A6: PC.NI | B6: Laba tahun berjalan | C6: =IS_Proj!C25 -> 4888165764 | D6: =IS_Proj!D25 -> 3539716397 | E6: =IS_Proj!E25 -> 2837363273 | F6: =IS_Proj!F25 -> 6021897517 | G6: =IS_Proj!G25 -> 3.1465181e+08 | H6: =IS_Proj!H25 -> 1.4042458e+09 | I6: =IS_Proj!I25 -> 2.5213667e+09 | J6: =IS_Proj!J25 -> 3.6740851e+09 | K6: =IS_Proj!K25 -> 4.8705401e+09
A7: PC.DA | B7: Penyusutan & amortisasi (nonkas) | G7: =-IS_Proj!G18 -> 1.2587434e+10 | H7: =-IS_Proj!H18 -> 1.2786288e+10 | I7: =-IS_Proj!I18 -> 1.3080573e+10 | J7: =-IS_Proj!J18 -> 1.3470096e+10 | K7: =-IS_Proj!K18 -> 1.3955422e+10
A8: PC.D_AR | B8: (Kenaikan) piutang usaha | G8: =BS_Proj!F7-BS_Proj!G7 -> -2.5530272e+09 | H8: =BS_Proj!G7-BS_Proj!H7 -> -1.7140379e+09 | I8: =BS_Proj!H7-BS_Proj!I7 -> -1.8511609e+09 | J8: =BS_Proj!I7-BS_Proj!J7 -> -1.9992538e+09 | K8: =BS_Proj!J7-BS_Proj!K7 -> -2.1591941e+09
A9: PC.D_INV | B9: (Kenaikan) persediaan | G9: =BS_Proj!F8-BS_Proj!G8 -> -1.5347713e+09 | H9: =BS_Proj!G8-BS_Proj!H8 -> -2.2968108e+08 | I9: =BS_Proj!H8-BS_Proj!I8 -> -2.4805556e+08 | J9: =BS_Proj!I8-BS_Proj!J8 -> -2.6790001e+08 | K9: =BS_Proj!J8-BS_Proj!K8 -> -2.8933201e+08
A10: PC.D_AP | B10: Kenaikan utang usaha | G10: =BS_Proj!G17-BS_Proj!F17 -> -2.6204726e+08 | H10: =BS_Proj!H17-BS_Proj!G17 -> 5.0529837e+08 | I10: =BS_Proj!I17-BS_Proj!H17 -> 5.4572224e+08 | J10: =BS_Proj!J17-BS_Proj!I17 -> 5.8938002e+08 | K10: =BS_Proj!K17-BS_Proj!J17 -> 6.3653042e+08
A11: PC.CFO | B11: Arus kas operasi | C11: =CF!C14 -> 7734100083 | D11: =CF!D14 -> 19735705441 | E11: =CF!E14 -> 2997687548 | F11: =CF!F14 -> 5567951370 | G11: =G6+G7+G8+G9+G10 -> 8.5522395e+09 | H11: =H6+H7+H8+H9+H10 -> 1.2752114e+10 | I11: =I6+I7+I8+I9+I10 -> 1.4048445e+10 | J11: =J6+J7+J8+J9+J10 -> 1.5466407e+10 | K11: =K6+K7+K8+K9+K10 -> 1.7013966e+10 | L11: historis: laporan (metode langsung); E: tidak langsung
B12: ARUS KAS INVESTASI
A13: PC.CAPEX | B13: Capex aset tetap + uang muka | C13: =CF!C16+CF!C17 -> -16981553674 | D13: =CF!D16+CF!D17 -> -36146492177 | E13: =CF!E16+CF!E17 -> -24447662378 | F13: =CF!F16+CF!F17 -> -27390827865 | G13: =-Schedules_Proj!G7 -> -1.4076536e+10 | H13: =-Schedules_Proj!H7 -> -1.5202659e+10 | I13: =-Schedules_Proj!I7 -> -1.6418872e+10 | J13: =-Schedules_Proj!J7 -> -1.7732382e+10 | K13: =-Schedules_Proj!K7 -> -1.9150972e+10
A14: PC.SW | B14: Perolehan aset takberwujud | C14: =CF!C19 -> 0 | D14: =CF!D19 -> 0 | E14: =CF!E19 -> 0 | F14: =CF!F19 -> 0 | G14: =-Schedules_Proj!G14 -> 0 | H14: =-Schedules_Proj!H14 -> 0 | I14: =-Schedules_Proj!I14 -> 0 | J14: =-Schedules_Proj!J14 -> 0 | K14: =-Schedules_Proj!K14 -> 0
A15: PC.CFI | B15: Arus kas investasi | C15: =CF!C24 -> -16981553674 | D15: =CF!D24 -> -36146492177 | E15: =CF!E24 -> -26160414859 | F15: =CF!F24 -> -27390827865 | G15: =G13+G14 -> -1.4076536e+10 | H15: =H13+H14 -> -1.5202659e+10 | I15: =I13+I14 -> -1.6418872e+10 | J15: =J13+J14 -> -1.7732382e+10 | K15: =K13+K14 -> -1.9150972e+10 | L15: historis: total laporan
B16: ARUS KAS PENDANAAN
A17: PC.DEBT | B17: Perubahan neto utang berbunga (kas) | C17: =(CF!C26+CF!C27+CF!C28+CF!C29+CF!C30+CF!C31+CF!C32+CF!C33+CF!C34+CF!C35) -> 24039069796 | D17: =(CF!D26+CF!D27+CF!D28+CF!D29+CF!D30+CF!D31+CF!D32+CF!D33+CF!D34+CF!D35) -> 58444061469 | E17: =(CF!E26+CF!E27+CF!E28+CF!E29+CF!E30+CF!E31+CF!E32+CF!E33+CF!E34+CF!E35) -> -3270309520 | F17: =(CF!F26+CF!F27+CF!F28+CF!F29+CF!F30+CF!F31+CF!F32+CF!F33+CF!F34+CF!F35) -> -21873507263 | G17: =Asumsi!G31 -> 0 | H17: =Asumsi!H31 -> 0 | I17: =Asumsi!I31 -> 0 | J17: =Asumsi!J31 -> 0 | K17: =Asumsi!K31 -> 0
A18: PC.LEASE | B18: Pembayaran sewa | C18: =CF!C40 -> -163528380 | D18: =CF!D40 -> 0 | E18: =CF!E40 -> -505637369 | F18: =CF!F40 -> -998837042 | G18: =-Schedules_Proj!G8 -> -5.3178025e+08 | H18: =-Schedules_Proj!H8 -> -5.7432268e+08 | I18: =-Schedules_Proj!I8 -> -6.2026849e+08 | J18: =-Schedules_Proj!J8 -> -6.6988997e+08 | K18: =-Schedules_Proj!K8 -> -7.2348117e+08
A19: PC.DIV | B19: Dividen dibayar | C19: =CF!C41 -> 0 | D19: =CF!D41 -> 0 | E19: =CF!E41 -> 0 | F19: =CF!F41 -> 0 | G19: =-Asumsi!G32*MAX(IS_Proj!F27,0) -> 0 | H19: =-Asumsi!H32*MAX(IS_Proj!G27,0) -> 0 | I19: =-Asumsi!I32*MAX(IS_Proj!H27,0) -> 0 | J19: =-Asumsi!J32*MAX(IS_Proj!I27,0) -> 0 | K19: =-Asumsi!K32*MAX(IS_Proj!J27,0) -> 0
A20: PC.CFF | B20: Arus kas pendanaan | C20: =CF!C43 -> -11058092740 | D20: =CF!D43 -> -13672626965 | E20: =CF!E43 -> 23362141885 | F20: =CF!F43 -> 23195995107 | G20: =G17+G18+G19 -> -5.3178025e+08 | H20: =H17+H18+H19 -> -5.7432268e+08 | I20: =I17+I18+I19 -> -6.2026849e+08 | J20: =J17+J18+J19 -> -6.6988997e+08 | K20: =K17+K18+K19 -> -7.2348117e+08 | L20: historis: total laporan
A22: PC.NET | B22: Kenaikan (penurunan) neto kas | C22: =C11+C15+C20 -> -20305546331 | D22: =D11+D15+D20 -> -30083413701 | E22: =E11+E15+E20 -> 199414574 | F22: =F11+F15+F20 -> 1373118612 | G22: =G11+G15+G20 -> -6.0560769e+09 | H22: =H11+H15+H20 -> -3.024868e+09 | I22: =I11+I15+I20 -> -2.9906952e+09 | J22: =J11+J15+J20 -> -2.9358644e+09 | K22: =K11+K15+K20 -> -2.860487e+09
A23: PC.CASH_BEGIN | B23: Kas awal tahun | C23: =CF!C45 -> 59602857240 | D23: =CF!D45 -> 29547207476 | E23: =CF!E45 -> 2463973775 | F23: =CF!F45 -> 2663388349 | G23: =BS_Proj!F6 -> 4036506961 | H23: =BS_Proj!G6 -> -2.0195699e+09 | I23: =BS_Proj!H6 -> -5.0444379e+09 | J23: =BS_Proj!I6 -> -8.0351331e+09 | K23: =BS_Proj!J6 -> -1.0970998e+10 | L23: E: kas neraca
A24: PC.CASH_END | B24: Kas akhir tahun | C24: =C23+C22 -> 39297310909 | D24: =D23+D22 -> -536206225 | E24: =E23+E22 -> 2663388349 | F24: =F23+F22 -> 4036506961 | G24: =G23+G22 -> -2.0195699e+09 | H24: =H23+H22 -> -5.0444379e+09 | I24: =I23+I22 -> -8.0351331e+09 | J24: =J23+J22 -> -1.0970998e+10 | K24: =K23+K22 -> -1.3831484e+10
B25: MEMO: ARUS KAS BEBAS
A26: PC.FCF | B26: FCF = arus kas operasi + capex | C26: =C11+C13+N(C14) -> -9247453591 | D26: =D11+D13+N(D14) -> -16410786736 | E26: =E11+E13+N(E14) -> -21449974830 | F26: =F11+F13+N(F14) -> -21822876495 | G26: =G11+G13+G14 -> -5.5242966e+09 | H26: =H11+H13+H14 -> -2.4505453e+09 | I26: =I11+I13+I14 -> -2.3704267e+09 | J26: =J11+J13+J14 -> -2.2659745e+09 | K26: =K11+K13+K14 -> -2.1370058e+09
A27: PC.FCF_L | B27: FCF setelah pembayaran sewa | C27: =C26+C18 -> -9410981971 | D27: =D26+D18 -> -16410786736 | E27: =E26+E18 -> -21955612199 | F27: =F26+F18 -> -22821713537 | G27: =G26+G18 -> -6.0560769e+09 | H27: =H26+H18 -> -3.024868e+09 | I27: =I26+I18 -> -2.9906952e+09 | J27: =J26+J18 -> -2.9358644e+09 | K27: =K26+K18 -> -2.860487e+09

Sheet Schedules_Proj
A1: Schedule proyeksi: aset tetap, ROU & sewa, utang, modal kerja
A2: Rp penuh | kolom A = aktual (link ke IS/BS/CF/Schedules), kolom E = proyeksi | Proyeksi ILUSTRATIF berbasis asumsi transparan - bukan rekomendasi investasi, bukan target, bukan nilai wajar.
A3: Skenario aktif: | C3: =Asumsi!C4 -> Base | G3: ilustratif | H3: ilustratif | I3: ilustratif | J3: ilustratif | K3: ilustratif
A4: Kode | B4: Akun | C4: FY2022A | D4: FY2023A | E4: FY2024A | F4: FY2025A | G4: FY2026E | H4: FY2027E | I4: FY2028E | J4: FY2029E | K4: FY2030E | L4: Catatan / sumber
B5: ASET TETAP (aset hak guna konstan di aset tidak lancar lain)
A6: S.PPE_BEG | B6: Aset tetap neto awal | G6: =BS_Proj!F11 -> 127921073027 | H6: =BS_Proj!G11 -> 1.2994196e+11 | I6: =BS_Proj!H11 -> 1.3293265e+11 | J6: =BS_Proj!I11 -> 1.3689122e+11 | K6: =BS_Proj!J11 -> 1.4182339e+11
A7: S.CAPEX | B7: Capex (kas) | C7: =-(CF!C16+CF!C17) -> 16981553674 | D7: =-(CF!D16+CF!D17) -> 36146492177 | E7: =-(CF!E16+CF!E17) -> 24447662378 | F7: =-(CF!F16+CF!F17) -> 27390827865 | G7: =Asumsi!G19*IS_Proj!G10 -> 1.4076536e+10 | H7: =Asumsi!H19*IS_Proj!H10 -> 1.5202659e+10 | I7: =Asumsi!I19*IS_Proj!I10 -> 1.6418872e+10 | J7: =Asumsi!J19*IS_Proj!J10 -> 1.7732382e+10 | K7: =Asumsi!K19*IS_Proj!K10 -> 1.9150972e+10
A8: S.LEASE_PD | B8: Pembayaran sewa (dikapitalisasi ke aset tetap) | C8: =-CF!C40 -> 163528380 | D8: =-CF!D40 -> 0 | E8: =-CF!E40 -> 505637369 | F8: =-CF!F40 -> 998837042 | G8: =Asumsi!G20*IS_Proj!G10 -> 5.3178025e+08 | H8: =Asumsi!H20*IS_Proj!H10 -> 5.7432268e+08 | I8: =Asumsi!I20*IS_Proj!I10 -> 6.2026849e+08 | J8: =Asumsi!J20*IS_Proj!J10 -> 6.6988997e+08 | K8: =Asumsi!K20*IS_Proj!K10 -> 7.2348117e+08
A9: S.DEP | B9: Penyusutan aset tetap + aset hak guna | C9: =Schedules!C14+Schedules!C16 -> 6778169378 | D9: =Schedules!D14+Schedules!D16 -> 7754681103 | E9: =Schedules!E14+Schedules!E16 -> 9756026475 | F9: =Schedules!F14+Schedules!F16 -> 12603292085 | G9: =G6*Asumsi!G21 -> 1.2587434e+10 | H9: =H6*Asumsi!H21 -> 1.2786288e+10 | I9: =I6*Asumsi!I21 -> 1.3080573e+10 | J9: =J6*Asumsi!J21 -> 1.3470096e+10 | K9: =K6*Asumsi!K21 -> 1.3955422e+10
A10: S.PPE_END | B10: Aset tetap neto akhir | C10: =BS!C21 -> 66252356120 | D10: =BS!D21 -> 117418739194 | E10: =BS!E21 -> 132385666764 | F10: =BS!F21 -> 127921073027 | G10: =G6+G7+G8-G9 -> 1.2994196e+11 | H10: =H6+H7+H8-H9 -> 1.3293265e+11 | I10: =I6+I7+I8-I9 -> 1.3689122e+11 | J10: =J6+J7+J8-J9 -> 1.4182339e+11 | K10: =K6+K7+K8-K9 -> 1.4774242e+11 | L10: historis: neraca (memuat penambahan nonkas, pelepasan, penurunan nilai)
B11: ASET TAKBERWUJUD
A12: S.INT_BEG | B12: Aset takberwujud awal | G12: =BS_Proj!F12 -> 0 | H12: =BS_Proj!G12 -> 0 | I12: =BS_Proj!H12 -> 0 | J12: =BS_Proj!I12 -> 0 | K12: =BS_Proj!J12 -> 0
A13: S.SW_AMORT | B13: Amortisasi | C13: =Schedules!C19 -> 0 | D13: =Schedules!D19 -> 0 | E13: =Schedules!E19 -> 0 | F13: =Schedules!F19 -> 0 | G13: =G12*Asumsi!G22 -> 0 | H13: =H12*Asumsi!H22 -> 0 | I13: =I12*Asumsi!I22 -> 0 | J13: =J12*Asumsi!J22 -> 0 | K13: =K12*Asumsi!K22 -> 0
A14: S.SW_CAPEX | B14: Penambahan (= amortisasi) | G14: =G13 -> 0 | H14: =H13 -> 0 | I14: =I13 -> 0 | J14: =J13 -> 0 | K14: =K13 -> 0
A15: S.INT_END | B15: Aset takberwujud akhir | C15: =BS!C17 -> 0 | D15: =BS!D17 -> 0 | E15: =BS!E17 -> 0 | F15: =BS!F17 -> 0 | G15: =G12+G14-G13 -> 0 | H15: =H12+H14-H13 -> 0 | I15: =I12+I14-I13 -> 0 | J15: =J12+J14-J13 -> 0 | K15: =K12+K14-K13 -> 0
B16: LIABILITAS SEWA
A17: S.LEASE_BEG | B17: Liabilitas sewa awal | G17: =BS_Proj!F19 -> 1329650108 | H17: =BS_Proj!G19 -> 1329650108 | I17: =BS_Proj!H19 -> 1329650108 | J17: =BS_Proj!I19 -> 1329650108 | K17: =BS_Proj!J19 -> 1329650108
A18: S.LEASE_END | B18: Liabilitas sewa akhir | C18: =(BS!C41+BS!C46) -> 0 | D18: =(BS!D41+BS!D46) -> 0 | E18: =(BS!E41+BS!E46) -> 2328487150 | F18: =(BS!F41+BS!F46) -> 1329650108 | G18: =G17 -> 1329650108 | H18: =H17 -> 1329650108 | I18: =I17 -> 1329650108 | J18: =J17 -> 1329650108 | K18: =K17 -> 1329650108 | L18: E: konstan (pembayaran sewa dikapitalisasi ke aset tetap)
A19: S.LEASE_AVG | B19: Rata-rata liabilitas sewa | D19: =AVERAGE((BS!C41+BS!C46),D18) -> 0 | E19: =AVERAGE((BS!D41+BS!D46),E18) -> 1164243575 | F19: =AVERAGE((BS!E41+BS!E46),F18) -> 1829068629 | G19: =AVERAGE(G17,G18) -> 1329650108 | H19: =AVERAGE(H17,H18) -> 1329650108 | I19: =AVERAGE(I17,I18) -> 1329650108 | J19: =AVERAGE(J17,J18) -> 1329650108 | K19: =AVERAGE(K17,K18) -> 1329650108
B20: UTANG BERBUNGA
A21: S.DEBT_BEG | B21: Utang awal | G21: =BS_Proj!F18 -> 89971932007 | H21: =BS_Proj!G18 -> 89971932007 | I21: =BS_Proj!H18 -> 89971932007 | J21: =BS_Proj!I18 -> 89971932007 | K21: =BS_Proj!J18 -> 89971932007
A22: S.DEBT_CHG | B22: Perubahan neto (tarik / (bayar)) | G22: =Asumsi!G31 -> 0 | H22: =Asumsi!H31 -> 0 | I22: =Asumsi!I31 -> 0 | J22: =Asumsi!J31 -> 0 | K22: =Asumsi!K31 -> 0
A23: S.DEBT_END | B23: Utang akhir | C23: =(BS!C29+BS!C38+BS!C43+BS!C39+BS!C44+BS!C40+BS!C45+BS!C49+BS!C50) -> 93671342320 | D23: =(BS!D29+BS!D38+BS!D43+BS!D39+BS!D44+BS!D40+BS!D45+BS!D49+BS!D50) -> 145115583789 | E23: =(BS!E29+BS!E38+BS!E43+BS!E39+BS!E44+BS!E40+BS!E45+BS!E49+BS!E50) -> 111845439271 | F23: =(BS!F29+BS!F38+BS!F43+BS!F39+BS!F44+BS!F40+BS!F45+BS!F49+BS!F50) -> 89971932007 | G23: =G21+G22 -> 89971932007 | H23: =H21+H22 -> 89971932007 | I23: =I21+I22 -> 89971932007 | J23: =J21+J22 -> 89971932007 | K23: =K21+K22 -> 89971932007
A24: S.DEBT_AVG | B24: Rata-rata utang | D24: =AVERAGE((BS!C29+BS!C38+BS!C43+BS!C39+BS!C44+BS!C40+BS!C45+BS!C49+BS!C50),D23) -> 1.1939346e+11 | E24: =AVERAGE((BS!D29+BS!D38+BS!D43+BS!D39+BS!D44+BS!D40+BS!D45+BS!D49+BS!D50),E23) -> 128480511530 | F24: =AVERAGE((BS!E29+BS!E38+BS!E43+BS!E39+BS!E44+BS!E40+BS!E45+BS!E49+BS!E50),F23) -> 100908685639 | G24: =AVERAGE(G21,G23) -> 89971932007 | H24: =AVERAGE(H21,H23) -> 89971932007 | I24: =AVERAGE(I21,I23) -> 89971932007 | J24: =AVERAGE(J21,J23) -> 89971932007 | K24: =AVERAGE(K21,K23) -> 89971932007
B25: MODAL KERJA
A26: S.AR | B26: Piutang usaha (DSO x pendapatan / 365) | C26: =(BS!C8+BS!C9) -> 12118406500 | D26: =(BS!D8+BS!D9) -> 16783681668 | E26: =(BS!E8+BS!E9) -> 25075858587 | F26: =(BS!F8+BS!F9) -> 18872446355 | G26: =IS_Proj!G10*Asumsi!G24/365 -> 2.1425474e+10 | H26: =IS_Proj!H10*Asumsi!H24/365 -> 2.3139511e+10 | I26: =IS_Proj!I10*Asumsi!I24/365 -> 2.4990672e+10 | J26: =IS_Proj!J10*Asumsi!J24/365 -> 2.6989926e+10 | K26: =IS_Proj!K10*Asumsi!K24/365 -> 2.914912e+10
A27: S.INV | B27: Persediaan (DIO x beban pokok / 365) | C27: =BS!C12 -> 2264889867 | D27: =BS!D12 -> 4036032457 | E27: =BS!E12 -> 4135618544 | F27: =BS!F12 -> 1336242114 | G27: =-IS_Proj!G13*Asumsi!G25/365 -> 2.8710135e+09 | H27: =-IS_Proj!H13*Asumsi!H25/365 -> 3.1006945e+09 | I27: =-IS_Proj!I13*Asumsi!I25/365 -> 3.3487501e+09 | J27: =-IS_Proj!J13*Asumsi!J25/365 -> 3.6166501e+09 | K27: =-IS_Proj!K13*Asumsi!K25/365 -> 3.9059821e+09
A28: S.AP | B28: Utang usaha (DPO x beban pokok / 365) | C28: =(BS!C30+BS!C31) -> 2059291014 | D28: =(BS!D30+BS!D31) -> 4772562529 | E28: =(BS!E30+BS!E31) -> 5668668826 | F28: =(BS!F30+BS!F31) -> 6578276878 | G28: =-IS_Proj!G13*Asumsi!G26/365 -> 6.3162296e+09 | H28: =-IS_Proj!H13*Asumsi!H26/365 -> 6.821528e+09 | I28: =-IS_Proj!I13*Asumsi!I26/365 -> 7.3672502e+09 | J28: =-IS_Proj!J13*Asumsi!J26/365 -> 7.9566302e+09 | K28: =-IS_Proj!K13*Asumsi!K26/365 -> 8.5931607e+09
A29: S.NWC | B29: Modal kerja usaha neto | C29: =C26+C27-C28 -> 12324005353 | D29: =D26+D27-D28 -> 16047151596 | E29: =E26+E27-E28 -> 23542808305 | F29: =F26+F27-F28 -> 13630411591 | G29: =G26+G27-G28 -> 1.7980257e+10 | H29: =H26+H27-H28 -> 1.9418678e+10 | I29: =I26+I27-I28 -> 2.0972172e+10 | J29: =J26+J27-J28 -> 2.2649946e+10 | K29: =K26+K27-K28 -> 2.4461942e+10
A30: S.D_NWC | B30: (Kenaikan) modal kerja | D30: =C29-D29 -> -3723146243 | E30: =D29-E29 -> -7495656709 | F30: =E29-F29 -> 9912396714 | G30: =F29-G29 -> -4.3498459e+09 | H30: =G29-H29 -> -1.4384206e+09 | I30: =H29-I29 -> -1.5534942e+09 | J30: =I29-J29 -> -1.6777738e+09 | K30: =J29-K29 -> -1.8119957e+09

Sheet DCF_Template
A1: Template DCF opsional - kalkulator untuk pengguna (input KOSONG)
A2: Sel kuning diisi sendiri oleh pengguna dan perlu diverifikasi. Hasil sepenuhnya bergantung pada input pengguna; BUKAN nilai wajar, target, atau rekomendasi dari penyusun.
B4: INPUT (kosong = template tidak menghitung)
B5: Suku bunga bebas risiko (Rf) | D5: perlu diisi/diverifikasi: mis. imbal hasil SUN 10 tahun; catat sumber & tanggal
B6: Equity risk premium (ERP) | D6: perlu diisi/diverifikasi: catat sumber
B7: Beta (levered) | D7: perlu diisi/diverifikasi: metode, periode & indeks acuan
B8: Premi tambahan (ukuran/spesifik), opsional | D8: perlu diisi/diverifikasi: isi 0 bila tidak dipakai
B9: Biaya utang sebelum pajak (Kd) | D9: perlu diisi/diverifikasi
B10: Tarif pajak untuk perisai bunga | D10: perlu diisi/diverifikasi: tarif PPh badan berlaku
B11: Bobot utang D/(D+E) target | D11: perlu diisi/diverifikasi
B12: Pertumbuhan terminal (g) - metode Gordon | D12: perlu diisi/diverifikasi
B13: Kelipatan EV/EBITDA terminal - metode exit multiple | D13: perlu diisi/diverifikasi: dokumentasikan sumber
B14: Aset non-operasi ditambahkan (Rp), mis. investasi saham | D14: perlu diisi/diverifikasi: isi 0 bila tidak dipakai
B15: Input inti lengkap? (Rf, ERP, beta, Kd, pajak, bobot utang) | C15: =COUNT($C$5,$C$6,$C$7,$C$9,$C$10,$C$11)=6 -> FALSE
B16: Siap hitung metode Gordon? | C16: =AND($C$15,COUNT($C$12)=1) -> FALSE
B17: Siap hitung metode exit multiple? | C17: =AND($C$15,COUNT($C$13)=1) -> FALSE
B19: WACC
B20: Biaya ekuitas Ke = Rf + beta x ERP + premi | C20: =IF($C$15,$C$5+$C$7*$C$6+N($C$8),"")
B21: Biaya utang setelah pajak | C21: =IF($C$15,$C$9*(1-$C$10),"")
B22: WACC | C22: =IF($C$15,$C$20*(1-$C$11)+$C$21*$C$11,"")
B24: FCFF (mengikuti skenario aktif di Asumsi)
G25: FY2026E | H25: FY2027E | I25: FY2028E | J25: FY2029E | K25: FY2030E
B26: Periode diskonto (tahun, akhir periode) | G26: 1 | H26: 2 | I26: 3 | J26: 4 | K26: 5
B27: EBIT | G27: =IS_Proj!G19 -> 8.0581528e+09 | H27: =IS_Proj!H19 -> 9.5109448e+09 | I27: =IS_Proj!I19 -> 1.1000439e+10 | J27: =IS_Proj!J19 -> 1.2537397e+10 | K27: =IS_Proj!K19 -> 1.413267e+10
B28: Pajak atas EBIT (tarif dari Asumsi) | G28: =-MAX(G27,0)*Asumsi!G28 -> -2.0145382e+09 | H28: =-MAX(H27,0)*Asumsi!H28 -> -2.3777362e+09 | I28: =-MAX(I27,0)*Asumsi!I28 -> -2.7501098e+09 | J28: =-MAX(J27,0)*Asumsi!J28 -> -3.1343493e+09 | K28: =-MAX(K27,0)*Asumsi!K28 -> -3.5331676e+09
B29: NOPAT | G29: =G27+G28 -> 6.0436146e+09 | H29: =H27+H28 -> 7.1332086e+09 | I29: =I27+I28 -> 8.2503294e+09 | J29: =J27+J28 -> 9.4030479e+09 | K29: =K27+K28 -> 1.0599503e+10
B30: + D&A | G30: =-IS_Proj!G18 -> 1.2587434e+10 | H30: =-IS_Proj!H18 -> 1.2786288e+10 | I30: =-IS_Proj!I18 -> 1.3080573e+10 | J30: =-IS_Proj!J18 -> 1.3470096e+10 | K30: =-IS_Proj!K18 -> 1.3955422e+10
B31: - Capex | G31: =CF_Proj!G13 -> -1.4076536e+10 | H31: =CF_Proj!H13 -> -1.5202659e+10 | I31: =CF_Proj!I13 -> -1.6418872e+10 | J31: =CF_Proj!J13 -> -1.7732382e+10 | K31: =CF_Proj!K13 -> -1.9150972e+10
B32: - Kenaikan modal kerja | G32: =Schedules_Proj!G30 -> -4.3498459e+09 | H32: =Schedules_Proj!H30 -> -1.4384206e+09 | I32: =Schedules_Proj!I30 -> -1.5534942e+09 | J32: =Schedules_Proj!J30 -> -1.6777738e+09 | K32: =Schedules_Proj!K30 -> -1.8119957e+09
B33: FCFF | G33: =SUM(G29:G32) -> 2.0466616e+08 | H33: =SUM(H29:H32) -> 3.2784174e+09 | I33: =SUM(I29:I32) -> 3.3585361e+09 | J33: =SUM(J29:J32) -> 3.4629883e+09 | K33: =SUM(K29:K32) -> 3.591957e+09
B34: Faktor diskonto | G34: =IF($C$15,1/(1+$C$22)^G26,"") | H34: =IF($C$15,1/(1+$C$22)^H26,"") | I34: =IF($C$15,1/(1+$C$22)^I26,"") | J34: =IF($C$15,1/(1+$C$22)^J26,"") | K34: =IF($C$15,1/(1+$C$22)^K26,"")
B35: PV FCFF | G35: =IF($C$15,G33*G34,"") | H35: =IF($C$15,H33*H34,"") | I35: =IF($C$15,I33*I34,"") | J35: =IF($C$15,J33*J34,"") | K35: =IF($C$15,K33*K34,"")
B36: Catatan IFRS 16: FCFF sebelum pembayaran sewa, sehingga liabilitas sewa diperlakukan sebagai utang di jembatan ekuitas.
B38: NILAI PERUSAHAAN & JEMBATAN EKUITAS (hasil kalkulator) | C38: Gordon | D38: Exit multiple
B39: Σ PV FCFF | C39: =IF($C$16,SUMPRODUCT($G$33:$K$33/(1+$C$22)^$G$26:$K$26),"") | D39: =IF($C$17,SUMPRODUCT($G$33:$K$33/(1+$C$22)^$G$26:$K$26),"")
B40: Nilai terminal (akhir FY2030E) | C40: =IF($C$16,IF($C$22>$C$12,$K$33*(1+$C$12)/($C$22-$C$12),"WACC<=g"),"") | D40: =IF($C$17,IS_Proj!$K$17*$C$13,"")
B41: PV nilai terminal | C41: =IFERROR(C40/(1+$C$22)^5,"") | D41: =IFERROR(D40/(1+$C$22)^5,"")
B42: Nilai perusahaan (EV) | C42: =IFERROR(C39+C41,"") | D42: =IFERROR(D39+D41,"")
B43: (-) Utang bank FY2025A | C43: =-BS_Proj!F18 -> -89971932007 | D43: =-BS_Proj!F18 -> -89971932007
B44: (-) Liabilitas sewa FY2025A | C44: =-BS_Proj!F19 -> -1329650108 | D44: =-BS_Proj!F19 -> -1329650108
B45: (+) Kas FY2025A | C45: =BS_Proj!F6 -> 4036506961 | D45: =BS_Proj!F6 -> 4036506961
B46: (-) Kepentingan nonpengendali (nilai buku FY2025A) | C46: =-BS_Proj!F26 -> -3850792 | D46: =-BS_Proj!F26 -> -3850792
B47: (+) Aset non-operasi (input) | C47: =N($C$14) -> 0 | D47: =N($C$14) -> 0
B48: Nilai ekuitas | C48: =IFERROR(C42+SUM(C43:C47),"") | D48: =IFERROR(D42+SUM(D43:D47),"")
B49: Nilai ekuitas per saham (Rp) | C49: =IFERROR(C48/Asumsi!$C$118,"") | D49: =IFERROR(D48/Asumsi!$C$118,"")
B50: Hanya keluaran rumus atas input pengguna; bukan target, bukan nilai wajar, bukan rekomendasi. NCI dikurangkan pada nilai buku (penyederhanaan).
B52: SENSITIVITAS nilai ekuitas per saham (Gordon): WACC (baris) x g (kolom)
B53: WACC \ g | C53: =IF($C$16,$C$12+(-0.01),"") | D53: =IF($C$16,$C$12+(-0.005),"") | E53: =IF($C$16,$C$12+(0),"") | F53: =IF($C$16,$C$12+(0.005),"") | G53: =IF($C$16,$C$12+(0.01),"")
B54: =IF($C$16,$C$22+(-0.02),"") | C54: =IF($C$16,IFERROR(IF($B54>C$53,(SUMPRODUCT($G$33:$K$33/(1+$B54)^$G$26:$K$26)+$K$33*(1+C$53)/($B54-C$53)/(1+$B54)^5+SUM($C$43:$C$47))/Asumsi!$C$118,"n/a"),""),"") | D54: =IF($C$16,IFERROR(IF($B54>D$53,(SUMPRODUCT($G$33:$K$33/(1+$B54)^$G$26:$K$26)+$K$33*(1+D$53)/($B54-D$53)/(1+$B54)^5+SUM($C$43:$C$47))/Asumsi!$C$118,"n/a"),""),"") | E54: =IF($C$16,IFERROR(IF($B54>E$53,(SUMPRODUCT($G$33:$K$33/(1+$B54)^$G$26:$K$26)+$K$33*(1+E$53)/($B54-E$53)/(1+$B54)^5+SUM($C$43:$C$47))/Asumsi!$C$118,"n/a"),""),"") | F54: =IF($C$16,IFERROR(IF($B54>F$53,(SUMPRODUCT($G$33:$K$33/(1+$B54)^$G$26:$K$26)+$K$33*(1+F$53)/($B54-F$53)/(1+$B54)^5+SUM($C$43:$C$47))/Asumsi!$C$118,"n/a"),""),"") | G54: =IF($C$16,IFERROR(IF($B54>G$53,(SUMPRODUCT($G$33:$K$33/(1+$B54)^$G$26:$K$26)+$K$33*(1+G$53)/($B54-G$53)/(1+$B54)^5+SUM($C$43:$C$47))/Asumsi!$C$118,"n/a"),""),"")
B55: =IF($C$16,$C$22+(-0.01),"") | C55: =IF($C$16,IFERROR(IF($B55>C$53,(SUMPRODUCT($G$33:$K$33/(1+$B55)^$G$26:$K$26)+$K$33*(1+C$53)/($B55-C$53)/(1+$B55)^5+SUM($C$43:$C$47))/Asumsi!$C$118,"n/a"),""),"") | D55: =IF($C$16,IFERROR(IF($B55>D$53,(SUMPRODUCT($G$33:$K$33/(1+$B55)^$G$26:$K$26)+$K$33*(1+D$53)/($B55-D$53)/(1+$B55)^5+SUM($C$43:$C$47))/Asumsi!$C$118,"n/a"),""),"") | E55: =IF($C$16,IFERROR(IF($B55>E$53,(SUMPRODUCT($G$33:$K$33/(1+$B55)^$G$26:$K$26)+$K$33*(1+E$53)/($B55-E$53)/(1+$B55)^5+SUM($C$43:$C$47))/Asumsi!$C$118,"n/a"),""),"") | F55: =IF($C$16,IFERROR(IF($B55>F$53,(SUMPRODUCT($G$33:$K$33/(1+$B55)^$G$26:$K$26)+$K$33*(1+F$53)/($B55-F$53)/(1+$B55)^5+SUM($C$43:$C$47))/Asumsi!$C$118,"n/a"),""),"") | G55: =IF($C$16,IFERROR(IF($B55>G$53,(SUMPRODUCT($G$33:$K$33/(1+$B55)^$G$26:$K$26)+$K$33*(1+G$53)/($B55-G$53)/(1+$B55)^5+SUM($C$43:$C$47))/Asumsi!$C$118,"n/a"),""),"")
B56: =IF($C$16,$C$22+(0),"") | C56: =IF($C$16,IFERROR(IF($B56>C$53,(SUMPRODUCT($G$33:$K$33/(1+$B56)^$G$26:$K$26)+$K$33*(1+C$53)/($B56-C$53)/(1+$B56)^5+SUM($C$43:$C$47))/Asumsi!$C$118,"n/a"),""),"") | D56: =IF($C$16,IFERROR(IF($B56>D$53,(SUMPRODUCT($G$33:$K$33/(1+$B56)^$G$26:$K$26)+$K$33*(1+D$53)/($B56-D$53)/(1+$B56)^5+SUM($C$43:$C$47))/Asumsi!$C$118,"n/a"),""),"") | E56: =IF($C$16,IFERROR(IF($B56>E$53,(SUMPRODUCT($G$33:$K$33/(1+$B56)^$G$26:$K$26)+$K$33*(1+E$53)/($B56-E$53)/(1+$B56)^5+SUM($C$43:$C$47))/Asumsi!$C$118,"n/a"),""),"") | F56: =IF($C$16,IFERROR(IF($B56>F$53,(SUMPRODUCT($G$33:$K$33/(1+$B56)^$G$26:$K$26)+$K$33*(1+F$53)/($B56-F$53)/(1+$B56)^5+SUM($C$43:$C$47))/Asumsi!$C$118,"n/a"),""),"") | G56: =IF($C$16,IFERROR(IF($B56>G$53,(SUMPRODUCT($G$33:$K$33/(1+$B56)^$G$26:$K$26)+$K$33*(1+G$53)/($B56-G$53)/(1+$B56)^5+SUM($C$43:$C$47))/Asumsi!$C$118,"n/a"),""),"")
B57: =IF($C$16,$C$22+(0.01),"") | C57: =IF($C$16,IFERROR(IF($B57>C$53,(SUMPRODUCT($G$33:$K$33/(1+$B57)^$G$26:$K$26)+$K$33*(1+C$53)/($B57-C$53)/(1+$B57)^5+SUM($C$43:$C$47))/Asumsi!$C$118,"n/a"),""),"") | D57: =IF($C$16,IFERROR(IF($B57>D$53,(SUMPRODUCT($G$33:$K$33/(1+$B57)^$G$26:$K$26)+$K$33*(1+D$53)/($B57-D$53)/(1+$B57)^5+SUM($C$43:$C$47))/Asumsi!$C$118,"n/a"),""),"") | E57: =IF($C$16,IFERROR(IF($B57>E$53,(SUMPRODUCT($G$33:$K$33/(1+$B57)^$G$26:$K$26)+$K$33*(1+E$53)/($B57-E$53)/(1+$B57)^5+SUM($C$43:$C$47))/Asumsi!$C$118,"n/a"),""),"") | F57: =IF($C$16,IFERROR(IF($B57>F$53,(SUMPRODUCT($G$33:$K$33/(1+$B57)^$G$26:$K$26)+$K$33*(1+F$53)/($B57-F$53)/(1+$B57)^5+SUM($C$43:$C$47))/Asumsi!$C$118,"n/a"),""),"") | G57: =IF($C$16,IFERROR(IF($B57>G$53,(SUMPRODUCT($G$33:$K$33/(1+$B57)^$G$26:$K$26)+$K$33*(1+G$53)/($B57-G$53)/(1+$B57)^5+SUM($C$43:$C$47))/Asumsi!$C$118,"n/a"),""),"")
B58: =IF($C$16,$C$22+(0.02),"") | C58: =IF($C$16,IFERROR(IF($B58>C$53,(SUMPRODUCT($G$33:$K$33/(1+$B58)^$G$26:$K$26)+$K$33*(1+C$53)/($B58-C$53)/(1+$B58)^5+SUM($C$43:$C$47))/Asumsi!$C$118,"n/a"),""),"") | D58: =IF($C$16,IFERROR(IF($B58>D$53,(SUMPRODUCT($G$33:$K$33/(1+$B58)^$G$26:$K$26)+$K$33*(1+D$53)/($B58-D$53)/(1+$B58)^5+SUM($C$43:$C$47))/Asumsi!$C$118,"n/a"),""),"") | E58: =IF($C$16,IFERROR(IF($B58>E$53,(SUMPRODUCT($G$33:$K$33/(1+$B58)^$G$26:$K$26)+$K$33*(1+E$53)/($B58-E$53)/(1+$B58)^5+SUM($C$43:$C$47))/Asumsi!$C$118,"n/a"),""),"") | F58: =IF($C$16,IFERROR(IF($B58>F$53,(SUMPRODUCT($G$33:$K$33/(1+$B58)^$G$26:$K$26)+$K$33*(1+F$53)/($B58-F$53)/(1+$B58)^5+SUM($C$43:$C$47))/Asumsi!$C$118,"n/a"),""),"") | G58: =IF($C$16,IFERROR(IF($B58>G$53,(SUMPRODUCT($G$33:$K$33/(1+$B58)^$G$26:$K$26)+$K$33*(1+G$53)/($B58-G$53)/(1+$B58)^5+SUM($C$43:$C$47))/Asumsi!$C$118,"n/a"),""),"")
B60: Template ini sengaja tidak memuat perbandingan dengan data pasar. Pengguna bertanggung jawab penuh atas input dan interpretasinya.

Sheet Peer
A1: Tabel pembanding - data FUNDAMENTAL saja (baris pembanding kosong)
A2: Isi hanya dengan data terverifikasi dari laporan keuangan publik tiap emiten; cantumkan sumber & tanggal akses. Tidak ada angka yang dikarang.
A4: Kode | B4: Nama emiten | C4: Fokus usaha | D4: Tahun buku | E4: Pendapatan (Rp miliar) | F4: Pertumbuhan pendapatan | G4: Margin EBITDA | H4: Margin laba bersih | I4: ROE | J4: ROA | K4: Utang / ekuitas | L4: Utang neto / EBITDA | M4: Jumlah RS | N4: Jumlah tempat tidur | O4: Porsi pendapatan penunjang medis | P4: Sumber (laporan, halaman) | Q4: Tanggal akses
A5: DKHH | B5: PT Cipta Sarana Medika Tbk | C5: 3 RS tipe C (Bekasi & Sukabumi) | D5: 2025 | E5: =IS_Proj!F10/1000000000 -> 144.87327 | F5: =IS_Proj!F11 -> -0.047777527 | G5: =IS_Proj!F31 -> 0.10591188 | H5: =IS_Proj!F33 -> 0.041566657 | I5: =BS_Proj!F32 -> 0.035818841 | J5: =IS_Proj!F25/BS_Proj!F15 -> 0.018236411 | K5: =BS_Proj!F18/BS_Proj!F27 -> 0.43568679 | L5: =BS_Proj!F33 -> 5.6873182 | O5: =IS_Proj!F6/IS_Proj!F10 -> 0.21122146 | P5: Model ini (laporan audited FY2025)
B14: Median pembanding (tanpa DKHH) | E14: =IF(COUNT(E6:E13)=0,"",MEDIAN(E6:E13)) | F14: =IF(COUNT(F6:F13)=0,"",MEDIAN(F6:F13)) | G14: =IF(COUNT(G6:G13)=0,"",MEDIAN(G6:G13)) | H14: =IF(COUNT(H6:H13)=0,"",MEDIAN(H6:H13)) | I14: =IF(COUNT(I6:I13)=0,"",MEDIAN(I6:I13)) | J14: =IF(COUNT(J6:J13)=0,"",MEDIAN(J6:J13)) | K14: =IF(COUNT(K6:K13)=0,"",MEDIAN(K6:K13)) | L14: =IF(COUNT(L6:L13)=0,"",MEDIAN(L6:L13)) | ... O14: =IF(COUNT(O6:O13)=0,"",MEDIAN(O6:O13))
B15: Rata-rata pembanding (tanpa DKHH) | E15: =IF(COUNT(E6:E13)=0,"",AVERAGE(E6:E13)) | F15: =IF(COUNT(F6:F13)=0,"",AVERAGE(F6:F13)) | G15: =IF(COUNT(G6:G13)=0,"",AVERAGE(G6:G13)) | H15: =IF(COUNT(H6:H13)=0,"",AVERAGE(H6:H13)) | I15: =IF(COUNT(I6:I13)=0,"",AVERAGE(I6:I13)) | J15: =IF(COUNT(J6:J13)=0,"",AVERAGE(J6:J13)) | K15: =IF(COUNT(K6:K13)=0,"",AVERAGE(K6:K13)) | L15: =IF(COUNT(L6:L13)=0,"",AVERAGE(L6:L13)) | ... O15: =IF(COUNT(O6:O13)=0,"",AVERAGE(O6:O13))
B17: Tabel ini sengaja tidak memuat kelipatan pasar (P/E, P/BV, EV/EBITDA): isinya ringkasan data fundamental, bukan penilaian.

Sheet IS
A1: Laporan Laba Rugi & OCI - historis FY2022A-FY2025A
A2: Rp penuh. Biru = input dari DKHH_seri_2022_2025.json (LK audited, Rupiah penuh), hitam = rumus. Kolom 2022-2023 dari LK audited dalam Prospektus IPO; 2024 dari komparatif LK FY2025 (Temuan D8). Dana syirkah temporer direklasifikasi ke liabilitas (Temuan D2).
B3: Sumber kolom | C3: Prospektus IPO 2025 (LK konsolidasian audited 2023/2022) | D3: Prospektus IPO 2025 (LK konsolidasian audited 2023/2022) | E3: LK FY2025 (komparatif) | F3: LK FY2025 | G3: Catatan sumber: DKHH (PT Cipta Sarana Medika Tbk), IPO 2025. Histori model FY2022-FY2025 (4 tahun). 2022-2023 dari LK konsolidasian audited dalam Prospektus IPO (disajikan proforma seolah restrukturisasi entitas sepe
A4: Kode | B4: Akun | C4: FY2022A | D4: FY2023A | E4: FY2024A | F4: FY2025A | G4: Catatan / sumber
B5: LABA RUGI
A6: IS.REVENUE | B6: Pendapatan (Cat 25) | C6: 99578144421 | D6: 134187678929 | E6: 152142248784 | F6: 144873268389 | G6: kunci JSON: pendapatan
A7: IS.COGS | B7: Beban pokok pendapatan (Cat 26) | C7: -67593755280 | D7: -89574415546 | E7: -104806476450 | F7: -110732463969 | G7: kunci JSON: beban_pokok
A8: IS.GROSS_PROFIT | B8: Laba bruto | C8: =C6+C7 -> 31984389141 | D8: =D6+D7 -> 44613263383 | E8: =E6+E7 -> 47335772334 | F8: =F6+F7 -> 34140804420
A9: IS.SELLING | B9: Beban penjualan (Cat 27) | C9: -974896353 | D9: -3183805931 | E9: -4061959293 | F9: -2783285450 | G9: kunci JSON: beban_penjualan
A10: IS.GA | B10: Beban umum dan administrasi (Cat 27) | C10: -23863495422 | D10: -31755062789 | E10: -31962658076 | F10: -27906878912 | G10: kunci JSON: beban_umum
A11: IS.OPEX_TOTAL | B11: Jumlah beban usaha | C11: =C9+C10 -> -24838391775 | D11: =D9+D10 -> -34938868720 | E11: =E9+E10 -> -36024617369 | F11: =F9+F10 -> -30690164362
A12: IS.OTHER_INCOME | B12: Pendapatan (beban) lain-lain - neto (sewa & lain-lain) | C12: 1226392843 | D12: 75326392 | E12: 313957191 | F12: -710131821 | G12: kunci JSON: pendapatan_lain
A13: IS.OTHER_OPER_NET | B13: Pendapatan (beban) lain-lain neto | C13: =C12 -> 1226392843 | D13: =D12 -> 75326392 | E13: =E12 -> 313957191 | F13: =F12 -> -710131821
A14: IS.OPER_PROFIT | B14: Laba usaha model (laba bruto - beban usaha + lain-lain neto; Temuan D9) | C14: =C8+C11+C13 -> 8372390209 | D14: =D8+D11+D13 -> 9749721055 | E14: =E8+E11+E13 -> 11625112156 | F14: =F8+F11+F13 -> 2740508237
A15: IS.FIN_COST | B15: Beban keuangan | C15: -3643595812 | D15: -7565985614 | E15: -11555610977 | F15: -10242145297 | G15: kunci JSON: beban_keuangan
A16: IS.FIN_INCOME | B16: Penghasilan keuangan | C16: 0 | D16: 0 | E16: 0 | F16: 13190576716 | G16: kunci JSON: penghasilan_keuangan
A17: IS.PBT | B17: Laba sebelum pajak | C17: =C14+C16+C15 -> 4728794397 | D17: =D14+D16+D15 -> 2183735441 | E17: =E14+E16+E15 -> 69501179 | F17: =F14+F16+F15 -> 5688939656
A18: IS.TAX_TOTAL | B18: Beban (manfaat) pajak penghasilan | C18: -1220088106 | D18: -1675692417 | E18: -480368880 | F18: 332957861 | G18: kunci JSON: beban_pajak
A19: IS.MERGING | B19: Laba entitas anak sebelum restrukturisasi (proforma 2022-2024; Temuan D1) | C19: 1379459473 | D19: 3031673373 | E19: 3248230974 | F19: 0 | G19: kunci JSON: laba_merging
A20: IS.NET_INCOME | B20: Laba tahun berjalan | C20: =C17+C18+C19 -> 4888165764 | D20: =D17+D18+D19 -> 3539716397 | E20: =E17+E18+E19 -> 2837363273 | F20: =F17+F18+F19 -> 6021897517
B21: PENGHASILAN KOMPREHENSIF LAIN (OCI)
A22: IS.OCI_REVAL | B22: Surplus revaluasi aset tetap | C22: 0 | D22: 25288897160 | E22: 0 | F22: 0 | G22: kunci JSON: oci_revaluasi
A23: IS.OCI_REMEASURE | B23: Pengukuran kembali program imbalan pasti | C23: -364663854 | D23: 2259954342 | E23: 209939468 | F23: 1003162921 | G23: kunci JSON: oci_remeasurement
A24: IS.OCI_TAX | B24: Pajak terkait | C24: 80226048 | D24: -497189955 | E24: -46186683 | F24: -220695843 | G24: kunci JSON: oci_pajak_terkait
A25: IS.OCI_PROFORMA | B25: OCI entitas anak sebelum restrukturisasi (proforma) | C25: 0 | D25: 0 | E25: 128763209 | F25: 0 | G25: kunci JSON: oci_proforma
A26: IS.OCI_TOTAL | B26: Jumlah OCI | C26: =C22+C23+C24+C25 -> -284437806 | D26: =D22+D23+D24+D25 -> 27051661547 | E26: =E22+E23+E24+E25 -> 292515994 | F26: =F22+F23+F24+F25 -> 782467078
A27: IS.TCI | B27: Jumlah laba komprehensif | C27: =C20+C26 -> 4603727958 | D27: =D20+D26 -> 30591377944 | E27: =E20+E26 -> 3129879267 | F27: =F20+F26 -> 6804364595
B28: ATRIBUSI & PER SAHAM
A29: IS.NI_PARENT | B29: Laba diatribusikan ke pemilik entitas induk | C29: 4888165764 | D29: 3539716397 | E29: 2837231824 | F29: 6021648113 | G29: kunci JSON: laba_induk
A30: IS.NI_NCI | B30: Laba diatribusikan ke kepentingan nonpengendali (NCI) | C30: 0 | D30: 0 | E30: 131449 | F30: 249404 | G30: kunci JSON: laba_nci
A31: IS.TCI_PARENT | B31: Laba komprehensif - pemilik entitas induk | C31: 4603727958 | D31: 30591377944 | E31: 3129872183 | F31: 6804407373 | G31: kunci JSON: tci_induk
A32: IS.TCI_NCI | B32: Laba komprehensif - NCI | C32: 0 | D32: 0 | E32: -7084 | F32: 42778 | G32: kunci JSON: tci_nci
A33: IS.EPS_BASIC | B33: Laba per saham dasar tercetak (Rp, penuh) | C33: 8.81 | D33: 6.38 | E33: 4 | F33: 3 | G33: kunci JSON: eps_dasar
A34: IS.EPS_DILUTED | B34: Laba per saham dilusian tercetak (Rp, penuh) | C34: 8.81 | D34: 6.38 | E34: 4 | F34: 3 | G34: kunci JSON: eps_dilusian
B35: MEMO: SUBTOTAL TERCETAK DI LK (untuk Rekonsiliasi)
A36: IS.GROSS_PROFIT_PRINTED | B36: Laba bruto (tercetak) | C36: 31984389141 | D36: 44613263383 | E36: 47335772334 | F36: 34140804420 | G36: kunci JSON: laba_bruto
A37: IS.OPER_PROFIT_PRINTED | B37: Laba usaha (tercetak; sebelum pendapatan lain-lain) | C37: 7145997366 | D37: 9674394663 | E37: 11311154965 | F37: 3450640058 | G37: kunci JSON: laba_usaha
A38: IS.PBT_PRINTED | B38: Laba sebelum pajak (tercetak) | C38: 4728794397 | D38: 2183735441 | E38: 69501179 | F38: 5688939656 | G38: kunci JSON: laba_sebelum_pajak
A39: IS.NET_INCOME_PRINTED | B39: Laba tahun berjalan (tercetak) | C39: 4888165764 | D39: 3539716397 | E39: 2837363273 | F39: 6021897517 | G39: kunci JSON: laba_tahun_berjalan
A40: IS.OCI_TOTAL_PRINTED | B40: Jumlah OCI (tercetak) | C40: -284437806 | D40: 27051661547 | E40: 292515994 | F40: 782467078 | G40: kunci JSON: oci_total
A41: IS.TCI_PRINTED | B41: Laba komprehensif (tercetak) | C41: 4603727958 | D41: 30591377944 | E41: 3129879267 | F41: 6804364595 | G41: kunci JSON: total_laba_komprehensif

Sheet BS
A1: Laporan Posisi Keuangan - historis FY2022A-FY2025A
A2: Rp penuh. Biru = input dari DKHH_seri_2022_2025.json (LK audited, Rupiah penuh), hitam = rumus. Kolom 2022-2023 dari LK audited dalam Prospektus IPO; 2024 dari komparatif LK FY2025 (Temuan D8). Dana syirkah temporer direklasifikasi ke liabilitas (Temuan D2).
B3: Sumber kolom | C3: Prospektus IPO 2025 (LK konsolidasian audited 2023/2022) | D3: Prospektus IPO 2025 (LK konsolidasian audited 2023/2022) | E3: LK FY2025 (komparatif) | F3: LK FY2025 | G3: Catatan sumber: DKHH (PT Cipta Sarana Medika Tbk), IPO 2025. Histori model FY2022-FY2025 (4 tahun). 2022-2023 dari LK konsolidasian audited dalam Prospektus IPO (disajikan proforma seolah restrukturisasi entitas sepe
A4: Kode | B4: Akun | C4: FY2022A | D4: FY2023A | E4: FY2024A | F4: FY2025A | G4: Catatan / sumber
B5: ASET
A6: BS.CASH | B6: Kas dan setara kas | C6: 29547207476 | D6: 2463973775 | E6: 2663388349 | F6: 4036506961 | G6: kunci JSON: kas
A7: BS.ST_INVEST | B7: Deposito berjangka | G7: kunci JSON: -
A8: BS.TRADE_REC | B8: Piutang usaha - pihak ketiga | C8: 12118406500 | D8: 16783681668 | E8: 25075858587 | F8: 18872446355 | G8: kunci JSON: piutang_usaha_pk3
A9: BS.TRADE_REC_RP | B9: Piutang usaha - pihak berelasi | G9: kunci JSON: -
A10: BS.OTHER_REC | B10: Piutang lain-lain - pihak ketiga | C10: 97099554 | D10: 27440000 | E10: 630259097 | F10: 140874649 | G10: kunci JSON: piutang_lain_pk3
A11: BS.OTHER_REC_RP | B11: Piutang lain-lain - pihak berelasi | C11: 0 | D11: 0 | E11: 0 | F11: 13190606059 | G11: kunci JSON: piutang_lain_rp
A12: BS.INVENTORY | B12: Persediaan | C12: 2264889867 | D12: 4036032457 | E12: 4135618544 | F12: 1336242114 | G12: kunci JSON: persediaan
A13: BS.PREPAID_ADV | B13: Beban dibayar dimuka | C13: 1533846590 | D13: 4549578293 | E13: 58296415 | F13: 166401766 | G13: kunci JSON: biaya_dimuka
A14: BS.PREPAID_TAX | B14: Pajak dibayar dimuka | C14: 54908963 | D14: 39319861 | E14: 1166210842 | F14: 1468574720 | G14: kunci JSON: pajak_dimuka
A15: BS.ADVANCES | B15: Uang muka | C15: 0 | D15: 0 | E15: 1362895270 | F15: 133200000 | G15: kunci JSON: uang_muka
A16: BS.TOTAL_CA | B16: Jumlah aset lancar | C16: =C6+C7+C8+C9+C10+C11+C12+C13+C14+C15 -> 45616358950 | D16: =D6+D7+D8+D9+D10+D11+D12+D13+D14+D15 -> 27900026054 | E16: =E6+E7+E8+E9+E10+E11+E12+E13+E14+E15 -> 35092527104 | F16: =F6+F7+F8+F9+F10+F11+F12+F13+F14+F15 -> 39344852624
A17: BS.INTANGIBLES | B17: Aset takberwujud (disajikan terpisah mulai LK FY2023) | G17: kunci JSON: -
A18: BS.DTA | B18: Aset pajak tangguhan | C18: 3268826531 | D18: 3377073718 | E18: 3733825590 | F18: 4029438145 | G18: kunci JSON: aset_pajak_tangguhan
A19: BS.GOODWILL | B19: Goodwill | G19: kunci JSON: -
A20: BS.PREPAID_ADV_NC | B20: Uang muka pembelian aset tetap | C20: 0 | D20: 0 | E20: 323045319 | F20: 23480000000 | G20: kunci JSON: uang_muka_aset
A21: BS.PPE | B21: Aset tetap - neto (model revaluasi tanah & bangunan sejak 2023) | C21: 66252356120 | D21: 117418739194 | E21: 132385666764 | F21: 127921073027 | G21: kunci JSON: aset_tetap
A22: BS.ROU | B22: Aset hak guna | C22: 0 | D22: 0 | E22: 4142708331 | F22: 3890104167 | G22: kunci JSON: aset_hak_guna
A23: BS.OTHER_REC_NC | B23: Piutang lain-lain - tidak lancar | C23: 0 | D23: 14040900000 | E23: 14040900000 | F23: 14502013517 | G23: kunci JSON: piutang_lain_tl
A24: BS.DUE_FROM_RP | B24: Piutang pihak berelasi - tidak lancar (Temuan D3) | C24: 14855847650 | D24: 107933153871 | E24: 78381566804 | F24: 117045389015 | G24: kunci JSON: piutang_rp_tl
A25: BS.OTHER_NCA | B25: Aset tidak lancar lainnya (2022: uang muka investasi) | C25: 30000000000 | D25: 30000000000 | E25: 0 | F25: 0 | G25: kunci JSON: aset_tl_lain
A26: BS.TOTAL_NCA | B26: Jumlah aset tidak lancar | C26: =C17+C18+C19+C20+C21+C22+C23+C24+C25 -> 114377030301 | D26: =D17+D18+D19+D20+D21+D22+D23+D24+D25 -> 272769866783 | E26: =E17+E18+E19+E20+E21+E22+E23+E24+E25 -> 233007712808 | F26: =F17+F18+F19+F20+F21+F22+F23+F24+F25 -> 290868017871
A27: BS.TOTAL_ASSETS | B27: JUMLAH ASET | C27: =C16+C26 -> 159993389251 | D27: =D16+D26 -> 300669892837 | E27: =E16+E26 -> 268100239912 | F27: =F16+F26 -> 330212870495
B28: LIABILITAS
A29: BS.ST_BANK | B29: Pinjaman bank jangka pendek | C29: 6988804035 | D29: 9988984035 | E29: 11162071905 | F29: 9396425044 | G29: kunci JSON: pinjaman_bank_jp
A30: BS.TRADE_PAY | B30: Utang usaha - pihak ketiga | C30: 2059291014 | D30: 4772562529 | E30: 5668668826 | F30: 6578276878 | G30: kunci JSON: utang_usaha_pk3
A31: BS.TRADE_PAY_RP | B31: Utang usaha - pihak berelasi | G31: kunci JSON: -
A32: BS.OTHER_PAY | B32: Utang lain-lain - pihak ketiga | C32: 889836562 | D32: 2310412449 | E32: 804070003 | F32: 708852420 | G32: kunci JSON: utang_lain_pk3
A33: BS.OTHER_PAY_RP | B33: Utang lain-lain - pihak berelasi | C33: 0 | D33: 0 | E33: 0 | F33: 233968266 | G33: kunci JSON: utang_lain_rp
A34: BS.ACCRUALS | B34: Beban akrual | C34: 6011636598 | D34: 11650476198 | E34: 2027768405 | F34: 1537989603 | G34: kunci JSON: beban_akrual
A35: BS.EMPLOYEE_BENEFIT_CUR | B35: Liabilitas imbalan kerja jangka pendek | C35: 0 | D35: 0 | E35: 7074679859 | F35: 1016716073 | G35: kunci JSON: imbalan_kerja_jp
A36: BS.CONTRACT_LIAB_CUR | B36: Liabilitas kontrak | C36: 4990900 | D36: 109015136 | E36: 217251809 | F36: 145725435 | G36: kunci JSON: kontrak_jt1
A37: BS.TAX_PAY | B37: Utang pajak | C37: 1576828919 | D37: 5339423095 | E37: 4563471447 | F37: 5125717507 | G37: kunci JSON: utang_pajak
A38: BS.LT_BANK_CUR | B38: Utang bank jk panjang - jatuh tempo 1 tahun | C38: 700008000 | D38: 7476298000 | E38: 7068000000 | F38: 7068000000 | G38: kunci JSON: utang_bank_jt1
A39: BS.OTHER_LIAB_CUR | B39: Liabilitas lainnya (pembiayaan peralatan) - jatuh tempo 1 tahun | G39: kunci JSON: -
A40: BS.FIN_LEASE_CUR | B40: Utang sewa pembiayaan - jatuh tempo 1 tahun | C40: 174233989 | D40: 231752112 | E40: 143594960 | F40: 52991281 | G40: kunci JSON: sewa_pemb_jt1
A41: BS.LEASE_CUR | B41: Liabilitas sewa - jatuh tempo 1 tahun | C41: 0 | D41: 0 | E41: 920444528 | F41: 1047230532 | G41: kunci JSON: sewa_jt1
A42: BS.TOTAL_CL | B42: Jumlah liabilitas jangka pendek | C42: =C29+C30+C31+C32+C33+C34+C35+C36+C37+C38+C39+C40+C41 -> 18405630017 | D42: =D29+D30+D31+D32+D33+D34+D35+D36+D37+D38+D39+D40+D41 -> 41878923554 | E42: =E29+E30+E31+E32+E33+E34+E35+E36+E37+E38+E39+E40+E41 -> 39650021742 | F42: =F29+F30+F31+F32+F33+F34+F35+F36+F37+F38+F39+F40+F41 -> 32911893039
A43: BS.LT_BANK_NC | B43: Utang bank jk panjang - setelah 1 tahun | C43: 55654298000 | D43: 71249929334 | E43: 15268666300 | F43: 4083000000 | G43: kunci JSON: utang_bank_jp
A44: BS.OTHER_LIAB_NC | B44: Liabilitas lainnya (pembiayaan peralatan) - setelah 1 tahun | G44: kunci JSON: -
A45: BS.FIN_LEASE_NC | B45: Utang sewa pembiayaan - setelah 1 tahun | C45: 331522552 | D45: 190255560 | E45: 50700680 | F45: 0 | G45: kunci JSON: sewa_pemb_jp
A46: BS.LEASE_NC | B46: Liabilitas sewa - setelah 1 tahun | C46: 0 | D46: 0 | E46: 1408042622 | F46: 282419576 | G46: kunci JSON: sewa_jp
A47: BS.EMPLOYEE_BENEFIT | B47: Liabilitas imbalan kerja jangka panjang | C47: 2095601594 | D47: 1058806553 | E47: 2680405972 | F47: 4024099405 | G47: kunci JSON: imbalan_kerja
A48: BS.OTHER_PAY_NC | B48: Utang lain-lain - pihak berelasi jangka panjang | C48: 2617116617 | D48: 1160606700 | E48: 1160606700 | F48: 13033951873 | G48: kunci JSON: utang_lain_tl
A49: BS.SH_LOAN | B49: Utang pemegang saham | G49: kunci JSON: -
A50: BS.SYIRKAH | B50: Dana syirkah temporer (pembiayaan bank syariah; disajikan di luar liabilitas di LK, Temuan D2) | C50: 29822475744 | D50: 55978364748 | E50: 78152405426 | F50: 69371515682 | G50: kunci JSON: dana_syirkah
A51: BS.TOTAL_NCL | B51: Jumlah liabilitas jangka panjang | C51: =C43+C44+C45+C46+C47+C48+C49+C50 -> 90521014507 | D51: =D43+D44+D45+D46+D47+D48+D49+D50 -> 129637962895 | E51: =E43+E44+E45+E46+E47+E48+E49+E50 -> 98720827700 | F51: =F43+F44+F45+F46+F47+F48+F49+F50 -> 90794986536
A52: BS.TOTAL_LIAB | B52: JUMLAH LIABILITAS | C52: =C42+C51 -> 108926644524 | D52: =D42+D51 -> 171516886449 | E52: =E42+E51 -> 138370849442 | F52: =F42+F51 -> 123706879575
B53: EKUITAS
A54: BS.SHARE_CAPITAL | B54: Modal saham | C54: 27734500000 | D54: 27734500000 | E54: 101000000000 | F54: 127503947050 | G54: kunci JSON: modal_saham
A55: BS.APIC | B55: Tambahan modal disetor | C55: 0 | D55: 0 | E55: -23437977914 | F55: 20030310891 | G55: kunci JSON: tambahan_modal
A56: BS.PROFORMA_EQ | B56: Ekuitas proforma entitas anak sebelum restrukturisasi (Temuan D1) | C56: 4889685079 | D56: 52384568796 | E56: 0 | F56: 0 | G56: kunci JSON: ekuitas_proforma
A57: BS.OCI_RES | B57: Penghasilan komprehensif lain (termasuk surplus revaluasi) | C57: -1098608204 | D57: 25953053343 | E57: 26245562252 | F57: 27027986552 | G57: kunci JSON: oci_ekuitas
A58: BS.RETAINED_EARN | B58: Saldo laba (defisit) (ditentukan + belum ditentukan penggunaannya) | C58: 19541167852 | D58: 23080884249 | E58: 25918247522 | F58: 31939895635 | G58: kunci JSON: saldo_laba
A59: BS.EQUITY_PARENT | B59: Ekuitas pemilik entitas induk | C59: =C54+C55+C56+C57+C58 -> 51066744727 | D59: =D54+D55+D56+D57+D58 -> 129153006388 | E59: =E54+E55+E56+E57+E58 -> 129725831860 | F59: =F54+F55+F56+F57+F58 -> 206502140128
A60: BS.NCI | B60: Kepentingan nonpengendali | C60: 0 | D60: 0 | E60: 3558610 | F60: 3850792 | G60: kunci JSON: nci
A61: BS.TOTAL_EQUITY | B61: JUMLAH EKUITAS | C61: =C59+C60 -> 51066744727 | D61: =D59+D60 -> 129153006388 | E61: =E59+E60 -> 129729390470 | F61: =F59+F60 -> 206505990920
A62: BS.TOTAL_LIAB_EQUITY | B62: JUMLAH LIABILITAS DAN EKUITAS | C62: =C52+C61 -> 159993389251 | D62: =D52+D61 -> 300669892837 | E62: =E52+E61 -> 268100239912 | F62: =F52+F61 -> 330212870495
B63: MEMO (tidak dijumlahkan)
A64: BS.RE_APPROP_MEMO | B64: Memo: saldo laba ditentukan penggunaannya (tercetak) | C64: 0 | D64: 0 | E64: 100000000 | F64: 100000000 | G64: kunci JSON: saldo_laba_ditentukan
A65: BS.RE_UNAPPROP_MEMO | B65: Memo: saldo laba (defisit) belum ditentukan penggunaannya (tercetak) | C65: 19541167852 | D65: 23080884249 | E65: 25818247522 | F65: 31839895635 | G65: kunci JSON: saldo_laba_belum
B66: MEMO: SUBTOTAL TERCETAK DI LK
A67: BS.TOTAL_CA_PRINTED | B67: Jumlah aset lancar (tercetak) | C67: 45616358950 | D67: 27900026054 | E67: 35092527104 | F67: 39344852624 | G67: kunci JSON: TOTAL_ASET_LANCAR
A68: BS.TOTAL_NCA_PRINTED | B68: Jumlah aset tidak lancar (tercetak) | C68: 114377030301 | D68: 272769866783 | E68: 233007712808 | F68: 290868017871 | G68: kunci JSON: TOTAL_ASET_TIDAK_LANCAR
A69: BS.TOTAL_ASSETS_PRINTED | B69: Jumlah aset (tercetak) | C69: 159993389251 | D69: 300669892837 | E69: 268100239912 | F69: 330212870495 | G69: kunci JSON: TOTAL_ASET
A70: BS.TOTAL_CL_PRINTED | B70: Liabilitas jangka pendek (tercetak) | C70: 18405630017 | D70: 41878923554 | E70: 39650021742 | F70: 32911893039 | G70: kunci JSON: TOTAL_LIAB_PENDEK
A71: BS.TOTAL_NCL_PRINTED | B71: Liabilitas jangka panjang (tercetak) | C71: 90521014507 | D71: 129637962895 | E71: 98720827700 | F71: 90794986536 | G71: kunci JSON: TOTAL_LIAB_PANJANG
A72: BS.TOTAL_LIAB_PRINTED | B72: Jumlah liabilitas (tercetak) | C72: 108926644524 | D72: 171516886449 | E72: 138370849442 | F72: 123706879575 | G72: kunci JSON: TOTAL_LIABILITAS
A73: BS.EQUITY_PARENT_PRINTED | B73: Ekuitas induk (tercetak) | C73: 51066744727 | D73: 129153006388 | E73: 129725831860 | F73: 206502140128 | G73: kunci JSON: EKUITAS_INDUK
A74: BS.TOTAL_EQUITY_PRINTED | B74: Jumlah ekuitas (tercetak) | C74: 51066744727 | D74: 129153006388 | E74: 129729390470 | F74: 206505990920 | G74: kunci JSON: TOTAL_EKUITAS
A75: BS.TOTAL_LIAB_EQUITY_PRINTED | B75: Jumlah liabilitas & ekuitas (tercetak) | C75: 159993389251 | D75: 300669892837 | E75: 268100239912 | F75: 330212870495 | G75: kunci JSON: TOTAL_LIAB_EKUITAS
B76: CEK
A77: BS.CHECK | B77: Aset - (liabilitas + ekuitas) = 0 | C77: =C27-C62 -> 0 | D77: =D27-D62 -> 0 | E77: =E27-E62 -> 0 | F77: =F27-F62 -> 0

Sheet CF
A1: Laporan Arus Kas - historis FY2022A-FY2025A
A2: Rp penuh. Biru = input dari DKHH_seri_2022_2025.json (LK audited, Rupiah penuh), hitam = rumus. Kolom 2022-2023 dari LK audited dalam Prospektus IPO; 2024 dari komparatif LK FY2025 (Temuan D8). Dana syirkah temporer direklasifikasi ke liabilitas (Temuan D2).
B3: Sumber kolom | C3: Prospektus IPO 2025 (LK konsolidasian audited 2023/2022) | D3: Prospektus IPO 2025 (LK konsolidasian audited 2023/2022) | E3: LK FY2025 (komparatif) | F3: LK FY2025 | G3: Catatan sumber: DKHH (PT Cipta Sarana Medika Tbk), IPO 2025. Histori model FY2022-FY2025 (4 tahun). 2022-2023 dari LK konsolidasian audited dalam Prospektus IPO (disajikan proforma seolah restrukturisasi entitas sepe
A4: Kode | B4: Akun | C4: FY2022A | D4: FY2023A | E4: FY2024A | F4: FY2025A | G4: Catatan / sumber
B5: ARUS KAS OPERASI
A6: CF.CASH_FROM_CUSTOMERS | B6: Penerimaan kas dari pelanggan | C6: 101458663684 | D6: 129626427997 | E6: 143981788308 | F6: 151063423185 | G6: kunci JSON: terima_pelanggan
A7: CF.OTHER_OPER_RECEIPTS | B7: Penerimaan lain-lain | C7: 2786380201 | D7: 4079886993 | E7: 0 | F7: 0 | G7: kunci JSON: terima_lain
A8: CF.CASH_TO_EMPLOYEES | B8: Pembayaran kas kepada karyawan | C8: -22608563678 | D8: -42022919130 | E8: -73980910685 | F8: -85117618388 | G8: kunci JSON: bayar_karyawan
A9: CF.CASH_TO_SUPPLIERS | B9: Pembayaran kas kepada pemasok & lainnya | C9: -40865720296 | D9: -48709047407 | E9: -35270130188 | F9: -42386915098 | G9: kunci JSON: bayar_pemasok
A10: CF.OTHER_OPER_PAID | B10: Pembayaran beban operasional lain | C10: -27383498762 | D10: -17209085814 | E10: -16945082659 | F10: -21302607009 | G10: kunci JSON: bayar_opex_lain
A11: CF.CASH_GEN | B11: Kas dari pelanggan dikurangi pembayaran operasi (subtotal model; tidak tercetak) | C11: =C6+C7+C8+C9+C10 -> 13387261149 | D11: =D6+D7+D8+D9+D10 -> 25765262639 | E11: =E6+E7+E8+E9+E10 -> 17785664776 | F11: =F6+F7+F8+F9+F10 -> 2256282690
A12: CF.FIN_COST_PAID | B12: Pembayaran (penerimaan) bunga - neto (2025: penerimaan, Temuan D7) | C12: -3643595812 | D12: -7565985614 | E12: -11523542360 | F12: 4181857038 | G12: kunci JSON: bayar_bunga
A13: CF.TAX_PAID | B13: Pembayaran pajak penghasilan | C13: -2009565254 | D13: 1536428416 | E13: -3264434868 | F13: -870188358 | G13: kunci JSON: bayar_pajak
A14: CF.CFO | B14: Kas neto dari aktivitas operasi | C14: =C11+C12+C13 -> 7734100083 | D14: =D11+D12+D13 -> 19735705441 | E14: =E11+E12+E13 -> 2997687548 | F14: =F11+F12+F13 -> 5567951370
B15: ARUS KAS INVESTASI
A16: CF.CAPEX_PPE | B16: Perolehan aset tetap | C16: -16981553674 | D16: -36091707048 | E16: -24447662378 | F16: -3910827865 | G16: kunci JSON: perolehan_aset_tetap
A17: CF.PPE_ADVANCES | B17: Uang muka pembelian aset tetap & aset dalam penyelesaian | C17: 0 | D17: -54785129 | E17: 0 | F17: -23480000000 | G17: kunci JSON: uang_muka_aset_tetap
A18: CF.CAPEX_ROU | B18: Perolehan aset hak guna | C18: 0 | D18: 0 | E18: -2015875481 | F18: 0 | G18: kunci JSON: perolehan_rou
A19: CF.CAPEX_INTANG | B19: Perolehan aset takberwujud | G19: kunci JSON: -
A20: CF.PPE_DISPOSAL_PROCEEDS | B20: Hasil penjualan aset tetap | C20: 0 | D20: 0 | E20: 303123000 | F20: 0 | G20: kunci JSON: jual_aset_tetap
A21: CF.ASSOC_INVEST | B21: Investasi pada entitas asosiasi | G21: kunci JSON: -
A22: CF.NCI_ACQ | B22: Akuisisi kepentingan nonpengendali | G22: kunci JSON: -
A23: CF.SUB_ACQ | B23: Akuisisi entitas anak | G23: kunci JSON: -
A24: CF.CFI | B24: Kas neto untuk aktivitas investasi | C24: =C16+C17+C18+C19+C20+C21+C22+C23 -> -16981553674 | D24: =D16+D17+D18+D19+D20+D21+D22+D23 -> -36146492177 | E24: =E16+E17+E18+E19+E20+E21+E22+E23 -> -26160414859 | F24: =F16+F17+F18+F19+F20+F21+F22+F23 -> -27390827865
B25: ARUS KAS PENDANAAN
A26: CF.ST_BANK_DRAW | B26: Penerimaan pinjaman bank jangka pendek | G26: kunci JSON: -
A27: CF.ST_BANK_REPAY | B27: Pembayaran pinjaman bank jangka pendek | G27: kunci JSON: -
A28: CF.LT_BANK_DRAW | B28: Penerimaan utang bank jangka panjang | C28: 55246000000 | D28: 33071929334 | E28: 6717555926 | F28: 0 | G28: kunci JSON: bank_lt_draw
A29: CF.LT_BANK_REPAY | B29: Pembayaran utang bank jangka panjang | C29: -30887841073 | D29: -700008000 | E29: -4015634050 | F29: -12951313161 | G29: kunci JSON: bank_lt_repay
A30: CF.FIN_LEASE_PAID | B30: Pembayaran utang sewa pembiayaan | C30: -174137725 | D30: -258986069 | E30: -227712033 | F30: -141304358 | G30: kunci JSON: bayar_sewa_pemb
A31: CF.OTHER_LIAB_PAID | B31: Pembayaran liabilitas lainnya (pembiayaan peralatan) | G31: kunci JSON: -
A32: CF.SH_LOAN_REPAY | B32: Pembayaran utang pemegang saham | G32: kunci JSON: -
A33: CF.SYIRKAH_DRAW | B33: Penerimaan dana syirkah temporer | C33: 3000000000 | D33: 30000000000 | E33: 0 | F33: 0 | G33: kunci JSON: syirkah_tambah
A34: CF.SYIRKAH_PAID | B34: Pembayaran dana syirkah temporer | C34: -3427524256 | D34: -3844110996 | E34: -5744519363 | F34: -8780889744 | G34: kunci JSON: syirkah_bayar
A35: CF.FIN_LEASE_DRAW | B35: Penerimaan pembiayaan konsumen/sewa pembiayaan | C35: 282572850 | D35: 175237200 | E35: 0 | F35: 0 | G35: kunci JSON: kons_tambah
A36: CF.RP_RECEIPT | B36: Penerimaan dari pihak berelasi | C36: 0 | D36: 2977204389 | E36: 16843417535 | F36: 6968037795 | G36: kunci JSON: rp_terima
A37: CF.RP_PAYMENT | B37: Pembayaran/pemberian ke pihak berelasi | C37: -4933634156 | D37: -45093892823 | E37: -20468827761 | F37: -30103370433 | G37: kunci JSON: rp_bayar
A38: CF.SHARE_ISSUE | B38: Setoran modal / penerbitan saham (2025: IPO + pelaksanaan waran) | C38: 0 | D38: 0 | E38: 30763499000 | F38: 69203672050 | G38: kunci JSON: terbit_saham
A39: CF.RESTRICTED_CASH | B39: Dana yang dibatasi penggunaannya | C39: -30000000000 | D39: -30000000000 | E39: 0 | F39: 0 | G39: kunci JSON: dana_dibatasi
A40: CF.LEASE_PAID | B40: Pembayaran liabilitas sewa | C40: -163528380 | D40: 0 | E40: -505637369 | F40: -998837042 | G40: kunci JSON: bayar_sewa
A41: CF.DIVIDENDS_PAID | B41: Pembayaran dividen tunai (pemilik entitas induk; tidak ada) | G41: kunci JSON: -
A42: CF.NCI_DIV | B42: Dividen kepada kepentingan nonpengendali | G42: kunci JSON: -
A43: CF.CFF | B43: Kas neto dari (untuk) aktivitas pendanaan | C43: =C26+C27+C28+C29+C30+C31+C32+C33+C34+C35+C36+C37+C38+C39+C40+C41+C42 -> -11058092740 | D43: =D26+D27+D28+D29+D30+D31+D32+D33+D34+D35+D36+D37+D38+D39+D40+D41+D42 -> -13672626965 | E43: =E26+E27+E28+E29+E30+E31+E32+E33+E34+E35+E36+E37+E38+E39+E40+E41+E42 -> 23362141885 | F43: =F26+F27+F28+F29+F30+F31+F32+F33+F34+F35+F36+F37+F38+F39+F40+F41+F42 -> 23195995107
A44: CF.NET_CHANGE | B44: Kenaikan (penurunan) neto kas | C44: =C14+C24+C43 -> -20305546331 | D44: =D14+D24+D43 -> -30083413701 | E44: =E14+E24+E43 -> 199414574 | F44: =F14+F24+F43 -> 1373118612
A45: CF.CASH_BEGIN | B45: Kas awal tahun | C45: 59602857240 | D45: 29547207476 | E45: 2463973775 | F45: 2663388349 | G45: kunci JSON: KAS_AWAL
A46: CF.CASH_END | B46: Kas akhir tahun | C46: =C44+C45 -> 39297310909 | D46: =D44+D45 -> -536206225 | E46: =E44+E45 -> 2663388349 | F46: =F44+F45 -> 4036506961
B47: MEMO: SUBTOTAL TERCETAK DI LK
A48: CF.CFO_PRINTED | B48: Kas neto operasi (tercetak) | C48: 7734100083 | D48: 19735705441 | E48: 2997687548 | F48: 5567951370 | G48: kunci JSON: NET_OPERASI
A49: CF.CFI_PRINTED | B49: Kas neto investasi (tercetak) | C49: -16981553674 | D49: -36146492177 | E49: -26160414859 | F49: -27390827865 | G49: kunci JSON: NET_INVESTASI
A50: CF.CFF_PRINTED | B50: Kas neto pendanaan (tercetak) | C50: -11058092740 | D50: -13672626965 | E50: 23362141885 | F50: 23195995107 | G50: kunci JSON: NET_PENDANAAN
A51: CF.NET_CHANGE_PRINTED | B51: Kenaikan neto kas (tercetak) | C51: -20305546331 | D51: -30083413701 | E51: 199414574 | F51: 1373118612 | G51: kunci JSON: KENAIKAN_NETO
A52: CF.CASH_END_PRINTED | B52: Kas akhir (tercetak) | C52: 39297310909 | D52: -536206225 | E52: 2663388349 | F52: 4036506961 | G52: kunci JSON: KAS_AKHIR

Sheet Schedules
A1: Schedules CALK FY2022A-FY2025A
A2: Rincian catatan atas LK (tahapD, Rp penuh). Bagian A = ringkasan yang dipakai Rasio/Asumsi; bagian B-C = rincian lengkap. Kolom 2022-2023 dari catatan LK audited dalam prospektus (Cat 28-30 asli), 2024-2025 dari LK FY2025 (Cat 25-27); nomor diseragamkan ke LK FY2025: pendapatan Cat 25, beban pokok Cat 26, beban usaha Cat 27, aset tetap Cat 10. Mutasi aset tetap hanya 2024-2025 (Temuan D8).
B3: Sumber kolom | C3: Prospektus IPO 2025 (LK konsolidasian audited 2023/2022) | D3: Prospektus IPO 2025 (LK konsolidasian audited 2023/2022) | E3: LK FY2025 (komparatif) | F3: LK FY2025
A4: Kode | B4: Akun | C4: FY2022A | D4: FY2023A | E4: FY2024A | F4: FY2025A | G4: Catatan / sumber
B5: A. RINGKASAN UNTUK MODEL (rumus dari bagian B-C)
A6: REV.MED | B6: Pendapatan - penunjang medis (farmasi, laboratorium, radiologi) | C6: =N(C50)+N(C53)+N(C54)+N(C55) -> 2534971388 | D6: =N(D50)+N(D53)+N(D54)+N(D55) -> 11883764227 | E6: =N(E50)+N(E53)+N(E54)+N(E55) -> 46134618145 | F6: =N(F50)+N(F53)+N(F54)+N(F55) -> 30600343048 | G6: Cat 25
A7: REV.INPAT | B7: Pendapatan - rawat inap | C7: =N(C48) -> 53534000426 | D7: =N(D48) -> 79579352582 | E7: =N(E48) -> 85919977894 | F7: =N(F48) -> 74120487810 | G7: Cat 25
A8: REV.OUTPAT | B8: Pendapatan - rawat jalan | C8: =N(C49) -> 43332660354 | D8: =N(D49) -> 42651501335 | E8: =N(E49) -> 19931209046 | F8: =N(F49) -> 39969278831 | G8: Cat 25
A9: REV.OTHER | B9: Pendapatan lainnya (administrasi & lainnya = jumlah tercetak - 3 kelompok) | C9: =N(C52)-C6-C7-C8 -> 176512253 | D9: =N(D52)-D6-D7-D8 -> 73060785 | E9: =N(E52)-E6-E7-E8 -> 156443699 | F9: =N(F52)-F6-F7-F8 -> 183158700 | G9: Cat 25; diturunkan
A10: REV.NET | B10: Pendapatan (rumus) | C10: =C6+C7+C8+C9 -> 99578144421 | D10: =D6+D7+D8+D9 -> 134187678929 | E10: =E6+E7+E8+E9 -> 152142248784 | F10: =F6+F7+F8+F9 -> 144873268389
A11: REV.MED_SH | B11: Porsi penunjang medis % pendapatan | C11: =IFERROR(C6/C10,0) -> 0.025457106 | D11: =IFERROR(D6/D10,0) -> 0.08856077 | E11: =IFERROR(E6/E10,0) -> 0.30323344 | F11: =IFERROR(F6/F10,0) -> 0.21122146
A12: DA.DEP_IN_COGS | B12: Penyusutan aset tetap di beban pokok (Cat 26) | C12: =N(C60) -> 3755552276 | D12: =N(D60) -> 4387072246 | E12: =N(E60) -> 4973386980 | F12: =N(F60) -> 9923656145 | G12: Cat 26
A13: DA.IN_OPEX | B13: Penyusutan aset tetap di beban usaha (Cat 27) | C13: =N(C80) -> 3022617102 | D13: =N(D80) -> 3367608857 | E13: =N(E80) -> 4075347826 | F13: =N(F80) -> 2073385940 | G13: Cat 27
A14: DA.PPE | B14: Penyusutan aset tetap (Cat 26 + 27) | C14: =C12+C13 -> 6778169378 | D14: =D12+D13 -> 7754681103 | E14: =E12+E13 -> 9048734806 | F14: =F12+F13 -> 11997042085
A15: DA.MUT | B15: Penyusutan menurut mutasi Cat 10 (-akumulasi: penambahan) | C15: =-C39 -> 0 | D15: =-D39 -> 0 | E15: =-E39 -> 9080234808 | F15: =-F39 -> 11997042085
A16: DA.ROU | B16: Penyusutan aset hak guna (di beban pokok, Cat 26) | C16: =N(C61) -> 0 | D16: =N(D61) -> 0 | E16: =N(E61) -> 707291669 | F16: =N(F61) -> 606250000 | G16: Cat 26
A17: DA.AMORT_COGS | B17: Amortisasi aset takberwujud di beban pokok (tidak ada) | C17: =0 -> 0 | D17: =0 -> 0 | E17: =0 -> 0 | F17: =0 -> 0 | G17: tidak ada
A18: DA.AMORT_OPEX | B18: Amortisasi aset takberwujud di beban usaha (tidak ada) | C18: =0 -> 0 | D18: =0 -> 0 | E18: =0 -> 0 | F18: =0 -> 0 | G18: tidak ada
A19: DA.SOFTWARE | B19: Amortisasi aset takberwujud (tidak ada) | C19: =C17+C18 -> 0 | D19: =D17+D18 -> 0 | E19: =E17+E18 -> 0 | F19: =F17+F18 -> 0 | G19: tidak ada
A20: DA.TOTAL | B20: Total D&A (untuk EBITDA) | C20: =C14+C16+C19 -> 6778169378 | D20: =D14+D16+D19 -> 7754681103 | E20: =E14+E16+E19 -> 9756026475 | F20: =F14+F16+F19 -> 12603292085
A21: PPE.ADDITIONS | B21: Penambahan aset tetap (biaya perolehan, kas + nonkas) | C21: =C31 -> 0 | D21: =D31 -> 0 | E21: =E31 -> 24447662378 | F21: =F31 -> 3910827865
A22: EPS.WSH | B22: Rata-rata tertimbang saham beredar - dasar (lembar) | C22: =C86 -> 554690000 | D22: =D86 -> 554690000 | E22: =E86 -> 800250192 | F22: =F86 -> 2364143916 | G22: Cat laba per saham
B27: B. MUTASI ASET TETAP (Cat 10 LK FY2025, baris JUMLAH; 2022-2023 tidak tersedia di model; aset hak guna terpisah)
B28: Cat 10 Aset tetap - biaya perolehan (JUMLAH)
A29: MUT.COST_T.saldo_awal | B29: Saldo awal | E29: 168037297279 | F29: 192052959656 | G29: mutasi_aset (biaya perolehan)
A30: MUT.COST_T.akuisisi | B30: Akuisisi entitas anak | E30: 0 | F30: 0
A31: MUT.COST_T.penambahan | B31: Penambahan | E31: 24447662378 | F31: 3910827865
A32: MUT.COST_T.pengurangan | B32: Pengurangan | E32: -432000000 | F32: -1182040600
A33: MUT.COST_T.reklasifikasi | B33: Reklasifikasi + revaluasi + penurunan nilai | E33: 0 | F33: 6537547527
A34: MUT.COST_T.saldo_akhir | B34: Saldo akhir (tercetak) | E34: 192052959657 | F34: 201319294448
A35: MUT.COST_T.END | B35: Saldo akhir (rumus: awal + akuisisi + penambahan + pengurangan + reklas) | C35: =C29+N(C30)+C31+C32+C33 -> 0 | D35: =D29+N(D30)+D31+D32+D33 -> 0 | E35: =E29+N(E30)+E31+E32+E33 -> 192052959657 | F35: =F29+N(F30)+F31+F32+F33 -> 201319294448
B36: Cat 10 Aset tetap - akumulasi penyusutan (JUMLAH; disimpan bertanda negatif, LK mencetak positif)
A37: MUT.AD_T.saldo_awal | B37: Saldo awal | E37: -50618558085 | F37: -59667292892 | G37: mutasi_aset (akumulasi penyusutan)
A38: MUT.AD_T.akuisisi | B38: Akuisisi entitas anak | E38: 0 | F38: 0
A39: MUT.AD_T.penambahan | B39: Penambahan | E39: -9080234808 | F39: -11997042085
A40: MUT.AD_T.pengurangan | B40: Pengurangan | E40: 31500000 | F40: 1148516683
A41: MUT.AD_T.reklasifikasi | B41: Reklasifikasi + revaluasi + penurunan nilai | E41: 0 | F41: -2882403127
A42: MUT.AD_T.saldo_akhir | B42: Saldo akhir (tercetak) | E42: -59667292893 | F42: -73398221421
A43: MUT.AD_T.END | B43: Saldo akhir (rumus: awal + akuisisi + penambahan + pengurangan + reklas) | C43: =C37+N(C38)+C39+C40+C41 -> 0 | D43: =D37+N(D38)+D39+D40+D41 -> 0 | E43: =E37+N(E38)+E39+E40+E41 -> -59667292893 | F43: =F37+N(F38)+F39+F40+F41 -> -73398221421
A44: PPE.NBV | B44: Nilai tercatat aset tetap (biaya + akumulasi bertanda negatif) | C44: =C34+C42 -> 0 | D44: =D34+D42 -> 0 | E44: =E34+E42 -> 132385666764 | F44: =F34+F42 -> 127921073027
B46: C. RINCIAN CATATAN (urut catatan LK)
B47: Cat 25 - Pendapatan
A48: CK001 | B48: Rawat inap | C48: 53534000426 | D48: 79579352582 | E48: 85919977894 | F48: 74120487810 | G48: hal PDF 367,83
A49: CK002 | B49: Rawat jalan | C49: 43332660354 | D49: 42651501335 | E49: 19931209046 | F49: 39969278831 | G49: hal PDF 367,83
A50: CK003 | B50: Penunjang medis | E50: 46134618145 | F50: 30600343048 | G50: hal PDF 83
A51: CK004 | B51: Administrasi dan lainnya | C51: 176512253 | D51: 73060785 | E51: 156443699 | F51: 183158701 | G51: hal PDF 367,83
A52: CK005 | B52: JUMLAH (lapor) | C52: 99578144421 | D52: 134187678929 | E52: 152142248784 | F52: 144873268389 | G52: hal PDF 367,83
A53: CK006 | B53: Farmasi | C53: 1277775973 | D53: 8040524868 | G53: hal PDF 367
A54: CK007 | B54: Laboratorium | C54: 1112931345 | D54: 3114336730 | G54: hal PDF 367
A55: CK008 | B55: Radiologi | C55: 144264070 | D55: 728902629 | G55: hal PDF 367
A56: SK001 | B56: Σ rincian (rumus) | C56: =N(C48)+N(C49)+N(C50)+N(C51)+N(C53)+N(C54)+N(C55) -> 99578144421 | D56: =N(D48)+N(D49)+N(D50)+N(D51)+N(D53)+N(D54)+N(D55) -> 134187678929 | E56: =N(E48)+N(E49)+N(E50)+N(E51)+N(E53)+N(E54)+N(E55) -> 152142248784 | F56: =N(F48)+N(F49)+N(F50)+N(F51)+N(F53)+N(F54)+N(F55) -> 144873268390
B57: Cat 26 - Beban pokok pendapatan
A58: CK009 | B58: Gaji dan tenaga medis | C58: 19746085035 | D58: 29012609659 | E58: 38575259386 | F58: 64636564388 | G58: hal PDF 367,83
A59: CK010 | B59: Obat dan alat kesehatan | C59: 26066288746 | D59: 33030769915 | E59: 41214713009 | F59: 23306223421 | G59: hal PDF 367,83
A60: CK011 | B60: Penyusutan aset tetap | C60: 3755552276 | D60: 4387072246 | E60: 4973386980 | F60: 9923656145 | G60: hal PDF 367,83
A61: CK012 | B61: Penyusutan aset hak guna | C61: 0 | D61: 0 | E61: 707291669 | F61: 606250000 | G61: hal PDF 367,83
A62: CK013 | B62: Rawat inap dan kamar operasi | E62: 11812827466 | F62: 2398588758 | G62: hal PDF 83
A63: CK014 | B63: Pemakaian/perlengkapan klinik | C63: 1883539295 | D63: 2281300964 | E63: 1618402664 | F63: 2680847994 | G63: hal PDF 367,83
A64: CK015 | B64: Utilitas | C64: 230063054 | D64: 626171992 | E64: 917366831 | F64: 1089875422 | G64: hal PDF 367,83
A65: CK016 | B65: Penunjang medis | E65: 3187994515 | F65: 1672912728 | G65: hal PDF 83
A66: CK017 | B66: Sewa alat medis | C66: 979911350 | D66: 1090431600 | E66: 505050750 | F66: 1641932300 | G66: hal PDF 367,83
A67: CK018 | B67: Biaya rujukan | C67: 354241470 | D67: 458820820 | E67: 686478195 | F67: 1407238790 | G67: hal PDF 367,83
A68: CK019 | B68: Pemeliharaan dan perbaikan | C68: 555306373 | D68: 1023304167 | E68: 381321330 | F68: 1031777229 | G68: hal PDF 367,83
A69: CK020 | B69: Lain-lain | C69: 2232988784 | D69: 2611123706 | E69: 226383655 | F69: 336596794 | G69: hal PDF 367,83
A70: CK021 | B70: JUMLAH (lapor) | C70: 67593755280 | D70: 89574415546 | E70: 104806476450 | F70: 110732463969 | G70: hal PDF 367,83
A71: CK022 | B71: Biaya langsung (prospektus) | C71: 11789778897 | D71: 15052810477 | G71: hal PDF 367
A72: SK002 | B72: Σ rincian (rumus) | C72: =N(C58)+N(C59)+N(C60)+N(C61)+N(C62)+N(C63)+N(C64)+N(C65)+N(C66)+N(C67)+N(C68)+N(C69)+N(C71) -> 67593755280 | D72: =N(D58)+N(D59)+N(D60)+N(D61)+N(D62)+N(D63)+N(D64)+N(D65)+N(D66)+N(D67)+N(D68)+N(D69)+N(D71) -> 89574415546 | E72: =N(E58)+N(E59)+N(E60)+N(E61)+N(E62)+N(E63)+N(E64)+N(E65)+N(E66)+N(E67)+N(E68)+N(E69)+N(E71) -> 104806476450 | F72: =N(F58)+N(F59)+N(F60)+N(F61)+N(F62)+N(F63)+N(F64)+N(F65)+N(F66)+N(F67)+N(F68)+N(F69)+N(F71) -> 110732463969
B73: Cat 27 - Beban penjualan
A74: CK023 | B74: Pemasaran | C74: 692431321 | D74: 2861277353 | E74: 3319996186 | F74: 1925473993 | G74: hal PDF 368,84
A75: CK024 | B75: Gaji dan tunjangan | C75: 282465032 | D75: 322528578 | E75: 741963107 | F75: 857811457 | G75: hal PDF 368,84
A76: CK025 | B76: JUMLAH (lapor) | C76: 974896353 | D76: 3183805931 | E76: 4061959293 | F76: 2783285450 | G76: hal PDF 368,84
A77: SK003 | B77: Σ rincian (rumus) | C77: =N(C74)+N(C75) -> 974896353 | D77: =N(D74)+N(D75) -> 3183805931 | E77: =N(E74)+N(E75) -> 4061959293 | F77: =N(F74)+N(F75) -> 2783285450
B78: Cat 27 - Beban umum dan administrasi
A79: CK026 | B79: Gaji dan tunjangan | C79: 11114790783 | D79: 13015396797 | E79: 14709205914 | F79: 14581994830 | G79: hal PDF 368,84
A80: CK027 | B80: Penyusutan aset tetap | C80: 3022617102 | D80: 3367608857 | E80: 4075347826 | F80: 2073385940 | G80: hal PDF 368,84
A81: CK028 | B81: Lain-lain | C81: 9726087537 | D81: 15372057135 | E81: 13178104336 | F81: 11251498142 | G81: hal PDF 368,84
A82: CK029 | B82: JUMLAH (lapor) | C82: 23863495422 | D82: 31755062789 | E82: 31962658076 | F82: 27906878912 | G82: hal PDF 368,84
A83: SK004 | B83: Σ rincian (rumus) | C83: =N(C79)+N(C80)+N(C81) -> 23863495422 | D83: =N(D79)+N(D80)+N(D81) -> 31755062789 | E83: =N(E79)+N(E80)+N(E81) -> 31962658076 | F83: =N(F79)+N(F80)+N(F81) -> 27906878912
B84: Cat EPS - Laba per saham
A85: CK030 | B85: Laba diatribusikan ke pemilik entitas induk | C85: 4888165764 | D85: 3539716397 | E85: 2837231824 | F85: 6021648113 | G85: hal PDF None
A86: CK031 | B86: Rata-rata tertimbang saham beredar (dasar) | C86: 554690000 | D86: 554690000 | E86: 800250192 | F86: 2364143916 | G86: hal PDF None

Sheet Rasio
A1: Rasio keuangan FY2022A-FY2025A
A2: Rumus dari IS/BS/CF/Schedules. Rata-rata saldo & pertumbuhan mulai 2023 (kolom 2022 = kolom pertama). Kolom rata-rata = FY2022-FY2025 (rasio pertumbuhan/rata-rata saldo: 2023-2025).
A4: Kode | B4: Akun | C4: FY2022A | D4: FY2023A | E4: FY2024A | F4: FY2025A | G4: Rata-rata FY2022-25 | H4: Definisi / catatan
B5: PERTUMBUHAN (yoy)
A6: R.G_REV | B6: Pendapatan | D6: =IFERROR(IS!D6/IS!C6-1,0) -> 0.34756155 | E6: =IFERROR(IS!E6/IS!D6-1,0) -> 0.13380193 | F6: =IFERROR(IS!F6/IS!E6-1,0) -> -0.047777527 | G6: =AVERAGE(C6:F6) -> 0.14452865
A7: R.G_MED | B7: Penunjang medis | D7: =IFERROR(Schedules!D6/Schedules!C6-1,0) -> 3.6879283 | E7: =IFERROR(Schedules!E6/Schedules!D6-1,0) -> 2.8821553 | F7: =IFERROR(Schedules!F6/Schedules!E6-1,0) -> -0.33671624 | G7: =AVERAGE(C7:F7) -> 2.0777891
A8: R.G_INPAT | B8: Rawat inap | D8: =IFERROR(Schedules!D7/Schedules!C7-1,0) -> 0.48651982 | E8: =IFERROR(Schedules!E7/Schedules!D7-1,0) -> 0.079676764 | F8: =IFERROR(Schedules!F7/Schedules!E7-1,0) -> -0.13733116 | G8: =AVERAGE(C8:F8) -> 0.14295514
A9: R.G_OUTPAT | B9: Rawat jalan | D9: =IFERROR(Schedules!D8/Schedules!C8-1,0) -> -0.015719298 | E9: =IFERROR(Schedules!E8/Schedules!D8-1,0) -> -0.53269619 | F9: =IFERROR(Schedules!F8/Schedules!E8-1,0) -> 1.0053615 | G9: =AVERAGE(C9:F9) -> 0.15231533
A10: R.G_EBITDA | B10: EBITDA | D10: =IFERROR((IS!D14+Schedules!D20)/(IS!C14+Schedules!C20)-1,0) -> 0.15536341 | E10: =IFERROR((IS!E14+Schedules!E20)/(IS!D14+Schedules!D20)-1,0) -> 0.22147209 | F10: =IFERROR((IS!F14+Schedules!F20)/(IS!E14+Schedules!E20)-1,0) -> -0.28236748 | G10: =AVERAGE(C10:F10) -> 0.031489337
A11: R.G_NI | B11: Laba tahun berjalan | D11: =IFERROR(IS!D20/IS!C20-1,0) -> -0.27585999 | E11: =IFERROR(IS!E20/IS!D20-1,0) -> -0.19842073 | F11: =IFERROR(IS!F20/IS!E20-1,0) -> 1.1223569 | G11: =AVERAGE(C11:F11) -> 0.21602539
A12: R.G_NIP | B12: Laba pemilik entitas induk | D12: =IFERROR(IS!D29/IS!C29-1,0) -> -0.27585999 | E12: =IFERROR(IS!E29/IS!D29-1,0) -> -0.19845787 | F12: =IFERROR(IS!F29/IS!E29-1,0) -> 1.1223673 | G12: =AVERAGE(C12:F12) -> 0.21601649
B13: PROFITABILITAS
A14: R.GM | B14: Margin laba bruto | C14: =IFERROR(IS!C8/IS!C6,0) -> 0.32119889 | D14: =IFERROR(IS!D8/IS!D6,0) -> 0.33246915 | E14: =IFERROR(IS!E8/IS!E6,0) -> 0.31112839 | F14: =IFERROR(IS!F8/IS!F6,0) -> 0.23565979 | G14: =AVERAGE(C14:F14) -> 0.30011405
A15: R.OPM | B15: Margin laba usaha | C15: =IFERROR(IS!C14/IS!C6,0) -> 0.084078592 | D15: =IFERROR(IS!D14/IS!D6,0) -> 0.072657349 | E15: =IFERROR(IS!E14/IS!E6,0) -> 0.076409493 | F15: =IFERROR(IS!F14/IS!F6,0) -> 0.01891659 | G15: =AVERAGE(C15:F15) -> 0.063015506
A16: R.EBITDA | B16: EBITDA (Rp) | C16: =(IS!C14+Schedules!C20) -> 15150559587 | D16: =(IS!D14+Schedules!D20) -> 17504402158 | E16: =(IS!E14+Schedules!E20) -> 21381138631 | F16: =(IS!F14+Schedules!F20) -> 15343800322 | G16: =AVERAGE(C16:F16) -> 1.7344975e+10 | H16: laba usaha model (termasuk pendapatan lain-lain neto) + penyusutan aset tetap (Cat 26+27) + penyusutan aset hak guna (Cat 26); tidak ada amortisasi
A17: R.EBITDA_M | B17: Margin EBITDA | C17: =IFERROR((IS!C14+Schedules!C20)/IS!C6,0) -> 0.15214744 | D17: =IFERROR((IS!D14+Schedules!D20)/IS!D6,0) -> 0.13044716 | E17: =IFERROR((IS!E14+Schedules!E20)/IS!E6,0) -> 0.14053387 | F17: =IFERROR((IS!F14+Schedules!F20)/IS!F6,0) -> 0.10591188 | G17: =AVERAGE(C17:F17) -> 0.13226009
A18: R.NM | B18: Margin laba bersih | C18: =IFERROR(IS!C20/IS!C6,0) -> 0.049088741 | D18: =IFERROR(IS!D20/IS!D6,0) -> 0.026378848 | E18: =IFERROR(IS!E20/IS!E6,0) -> 0.018649411 | F18: =IFERROR(IS!F20/IS!F6,0) -> 0.041566657 | G18: =AVERAGE(C18:F18) -> 0.033920914
A19: R.NMP | B19: Margin laba induk | C19: =IFERROR(IS!C29/IS!C6,0) -> 0.049088741 | D19: =IFERROR(IS!D29/IS!D6,0) -> 0.026378848 | E19: =IFERROR(IS!E29/IS!E6,0) -> 0.018648547 | F19: =IFERROR(IS!F29/IS!F6,0) -> 0.041564936 | G19: =AVERAGE(C19:F19) -> 0.033920268
A20: R.ROE | B20: ROE (laba induk / rata-rata ekuitas induk) | D20: =IFERROR(IS!D29/((BS!D59+BS!C59)/2),0) -> 0.039282225 | E20: =IFERROR(IS!E29/((BS!E59+BS!D59)/2),0) -> 0.02191938 | F20: =IFERROR(IS!F29/((BS!F59+BS!E59)/2),0) -> 0.035818841 | G20: =AVERAGE(C20:F20) -> 0.032340149
A21: R.ROA | B21: ROA (laba / rata-rata aset) | D21: =IFERROR(IS!D20/((BS!D27+BS!C27)/2),0) -> 0.015367912 | E21: =IFERROR(IS!E20/((BS!E27+BS!D27)/2),0) -> 0.009977188 | F21: =IFERROR(IS!F20/((BS!F27+BS!E27)/2),0) -> 0.020129586 | G21: =AVERAGE(C21:F21) -> 0.015158229
A22: R.ETR | B22: Tarif pajak efektif | C22: =IFERROR(-IS!C18/IS!C17,0) -> 0.25801251 | D22: =IFERROR(-IS!D18/IS!D17,0) -> 0.76735139 | E22: =IFERROR(-IS!E18/IS!E17,0) -> 6.9116652 | F22: =IFERROR(-IS!F18/IS!F17,0) -> -0.058527227 | G22: =AVERAGE(C22:F22) -> 1.9696255
A23: R.NCI_SH | B23: Porsi laba ke NCI | C23: =IFERROR(IS!C30/IS!C20,0) -> 0 | D23: =IFERROR(IS!D30/IS!D20,0) -> 0 | E23: =IFERROR(IS!E30/IS!E20,0) -> 4.6327871e-05 | F23: =IFERROR(IS!F30/IS!F20,0) -> 4.1416181e-05 | G23: =AVERAGE(C23:F23) -> 2.1936013e-05
A24: R.OTH | B24: Pendapatan (beban) lain neto % pendapatan | C24: =IFERROR(IS!C13/IS!C6,0) -> 0.012315884 | D24: =IFERROR(IS!D13/IS!D6,0) -> 0.00056135103 | E24: =IFERROR(IS!E13/IS!E6,0) -> 0.0020635766 | F24: =IFERROR(IS!F13/IS!F6,0) -> -0.004901745 | G24: =AVERAGE(C24:F24) -> 0.0025097666 | H24: pendapatan sewa & lain-lain neto (di atas laba usaha model)
B25: PENDAPATAN
A26: R.SH_MED | B26: Porsi penunjang medis (% pendapatan) | C26: =Schedules!C11 -> 0.025457106 | D26: =Schedules!D11 -> 0.08856077 | E26: =Schedules!E11 -> 0.30323344 | F26: =Schedules!F11 -> 0.21122146 | G26: =AVERAGE(C26:F26) -> 0.15711819
B27: MODAL KERJA (hari, saldo akhir)
A28: R.DSO | B28: DSO piutang usaha (hari) | C28: =IFERROR((BS!C8+BS!C9)/IS!C6*365,0) -> 44.41957 | D28: =IFERROR((BS!D8+BS!D9)/IS!D6*365,0) -> 45.652804 | E28: =IFERROR((BS!E8+BS!E9)/IS!E6*365,0) -> 60.158756 | F28: =IFERROR((BS!F8+BS!F9)/IS!F6*365,0) -> 47.54806 | G28: =AVERAGE(C28:F28) -> 49.444798
A29: R.DIO | B29: DIO persediaan (hari, atas beban pokok) | C29: =IFERROR(BS!C12/-IS!C7*365,0) -> 12.230195 | D29: =IFERROR(BS!D12/-IS!D7*365,0) -> 16.446123 | E29: =IFERROR(BS!E12/-IS!E7*365,0) -> 14.402743 | F29: =IFERROR(BS!F12/-IS!F7*365,0) -> 4.4045653 | G29: =AVERAGE(C29:F29) -> 11.870907
A30: R.DPO | B30: DPO utang usaha (hari, atas beban pokok) | C30: =IFERROR((BS!C30+BS!C31)/-IS!C7*365,0) -> 11.11998 | D30: =IFERROR((BS!D30+BS!D31)/-IS!D7*365,0) -> 19.447353 | E30: =IFERROR((BS!E30+BS!E31)/-IS!E7*365,0) -> 19.741758 | F30: =IFERROR((BS!F30+BS!F31)/-IS!F7*365,0) -> 21.683533 | G30: =AVERAGE(C30:F30) -> 17.998156
B31: LIKUIDITAS & SOLVABILITAS
A32: R.CR | B32: Current ratio | C32: =IFERROR(BS!C16/BS!C42,0) -> 2.4783916 | D32: =IFERROR(BS!D16/BS!D42,0) -> 0.66620686 | E32: =IFERROR(BS!E16/BS!E42,0) -> 0.88505694 | F32: =IFERROR(BS!F16/BS!F42,0) -> 1.19546 | G32: =AVERAGE(C32:F32) -> 1.3062789
A33: R.DEBT | B33: Utang berbunga: bank + pembiayaan konsumen + dana syirkah temporer (Rp) | C33: =(BS!C29+BS!C38+BS!C43+BS!C39+BS!C44+BS!C40+BS!C45+BS!C49+BS!C50) -> 93671342320 | D33: =(BS!D29+BS!D38+BS!D43+BS!D39+BS!D44+BS!D40+BS!D45+BS!D49+BS!D50) -> 145115583789 | E33: =(BS!E29+BS!E38+BS!E43+BS!E39+BS!E44+BS!E40+BS!E45+BS!E49+BS!E50) -> 111845439271 | F33: =(BS!F29+BS!F38+BS!F43+BS!F39+BS!F44+BS!F40+BS!F45+BS!F49+BS!F50) -> 89971932007 | G33: =AVERAGE(C33:F33) -> 1.1015107e+11 | H33: syirkah = pembiayaan musyarakah bank syariah, diperlakukan sebagai utang (Temuan D2)
A34: R.LEASE | B34: Liabilitas sewa (Rp) | C34: =(BS!C41+BS!C46) -> 0 | D34: =(BS!D41+BS!D46) -> 0 | E34: =(BS!E41+BS!E46) -> 2328487150 | F34: =(BS!F41+BS!F46) -> 1329650108 | G34: =AVERAGE(C34:F34) -> 9.1453431e+08
A35: R.CASHINV | B35: Kas dan setara kas (Rp) | C35: =(BS!C6+BS!C7) -> 29547207476 | D35: =(BS!D6+BS!D7) -> 2463973775 | E35: =(BS!E6+BS!E7) -> 2663388349 | F35: =(BS!F6+BS!F7) -> 4036506961 | G35: =AVERAGE(C35:F35) -> 9.6777691e+09
A36: R.ND | B36: Utang neto (utang + sewa - kas) (Rp) | C36: =(BS!C29+BS!C38+BS!C43+BS!C39+BS!C44+BS!C40+BS!C45+BS!C49+BS!C50)+(BS!C41+BS!C46)-BS!C6 -> 64124134844 | D36: =(BS!D29+BS!D38+BS!D43+BS!D39+BS!D44+BS!D40+BS!D45+BS!D49+BS!D50)+(BS!D41+BS!D46)-BS!D6 -> 142651610014 | E36: =(BS!E29+BS!E38+BS!E43+BS!E39+BS!E44+BS!E40+BS!E45+BS!E49+BS!E50)+(BS!E41+BS!E46)-BS!E6 -> 111510538072 | F36: =(BS!F29+BS!F38+BS!F43+BS!F39+BS!F44+BS!F40+BS!F45+BS!F49+BS!F50)+(BS!F41+BS!F46)-BS!F6 -> 87265075154 | G36: =AVERAGE(C36:F36) -> 101387839521 | H36: negatif = kas neto
A37: R.DE | B37: Utang / ekuitas | C37: =IFERROR((BS!C29+BS!C38+BS!C43+BS!C39+BS!C44+BS!C40+BS!C45+BS!C49+BS!C50)/BS!C61,0) -> 1.8342924 | D37: =IFERROR((BS!D29+BS!D38+BS!D43+BS!D39+BS!D44+BS!D40+BS!D45+BS!D49+BS!D50)/BS!D61,0) -> 1.1235943 | E37: =IFERROR((BS!E29+BS!E38+BS!E43+BS!E39+BS!E44+BS!E40+BS!E45+BS!E49+BS!E50)/BS!E61,0) -> 0.86214418 | F37: =IFERROR((BS!F29+BS!F38+BS!F43+BS!F39+BS!F44+BS!F40+BS!F45+BS!F49+BS!F50)/BS!F61,0) -> 0.43568679 | G37: =AVERAGE(C37:F37) -> 1.0639294
A38: R.NDE | B38: Utang neto / EBITDA | C38: =IFERROR(((BS!C29+BS!C38+BS!C43+BS!C39+BS!C44+BS!C40+BS!C45+BS!C49+BS!C50)+(BS!C41+BS!C46)-BS!C6)/(IS!C14+Schedules!C20),0) -> 4.2324598 | D38: =IFERROR(((BS!D29+BS!D38+BS!D43+BS!D39+BS!D44+BS!D40+BS!D45+BS!D49+BS!D50)+(BS!D41+BS!D46)-BS!D6)/(IS!D14+Schedules!D20),0) -> 8.1494706 | E38: =IFERROR(((BS!E29+BS!E38+BS!E43+BS!E39+BS!E44+BS!E40+BS!E45+BS!E49+BS!E50)+(BS!E41+BS!E46)-BS!E6)/(IS!E14+Schedules!E20),0) -> 5.2153695 | F38: =IFERROR(((BS!F29+BS!F38+BS!F43+BS!F39+BS!F44+BS!F40+BS!F45+BS!F49+BS!F50)+(BS!F41+BS!F46)-BS!F6)/(IS!F14+Schedules!F20),0) -> 5.6873182 | G38: =AVERAGE(C38:F38) -> 5.8211545
A39: R.ICR | B39: EBITDA / beban keuangan | C39: =IFERROR((IS!C14+Schedules!C20)/-IS!C15,0) -> 4.158134 | D39: =IFERROR((IS!D14+Schedules!D20)/-IS!D15,0) -> 2.3135654 | E39: =IFERROR((IS!E14+Schedules!E20)/-IS!E15,0) -> 1.850282 | F39: =IFERROR((IS!F14+Schedules!F20)/-IS!F15,0) -> 1.4981041 | G39: =AVERAGE(C39:F39) -> 2.4550214
B40: ARUS KAS
A41: R.CAPEX | B41: Capex (perolehan aset tetap + uang muka aset tetap) (Rp) | C41: =-(CF!C16+CF!C17) -> 16981553674 | D41: =-(CF!D16+CF!D17) -> 36146492177 | E41: =-(CF!E16+CF!E17) -> 24447662378 | F41: =-(CF!F16+CF!F17) -> 27390827865 | G41: =AVERAGE(C41:F41) -> 2.6241634e+10
A42: R.CAPEX_R | B42: Capex % pendapatan | C42: =IFERROR(-(CF!C16+CF!C17)/IS!C6,0) -> 0.17053495 | D42: =IFERROR(-(CF!D16+CF!D17)/IS!D6,0) -> 0.26937266 | E42: =IFERROR(-(CF!E16+CF!E17)/IS!E6,0) -> 0.1606895 | F42: =IFERROR(-(CF!F16+CF!F17)/IS!F6,0) -> 0.18906751 | G42: =AVERAGE(C42:F42) -> 0.19741616
A43: R.LEASE_R | B43: Pembayaran sewa % pendapatan | C43: =IFERROR(-CF!C40/IS!C6,0) -> 0.0016422116 | D43: =IFERROR(-CF!D40/IS!D6,0) -> 0 | E43: =IFERROR(-CF!E40/IS!E6,0) -> 0.0033234514 | F43: =IFERROR(-CF!F40/IS!F6,0) -> 0.0068945572 | G43: =AVERAGE(C43:F43) -> 0.0029650551
A44: R.FCF | B44: Arus kas bebas sederhana (CFO - capex + sewa dibayar) (Rp) | C44: =CF!C14--(CF!C16+CF!C17)+CF!C40 -> -9410981971 | D44: =CF!D14--(CF!D16+CF!D17)+CF!D40 -> -16410786736 | E44: =CF!E14--(CF!E16+CF!E17)+CF!E40 -> -21955612199 | F44: =CF!F14--(CF!F16+CF!F17)+CF!F40 -> -22821713537 | G44: =AVERAGE(C44:F44) -> -1.7649774e+10
A45: R.CCONV | B45: CFO / laba tahun berjalan | C45: =IFERROR(CF!C14/IS!C20,0) -> 1.582209 | D45: =IFERROR(CF!D14/IS!D20,0) -> 5.5755047 | E45: =IFERROR(CF!E14/IS!E20,0) -> 1.0565047 | F45: =IFERROR(CF!F14/IS!F20,0) -> 0.92461742 | G45: =AVERAGE(C45:F45) -> 2.284709
B46: PER SAHAM (informasi, bukan penilaian)
A47: R.EPS | B47: Laba induk / 2,550,078,941 saham tercatat (Rp) | C47: =IFERROR(IS!C29/2550078941,0) -> 1.9168684 | D47: =IFERROR(IS!D29/2550078941,0) -> 1.3880811 | E47: =IFERROR(IS!E29/2550078941,0) -> 1.1126055 | F47: =IFERROR(IS!F29/2550078941,0) -> 2.3613575 | G47: =AVERAGE(C47:F47) -> 1.6947281 | H47: saham tercatat akhir 2025 (setelah IPO & waran)
A48: R.EPS_W | B48: Laba induk / saham rata-rata tertimbang CALK (Rp) | C48: =IFERROR(IS!C29/Schedules!C22,0) -> 8.8124281 | D48: =IFERROR(IS!D29/Schedules!D22,0) -> 6.3814318 | E48: =IFERROR(IS!E29/Schedules!E22,0) -> 3.545431 | F48: =IFERROR(IS!F29/Schedules!F22,0) -> 2.5470734 | G48: =AVERAGE(C48:F48) -> 5.3215911
A49: R.EPS_P | B49: EPS dasar tercetak (Rp) | C49: =IS!C33 -> 8.81 | D49: =IS!D33 -> 6.38 | E49: =IS!E33 -> 4 | F49: =IS!F33 -> 3 | G49: =AVERAGE(C49:F49) -> 5.5475 | H49: Temuan D9
A50: R.BVPS | B50: Ekuitas induk per saham (Rp) | C50: =IFERROR(BS!C59/2550078941,0) -> 20.025554 | D50: =IFERROR(BS!D59/2550078941,0) -> 50.64667 | E50: =IFERROR(BS!E59/2550078941,0) -> 50.8713 | F50: =IFERROR(BS!F59/2550078941,0) -> 80.978725 | G50: =AVERAGE(C50:F50) -> 50.630562
A51: R.DIV | B51: Dividen tunai dibayar (Rp) | C51: =-CF!C41 -> 0 | D51: =-CF!D41 -> 0 | E51: =-CF!E41 -> 0 | F51: =-CF!F41 -> 0 | H51: dividen ke pemilik induk

Sheet Rekonsiliasi
A1: Rekonsiliasi & cek integritas (225 cek)
A2: Status = hasil rumus saat ini; Ekspektasi = hasil yang diharapkan dari data sumber (dihitung saat build). Semua ❌ yang diharapkan dijelaskan dan ditautkan ke Temuan.
B3: Ringkasan | C3: =IF(COUNTIF(K7:K231,"✖*")=0,"SEMUA 225 CEK SESUAI EKSPEKTASI","ADA "&COUNTIF(K7:K231,"✖*")&" CEK TIDAK SESUAI EKSPEKTASI") -> SEMUA 225 CEK SESUAI EKSPEKTASI
C4: ="OK: "&COUNTIF(I7:I231,"OK")&" | ❌ (diharapkan, dijelaskan di Temuan): "&COUNTIF(I7:I231,"❌")&" | N/A/INFO: "&(COUNTIF(I7:I231,"N/A")+COUNTIF(I7:I231,"INFO")) -> OK: 207 | ❌ (diharapkan, dijelaskan di Temuan): 11 | N/A/INFO: 7
A6: No | B6: Kategori | C6: Cek | D6: Tahun | E6: Nilai A | F6: Nilai B | G6: Selisih A-B | H6: Toleransi | I6: Status | J6: Ekspektasi | K6: Sesuai ekspektasi? | L6: Penjelasan / Temuan
A7: 1 | B7: Subtotal rumus vs tercetak | C7: IS: GROSS_PROFIT rumus = tercetak | D7: 2022 | E7: =IS!C8 -> 31984389141 | F7: =IS!C36 -> 31984389141 | G7: =IF(COUNT(E7:F7)=2,E7-F7,"") -> 0 | H7: 1 | I7: =IF(COUNT(E7:F7)<2,"N/A",IF(ABS(G7)<=H7,"OK","❌")) -> OK | J7: OK | K7: =IF(I7=J7,"✔ sesuai","✖ TIDAK sesuai") -> ✔ sesuai
A8: 2 | B8: Subtotal rumus vs tercetak | C8: IS: PBT rumus = tercetak | D8: 2022 | E8: =IS!C17 -> 4728794397 | F8: =IS!C38 -> 4728794397 | G8: =IF(COUNT(E8:F8)=2,E8-F8,"") -> 0 | H8: 1 | I8: =IF(COUNT(E8:F8)<2,"N/A",IF(ABS(G8)<=H8,"OK","❌")) -> OK | J8: OK | K8: =IF(I8=J8,"✔ sesuai","✖ TIDAK sesuai") -> ✔ sesuai
A9: 3 | B9: Subtotal rumus vs tercetak | C9: IS: NET_INCOME rumus = tercetak | D9: 2022 | E9: =IS!C20 -> 4888165764 | F9: =IS!C39 -> 4888165764 | G9: =IF(COUNT(E9:F9)=2,E9-F9,"") -> 0 | H9: 1 | I9: =IF(COUNT(E9:F9)<2,"N/A",IF(ABS(G9)<=H9,"OK","❌")) -> OK | J9: OK | K9: =IF(I9=J9,"✔ sesuai","✖ TIDAK sesuai") -> ✔ sesuai
A10: 4 | B10: Subtotal rumus vs tercetak | C10: IS: OCI_TOTAL rumus = tercetak | D10: 2022 | E10: =IS!C26 -> -284437806 | F10: =IS!C40 -> -284437806 | G10: =IF(COUNT(E10:F10)=2,E10-F10,"") -> 0 | H10: 1 | I10: =IF(COUNT(E10:F10)<2,"N/A",IF(ABS(G10)<=H10,"OK","❌")) -> OK | J10: OK | K10: =IF(I10=J10,"✔ sesuai","✖ TIDAK sesuai") -> ✔ sesuai
A11: 5 | B11: Subtotal rumus vs tercetak | C11: IS: TCI rumus = tercetak | D11: 2022 | E11: =IS!C27 -> 4603727958 | F11: =IS!C41 -> 4603727958 | G11: =IF(COUNT(E11:F11)=2,E11-F11,"") -> 0 | H11: 1 | I11: =IF(COUNT(E11:F11)<2,"N/A",IF(ABS(G11)<=H11,"OK","❌")) -> OK | J11: OK | K11: =IF(I11=J11,"✔ sesuai","✖ TIDAK sesuai") -> ✔ sesuai
A12: 6 | B12: Subtotal rumus vs tercetak | C12: BS: TOTAL_CA rumus = tercetak | D12: 2022 | E12: =BS!C16 -> 45616358950 | F12: =BS!C67 -> 45616358950 | G12: =IF(COUNT(E12:F12)=2,E12-F12,"") -> 0 | H12: 1 | I12: =IF(COUNT(E12:F12)<2,"N/A",IF(ABS(G12)<=H12,"OK","❌")) -> OK | J12: OK | K12: =IF(I12=J12,"✔ sesuai","✖ TIDAK sesuai") -> ✔ sesuai
A13: 7 | B13: Subtotal rumus vs tercetak | C13: BS: TOTAL_NCA rumus = tercetak | D13: 2022 | E13: =BS!C26 -> 114377030301 | F13: =BS!C68 -> 114377030301 | G13: =IF(COUNT(E13:F13)=2,E13-F13,"") -> 0 | H13: 1 | I13: =IF(COUNT(E13:F13)<2,"N/A",IF(ABS(G13)<=H13,"OK","❌")) -> OK | J13: OK | K13: =IF(I13=J13,"✔ sesuai","✖ TIDAK sesuai") -> ✔ sesuai
A14: 8 | B14: Subtotal rumus vs tercetak | C14: BS: TOTAL_ASSETS rumus = tercetak | D14: 2022 | E14: =BS!C27 -> 159993389251 | F14: =BS!C69 -> 159993389251 | G14: =IF(COUNT(E14:F14)=2,E14-F14,"") -> 0 | H14: 1 | I14: =IF(COUNT(E14:F14)<2,"N/A",IF(ABS(G14)<=H14,"OK","❌")) -> OK | J14: OK | K14: =IF(I14=J14,"✔ sesuai","✖ TIDAK sesuai") -> ✔ sesuai
A15: 9 | B15: Subtotal rumus vs tercetak | C15: BS: TOTAL_CL rumus = tercetak | D15: 2022 | E15: =BS!C42 -> 18405630017 | F15: =BS!C70 -> 18405630017 | G15: =IF(COUNT(E15:F15)=2,E15-F15,"") -> 0 | H15: 1 | I15: =IF(COUNT(E15:F15)<2,"N/A",IF(ABS(G15)<=H15,"OK","❌")) -> OK | J15: OK | K15: =IF(I15=J15,"✔ sesuai","✖ TIDAK sesuai") -> ✔ sesuai
A16: 10 | B16: Subtotal rumus vs tercetak | C16: BS: TOTAL_NCL rumus = tercetak | D16: 2022 | E16: =BS!C51 -> 90521014507 | F16: =BS!C71 -> 90521014507 | G16: =IF(COUNT(E16:F16)=2,E16-F16,"") -> 0 | H16: 1 | I16: =IF(COUNT(E16:F16)<2,"N/A",IF(ABS(G16)<=H16,"OK","❌")) -> OK | J16: OK | K16: =IF(I16=J16,"✔ sesuai","✖ TIDAK sesuai") -> ✔ sesuai
A17: 11 | B17: Subtotal rumus vs tercetak | C17: BS: TOTAL_LIAB rumus = tercetak | D17: 2022 | E17: =BS!C52 -> 108926644524 | F17: =BS!C72 -> 108926644524 | G17: =IF(COUNT(E17:F17)=2,E17-F17,"") -> 0 | H17: 1 | I17: =IF(COUNT(E17:F17)<2,"N/A",IF(ABS(G17)<=H17,"OK","❌")) -> OK | J17: OK | K17: =IF(I17=J17,"✔ sesuai","✖ TIDAK sesuai") -> ✔ sesuai
A18: 12 | B18: Subtotal rumus vs tercetak | C18: BS: EQUITY_PARENT rumus = tercetak | D18: 2022 | E18: =BS!C59 -> 51066744727 | F18: =BS!C73 -> 51066744727 | G18: =IF(COUNT(E18:F18)=2,E18-F18,"") -> 0 | H18: 1 | I18: =IF(COUNT(E18:F18)<2,"N/A",IF(ABS(G18)<=H18,"OK","❌")) -> OK | J18: OK | K18: =IF(I18=J18,"✔ sesuai","✖ TIDAK sesuai") -> ✔ sesuai
A19: 13 | B19: Subtotal rumus vs tercetak | C19: BS: TOTAL_EQUITY rumus = tercetak | D19: 2022 | E19: =BS!C61 -> 51066744727 | F19: =BS!C74 -> 51066744727 | G19: =IF(COUNT(E19:F19)=2,E19-F19,"") -> 0 | H19: 1 | I19: =IF(COUNT(E19:F19)<2,"N/A",IF(ABS(G19)<=H19,"OK","❌")) -> OK | J19: OK | K19: =IF(I19=J19,"✔ sesuai","✖ TIDAK sesuai") -> ✔ sesuai
A20: 14 | B20: Subtotal rumus vs tercetak | C20: BS: TOTAL_LIAB_EQUITY rumus = tercetak | D20: 2022 | E20: =BS!C62 -> 159993389251 | F20: =BS!C75 -> 159993389251 | G20: =IF(COUNT(E20:F20)=2,E20-F20,"") -> 0 | H20: 1 | I20: =IF(COUNT(E20:F20)<2,"N/A",IF(ABS(G20)<=H20,"OK","❌")) -> OK | J20: OK | K20: =IF(I20=J20,"✔ sesuai","✖ TIDAK sesuai") -> ✔ sesuai
A21: 15 | B21: Subtotal rumus vs tercetak | C21: CF: CFO rumus = tercetak | D21: 2022 | E21: =CF!C14 -> 7734100083 | F21: =CF!C48 -> 7734100083 | G21: =IF(COUNT(E21:F21)=2,E21-F21,"") -> 0 | H21: 1 | I21: =IF(COUNT(E21:F21)<2,"N/A",IF(ABS(G21)<=H21,"OK","❌")) -> OK | J21: OK | K21: =IF(I21=J21,"✔ sesuai","✖ TIDAK sesuai") -> ✔ sesuai
A22: 16 | B22: Subtotal rumus vs tercetak | C22: CF: CFI rumus = tercetak | D22: 2022 | E22: =CF!C24 -> -16981553674 | F22: =CF!C49 -> -16981553674 | G22: =IF(COUNT(E22:F22)=2,E22-F22,"") -> 0 | H22: 1 | I22: =IF(COUNT(E22:F22)<2,"N/A",IF(ABS(G22)<=H22,"OK","❌")) -> OK | J22: OK | K22: =IF(I22=J22,"✔ sesuai","✖ TIDAK sesuai") -> ✔ sesuai
A23: 17 | B23: Subtotal rumus vs tercetak | C23: CF: CFF rumus = tercetak | D23: 2022 | E23: =CF!C43 -> -11058092740 | F23: =CF!C50 -> -11058092740 | G23: =IF(COUNT(E23:F23)=2,E23-F23,"") -> 0 | H23: 1 | I23: =IF(COUNT(E23:F23)<2,"N/A",IF(ABS(G23)<=H23,"OK","❌")) -> OK | J23: OK | K23: =IF(I23=J23,"✔ sesuai","✖ TIDAK sesuai") -> ✔ sesuai
A24: 18 | B24: Subtotal rumus vs tercetak | C24: CF: NET_CHANGE rumus = tercetak | D24: 2022 | E24: =CF!C44 -> -20305546331 | F24: =CF!C51 -> -20305546331 | G24: =IF(COUNT(E24:F24)=2,E24-F24,"") -> 0 | H24: 1 | I24: =IF(COUNT(E24:F24)<2,"N/A",IF(ABS(G24)<=H24,"OK","❌")) -> OK | J24: OK | K24: =IF(I24=J24,"✔ sesuai","✖ TIDAK sesuai") -> ✔ sesuai
A25: 19 | B25: Subtotal rumus vs tercetak | C25: CF: CASH_END rumus = tercetak | D25: 2022 | E25: =CF!C46 -> 39297310909 | F25: =CF!C52 -> 39297310909 | G25: =IF(COUNT(E25:F25)=2,E25-F25,"") -> 0 | H25: 1 | I25: =IF(COUNT(E25:F25)<2,"N/A",IF(ABS(G25)<=H25,"OK","❌")) -> OK | J25: OK | K25: =IF(I25=J25,"✔ sesuai","✖ TIDAK sesuai") -> ✔ sesuai
A26: 20 | B26: Integritas laporan | C26: BS: aset = liabilitas + ekuitas | D26: 2022 | E26: =BS!C27 -> 159993389251 | F26: =BS!C62 -> 159993389251 | G26: =IF(COUNT(E26:F26)=2,E26-F26,"") -> 0 | H26: 1 | I26: =IF(COUNT(E26:F26)<2,"N/A",IF(ABS(G26)<=H26,"OK","❌")) -> OK | J26: OK | K26: =IF(I26=J26,"✔ sesuai","✖ TIDAK sesuai") -> ✔ sesuai
A27: 21 | B27: Integritas laporan | C27: IS: laba = induk + NCI | D27: 2022 | E27: =IS!C20 -> 4888165764 | F27: =IS!C29+IS!C30 -> 4888165764 | G27: =IF(COUNT(E27:F27)=2,E27-F27,"") -> 0 | H27: 1 | I27: =IF(COUNT(E27:F27)<2,"N/A",IF(ABS(G27)<=H27,"OK","❌")) -> OK | J27: OK | K27: =IF(I27=J27,"✔ sesuai","✖ TIDAK sesuai") -> ✔ sesuai
A28: 22 | B28: Integritas laporan | C28: IS: laba komprehensif = induk + NCI | D28: 2022 | E28: =IS!C27 -> 4603727958 | F28: =IS!C31+IS!C32 -> 4603727958 | G28: =IF(COUNT(E28:F28)=2,E28-F28,"") -> 0 | H28: 1 | I28: =IF(COUNT(E28:F28)<2,"N/A",IF(ABS(G28)<=H28,"OK","❌")) -> OK | J28: OK | K28: =IF(I28=J28,"✔ sesuai","✖ TIDAK sesuai") -> ✔ sesuai
A29: 23 | B29: Integritas laporan | C29: CF: kas akhir = kas neraca (tanpa cerukan) | D29: 2022 | E29: =CF!C46 -> 39297310909 | F29: =BS!C6 -> 29547207476 | G29: =IF(COUNT(E29:F29)=2,E29-F29,"") -> 9750103433 | H29: 1 | I29: =IF(COUNT(E29:F29)<2,"N/A",IF(ABS(G29)<=H29,"OK","❌")) -> ❌ | J29: ❌ | K29: =IF(I29=J29,"✔ sesuai","✖ TIDAK sesuai") -> ✔ sesuai | L29: Temuan D6: LAK prospektus memuat efek cerukan.
A30: 24 | B30: Integritas laporan | C30: LPE: dividen ke pemilik induk = dividen dibayar (CF) | D30: 2022 | E30: 0 | F30: =CF!C41 -> 0 | G30: =IF(COUNT(E30:F30)=2,E30-F30,"") -> 0 | H30: 1 | I30: =IF(COUNT(E30:F30)<2,"N/A",IF(ABS(G30)<=H30,"OK","❌")) -> OK | J30: OK | K30: =IF(I30=J30,"✔ sesuai","✖ TIDAK sesuai") -> ✔ sesuai | L30: LPE: 2022: awal periode model
A31: 25 | B31: CALK vs laporan | C31: Cat 25: penunjang medis + rawat inap + rawat jalan + lainnya = pendapatan IS | D31: 2022 | E31: =Schedules!C10 -> 99578144421 | F31: =IS!C6 -> 99578144421 | G31: =IF(COUNT(E31:F31)=2,E31-F31,"") -> 0 | H31: 1 | I31: =IF(COUNT(E31:F31)<2,"N/A",IF(ABS(G31)<=H31,"OK","❌")) -> OK | J31: OK | K31: =IF(I31=J31,"✔ sesuai","✖ TIDAK sesuai") -> ✔ sesuai
A32: 26 | B32: CALK vs laporan | C32: Cat 25: jumlah pendapatan tercetak = IS | D32: 2022 | E32: =Schedules!C52 -> 99578144421 | F32: =IS!C6 -> 99578144421 | G32: =IF(COUNT(E32:F32)=2,E32-F32,"") -> 0 | H32: 1 | I32: =IF(COUNT(E32:F32)<2,"N/A",IF(ABS(G32)<=H32,"OK","❌")) -> OK | J32: OK | K32: =IF(I32=J32,"✔ sesuai","✖ TIDAK sesuai") -> ✔ sesuai
A33: 27 | B33: CALK vs laporan | C33: Cat 26: jumlah beban pokok tercetak = IS | D33: 2022 | E33: =Schedules!C70 -> 67593755280 | F33: =-IS!C7 -> 67593755280 | G33: =IF(COUNT(E33:F33)=2,E33-F33,"") -> 0 | H33: 1 | I33: =IF(COUNT(E33:F33)<2,"N/A",IF(ABS(G33)<=H33,"OK","❌")) -> OK | J33: OK | K33: =IF(I33=J33,"✔ sesuai","✖ TIDAK sesuai") -> ✔ sesuai
A34: 28 | B34: CALK vs laporan | C34: Cat 27: jumlah beban penjualan tercetak = IS | D34: 2022 | E34: =Schedules!C76 -> 974896353 | F34: =-IS!C9 -> 974896353 | G34: =IF(COUNT(E34:F34)=2,E34-F34,"") -> 0 | H34: 1 | I34: =IF(COUNT(E34:F34)<2,"N/A",IF(ABS(G34)<=H34,"OK","❌")) -> OK | J34: OK | K34: =IF(I34=J34,"✔ sesuai","✖ TIDAK sesuai") -> ✔ sesuai
A35: 29 | B35: CALK vs laporan | C35: Cat 27: jumlah beban umum & administrasi tercetak = IS | D35: 2022 | E35: =Schedules!C82 -> 23863495422 | F35: =-IS!C10 -> 23863495422 | G35: =IF(COUNT(E35:F35)=2,E35-F35,"") -> 0 | H35: 1 | I35: =IF(COUNT(E35:F35)<2,"N/A",IF(ABS(G35)<=H35,"OK","❌")) -> OK | J35: OK | K35: =IF(I35=J35,"✔ sesuai","✖ TIDAK sesuai") -> ✔ sesuai
A36: 30 | B36: CALK internal | C36: Cat 26+27: penyusutan aset tetap di laba rugi = penambahan akumulasi Cat 10 | D36: 2022 | E36: =Schedules!C14 -> 6778169378 | F36: =Schedules!C15 -> 0 | G36: =IF(COUNT(E36:F36)=2,E36-F36,"") -> 6778169378 | H36: 1 | I36: =IF(COUNT(E36:F36)<2,"N/A",IF(ABS(G36)<=H36,"OK","N/A")) -> N/A | J36: N/A | K36: =IF(I36=J36,"✔ sesuai","✖ TIDAK sesuai") -> ✔ sesuai
A37: 31 | B37: CALK internal | C37: Cat 25: Σ rincian = Jumlah tercetak | D37: 2022 | E37: =Schedules!C56 -> 99578144421 | F37: =Schedules!C52 -> 99578144421 | G37: =IF(COUNT(E37:F37)=2,E37-F37,"") -> 0 | H37: 1 | I37: =IF(COUNT(E37:F37)<2,"N/A",IF(ABS(G37)<=H37,"OK","❌")) -> OK | J37: OK | K37: =IF(I37=J37,"✔ sesuai","✖ TIDAK sesuai") -> ✔ sesuai
A38: 32 | B38: CALK internal | C38: Cat 26: Σ rincian = Jumlah tercetak | D38: 2022 | E38: =Schedules!C72 -> 67593755280 | F38: =Schedules!C70 -> 67593755280 | G38: =IF(COUNT(E38:F38)=2,E38-F38,"") -> 0 | H38: 1 | I38: =IF(COUNT(E38:F38)<2,"N/A",IF(ABS(G38)<=H38,"OK","❌")) -> OK | J38: OK | K38: =IF(I38=J38,"✔ sesuai","✖ TIDAK sesuai") -> ✔ sesuai
A39: 33 | B39: CALK internal | C39: Cat 27: Σ rincian = Jumlah tercetak | D39: 2022 | E39: =Schedules!C77 -> 974896353 | F39: =Schedules!C76 -> 974896353 | G39: =IF(COUNT(E39:F39)=2,E39-F39,"") -> 0 | H39: 1 | I39: =IF(COUNT(E39:F39)<2,"N/A",IF(ABS(G39)<=H39,"OK","❌")) -> OK | J39: OK | K39: =IF(I39=J39,"✔ sesuai","✖ TIDAK sesuai") -> ✔ sesuai
A40: 34 | B40: CALK internal | C40: Cat 27: Σ rincian = Jumlah tercetak | D40: 2022 | E40: =Schedules!C83 -> 23863495422 | F40: =Schedules!C82 -> 23863495422 | G40: =IF(COUNT(E40:F40)=2,E40-F40,"") -> 0 | H40: 1 | I40: =IF(COUNT(E40:F40)<2,"N/A",IF(ABS(G40)<=H40,"OK","❌")) -> OK | J40: OK | K40: =IF(I40=J40,"✔ sesuai","✖ TIDAK sesuai") -> ✔ sesuai
A41: 35 | B41: Per saham | C41: EPS tercetak vs laba induk / saham rata-rata tertimbang CALK (toleransi Rp1) | D41: 2022 | E41: =IS!C33 -> 8.81 | F41: =ROUND(IS!C29/Schedules!C22,2) -> 8.81 | G41: =IF(COUNT(E41:F41)=2,E41-F41,"") -> 0 | H41: 1 | I41: =IF(COUNT(E41:F41)<2,"N/A",IF(ABS(G41)<=H41,"OK","❌")) -> OK | J41: OK | K41: =IF(I41=J41,"✔ sesuai","✖ TIDAK sesuai") -> ✔ sesuai
A42: 36 | B42: Subtotal rumus vs tercetak | C42: IS: GROSS_PROFIT rumus = tercetak | D42: 2023 | E42: =IS!D8 -> 44613263383 | F42: =IS!D36 -> 44613263383 | G42: =IF(COUNT(E42:F42)=2,E42-F42,"") -> 0 | H42: 1 | I42: =IF(COUNT(E42:F42)<2,"N/A",IF(ABS(G42)<=H42,"OK","❌")) -> OK | J42: OK | K42: =IF(I42=J42,"✔ sesuai","✖ TIDAK sesuai") -> ✔ sesuai
A43: 37 | B43: Subtotal rumus vs tercetak | C43: IS: PBT rumus = tercetak | D43: 2023 | E43: =IS!D17 -> 2183735441 | F43: =IS!D38 -> 2183735441 | G43: =IF(COUNT(E43:F43)=2,E43-F43,"") -> 0 | H43: 1 | I43: =IF(COUNT(E43:F43)<2,"N/A",IF(ABS(G43)<=H43,"OK","❌")) -> OK | J43: OK | K43: =IF(I43=J43,"✔ sesuai","✖ TIDAK sesuai") -> ✔ sesuai
A44: 38 | B44: Subtotal rumus vs tercetak | C44: IS: NET_INCOME rumus = tercetak | D44: 2023 | E44: =IS!D20 -> 3539716397 | F44: =IS!D39 -> 3539716397 | G44: =IF(COUNT(E44:F44)=2,E44-F44,"") -> 0 | H44: 1 | I44: =IF(COUNT(E44:F44)<2,"N/A",IF(ABS(G44)<=H44,"OK","❌")) -> OK | J44: OK | K44: =IF(I44=J44,"✔ sesuai","✖ TIDAK sesuai") -> ✔ sesuai
A45: 39 | B45: Subtotal rumus vs tercetak | C45: IS: OCI_TOTAL rumus = tercetak | D45: 2023 | E45: =IS!D26 -> 27051661547 | F45: =IS!D40 -> 27051661547 | G45: =IF(COUNT(E45:F45)=2,E45-F45,"") -> 0 | H45: 1 | I45: =IF(COUNT(E45:F45)<2,"N/A",IF(ABS(G45)<=H45,"OK","❌")) -> OK | J45: OK | K45: =IF(I45=J45,"✔ sesuai","✖ TIDAK sesuai") -> ✔ sesuai
A46: 40 | B46: Subtotal rumus vs tercetak | C46: IS: TCI rumus = tercetak | D46: 2023 | E46: =IS!D27 -> 30591377944 | F46: =IS!D41 -> 30591377944 | G46: =IF(COUNT(E46:F46)=2,E46-F46,"") -> 0 | H46: 1 | I46: =IF(COUNT(E46:F46)<2,"N/A",IF(ABS(G46)<=H46,"OK","❌")) -> OK | J46: OK | K46: =IF(I46=J46,"✔ sesuai","✖ TIDAK sesuai") -> ✔ sesuai
A47: 41 | B47: Subtotal rumus vs tercetak | C47: BS: TOTAL_CA rumus = tercetak | D47: 2023 | E47: =BS!D16 -> 27900026054 | F47: =BS!D67 -> 27900026054 | G47: =IF(COUNT(E47:F47)=2,E47-F47,"") -> 0 | H47: 1 | I47: =IF(COUNT(E47:F47)<2,"N/A",IF(ABS(G47)<=H47,"OK","❌")) -> OK | J47: OK | K47: =IF(I47=J47,"✔ sesuai","✖ TIDAK sesuai") -> ✔ sesuai
A48: 42 | B48: Subtotal rumus vs tercetak | C48: BS: TOTAL_NCA rumus = tercetak | D48: 2023 | E48: =BS!D26 -> 272769866783 | F48: =BS!D68 -> 272769866783 | G48: =IF(COUNT(E48:F48)=2,E48-F48,"") -> 0 | H48: 1 | I48: =IF(COUNT(E48:F48)<2,"N/A",IF(ABS(G48)<=H48,"OK","❌")) -> OK | J48: OK | K48: =IF(I48=J48,"✔ sesuai","✖ TIDAK sesuai") -> ✔ sesuai
A49: 43 | B49: Subtotal rumus vs tercetak | C49: BS: TOTAL_ASSETS rumus = tercetak | D49: 2023 | E49: =BS!D27 -> 300669892837 | F49: =BS!D69 -> 300669892837 | G49: =IF(COUNT(E49:F49)=2,E49-F49,"") -> 0 | H49: 1 | I49: =IF(COUNT(E49:F49)<2,"N/A",IF(ABS(G49)<=H49,"OK","❌")) -> OK | J49: OK | K49: =IF(I49=J49,"✔ sesuai","✖ TIDAK sesuai") -> ✔ sesuai
A50: 44 | B50: Subtotal rumus vs tercetak | C50: BS: TOTAL_CL rumus = tercetak | D50: 2023 | E50: =BS!D42 -> 41878923554 | F50: =BS!D70 -> 41878923554 | G50: =IF(COUNT(E50:F50)=2,E50-F50,"") -> 0 | H50: 1 | I50: =IF(COUNT(E50:F50)<2,"N/A",IF(ABS(G50)<=H50,"OK","❌")) -> OK | J50: OK | K50: =IF(I50=J50,"✔ sesuai","✖ TIDAK sesuai") -> ✔ sesuai
A51: 45 | B51: Subtotal rumus vs tercetak | C51: BS: TOTAL_NCL rumus = tercetak | D51: 2023 | E51: =BS!D51 -> 129637962895 | F51: =BS!D71 -> 129637962895 | G51: =IF(COUNT(E51:F51)=2,E51-F51,"") -> 0 | H51: 1 | I51: =IF(COUNT(E51:F51)<2,"N/A",IF(ABS(G51)<=H51,"OK","❌")) -> OK | J51: OK | K51: =IF(I51=J51,"✔ sesuai","✖ TIDAK sesuai") -> ✔ sesuai
A52: 46 | B52: Subtotal rumus vs tercetak | C52: BS: TOTAL_LIAB rumus = tercetak | D52: 2023 | E52: =BS!D52 -> 171516886449 | F52: =BS!D72 -> 171516886449 | G52: =IF(COUNT(E52:F52)=2,E52-F52,"") -> 0 | H52: 1 | I52: =IF(COUNT(E52:F52)<2,"N/A",IF(ABS(G52)<=H52,"OK","❌")) -> OK | J52: OK | K52: =IF(I52=J52,"✔ sesuai","✖ TIDAK sesuai") -> ✔ sesuai
A53: 47 | B53: Subtotal rumus vs tercetak | C53: BS: EQUITY_PARENT rumus = tercetak | D53: 2023 | E53: =BS!D59 -> 129153006388 | F53: =BS!D73 -> 129153006388 | G53: =IF(COUNT(E53:F53)=2,E53-F53,"") -> 0 | H53: 1 | I53: =IF(COUNT(E53:F53)<2,"N/A",IF(ABS(G53)<=H53,"OK","❌")) -> OK | J53: OK | K53: =IF(I53=J53,"✔ sesuai","✖ TIDAK sesuai") -> ✔ sesuai
A54: 48 | B54: Subtotal rumus vs tercetak | C54: BS: TOTAL_EQUITY rumus = tercetak | D54: 2023 | E54: =BS!D61 -> 129153006388 | F54: =BS!D74 -> 129153006388 | G54: =IF(COUNT(E54:F54)=2,E54-F54,"") -> 0 | H54: 1 | I54: =IF(COUNT(E54:F54)<2,"N/A",IF(ABS(G54)<=H54,"OK","❌")) -> OK | J54: OK | K54: =IF(I54=J54,"✔ sesuai","✖ TIDAK sesuai") -> ✔ sesuai
A55: 49 | B55: Subtotal rumus vs tercetak | C55: BS: TOTAL_LIAB_EQUITY rumus = tercetak | D55: 2023 | E55: =BS!D62 -> 300669892837 | F55: =BS!D75 -> 300669892837 | G55: =IF(COUNT(E55:F55)=2,E55-F55,"") -> 0 | H55: 1 | I55: =IF(COUNT(E55:F55)<2,"N/A",IF(ABS(G55)<=H55,"OK","❌")) -> OK | J55: OK | K55: =IF(I55=J55,"✔ sesuai","✖ TIDAK sesuai") -> ✔ sesuai
A56: 50 | B56: Subtotal rumus vs tercetak | C56: CF: CFO rumus = tercetak | D56: 2023 | E56: =CF!D14 -> 19735705441 | F56: =CF!D48 -> 19735705441 | G56: =IF(COUNT(E56:F56)=2,E56-F56,"") -> 0 | H56: 1 | I56: =IF(COUNT(E56:F56)<2,"N/A",IF(ABS(G56)<=H56,"OK","❌")) -> OK | J56: OK | K56: =IF(I56=J56,"✔ sesuai","✖ TIDAK sesuai") -> ✔ sesuai
A57: 51 | B57: Subtotal rumus vs tercetak | C57: CF: CFI rumus = tercetak | D57: 2023 | E57: =CF!D24 -> -36146492177 | F57: =CF!D49 -> -36146492177 | G57: =IF(COUNT(E57:F57)=2,E57-F57,"") -> 0 | H57: 1 | I57: =IF(COUNT(E57:F57)<2,"N/A",IF(ABS(G57)<=H57,"OK","❌")) -> OK | J57: OK | K57: =IF(I57=J57,"✔ sesuai","✖ TIDAK sesuai") -> ✔ sesuai
A58: 52 | B58: Subtotal rumus vs tercetak | C58: CF: CFF rumus = tercetak | D58: 2023 | E58: =CF!D43 -> -13672626965 | F58: =CF!D50 -> -13672626965 | G58: =IF(COUNT(E58:F58)=2,E58-F58,"") -> 0 | H58: 1 | I58: =IF(COUNT(E58:F58)<2,"N/A",IF(ABS(G58)<=H58,"OK","❌")) -> OK | J58: OK | K58: =IF(I58=J58,"✔ sesuai","✖ TIDAK sesuai") -> ✔ sesuai
A59: 53 | B59: Subtotal rumus vs tercetak | C59: CF: NET_CHANGE rumus = tercetak | D59: 2023 | E59: =CF!D44 -> -30083413701 | F59: =CF!D51 -> -30083413701 | G59: =IF(COUNT(E59:F59)=2,E59-F59,"") -> 0 | H59: 1 | I59: =IF(COUNT(E59:F59)<2,"N/A",IF(ABS(G59)<=H59,"OK","❌")) -> OK | J59: OK | K59: =IF(I59=J59,"✔ sesuai","✖ TIDAK sesuai") -> ✔ sesuai
A60: 54 | B60: Subtotal rumus vs tercetak | C60: CF: CASH_END rumus = tercetak | D60: 2023 | E60: =CF!D46 -> -536206225 | F60: =CF!D52 -> -536206225 | G60: =IF(COUNT(E60:F60)=2,E60-F60,"") -> 0 | H60: 1 | I60: =IF(COUNT(E60:F60)<2,"N/A",IF(ABS(G60)<=H60,"OK","❌")) -> OK | J60: OK | K60: =IF(I60=J60,"✔ sesuai","✖ TIDAK sesuai") -> ✔ sesuai
A61: 55 | B61: Integritas laporan | C61: BS: aset = liabilitas + ekuitas | D61: 2023 | E61: =BS!D27 -> 300669892837 | F61: =BS!D62 -> 300669892837 | G61: =IF(COUNT(E61:F61)=2,E61-F61,"") -> 0 | H61: 1 | I61: =IF(COUNT(E61:F61)<2,"N/A",IF(ABS(G61)<=H61,"OK","❌")) -> OK | J61: OK | K61: =IF(I61=J61,"✔ sesuai","✖ TIDAK sesuai") -> ✔ sesuai
A62: 56 | B62: Integritas laporan | C62: IS: laba = induk + NCI | D62: 2023 | E62: =IS!D20 -> 3539716397 | F62: =IS!D29+IS!D30 -> 3539716397 | G62: =IF(COUNT(E62:F62)=2,E62-F62,"") -> 0 | H62: 1 | I62: =IF(COUNT(E62:F62)<2,"N/A",IF(ABS(G62)<=H62,"OK","❌")) -> OK | J62: OK | K62: =IF(I62=J62,"✔ sesuai","✖ TIDAK sesuai") -> ✔ sesuai
A63: 57 | B63: Integritas laporan | C63: IS: laba komprehensif = induk + NCI | D63: 2023 | E63: =IS!D27 -> 30591377944 | F63: =IS!D31+IS!D32 -> 30591377944 | G63: =IF(COUNT(E63:F63)=2,E63-F63,"") -> 0 | H63: 1 | I63: =IF(COUNT(E63:F63)<2,"N/A",IF(ABS(G63)<=H63,"OK","❌")) -> OK | J63: OK | K63: =IF(I63=J63,"✔ sesuai","✖ TIDAK sesuai") -> ✔ sesuai
A64: 58 | B64: Integritas laporan | C64: CF: kas akhir = kas neraca (tanpa cerukan) | D64: 2023 | E64: =CF!D46 -> -536206225 | F64: =BS!D6 -> 2463973775 | G64: =IF(COUNT(E64:F64)=2,E64-F64,"") -> -3000180000 | H64: 1 | I64: =IF(COUNT(E64:F64)<2,"N/A",IF(ABS(G64)<=H64,"OK","❌")) -> ❌ | J64: ❌ | K64: =IF(I64=J64,"✔ sesuai","✖ TIDAK sesuai") -> ✔ sesuai | L64: Temuan D6: LAK prospektus berakhir pada kas neto cerukan.
A65: 59 | B65: Integritas laporan | C65: LPE: dividen ke pemilik induk = dividen dibayar (CF) | D65: 2023 | E65: 0 | F65: =CF!D41 -> 0 | G65: =IF(COUNT(E65:F65)=2,E65-F65,"") -> 0 | H65: 1 | I65: =IF(COUNT(E65:F65)<2,"N/A",IF(ABS(G65)<=H65,"OK","❌")) -> OK | J65: OK | K65: =IF(I65=J65,"✔ sesuai","✖ TIDAK sesuai") -> ✔ sesuai | L65: LPE: Prospektus LPE hal 276-277: laba tahun berjalan 3.539.716.397 ke saldo laba
A66: 60 | B66: Antar tahun | C66: CF: kas awal = kas neraca tahun lalu | D66: 2023 | E66: =CF!D45 -> 29547207476 | F66: =BS!C6 -> 29547207476 | G66: =IF(COUNT(E66:F66)=2,E66-F66,"") -> 0 | H66: 1 | I66: =IF(COUNT(E66:F66)<2,"N/A",IF(ABS(G66)<=H66,"OK","❌")) -> OK | J66: OK | K66: =IF(I66=J66,"✔ sesuai","✖ TIDAK sesuai") -> ✔ sesuai
A67: 61 | B67: Antar tahun | C67: Saldo laba: awal + laba komprehensif ke saldo laba (LPE) + dividen (CF) + lainnya (LPE) = akhir | D67: 2023 | E67: =BS!C58+3539716397+CF!D41+0 -> 23080884249 | F67: =BS!D58 -> 23080884249 | G67: =IF(COUNT(E67:F67)=2,E67-F67,"") -> 0 | H67: 1 | I67: =IF(COUNT(E67:F67)<2,"N/A",IF(ABS(G67)<=H67,"OK","❌")) -> OK | J67: OK | K67: =IF(I67=J67,"✔ sesuai","✖ TIDAK sesuai") -> ✔ sesuai | L67: saldo laba = ditentukan + belum ditentukan penggunaannya; OCI (surplus revaluasi, pengukuran kembali) di kolom terpisah; lainnya = pos LPE lain (lihat DKHH_cek_silang.json). Angka statis LPE dari DKHH_cek_silang.json
A68: 62 | B68: CALK vs laporan | C68: Cat 25: penunjang medis + rawat inap + rawat jalan + lainnya = pendapatan IS | D68: 2023 | E68: =Schedules!D10 -> 134187678929 | F68: =IS!D6 -> 134187678929 | G68: =IF(COUNT(E68:F68)=2,E68-F68,"") -> 0 | H68: 1 | I68: =IF(COUNT(E68:F68)<2,"N/A",IF(ABS(G68)<=H68,"OK","❌")) -> OK | J68: OK | K68: =IF(I68=J68,"✔ sesuai","✖ TIDAK sesuai") -> ✔ sesuai
A69: 63 | B69: CALK vs laporan | C69: Cat 25: jumlah pendapatan tercetak = IS | D69: 2023 | E69: =Schedules!D52 -> 134187678929 | F69: =IS!D6 -> 134187678929 | G69: =IF(COUNT(E69:F69)=2,E69-F69,"") -> 0 | H69: 1 | I69: =IF(COUNT(E69:F69)<2,"N/A",IF(ABS(G69)<=H69,"OK","❌")) -> OK | J69: OK | K69: =IF(I69=J69,"✔ sesuai","✖ TIDAK sesuai") -> ✔ sesuai
A70: 64 | B70: CALK vs laporan | C70: Cat 26: jumlah beban pokok tercetak = IS | D70: 2023 | E70: =Schedules!D70 -> 89574415546 | F70: =-IS!D7 -> 89574415546 | G70: =IF(COUNT(E70:F70)=2,E70-F70,"") -> 0 | H70: 1 | I70: =IF(COUNT(E70:F70)<2,"N/A",IF(ABS(G70)<=H70,"OK","❌")) -> OK | J70: OK | K70: =IF(I70=J70,"✔ sesuai","✖ TIDAK sesuai") -> ✔ sesuai
A71: 65 | B71: CALK vs laporan | C71: Cat 27: jumlah beban penjualan tercetak = IS | D71: 2023 | E71: =Schedules!D76 -> 3183805931 | F71: =-IS!D9 -> 3183805931 | G71: =IF(COUNT(E71:F71)=2,E71-F71,"") -> 0 | H71: 1 | I71: =IF(COUNT(E71:F71)<2,"N/A",IF(ABS(G71)<=H71,"OK","❌")) -> OK | J71: OK | K71: =IF(I71=J71,"✔ sesuai","✖ TIDAK sesuai") -> ✔ sesuai
A72: 66 | B72: CALK vs laporan | C72: Cat 27: jumlah beban umum & administrasi tercetak = IS | D72: 2023 | E72: =Schedules!D82 -> 31755062789 | F72: =-IS!D10 -> 31755062789 | G72: =IF(COUNT(E72:F72)=2,E72-F72,"") -> 0 | H72: 1 | I72: =IF(COUNT(E72:F72)<2,"N/A",IF(ABS(G72)<=H72,"OK","❌")) -> OK | J72: OK | K72: =IF(I72=J72,"✔ sesuai","✖ TIDAK sesuai") -> ✔ sesuai
A73: 67 | B73: CALK internal | C73: Cat 26+27: penyusutan aset tetap di laba rugi = penambahan akumulasi Cat 10 | D73: 2023 | E73: =Schedules!D14 -> 7754681103 | F73: =Schedules!D15 -> 0 | G73: =IF(COUNT(E73:F73)=2,E73-F73,"") -> 7754681103 | H73: 1 | I73: =IF(COUNT(E73:F73)<2,"N/A",IF(ABS(G73)<=H73,"OK","N/A")) -> N/A | J73: N/A | K73: =IF(I73=J73,"✔ sesuai","✖ TIDAK sesuai") -> ✔ sesuai
A74: 68 | B74: CALK internal | C74: Cat 25: Σ rincian = Jumlah tercetak | D74: 2023 | E74: =Schedules!D56 -> 134187678929 | F74: =Schedules!D52 -> 134187678929 | G74: =IF(COUNT(E74:F74)=2,E74-F74,"") -> 0 | H74: 1 | I74: =IF(COUNT(E74:F74)<2,"N/A",IF(ABS(G74)<=H74,"OK","❌")) -> OK | J74: OK | K74: =IF(I74=J74,"✔ sesuai","✖ TIDAK sesuai") -> ✔ sesuai
A75: 69 | B75: CALK internal | C75: Cat 26: Σ rincian = Jumlah tercetak | D75: 2023 | E75: =Schedules!D72 -> 89574415546 | F75: =Schedules!D70 -> 89574415546 | G75: =IF(COUNT(E75:F75)=2,E75-F75,"") -> 0 | H75: 1 | I75: =IF(COUNT(E75:F75)<2,"N/A",IF(ABS(G75)<=H75,"OK","❌")) -> OK | J75: OK | K75: =IF(I75=J75,"✔ sesuai","✖ TIDAK sesuai") -> ✔ sesuai
A76: 70 | B76: CALK internal | C76: Cat 27: Σ rincian = Jumlah tercetak | D76: 2023 | E76: =Schedules!D77 -> 3183805931 | F76: =Schedules!D76 -> 3183805931 | G76: =IF(COUNT(E76:F76)=2,E76-F76,"") -> 0 | H76: 1 | I76: =IF(COUNT(E76:F76)<2,"N/A",IF(ABS(G76)<=H76,"OK","❌")) -> OK | J76: OK | K76: =IF(I76=J76,"✔ sesuai","✖ TIDAK sesuai") -> ✔ sesuai
A77: 71 | B77: CALK internal | C77: Cat 27: Σ rincian = Jumlah tercetak | D77: 2023 | E77: =Schedules!D83 -> 31755062789 | F77: =Schedules!D82 -> 31755062789 | G77: =IF(COUNT(E77:F77)=2,E77-F77,"") -> 0 | H77: 1 | I77: =IF(COUNT(E77:F77)<2,"N/A",IF(ABS(G77)<=H77,"OK","❌")) -> OK | J77: OK | K77: =IF(I77=J77,"✔ sesuai","✖ TIDAK sesuai") -> ✔ sesuai
A78: 72 | B78: Per saham | C78: EPS tercetak vs laba induk / saham rata-rata tertimbang CALK (toleransi Rp1) | D78: 2023 | E78: =IS!D33 -> 6.38 | F78: =ROUND(IS!D29/Schedules!D22,2) -> 6.38 | G78: =IF(COUNT(E78:F78)=2,E78-F78,"") -> 0 | H78: 1 | I78: =IF(COUNT(E78:F78)<2,"N/A",IF(ABS(G78)<=H78,"OK","❌")) -> OK | J78: OK | K78: =IF(I78=J78,"✔ sesuai","✖ TIDAK sesuai") -> ✔ sesuai
A79: 73 | B79: Subtotal rumus vs tercetak | C79: IS: GROSS_PROFIT rumus = tercetak | D79: 2024 | E79: =IS!E8 -> 47335772334 | F79: =IS!E36 -> 47335772334 | G79: =IF(COUNT(E79:F79)=2,E79-F79,"") -> 0 | H79: 1 | I79: =IF(COUNT(E79:F79)<2,"N/A",IF(ABS(G79)<=H79,"OK","❌")) -> OK | J79: OK | K79: =IF(I79=J79,"✔ sesuai","✖ TIDAK sesuai") -> ✔ sesuai
A80: 74 | B80: Subtotal rumus vs tercetak | C80: IS: PBT rumus = tercetak | D80: 2024 | E80: =IS!E17 -> 69501179 | F80: =IS!E38 -> 69501179 | G80: =IF(COUNT(E80:F80)=2,E80-F80,"") -> 0 | H80: 1 | I80: =IF(COUNT(E80:F80)<2,"N/A",IF(ABS(G80)<=H80,"OK","❌")) -> OK | J80: OK | K80: =IF(I80=J80,"✔ sesuai","✖ TIDAK sesuai") -> ✔ sesuai
A81: 75 | B81: Subtotal rumus vs tercetak | C81: IS: NET_INCOME rumus = tercetak | D81: 2024 | E81: =IS!E20 -> 2837363273 | F81: =IS!E39 -> 2837363273 | G81: =IF(COUNT(E81:F81)=2,E81-F81,"") -> 0 | H81: 1 | I81: =IF(COUNT(E81:F81)<2,"N/A",IF(ABS(G81)<=H81,"OK","❌")) -> OK | J81: OK | K81: =IF(I81=J81,"✔ sesuai","✖ TIDAK sesuai") -> ✔ sesuai
A82: 76 | B82: Subtotal rumus vs tercetak | C82: IS: OCI_TOTAL rumus = tercetak | D82: 2024 | E82: =IS!E26 -> 292515994 | F82: =IS!E40 -> 292515994 | G82: =IF(COUNT(E82:F82)=2,E82-F82,"") -> 0 | H82: 1 | I82: =IF(COUNT(E82:F82)<2,"N/A",IF(ABS(G82)<=H82,"OK","❌")) -> OK | J82: OK | K82: =IF(I82=J82,"✔ sesuai","✖ TIDAK sesuai") -> ✔ sesuai
A83: 77 | B83: Subtotal rumus vs tercetak | C83: IS: TCI rumus = tercetak | D83: 2024 | E83: =IS!E27 -> 3129879267 | F83: =IS!E41 -> 3129879267 | G83: =IF(COUNT(E83:F83)=2,E83-F83,"") -> 0 | H83: 1 | I83: =IF(COUNT(E83:F83)<2,"N/A",IF(ABS(G83)<=H83,"OK","❌")) -> OK | J83: OK | K83: =IF(I83=J83,"✔ sesuai","✖ TIDAK sesuai") -> ✔ sesuai
A84: 78 | B84: Subtotal rumus vs tercetak | C84: BS: TOTAL_CA rumus = tercetak | D84: 2024 | E84: =BS!E16 -> 35092527104 | F84: =BS!E67 -> 35092527104 | G84: =IF(COUNT(E84:F84)=2,E84-F84,"") -> 0 | H84: 1 | I84: =IF(COUNT(E84:F84)<2,"N/A",IF(ABS(G84)<=H84,"OK","❌")) -> OK | J84: OK | K84: =IF(I84=J84,"✔ sesuai","✖ TIDAK sesuai") -> ✔ sesuai
A85: 79 | B85: Subtotal rumus vs tercetak | C85: BS: TOTAL_NCA rumus = tercetak | D85: 2024 | E85: =BS!E26 -> 233007712808 | F85: =BS!E68 -> 233007712808 | G85: =IF(COUNT(E85:F85)=2,E85-F85,"") -> 0 | H85: 1 | I85: =IF(COUNT(E85:F85)<2,"N/A",IF(ABS(G85)<=H85,"OK","❌")) -> OK | J85: OK | K85: =IF(I85=J85,"✔ sesuai","✖ TIDAK sesuai") -> ✔ sesuai
A86: 80 | B86: Subtotal rumus vs tercetak | C86: BS: TOTAL_ASSETS rumus = tercetak | D86: 2024 | E86: =BS!E27 -> 268100239912 | F86: =BS!E69 -> 268100239912 | G86: =IF(COUNT(E86:F86)=2,E86-F86,"") -> 0 | H86: 1 | I86: =IF(COUNT(E86:F86)<2,"N/A",IF(ABS(G86)<=H86,"OK","❌")) -> OK | J86: OK | K86: =IF(I86=J86,"✔ sesuai","✖ TIDAK sesuai") -> ✔ sesuai
A87: 81 | B87: Subtotal rumus vs tercetak | C87: BS: TOTAL_CL rumus = tercetak | D87: 2024 | E87: =BS!E42 -> 39650021742 | F87: =BS!E70 -> 39650021742 | G87: =IF(COUNT(E87:F87)=2,E87-F87,"") -> 0 | H87: 1 | I87: =IF(COUNT(E87:F87)<2,"N/A",IF(ABS(G87)<=H87,"OK","❌")) -> OK | J87: OK | K87: =IF(I87=J87,"✔ sesuai","✖ TIDAK sesuai") -> ✔ sesuai
A88: 82 | B88: Subtotal rumus vs tercetak | C88: BS: TOTAL_NCL rumus = tercetak | D88: 2024 | E88: =BS!E51 -> 98720827700 | F88: =BS!E71 -> 98720827700 | G88: =IF(COUNT(E88:F88)=2,E88-F88,"") -> 0 | H88: 1 | I88: =IF(COUNT(E88:F88)<2,"N/A",IF(ABS(G88)<=H88,"OK","❌")) -> OK | J88: OK | K88: =IF(I88=J88,"✔ sesuai","✖ TIDAK sesuai") -> ✔ sesuai
A89: 83 | B89: Subtotal rumus vs tercetak | C89: BS: TOTAL_LIAB rumus = tercetak | D89: 2024 | E89: =BS!E52 -> 138370849442 | F89: =BS!E72 -> 138370849442 | G89: =IF(COUNT(E89:F89)=2,E89-F89,"") -> 0 | H89: 1 | I89: =IF(COUNT(E89:F89)<2,"N/A",IF(ABS(G89)<=H89,"OK","❌")) -> OK | J89: OK | K89: =IF(I89=J89,"✔ sesuai","✖ TIDAK sesuai") -> ✔ sesuai
A90: 84 | B90: Subtotal rumus vs tercetak | C90: BS: EQUITY_PARENT rumus = tercetak | D90: 2024 | E90: =BS!E59 -> 129725831860 | F90: =BS!E73 -> 129725831860 | G90: =IF(COUNT(E90:F90)=2,E90-F90,"") -> 0 | H90: 1 | I90: =IF(COUNT(E90:F90)<2,"N/A",IF(ABS(G90)<=H90,"OK","❌")) -> OK | J90: OK | K90: =IF(I90=J90,"✔ sesuai","✖ TIDAK sesuai") -> ✔ sesuai
A91: 85 | B91: Subtotal rumus vs tercetak | C91: BS: TOTAL_EQUITY rumus = tercetak | D91: 2024 | E91: =BS!E61 -> 129729390470 | F91: =BS!E74 -> 129729390470 | G91: =IF(COUNT(E91:F91)=2,E91-F91,"") -> 0 | H91: 1 | I91: =IF(COUNT(E91:F91)<2,"N/A",IF(ABS(G91)<=H91,"OK","❌")) -> OK | J91: OK | K91: =IF(I91=J91,"✔ sesuai","✖ TIDAK sesuai") -> ✔ sesuai
A92: 86 | B92: Subtotal rumus vs tercetak | C92: BS: TOTAL_LIAB_EQUITY rumus = tercetak | D92: 2024 | E92: =BS!E62 -> 268100239912 | F92: =BS!E75 -> 268100239912 | G92: =IF(COUNT(E92:F92)=2,E92-F92,"") -> 0 | H92: 1 | I92: =IF(COUNT(E92:F92)<2,"N/A",IF(ABS(G92)<=H92,"OK","❌")) -> OK | J92: OK | K92: =IF(I92=J92,"✔ sesuai","✖ TIDAK sesuai") -> ✔ sesuai
A93: 87 | B93: Subtotal rumus vs tercetak | C93: CF: CFO rumus = tercetak | D93: 2024 | E93: =CF!E14 -> 2997687548 | F93: =CF!E48 -> 2997687548 | G93: =IF(COUNT(E93:F93)=2,E93-F93,"") -> 0 | H93: 1 | I93: =IF(COUNT(E93:F93)<2,"N/A",IF(ABS(G93)<=H93,"OK","❌")) -> OK | J93: OK | K93: =IF(I93=J93,"✔ sesuai","✖ TIDAK sesuai") -> ✔ sesuai
A94: 88 | B94: Subtotal rumus vs tercetak | C94: CF: CFI rumus = tercetak | D94: 2024 | E94: =CF!E24 -> -26160414859 | F94: =CF!E49 -> -26160414859 | G94: =IF(COUNT(E94:F94)=2,E94-F94,"") -> 0 | H94: 1 | I94: =IF(COUNT(E94:F94)<2,"N/A",IF(ABS(G94)<=H94,"OK","❌")) -> OK | J94: OK | K94: =IF(I94=J94,"✔ sesuai","✖ TIDAK sesuai") -> ✔ sesuai
A95: 89 | B95: Subtotal rumus vs tercetak | C95: CF: CFF rumus = tercetak | D95: 2024 | E95: =CF!E43 -> 23362141885 | F95: =CF!E50 -> 23362141885 | G95: =IF(COUNT(E95:F95)=2,E95-F95,"") -> 0 | H95: 1 | I95: =IF(COUNT(E95:F95)<2,"N/A",IF(ABS(G95)<=H95,"OK","❌")) -> OK | J95: OK | K95: =IF(I95=J95,"✔ sesuai","✖ TIDAK sesuai") -> ✔ sesuai
A96: 90 | B96: Subtotal rumus vs tercetak | C96: CF: NET_CHANGE rumus = tercetak | D96: 2024 | E96: =CF!E44 -> 199414574 | F96: =CF!E51 -> 199414574 | G96: =IF(COUNT(E96:F96)=2,E96-F96,"") -> 0 | H96: 1 | I96: =IF(COUNT(E96:F96)<2,"N/A",IF(ABS(G96)<=H96,"OK","❌")) -> OK | J96: OK | K96: =IF(I96=J96,"✔ sesuai","✖ TIDAK sesuai") -> ✔ sesuai
A97: 91 | B97: Subtotal rumus vs tercetak | C97: CF: CASH_END rumus = tercetak | D97: 2024 | E97: =CF!E46 -> 2663388349 | F97: =CF!E52 -> 2663388349 | G97: =IF(COUNT(E97:F97)=2,E97-F97,"") -> 0 | H97: 1 | I97: =IF(COUNT(E97:F97)<2,"N/A",IF(ABS(G97)<=H97,"OK","❌")) -> OK | J97: OK | K97: =IF(I97=J97,"✔ sesuai","✖ TIDAK sesuai") -> ✔ sesuai
A98: 92 | B98: Integritas laporan | C98: BS: aset = liabilitas + ekuitas | D98: 2024 | E98: =BS!E27 -> 268100239912 | F98: =BS!E62 -> 268100239912 | G98: =IF(COUNT(E98:F98)=2,E98-F98,"") -> 0 | H98: 1 | I98: =IF(COUNT(E98:F98)<2,"N/A",IF(ABS(G98)<=H98,"OK","❌")) -> OK | J98: OK | K98: =IF(I98=J98,"✔ sesuai","✖ TIDAK sesuai") -> ✔ sesuai
A99: 93 | B99: Integritas laporan | C99: IS: laba = induk + NCI | D99: 2024 | E99: =IS!E20 -> 2837363273 | F99: =IS!E29+IS!E30 -> 2837363273 | G99: =IF(COUNT(E99:F99)=2,E99-F99,"") -> 0 | H99: 1 | I99: =IF(COUNT(E99:F99)<2,"N/A",IF(ABS(G99)<=H99,"OK","❌")) -> OK | J99: OK | K99: =IF(I99=J99,"✔ sesuai","✖ TIDAK sesuai") -> ✔ sesuai
A100: 94 | B100: Integritas laporan | C100: IS: laba komprehensif = induk + NCI | D100: 2024 | E100: =IS!E27 -> 3129879267 | F100: =IS!E31+IS!E32 -> 3129865099 | G100: =IF(COUNT(E100:F100)=2,E100-F100,"") -> 14168 | H100: 1 | I100: =IF(COUNT(E100:F100)<2,"N/A",IF(ABS(G100)<=H100,"OK","❌")) -> ❌ | J100: ❌ | K100: =IF(I100=J100,"✔ sesuai","✖ TIDAK sesuai") -> ✔ sesuai | L100: Temuan D9: atribusi TCI tercetak tidak menjumlah.
A101: 95 | B101: Integritas laporan | C101: CF: kas akhir = kas neraca (tanpa cerukan) | D101: 2024 | E101: =CF!E46 -> 2663388349 | F101: =BS!E6 -> 2663388349 | G101: =IF(COUNT(E101:F101)=2,E101-F101,"") -> 0 | H101: 1 | I101: =IF(COUNT(E101:F101)<2,"N/A",IF(ABS(G101)<=H101,"OK","❌")) -> OK | J101: OK | K101: =IF(I101=J101,"✔ sesuai","✖ TIDAK sesuai") -> ✔ sesuai
...

Sheet Temuan
A1: Temuan inkonsistensi & catatan forensik (2022-2025)
A2: Nilai statis dari LK (Rp penuh kecuali jumlah saham/token); selisih = rumus.
A4: Kode | B4: Topik | C4: Nilai A | D4: Nilai B | E4: Selisih A-B | F4: Sumber / hal | G4: Penjelasan | H4: Perlakuan di model
A5: D1 | B5: Restrukturisasi entitas sepengendali: laba & ekuitas proforma | C5: 3248230974 | D5: 52384568796 | E5: =C5-D5 -> -49136337822 | F5: Prospektus hal 272-278; LK FY2025 hal 13-18 | G5: Laporan 2022-2024 disajikan seolah restrukturisasi entitas sepengendali (akuisisi entitas anak oleh Perseroan) terjadi sejak awal. Laba entitas anak sebelum restrukturisasi (proforma) ditambahkan di bawah laba setelah pajak: 2022 1,4 M, 2023 3,0 M, 2024 3,2 M. Ekuitas proforma: 2022 4,9 M, 2023 52,4 M; 2024 menjadi nol setelah restrukturisasi (tambahan modal disetor 2024 -23,4 M = selisih nilai transaksi restrukturisasi). | H5: Baris IS.MERGING terpisah; laba tahun berjalan = laba sebelum pajak + pajak + laba proforma. Proyeksi: laba proforma = 0 (restrukturisasi selesai 2024).
A6: D2 | B6: Dana syirkah temporer diperlakukan sebagai utang berbunga | C6: 69371515682 | D6: 123706879575 | E6: =C6-D6 -> -54335363893 | F6: LK FY2025 hal 13-14; Prospektus | G6: Pembiayaan musyarakah mutanaqisah bank syariah (dana syirkah temporer): 2022 29,8 M, 2023 56,0 M, 2024 78,2 M, 2025 69,4 M. LK FY2025 menyajikannya di antara liabilitas dan ekuitas (total liabilitas tercetak 2025 54,3 M; 2024 60,2 M), sedangkan prospektus menyajikannya dalam liabilitas jangka panjang. Model memindahkannya ke liabilitas tidak lancar untuk semua tahun (konservatif, konsisten antar tahun). Utang berbunga model (bank + pembiayaan konsumen + syirkah): 2022 93,7 M, 2023 145,1 M, 2024 111,8 M, 2025 90,0 M. | H6: Rekonsiliasi "jumlah liabilitas" memakai total model (tercetak + syirkah); ekuitas tidak berubah. Syirkah konstan di proyeksi.
A7: D3 | B7: Piutang pihak berelasi besar & penghasilan bunga 2025 | C7: 117045389015 | D7: 13190576716 | E7: =C7-D7 -> 103854812299 | F7: Neraca & laba rugi; LAK | G7: Piutang pihak berelasi tidak lancar: 2022 14,9 M, 2023 107,9 M, 2024 78,4 M, 2025 117,0 M (2025 = 35% total aset). Penghasilan keuangan 2025 13,2 M (sebelumnya nol), sementara piutang lain-lain pihak berelasi lancar 2025 13,2 M - besarnya hampir sama, mengindikasikan bunga pinjaman ke pihak berelasi yang masih terutang (belum diterima kas). Arus kas pemberian ke pihak berelasi: 2022 -4,9 M, 2023 -45,1 M, 2024 -20,5 M, 2025 -30,1 M. | H7: Imbal hasil kas (yld) = 0 di semua skenario: penghasilan bunga 2025 tidak dianggap berulang. Piutang pihak berelasi konstan.
A8: D4 | B8: Uang muka pembelian aset tetap 2025 | C8: 23480000000 | D8: 3910827865 | E8: =C8-D8 -> 19569172135 | F8: Neraca & LAK FY2025 | G8: Uang muka pembelian aset tetap 2025 23,5 M (dibayar tunai, di arus kas investasi) - jauh di atas perolehan aset tetap tunai tahun itu 3,9 M. Capex tunai historis (perolehan + uang muka): 2022 17,0 M, 2023 36,1 M, 2024 24,4 M, 2025 27,4 M. | H8: Capex rasio historis memuat uang muka ini; asumsi capex Base 9% (setara penyusutan) tidak memodelkan proyek baru.
A9: D5 | B9: Revaluasi tanah & bangunan 2023 | C9: 25288897160 | F9: Prospektus (OCI 2023) | G9: Tahun 2023 aset tetap (tanah & bangunan) beralih ke model revaluasi; surplus revaluasi 25,3 M dicatat di OCI sehingga aset tetap naik dari 66,3 M (2022) ke 117,4 M (2023). | H9: Tanpa revaluasi baru di proyeksi; rasio ROA/ROE 2023 ke atas memakai basis aset/ekuitas yang lebih besar.
A10: D6 | B10: Kas akhir LAK prospektus 2022-2023 tidak sama dengan kas neraca | C10: 39297310909 | D10: 29547207476 | E10: =C10-D10 -> 9750103433 | F10: Prospektus LAK hal 278 | G10: LAK prospektus 2022 berakhir 39,3 M (kas awal 59,6 M termasuk efek cerukan 2021), kas neraca 29,5 M; 2023 LAK berakhir (0,5 M) = kas neto setelah cerukan, kas neraca 2,5 M. Selisih = cerukan bank yang di neraca disajikan di pinjaman bank jangka pendek. | H10: LAK dicetak apa adanya; cek "kas akhir = kas neraca" 2022-2023 ditandai ❌ (dijelaskan). Kas awal 2023 = kas neraca 2022. Proyeksi berangkat dari kas neraca 2025.
A11: D7 | B11: Bunga di arus kas operasi 2025 bertanda positif | C11: 4181857038 | D11: -10242145297 | E11: =C11-D11 -> 14424002335 | F11: LAK FY2025 | G11: Baris pembayaran bunga di LAK 2025 tercetak sebagai penerimaan neto 4,2 M, padahal beban keuangan di laba rugi 10,2 M; tahun 2024 pembayaran 11,5 M. Kemungkinan bunga diterima dari pihak berelasi dinetokan di baris ini. | H11: Dicetak apa adanya; arus kas operasi 2025 tidak dipakai sebagai patokan proyeksi.
A12: D8 | B12: Sumber: FY2021 tidak dipakai; prospektus IDX 403; 2024 komparatif | F12: Prospektus IPO 2025; LK FY2025 | G12: DKHH (PT Cipta Sarana Medika Tbk), IPO 2025. Histori model FY2022-FY2025 (4 tahun). 2022-2023 dari LK konsolidasian audited dalam Prospektus IPO (disajikan proforma seolah restrukturisasi entitas sepengendali terjadi sejak awal); 2024-2025 dari LK FY2025. Kolom 2021 prospektus TIDAK dikonsolidasi (entitas induk saja) sehingga tidak dipakai; periode interim 10 bulan s.d. 31 Okt 2024 juga tidak dipakai. 2020 tidak disajikan. Salinan prospektus di IDX ditolak (403); dipakai salinan di situs emiten (dkhhospitals.com). LK FY2024 tidak tersedia terpisah di IDX: kolom 2024 dari komparatif LK FY2025. Mutasi aset tetap (Cat 10) hanya tersedia 2024-2025. | H12: Histori model FY2022-FY2025 (4 tahun); cek mutasi aset tetap hanya 2024-2025.
A13: D9 | B13: Atribusi laba komprehensif, LPE & EPS tercetak | C13: 6804364595 | D13: 6804450151 | E13: =C13-D13 -> -85556 | F13: LK FY2025 hal 17-18 | G13: Atribusi laba komprehensif tercetak (induk + NCI) tidak menjumlah ke total: 2024 selisih 14.168, 2025 selisih -85.556 (Rp penuh). LPE 2024 mengkredit saldo laba dengan laba penuh 2.837.363.273 (termasuk bagian NCI 131.449). EPS tercetak 2024-2025 dibulatkan ke Rupiah penuh (Rp4 dan Rp3). Laba usaha tercetak LK (sebelum pendapatan lain-lain): 2022 7,1 M, 2023 9,7 M, 2024 11,3 M, 2025 3,5 M; model memakai laba usaha + pendapatan lain-lain neto. | H13: Dicetak apa adanya (selisih kecil, ditandai ❌ dan dijelaskan). Cek EPS toleransi Rp1.
A14: D10 | B14: Selisih penyusutan Cat 10, kategori pendapatan & uji ekstraksi ganda | C14: 9048734806 | D14: 9080234808 | E14: =C14-D14 -> -31500002 | F14: LK FY2025 Cat 10, 25-27 | G14: Alokasi penyusutan 2024 (beban pokok + beban umum) berbeda Rp31,5 juta dari penambahan akumulasi tabel mutasi (= nilai pengurangan akumulasi tahun itu; inkonsistensi internal LK). Kategori pendapatan prospektus (farmasi, laboratorium, radiologi, rawat inap, rawat jalan) dan LK FY2025 (penunjang medis, rawat inap, rawat jalan) dikelompokkan ke 3 kelompok + lainnya. Ekstraksi A: input manual dari pdftotext -layout (prospektus IPO hal 272-278 untuk 2022-2023; LK FY2025 hal 13-20 untuk 2024-2025). Ekstraksi B: setiap angka A dicari verbatim di teks sumber (dan untuk 2022-2023 juga di Ikhtisar Data Keuangan Penting prospektus); subtotal diuji ulang secara aritmetis; saldo awal 2023-2025 diuji ke neraca tahun sebelumnya (cek silang antar tahun). Hasil laporan: 408 nilai sama, 0 berbeda, 0 tidak ditemukan di B. CALK: 110 nilai sama, 0 tidak ditemukan. | H14: Penyusutan model = alokasi di laba rugi. Pertumbuhan per kelompok 2024 vs 2023 bisa terpengaruh batas kategori.
A15: D11 | B15: Tarif pajak efektif ekstrem, tanpa dividen | C15: -480368880 | D15: 69501179 | E15: =C15-D15 -> -549870059 | F15: Laba rugi FY2022-25 | G15: Tarif pajak efektif: 2022 26%, 2023 77%, 2024 691%, 2025 -6%. Laba sebelum pajak 2024 sangat kecil (0,1 M) sehingga tarif ekstrem; 2025 manfaat pajak. Tidak ada dividen ke pemilik induk 2022-2025; NCI sangat kecil. | H15: Pajak Base 25% (tarif badan 22% + beban tidak dapat dikurangkan); payout 0%; NCI 0%.

Sheet Database
A1: Database format panjang FY2022-FY2025 (untuk digabung antar emiten)
A2: Nilai statis sesuai sumber, Rp penuh. Kolom basis: komparatif / dilaporkan.
A4: emiten | B4: kode_emiten | C4: periode | D4: laporan | E4: kode_akun | F4: akun | G4: nilai | H4: satuan | I4: catatan | J4: halaman | K4: sumber | L4: basis | M4: keterangan
A5: PT Cipta Sarana Medika Tbk | B5: DKHH | C5: FY2022 | D5: IS | E5: IS.REVENUE | F5: Pendapatan (Cat 25) | G5: 99578144421 | H5: Rp | J5: Prospektus IPO (LK audited) hal 274-275 | K5: Prospektus IPO DKHH 2025 - LK konsolidasian audited (proforma restrukturisasi entitas sepengendali), kolom 2022 | L5: dilaporkan
A6: PT Cipta Sarana Medika Tbk | B6: DKHH | C6: FY2023 | D6: IS | E6: IS.REVENUE | F6: Pendapatan (Cat 25) | G6: 134187678929 | H6: Rp | J6: Prospektus IPO (LK audited) hal 274-275 | K6: Prospektus IPO DKHH 2025 - LK konsolidasian audited, kolom 31 Des 2023 | L6: dilaporkan
A7: PT Cipta Sarana Medika Tbk | B7: DKHH | C7: FY2024 | D7: IS | E7: IS.REVENUE | F7: Pendapatan (Cat 25) | G7: 152142248784 | H7: Rp | J7: LK FY2025 hal 16-17 | K7: LK FY2025 (komparatif 2024) | L7: komparatif
A8: PT Cipta Sarana Medika Tbk | B8: DKHH | C8: FY2025 | D8: IS | E8: IS.REVENUE | F8: Pendapatan (Cat 25) | G8: 144873268389 | H8: Rp | J8: LK FY2025 hal 16-17 | K8: LK FY2025 | L8: dilaporkan
A9: PT Cipta Sarana Medika Tbk | B9: DKHH | C9: FY2022 | D9: IS | E9: IS.COGS | F9: Beban pokok pendapatan (Cat 26) | G9: -67593755280 | H9: Rp | J9: Prospektus IPO (LK audited) hal 274-275 | K9: Prospektus IPO DKHH 2025 - LK konsolidasian audited (proforma restrukturisasi entitas sepengendali), kolom 2022 | L9: dilaporkan
A10: PT Cipta Sarana Medika Tbk | B10: DKHH | C10: FY2023 | D10: IS | E10: IS.COGS | F10: Beban pokok pendapatan (Cat 26) | G10: -89574415546 | H10: Rp | J10: Prospektus IPO (LK audited) hal 274-275 | K10: Prospektus IPO DKHH 2025 - LK konsolidasian audited, kolom 31 Des 2023 | L10: dilaporkan
A11: PT Cipta Sarana Medika Tbk | B11: DKHH | C11: FY2024 | D11: IS | E11: IS.COGS | F11: Beban pokok pendapatan (Cat 26) | G11: -104806476450 | H11: Rp | J11: LK FY2025 hal 16-17 | K11: LK FY2025 (komparatif 2024) | L11: komparatif
A12: PT Cipta Sarana Medika Tbk | B12: DKHH | C12: FY2025 | D12: IS | E12: IS.COGS | F12: Beban pokok pendapatan (Cat 26) | G12: -110732463969 | H12: Rp | J12: LK FY2025 hal 16-17 | K12: LK FY2025 | L12: dilaporkan
A13: PT Cipta Sarana Medika Tbk | B13: DKHH | C13: FY2022 | D13: IS | E13: IS.GROSS_PROFIT | F13: Laba bruto | G13: 31984389141 | H13: Rp | K13: Prospektus IPO DKHH 2025 - LK konsolidasian audited (proforma restrukturisasi entitas sepengendali), kolom 2022 | L13: dilaporkan | M13: subtotal dihitung
A14: PT Cipta Sarana Medika Tbk | B14: DKHH | C14: FY2023 | D14: IS | E14: IS.GROSS_PROFIT | F14: Laba bruto | G14: 44613263383 | H14: Rp | K14: Prospektus IPO DKHH 2025 - LK konsolidasian audited, kolom 31 Des 2023 | L14: dilaporkan | M14: subtotal dihitung
A15: PT Cipta Sarana Medika Tbk | B15: DKHH | C15: FY2024 | D15: IS | E15: IS.GROSS_PROFIT | F15: Laba bruto | G15: 47335772334 | H15: Rp | K15: LK FY2025 (komparatif 2024) | L15: komparatif | M15: subtotal dihitung
A16: PT Cipta Sarana Medika Tbk | B16: DKHH | C16: FY2025 | D16: IS | E16: IS.GROSS_PROFIT | F16: Laba bruto | G16: 34140804420 | H16: Rp | K16: LK FY2025 | L16: dilaporkan | M16: subtotal dihitung
A17: PT Cipta Sarana Medika Tbk | B17: DKHH | C17: FY2022 | D17: IS | E17: IS.SELLING | F17: Beban penjualan (Cat 27) | G17: -974896353 | H17: Rp | J17: Prospektus IPO Cat 30 hal 368 (subtotal beban penjualan; laba rugi hanya menyajikan beban usaha gabungan) & Ikhtisar hal 41 | K17: Prospektus IPO DKHH 2025 - LK konsolidasian audited (proforma restrukturisasi entitas sepengendali), kolom 2022 | L17: dilaporkan
A18: PT Cipta Sarana Medika Tbk | B18: DKHH | C18: FY2023 | D18: IS | E18: IS.SELLING | F18: Beban penjualan (Cat 27) | G18: -3183805931 | H18: Rp | J18: Prospektus IPO Cat 30 hal 368 (subtotal beban penjualan; laba rugi hanya menyajikan beban usaha gabungan) & Ikhtisar hal 41 | K18: Prospektus IPO DKHH 2025 - LK konsolidasian audited, kolom 31 Des 2023 | L18: dilaporkan
A19: PT Cipta Sarana Medika Tbk | B19: DKHH | C19: FY2024 | D19: IS | E19: IS.SELLING | F19: Beban penjualan (Cat 27) | G19: -4061959293 | H19: Rp | J19: LK FY2025 hal 16-17 | K19: LK FY2025 (komparatif 2024) | L19: komparatif
A20: PT Cipta Sarana Medika Tbk | B20: DKHH | C20: FY2025 | D20: IS | E20: IS.SELLING | F20: Beban penjualan (Cat 27) | G20: -2783285450 | H20: Rp | J20: LK FY2025 hal 16-17 | K20: LK FY2025 | L20: dilaporkan
A21: PT Cipta Sarana Medika Tbk | B21: DKHH | C21: FY2022 | D21: IS | E21: IS.GA | F21: Beban umum dan administrasi (Cat 27) | G21: -23863495422 | H21: Rp | J21: Prospektus IPO Cat 30 hal 368 (subtotal beban umum & administrasi) & Ikhtisar hal 41 | K21: Prospektus IPO DKHH 2025 - LK konsolidasian audited (proforma restrukturisasi entitas sepengendali), kolom 2022 | L21: dilaporkan
A22: PT Cipta Sarana Medika Tbk | B22: DKHH | C22: FY2023 | D22: IS | E22: IS.GA | F22: Beban umum dan administrasi (Cat 27) | G22: -31755062789 | H22: Rp | J22: Prospektus IPO Cat 30 hal 368 (subtotal beban umum & administrasi) & Ikhtisar hal 41 | K22: Prospektus IPO DKHH 2025 - LK konsolidasian audited, kolom 31 Des 2023 | L22: dilaporkan
A23: PT Cipta Sarana Medika Tbk | B23: DKHH | C23: FY2024 | D23: IS | E23: IS.GA | F23: Beban umum dan administrasi (Cat 27) | G23: -31962658076 | H23: Rp | J23: LK FY2025 hal 16-17 | K23: LK FY2025 (komparatif 2024) | L23: komparatif
A24: PT Cipta Sarana Medika Tbk | B24: DKHH | C24: FY2025 | D24: IS | E24: IS.GA | F24: Beban umum dan administrasi (Cat 27) | G24: -27906878912 | H24: Rp | J24: LK FY2025 hal 16-17 | K24: LK FY2025 | L24: dilaporkan
A25: PT Cipta Sarana Medika Tbk | B25: DKHH | C25: FY2022 | D25: IS | E25: IS.OPEX_TOTAL | F25: Jumlah beban usaha | G25: -24838391775 | H25: Rp | K25: Prospektus IPO DKHH 2025 - LK konsolidasian audited (proforma restrukturisasi entitas sepengendali), kolom 2022 | L25: dilaporkan | M25: subtotal dihitung
A26: PT Cipta Sarana Medika Tbk | B26: DKHH | C26: FY2023 | D26: IS | E26: IS.OPEX_TOTAL | F26: Jumlah beban usaha | G26: -34938868720 | H26: Rp | K26: Prospektus IPO DKHH 2025 - LK konsolidasian audited, kolom 31 Des 2023 | L26: dilaporkan | M26: subtotal dihitung
A27: PT Cipta Sarana Medika Tbk | B27: DKHH | C27: FY2024 | D27: IS | E27: IS.OPEX_TOTAL | F27: Jumlah beban usaha | G27: -36024617369 | H27: Rp | K27: LK FY2025 (komparatif 2024) | L27: komparatif | M27: subtotal dihitung
A28: PT Cipta Sarana Medika Tbk | B28: DKHH | C28: FY2025 | D28: IS | E28: IS.OPEX_TOTAL | F28: Jumlah beban usaha | G28: -30690164362 | H28: Rp | K28: LK FY2025 | L28: dilaporkan | M28: subtotal dihitung
A29: PT Cipta Sarana Medika Tbk | B29: DKHH | C29: FY2022 | D29: IS | E29: IS.OTHER_INCOME | F29: Pendapatan (beban) lain-lain - neto (sewa & lain-lain) | G29: 1226392843 | H29: Rp | J29: Prospektus IPO (LK audited) hal 274-275 | K29: Prospektus IPO DKHH 2025 - LK konsolidasian audited (proforma restrukturisasi entitas sepengendali), kolom 2022 | L29: dilaporkan
A30: PT Cipta Sarana Medika Tbk | B30: DKHH | C30: FY2023 | D30: IS | E30: IS.OTHER_INCOME | F30: Pendapatan (beban) lain-lain - neto (sewa & lain-lain) | G30: 75326392 | H30: Rp | J30: Prospektus IPO (LK audited) hal 274-275 | K30: Prospektus IPO DKHH 2025 - LK konsolidasian audited, kolom 31 Des 2023 | L30: dilaporkan
A31: PT Cipta Sarana Medika Tbk | B31: DKHH | C31: FY2024 | D31: IS | E31: IS.OTHER_INCOME | F31: Pendapatan (beban) lain-lain - neto (sewa & lain-lain) | G31: 313957191 | H31: Rp | J31: LK FY2025 hal 16-17 (= sewa & non-operasional lainnya + penghasilan lainnya - neto) | K31: LK FY2025 (komparatif 2024) | L31: komparatif
A32: PT Cipta Sarana Medika Tbk | B32: DKHH | C32: FY2025 | D32: IS | E32: IS.OTHER_INCOME | F32: Pendapatan (beban) lain-lain - neto (sewa & lain-lain) | G32: -710131821 | H32: Rp | J32: LK FY2025 hal 16-17 (= sewa & non-operasional lainnya + penghasilan lainnya - neto) | K32: LK FY2025 | L32: dilaporkan
A33: PT Cipta Sarana Medika Tbk | B33: DKHH | C33: FY2022 | D33: IS | E33: IS.OTHER_OPER_NET | F33: Pendapatan (beban) lain-lain neto | G33: 1226392843 | H33: Rp | K33: Prospektus IPO DKHH 2025 - LK konsolidasian audited (proforma restrukturisasi entitas sepengendali), kolom 2022 | L33: dilaporkan | M33: subtotal dihitung
A34: PT Cipta Sarana Medika Tbk | B34: DKHH | C34: FY2023 | D34: IS | E34: IS.OTHER_OPER_NET | F34: Pendapatan (beban) lain-lain neto | G34: 75326392 | H34: Rp | K34: Prospektus IPO DKHH 2025 - LK konsolidasian audited, kolom 31 Des 2023 | L34: dilaporkan | M34: subtotal dihitung
A35: PT Cipta Sarana Medika Tbk | B35: DKHH | C35: FY2024 | D35: IS | E35: IS.OTHER_OPER_NET | F35: Pendapatan (beban) lain-lain neto | G35: 313957191 | H35: Rp | K35: LK FY2025 (komparatif 2024) | L35: komparatif | M35: subtotal dihitung
A36: PT Cipta Sarana Medika Tbk | B36: DKHH | C36: FY2025 | D36: IS | E36: IS.OTHER_OPER_NET | F36: Pendapatan (beban) lain-lain neto | G36: -710131821 | H36: Rp | K36: LK FY2025 | L36: dilaporkan | M36: subtotal dihitung
A37: PT Cipta Sarana Medika Tbk | B37: DKHH | C37: FY2022 | D37: IS | E37: IS.OPER_PROFIT | F37: Laba usaha model (laba bruto - beban usaha + lain-lain neto; Temuan D9) | G37: 8372390209 | H37: Rp | K37: Prospektus IPO DKHH 2025 - LK konsolidasian audited (proforma restrukturisasi entitas sepengendali), kolom 2022 | L37: dilaporkan | M37: subtotal dihitung
A38: PT Cipta Sarana Medika Tbk | B38: DKHH | C38: FY2023 | D38: IS | E38: IS.OPER_PROFIT | F38: Laba usaha model (laba bruto - beban usaha + lain-lain neto; Temuan D9) | G38: 9749721055 | H38: Rp | K38: Prospektus IPO DKHH 2025 - LK konsolidasian audited, kolom 31 Des 2023 | L38: dilaporkan | M38: subtotal dihitung
A39: PT Cipta Sarana Medika Tbk | B39: DKHH | C39: FY2024 | D39: IS | E39: IS.OPER_PROFIT | F39: Laba usaha model (laba bruto - beban usaha + lain-lain neto; Temuan D9) | G39: 11625112156 | H39: Rp | K39: LK FY2025 (komparatif 2024) | L39: komparatif | M39: subtotal dihitung
A40: PT Cipta Sarana Medika Tbk | B40: DKHH | C40: FY2025 | D40: IS | E40: IS.OPER_PROFIT | F40: Laba usaha model (laba bruto - beban usaha + lain-lain neto; Temuan D9) | G40: 2740508237 | H40: Rp | K40: LK FY2025 | L40: dilaporkan | M40: subtotal dihitung
A41: PT Cipta Sarana Medika Tbk | B41: DKHH | C41: FY2022 | D41: IS | E41: IS.FIN_COST | F41: Beban keuangan | G41: -3643595812 | H41: Rp | J41: Prospektus IPO (LK audited) hal 274-275 | K41: Prospektus IPO DKHH 2025 - LK konsolidasian audited (proforma restrukturisasi entitas sepengendali), kolom 2022 | L41: dilaporkan
A42: PT Cipta Sarana Medika Tbk | B42: DKHH | C42: FY2023 | D42: IS | E42: IS.FIN_COST | F42: Beban keuangan | G42: -7565985614 | H42: Rp | J42: Prospektus IPO (LK audited) hal 274-275 | K42: Prospektus IPO DKHH 2025 - LK konsolidasian audited, kolom 31 Des 2023 | L42: dilaporkan
A43: PT Cipta Sarana Medika Tbk | B43: DKHH | C43: FY2024 | D43: IS | E43: IS.FIN_COST | F43: Beban keuangan | G43: -11555610977 | H43: Rp | J43: LK FY2025 hal 16-17 | K43: LK FY2025 (komparatif 2024) | L43: komparatif
A44: PT Cipta Sarana Medika Tbk | B44: DKHH | C44: FY2025 | D44: IS | E44: IS.FIN_COST | F44: Beban keuangan | G44: -10242145297 | H44: Rp | J44: LK FY2025 hal 16-17 | K44: LK FY2025 | L44: dilaporkan
A45: PT Cipta Sarana Medika Tbk | B45: DKHH | C45: FY2022 | D45: IS | E45: IS.FIN_INCOME | F45: Penghasilan keuangan | G45: 0 | H45: Rp | J45: Prospektus IPO (LK audited) hal 274-275 | K45: Prospektus IPO DKHH 2025 - LK konsolidasian audited (proforma restrukturisasi entitas sepengendali), kolom 2022 | L45: dilaporkan
A46: PT Cipta Sarana Medika Tbk | B46: DKHH | C46: FY2023 | D46: IS | E46: IS.FIN_INCOME | F46: Penghasilan keuangan | G46: 0 | H46: Rp | J46: Prospektus IPO (LK audited) hal 274-275 | K46: Prospektus IPO DKHH 2025 - LK konsolidasian audited, kolom 31 Des 2023 | L46: dilaporkan
A47: PT Cipta Sarana Medika Tbk | B47: DKHH | C47: FY2024 | D47: IS | E47: IS.FIN_INCOME | F47: Penghasilan keuangan | G47: 0 | H47: Rp | J47: LK FY2025 hal 16-17 | K47: LK FY2025 (komparatif 2024) | L47: komparatif
A48: PT Cipta Sarana Medika Tbk | B48: DKHH | C48: FY2025 | D48: IS | E48: IS.FIN_INCOME | F48: Penghasilan keuangan | G48: 13190576716 | H48: Rp | J48: LK FY2025 hal 16-17 | K48: LK FY2025 | L48: dilaporkan
A49: PT Cipta Sarana Medika Tbk | B49: DKHH | C49: FY2022 | D49: IS | E49: IS.PBT | F49: Laba sebelum pajak | G49: 4728794397 | H49: Rp | K49: Prospektus IPO DKHH 2025 - LK konsolidasian audited (proforma restrukturisasi entitas sepengendali), kolom 2022 | L49: dilaporkan | M49: subtotal dihitung
A50: PT Cipta Sarana Medika Tbk | B50: DKHH | C50: FY2023 | D50: IS | E50: IS.PBT | F50: Laba sebelum pajak | G50: 2183735441 | H50: Rp | K50: Prospektus IPO DKHH 2025 - LK konsolidasian audited, kolom 31 Des 2023 | L50: dilaporkan | M50: subtotal dihitung
A51: PT Cipta Sarana Medika Tbk | B51: DKHH | C51: FY2024 | D51: IS | E51: IS.PBT | F51: Laba sebelum pajak | G51: 69501179 | H51: Rp | K51: LK FY2025 (komparatif 2024) | L51: komparatif | M51: subtotal dihitung
A52: PT Cipta Sarana Medika Tbk | B52: DKHH | C52: FY2025 | D52: IS | E52: IS.PBT | F52: Laba sebelum pajak | G52: 5688939656 | H52: Rp | K52: LK FY2025 | L52: dilaporkan | M52: subtotal dihitung
A53: PT Cipta Sarana Medika Tbk | B53: DKHH | C53: FY2022 | D53: IS | E53: IS.TAX_TOTAL | F53: Beban (manfaat) pajak penghasilan | G53: -1220088106 | H53: Rp | J53: Prospektus IPO (LK audited) hal 274-275 | K53: Prospektus IPO DKHH 2025 - LK konsolidasian audited (proforma restrukturisasi entitas sepengendali), kolom 2022 | L53: dilaporkan
A54: PT Cipta Sarana Medika Tbk | B54: DKHH | C54: FY2023 | D54: IS | E54: IS.TAX_TOTAL | F54: Beban (manfaat) pajak penghasilan | G54: -1675692417 | H54: Rp | J54: Prospektus IPO (LK audited) hal 274-275 | K54: Prospektus IPO DKHH 2025 - LK konsolidasian audited, kolom 31 Des 2023 | L54: dilaporkan
A55: PT Cipta Sarana Medika Tbk | B55: DKHH | C55: FY2024 | D55: IS | E55: IS.TAX_TOTAL | F55: Beban (manfaat) pajak penghasilan | G55: -480368880 | H55: Rp | J55: LK FY2025 hal 16-17 (pajak kini + tangguhan) | K55: LK FY2025 (komparatif 2024) | L55: komparatif
A56: PT Cipta Sarana Medika Tbk | B56: DKHH | C56: FY2025 | D56: IS | E56: IS.TAX_TOTAL | F56: Beban (manfaat) pajak penghasilan | G56: 332957861 | H56: Rp | J56: LK FY2025 hal 16-17 (pajak kini + tangguhan) | K56: LK FY2025 | L56: dilaporkan
A57: PT Cipta Sarana Medika Tbk | B57: DKHH | C57: FY2022 | D57: IS | E57: IS.MERGING | F57: Laba entitas anak sebelum restrukturisasi (proforma 2022-2024; Temuan D1) | G57: 1379459473 | H57: Rp | J57: Prospektus IPO (LK audited) hal 274-275 (laba entitas anak - dampak penyesuaian proforma restrukturisasi entitas sepengendali) | K57: Prospektus IPO DKHH 2025 - LK konsolidasian audited (proforma restrukturisasi entitas sepengendali), kolom 2022 | L57: dilaporkan
