Workbook

Sheet Cover
B2: PT Sejahteraraya Anugrahjaya Tbk (SRAJ) - Model data fundamental 6 tahun & proyeksi ilustratif
B3: Historis FY2020-FY2025 (laporan keuangan konsolidasian audited) | proyeksi ilustratif FY2026-FY2030 | Format: PRO
B5: Penting - sifat dokumen
B6: Bukan rekomendasi | C6: Dokumen ini hanya ringkasan informasi dan analisis data fundamental yang bersumber dari laporan keuangan publik (audited) PT Sejahteraraya Anugrahjaya Tbk. Dokumen ini BUKAN saran atau rekomendasi investasi, bukan ajakan membeli, menjual, atau menahan efek apa pun, dan tidak memuat target atau penilaian nilai wajar. Proyeksi bersifat ilustratif dan dapat berbeda jauh dari realisasi. Data dapat mengandung kesalahan ekstraksi; selalu cek ke laporan asli. Dokumen ini disusun dengan bantuan kecerdasan buatan (AI) dari laporan keuangan publik; kemungkinan kesalahan tetap ada, harap verifikasi ke sumber.
B7: Proyeksi | C7: Angka FY..E adalah proyeksi ILUSTRATIF berbasis asumsi transparan di sheet Asumsi (Base/Bull/Bear), dikalibrasi dari tren FY2022-2025. Tidak ada target, nilai wajar, atau kesimpulan nilai per saham.
B8: Sumber data | C8: Laporan keuangan konsolidasian audited PT Sejahteraraya Anugrahjaya Tbk FY2020-FY2025 (diunduh dari situs perusahaan mayapadahospital.com, halaman hubungan investor). Kolom 2020-2023 dan 2025 dari LK tahun masing-masing (dasar asli); kolom 2024 dari komparatif LK FY2025 yang disajikan kembali (PSAK 115: Grup sebagai agen atas jasa dokter). LK FY2023-FY2025 dalam jutaan Rupiah (dikonversi ke Rupiah penuh). Lihat Data_Log & Temuan.
B10: Hak cipta & lisensi
B11: Hak cipta | C11: © 2026 Ryant Gabein Pasaribu. Kompilasi, struktur, metodologi, kode akun standar, dan analisis dalam file ini adalah ciptaan Ryant Gabein Pasaribu. Dilisensikan di bawah Creative Commons Atribusi 4.0 Internasional (CC BY 4.0): bebas digunakan dan dibagikan dengan wajib mencantumkan atribusi "Ryant Gabein Pasaribu" dan menyertakan tautan lisensi https://creativecommons.org/licenses/by/4.0/deed.id. Data laporan keuangan bersumber dari laporan publik emiten.
B12: Versi | C12: v1.0
B13: Tanggal terbit | C13: 2026-10-26
B14: ID file | C14: SRAJ-FY2025-v1.0-79A95C20
B16: Format
B17: Data terbuka | C17: Data dan model ini terbuka dan gratis untuk semua orang.
B18: Format output | C18: Tiga format (bukan tingkatan akses, semuanya gratis): Ritel (PDF ringkasan 4 halaman), Akademik (Excel data historis, rasio, rekonsiliasi), Pro (Excel model penuh dengan proyeksi ilustratif & template DCF kosong).
B20: Informasi model
B21: Emiten | C21: PT Sejahteraraya Anugrahjaya Tbk dan Entitas Anaknya (kode SRAJ) - jaringan rumah sakit swasta Mayapada Hospital (Jakarta, Tangerang, Bogor, Surabaya, Bandung)
B22: Satuan | C22: Rupiah penuh (Ringkasan/Dashboard: Rp miliar); beban & arus kas keluar negatif (kurung)
B23: Tahun historis | C23: FY2020, FY2021, FY2022, FY2023, FY2024, FY2025
B24: Status rekonsiliasi | C24: =Rekonsiliasi!$C$3 -> SEMUA 330 CEK SESUAI EKSPEKTASI
B25: Skenario aktif | C25: =Asumsi!C4 -> Base
B26: Dibangun | C26: 26-10-2026 oleh /workspace/emiten/common/build_model.py --ticker SRAJ
B28: Daftar sheet
B29: Cover | C29: Sifat dokumen, lisensi, keterangan warna
B30: Panduan | C30: Cara memakai model ini
B31: Ringkasan | C31: Ringkasan siap cetak/PDF (A4): highlights, indikator utama, grafik, tanda perhatian
B32: Dashboard | C32: Indikator & grafik historis + proyeksi ilustratif
B33: Asumsi | C33: Selektor skenario Base/Bull/Bear & driver per tahun, dengan dasar kalibrasi FY2023-2025
B34: IS_Proj | C34: Proyeksi laba rugi (pendapatan per kelompok, EBITDA, laba)
B35: BS_Proj | C35: Proyeksi neraca agregat; kas = penyeimbang; cek balance
B36: CF_Proj | C36: Proyeksi arus kas tidak langsung; FCF
B37: Schedules_Proj | C37: Aset tetap, aset takberwujud, sewa, utang, modal kerja
B38: DCF_Template | C38: Kalkulator DCF opsional dengan input KOSONG (tanpa kesimpulan)
B39: Peer | C39: Tabel pembanding fundamental (input kosong, tanpa kelipatan pasar)
B40: IS | C40: Laba rugi & OCI FY2020-2025
... B48: Data_Log | C48: Sumber per tahun, pemetaan akun, override

Sheet Panduan
A1: Panduan pemakaian
A2: Format PRO (model penuh) - gratis & terbuka; bukan rekomendasi investasi
B4: Langkah
B5: 1. Mulai | C5: Baca Cover (sifat dokumen) lalu Ringkasan (siap cetak A4: File > Print/Export PDF untuk sheet Ringkasan).
B6: 2. Data historis | C6: IS, BS, CF berisi angka laporan (biru) dan subtotal rumus (hitam). Baris 3 menyebut sumber tiap kolom; kolom FY2020 berlatar oranye = kolom pertama (LK FY2020); kolom 2024 dari komparatif LK FY2025 yang disajikan kembali (Temuan S1-S2).
B7: 3. Rincian & rasio | C7: Schedules memuat rincian catatan (CALK) FY2020-2025; bagian A merangkum angka yang dipakai Rasio. Rasio memakai rumus hidup dan kolom rata-rata FY2022-25.
B8: 4. Cek kualitas | C8: Rekonsiliasi: kolom "Sesuai ekspektasi?" harus ✔ untuk semua baris. ❌ yang diharapkan adalah selisih di laporan sumber dan dijelaskan di kolom Penjelasan / sheet Temuan.
B9: 5. Proyeksi ilustratif | C9: Pilih skenario di Asumsi!C4 (Base/Bull/Bear). Ubah sel biru di blok skenario untuk mencoba asumsi sendiri; IS_Proj, BS_Proj, CF_Proj ikut berubah. Cek BS_Proj baris "Cek" harus 0.
B10: 6. Template DCF (opsional) | C10: Isi sendiri sel kuning (Rf, ERP, beta, Kd, pajak, bobot utang, g / kelipatan). Tanpa input, template tidak menghitung apa pun. Hasil adalah keluaran rumus atas input Anda, bukan nilai wajar atau rekomendasi.
B11: 7. Peer | C11: Isi data fundamental pembanding dari laporan publik masing-masing emiten beserta sumbernya. Tidak ada angka pembanding yang dikarang di file ini.
B13: Keterangan warna
B14: Biru | C14: Input / angka dari laporan (bisa diubah)
B15: Hitam | C15: Rumus di sheet yang sama
B16: Hijau | C16: Rumus yang merujuk sheet lain
B17: Kuning | C17: Sel yang perlu diisi/diverifikasi pengguna atau angka yang dikoreksi (ada komentar sel)
B18: Oranye | C18: Kolom FY2020 (kolom pertama) dari LK FY2020
B19: Biru muda | C19: Kolom tahun proyeksi (E) - ilustratif
B21: Definisi penting
B22: EBITDA | C22: Laba usaha dihitung (laba bruto - beban penjualan - beban umum & administrasi + pendapatan lain neto) + penyusutan aset tetap (Cat 27-28) + penyusutan aset hak guna + amortisasi aset takberwujud (Cat 28).
B23: Utang | C23: Utang berbunga: utang bank, pinjaman non-bank, surat utang/obligasi dan utang pembiayaan. Utang neto juga menambahkan liabilitas sewa dan mengurangi kas (negatif = kas neto).
B24: EPS | C24: EPS tercetak memakai saham rata-rata tertimbang (CALK) (Temuan S9).
B25: Satuan | C25: Rupiah penuh kecuali disebut (Ringkasan/Dashboard: Rp miliar). Beban & arus kas keluar bertanda negatif.
B27: Daftar sheet (format ini)
B28: Cover | C28: Sifat dokumen, lisensi, keterangan warna
B29: Panduan | C29: Cara memakai model ini
B30: Ringkasan | C30: Ringkasan siap cetak/PDF (A4): highlights, indikator utama, grafik, tanda perhatian
B31: Dashboard | C31: Indikator & grafik historis + proyeksi ilustratif
B32: Asumsi | C32: Selektor skenario Base/Bull/Bear & driver per tahun, dengan dasar kalibrasi FY2023-2025
B33: IS_Proj | C33: Proyeksi laba rugi (pendapatan per kelompok, EBITDA, laba)
B34: BS_Proj | C34: Proyeksi neraca agregat; kas = penyeimbang; cek balance
B35: CF_Proj | C35: Proyeksi arus kas tidak langsung; FCF
B36: Schedules_Proj | C36: Aset tetap, aset takberwujud, sewa, utang, modal kerja
B37: DCF_Template | C37: Kalkulator DCF opsional dengan input KOSONG (tanpa kesimpulan)
B38: Peer | C38: Tabel pembanding fundamental (input kosong, tanpa kelipatan pasar)
B39: IS | C39: Laba rugi & OCI FY2020-2025
... B47: Data_Log | C47: Sumber per tahun, pemetaan akun, override
B49: Batasan
B50: Data | C50: Angka diekstrak dari PDF dan dapat mengandung kesalahan; cek ke laporan asli sebelum dipakai.
B51: Proyeksi | C51: Asumsi sederhana: pos neraca lain konstan, utang & liabilitas sewa konstan (pembayaran sewa dikapitalisasi ke aset tetap), beban keuangan = suku bunga x rata-rata utang, aset hak guna konstan, tanpa OCI/penurunan nilai baru, tanpa transaksi saham, akuisisi atau pendanaan baru. Hasil sangat sensitif terhadap asumsi.
B52: Bukan saran | C52: Dokumen ini hanya ringkasan informasi dan analisis data fundamental yang bersumber dari laporan keuangan publik (audited) PT Sejahteraraya Anugrahjaya Tbk. Dokumen ini BUKAN saran atau rekomendasi investasi, bukan ajakan membeli, menjual, atau menahan efek apa pun, dan tidak memuat target atau penilaian nilai wajar. Proyeksi bersifat ilustratif dan dapat berbeda jauh dari realisasi. Data dapat mengandung kesalahan ekstraksi; selalu cek ke laporan asli. Dokumen ini disusun dengan bantuan kecerdasan buatan (AI) dari laporan keuangan publik; kemungkinan kesalahan tetap ada, harap verifikasi ke sumber.

Sheet Ringkasan
B1: Mayapada Hospital (SRAJ) | Ringkasan FY2020-FY2025
B2: Jaringan rumah sakit swasta Mayapada Hospital (Jakarta, Tangerang, Bogor, Surabaya, Bandung) | sumber: laporan keuangan konsolidasian audited | gratis & terbuka | BUKAN rekomendasi investasi
B4: Penting: Dokumen ini hanya ringkasan informasi dan analisis data fundamental yang bersumber dari laporan keuangan publik (audited) PT Sejahteraraya Anugrahjaya Tbk. Dokumen ini BUKAN saran atau rekomendasi investasi, bukan ajakan membeli, menjual, atau menahan efek apa pun, dan tidak memuat target atau penilaian nilai wajar. Proyeksi bersifat ilustratif dan dapat berbeda jauh dari realisasi. Data dapat mengandung kesalahan ekstraksi; selalu cek ke laporan asli. Dokumen ini disusun dengan bantuan kecerdasan buatan (AI) dari laporan keuangan publik; kemungkinan kesalahan tetap ada, harap verifikasi ke sumber.
B6: Ringkasan Eksekutif / Highlights
B7: • Pendapatan FY2025 Rp2.589 miliar (+10,6% vs FY2024, basis neto agen): obat & perlengkapan medis Rp1.292 miliar, rawat inap Rp1.400 miliar, rawat jalan & penunjang Rp810 miliar, dikurangi jasa tenaga ahli (agen) & diskon Rp912 miliar.
B8: • Pendapatan tercetak naik dari Rp1.284 miliar (FY2020) ke Rp2.503 miliar (FY2023, bruto); 2024 disajikan kembali menjadi Rp2.340 miliar karena jasa dokter dicatat neto (agen).
B9: • Rugi pemilik induk FY2025 Rp199,0 miliar (EPS Rp-16,31) vs Rp-23,5 miliar FY2024; margin laba bersih -7,7%. Beban keuangan FY2025 Rp388 miliar.
B10: • Utang berbunga Rp4.684 miliar vs kas Rp1.826 miliar (FY2025), naik dari Rp1.072 miliar (FY2020) untuk ekspansi rumah sakit (termasuk surat utang 2025); utang neto / EBITDA 6,1x.
B11: • Data 6 tahun direkonsiliasi dengan 330 cek; 5 selisih di laporan sumber sudah diperkirakan dan dijelaskan (lihat tanda perhatian & sheet Temuan).
B13: Indikator utama (Rp miliar, kecuali disebut lain) - rumus hidup dari sheet IS/BS/CF/Rasio
B14: Indikator | C14: FY2020A | D14: FY2021A | E14: FY2022A | F14: FY2023A | G14: FY2024A | H14: FY2025A
B15: Pendapatan | C15: =IS!C6/1000000000 -> 1283.7986 | D15: =IS!D6/1000000000 -> 1924.4531 | E15: =IS!E6/1000000000 -> 1934.1637 | F15: =IS!F6/1000000000 -> 2503.174 | G15: =IS!G6/1000000000 -> 2340.431 | H15: =IS!H6/1000000000 -> 2589.44
B16: Pertumbuhan | D16: =Rasio!D6 -> 0.4990304 | E16: =Rasio!E6 -> 0.0050458698 | F16: =Rasio!F6 -> 0.29418933 | G16: =Rasio!G6 -> -0.065014657 | H16: =Rasio!H6 -> 0.10639451
B17: Porsi obat & perlengkapan medis | C17: =Rasio!C26 -> 0.19780117 | D17: =Rasio!D26 -> 0.21709091 | E17: =Rasio!E26 -> 0.22323405 | F17: =Rasio!F26 -> 0.30145088 | G17: =Rasio!G26 -> 0.49735369 | H17: =Rasio!H26 -> 0.49884145
B18: EBITDA | C18: =Rasio!C16/1000000000 -> 176.84041 | D18: =Rasio!D16/1000000000 -> 431.70323 | E18: =Rasio!E16/1000000000 -> 268.70754 | F18: =Rasio!F16/1000000000 -> 402.552 | G18: =Rasio!G16/1000000000 -> 484.442 | H18: =Rasio!H16/1000000000 -> 466.738
B19: Margin EBITDA | C19: =Rasio!C17 -> 0.13774778 | D19: =Rasio!D17 -> 0.22432515 | E19: =Rasio!E17 -> 0.13892699 | F19: =Rasio!F17 -> 0.16081663 | G19: =Rasio!G17 -> 0.20698837 | H19: =Rasio!H17 -> 0.18024669
B20: Laba tahun berjalan | C20: =IS!C19/1000000000 -> -14.498058 | D20: =IS!D19/1000000000 -> 165.60405 | E20: =IS!E19/1000000000 -> -44.187231 | F20: =IS!F19/1000000000 -> -38.313 | G20: =IS!G19/1000000000 -> -23.344 | H20: =IS!H19/1000000000 -> -198.79
B21: Laba pemilik entitas induk | C21: =IS!C26/1000000000 -> -14.380627 | D21: =IS!D26/1000000000 -> 165.30824 | E21: =IS!E26/1000000000 -> -44.314949 | F21: =IS!F26/1000000000 -> -38.49 | G21: =IS!G26/1000000000 -> -23.513 | H21: =IS!H26/1000000000 -> -199
B22: Porsi laba ke NCI | C22: =Rasio!C23 -> 0.0080997698 | D22: =Rasio!D23 -> 0.0017862363 | E22: =Rasio!E23 -> -0.0028903894 | F22: =Rasio!F23 -> -0.0046198418 | G22: =Rasio!G23 -> -0.0072395476 | H22: =Rasio!H23 -> -0.0010563912
B23: ROE (rata-rata ekuitas induk) | D23: =Rasio!D20 -> 0.089835082 | E23: =Rasio!E20 -> -0.023200175 | F23: =Rasio!F20 -> -0.020528177 | G23: =Rasio!G20 -> -0.012756941 | H23: =Rasio!H20 -> -0.12583619
B24: Arus kas operasi | C24: =CF!C13/1000000000 -> 93.881891 | D24: =CF!D13/1000000000 -> 336.78666 | E24: =CF!E13/1000000000 -> 210.47482 | F24: =CF!F13/1000000000 -> 55.917 | G24: =CF!G13/1000000000 -> 273.248 | H24: =CF!H13/1000000000 -> 129.67
B25: Capex | C25: =Rasio!C41/1000000000 -> 544.12234 | D25: =Rasio!D41/1000000000 -> 464.02328 | E25: =Rasio!E41/1000000000 -> 655.54652 | F25: =Rasio!F41/1000000000 -> 583.532 | G25: =Rasio!G41/1000000000 -> 525.029 | H25: =Rasio!H41/1000000000 -> 579.605
B26: Utang neto (utang + sewa - kas) | C26: =Rasio!C36/1000000000 -> 442.64253 | D26: =Rasio!D36/1000000000 -> 145.27236 | E26: =Rasio!E36/1000000000 -> 607.05664 | F26: =Rasio!F36/1000000000 -> 1135.049 | G26: =Rasio!G36/1000000000 -> 1391.934 | H26: =Rasio!H36/1000000000 -> 2865.829
B27: Utang neto / EBITDA (x) | C27: =Rasio!C38 -> 2.5030622 | D27: =Rasio!D38 -> 0.33650978 | E27: =Rasio!E38 -> 2.2591723 | F27: =Rasio!F38 -> 2.8196332 | G27: =Rasio!G38 -> 2.8732728 | H27: =Rasio!H38 -> 6.1401236
B28: DSO piutang (hari) | C28: =Rasio!C28 -> 64.090527 | D28: =Rasio!D28 -> 44.362731 | E28: =Rasio!E28 -> 45.853511 | F28: =Rasio!F28 -> 57.643682 | G28: =Rasio!G28 -> 66.171047 | H28: =Rasio!H28 -> 78.644628
B29: Tarif pajak efektif | C29: =Rasio!C22 -> 76.751242 | D29: =Rasio!D22 -> -0.058717335 | E29: =Rasio!E22 -> -0.049904963 | F29: =Rasio!F22 -> -0.22440957 | G29: =Rasio!G22 -> -7.8424242 | H29: =Rasio!H22 -> 0.1546966
B30: Catatan: tiap kolom dari LK tahun itu (dasar asli); 2024 = komparatif LK FY2025 yang disajikan kembali (PSAK 115: Grup sebagai agen atas jasa dokter), sehingga pendapatan & margin bruto 2020-2023 (basis bruto) tidak sebanding dengan 2024-2025. Laba usaha tidak dicetak di LK dan dihitung model. (Temuan S1-S4)
B32: Tren 5 tahun
B50: Batang = pendapatan per kelompok (Cat 26; lainnya = administrasi & operasional lain dikurangi diskon); garis putus-putus = porsi obat & perlengkapan medis terhadap pendapatan (sumbu kanan).
B68: Kiri: margin terhadap pendapatan. Kanan: arus kas operasi (abu-abu), capex (arsir), pembayaran sewa (titik), dan sisanya (garis).
B86: Tanda perhatian dari laporan keuangan (bahasa sederhana)
B87: 1. Rugi berulang - Grup rugi bersih pada 2020 dan 2022-2025 (2025 rugi sekitar Rp199 miliar), hanya 2021 laba; tidak ada dividen. (Temuan S9)
B88: 2. Utang & beban bunga naik tajam - Utang berbunga (termasuk surat utang 2025) naik tajam; beban keuangan 2025 sekitar Rp388 miliar. Proyeksi Base dapat menunjukkan kebutuhan pendanaan. (Temuan S6)
B89: 3. Penyajian kembali 2024 - LK FY2025 menyajikan kembali 2024: jasa dokter dicatat neto (agen), pendapatan turun sekitar Rp808 miliar tanpa mengubah laba; 2020-2023 masih bruto. (Temuan S2)
B90: 4. Pihak berelasi - Utang lain-lain kepada pihak berelasi besar (sekitar Rp1,0-1,5 triliun) dan menjadi sumber pendanaan. (Temuan S7)
B91: 5. Definisi kas & kategori pendapatan - Kas di laporan arus kas berbeda dengan kas neraca pada beberapa tahun (cerukan, penyajian kembali); kategori pendapatan berubah di LK FY2023. (Temuan S3, S5)
B92: 6. Proyeksi ilustratif - Skenario Base/Bull/Bear bukan perkiraan; tidak ada target harga atau nilai wajar.
B93: Detail lengkap ada di sheet Temuan dan Rekonsiliasi. Tanda perhatian bukan tuduhan kecurangan; ini daftar hal yang perlu dicek ulang ke laporan asli.
... B103: Dokumen ini hanya ringkasan informasi dan analisis data fundamental yang bersumber dari laporan keuangan publik (audited) PT Sejahteraraya Anugrahjaya Tbk. Dokumen ini BUKAN saran atau rekomendasi investasi, bukan ajakan membeli, menjual, atau menahan efek apa pun, dan tidak memuat target atau penilaian nilai wajar. Proyeksi bersifat ilustratif dan dapat berbeda jauh dari realisasi. Data dapat mengandung kesalahan ekstraksi; selalu cek ke laporan asli. Dokumen ini disusun dengan bantuan kecerdasan buatan (AI) dari laporan keuangan publik; kemungkinan kesalahan tetap ada, harap verifikasi ke sumber. Penyusun tidak bertanggung jawab atas keputusan apa pun yang diambil berdasarkan dokumen ini. Dokumen ini disusun pada 26-10-2026.

Sheet Dashboard
A1: Dashboard - historis FY2020-FY2025 & proyeksi ilustratif FY2026-FY2030 (skenario aktif)
A2: Rp miliar. Kolom E = Proyeksi ILUSTRATIF berbasis asumsi transparan - bukan rekomendasi investasi, bukan target, bukan nilai wajar. Tidak ada nilai per saham/target di sheet ini.
B3: Skenario aktif: | C3: =Asumsi!C4 -> Base
B4: Indikator | C4: FY2020A | D4: FY2021A | E4: FY2022A | F4: FY2023A | G4: FY2024A | H4: FY2025A | I4: FY2026E | J4: FY2027E | K4: FY2028E | L4: FY2029E | M4: FY2030E | N4: Catatan
B5: Pendapatan neto | C5: =IS_Proj!C10/1000000000 -> 1283.7986 | D5: =IS_Proj!D10/1000000000 -> 1924.4531 | E5: =IS_Proj!E10/1000000000 -> 1934.1637 | F5: =IS_Proj!F10/1000000000 -> 2503.174 | G5: =IS_Proj!G10/1000000000 -> 2340.431 | H5: =IS_Proj!H10/1000000000 -> 2589.44 | I5: =IS_Proj!I10/1000000000 -> 2829.5602 | J5: =IS_Proj!J10/1000000000 -> 3090.1339 | ... M5: =IS_Proj!M10/1000000000 -> 4026.8064
B6: Pertumbuhan pendapatan | D6: =IS_Proj!D11 -> 0.4990304 | E6: =IS_Proj!E11 -> 0.0050458698 | F6: =IS_Proj!F11 -> 0.29418933 | G6: =IS_Proj!G11 -> -0.065014657 | H6: =IS_Proj!H11 -> 0.10639451 | I6: =IS_Proj!I11 -> 0.092730535 | J6: =IS_Proj!J11 -> 0.092089837 | K6: =IS_Proj!K11 -> 0.092177405 | ... M6: =IS_Proj!M11 -> 0.092351482
B7: EBITDA | C7: =IS_Proj!C17/1000000000 -> 176.84041 | D7: =IS_Proj!D17/1000000000 -> 431.70323 | E7: =IS_Proj!E17/1000000000 -> 268.70754 | F7: =IS_Proj!F17/1000000000 -> 402.552 | G7: =IS_Proj!G17/1000000000 -> 484.442 | H7: =IS_Proj!H17/1000000000 -> 466.738 | I7: =IS_Proj!I17/1000000000 -> 591.37807 | J7: =IS_Proj!J17/1000000000 -> 645.83798 | ... M7: =IS_Proj!M17/1000000000 -> 841.60255
B8: Margin EBITDA | C8: =IS_Proj!C30 -> 0.13774778 | D8: =IS_Proj!D30 -> 0.22432515 | E8: =IS_Proj!E30 -> 0.13892699 | F8: =IS_Proj!F30 -> 0.16081663 | G8: =IS_Proj!G30 -> 0.20698837 | H8: =IS_Proj!H30 -> 0.18024669 | I8: =IS_Proj!I30 -> 0.209 | J8: =IS_Proj!J30 -> 0.209 | ... M8: =IS_Proj!M30 -> 0.209
B9: Laba tahun berjalan | C9: =IS_Proj!C24/1000000000 -> -14.498058 | D9: =IS_Proj!D24/1000000000 -> 165.60405 | E9: =IS_Proj!E24/1000000000 -> -44.187231 | F9: =IS_Proj!F24/1000000000 -> -38.313 | G9: =IS_Proj!G24/1000000000 -> -23.344 | H9: =IS_Proj!H24/1000000000 -> -198.79 | I9: =IS_Proj!I24/1000000000 -> -133.78239 | J9: =IS_Proj!J24/1000000000 -> -110.28182 | ... M9: =IS_Proj!M24/1000000000 -> -32.064487
B10: Laba pemilik entitas induk | C10: =IS_Proj!C26/1000000000 -> -14.380627 | D10: =IS_Proj!D26/1000000000 -> 165.30824 | E10: =IS_Proj!E26/1000000000 -> -44.314949 | F10: =IS_Proj!F26/1000000000 -> -38.49 | G10: =IS_Proj!G26/1000000000 -> -23.513 | H10: =IS_Proj!H26/1000000000 -> -199 | I10: =IS_Proj!I26/1000000000 -> -133.78239 | J10: =IS_Proj!J26/1000000000 -> -110.28182 | ... M10: =IS_Proj!M26/1000000000 -> -32.064487
B11: Arus kas operasi | C11: =CF_Proj!C11/1000000000 -> 93.881891 | D11: =CF_Proj!D11/1000000000 -> 336.78666 | E11: =CF_Proj!E11/1000000000 -> 210.47482 | F11: =CF_Proj!F11/1000000000 -> 55.917 | G11: =CF_Proj!G11/1000000000 -> 273.248 | H11: =CF_Proj!H11/1000000000 -> 129.67 | I11: =CF_Proj!I11/1000000000 -> 205.27465 | J11: =CF_Proj!J11/1000000000 -> 231.9646 | ... M11: =CF_Proj!M11/1000000000 -> 328.82262
B12: Capex | C12: =CF_Proj!C13/1000000000 -> -544.12234 | D12: =CF_Proj!D13/1000000000 -> -464.02328 | E12: =CF_Proj!E13/1000000000 -> -655.54652 | F12: =CF_Proj!F13/1000000000 -> -583.532 | G12: =CF_Proj!G13/1000000000 -> -525.029 | H12: =CF_Proj!H13/1000000000 -> -584.29 | I12: =CF_Proj!I13/1000000000 -> -424.43402 | J12: =CF_Proj!J13/1000000000 -> -463.52008 | ... M12: =CF_Proj!M13/1000000000 -> -604.02097
B13: FCF setelah sewa | C13: =CF_Proj!C28/1000000000 -> -786.93779 | D13: =CF_Proj!D28/1000000000 -> -130.40213 | E13: =CF_Proj!E28/1000000000 -> -449.41567 | F13: =CF_Proj!F28/1000000000 -> -533.388 | G13: =CF_Proj!G28/1000000000 -> -260.057 | H13: =CF_Proj!H28/1000000000 -> -484.436 | I13: =CF_Proj!I28/1000000000 -> -255.58119 | J13: =CF_Proj!J28/1000000000 -> -268.08153 | ... M13: =CF_Proj!M28/1000000000 -> -312.09906
B14: Kas akhir | C14: =BS_Proj!C6/1000000000 -> 629.60869 | D14: =BS_Proj!D6/1000000000 -> 700.92236 | E14: =BS_Proj!E6/1000000000 -> 1118.2543 | F14: =BS_Proj!F6/1000000000 -> 515.185 | G14: =BS_Proj!G6/1000000000 -> 277.208 | H14: =BS_Proj!H6/1000000000 -> 1826.263 | I14: =BS_Proj!I6/1000000000 -> 1570.6818 | J14: =BS_Proj!J6/1000000000 -> 1302.6003 | ... M14: =BS_Proj!M6/1000000000 -> 410.86524
B15: Utang neto (utang + sewa - kas) | C15: =BS_Proj!C31/1000000000 -> 442.64253 | D15: =BS_Proj!D31/1000000000 -> 145.27236 | E15: =BS_Proj!E31/1000000000 -> 607.05664 | F15: =BS_Proj!F31/1000000000 -> 1135.049 | G15: =BS_Proj!G31/1000000000 -> 1391.934 | H15: =BS_Proj!H31/1000000000 -> 2865.829 | I15: =BS_Proj!I31/1000000000 -> 3121.4102 | J15: =BS_Proj!J31/1000000000 -> 3389.4917 | ... M15: =BS_Proj!M31/1000000000 -> 4281.2268
B16: Utang neto / EBITDA | C16: =BS_Proj!C33 -> 2.5030622 | D16: =BS_Proj!D33 -> 0.33650978 | E16: =BS_Proj!E33 -> 2.2591723 | F16: =BS_Proj!F33 -> 2.8196332 | G16: =BS_Proj!G33 -> 2.8732728 | H16: =BS_Proj!H33 -> 6.1401236 | I16: =BS_Proj!I33 -> 5.2781974 | J16: =BS_Proj!J33 -> 5.2482075 | ... M16: =BS_Proj!M33 -> 5.0869936
B17: ROE | D17: =BS_Proj!D32 -> 0.089835082 | E17: =BS_Proj!E32 -> -0.023200175 | F17: =BS_Proj!F32 -> -0.020528177 | G17: =BS_Proj!G32 -> -0.012756941 | H17: =BS_Proj!H32 -> -0.12583619 | I17: =BS_Proj!I32 -> -0.10569844 | J17: =BS_Proj!J32 -> -0.096428286 | K17: =BS_Proj!K32 -> -0.081926611 | ... M17: =BS_Proj!M32 -> -0.034585997
B18: Cek balance BS_Proj (harus 0) | C18: =BS_Proj!C30 -> 0 | D18: =BS_Proj!D30 -> 0 | E18: =BS_Proj!E30 -> 0 | F18: =BS_Proj!F30 -> 0 | G18: =BS_Proj!G30 -> 0 | H18: =BS_Proj!H30 -> 0 | I18: =BS_Proj!I30 -> 0 | J18: =BS_Proj!J30 -> 0 | ... M18: =BS_Proj!M30 -> 0
B19: Status rekonsiliasi | C19: =Rekonsiliasi!$C$3 -> SEMUA 330 CEK SESUAI EKSPEKTASI

Sheet Asumsi
A1: Asumsi proyeksi ilustratif FY2026E-FY2030E (Base / Bull / Bear)
A2: Proyeksi ILUSTRATIF berbasis asumsi transparan - bukan rekomendasi investasi, bukan target, bukan nilai wajar.
A4: Skenario aktif | C4: Base | D4: =IF(C4="Bull",2,IF(C4="Bear",3,1)) -> 1 | E4: <- pilih Base / Bull / Bear. Kolom historis = aktual (rumus dari IS/BS/CF/Schedules); kolom E = asumsi skenario aktif.
A5: Kalibrasi | C5: Margin & modal kerja dikalibrasi dari FY2024-FY2025 (basis agen/neto setelah penyajian kembali PSAK 115). FY2020-2023 basis bruto (jasa dokter di pendapatan & beban pokok) tidak dipakai sebagai patokan margin.
A7: Kunci | B7: Driver | C7: FY2020A | D7: FY2021A | E7: FY2022A | F7: FY2023A | G7: FY2024A | H7: FY2025A | I7: FY2026E | J7: FY2027E | K7: FY2028E | L7: FY2029E | M7: FY2030E | N7: Dasar asumsi (kalibrasi FY2022-FY2025)
B8: ASUMSI AKTIF - kolom historis = aktual (rumus), kolom E = skenario terpilih
B9: PENDAPATAN (per kelompok, Cat 26)
A10: g_med | B10: Pertumbuhan pendapatan obat & perlengkapan medis | D10: =IFERROR(Schedules!D6/Schedules!C6-1,"") -> 0.64521714 | E10: =IFERROR(Schedules!E6/Schedules!D6-1,"") -> 0.033486197 | F10: =IFERROR(Schedules!F6/Schedules!E6-1,"") -> 0.74764788 | G10: =IFERROR(Schedules!G6/Schedules!F6-1,"") -> 0.54260096 | H10: =IFERROR(Schedules!H6/Schedules!G6-1,"") -> 0.10970411 | I10: =CHOOSE(Asumsi!$D$4,I38,I65,I92) -> 0.1 | J10: =CHOOSE(Asumsi!$D$4,J38,J65,J92) -> 0.1 | K10: =CHOOSE(Asumsi!$D$4,K38,K65,K92) -> 0.1 | L10: =CHOOSE(Asumsi!$D$4,L38,L65,L92) -> 0.1 | M10: =CHOOSE(Asumsi!$D$4,M38,M65,M92) -> 0.1 | N10: Pendapatan: 2022 432 M, 2023 755 M, 2024 1.164 M, 2025 1.292 M. CAGR 2023-25 30,8%. Base 10%; Bull 14%; Bear 5%.
A11: g_inpat | B11: Pertumbuhan pendapatan rawat inap (bruto sebelum pengurang agen) | D11: =IFERROR(Schedules!D7/Schedules!C7-1,"") -> 0.61122023 | E11: =IFERROR(Schedules!E7/Schedules!D7-1,"") -> 0.084318065 | F11: =IFERROR(Schedules!F7/Schedules!E7-1,"") -> 0.30407456 | G11: =IFERROR(Schedules!G7/Schedules!F7-1,"") -> 0.25075627 | H11: =IFERROR(Schedules!H7/Schedules!G7-1,"") -> 0.050800054 | I11: =CHOOSE(Asumsi!$D$4,I39,I66,I93) -> 0.08 | J11: =CHOOSE(Asumsi!$D$4,J39,J66,J93) -> 0.08 | K11: =CHOOSE(Asumsi!$D$4,K39,K66,K93) -> 0.08 | L11: =CHOOSE(Asumsi!$D$4,L39,L66,L93) -> 0.08 | M11: =CHOOSE(Asumsi!$D$4,M39,M66,M93) -> 0.08 | N11: Pendapatan: 2022 817 M, 2023 1.065 M, 2024 1.333 M, 2025 1.400 M. CAGR 2023-25 14,6%. Base 8%; Bull 12%; Bear 4%.
A12: g_outpat | B12: Pertumbuhan pendapatan rawat jalan & penunjang (bruto) | D12: =IFERROR(Schedules!D8/Schedules!C8-1,"") -> 0.32221062 | E12: =IFERROR(Schedules!E8/Schedules!D8-1,"") -> -0.10684834 | F12: =IFERROR(Schedules!F8/Schedules!E8-1,"") -> -0.030236747 | G12: =IFERROR(Schedules!G8/Schedules!F8-1,"") -> -0.046008458 | H12: =IFERROR(Schedules!H8/Schedules!G8-1,"") -> 0.24218613 | I12: =CHOOSE(Asumsi!$D$4,I40,I67,I94) -> 0.1 | J12: =CHOOSE(Asumsi!$D$4,J40,J67,J94) -> 0.1 | K12: =CHOOSE(Asumsi!$D$4,K40,K67,K94) -> 0.1 | L12: =CHOOSE(Asumsi!$D$4,L40,L67,L94) -> 0.1 | M12: =CHOOSE(Asumsi!$D$4,M40,M67,M94) -> 0.1 | N12: Pendapatan: 2022 704 M, 2023 683 M, 2024 652 M, 2025 810 M. CAGR 2023-25 8,9% (kategori berubah 2023, Temuan S3). Base 10%; Bull 14%; Bear 5%.
A13: rev_oth | B13: Lainnya: diskon & pengurang jasa tenaga ahli/agen (% 3 kelompok bruto) | C13: =IFERROR(Schedules!C9/(Schedules!C6+Schedules!C7+Schedules!C8),"") -> -0.026025415 | D13: =IFERROR(Schedules!D9/(Schedules!D6+Schedules!D7+Schedules!D8),"") -> -0.018128818 | E13: =IFERROR(Schedules!E9/(Schedules!E6+Schedules!E7+Schedules!E8),"") -> -0.0097623541 | F13: =IFERROR(Schedules!F9/(Schedules!F6+Schedules!F7+Schedules!F8),"") -> 0 | G13: =IFERROR(Schedules!G9/(Schedules!G6+Schedules!G7+Schedules!G8),"") -> -0.25661546 | H13: =IFERROR(Schedules!H9/(Schedules!H6+Schedules!H7+Schedules!H8),"") -> -0.26049341 | I13: =CHOOSE(Asumsi!$D$4,I41,I68,I95) -> -0.26 | J13: =CHOOSE(Asumsi!$D$4,J41,J68,J95) -> -0.26 | K13: =CHOOSE(Asumsi!$D$4,K41,K68,K95) -> -0.26 | L13: =CHOOSE(Asumsi!$D$4,L41,L68,L95) -> -0.26 | M13: =CHOOSE(Asumsi!$D$4,M41,M68,M95) -> -0.26 | N13: Historis: 2022 -1,0%, 2023 0,0%, 2024 -25,7%, 2025 -26,0% (2020-23 hanya diskon; 2024-25 pengurang agen PSAK 115, Temuan S2-S3). Semua skenario = rasio 2025.
B14: MARGIN & BIAYA (% pendapatan)
A15: cogs | B15: Beban pokok di luar penyusutan | C15: =IFERROR(-(IS!C7+Schedules!C12+Schedules!C17)/IS!C6,"") -> 0.60810027 | D15: =IFERROR(-(IS!D7+Schedules!D12+Schedules!D17)/IS!D6,"") -> 0.5759391 | E15: =IFERROR(-(IS!E7+Schedules!E12+Schedules!E17)/IS!E6,"") -> 0.6349414 | F15: =IFERROR(-(IS!F7+Schedules!F12+Schedules!F17)/IS!F6,"") -> 0.63567694 | G15: =IFERROR(-(IS!G7+Schedules!G12+Schedules!G17)/IS!G6,"") -> 0.51201937 | H15: =IFERROR(-(IS!H7+Schedules!H12+Schedules!H17)/IS!H6,"") -> 0.49002062 | I15: =CHOOSE(Asumsi!$D$4,I43,I70,I97) -> 0.49 | J15: =CHOOSE(Asumsi!$D$4,J43,J70,J97) -> 0.49 | K15: =CHOOSE(Asumsi!$D$4,K43,K70,K97) -> 0.49 | L15: =CHOOSE(Asumsi!$D$4,L43,L70,L97) -> 0.49 | M15: =CHOOSE(Asumsi!$D$4,M43,M70,M97) -> 0.49 | N15: Historis: 2022 63,5%, 2023 63,6%, 2024 51,2%, 2025 49,0% (2022-23 basis bruto, tidak sebanding). Base = 2025 (49,0%); Bull -1,5 poin; Bear +1,5 poin.
A16: opex | B16: Beban usaha di luar penyusutan, penyusutan aset hak guna & amortisasi | C16: =IFERROR(-(IS!C11+Schedules!C13+Schedules!C16+Schedules!C18)/IS!C6,"") -> 0.27629681 | D16: =IFERROR(-(IS!D11+Schedules!D13+Schedules!D16+Schedules!D18)/IS!D6,"") -> 0.21222146 | E16: =IFERROR(-(IS!E11+Schedules!E13+Schedules!E16+Schedules!E18)/IS!E6,"") -> 0.22828234 | F16: =IFERROR(-(IS!F11+Schedules!F13+Schedules!F16+Schedules!F18)/IS!F6,"") -> 0.20630847 | G16: =IFERROR(-(IS!G11+Schedules!G13+Schedules!G16+Schedules!G18)/IS!G6,"") -> 0.27040575 | H16: =IFERROR(-(IS!H11+Schedules!H13+Schedules!H16+Schedules!H18)/IS!H6,"") -> 0.33084605 | I16: =CHOOSE(Asumsi!$D$4,I44,I71,I98) -> 0.301 | J16: =CHOOSE(Asumsi!$D$4,J44,J71,J98) -> 0.301 | K16: =CHOOSE(Asumsi!$D$4,K44,K71,K98) -> 0.301 | L16: =CHOOSE(Asumsi!$D$4,L44,L71,L98) -> 0.301 | M16: =CHOOSE(Asumsi!$D$4,M44,M71,M98) -> 0.301 | N16: Historis: 2022 22,8%, 2023 20,6%, 2024 27,0%, 2025 33,1% (2025 naik: rumah sakit baru). Base = rata-rata 2024-25 (30,1%); Bull -2 poin; Bear = 2025.
A17: other_op | B17: Pendapatan (beban) lain-lain neto (% pendapatan) | C17: =IFERROR(IS!C13/IS!C6,"") -> 0.022144854 | D17: =IFERROR(IS!D13/IS!D6,"") -> 0.012485705 | E17: =IFERROR(IS!E13/IS!E6,"") -> 0.0021507288 | F17: =IFERROR(IS!F13/IS!F6,"") -> 0.0028020425 | G17: =IFERROR(IS!G13/IS!G6,"") -> -0.010586512 | H17: =IFERROR(IS!H13/IS!H6,"") -> 0.0011133681 | I17: =CHOOSE(Asumsi!$D$4,I45,I72,I99) -> 0 | J17: =CHOOSE(Asumsi!$D$4,J45,J72,J99) -> 0 | K17: =CHOOSE(Asumsi!$D$4,K45,K72,K99) -> 0 | L17: =CHOOSE(Asumsi!$D$4,L45,L72,L99) -> 0 | M17: =CHOOSE(Asumsi!$D$4,M45,M72,M99) -> 0 | N17: Historis: 2022 0,2%, 2023 0,3%, 2024 -1,1%, 2025 0,1% (memuat penurunan nilai piutang & selisih kurs). Base 0%; Bull 0,2%; Bear -0,5%.
B18: INVESTASI & ASET
A19: capex | B19: Capex aset tetap (% pendapatan) | C19: =IFERROR(-(CF!C15+CF!C16)/IS!C6,"") -> 0.42383777 | D19: =IFERROR(-(CF!D15+CF!D16)/IS!D6,"") -> 0.24111955 | E19: =IFERROR(-(CF!E15+CF!E16)/IS!E6,"") -> 0.33893022 | F19: =IFERROR(-(CF!F15+CF!F16)/IS!F6,"") -> 0.23311683 | G19: =IFERROR(-(CF!G15+CF!G16)/IS!G6,"") -> 0.22433005 | H19: =IFERROR(-(CF!H15+CF!H16)/IS!H6,"") -> 0.22383411 | I19: =CHOOSE(Asumsi!$D$4,I47,I74,I101) -> 0.15 | J19: =CHOOSE(Asumsi!$D$4,J47,J74,J101) -> 0.15 | K19: =CHOOSE(Asumsi!$D$4,K47,K74,K101) -> 0.15 | L19: =CHOOSE(Asumsi!$D$4,L47,L74,L101) -> 0.15 | M19: =CHOOSE(Asumsi!$D$4,M47,M74,M101) -> 0.15 | N19: Historis kas: 2022 33,9%, 2023 23,3%, 2024 22,4%, 2025 22,4% (pembangunan rumah sakit baru). Base 15%; Bull 12%; Bear 20%.
A20: lease_pd | B20: Pembayaran sewa dikapitalisasi ke aset tetap (% pendapatan) | C20: =IFERROR(-CF!C35/IS!C6,"") -> 0.25704966 | D20: =IFERROR(-CF!D35/IS!D6,"") -> 0 | E20: =IFERROR(-CF!E35/IS!E6,"") -> 0 | F20: =IFERROR(-CF!F35/IS!F6,"") -> 0.00028244141 | G20: =IFERROR(-CF!G35/IS!G6,"") -> 0.00030250838 | H20: =IFERROR(-CF!H35/IS!H6,"") -> 0.00061750803 | I20: =CHOOSE(Asumsi!$D$4,I48,I75,I102) -> 0.0004 | J20: =CHOOSE(Asumsi!$D$4,J48,J75,J102) -> 0.0004 | K20: =CHOOSE(Asumsi!$D$4,K48,K75,K102) -> 0.0004 | L20: =CHOOSE(Asumsi!$D$4,L48,L75,L102) -> 0.0004 | M20: =CHOOSE(Asumsi!$D$4,M48,M75,M102) -> 0.0004 | N20: Historis: 2022 0,0%, 2023 0,0%, 2024 0,0%, 2025 0,1%. Base/Bull/Bear = rata-rata 2023-25; liabilitas sewa & aset hak guna konstan.
A21: dep | B21: Penyusutan aset tetap + aset hak guna (% aset tetap neto awal) | D21: =IFERROR((Schedules!D14+Schedules!D16)/BS!C19,"") -> 0.06688873 | E21: =IFERROR((Schedules!E14+Schedules!E16)/BS!D19,"") -> 0.071688859 | F21: =IFERROR((Schedules!F14+Schedules!F16)/BS!E19,"") -> 0.078537243 | G21: =IFERROR((Schedules!G14+Schedules!G16)/BS!F19,"") -> 0.080706432 | H21: =IFERROR((Schedules!H14+Schedules!H16)/BS!G19,"") -> 0.087860639 | I21: =CHOOSE(Asumsi!$D$4,I49,I76,I103) -> 0.0824 | J21: =CHOOSE(Asumsi!$D$4,J49,J76,J103) -> 0.0824 | K21: =CHOOSE(Asumsi!$D$4,K49,K76,K103) -> 0.0824 | L21: =CHOOSE(Asumsi!$D$4,L49,L76,L103) -> 0.0824 | M21: =CHOOSE(Asumsi!$D$4,M49,M76,M103) -> 0.0824 | N21: Historis: 2022 7,2%, 2023 7,9%, 2024 8,1%, 2025 8,8%. Base/Bull/Bear = rata-rata 2023-25.
A22: sw | B22: Amortisasi aset takberwujud (% saldo awal) | D22: =IFERROR(Schedules!D19/BS!C22,"") -> 0.44820278 | E22: =IFERROR(Schedules!E19/BS!D22,"") -> 0.34947122 | F22: =IFERROR(Schedules!F19/BS!E22,"") -> 0.46646772 | G22: =IFERROR(Schedules!G19/BS!F22,"") -> 0.65616241 | H22: =IFERROR(Schedules!H19/BS!G22,"") -> 1.3246384 | I22: =CHOOSE(Asumsi!$D$4,I50,I77,I104) -> 1.3246 | J22: =CHOOSE(Asumsi!$D$4,J50,J77,J104) -> 1.3246 | K22: =CHOOSE(Asumsi!$D$4,K50,K77,K104) -> 1.3246 | L22: =CHOOSE(Asumsi!$D$4,L50,L77,L104) -> 1.3246 | M22: =CHOOSE(Asumsi!$D$4,M50,M77,M104) -> 1.3246 | N22: Historis: 2022 34,9%, 2023 46,6%, 2024 65,6%, 2025 132,5%. Penambahan E = amortisasi (saldo konstan). Base/Bull/Bear = 2025.
B23: MODAL KERJA (hari, saldo akhir, basis 365)
A24: dso | B24: DSO piutang usaha / pendapatan | C24: =IFERROR((BS!C8+BS!C9)/IS!C6*365,"") -> 64.090527 | D24: =IFERROR((BS!D8+BS!D9)/IS!D6*365,"") -> 44.362731 | E24: =IFERROR((BS!E8+BS!E9)/IS!E6*365,"") -> 45.853511 | F24: =IFERROR((BS!F8+BS!F9)/IS!F6*365,"") -> 57.643682 | G24: =IFERROR((BS!G8+BS!G9)/IS!G6*365,"") -> 66.171047 | H24: =IFERROR((BS!H8+BS!H9)/IS!H6*365,"") -> 78.644628 | I24: =CHOOSE(Asumsi!$D$4,I52,I79,I106) -> 79 | J24: =CHOOSE(Asumsi!$D$4,J52,J79,J106) -> 79 | K24: =CHOOSE(Asumsi!$D$4,K52,K79,K106) -> 79 | L24: =CHOOSE(Asumsi!$D$4,L52,L79,L106) -> 79 | M24: =CHOOSE(Asumsi!$D$4,M52,M79,M106) -> 79 | N24: Historis: 2022 45,9, 2023 57,6, 2024 66,2, 2025 78,6 (piutang asuransi/korporasi/BPJS; 2024-25 atas pendapatan neto agen). Base = 2025; Bull -5; Bear +10.
A25: dio | B25: DIO persediaan / beban pokok di luar penyusutan | C25: =IFERROR(BS!C12/-(IS!C7+Schedules!C12+Schedules!C17)*365,"") -> 34.921294 | D25: =IFERROR(BS!D12/-(IS!D7+Schedules!D12+Schedules!D17)*365,"") -> 23.186631 | E25: =IFERROR(BS!E12/-(IS!E7+Schedules!E12+Schedules!E17)*365,"") -> 14.748203 | F25: =IFERROR(BS!F12/-(IS!F7+Schedules!F12+Schedules!F17)*365,"") -> 11.226111 | G25: =IFERROR(BS!G12/-(IS!G7+Schedules!G12+Schedules!G17)*365,"") -> 18.676025 | H25: =IFERROR(BS!H12/-(IS!H7+Schedules!H12+Schedules!H17)*365,"") -> 21.091763 | I25: =CHOOSE(Asumsi!$D$4,I53,I80,I107) -> 21 | J25: =CHOOSE(Asumsi!$D$4,J53,J80,J107) -> 21 | K25: =CHOOSE(Asumsi!$D$4,K53,K80,K107) -> 21 | L25: =CHOOSE(Asumsi!$D$4,L53,L80,L107) -> 21 | M25: =CHOOSE(Asumsi!$D$4,M53,M80,M107) -> 21 | N25: Historis: 2022 14,7, 2023 11,2, 2024 18,7, 2025 21,1. Base = 2025; Bull -2; Bear +4.
A26: dpo | B26: DPO utang usaha / beban pokok di luar penyusutan | C26: =IFERROR((BS!C30+BS!C31)/-(IS!C7+Schedules!C12+Schedules!C17)*365,"") -> 81.916469 | D26: =IFERROR((BS!D30+BS!D31)/-(IS!D7+Schedules!D12+Schedules!D17)*365,"") -> 63.327242 | E26: =IFERROR((BS!E30+BS!E31)/-(IS!E7+Schedules!E12+Schedules!E17)*365,"") -> 48.145702 | F26: =IFERROR((BS!F30+BS!F31)/-(IS!F7+Schedules!F12+Schedules!F17)*365,"") -> 32.274954 | G26: =IFERROR((BS!G30+BS!G31)/-(IS!G7+Schedules!G12+Schedules!G17)*365,"") -> 47.574582 | H26: =IFERROR((BS!H30+BS!H31)/-(IS!H7+Schedules!H12+Schedules!H17)*365,"") -> 32.7467 | I26: =CHOOSE(Asumsi!$D$4,I54,I81,I108) -> 33 | J26: =CHOOSE(Asumsi!$D$4,J54,J81,J108) -> 33 | K26: =CHOOSE(Asumsi!$D$4,K54,K81,K108) -> 33 | L26: =CHOOSE(Asumsi!$D$4,L54,L81,L108) -> 33 | M26: =CHOOSE(Asumsi!$D$4,M54,M81,M108) -> 33 | N26: Historis: 2022 48,1, 2023 32,3, 2024 47,6, 2025 32,7 (termasuk utang jasa dokter). Base = 2025; Bull +10; Bear -15.
B27: PAJAK, PENDANAAN, DISTRIBUSI
A28: tax | B28: Tarif pajak efektif (% laba sebelum pajak) | C28: =IFERROR(-IS!C18/IS!C17,"") -> 76.751242 | D28: =IFERROR(-IS!D18/IS!D17,"") -> -0.058717335 | E28: =IFERROR(-IS!E18/IS!E17,"") -> -0.049904963 | F28: =IFERROR(-IS!F18/IS!F17,"") -> -0.22440957 | G28: =IFERROR(-IS!G18/IS!G17,"") -> -7.8424242 | H28: =IFERROR(-IS!H18/IS!H17,"") -> 0.1546966 | I28: =CHOOSE(Asumsi!$D$4,I56,I83,I110) -> 0.25 | J28: =CHOOSE(Asumsi!$D$4,J56,J83,J110) -> 0.25 | K28: =CHOOSE(Asumsi!$D$4,K56,K83,K110) -> 0.25 | L28: =CHOOSE(Asumsi!$D$4,L56,L83,L110) -> 0.25 | M28: =CHOOSE(Asumsi!$D$4,M56,M83,M110) -> 0.25 | N28: Historis: 2022 -5,0%, 2023 -22,4%, 2024 -784,2%, 2025 15,5% (rugi sebelum pajak 2022-25 membuat tarif efektif tidak bermakna, Temuan S9). Base 25%; Bull 22%; Bear 30% (tarif normatif 22% + beban tidak dapat dikurangkan; manfaat pajak saat rugi).
A29: fin_cost | B29: Suku bunga efektif (beban keuangan / rata-rata utang berbunga) | D29: =IFERROR(-IS!D15/AVERAGE((BS!D29+BS!D38+BS!D45+BS!D39+BS!D46+BS!D40+BS!D47+BS!D41+BS!D48),(BS!C29+BS!C38+BS!C45+BS!C39+BS!C46+BS!C40+BS!C47+BS!C41+BS!C48)),"") -> 0.12305174 | E29: =IFERROR(-IS!E15/AVERAGE((BS!E29+BS!E38+BS!E45+BS!E39+BS!E46+BS!E40+BS!E47+BS!E41+BS!E48),(BS!D29+BS!D38+BS!D45+BS!D39+BS!D46+BS!D40+BS!D47+BS!D41+BS!D48)),"") -> 0.07518173 | F29: =IFERROR(-IS!F15/AVERAGE((BS!F29+BS!F38+BS!F45+BS!F39+BS!F46+BS!F40+BS!F47+BS!F41+BS!F48),(BS!E29+BS!E38+BS!E45+BS!E39+BS!E46+BS!E40+BS!E47+BS!E41+BS!E48)),"") -> 0.10302659 | G29: =IFERROR(-IS!G15/AVERAGE((BS!G29+BS!G38+BS!G45+BS!G39+BS!G46+BS!G40+BS!G47+BS!G41+BS!G48),(BS!F29+BS!F38+BS!F45+BS!F39+BS!F46+BS!F40+BS!F47+BS!F41+BS!F48)),"") -> 0.10498311 | H29: =IFERROR(-IS!H15/AVERAGE((BS!H29+BS!H38+BS!H45+BS!H39+BS!H46+BS!H40+BS!H47+BS!H41+BS!H48),(BS!G29+BS!G38+BS!G45+BS!G39+BS!G46+BS!G40+BS!G47+BS!G41+BS!G48)),"") -> 0.12205885 | I29: =CHOOSE(Asumsi!$D$4,I57,I84,I111) -> 0.11 | J29: =CHOOSE(Asumsi!$D$4,J57,J84,J111) -> 0.11 | K29: =CHOOSE(Asumsi!$D$4,K57,K84,K111) -> 0.11 | L29: =CHOOSE(Asumsi!$D$4,L57,L84,L111) -> 0.11 | M29: =CHOOSE(Asumsi!$D$4,M57,M84,M111) -> 0.11 | N29: Historis: 2023 10,30%, 2024 10,50%, 2025 12,21% (beban keuangan termasuk bunga sewa & amortisasi surat utang). Base = rata-rata 2023-25; Bull x0,9; Bear x1,1 (Temuan S6).
A30: yld | B30: Imbal hasil kas (penghasilan keuangan / kas awal) | D30: =IFERROR(IS!D16/BS!C6,"") -> 0.038025105 | E30: =IFERROR(IS!E16/BS!D6,"") -> 0.027684355 | F30: =IFERROR(IS!F16/BS!E6,"") -> 0.026039695 | G30: =IFERROR(IS!G16/BS!F6,"") -> 0.026171181 | H30: =IFERROR(IS!H16/BS!G6,"") -> 0.2413242 | I30: =CHOOSE(Asumsi!$D$4,I58,I85,I112) -> 0.0978 | J30: =CHOOSE(Asumsi!$D$4,J58,J85,J112) -> 0.0978 | K30: =CHOOSE(Asumsi!$D$4,K58,K85,K112) -> 0.0978 | L30: =CHOOSE(Asumsi!$D$4,L58,L85,L112) -> 0.0978 | M30: =CHOOSE(Asumsi!$D$4,M58,M85,M112) -> 0.0978 | N30: Historis: 2022 2,77%, 2023 2,60%, 2024 2,62%, 2025 24,13%. Base = rata-rata 2023-25; Bear x0,8; tanpa circular reference.
A31: debt_chg | B31: Perubahan neto utang (Rp; + = tambah) | D31: =(BS!D29+BS!D38+BS!D45+BS!D39+BS!D46+BS!D40+BS!D47+BS!D41+BS!D48)-(BS!C29+BS!C38+BS!C45+BS!C39+BS!C46+BS!C40+BS!C47+BS!C41+BS!C48) -> -226056502380 | E31: =(BS!E29+BS!E38+BS!E45+BS!E39+BS!E46+BS!E40+BS!E47+BS!E41+BS!E48)-(BS!D29+BS!D38+BS!D45+BS!D39+BS!D46+BS!D40+BS!D47+BS!D41+BS!D48) -> 879116171608 | F31: =(BS!F29+BS!F38+BS!F45+BS!F39+BS!F46+BS!F40+BS!F47+BS!F41+BS!F48)-(BS!E29+BS!E38+BS!E45+BS!E39+BS!E46+BS!E40+BS!E47+BS!E41+BS!E48) -> -78967890922 | G31: =(BS!G29+BS!G38+BS!G45+BS!G39+BS!G46+BS!G40+BS!G47+BS!G41+BS!G48)-(BS!F29+BS!F38+BS!F45+BS!F39+BS!F46+BS!F40+BS!F47+BS!F41+BS!F48) -> 19523000000 | H31: =(BS!H29+BS!H38+BS!H45+BS!H39+BS!H46+BS!H40+BS!H47+BS!H41+BS!H48)-(BS!G29+BS!G38+BS!G45+BS!G39+BS!G46+BS!G40+BS!G47+BS!G41+BS!G48) -> 3018549000000 | I31: =CHOOSE(Asumsi!$D$4,I59,I86,I113) -> 0 | J31: =CHOOSE(Asumsi!$D$4,J59,J86,J113) -> 0 | K31: =CHOOSE(Asumsi!$D$4,K59,K86,K113) -> 0 | L31: =CHOOSE(Asumsi!$D$4,L59,L86,L113) -> 0 | M31: =CHOOSE(Asumsi!$D$4,M59,M86,M113) -> 0 | N31: Historis utang berbunga: 2022 1.725 M, 2023 1.646 M, 2024 1.666 M, 2025 4.684 M. Semua skenario 0 (kas = penyeimbang; pendanaan ekspansi tidak dimodelkan).
A32: payout | B32: Payout dividen (% laba induk tahun lalu) | D32: =IFERROR(-CF!D36/IS!C26,"") -> 0 | E32: =IFERROR(-CF!E36/IS!D26,"") -> 0 | F32: =IFERROR(-CF!F36/IS!E26,"") -> 0 | G32: =IFERROR(-CF!G36/IS!F26,"") -> 0 | H32: =IFERROR(-CF!H36/IS!G26,"") -> 0 | I32: =CHOOSE(Asumsi!$D$4,I60,I87,I114) -> 0 | J32: =CHOOSE(Asumsi!$D$4,J60,J87,J114) -> 0 | K32: =CHOOSE(Asumsi!$D$4,K60,K87,K114) -> 0 | L32: =CHOOSE(Asumsi!$D$4,L60,L87,L114) -> 0 | M32: =CHOOSE(Asumsi!$D$4,M60,M87,M114) -> 0 | N32: Tidak ada dividen ke pemilik induk 2020-2025 (Temuan S9). Semua skenario 0%.
A33: nci_share | B33: Porsi laba ke NCI (% laba tahun berjalan) | C33: =IFERROR(IS!C27/IS!C19,"") -> 0.0080997698 | D33: =IFERROR(IS!D27/IS!D19,"") -> 0.0017862363 | E33: =IFERROR(IS!E27/IS!E19,"") -> -0.0028903894 | F33: =IFERROR(IS!F27/IS!F19,"") -> -0.0046198418 | G33: =IFERROR(IS!G27/IS!G19,"") -> -0.0072395476 | H33: =IFERROR(IS!H27/IS!H19,"") -> -0.0010563912 | I33: =CHOOSE(Asumsi!$D$4,I61,I88,I115) -> 0 | J33: =CHOOSE(Asumsi!$D$4,J61,J88,J115) -> 0 | K33: =CHOOSE(Asumsi!$D$4,K61,K88,K115) -> 0 | L33: =CHOOSE(Asumsi!$D$4,L61,L88,L115) -> 0 | M33: =CHOOSE(Asumsi!$D$4,M61,M88,M115) -> 0 | N33: Historis: 2022 -0,3%, 2023 -0,5%, 2024 -0,7%, 2025 -0,1% (sangat kecil; tanda terbalik karena grup rugi). Semua skenario 0%.
B36: SKENARIO BASE - input biru per tahun (boleh diubah pengguna)
B37: PENDAPATAN (per kelompok, Cat 26)
A38: Base.g_med | B38: Pertumbuhan pendapatan obat & perlengkapan medis | I38: 0.1 | J38: 0.1 | K38: 0.1 | L38: 0.1 | M38: 0.1
A39: Base.g_inpat | B39: Pertumbuhan pendapatan rawat inap (bruto sebelum pengurang agen) | I39: 0.08 | J39: 0.08 | K39: 0.08 | L39: 0.08 | M39: 0.08
A40: Base.g_outpat | B40: Pertumbuhan pendapatan rawat jalan & penunjang (bruto) | I40: 0.1 | J40: 0.1 | K40: 0.1 | L40: 0.1 | M40: 0.1
A41: Base.rev_oth | B41: Lainnya: diskon & pengurang jasa tenaga ahli/agen (% 3 kelompok bruto) | I41: -0.26 | J41: -0.26 | K41: -0.26 | L41: -0.26 | M41: -0.26
B42: MARGIN & BIAYA (% pendapatan)
A43: Base.cogs | B43: Beban pokok di luar penyusutan | I43: 0.49 | J43: 0.49 | K43: 0.49 | L43: 0.49 | M43: 0.49
A44: Base.opex | B44: Beban usaha di luar penyusutan, penyusutan aset hak guna & amortisasi | I44: 0.301 | J44: 0.301 | K44: 0.301 | L44: 0.301 | M44: 0.301
A45: Base.other_op | B45: Pendapatan (beban) lain-lain neto (% pendapatan) | I45: 0 | J45: 0 | K45: 0 | L45: 0 | M45: 0
B46: INVESTASI & ASET
A47: Base.capex | B47: Capex aset tetap (% pendapatan) | I47: 0.15 | J47: 0.15 | K47: 0.15 | L47: 0.15 | M47: 0.15
A48: Base.lease_pd | B48: Pembayaran sewa dikapitalisasi ke aset tetap (% pendapatan) | I48: 0.0004 | J48: 0.0004 | K48: 0.0004 | L48: 0.0004 | M48: 0.0004
A49: Base.dep | B49: Penyusutan aset tetap + aset hak guna (% aset tetap neto awal) | I49: 0.0824 | J49: 0.0824 | K49: 0.0824 | L49: 0.0824 | M49: 0.0824
A50: Base.sw | B50: Amortisasi aset takberwujud (% saldo awal) | I50: 1.3246 | J50: 1.3246 | K50: 1.3246 | L50: 1.3246 | M50: 1.3246
B51: MODAL KERJA (hari, saldo akhir, basis 365)
A52: Base.dso | B52: DSO piutang usaha / pendapatan | I52: 79 | J52: 79 | K52: 79 | L52: 79 | M52: 79
A53: Base.dio | B53: DIO persediaan / beban pokok di luar penyusutan | I53: 21 | J53: 21 | K53: 21 | L53: 21 | M53: 21
A54: Base.dpo | B54: DPO utang usaha / beban pokok di luar penyusutan | I54: 33 | J54: 33 | K54: 33 | L54: 33 | M54: 33
B55: PAJAK, PENDANAAN, DISTRIBUSI
A56: Base.tax | B56: Tarif pajak efektif (% laba sebelum pajak) | I56: 0.25 | J56: 0.25 | K56: 0.25 | L56: 0.25 | M56: 0.25
A57: Base.fin_cost | B57: Suku bunga efektif (beban keuangan / rata-rata utang berbunga) | I57: 0.11 | J57: 0.11 | K57: 0.11 | L57: 0.11 | M57: 0.11
A58: Base.yld | B58: Imbal hasil kas (penghasilan keuangan / kas awal) | I58: 0.0978 | J58: 0.0978 | K58: 0.0978 | L58: 0.0978 | M58: 0.0978
A59: Base.debt_chg | B59: Perubahan neto utang (Rp; + = tambah) | I59: 0 | J59: 0 | K59: 0 | L59: 0 | M59: 0
A60: Base.payout | B60: Payout dividen (% laba induk tahun lalu) | I60: 0 | J60: 0 | K60: 0 | L60: 0 | M60: 0
A61: Base.nci_share | B61: Porsi laba ke NCI (% laba tahun berjalan) | I61: 0 | J61: 0 | K61: 0 | L61: 0 | M61: 0
B63: SKENARIO BULL - input biru per tahun (boleh diubah pengguna)
B64: PENDAPATAN (per kelompok, Cat 26)
A65: Bull.g_med | B65: Pertumbuhan pendapatan obat & perlengkapan medis | I65: 0.14 | J65: 0.14 | K65: 0.14 | L65: 0.14 | M65: 0.14
A66: Bull.g_inpat | B66: Pertumbuhan pendapatan rawat inap (bruto sebelum pengurang agen) | I66: 0.12 | J66: 0.12 | K66: 0.12 | L66: 0.12 | M66: 0.12
A67: Bull.g_outpat | B67: Pertumbuhan pendapatan rawat jalan & penunjang (bruto) | I67: 0.14 | J67: 0.14 | K67: 0.14 | L67: 0.14 | M67: 0.14
A68: Bull.rev_oth | B68: Lainnya: diskon & pengurang jasa tenaga ahli/agen (% 3 kelompok bruto) | I68: -0.26 | J68: -0.26 | K68: -0.26 | L68: -0.26 | M68: -0.26
B69: MARGIN & BIAYA (% pendapatan)
A70: Bull.cogs | B70: Beban pokok di luar penyusutan | I70: 0.475 | J70: 0.475 | K70: 0.475 | L70: 0.475 | M70: 0.475
A71: Bull.opex | B71: Beban usaha di luar penyusutan, penyusutan aset hak guna & amortisasi | I71: 0.281 | J71: 0.281 | K71: 0.281 | L71: 0.281 | M71: 0.281
A72: Bull.other_op | B72: Pendapatan (beban) lain-lain neto (% pendapatan) | I72: 0.002 | J72: 0.002 | K72: 0.002 | L72: 0.002 | M72: 0.002
B73: INVESTASI & ASET
A74: Bull.capex | B74: Capex aset tetap (% pendapatan) | I74: 0.12 | J74: 0.12 | K74: 0.12 | L74: 0.12 | M74: 0.12
A75: Bull.lease_pd | B75: Pembayaran sewa dikapitalisasi ke aset tetap (% pendapatan) | I75: 0.0004 | J75: 0.0004 | K75: 0.0004 | L75: 0.0004 | M75: 0.0004
A76: Bull.dep | B76: Penyusutan aset tetap + aset hak guna (% aset tetap neto awal) | I76: 0.0824 | J76: 0.0824 | K76: 0.0824 | L76: 0.0824 | M76: 0.0824
A77: Bull.sw | B77: Amortisasi aset takberwujud (% saldo awal) | I77: 1.3246 | J77: 1.3246 | K77: 1.3246 | L77: 1.3246 | M77: 1.3246
B78: MODAL KERJA (hari, saldo akhir, basis 365)
A79: Bull.dso | B79: DSO piutang usaha / pendapatan | I79: 74 | J79: 74 | K79: 74 | L79: 74 | M79: 74
A80: Bull.dio | B80: DIO persediaan / beban pokok di luar penyusutan | I80: 19 | J80: 19 | K80: 19 | L80: 19 | M80: 19
A81: Bull.dpo | B81: DPO utang usaha / beban pokok di luar penyusutan | I81: 43 | J81: 43 | K81: 43 | L81: 43 | M81: 43
B82: PAJAK, PENDANAAN, DISTRIBUSI
A83: Bull.tax | B83: Tarif pajak efektif (% laba sebelum pajak) | I83: 0.22 | J83: 0.22 | K83: 0.22 | L83: 0.22 | M83: 0.22
A84: Bull.fin_cost | B84: Suku bunga efektif (beban keuangan / rata-rata utang berbunga) | I84: 0.099 | J84: 0.099 | K84: 0.099 | L84: 0.099 | M84: 0.099
A85: Bull.yld | B85: Imbal hasil kas (penghasilan keuangan / kas awal) | I85: 0.0978 | J85: 0.0978 | K85: 0.0978 | L85: 0.0978 | M85: 0.0978
A86: Bull.debt_chg | B86: Perubahan neto utang (Rp; + = tambah) | I86: 0 | J86: 0 | K86: 0 | L86: 0 | M86: 0
A87: Bull.payout | B87: Payout dividen (% laba induk tahun lalu) | I87: 0 | J87: 0 | K87: 0 | L87: 0 | M87: 0
A88: Bull.nci_share | B88: Porsi laba ke NCI (% laba tahun berjalan) | I88: 0 | J88: 0 | K88: 0 | L88: 0 | M88: 0
B90: SKENARIO BEAR - input biru per tahun (boleh diubah pengguna)
B91: PENDAPATAN (per kelompok, Cat 26)
A92: Bear.g_med | B92: Pertumbuhan pendapatan obat & perlengkapan medis | I92: 0.05 | J92: 0.05 | K92: 0.05 | L92: 0.05 | M92: 0.05
A93: Bear.g_inpat | B93: Pertumbuhan pendapatan rawat inap (bruto sebelum pengurang agen) | I93: 0.04 | J93: 0.04 | K93: 0.04 | L93: 0.04 | M93: 0.04
A94: Bear.g_outpat | B94: Pertumbuhan pendapatan rawat jalan & penunjang (bruto) | I94: 0.05 | J94: 0.05 | K94: 0.05 | L94: 0.05 | M94: 0.05
A95: Bear.rev_oth | B95: Lainnya: diskon & pengurang jasa tenaga ahli/agen (% 3 kelompok bruto) | I95: -0.26 | J95: -0.26 | K95: -0.26 | L95: -0.26 | M95: -0.26
B96: MARGIN & BIAYA (% pendapatan)
A97: Bear.cogs | B97: Beban pokok di luar penyusutan | I97: 0.505 | J97: 0.505 | K97: 0.505 | L97: 0.505 | M97: 0.505
A98: Bear.opex | B98: Beban usaha di luar penyusutan, penyusutan aset hak guna & amortisasi | I98: 0.331 | J98: 0.331 | K98: 0.331 | L98: 0.331 | M98: 0.331
A99: Bear.other_op | B99: Pendapatan (beban) lain-lain neto (% pendapatan) | I99: -0.005 | J99: -0.005 | K99: -0.005 | L99: -0.005 | M99: -0.005
B100: INVESTASI & ASET
A101: Bear.capex | B101: Capex aset tetap (% pendapatan) | I101: 0.2 | J101: 0.2 | K101: 0.2 | L101: 0.2 | M101: 0.2
A102: Bear.lease_pd | B102: Pembayaran sewa dikapitalisasi ke aset tetap (% pendapatan) | I102: 0.0004 | J102: 0.0004 | K102: 0.0004 | L102: 0.0004 | M102: 0.0004
A103: Bear.dep | B103: Penyusutan aset tetap + aset hak guna (% aset tetap neto awal) | I103: 0.0824 | J103: 0.0824 | K103: 0.0824 | L103: 0.0824 | M103: 0.0824
A104: Bear.sw | B104: Amortisasi aset takberwujud (% saldo awal) | I104: 1.3246 | J104: 1.3246 | K104: 1.3246 | L104: 1.3246 | M104: 1.3246
B105: MODAL KERJA (hari, saldo akhir, basis 365)
A106: Bear.dso | B106: DSO piutang usaha / pendapatan | I106: 89 | J106: 89 | K106: 89 | L106: 89 | M106: 89
...

Sheet IS_Proj
A1: Proyeksi laba rugi (ilustratif)
A2: Rp penuh | kolom A = aktual (link ke IS/BS/CF/Schedules), kolom E = proyeksi | Proyeksi ILUSTRATIF berbasis asumsi transparan - bukan rekomendasi investasi, bukan target, bukan nilai wajar.
A3: Skenario aktif: | C3: =Asumsi!C4 -> Base | I3: ilustratif | J3: ilustratif | K3: ilustratif | L3: ilustratif | M3: ilustratif
A4: Kode | B4: Akun | C4: FY2020A | D4: FY2021A | E4: FY2022A | F4: FY2023A | G4: FY2024A | H4: FY2025A | I4: FY2026E | J4: FY2027E | K4: FY2028E | L4: FY2029E | M4: FY2030E | N4: Catatan / sumber
B5: PENDAPATAN (per kelompok)
A6: P.REV_MED | B6: Obat & perlengkapan medis | C6: =Schedules!C6 -> 253936863405 | D6: =Schedules!D6 -> 417781280603 | E6: =Schedules!E6 -> 431771186720 | F6: =Schedules!F6 -> 754584000000 | G6: =Schedules!G6 -> 1164022000000 | H6: =Schedules!H6 -> 1291720000000 | I6: =H6*(1+Asumsi!I10) -> 1420892000000 | J6: =I6*(1+Asumsi!J10) -> 1562981200000 | K6: =J6*(1+Asumsi!K10) -> 1719279320000 | L6: =K6*(1+Asumsi!L10) -> 1891207252000 | M6: =L6*(1+Asumsi!M10) -> 2080327977200
A7: P.REV_INPAT | B7: Rawat inap (bruto) | C7: =Schedules!C7 -> 467640506965 | D7: =Schedules!D7 -> 753471843387 | E7: =Schedules!E7 -> 817003131432 | F7: =Schedules!F7 -> 1065433000000 | G7: =Schedules!G7 -> 1332597000000 | H7: =Schedules!H7 -> 1400293000000 | I7: =H7*(1+Asumsi!I11) -> 1512316440000 | J7: =I7*(1+Asumsi!J11) -> 1633301755200 | K7: =J7*(1+Asumsi!K11) -> 1763965895616 | L7: =K7*(1+Asumsi!L11) -> 1.9050832e+12 | M7: =L7*(1+Asumsi!M11) -> 2.0574898e+12
A8: P.REV_OUTPAT | B8: Rawat jalan & penunjang (bruto) | C8: =Schedules!C8 -> 596525411320 | D8: =Schedules!D8 -> 788732235692 | E8: =Schedules!E8 -> 704457503479 | F8: =Schedules!F8 -> 683157000000 | G8: =Schedules!G8 -> 651726000000 | H8: =Schedules!H8 -> 809565000000 | I8: =H8*(1+Asumsi!I12) -> 890521500000 | J8: =I8*(1+Asumsi!J12) -> 979573650000 | K8: =J8*(1+Asumsi!K12) -> 1077531015000 | L8: =K8*(1+Asumsi!L12) -> 1185284116500 | M8: =L8*(1+Asumsi!M12) -> 1303812528150
A9: P.REV_OTHER | B9: Lainnya (administrasi, operasional lain, dikurangi diskon) | C9: =Schedules!C9 -> -34304172516 | D9: =Schedules!D9 -> -35532218704 | E9: =Schedules!E9 -> -19068140667 | F9: =Schedules!F9 -> 0 | G9: =Schedules!G9 -> -807914000000 | H9: =Schedules!H9 -> -912138000000 | I9: =(I6+I7+I8)*Asumsi!I13 -> -994169784400 | J9: =(J6+J7+J8)*Asumsi!J13 -> -1085722717352 | K9: =(K6+K7+K8)*Asumsi!K13 -> -1.1858018e+12 | L9: =(L6+L7+L8)*Asumsi!L13 -> -1.2952094e+12 | M9: =(M6+M7+M8)*Asumsi!M13 -> -1.4148239e+12
A10: P.REVENUE | B10: Pendapatan | C10: =IS!C6 -> 1283798609174 | D10: =IS!D6 -> 1924453140978 | E10: =IS!E6 -> 1934163680964 | F10: =IS!F6 -> 2503174000000 | G10: =IS!G6 -> 2340431000000 | H10: =IS!H6 -> 2589440000000 | I10: =I6+I7+I8+I9 -> 2829560155600 | J10: =J6+J7+J8+J9 -> 3090133887848 | K10: =K6+K7+K8+K9 -> 3.3749744e+12 | L10: =L6+L7+L8+L9 -> 3.6863652e+12 | M10: =M6+M7+M8+M9 -> 4.0268064e+12
A11: P.REV_GROWTH | B11: Pertumbuhan pendapatan | D11: =D10/C10-1 -> 0.4990304 | E11: =E10/D10-1 -> 0.0050458698 | F11: =F10/E10-1 -> 0.29418933 | G11: =G10/F10-1 -> -0.065014657 | H11: =H10/G10-1 -> 0.10639451 | I11: =I10/H10-1 -> 0.092730535 | J11: =J10/I10-1 -> 0.092089837 | K11: =K10/J10-1 -> 0.092177405 | ... M11: =M10/L10-1 -> 0.092351482
B12: BIAYA & EBITDA
A13: P.COGS_X | B13: Beban pokok di luar penyusutan & amortisasi | C13: =IS!C7+Schedules!C12+Schedules!C17 -> -780678281447 | D13: =IS!D7+Schedules!D12+Schedules!D17 -> -1108367805956 | E13: =IS!E7+Schedules!E12+Schedules!E17 -> -1228080599500 | F13: =IS!F7+Schedules!F12+Schedules!F17 -> -1591210000000 | G13: =IS!G7+Schedules!G12+Schedules!G17 -> -1198346000000 | H13: =IS!H7+Schedules!H12+Schedules!H17 -> -1268879000000 | I13: =-I10*Asumsi!I15 -> -1386484476244 | J13: =-J10*Asumsi!J15 -> -1.5141656e+12 | K13: =-K10*Asumsi!K15 -> -1.6537375e+12 | L13: =-L10*Asumsi!L15 -> -1.8063189e+12 | M13: =-M10*Asumsi!M15 -> -1.9731352e+12
A14: P.GP_X | B14: Laba bruto sebelum penyusutan | C14: =C10+C13 -> 503120327727 | D14: =D10+D13 -> 816085335022 | E14: =E10+E13 -> 706083081464 | F14: =F10+F13 -> 911964000000 | G14: =G10+G13 -> 1142085000000 | H14: =H10+H13 -> 1320561000000 | I14: =I10+I13 -> 1443075679356 | J14: =J10+J13 -> 1.5759683e+12 | ... M14: =M10+M13 -> 2.0536713e+12
A15: P.OPEX_X | B15: Beban usaha di luar penyusutan & amortisasi | C15: =IS!C11+Schedules!C13+Schedules!C16+Schedules!C18 -> -354709454153 | D15: =IS!D11+Schedules!D13+Schedules!D16+Schedules!D18 -> -408410258960 | E15: =IS!E11+Schedules!E13+Schedules!E16+Schedules!E18 -> -441535401895 | F15: =IS!F11+Schedules!F13+Schedules!F16+Schedules!F18 -> -516426000000 | G15: =IS!G11+Schedules!G13+Schedules!G16+Schedules!G18 -> -632866000000 | H15: =IS!H11+Schedules!H13+Schedules!H16+Schedules!H18 -> -856706000000 | I15: =-I10*Asumsi!I16 -> -8.5169761e+11 | J15: =-J10*Asumsi!J16 -> -9.301303e+11 | K15: =-K10*Asumsi!K16 -> -1.0158673e+12 | L15: =-L10*Asumsi!L16 -> -1.1095959e+12 | M15: =-M10*Asumsi!M16 -> -1.2120687e+12
A16: P.OTHER_OP | B16: Pendapatan (beban) lain-lain neto | C16: =IS!C13 -> 28429533228 | D16: =IS!D13 -> 24028154926 | E16: =IS!E13 -> 4159861446 | F16: =IS!F13 -> 7014000000 | G16: =IS!G13 -> -24777000000 | H16: =IS!H13 -> 2883000000 | I16: =I10*Asumsi!I17 -> 0 | J16: =J10*Asumsi!J17 -> 0 | K16: =K10*Asumsi!K17 -> 0 | L16: =L10*Asumsi!L17 -> 0 | M16: =M10*Asumsi!M17 -> 0
A17: P.EBITDA | B17: EBITDA | C17: =C14+C15+C16 -> 176840406802 | D17: =D14+D15+D16 -> 431703230988 | E17: =E14+E15+E16 -> 268707541015 | F17: =F14+F15+F16 -> 402552000000 | G17: =G14+G15+G16 -> 484442000000 | H17: =H14+H15+H16 -> 466738000000 | I17: =I14+I15+I16 -> 5.9137807e+11 | J17: =J14+J15+J16 -> 6.4583798e+11 | ... M17: =M14+M15+M16 -> 8.4160255e+11 | N17: laba usaha (dihitung) + penyusutan aset tetap + penyusutan aset hak guna + amortisasi
A18: P.DA | B18: Penyusutan & amortisasi | C18: =-Schedules!C20 -> -132557566789 | D18: =-Schedules!D20 -> -181190606441 | E18: =-Schedules!E20 -> -233533889845 | F18: =-Schedules!F20 -> -289277000000 | G18: =-Schedules!G20 -> -326702000000 | H18: =-Schedules!H20 -> -381251000000 | I18: =-(Schedules_Proj!I9+Schedules_Proj!I13) -> -388483338000 | J18: =-(Schedules_Proj!J9+Schedules_Proj!J13) -> -3.9444683e+11 | K18: =-(Schedules_Proj!K9+Schedules_Proj!K13) -> -4.0314821e+11 | L18: =-(Schedules_Proj!L9+Schedules_Proj!L13) -> -4.1466262e+11 | M18: =-(Schedules_Proj!M9+Schedules_Proj!M13) -> -4.2908729e+11
A19: P.EBIT | B19: Laba usaha (EBIT) | C19: =C17+C18 -> 44282840013 | D19: =D17+D18 -> 250512624547 | E19: =E17+E18 -> 35173651170 | F19: =F17+F18 -> 113275000000 | G19: =G17+G18 -> 157740000000 | H19: =H17+H18 -> 85487000000 | I19: =I17+I18 -> 2.0289473e+11 | J19: =J17+J18 -> 2.5139115e+11 | ... M19: =M17+M18 -> 4.1251525e+11 | N19: historis: = laba usaha IS hasil hitung (cek di Rekonsiliasi; Temuan S4)
A20: P.FIN_INC | B20: Penghasilan keuangan | C20: =IS!C16 -> 26470099827 | D20: =IS!D16 -> 23940936423 | E20: =IS!E16 -> 19404583424 | F20: =IS!F16 -> 29119000000 | G20: =IS!G16 -> 13483000000 | H20: =IS!H16 -> 66897000000 | I20: =BS_Proj!H6*Asumsi!I30 -> 178608521400 | J20: =BS_Proj!I6*Asumsi!J30 -> 1.5361268e+11 | K20: =BS_Proj!J6*Asumsi!K30 -> 1.2739431e+11 | L20: =BS_Proj!K6*Asumsi!L30 -> 9.9768781e+10 | M20: =BS_Proj!L6*Asumsi!M30 -> 7.0705909e+10 | N20: E: imbal hasil x kas awal
A21: P.FIN_COST | B21: Beban keuangan | C21: =IS!C15 -> -70561549474 | D21: =IS!D15 -> -118034051135 | E21: =IS!E15 -> -96665120830 | F21: =IS!F15 -> -173685000000 | G21: =IS!G15 -> -173863000000 | H21: =IS!H15 -> -387554000000 | I21: =-Schedules_Proj!I24*Asumsi!I29 -> -515285650000 | J21: =-Schedules_Proj!J24*Asumsi!J29 -> -515285650000 | K21: =-Schedules_Proj!K24*Asumsi!K29 -> -515285650000 | L21: =-Schedules_Proj!L24*Asumsi!L29 -> -515285650000 | M21: =-Schedules_Proj!M24*Asumsi!M29 -> -515285650000 | N21: E: suku bunga x rata-rata utang (Temuan S6)
A22: P.PBT | B22: Laba sebelum pajak | C22: =C19+C20+C21 -> 191390366 | D22: =D19+D20+D21 -> 156419509835 | E22: =E19+E20+E21 -> -42086886236 | F22: =F19+F20+F21 -> -31291000000 | G22: =G19+G20+G21 -> -2640000000 | H22: =H19+H20+H21 -> -235170000000 | I22: =I19+I20+I21 -> -1.3378239e+11 | J22: =J19+J20+J21 -> -1.1028182e+11 | ... M22: =M19+M20+M21 -> -3.2064487e+10
A23: P.TAX | B23: Beban pajak | C23: =IS!C18 -> -14689448354 | D23: =IS!D18 -> 9184536739 | E23: =IS!E18 -> -2100344487 | F23: =IS!F18 -> -7022000000 | G23: =IS!G18 -> -20704000000 | H23: =IS!H18 -> 36380000000 | I23: =-MAX(I22,0)*Asumsi!I28 -> 0 | J23: =-MAX(J22,0)*Asumsi!J28 -> 0 | K23: =-MAX(K22,0)*Asumsi!K28 -> 0 | L23: =-MAX(L22,0)*Asumsi!L28 -> 0 | M23: =-MAX(M22,0)*Asumsi!M28 -> 0
A24: P.NI | B24: Laba tahun berjalan | C24: =C22+C23 -> -14498057988 | D24: =D22+D23 -> 165604046574 | E24: =E22+E23 -> -44187230723 | F24: =F22+F23 -> -38313000000 | G24: =G22+G23 -> -23344000000 | H24: =H22+H23 -> -198790000000 | I24: =I22+I23 -> -1.3378239e+11 | J24: =J22+J23 -> -1.1028182e+11 | ... M24: =M22+M23 -> -3.2064487e+10
A25: P.NI_NCI | B25: Diatribusikan ke NCI | C25: =IS!C27 -> -117430932 | D25: =IS!D27 -> 295807955 | E25: =IS!E27 -> 127718302 | F25: =IS!F27 -> 177000000 | G25: =IS!G27 -> 169000000 | H25: =IS!H27 -> 210000000 | I25: =I24*Asumsi!I33 -> 0 | J25: =J24*Asumsi!J33 -> 0 | K25: =K24*Asumsi!K33 -> 0 | L25: =L24*Asumsi!L33 -> 0 | M25: =M24*Asumsi!M33 -> 0
A26: P.NI_PARENT | B26: Diatribusikan ke pemilik entitas induk | C26: =C24-C25 -> -14380627056 | D26: =D24-D25 -> 165308238619 | E26: =E24-E25 -> -44314949025 | F26: =F24-F25 -> -38490000000 | G26: =G24-G25 -> -23513000000 | H26: =H24-H25 -> -199000000000 | I26: =I24-I25 -> -1.3378239e+11 | J26: =J24-J25 -> -1.1028182e+11 | ... M26: =M24-M25 -> -3.2064487e+10
A27: P.EPS | B27: Laba induk per saham (Rp; / 12.238.959.990 saham) | C27: =C26/Asumsi!$C$118 -> -1.1749877 | D27: =D26/Asumsi!$C$118 -> 13.506723 | E27: =E26/Asumsi!$C$118 -> -3.62081 | F27: =F26/Asumsi!$C$118 -> -3.1448751 | G27: =G26/Asumsi!$C$118 -> -1.92116 | H27: =H26/Asumsi!$C$118 -> -16.259551 | I27: =I26/Asumsi!$C$118 -> -10.930863 | J27: =J26/Asumsi!$C$118 -> -9.0107182 | ... M27: =M26/Asumsi!$C$118 -> -2.6198702 | N27: EPS tercetak memakai saham tertimbang (Temuan S9)
B28: MARGIN
A29: P.GM_X | B29: Margin laba bruto sebelum penyusutan | C29: =C14/C10 -> 0.39189973 | D29: =D14/D10 -> 0.4240609 | E29: =E14/E10 -> 0.3650586 | F29: =F14/F10 -> 0.36432306 | G29: =G14/G10 -> 0.48798063 | H29: =H14/H10 -> 0.50997938 | I29: =I14/I10 -> 0.51 | J29: =J14/J10 -> 0.51 | ... M29: =M14/M10 -> 0.51
A30: P.EBITDA_M | B30: Margin EBITDA | C30: =C17/C10 -> 0.13774778 | D30: =D17/D10 -> 0.22432515 | E30: =E17/E10 -> 0.13892699 | F30: =F17/F10 -> 0.16081663 | G30: =G17/G10 -> 0.20698837 | H30: =H17/H10 -> 0.18024669 | I30: =I17/I10 -> 0.209 | J30: =J17/J10 -> 0.209 | ... M30: =M17/M10 -> 0.209
A31: P.EBIT_M | B31: Margin EBIT | C31: =C19/C10 -> 0.034493603 | D31: =D19/D10 -> 0.13017341 | E31: =E19/E10 -> 0.018185457 | F31: =F19/F10 -> 0.045252547 | G31: =G19/G10 -> 0.067397843 | H31: =H19/H10 -> 0.033013702 | I31: =I19/I10 -> 0.071705397 | J31: =J19/J10 -> 0.081352834 | ... M31: =M19/M10 -> 0.10244229
A32: P.NI_M | B32: Margin laba bersih | C32: =C24/C10 -> -0.011293094 | D32: =D24/D10 -> 0.086052522 | E32: =E24/E10 -> -0.022845652 | F32: =F24/F10 -> -0.015305768 | G32: =G24/G10 -> -0.0099742312 | H32: =H24/H10 -> -0.076769495 | I32: =I24/I10 -> -0.047280279 | J32: =J24/J10 -> -0.035688363 | ... M32: =M24/M10 -> -0.0079627583

Sheet BS_Proj
A1: Proyeksi posisi keuangan agregat (ilustratif)
A2: Rp penuh | kolom A = aktual (link ke IS/BS/CF/Schedules), kolom E = proyeksi | Proyeksi ILUSTRATIF berbasis asumsi transparan - bukan rekomendasi investasi, bukan target, bukan nilai wajar.
A3: Skenario aktif: | C3: =Asumsi!C4 -> Base | I3: ilustratif | J3: ilustratif | K3: ilustratif | L3: ilustratif | M3: ilustratif
A4: Kode | B4: Akun | C4: FY2020A | D4: FY2021A | E4: FY2022A | F4: FY2023A | G4: FY2024A | H4: FY2025A | I4: FY2026E | J4: FY2027E | K4: FY2028E | L4: FY2029E | M4: FY2030E | N4: Catatan / sumber
B5: ASET
A6: PB.CASH | B6: Kas dan setara kas | C6: =BS!C6 -> 629608688874 | D6: =BS!D6 -> 700922359619 | E6: =BS!E6 -> 1118254250664 | F6: =BS!F6 -> 515185000000 | G6: =BS!G6 -> 277208000000 | H6: =BS!H6 -> 1826263000000 | I6: =CF_Proj!I25 -> 1.5706818e+12 | J6: =CF_Proj!J25 -> 1.3026003e+12 | K6: =CF_Proj!K25 -> 1.0201307e+12 | L6: =CF_Proj!L25 -> 7.229643e+11 | M6: =CF_Proj!M25 -> 4.1086524e+11 | N6: E: penyeimbang dari CF_Proj
A7: PB.AR | B7: Piutang usaha (pihak ketiga + berelasi) | C7: =(BS!C8+BS!C9) -> 225422821680 | D7: =(BS!D8+BS!D9) -> 233901361278 | E7: =(BS!E8+BS!E9) -> 242981358318 | F7: =(BS!F8+BS!F9) -> 395321000000 | G7: =(BS!G8+BS!G9) -> 424298000000 | H7: =(BS!H8+BS!H9) -> 557933000000 | I7: =Schedules_Proj!I26 -> 6.1242535e+11 | J7: =Schedules_Proj!J26 -> 6.688235e+11 | K7: =Schedules_Proj!K26 -> 7.3047391e+11 | L7: =Schedules_Proj!L26 -> 7.9787081e+11 | M7: =Schedules_Proj!M26 -> 8.7155537e+11
A8: PB.INV | B8: Persediaan | C8: =BS!C12 -> 74691220678 | D8: =BS!D12 -> 70409082280 | E8: =BS!E12 -> 49621868590 | F8: =BS!F12 -> 48940000000 | G8: =BS!G12 -> 61316000000 | H8: =BS!H12 -> 73323000000 | I8: =Schedules_Proj!I27 -> 7.977034e+10 | J8: =Schedules_Proj!J27 -> 8.7116377e+10 | K8: =Schedules_Proj!K27 -> 9.5146539e+10 | L8: =Schedules_Proj!L27 -> 1.039252e+11 | M8: =Schedules_Proj!M27 -> 1.1352284e+11
A9: PB.OCA | B9: Aset lancar lainnya | C9: =BS!C16-BS!C6-BS!C8-BS!C9-BS!C12 -> 10112775510 | D9: =BS!D16-BS!D6-BS!D8-BS!D9-BS!D12 -> 16221734195 | E9: =BS!E16-BS!E6-BS!E8-BS!E9-BS!E12 -> 34756121020 | F9: =BS!F16-BS!F6-BS!F8-BS!F9-BS!F12 -> 38803000000 | G9: =BS!G16-BS!G6-BS!G8-BS!G9-BS!G12 -> 69980000000 | H9: =BS!H16-BS!H6-BS!H8-BS!H9-BS!H12 -> 70398000000 | I9: =H9 -> 70398000000 | J9: =I9 -> 70398000000 | K9: =J9 -> 70398000000 | L9: =K9 -> 70398000000 | M9: =L9 -> 70398000000 | N9: E: konstan
A10: PB.TCA | B10: Jumlah aset lancar | C10: =C6+C7+C8+C9 -> 939835506742 | D10: =D6+D7+D8+D9 -> 1021454537372 | E10: =E6+E7+E8+E9 -> 1445613598592 | F10: =F6+F7+F8+F9 -> 998249000000 | G10: =G6+G7+G8+G9 -> 832802000000 | H10: =H6+H7+H8+H9 -> 2527917000000 | I10: =I6+I7+I8+I9 -> 2.3332755e+12 | J10: =J6+J7+J8+J9 -> 2.1289382e+12 | ... M10: =M6+M7+M8+M9 -> 1.4663415e+12
A11: PB.PPE | B11: Aset tetap - neto | C11: =BS!C19 -> 2641613456689 | D11: =BS!D19 -> 3169775593830 | E11: =BS!E19 -> 3607142163990 | F11: =BS!F19 -> 3952312000000 | G11: =BS!G19 -> 4164140000000 | H11: =BS!H19 -> 4286327000000 | I11: =Schedules_Proj!I10 -> 4.3586995e+12 | J11: =Schedules_Proj!J10 -> 4.4642988e+12 | K11: =Schedules_Proj!K10 -> 4.6040367e+12 | L11: =Schedules_Proj!L10 -> 4.7790934e+12 | M11: =Schedules_Proj!M10 -> 4.9909278e+12
A12: PB.INTANG | B12: Aset takberwujud | C12: =BS!C22 -> 10032147719 | D12: =BS!D22 -> 18016628295 | E12: =BS!E22 -> 12824038513 | F12: =BS!F22 -> 11773000000 | G12: =BS!G22 -> 11616000000 | H12: =BS!H22 -> 26642000000 | I12: =Schedules_Proj!I15 -> 26642000000 | J12: =Schedules_Proj!J15 -> 26642000000 | K12: =Schedules_Proj!K15 -> 26642000000 | L12: =Schedules_Proj!L15 -> 26642000000 | M12: =Schedules_Proj!M15 -> 26642000000
A13: PB.ONCA | B13: Aset tidak lancar lain (aset hak guna, properti investasi, goodwill, uang muka, pajak tangguhan) | C13: =BS!C26-BS!C19-BS!C22 -> 754847976856 | D13: =BS!D26-BS!D19-BS!D22 -> 662559848864 | E13: =BS!E26-BS!E19-BS!E22 -> 684019446657 | F13: =BS!F26-BS!F19-BS!F22 -> 643957000000 | G13: =BS!G26-BS!G19-BS!G22 -> 674464000000 | H13: =BS!H26-BS!H19-BS!H22 -> 783024000000 | I13: =H13 -> 783024000000 | J13: =I13 -> 783024000000 | K13: =J13 -> 783024000000 | L13: =K13 -> 783024000000 | M13: =L13 -> 783024000000 | N13: E: konstan
A14: PB.TNCA | B14: Jumlah aset tidak lancar | C14: =C11+C12+C13 -> 3406493581264 | D14: =D11+D12+D13 -> 3850352070989 | E14: =E11+E12+E13 -> 4303985649160 | F14: =F11+F12+F13 -> 4608042000000 | G14: =G11+G12+G13 -> 4850220000000 | H14: =H11+H12+H13 -> 5095993000000 | I14: =I11+I12+I13 -> 5.1683655e+12 | J14: =J11+J12+J13 -> 5.2739648e+12 | ... M14: =M11+M12+M13 -> 5.8005938e+12
A15: PB.TA | B15: JUMLAH ASET | C15: =C10+C14 -> 4346329088006 | D15: =D10+D14 -> 4871806608361 | E15: =E10+E14 -> 5749599247752 | F15: =F10+F14 -> 5606291000000 | G15: =G10+G14 -> 5683022000000 | H15: =H10+H14 -> 7623910000000 | I15: =I10+I14 -> 7.501641e+12 | J15: =J10+J14 -> 7.402903e+12 | ... M15: =M10+M14 -> 7.2669353e+12
B16: LIABILITAS
A17: PB.AP | B17: Utang usaha (pihak ketiga + berelasi) | C17: =(BS!C30+BS!C31) -> 175206597303 | D17: =(BS!D30+BS!D31) -> 192301032210 | E17: =(BS!E30+BS!E31) -> 161991239794 | F17: =(BS!F30+BS!F31) -> 140702000000 | G17: =(BS!G30+BS!G31) -> 156194000000 | H17: =(BS!H30+BS!H31) -> 113840000000 | I17: =Schedules_Proj!I28 -> 1.2535339e+11 | J17: =Schedules_Proj!J28 -> 1.3689716e+11 | K17: =Schedules_Proj!K28 -> 1.4951599e+11 | L17: =Schedules_Proj!L28 -> 1.6331103e+11 | M17: =Schedules_Proj!M28 -> 1.7839304e+11
A18: PB.DEBT | B18: Utang berbunga (bank, non-bank, surat utang, pembiayaan) | C18: =(BS!C29+BS!C38+BS!C45+BS!C39+BS!C46+BS!C40+BS!C47+BS!C41+BS!C48) -> 1072251221694 | D18: =(BS!D29+BS!D38+BS!D45+BS!D39+BS!D46+BS!D40+BS!D47+BS!D41+BS!D48) -> 846194719314 | E18: =(BS!E29+BS!E38+BS!E45+BS!E39+BS!E46+BS!E40+BS!E47+BS!E41+BS!E48) -> 1725310890922 | F18: =(BS!F29+BS!F38+BS!F45+BS!F39+BS!F46+BS!F40+BS!F47+BS!F41+BS!F48) -> 1646343000000 | G18: =(BS!G29+BS!G38+BS!G45+BS!G39+BS!G46+BS!G40+BS!G47+BS!G41+BS!G48) -> 1665866000000 | H18: =(BS!H29+BS!H38+BS!H45+BS!H39+BS!H46+BS!H40+BS!H47+BS!H41+BS!H48) -> 4684415000000 | I18: =Schedules_Proj!I23 -> 4684415000000 | J18: =Schedules_Proj!J23 -> 4684415000000 | K18: =Schedules_Proj!K23 -> 4684415000000 | L18: =Schedules_Proj!L23 -> 4684415000000 | M18: =Schedules_Proj!M23 -> 4684415000000
A19: PB.LEASE | B19: Liabilitas sewa | C19: =(BS!C42+BS!C49) -> 0 | D19: =(BS!D42+BS!D49) -> 0 | E19: =(BS!E42+BS!E49) -> 0 | F19: =(BS!F42+BS!F49) -> 3891000000 | G19: =(BS!G42+BS!G49) -> 3276000000 | H19: =(BS!H42+BS!H49) -> 7677000000 | I19: =Schedules_Proj!I18 -> 7677000000 | J19: =Schedules_Proj!J18 -> 7677000000 | K19: =Schedules_Proj!K18 -> 7677000000 | L19: =Schedules_Proj!L18 -> 7677000000 | M19: =Schedules_Proj!M18 -> 7677000000
A20: PB.OL | B20: Liabilitas lainnya | C20: =BS!C53-BS!C30-BS!C31-(BS!C29+BS!C38+BS!C45+BS!C39+BS!C46+BS!C40+BS!C47+BS!C41+BS!C48)-BS!C42-BS!C49 -> 1344134996245 | D20: =BS!D53-BS!D30-BS!D31-(BS!D29+BS!D38+BS!D45+BS!D39+BS!D46+BS!D40+BS!D47+BS!D41+BS!D48)-BS!D42-BS!D49 -> 1905908311154 | E20: =BS!E53-BS!E30-BS!E31-(BS!E29+BS!E38+BS!E45+BS!E39+BS!E46+BS!E40+BS!E47+BS!E41+BS!E48)-BS!E42-BS!E49 -> 1967158995920 | F20: =BS!F53-BS!F30-BS!F31-(BS!F29+BS!F38+BS!F45+BS!F39+BS!F46+BS!F40+BS!F47+BS!F41+BS!F48)-BS!F42-BS!F49 -> 1957898000000 | G20: =BS!G53-BS!G30-BS!G31-(BS!G29+BS!G38+BS!G45+BS!G39+BS!G46+BS!G40+BS!G47+BS!G41+BS!G48)-BS!G42-BS!G49 -> 2024382000000 | H20: =BS!H53-BS!H30-BS!H31-(BS!H29+BS!H38+BS!H45+BS!H39+BS!H46+BS!H40+BS!H47+BS!H41+BS!H48)-BS!H42-BS!H49 -> 1482253000000 | I20: =H20 -> 1482253000000 | J20: =I20 -> 1482253000000 | K20: =J20 -> 1482253000000 | L20: =K20 -> 1482253000000 | M20: =L20 -> 1482253000000 | N20: utang lain, akrual, pajak, liabilitas kontrak, imbalan kerja; E: konstan
A21: PB.TL | B21: JUMLAH LIABILITAS | C21: =C17+C18+C19+C20 -> 2591592815242 | D21: =D17+D18+D19+D20 -> 2944404062678 | E21: =E17+E18+E19+E20 -> 3854461126636 | F21: =F17+F18+F19+F20 -> 3748834000000 | G21: =G17+G18+G19+G20 -> 3849718000000 | H21: =H17+H18+H19+H20 -> 6288185000000 | I21: =I17+I18+I19+I20 -> 6.2996984e+12 | J21: =J17+J18+J19+J20 -> 6.3112422e+12 | ... M21: =M17+M18+M19+M20 -> 6.352738e+12
B22: EKUITAS
A23: PB.EQ_OTHER | B23: Modal & cadangan (selain saldo laba) | C23: =BS!C60-BS!C59 -> 2354636312859 | D23: =BS!D60-BS!D59 -> 2361693272138 | E23: =BS!E60-BS!E59 -> 2373608250616 | F23: =BS!F60-BS!F59 -> 2374241000000 | G23: =BS!G60-BS!G59 -> 2371951000000 | H23: =BS!H60-BS!H59 -> 2073289000000 | I23: =H23 -> 2073289000000 | J23: =I23 -> 2073289000000 | K23: =J23 -> 2073289000000 | L23: =K23 -> 2073289000000 | M23: =L23 -> 2073289000000 | N23: E: konstan
A24: PB.RE | B24: Saldo laba | C24: =BS!C59 -> -600688806428 | D24: =BS!D59 -> -435380567809 | E24: =BS!E59 -> -479695516834 | F24: =BS!F59 -> -518186000000 | G24: =BS!G59 -> -541699000000 | H24: =BS!H59 -> -740699000000 | I24: =H24+IS_Proj!I26+CF_Proj!I19 -> -8.7448139e+11 | J24: =I24+IS_Proj!J26+CF_Proj!J19 -> -9.8476321e+11 | K24: =J24+IS_Proj!K26+CF_Proj!K19 -> -1.0704331e+12 | L24: =K24+IS_Proj!L26+CF_Proj!L19 -> -1.1301623e+12 | M24: =L24+IS_Proj!M26+CF_Proj!M19 -> -1.1622268e+12
A25: PB.EQ_PARENT | B25: Ekuitas pemilik entitas induk | C25: =C23+C24 -> 1753947506431 | D25: =D23+D24 -> 1926312704329 | E25: =E23+E24 -> 1893912733782 | F25: =F23+F24 -> 1856055000000 | G25: =G23+G24 -> 1830252000000 | H25: =H23+H24 -> 1332590000000 | I25: =I23+I24 -> 1.1988076e+12 | J25: =J23+J24 -> 1.0885258e+12 | ... M25: =M23+M24 -> 9.1106222e+11
A26: PB.NCI | B26: Kepentingan nonpengendali | C26: =BS!C61 -> 788766333 | D26: =BS!D61 -> 1089841354 | E26: =BS!E61 -> 1225387334 | F26: =BS!F61 -> 1402000000 | G26: =BS!G61 -> 3052000000 | H26: =BS!H61 -> 3135000000 | I26: =H26+IS_Proj!I25 -> 3135000000 | J26: =I26+IS_Proj!J25 -> 3135000000 | K26: =J26+IS_Proj!K25 -> 3135000000 | L26: =K26+IS_Proj!L25 -> 3135000000 | M26: =L26+IS_Proj!M25 -> 3135000000 | N26: E: tanpa dividen ke NCI (ilustratif)
A27: PB.TE | B27: JUMLAH EKUITAS | C27: =C25+C26 -> 1754736272764 | D27: =D25+D26 -> 1927402545683 | E27: =E25+E26 -> 1895138121116 | F27: =F25+F26 -> 1857457000000 | G27: =G25+G26 -> 1833304000000 | H27: =H25+H26 -> 1335725000000 | I27: =I25+I26 -> 1.2019426e+12 | J27: =J25+J26 -> 1.0916608e+12 | ... M27: =M25+M26 -> 9.1419722e+11
A28: PB.TLE | B28: JUMLAH LIABILITAS DAN EKUITAS | C28: =C21+C27 -> 4346329088006 | D28: =D21+D27 -> 4871806608361 | E28: =E21+E27 -> 5749599247752 | F28: =F21+F27 -> 5606291000000 | G28: =G21+G27 -> 5683022000000 | H28: =H21+H27 -> 7623910000000 | I28: =I21+I27 -> 7.501641e+12 | J28: =J21+J27 -> 7.402903e+12 | ... M28: =M21+M27 -> 7.2669353e+12
A30: PB.CHECK | B30: Cek: aset - (liabilitas + ekuitas), harus 0 | C30: =ROUND(C15-C28,0) -> 0 | D30: =ROUND(D15-D28,0) -> 0 | E30: =ROUND(E15-E28,0) -> 0 | F30: =ROUND(F15-F28,0) -> 0 | G30: =ROUND(G15-G28,0) -> 0 | H30: =ROUND(H15-H28,0) -> 0 | I30: =ROUND(I15-I28,0) -> 0 | J30: =ROUND(J15-J28,0) -> 0 | ... M30: =ROUND(M15-M28,0) -> 0
A31: PB.NETDEBT | B31: Memo: utang neto (utang + sewa - kas) | C31: =C18+C19-C6 -> 442642532820 | D31: =D18+D19-D6 -> 145272359695 | E31: =E18+E19-E6 -> 607056640258 | F31: =F18+F19-F6 -> 1135049000000 | G31: =G18+G19-G6 -> 1391934000000 | H31: =H18+H19-H6 -> 2865829000000 | I31: =I18+I19-I6 -> 3.1214102e+12 | J31: =J18+J19-J6 -> 3.3894917e+12 | ... M31: =M18+M19-M6 -> 4.2812268e+12
A32: PB.ROE | B32: Memo: ROE (laba induk / rata-rata ekuitas induk) | D32: =IS_Proj!D26/AVERAGE(C25,D25) -> 0.089835082 | E32: =IS_Proj!E26/AVERAGE(D25,E25) -> -0.023200175 | F32: =IS_Proj!F26/AVERAGE(E25,F25) -> -0.020528177 | G32: =IS_Proj!G26/AVERAGE(F25,G25) -> -0.012756941 | H32: =IS_Proj!H26/AVERAGE(G25,H25) -> -0.12583619 | I32: =IS_Proj!I26/AVERAGE(H25,I25) -> -0.10569844 | J32: =IS_Proj!J26/AVERAGE(I25,J25) -> -0.096428286 | K32: =IS_Proj!K26/AVERAGE(J25,K25) -> -0.081926611 | ... M32: =IS_Proj!M26/AVERAGE(L25,M25) -> -0.034585997
A33: PB.ND_EBITDA | B33: Memo: utang neto / EBITDA | C33: =C31/IS_Proj!C17 -> 2.5030622 | D33: =D31/IS_Proj!D17 -> 0.33650978 | E33: =E31/IS_Proj!E17 -> 2.2591723 | F33: =F31/IS_Proj!F17 -> 2.8196332 | G33: =G31/IS_Proj!G17 -> 2.8732728 | H33: =H31/IS_Proj!H17 -> 6.1401236 | I33: =I31/IS_Proj!I17 -> 5.2781974 | J33: =J31/IS_Proj!J17 -> 5.2482075 | ... M33: =M31/IS_Proj!M17 -> 5.0869936

Sheet CF_Proj
A1: Proyeksi arus kas (metode tidak langsung untuk tahun E)
A2: Rp penuh | kolom A = aktual (link ke IS/BS/CF/Schedules), kolom E = proyeksi | Proyeksi ILUSTRATIF berbasis asumsi transparan - bukan rekomendasi investasi, bukan target, bukan nilai wajar.
A3: Skenario aktif: | C3: =Asumsi!C4 -> Base | I3: ilustratif | J3: ilustratif | K3: ilustratif | L3: ilustratif | M3: ilustratif
A4: Kode | B4: Akun | C4: FY2020A | D4: FY2021A | E4: FY2022A | F4: FY2023A | G4: FY2024A | H4: FY2025A | I4: FY2026E | J4: FY2027E | K4: FY2028E | L4: FY2029E | M4: FY2030E | N4: Catatan / sumber
B5: ARUS KAS OPERASI
A6: PC.NI | B6: Laba tahun berjalan | C6: =IS_Proj!C24 -> -14498057988 | D6: =IS_Proj!D24 -> 165604046574 | E6: =IS_Proj!E24 -> -44187230723 | F6: =IS_Proj!F24 -> -38313000000 | G6: =IS_Proj!G24 -> -23344000000 | H6: =IS_Proj!H24 -> -198790000000 | I6: =IS_Proj!I24 -> -1.3378239e+11 | J6: =IS_Proj!J24 -> -1.1028182e+11 | ... M6: =IS_Proj!M24 -> -3.2064487e+10
A7: PC.DA | B7: Penyusutan & amortisasi (nonkas) | I7: =-IS_Proj!I18 -> 388483338000 | J7: =-IS_Proj!J18 -> 3.9444683e+11 | K7: =-IS_Proj!K18 -> 4.0314821e+11 | L7: =-IS_Proj!L18 -> 4.1466262e+11 | M7: =-IS_Proj!M18 -> 4.2908729e+11
A8: PC.D_AR | B8: (Kenaikan) piutang usaha | I8: =BS_Proj!H7-BS_Proj!I7 -> -5.4492349e+10 | J8: =BS_Proj!I7-BS_Proj!J7 -> -5.639815e+10 | K8: =BS_Proj!J7-BS_Proj!K7 -> -6.1650415e+10 | L8: =BS_Proj!K7-BS_Proj!L7 -> -6.7396901e+10 | M8: =BS_Proj!L7-BS_Proj!M7 -> -7.3684552e+10
A9: PC.D_INV | B9: (Kenaikan) persediaan | I9: =BS_Proj!H8-BS_Proj!I8 -> -6.4473397e+09 | J9: =BS_Proj!I8-BS_Proj!J8 -> -7.3460375e+09 | K9: =BS_Proj!J8-BS_Proj!K8 -> -8.0301616e+09 | L9: =BS_Proj!K8-BS_Proj!L8 -> -8.7786597e+09 | M9: =BS_Proj!L8-BS_Proj!M8 -> -9.5976461e+09
A10: PC.D_AP | B10: Kenaikan utang usaha | I10: =BS_Proj!I17-BS_Proj!H17 -> 1.1513391e+10 | J10: =BS_Proj!J17-BS_Proj!I17 -> 1.1543773e+10 | K10: =BS_Proj!K17-BS_Proj!J17 -> 1.2618825e+10 | L10: =BS_Proj!L17-BS_Proj!K17 -> 1.3795037e+10 | M10: =BS_Proj!M17-BS_Proj!L17 -> 1.5082015e+10
A11: PC.CFO | B11: Arus kas operasi | C11: =CF!C13 -> 93881891402 | D11: =CF!D13 -> 336786662790 | E11: =CF!E13 -> 210474822261 | F11: =CF!F13 -> 55917000000 | G11: =CF!G13 -> 273248000000 | H11: =CF!H13 -> 129670000000 | I11: =I6+I7+I8+I9+I10 -> 2.0527465e+11 | J11: =J6+J7+J8+J9+J10 -> 2.319646e+11 | K11: =K6+K7+K8+K9+K10 -> 2.6041656e+11 | L11: =L6+L7+L8+L9+L10 -> 2.9255292e+11 | M11: =M6+M7+M8+M9+M10 -> 3.2882262e+11 | N11: historis: laporan (metode langsung); E: tidak langsung
B12: ARUS KAS INVESTASI
A13: PC.CAPEX | B13: Capex aset tetap + uang muka + properti investasi | C13: =CF!C15+CF!C16+CF!C18 -> -544122343656 | D13: =CF!D15+CF!D16+CF!D18 -> -464023277324 | E13: =CF!E15+CF!E16+CF!E18 -> -655546517280 | F13: =CF!F15+CF!F16+CF!F18 -> -583532000000 | G13: =CF!G15+CF!G16+CF!G18 -> -525029000000 | H13: =CF!H15+CF!H16+CF!H18 -> -584290000000 | I13: =-Schedules_Proj!I7 -> -424434023340 | J13: =-Schedules_Proj!J7 -> -4.6352008e+11 | K13: =-Schedules_Proj!K7 -> -5.0624616e+11 | L13: =-Schedules_Proj!L7 -> -5.5295477e+11 | M13: =-Schedules_Proj!M7 -> -6.0402097e+11
A14: PC.SW | B14: Perolehan aset takberwujud | C14: =CF!C17 -> -6697340640 | D14: =CF!D17 -> -3165516135 | E14: =CF!E17 -> -4343974611 | F14: =CF!F17 -> -5066000000 | G14: =CF!G17 -> -7568000000 | H14: =CF!H17 -> -28217000000 | I14: =-Schedules_Proj!I14 -> -35289993200 | J14: =-Schedules_Proj!J14 -> -35289993200 | K14: =-Schedules_Proj!K14 -> -35289993200 | L14: =-Schedules_Proj!L14 -> -35289993200 | M14: =-Schedules_Proj!M14 -> -35289993200
A15: PC.CFI | B15: Arus kas investasi | C15: =CF!C21 -> -550711027296 | D15: =CF!D21 -> -468280289395 | E15: =CF!E21 -> -678222368151 | F15: =CF!F21 -> -585390000000 | G15: =CF!G21 -> -532317000000 | H15: =CF!H21 -> -612150000000 | I15: =I13+I14 -> -459724016540 | J15: =J13+J14 -> -4.9881008e+11 | K15: =K13+K14 -> -5.4153615e+11 | L15: =L13+L14 -> -5.8824477e+11 | M15: =M13+M14 -> -6.3931096e+11 | N15: historis: total laporan
B16: ARUS KAS PENDANAAN
A17: PC.DEBT | B17: Perubahan neto utang berbunga (kas) | C17: =(CF!C23+CF!C24+CF!C25+CF!C26+CF!C27+CF!C28+CF!C29+CF!C30+CF!C31) -> 842012402091 | D17: =(CF!D23+CF!D24+CF!D25+CF!D26+CF!D27+CF!D28+CF!D29+CF!D30+CF!D31) -> -249603489944 | E17: =(CF!E23+CF!E24+CF!E25+CF!E26+CF!E27+CF!E28+CF!E29+CF!E30+CF!E31) -> 885079436935 | F17: =(CF!F23+CF!F24+CF!F25+CF!F26+CF!F27+CF!F28+CF!F29+CF!F30+CF!F31) -> -72889000000 | G17: =(CF!G23+CF!G24+CF!G25+CF!G26+CF!G27+CF!G28+CF!G29+CF!G30+CF!G31) -> 10445000000 | H17: =(CF!H23+CF!H24+CF!H25+CF!H26+CF!H27+CF!H28+CF!H29+CF!H30+CF!H31) -> 1956697000000 | I17: =Asumsi!I31 -> 0 | J17: =Asumsi!J31 -> 0 | K17: =Asumsi!K31 -> 0 | L17: =Asumsi!L31 -> 0 | M17: =Asumsi!M31 -> 0
A18: PC.LEASE | B18: Pembayaran sewa | C18: =CF!C35 -> -330000000000 | D18: =CF!D35 -> 0 | E18: =CF!E35 -> 0 | F18: =CF!F35 -> -707000000 | G18: =CF!G35 -> -708000000 | H18: =CF!H35 -> -1599000000 | I18: =-Schedules_Proj!I8 -> -1.1318241e+09 | J18: =-Schedules_Proj!J8 -> -1.2360536e+09 | K18: =-Schedules_Proj!K8 -> -1.3499898e+09 | L18: =-Schedules_Proj!L8 -> -1.4745461e+09 | M18: =-Schedules_Proj!M8 -> -1.6107226e+09
A19: PC.DIV | B19: Dividen dibayar | C19: =CF!C36 -> 0 | D19: =CF!D36 -> 0 | E19: =CF!E36 -> 0 | F19: =CF!F36 -> 0 | G19: =CF!G36 -> 0 | H19: =CF!H36 -> 0 | I19: =-Asumsi!I32*MAX(IS_Proj!H26,0) -> 0 | J19: =-Asumsi!J32*MAX(IS_Proj!I26,0) -> 0 | K19: =-Asumsi!K32*MAX(IS_Proj!J26,0) -> 0 | L19: =-Asumsi!L32*MAX(IS_Proj!K26,0) -> 0 | M19: =-Asumsi!M32*MAX(IS_Proj!L26,0) -> 0
A20: PC.CFF | B20: Arus kas pendanaan | C20: =CF!C37 -> 854320635527 | D20: =CF!D37 -> 179238263141 | E20: =CF!E37 -> 885079436935 | F20: =CF!F37 -> -73596000000 | G20: =CF!G37 -> 9737000000 | H20: =CF!H37 -> 2023440000000 | I20: =I17+I18+I19 -> -1.1318241e+09 | J20: =J17+J18+J19 -> -1.2360536e+09 | K20: =K17+K18+K19 -> -1.3499898e+09 | L20: =L17+L18+L19 -> -1.4745461e+09 | M20: =M17+M18+M19 -> -1.6107226e+09 | N20: historis: total laporan
A22: PC.NET | B22: Kenaikan (penurunan) neto kas | C22: =C11+C15+C20 -> 397491499633 | D22: =D11+D15+D20 -> 47744636536 | E22: =E11+E15+E20 -> 417331891045 | F22: =F11+F15+F20 -> -603069000000 | G22: =G11+G15+G20 -> -249332000000 | H22: =H11+H15+H20 -> 1540960000000 | I22: =I11+I15+I20 -> -2.5558119e+11 | J22: =J11+J15+J20 -> -2.6808153e+11 | ... M22: =M11+M15+M20 -> -3.1209906e+11
A23: PC.CASH_BEGIN | B23: Kas awal tahun | C23: =CF!C40 -> 232117189241 | D23: =CF!D40 -> 653177723083 | E23: =CF!E40 -> 700922359619 | F23: =CF!F40 -> 1118254000000 | G23: =CF!G40 -> 497371000000 | H23: =CF!H40 -> 248039000000 | I23: =BS_Proj!H6 -> 1826263000000 | J23: =BS_Proj!I6 -> 1.5706818e+12 | K23: =BS_Proj!J6 -> 1.3026003e+12 | L23: =BS_Proj!K6 -> 1.0201307e+12 | M23: =BS_Proj!L6 -> 7.229643e+11 | N23: E: kas neraca
A24: PC.FX | B24: Efek kurs & selisih definisi kas LAK vs neraca | C24: =BS!C6-C23-C22 -> 0 | D24: =BS!D6-D23-D22 -> 0 | E24: =BS!E6-E23-E22 -> 0 | F24: =BS!F6-F23-F22 -> 0 | G24: =BS!G6-G23-G22 -> 29169000000 | H24: =BS!H6-H23-H22 -> 37264000000 | I24: =0 -> 0 | J24: =0 -> 0 | K24: =0 -> 0 | L24: =0 -> 0 | M24: =0 -> 0 | N24: historis: kas neraca - kas awal LAK - kenaikan neto (Temuan S5); E: 0
A25: PC.CASH_END | B25: Kas akhir tahun (neraca) | C25: =C23+C22+C24 -> 629608688874 | D25: =D23+D22+D24 -> 700922359619 | E25: =E23+E22+E24 -> 1118254250664 | F25: =F23+F22+F24 -> 515185000000 | G25: =G23+G22+G24 -> 277208000000 | H25: =H23+H22+H24 -> 1826263000000 | I25: =I23+I22+I24 -> 1.5706818e+12 | J25: =J23+J22+J24 -> 1.3026003e+12 | ... M25: =M23+M22+M24 -> 4.1086524e+11
B26: MEMO: ARUS KAS BEBAS
A27: PC.FCF | B27: FCF = arus kas operasi + capex | C27: =C11+C13+N(C14) -> -456937792894 | D27: =D11+D13+N(D14) -> -130402130669 | E27: =E11+E13+N(E14) -> -449415669630 | F27: =F11+F13+N(F14) -> -532681000000 | G27: =G11+G13+N(G14) -> -259349000000 | H27: =H11+H13+N(H14) -> -482837000000 | I27: =I11+I13+I14 -> -2.5444937e+11 | J27: =J11+J13+J14 -> -2.6684548e+11 | K27: =K11+K13+K14 -> -2.811196e+11 | L27: =L11+L13+L14 -> -2.9569184e+11 | M27: =M11+M13+M14 -> -3.1048834e+11
A28: PC.FCF_L | B28: FCF setelah pembayaran sewa | C28: =C27+C18 -> -786937792894 | D28: =D27+D18 -> -130402130669 | E28: =E27+E18 -> -449415669630 | F28: =F27+F18 -> -533388000000 | G28: =G27+G18 -> -260057000000 | H28: =H27+H18 -> -484436000000 | I28: =I27+I18 -> -2.5558119e+11 | J28: =J27+J18 -> -2.6808153e+11 | ... M28: =M27+M18 -> -3.1209906e+11

Sheet Schedules_Proj
A1: Schedule proyeksi: aset tetap, ROU & sewa, utang, modal kerja
A2: Rp penuh | kolom A = aktual (link ke IS/BS/CF/Schedules), kolom E = proyeksi | Proyeksi ILUSTRATIF berbasis asumsi transparan - bukan rekomendasi investasi, bukan target, bukan nilai wajar.
A3: Skenario aktif: | C3: =Asumsi!C4 -> Base | I3: ilustratif | J3: ilustratif | K3: ilustratif | L3: ilustratif | M3: ilustratif
A4: Kode | B4: Akun | C4: FY2020A | D4: FY2021A | E4: FY2022A | F4: FY2023A | G4: FY2024A | H4: FY2025A | I4: FY2026E | J4: FY2027E | K4: FY2028E | L4: FY2029E | M4: FY2030E | N4: Catatan / sumber
B5: ASET TETAP (aset hak guna konstan di aset tidak lancar lain)
A6: S.PPE_BEG | B6: Aset tetap neto awal | I6: =BS_Proj!H11 -> 4286327000000 | J6: =BS_Proj!I11 -> 4.3586995e+12 | K6: =BS_Proj!J11 -> 4.4642988e+12 | L6: =BS_Proj!K11 -> 4.6040367e+12 | M6: =BS_Proj!L11 -> 4.7790934e+12
A7: S.CAPEX | B7: Capex (kas) | C7: =-(CF!C15+CF!C16) -> 544122343656 | D7: =-(CF!D15+CF!D16) -> 464023277324 | E7: =-(CF!E15+CF!E16) -> 655546517280 | F7: =-(CF!F15+CF!F16) -> 583532000000 | G7: =-(CF!G15+CF!G16) -> 525029000000 | H7: =-(CF!H15+CF!H16) -> 579605000000 | I7: =Asumsi!I19*IS_Proj!I10 -> 424434023340 | J7: =Asumsi!J19*IS_Proj!J10 -> 4.6352008e+11 | K7: =Asumsi!K19*IS_Proj!K10 -> 5.0624616e+11 | L7: =Asumsi!L19*IS_Proj!L10 -> 5.5295477e+11 | M7: =Asumsi!M19*IS_Proj!M10 -> 6.0402097e+11
A8: S.LEASE_PD | B8: Pembayaran sewa (dikapitalisasi ke aset tetap) | C8: =-CF!C35 -> 330000000000 | D8: =-CF!D35 -> 0 | E8: =-CF!E35 -> 0 | F8: =-CF!F35 -> 707000000 | G8: =-CF!G35 -> 708000000 | H8: =-CF!H35 -> 1599000000 | I8: =Asumsi!I20*IS_Proj!I10 -> 1.1318241e+09 | J8: =Asumsi!J20*IS_Proj!J10 -> 1.2360536e+09 | K8: =Asumsi!K20*IS_Proj!K10 -> 1.3499898e+09 | L8: =Asumsi!L20*IS_Proj!L10 -> 1.4745461e+09 | M8: =Asumsi!M20*IS_Proj!M10 -> 1.6107226e+09
A9: S.DEP | B9: Penyusutan aset tetap + aset hak guna | C9: =Schedules!C14+Schedules!C16 -> 130182090222 | D9: =Schedules!D14+Schedules!D16 -> 176694169969 | E9: =Schedules!E14+Schedules!E16 -> 227237596826 | F9: =Schedules!F14+Schedules!F16 -> 283295000000 | G9: =Schedules!G14+Schedules!G16 -> 318977000000 | H9: =Schedules!H14+Schedules!H16 -> 365864000000 | I9: =I6*Asumsi!I21 -> 353193344800 | J9: =J6*Asumsi!J21 -> 3.5915684e+11 | K9: =K6*Asumsi!K21 -> 3.6785822e+11 | L9: =L6*Asumsi!L21 -> 3.7937263e+11 | M9: =M6*Asumsi!M21 -> 3.937973e+11
A10: S.PPE_END | B10: Aset tetap neto akhir | C10: =BS!C19 -> 2641613456689 | D10: =BS!D19 -> 3169775593830 | E10: =BS!E19 -> 3607142163990 | F10: =BS!F19 -> 3952312000000 | G10: =BS!G19 -> 4164140000000 | H10: =BS!H19 -> 4286327000000 | I10: =I6+I7+I8-I9 -> 4.3586995e+12 | J10: =J6+J7+J8-J9 -> 4.4642988e+12 | K10: =K6+K7+K8-K9 -> 4.6040367e+12 | L10: =L6+L7+L8-L9 -> 4.7790934e+12 | M10: =M6+M7+M8-M9 -> 4.9909278e+12 | N10: historis: neraca (memuat penambahan nonkas, pelepasan, penurunan nilai)
B11: ASET TAKBERWUJUD
A12: S.INT_BEG | B12: Aset takberwujud awal | I12: =BS_Proj!H12 -> 26642000000 | J12: =BS_Proj!I12 -> 26642000000 | K12: =BS_Proj!J12 -> 26642000000 | L12: =BS_Proj!K12 -> 26642000000 | M12: =BS_Proj!L12 -> 26642000000
A13: S.SW_AMORT | B13: Amortisasi | C13: =Schedules!C19 -> 2375476567 | D13: =Schedules!D19 -> 4496436472 | E13: =Schedules!E19 -> 6296293019 | F13: =Schedules!F19 -> 5982000000 | G13: =Schedules!G19 -> 7725000000 | H13: =Schedules!H19 -> 15387000000 | I13: =I12*Asumsi!I22 -> 35289993200 | J13: =J12*Asumsi!J22 -> 35289993200 | K13: =K12*Asumsi!K22 -> 35289993200 | L13: =L12*Asumsi!L22 -> 35289993200 | M13: =M12*Asumsi!M22 -> 35289993200
A14: S.SW_CAPEX | B14: Penambahan (= amortisasi) | I14: =I13 -> 35289993200 | J14: =J13 -> 35289993200 | K14: =K13 -> 35289993200 | L14: =L13 -> 35289993200 | M14: =M13 -> 35289993200
A15: S.INT_END | B15: Aset takberwujud akhir | C15: =BS!C22 -> 10032147719 | D15: =BS!D22 -> 18016628295 | E15: =BS!E22 -> 12824038513 | F15: =BS!F22 -> 11773000000 | G15: =BS!G22 -> 11616000000 | H15: =BS!H22 -> 26642000000 | I15: =I12+I14-I13 -> 26642000000 | J15: =J12+J14-J13 -> 26642000000 | K15: =K12+K14-K13 -> 26642000000 | L15: =L12+L14-L13 -> 26642000000 | M15: =M12+M14-M13 -> 26642000000
B16: LIABILITAS SEWA
A17: S.LEASE_BEG | B17: Liabilitas sewa awal | I17: =BS_Proj!H19 -> 7677000000 | J17: =BS_Proj!I19 -> 7677000000 | K17: =BS_Proj!J19 -> 7677000000 | L17: =BS_Proj!K19 -> 7677000000 | M17: =BS_Proj!L19 -> 7677000000
A18: S.LEASE_END | B18: Liabilitas sewa akhir | C18: =(BS!C42+BS!C49) -> 0 | D18: =(BS!D42+BS!D49) -> 0 | E18: =(BS!E42+BS!E49) -> 0 | F18: =(BS!F42+BS!F49) -> 3891000000 | G18: =(BS!G42+BS!G49) -> 3276000000 | H18: =(BS!H42+BS!H49) -> 7677000000 | I18: =I17 -> 7677000000 | J18: =J17 -> 7677000000 | K18: =K17 -> 7677000000 | L18: =L17 -> 7677000000 | M18: =M17 -> 7677000000 | N18: E: konstan (pembayaran sewa dikapitalisasi ke aset tetap)
A19: S.LEASE_AVG | B19: Rata-rata liabilitas sewa | D19: =AVERAGE((BS!C42+BS!C49),D18) -> 0 | E19: =AVERAGE((BS!D42+BS!D49),E18) -> 0 | F19: =AVERAGE((BS!E42+BS!E49),F18) -> 1945500000 | G19: =AVERAGE((BS!F42+BS!F49),G18) -> 3583500000 | H19: =AVERAGE((BS!G42+BS!G49),H18) -> 5476500000 | I19: =AVERAGE(I17,I18) -> 7677000000 | J19: =AVERAGE(J17,J18) -> 7677000000 | K19: =AVERAGE(K17,K18) -> 7677000000 | L19: =AVERAGE(L17,L18) -> 7677000000 | M19: =AVERAGE(M17,M18) -> 7677000000
B20: UTANG BERBUNGA
A21: S.DEBT_BEG | B21: Utang awal | I21: =BS_Proj!H18 -> 4684415000000 | J21: =BS_Proj!I18 -> 4684415000000 | K21: =BS_Proj!J18 -> 4684415000000 | L21: =BS_Proj!K18 -> 4684415000000 | M21: =BS_Proj!L18 -> 4684415000000
A22: S.DEBT_CHG | B22: Perubahan neto (tarik / (bayar)) | I22: =Asumsi!I31 -> 0 | J22: =Asumsi!J31 -> 0 | K22: =Asumsi!K31 -> 0 | L22: =Asumsi!L31 -> 0 | M22: =Asumsi!M31 -> 0
A23: S.DEBT_END | B23: Utang akhir | C23: =(BS!C29+BS!C38+BS!C45+BS!C39+BS!C46+BS!C40+BS!C47+BS!C41+BS!C48) -> 1072251221694 | D23: =(BS!D29+BS!D38+BS!D45+BS!D39+BS!D46+BS!D40+BS!D47+BS!D41+BS!D48) -> 846194719314 | E23: =(BS!E29+BS!E38+BS!E45+BS!E39+BS!E46+BS!E40+BS!E47+BS!E41+BS!E48) -> 1725310890922 | F23: =(BS!F29+BS!F38+BS!F45+BS!F39+BS!F46+BS!F40+BS!F47+BS!F41+BS!F48) -> 1646343000000 | G23: =(BS!G29+BS!G38+BS!G45+BS!G39+BS!G46+BS!G40+BS!G47+BS!G41+BS!G48) -> 1665866000000 | H23: =(BS!H29+BS!H38+BS!H45+BS!H39+BS!H46+BS!H40+BS!H47+BS!H41+BS!H48) -> 4684415000000 | I23: =I21+I22 -> 4684415000000 | J23: =J21+J22 -> 4684415000000 | K23: =K21+K22 -> 4684415000000 | L23: =L21+L22 -> 4684415000000 | M23: =M21+M22 -> 4684415000000
A24: S.DEBT_AVG | B24: Rata-rata utang | D24: =AVERAGE((BS!C29+BS!C38+BS!C45+BS!C39+BS!C46+BS!C40+BS!C47+BS!C41+BS!C48),D23) -> 959222970504 | E24: =AVERAGE((BS!D29+BS!D38+BS!D45+BS!D39+BS!D46+BS!D40+BS!D47+BS!D41+BS!D48),E23) -> 1285752805118 | F24: =AVERAGE((BS!E29+BS!E38+BS!E45+BS!E39+BS!E46+BS!E40+BS!E47+BS!E41+BS!E48),F23) -> 1685826945461 | G24: =AVERAGE((BS!F29+BS!F38+BS!F45+BS!F39+BS!F46+BS!F40+BS!F47+BS!F41+BS!F48),G23) -> 1656104500000 | H24: =AVERAGE((BS!G29+BS!G38+BS!G45+BS!G39+BS!G46+BS!G40+BS!G47+BS!G41+BS!G48),H23) -> 3175140500000 | I24: =AVERAGE(I21,I23) -> 4684415000000 | J24: =AVERAGE(J21,J23) -> 4684415000000 | K24: =AVERAGE(K21,K23) -> 4684415000000 | L24: =AVERAGE(L21,L23) -> 4684415000000 | M24: =AVERAGE(M21,M23) -> 4684415000000
B25: MODAL KERJA
A26: S.AR | B26: Piutang usaha (DSO x pendapatan / 365) | C26: =(BS!C8+BS!C9) -> 225422821680 | D26: =(BS!D8+BS!D9) -> 233901361278 | E26: =(BS!E8+BS!E9) -> 242981358318 | F26: =(BS!F8+BS!F9) -> 395321000000 | G26: =(BS!G8+BS!G9) -> 424298000000 | H26: =(BS!H8+BS!H9) -> 557933000000 | I26: =IS_Proj!I10*Asumsi!I24/365 -> 6.1242535e+11 | J26: =IS_Proj!J10*Asumsi!J24/365 -> 6.688235e+11 | K26: =IS_Proj!K10*Asumsi!K24/365 -> 7.3047391e+11 | L26: =IS_Proj!L10*Asumsi!L24/365 -> 7.9787081e+11 | M26: =IS_Proj!M10*Asumsi!M24/365 -> 8.7155537e+11
A27: S.INV | B27: Persediaan (DIO x beban pokok / 365) | C27: =BS!C12 -> 74691220678 | D27: =BS!D12 -> 70409082280 | E27: =BS!E12 -> 49621868590 | F27: =BS!F12 -> 48940000000 | G27: =BS!G12 -> 61316000000 | H27: =BS!H12 -> 73323000000 | I27: =-IS_Proj!I13*Asumsi!I25/365 -> 7.977034e+10 | J27: =-IS_Proj!J13*Asumsi!J25/365 -> 8.7116377e+10 | K27: =-IS_Proj!K13*Asumsi!K25/365 -> 9.5146539e+10 | L27: =-IS_Proj!L13*Asumsi!L25/365 -> 1.039252e+11 | M27: =-IS_Proj!M13*Asumsi!M25/365 -> 1.1352284e+11
A28: S.AP | B28: Utang usaha (DPO x beban pokok / 365) | C28: =(BS!C30+BS!C31) -> 175206597303 | D28: =(BS!D30+BS!D31) -> 192301032210 | E28: =(BS!E30+BS!E31) -> 161991239794 | F28: =(BS!F30+BS!F31) -> 140702000000 | G28: =(BS!G30+BS!G31) -> 156194000000 | H28: =(BS!H30+BS!H31) -> 113840000000 | I28: =-IS_Proj!I13*Asumsi!I26/365 -> 1.2535339e+11 | J28: =-IS_Proj!J13*Asumsi!J26/365 -> 1.3689716e+11 | K28: =-IS_Proj!K13*Asumsi!K26/365 -> 1.4951599e+11 | L28: =-IS_Proj!L13*Asumsi!L26/365 -> 1.6331103e+11 | M28: =-IS_Proj!M13*Asumsi!M26/365 -> 1.7839304e+11
A29: S.NWC | B29: Modal kerja usaha neto | C29: =C26+C27-C28 -> 124907445055 | D29: =D26+D27-D28 -> 112009411348 | E29: =E26+E27-E28 -> 130611987114 | F29: =F26+F27-F28 -> 303559000000 | G29: =G26+G27-G28 -> 329420000000 | H29: =H26+H27-H28 -> 517416000000 | I29: =I26+I27-I28 -> 5.668423e+11 | J29: =J26+J27-J28 -> 6.1904271e+11 | ... M29: =M26+M27-M28 -> 8.0668517e+11
A30: S.D_NWC | B30: (Kenaikan) modal kerja | D30: =C29-D29 -> 12898033707 | E30: =D29-E29 -> -18602575766 | F30: =E29-F29 -> -172947012886 | G30: =F29-G29 -> -25861000000 | H30: =G29-H29 -> -187996000000 | I30: =H29-I29 -> -4.9426297e+10 | J30: =I29-J29 -> -5.2200415e+10 | K30: =J29-K29 -> -5.7061751e+10 | ... M30: =L29-M29 -> -6.8200183e+10

Sheet DCF_Template
A1: Template DCF opsional - kalkulator untuk pengguna (input KOSONG)
A2: Sel kuning diisi sendiri oleh pengguna dan perlu diverifikasi. Hasil sepenuhnya bergantung pada input pengguna; BUKAN nilai wajar, target, atau rekomendasi dari penyusun.
B4: INPUT (kosong = template tidak menghitung)
B5: Suku bunga bebas risiko (Rf) | D5: perlu diisi/diverifikasi: mis. imbal hasil SUN 10 tahun; catat sumber & tanggal
B6: Equity risk premium (ERP) | D6: perlu diisi/diverifikasi: catat sumber
B7: Beta (levered) | D7: perlu diisi/diverifikasi: metode, periode & indeks acuan
B8: Premi tambahan (ukuran/spesifik), opsional | D8: perlu diisi/diverifikasi: isi 0 bila tidak dipakai
B9: Biaya utang sebelum pajak (Kd) | D9: perlu diisi/diverifikasi
B10: Tarif pajak untuk perisai bunga | D10: perlu diisi/diverifikasi: tarif PPh badan berlaku
B11: Bobot utang D/(D+E) target | D11: perlu diisi/diverifikasi
B12: Pertumbuhan terminal (g) - metode Gordon | D12: perlu diisi/diverifikasi
B13: Kelipatan EV/EBITDA terminal - metode exit multiple | D13: perlu diisi/diverifikasi: dokumentasikan sumber
B14: Aset non-operasi ditambahkan (Rp), mis. investasi saham | D14: perlu diisi/diverifikasi: isi 0 bila tidak dipakai
B15: Input inti lengkap? (Rf, ERP, beta, Kd, pajak, bobot utang) | C15: =COUNT($C$5,$C$6,$C$7,$C$9,$C$10,$C$11)=6 -> FALSE
B16: Siap hitung metode Gordon? | C16: =AND($C$15,COUNT($C$12)=1) -> FALSE
B17: Siap hitung metode exit multiple? | C17: =AND($C$15,COUNT($C$13)=1) -> FALSE
B19: WACC
B20: Biaya ekuitas Ke = Rf + beta x ERP + premi | C20: =IF($C$15,$C$5+$C$7*$C$6+N($C$8),"")
B21: Biaya utang setelah pajak | C21: =IF($C$15,$C$9*(1-$C$10),"")
B22: WACC | C22: =IF($C$15,$C$20*(1-$C$11)+$C$21*$C$11,"")
B24: FCFF (mengikuti skenario aktif di Asumsi)
I25: FY2026E | J25: FY2027E | K25: FY2028E | L25: FY2029E | M25: FY2030E
B26: Periode diskonto (tahun, akhir periode) | I26: 1 | J26: 2 | K26: 3 | L26: 4 | M26: 5
B27: EBIT | I27: =IS_Proj!I19 -> 2.0289473e+11 | J27: =IS_Proj!J19 -> 2.5139115e+11 | K27: =IS_Proj!K19 -> 3.0222144e+11 | L27: =IS_Proj!L19 -> 3.557877e+11 | M27: =IS_Proj!M19 -> 4.1251525e+11
B28: Pajak atas EBIT (tarif dari Asumsi) | I28: =-MAX(I27,0)*Asumsi!I28 -> -5.0723684e+10 | J28: =-MAX(J27,0)*Asumsi!J28 -> -6.2847788e+10 | K28: =-MAX(K27,0)*Asumsi!K28 -> -7.5555359e+10 | L28: =-MAX(L27,0)*Asumsi!L28 -> -8.8946924e+10 | M28: =-MAX(M27,0)*Asumsi!M28 -> -1.0312881e+11
B29: NOPAT | I29: =I27+I28 -> 1.5217105e+11 | J29: =J27+J28 -> 1.8854336e+11 | K29: =K27+K28 -> 2.2666608e+11 | L29: =L27+L28 -> 2.6684077e+11 | M29: =M27+M28 -> 3.0938644e+11
B30: + D&A | I30: =-IS_Proj!I18 -> 388483338000 | J30: =-IS_Proj!J18 -> 3.9444683e+11 | K30: =-IS_Proj!K18 -> 4.0314821e+11 | L30: =-IS_Proj!L18 -> 4.1466262e+11 | M30: =-IS_Proj!M18 -> 4.2908729e+11
B31: - Capex | I31: =CF_Proj!I13 -> -424434023340 | J31: =CF_Proj!J13 -> -4.6352008e+11 | K31: =CF_Proj!K13 -> -5.0624616e+11 | L31: =CF_Proj!L13 -> -5.5295477e+11 | M31: =CF_Proj!M13 -> -6.0402097e+11
B32: - Kenaikan modal kerja | I32: =Schedules_Proj!I30 -> -4.9426297e+10 | J32: =Schedules_Proj!J30 -> -5.2200415e+10 | K32: =Schedules_Proj!K30 -> -5.7061751e+10 | L32: =Schedules_Proj!L30 -> -6.2380524e+10 | M32: =Schedules_Proj!M30 -> -6.8200183e+10
B33: FCFF | I33: =SUM(I29:I32) -> 6.6794068e+10 | J33: =SUM(J29:J32) -> 6.7269697e+10 | K33: =SUM(K29:K32) -> 6.650638e+10 | L33: =SUM(L29:L32) -> 6.6168096e+10 | M33: =SUM(M29:M32) -> 6.6252583e+10
B34: Faktor diskonto | I34: =IF($C$15,1/(1+$C$22)^I26,"") | J34: =IF($C$15,1/(1+$C$22)^J26,"") | K34: =IF($C$15,1/(1+$C$22)^K26,"") | L34: =IF($C$15,1/(1+$C$22)^L26,"") | M34: =IF($C$15,1/(1+$C$22)^M26,"")
B35: PV FCFF | I35: =IF($C$15,I33*I34,"") | J35: =IF($C$15,J33*J34,"") | K35: =IF($C$15,K33*K34,"") | L35: =IF($C$15,L33*L34,"") | M35: =IF($C$15,M33*M34,"")
B36: Catatan IFRS 16: FCFF sebelum pembayaran sewa, sehingga liabilitas sewa diperlakukan sebagai utang di jembatan ekuitas.
B38: NILAI PERUSAHAAN & JEMBATAN EKUITAS (hasil kalkulator) | C38: Gordon | D38: Exit multiple
B39: Σ PV FCFF | C39: =IF($C$16,SUMPRODUCT($I$33:$M$33/(1+$C$22)^$I$26:$M$26),"") | D39: =IF($C$17,SUMPRODUCT($I$33:$M$33/(1+$C$22)^$I$26:$M$26),"")
B40: Nilai terminal (akhir FY2030E) | C40: =IF($C$16,IF($C$22>$C$12,$M$33*(1+$C$12)/($C$22-$C$12),"WACC<=g"),"") | D40: =IF($C$17,IS_Proj!$M$17*$C$13,"")
B41: PV nilai terminal | C41: =IFERROR(C40/(1+$C$22)^5,"") | D41: =IFERROR(D40/(1+$C$22)^5,"")
B42: Nilai perusahaan (EV) | C42: =IFERROR(C39+C41,"") | D42: =IFERROR(D39+D41,"")
B43: (-) Utang bank FY2025A | C43: =-BS_Proj!H18 -> -4684415000000 | D43: =-BS_Proj!H18 -> -4684415000000
B44: (-) Liabilitas sewa FY2025A | C44: =-BS_Proj!H19 -> -7677000000 | D44: =-BS_Proj!H19 -> -7677000000
B45: (+) Kas FY2025A | C45: =BS_Proj!H6 -> 1826263000000 | D45: =BS_Proj!H6 -> 1826263000000
B46: (-) Kepentingan nonpengendali (nilai buku FY2025A) | C46: =-BS_Proj!H26 -> -3135000000 | D46: =-BS_Proj!H26 -> -3135000000
B47: (+) Aset non-operasi (input) | C47: =N($C$14) -> 0 | D47: =N($C$14) -> 0
B48: Nilai ekuitas | C48: =IFERROR(C42+SUM(C43:C47),"") | D48: =IFERROR(D42+SUM(D43:D47),"")
B49: Nilai ekuitas per saham (Rp) | C49: =IFERROR(C48/Asumsi!$C$118,"") | D49: =IFERROR(D48/Asumsi!$C$118,"")
B50: Hanya keluaran rumus atas input pengguna; bukan target, bukan nilai wajar, bukan rekomendasi. NCI dikurangkan pada nilai buku (penyederhanaan).
B52: SENSITIVITAS nilai ekuitas per saham (Gordon): WACC (baris) x g (kolom)
B53: WACC \ g | C53: =IF($C$16,$C$12+(-0.01),"") | D53: =IF($C$16,$C$12+(-0.005),"") | E53: =IF($C$16,$C$12+(0),"") | F53: =IF($C$16,$C$12+(0.005),"") | G53: =IF($C$16,$C$12+(0.01),"")
B54: =IF($C$16,$C$22+(-0.02),"") | C54: =IF($C$16,IFERROR(IF($B54>C$53,(SUMPRODUCT($I$33:$M$33/(1+$B54)^$I$26:$M$26)+$M$33*(1+C$53)/($B54-C$53)/(1+$B54)^5+SUM($C$43:$C$47))/Asumsi!$C$118,"n/a"),""),"") | D54: =IF($C$16,IFERROR(IF($B54>D$53,(SUMPRODUCT($I$33:$M$33/(1+$B54)^$I$26:$M$26)+$M$33*(1+D$53)/($B54-D$53)/(1+$B54)^5+SUM($C$43:$C$47))/Asumsi!$C$118,"n/a"),""),"") | E54: =IF($C$16,IFERROR(IF($B54>E$53,(SUMPRODUCT($I$33:$M$33/(1+$B54)^$I$26:$M$26)+$M$33*(1+E$53)/($B54-E$53)/(1+$B54)^5+SUM($C$43:$C$47))/Asumsi!$C$118,"n/a"),""),"") | F54: =IF($C$16,IFERROR(IF($B54>F$53,(SUMPRODUCT($I$33:$M$33/(1+$B54)^$I$26:$M$26)+$M$33*(1+F$53)/($B54-F$53)/(1+$B54)^5+SUM($C$43:$C$47))/Asumsi!$C$118,"n/a"),""),"") | G54: =IF($C$16,IFERROR(IF($B54>G$53,(SUMPRODUCT($I$33:$M$33/(1+$B54)^$I$26:$M$26)+$M$33*(1+G$53)/($B54-G$53)/(1+$B54)^5+SUM($C$43:$C$47))/Asumsi!$C$118,"n/a"),""),"")
B55: =IF($C$16,$C$22+(-0.01),"") | C55: =IF($C$16,IFERROR(IF($B55>C$53,(SUMPRODUCT($I$33:$M$33/(1+$B55)^$I$26:$M$26)+$M$33*(1+C$53)/($B55-C$53)/(1+$B55)^5+SUM($C$43:$C$47))/Asumsi!$C$118,"n/a"),""),"") | D55: =IF($C$16,IFERROR(IF($B55>D$53,(SUMPRODUCT($I$33:$M$33/(1+$B55)^$I$26:$M$26)+$M$33*(1+D$53)/($B55-D$53)/(1+$B55)^5+SUM($C$43:$C$47))/Asumsi!$C$118,"n/a"),""),"") | E55: =IF($C$16,IFERROR(IF($B55>E$53,(SUMPRODUCT($I$33:$M$33/(1+$B55)^$I$26:$M$26)+$M$33*(1+E$53)/($B55-E$53)/(1+$B55)^5+SUM($C$43:$C$47))/Asumsi!$C$118,"n/a"),""),"") | F55: =IF($C$16,IFERROR(IF($B55>F$53,(SUMPRODUCT($I$33:$M$33/(1+$B55)^$I$26:$M$26)+$M$33*(1+F$53)/($B55-F$53)/(1+$B55)^5+SUM($C$43:$C$47))/Asumsi!$C$118,"n/a"),""),"") | G55: =IF($C$16,IFERROR(IF($B55>G$53,(SUMPRODUCT($I$33:$M$33/(1+$B55)^$I$26:$M$26)+$M$33*(1+G$53)/($B55-G$53)/(1+$B55)^5+SUM($C$43:$C$47))/Asumsi!$C$118,"n/a"),""),"")
B56: =IF($C$16,$C$22+(0),"") | C56: =IF($C$16,IFERROR(IF($B56>C$53,(SUMPRODUCT($I$33:$M$33/(1+$B56)^$I$26:$M$26)+$M$33*(1+C$53)/($B56-C$53)/(1+$B56)^5+SUM($C$43:$C$47))/Asumsi!$C$118,"n/a"),""),"") | D56: =IF($C$16,IFERROR(IF($B56>D$53,(SUMPRODUCT($I$33:$M$33/(1+$B56)^$I$26:$M$26)+$M$33*(1+D$53)/($B56-D$53)/(1+$B56)^5+SUM($C$43:$C$47))/Asumsi!$C$118,"n/a"),""),"") | E56: =IF($C$16,IFERROR(IF($B56>E$53,(SUMPRODUCT($I$33:$M$33/(1+$B56)^$I$26:$M$26)+$M$33*(1+E$53)/($B56-E$53)/(1+$B56)^5+SUM($C$43:$C$47))/Asumsi!$C$118,"n/a"),""),"") | F56: =IF($C$16,IFERROR(IF($B56>F$53,(SUMPRODUCT($I$33:$M$33/(1+$B56)^$I$26:$M$26)+$M$33*(1+F$53)/($B56-F$53)/(1+$B56)^5+SUM($C$43:$C$47))/Asumsi!$C$118,"n/a"),""),"") | G56: =IF($C$16,IFERROR(IF($B56>G$53,(SUMPRODUCT($I$33:$M$33/(1+$B56)^$I$26:$M$26)+$M$33*(1+G$53)/($B56-G$53)/(1+$B56)^5+SUM($C$43:$C$47))/Asumsi!$C$118,"n/a"),""),"")
B57: =IF($C$16,$C$22+(0.01),"") | C57: =IF($C$16,IFERROR(IF($B57>C$53,(SUMPRODUCT($I$33:$M$33/(1+$B57)^$I$26:$M$26)+$M$33*(1+C$53)/($B57-C$53)/(1+$B57)^5+SUM($C$43:$C$47))/Asumsi!$C$118,"n/a"),""),"") | D57: =IF($C$16,IFERROR(IF($B57>D$53,(SUMPRODUCT($I$33:$M$33/(1+$B57)^$I$26:$M$26)+$M$33*(1+D$53)/($B57-D$53)/(1+$B57)^5+SUM($C$43:$C$47))/Asumsi!$C$118,"n/a"),""),"") | E57: =IF($C$16,IFERROR(IF($B57>E$53,(SUMPRODUCT($I$33:$M$33/(1+$B57)^$I$26:$M$26)+$M$33*(1+E$53)/($B57-E$53)/(1+$B57)^5+SUM($C$43:$C$47))/Asumsi!$C$118,"n/a"),""),"") | F57: =IF($C$16,IFERROR(IF($B57>F$53,(SUMPRODUCT($I$33:$M$33/(1+$B57)^$I$26:$M$26)+$M$33*(1+F$53)/($B57-F$53)/(1+$B57)^5+SUM($C$43:$C$47))/Asumsi!$C$118,"n/a"),""),"") | G57: =IF($C$16,IFERROR(IF($B57>G$53,(SUMPRODUCT($I$33:$M$33/(1+$B57)^$I$26:$M$26)+$M$33*(1+G$53)/($B57-G$53)/(1+$B57)^5+SUM($C$43:$C$47))/Asumsi!$C$118,"n/a"),""),"")
B58: =IF($C$16,$C$22+(0.02),"") | C58: =IF($C$16,IFERROR(IF($B58>C$53,(SUMPRODUCT($I$33:$M$33/(1+$B58)^$I$26:$M$26)+$M$33*(1+C$53)/($B58-C$53)/(1+$B58)^5+SUM($C$43:$C$47))/Asumsi!$C$118,"n/a"),""),"") | D58: =IF($C$16,IFERROR(IF($B58>D$53,(SUMPRODUCT($I$33:$M$33/(1+$B58)^$I$26:$M$26)+$M$33*(1+D$53)/($B58-D$53)/(1+$B58)^5+SUM($C$43:$C$47))/Asumsi!$C$118,"n/a"),""),"") | E58: =IF($C$16,IFERROR(IF($B58>E$53,(SUMPRODUCT($I$33:$M$33/(1+$B58)^$I$26:$M$26)+$M$33*(1+E$53)/($B58-E$53)/(1+$B58)^5+SUM($C$43:$C$47))/Asumsi!$C$118,"n/a"),""),"") | F58: =IF($C$16,IFERROR(IF($B58>F$53,(SUMPRODUCT($I$33:$M$33/(1+$B58)^$I$26:$M$26)+$M$33*(1+F$53)/($B58-F$53)/(1+$B58)^5+SUM($C$43:$C$47))/Asumsi!$C$118,"n/a"),""),"") | G58: =IF($C$16,IFERROR(IF($B58>G$53,(SUMPRODUCT($I$33:$M$33/(1+$B58)^$I$26:$M$26)+$M$33*(1+G$53)/($B58-G$53)/(1+$B58)^5+SUM($C$43:$C$47))/Asumsi!$C$118,"n/a"),""),"")
B60: Template ini sengaja tidak memuat perbandingan dengan data pasar. Pengguna bertanggung jawab penuh atas input dan interpretasinya.

Sheet Peer
A1: Tabel pembanding - data FUNDAMENTAL saja (baris pembanding kosong)
A2: Isi hanya dengan data terverifikasi dari laporan keuangan publik tiap emiten; cantumkan sumber & tanggal akses. Tidak ada angka yang dikarang.
A4: Kode | B4: Nama emiten | C4: Fokus usaha | D4: Tahun buku | E4: Pendapatan (Rp miliar) | F4: Pertumbuhan pendapatan | G4: Margin EBITDA | H4: Margin laba bersih | I4: ROE | J4: ROA | K4: Utang / ekuitas | L4: Utang neto / EBITDA | M4: Jumlah RS | N4: Jumlah tempat tidur | O4: Porsi pendapatan obat & perlengkapan medis | P4: Sumber (laporan, halaman) | Q4: Tanggal akses
A5: SRAJ | B5: PT Sejahteraraya Anugrahjaya Tbk | C5: Jaringan rumah sakit swasta (Mayapada Hospital, Jakarta dll) | D5: 2025 | E5: =IS_Proj!H10/1000000000 -> 2589.44 | F5: =IS_Proj!H11 -> 0.10639451 | G5: =IS_Proj!H30 -> 0.18024669 | H5: =IS_Proj!H32 -> -0.076769495 | I5: =BS_Proj!H32 -> -0.12583619 | J5: =IS_Proj!H24/BS_Proj!H15 -> -0.026074547 | K5: =BS_Proj!H18/BS_Proj!H27 -> 3.5070205 | L5: =BS_Proj!H33 -> 6.1401236 | O5: =IS_Proj!H6/IS_Proj!H10 -> 0.49884145 | P5: Model ini (laporan audited FY2025)
B14: Median pembanding (tanpa SRAJ) | E14: =IF(COUNT(E6:E13)=0,"",MEDIAN(E6:E13)) | F14: =IF(COUNT(F6:F13)=0,"",MEDIAN(F6:F13)) | G14: =IF(COUNT(G6:G13)=0,"",MEDIAN(G6:G13)) | H14: =IF(COUNT(H6:H13)=0,"",MEDIAN(H6:H13)) | I14: =IF(COUNT(I6:I13)=0,"",MEDIAN(I6:I13)) | J14: =IF(COUNT(J6:J13)=0,"",MEDIAN(J6:J13)) | K14: =IF(COUNT(K6:K13)=0,"",MEDIAN(K6:K13)) | L14: =IF(COUNT(L6:L13)=0,"",MEDIAN(L6:L13)) | ... O14: =IF(COUNT(O6:O13)=0,"",MEDIAN(O6:O13))
B15: Rata-rata pembanding (tanpa SRAJ) | E15: =IF(COUNT(E6:E13)=0,"",AVERAGE(E6:E13)) | F15: =IF(COUNT(F6:F13)=0,"",AVERAGE(F6:F13)) | G15: =IF(COUNT(G6:G13)=0,"",AVERAGE(G6:G13)) | H15: =IF(COUNT(H6:H13)=0,"",AVERAGE(H6:H13)) | I15: =IF(COUNT(I6:I13)=0,"",AVERAGE(I6:I13)) | J15: =IF(COUNT(J6:J13)=0,"",AVERAGE(J6:J13)) | K15: =IF(COUNT(K6:K13)=0,"",AVERAGE(K6:K13)) | L15: =IF(COUNT(L6:L13)=0,"",AVERAGE(L6:L13)) | ... O15: =IF(COUNT(O6:O13)=0,"",AVERAGE(O6:O13))
B17: Tabel ini sengaja tidak memuat kelipatan pasar (P/E, P/BV, EV/EBITDA): isinya ringkasan data fundamental, bukan penilaian.

Sheet IS
A1: Laporan Laba Rugi & OCI - historis FY2021A-FY2025A
A2: Rp penuh. Biru = input dari SRAJ_seri_2020_2025.json (LK audited; 2023-2025 dari Rp juta), hitam = rumus. Tiap kolom dari LK tahun itu (dasar asli), kecuali 2024 = komparatif LK FY2025 disajikan kembali (Temuan S1-S2).
B3: Sumber kolom | C3: LK FY2020 (audit, Rp penuh) | D3: LK FY2021 (audit, Rp penuh) | E3: LK FY2022 (audit, Rp penuh) | F3: LK FY2023 (audit, Rp juta) | G3: LK FY2025 (komparatif disajikan kembali, Rp juta) | H3: LK FY2025 (audit, Rp juta) | I3: Catatan sumber: SRAJ (PT Sejahteraraya Anugrahjaya Tbk / Mayapada Hospital). Histori FY2020-FY2025 dari LK audit masing-masing tahun (dasar asli), kecuali 2024 dari komparatif LK FY2025
A4: Kode | B4: Akun | C4: FY2020A | D4: FY2021A | E4: FY2022A | F4: FY2023A | G4: FY2024A | H4: FY2025A | I4: Catatan / sumber
B5: LABA RUGI
A6: IS.REVENUE | B6: Pendapatan (Cat 26) | C6: 1283798609174 | D6: 1924453140978 | E6: 1934163680964 | F6: 2503174000000 | G6: 2340431000000 | H6: 2589440000000 | I6: kunci JSON: pendapatan
A7: IS.COGS | B7: Beban pokok pendapatan (Cat 27) | C7: -864698280519 | D7: -1219420404326 | E7: -1377109387379 | F7: -1785154000000 | G7: -1423988000000 | H7: -1530564000000 | I7: kunci JSON: beban_pokok
A8: IS.GROSS_PROFIT | B8: Laba bruto | C8: =C6+C7 -> 419100328655 | D8: =D6+D7 -> 705032736652 | E8: =E6+E7 -> 557054293585 | F8: =F6+F7 -> 718020000000 | G8: =G6+G7 -> 916443000000 | H8: =H6+H7 -> 1058876000000
A9: IS.SELLING | B9: Beban penjualan | C9: -10542219731 | D9: -16138644007 | E9: -24027267689 | F9: -34839000000 | G9: -44779000000 | H9: -53940000000 | I9: kunci JSON: beban_penjualan
A10: IS.GA | B10: Beban umum dan administrasi (Cat 28) | C10: -392704802139 | D10: -462409623024 | E10: -502013236172 | F10: -576920000000 | G10: -689147000000 | H10: -922332000000 | I10: kunci JSON: beban_umum
A11: IS.OPEX_TOTAL | B11: Jumlah beban usaha | C11: =C9+C10 -> -403247021870 | D11: =D9+D10 -> -478548267031 | E11: =E9+E10 -> -526040503861 | F11: =F9+F10 -> -611759000000 | G11: =G9+G10 -> -733926000000 | H11: =H9+H10 -> -976272000000
A12: IS.OTHER_INCOME | B12: Pendapatan (beban) lain-lain - neto (Cat 30) | C12: 28429533228 | D12: 24028154926 | E12: 4159861446 | F12: 7014000000 | G12: -24777000000 | H12: 2883000000 | I12: kunci JSON: pendapatan_lain
A13: IS.OTHER_OPER_NET | B13: Pendapatan (beban) lain-lain neto | C13: =C12 -> 28429533228 | D13: =D12 -> 24028154926 | E13: =E12 -> 4159861446 | F13: =F12 -> 7014000000 | G13: =G12 -> -24777000000 | H13: =H12 -> 2883000000
A14: IS.OPER_PROFIT | B14: Laba (rugi) usaha (dihitung; tidak dicetak di LK) | C14: =C8+C11+C13 -> 44282840013 | D14: =D8+D11+D13 -> 250512624547 | E14: =E8+E11+E13 -> 35173651170 | F14: =F8+F11+F13 -> 113275000000 | G14: =G8+G11+G13 -> 157740000000 | H14: =H8+H11+H13 -> 85487000000
A15: IS.FIN_COST | B15: Beban keuangan | C15: -70561549474 | D15: -118034051135 | E15: -96665120830 | F15: -173685000000 | G15: -173863000000 | H15: -387554000000 | I15: kunci JSON: beban_keuangan
A16: IS.FIN_INCOME | B16: Penghasilan keuangan | C16: 26470099827 | D16: 23940936423 | E16: 19404583424 | F16: 29119000000 | G16: 13483000000 | H16: 66897000000 | I16: kunci JSON: penghasilan_keuangan
A17: IS.PBT | B17: Laba (rugi) sebelum pajak | C17: =C14+C16+C15 -> 191390366 | D17: =D14+D16+D15 -> 156419509835 | E17: =E14+E16+E15 -> -42086886236 | F17: =F14+F16+F15 -> -31291000000 | G17: =G14+G16+G15 -> -2640000000 | H17: =H14+H16+H15 -> -235170000000
A18: IS.TAX_TOTAL | B18: Beban (manfaat) pajak penghasilan | C18: -14689448354 | D18: 9184536739 | E18: -2100344487 | F18: -7022000000 | G18: -20704000000 | H18: 36380000000 | I18: kunci JSON: beban_pajak
A19: IS.NET_INCOME | B19: Laba (rugi) tahun berjalan | C19: =C17+C18 -> -14498057988 | D19: =D17+D18 -> 165604046574 | E19: =E17+E18 -> -44187230723 | F19: =F17+F18 -> -38313000000 | G19: =G17+G18 -> -23344000000 | H19: =H17+H18 -> -198790000000
B20: PENGHASILAN KOMPREHENSIF LAIN (OCI)
A21: IS.OCI_REMEASURE | B21: Pengukuran kembali program imbalan pasti | C21: 7358311173 | D21: 9054136342 | E21: 15285648917 | F21: 810000000 | G21: -1037000000 | H21: -5373000000 | I21: kunci JSON: oci_remeasurement
A22: IS.OCI_TAX | B22: Pajak terkait | C22: -2361493433 | D22: -1991909997 | E22: -3362842761 | F22: -178000000 | G22: 228000000 | H22: 1182000000 | I22: kunci JSON: oci_pajak_terkait
A23: IS.OCI_TOTAL | B23: Jumlah OCI | C23: =C21+C22 -> 4996817740 | D23: =D21+D22 -> 7062226345 | E23: =E21+E22 -> 11922806156 | F23: =F21+F22 -> 632000000 | G23: =G21+G22 -> -809000000 | H23: =H21+H22 -> -4191000000
A24: IS.TCI | B24: Jumlah laba komprehensif | C24: =C19+C23 -> -9501240248 | D24: =D19+D23 -> 172666272919 | E24: =E19+E23 -> -32264424567 | F24: =F19+F23 -> -37681000000 | G24: =G19+G23 -> -24153000000 | H24: =H19+H23 -> -202981000000
B25: ATRIBUSI & PER SAHAM
A26: IS.NI_PARENT | B26: Laba diatribusikan ke pemilik entitas induk | C26: -14380627056 | D26: 165308238619 | E26: -44314949025 | F26: -38490000000 | G26: -23513000000 | H26: -199000000000 | I26: kunci JSON: laba_induk
A27: IS.NI_NCI | B27: Laba diatribusikan ke kepentingan nonpengendali (NCI) | C27: -117430932 | D27: 295807955 | E27: 127718302 | F27: 177000000 | G27: 169000000 | H27: 210000000 | I27: kunci JSON: laba_nci
A28: IS.TCI_PARENT | B28: Laba komprehensif - pemilik entitas induk | C28: -9387214298 | D28: 172365197898 | E28: -32399970547 | F28: -37858000000 | G28: -24323000000 | H28: -203188000000 | I28: kunci JSON: tci_induk
A29: IS.TCI_NCI | B29: Laba komprehensif - NCI | C29: -114025950 | D29: 301075021 | E29: 135545980 | F29: 177000000 | G29: 170000000 | H29: 207000000 | I29: kunci JSON: tci_nci
A30: IS.EPS_BASIC | B30: Laba (rugi) per saham dasar tercetak (Rp, penuh) | C30: -1.2 | D30: 13.77 | E30: -3.69 | F30: -3.21 | G30: -1.96 | H30: -16.31 | I30: kunci JSON: eps_dasar
B31: MEMO: SUBTOTAL TERCETAK DI LK (untuk Rekonsiliasi)
A32: IS.GROSS_PROFIT_PRINTED | B32: Laba bruto (tercetak) | C32: 419100328655 | D32: 705032736652 | E32: 557054293585 | F32: 718020000000 | G32: 916443000000 | H32: 1058876000000 | I32: kunci JSON: laba_bruto
A33: IS.PBT_PRINTED | B33: Laba sebelum pajak (tercetak) | C33: 191390366 | D33: 156419509835 | E33: -42086886236 | F33: -31291000000 | G33: -2640000000 | H33: -235170000000 | I33: kunci JSON: laba_sebelum_pajak
A34: IS.NET_INCOME_PRINTED | B34: Laba tahun berjalan (tercetak) | C34: -14498057988 | D34: 165604046574 | E34: -44187230723 | F34: -38313000000 | G34: -23344000000 | H34: -198790000000 | I34: kunci JSON: laba_tahun_berjalan
A35: IS.OCI_TOTAL_PRINTED | B35: Jumlah OCI (tercetak) | C35: 4996817740 | D35: 7062226345 | E35: 11922806156 | F35: 632000000 | G35: -809000000 | H35: -4191000000 | I35: kunci JSON: oci_total
A36: IS.TCI_PRINTED | B36: Laba komprehensif (tercetak) | C36: -9501240248 | D36: 172666272919 | E36: -32264424567 | F36: -37681000000 | G36: -24153000000 | H36: -202981000000 | I36: kunci JSON: total_laba_komprehensif

Sheet BS
A1: Laporan Posisi Keuangan - historis FY2021A-FY2025A
A2: Rp penuh. Biru = input dari SRAJ_seri_2020_2025.json (LK audited; 2023-2025 dari Rp juta), hitam = rumus. Tiap kolom dari LK tahun itu (dasar asli), kecuali 2024 = komparatif LK FY2025 disajikan kembali (Temuan S1-S2).
B3: Sumber kolom | C3: LK FY2020 (audit, Rp penuh) | D3: LK FY2021 (audit, Rp penuh) | E3: LK FY2022 (audit, Rp penuh) | F3: LK FY2023 (audit, Rp juta) | G3: LK FY2025 (komparatif disajikan kembali, Rp juta) | H3: LK FY2025 (audit, Rp juta) | I3: Catatan sumber: SRAJ (PT Sejahteraraya Anugrahjaya Tbk / Mayapada Hospital). Histori FY2020-FY2025 dari LK audit masing-masing tahun (dasar asli), kecuali 2024 dari komparatif LK FY2025
A4: Kode | B4: Akun | C4: FY2020A | D4: FY2021A | E4: FY2022A | F4: FY2023A | G4: FY2024A | H4: FY2025A | I4: Catatan / sumber
B5: ASET
A6: BS.CASH | B6: Kas dan setara kas | C6: 629608688874 | D6: 700922359619 | E6: 1118254250664 | F6: 515185000000 | G6: 277208000000 | H6: 1826263000000 | I6: kunci JSON: kas
A7: BS.RESTRICTED_CASH | B7: Kas yang dibatasi penggunaannya (lancar) | F7: 6517000000 | G7: 6532000000 | H7: 24842000000 | I7: kunci JSON: kas_dibatasi
A8: BS.TRADE_REC | B8: Piutang usaha - pihak ketiga | C8: 220460304910 | D8: 220052635242 | E8: 236288599157 | F8: 386346000000 | G8: 414860000000 | H8: 547368000000 | I8: kunci JSON: piutang_usaha_pk3
A9: BS.TRADE_REC_RP | B9: Piutang usaha - pihak berelasi | C9: 4962516770 | D9: 13848726036 | E9: 6692759161 | F9: 8975000000 | G9: 9438000000 | H9: 10565000000 | I9: kunci JSON: piutang_usaha_rp
A10: BS.OTHER_REC | B10: Piutang lain-lain - pihak ketiga | C10: 5236876642 | D10: 6793936211 | E10: 7310678172 | F10: 8852000000 | G10: 10458000000 | H10: 12256000000 | I10: kunci JSON: piutang_lain_pk3
A11: BS.OTHER_REC_RP | B11: Piutang lain-lain - pihak berelasi | D11: 1404495936 | E11: 18626561484 | F11: 90000000 | G11: 23876000000 | H11: 165000000 | I11: kunci JSON: piutang_lain_rp
A12: BS.INVENTORY | B12: Persediaan | C12: 74691220678 | D12: 70409082280 | E12: 49621868590 | F12: 48940000000 | G12: 61316000000 | H12: 73323000000 | I12: kunci JSON: persediaan
A13: BS.ADVANCES | B13: Uang muka | C13: 2034924128 | D13: 2900786193 | E13: 4312304352 | F13: 14564000000 | G13: 16299000000 | H13: 4624000000 | I13: kunci JSON: uang_muka
A14: BS.PREPAID_ADV | B14: Beban dibayar dimuka | C14: 2833681995 | D14: 3822885889 | E14: 4402483862 | F14: 8381000000 | G14: 11258000000 | H14: 26770000000 | I14: kunci JSON: biaya_dimuka
A15: BS.PREPAID_TAX | B15: Pajak dibayar dimuka | C15: 7292745 | D15: 1299629966 | E15: 104093150 | F15: 399000000 | G15: 1557000000 | H15: 1741000000 | I15: kunci JSON: pajak_dimuka
A16: BS.TOTAL_CA | B16: Jumlah aset lancar | C16: =C6+C7+C8+C9+C10+C11+C12+C13+C14+C15 -> 939835506742 | D16: =D6+D7+D8+D9+D10+D11+D12+D13+D14+D15 -> 1021454537372 | E16: =E6+E7+E8+E9+E10+E11+E12+E13+E14+E15 -> 1445613598592 | F16: =F6+F7+F8+F9+F10+F11+F12+F13+F14+F15 -> 998249000000 | G16: =G6+G7+G8+G9+G10+G11+G12+G13+G14+G15 -> 832802000000 | H16: =H6+H7+H8+H9+H10+H11+H12+H13+H14+H15 -> 2527917000000
A17: BS.OTHER_NCA | B17: Aset tidak lancar lainnya (termasuk kas dibatasi tidak lancar) | C17: 104654187444 | F17: 1581000000 | G17: 1569000000 | H17: 101000000 | I17: kunci JSON: aset_tl_lain
A18: BS.PREPAID_ADV_NC | B18: Uang muka pembelian aset tetap | C18: 16208296660 | D18: 36491564325 | E18: 58126636520 | F18: 17269000000 | G18: 62164000000 | H18: 131298000000 | I18: kunci JSON: uang_muka_aset
A19: BS.PPE | B19: Aset tetap - neto (model biaya) | C19: 2641613456689 | D19: 3169775593830 | E19: 3607142163990 | F19: 3952312000000 | G19: 4164140000000 | H19: 4286327000000 | I19: kunci JSON: aset_tetap
A20: BS.INVEST_PROPERTY | B20: Properti investasi | C20: 40010000000 | D20: 40010000000 | E20: 40010000000 | F20: 40010000000 | G20: 40010000000 | H20: 44695000000 | I20: kunci JSON: properti_investasi
A21: BS.ROU | B21: Aset hak guna | C21: 308029359532 | D21: 280850298397 | E21: 253671237262 | F21: 227253000000 | G21: 199858000000 | H21: 177145000000 | I21: kunci JSON: aset_hak_guna
A22: BS.INTANGIBLES | B22: Aset takberwujud | C22: 10032147719 | D22: 18016628295 | E22: 12824038513 | F22: 11773000000 | G22: 11616000000 | H22: 26642000000 | I22: kunci JSON: aset_takberwujud
A23: BS.TAX_REFUND_CLAIM | B23: Klaim restitusi pajak | C23: 1292381206 | D23: 1292381206 | E23: 7436614727 | F23: 12673000000 | G23: 11645000000 | H23: 11151000000 | I23: kunci JSON: klaim_restitusi
A24: BS.DTA | B24: Aset pajak tangguhan | C24: 46883177777 | D24: 66145030699 | E24: 87004383911 | F24: 107400000000 | G24: 121447000000 | H24: 180863000000 | I24: kunci JSON: aset_pajak_tangguhan
A25: BS.GOODWILL | B25: Goodwill | C25: 237770574237 | D25: 237770574237 | E25: 237770574237 | F25: 237771000000 | G25: 237771000000 | H25: 237771000000 | I25: kunci JSON: goodwill
A26: BS.TOTAL_NCA | B26: Jumlah aset tidak lancar | C26: =C17+C18+C19+C20+C21+C22+C23+C24+C25 -> 3406493581264 | D26: =D17+D18+D19+D20+D21+D22+D23+D24+D25 -> 3850352070989 | E26: =E17+E18+E19+E20+E21+E22+E23+E24+E25 -> 4303985649160 | F26: =F17+F18+F19+F20+F21+F22+F23+F24+F25 -> 4608042000000 | G26: =G17+G18+G19+G20+G21+G22+G23+G24+G25 -> 4850220000000 | H26: =H17+H18+H19+H20+H21+H22+H23+H24+H25 -> 5095993000000
A27: BS.TOTAL_ASSETS | B27: JUMLAH ASET | C27: =C16+C26 -> 4346329088006 | D27: =D16+D26 -> 4871806608361 | E27: =E16+E26 -> 5749599247752 | F27: =F16+F26 -> 5606291000000 | G27: =G16+G26 -> 5683022000000 | H27: =H16+H26 -> 7623910000000
B28: LIABILITAS
A29: BS.ST_BANK | B29: Pinjaman bank jangka pendek | C29: 221000000000 | D29: 589152777778 | E29: 483535978780 | F29: 17814000000 | G29: 29169000000 | I29: kunci JSON: pinjaman_bank_jp
A30: BS.TRADE_PAY | B30: Utang usaha - pihak ketiga | C30: 175206597303 | D30: 192301032210 | E30: 161991239794 | F30: 140702000000 | G30: 156194000000 | H30: 113840000000 | I30: kunci JSON: utang_usaha_pk3
A31: BS.TRADE_PAY_RP | B31: Utang usaha - pihak berelasi | I31: kunci JSON: -
A32: BS.OTHER_PAY | B32: Utang lain-lain - pihak ketiga (termasuk utang kontraktor) | C32: 66098090281 | D32: 170509062467 | E32: 201562330538 | F32: 145827000000 | G32: 191476000000 | H32: 118144000000 | I32: kunci JSON: utang_lain_pk3
A33: BS.OTHER_PAY_RP | B33: Utang lain-lain - pihak berelasi (Temuan S7) | C33: 1085218611770 | D33: 1514060364827 | E33: 1512219212558 | F33: 1512219000000 | G33: 1512219000000 | H33: 972118000000 | I33: kunci JSON: utang_lain_rp
A34: BS.TAX_PAY | B34: Utang pajak | C34: 5880237037 | D34: 14970177592 | E34: 25707571372 | F34: 31481000000 | G34: 15733000000 | H34: 12818000000 | I34: kunci JSON: utang_pajak
A35: BS.ACCRUALS | B35: Beban akrual | C35: 95105436109 | D35: 123381315476 | E35: 139578855784 | F35: 158668000000 | G35: 143972000000 | H35: 186564000000 | I35: kunci JSON: beban_akrual
A36: BS.CONTRACT_LIAB_CUR | B36: Pendapatan diterima dimuka / liabilitas kontrak | C36: 1303280866 | D36: 938125432 | E36: 1287099899 | F36: 8693000000 | G36: 11579000000 | H36: 9708000000 | I36: kunci JSON: kontrak_jt1
A37: BS.EMPLOYEE_BENEFIT_CUR | B37: Liabilitas imbalan kerja jangka pendek | G37: 22216000000 | H37: 27260000000 | I37: kunci JSON: imbalan_kerja_jp
A38: BS.LT_BANK_CUR | B38: Utang bank jk panjang - jatuh tempo 1 tahun | C38: 91176257959 | D38: 52297722986 | E38: 74790481477 | F38: 63114000000 | G38: 78393000000 | H38: 91017000000 | I38: kunci JSON: utang_bank_jt1
A39: BS.FINLOAN_CUR | B39: Pinjaman lembaga keuangan non-bank - jatuh tempo 1 tahun | F39: 24083000000 | G39: 27093000000 | H39: 76309000000 | I39: kunci JSON: pinjaman_jt1
A40: BS.BOND_CUR | B40: Surat utang / obligasi - jatuh tempo 1 tahun | G40: 407900000000 | I40: kunci JSON: obligasi_jt1
A41: BS.FIN_LEASE_CUR | B41: Utang pembiayaan (sewa pembiayaan/konsumen) - jatuh tempo 1 tahun | D41: 1570320009 | E41: 2092655844 | F41: 2311000000 | G41: 431000000 | I41: kunci JSON: sewa_pemb_jt1
A42: BS.LEASE_CUR | B42: Liabilitas sewa - jatuh tempo 1 tahun | F42: 614000000 | G42: 671000000 | H42: 2252000000 | I42: kunci JSON: sewa_jt1
A43: BS.TOTAL_CL | B43: Jumlah liabilitas jangka pendek | C43: =C29+C30+C31+C32+C33+C34+C35+C36+C37+C38+C39+C40+C41+C42 -> 1740988511325 | D43: =D29+D30+D31+D32+D33+D34+D35+D36+D37+D38+D39+D40+D41+D42 -> 2659180898777 | E43: =E29+E30+E31+E32+E33+E34+E35+E36+E37+E38+E39+E40+E41+E42 -> 2602765426046 | F43: =F29+F30+F31+F32+F33+F34+F35+F36+F37+F38+F39+F40+F41+F42 -> 2105526000000 | G43: =G29+G30+G31+G32+G33+G34+G35+G36+G37+G38+G39+G40+G41+G42 -> 2597046000000 | H43: =H29+H30+H31+H32+H33+H34+H35+H36+H37+H38+H39+H40+H41+H42 -> 1610030000000
A44: BS.OTHER_NCL | B44: Liabilitas tidak lancar lainnya | C44: 1231545813 | E44: 212900943 | I44: kunci JSON: liab_tl_lain
A45: BS.LT_BANK_NC | B45: Utang bank jk panjang - setelah 1 tahun | C45: 760074963735 | D45: 199591059102 | E45: 219148960138 | F45: 150054000000 | G45: 166878000000 | H45: 208514000000 | I45: kunci JSON: utang_bank_jp
A46: BS.FINLOAN_NC | B46: Pinjaman lembaga keuangan non-bank - setelah 1 tahun | F46: 443840000000 | G46: 417535000000 | H46: 734153000000 | I46: kunci JSON: pinjaman_jp
A47: BS.BOND_NC | B47: Surat utang / obligasi - setelah 1 tahun | E47: 943301762640 | F47: 944725000000 | G47: 538467000000 | H47: 3574422000000 | I47: kunci JSON: obligasi_jp
A48: BS.FIN_LEASE_NC | B48: Utang pembiayaan (sewa pembiayaan/konsumen) - setelah 1 tahun | D48: 3582839439 | E48: 2441052043 | F48: 402000000 | I48: kunci JSON: sewa_pemb_jp
A49: BS.LEASE_NC | B49: Liabilitas sewa - setelah 1 tahun | F49: 3277000000 | G49: 2605000000 | H49: 5425000000 | I49: kunci JSON: sewa_jp
A50: BS.EMPLOYEE_BENEFIT | B50: Liabilitas imbalan kerja jangka panjang | C50: 89297794369 | D50: 82049265360 | E50: 76938154146 | F50: 86578000000 | G50: 111014000000 | H50: 155333000000 | I50: kunci JSON: imbalan_kerja
A51: BS.DTL | B51: Liabilitas pajak tangguhan | E51: 9652870680 | F51: 14432000000 | G51: 16173000000 | H51: 308000000 | I51: kunci JSON: liab_pajak_tangguhan
A52: BS.TOTAL_NCL | B52: Jumlah liabilitas jangka panjang | C52: =C44+C45+C46+C47+C48+C49+C50+C51 -> 850604303917 | D52: =D44+D45+D46+D47+D48+D49+D50+D51 -> 285223163901 | E52: =E44+E45+E46+E47+E48+E49+E50+E51 -> 1251695700590 | F52: =F44+F45+F46+F47+F48+F49+F50+F51 -> 1643308000000 | G52: =G44+G45+G46+G47+G48+G49+G50+G51 -> 1252672000000 | H52: =H44+H45+H46+H47+H48+H49+H50+H51 -> 4678155000000
A53: BS.TOTAL_LIAB | B53: JUMLAH LIABILITAS | C53: =C43+C52 -> 2591592815242 | D53: =D43+D52 -> 2944404062678 | E53: =E43+E52 -> 3854461126636 | F53: =F43+F52 -> 3748834000000 | G53: =G43+G52 -> 3849718000000 | H53: =H43+H52 -> 6288185000000
B54: EKUITAS
A55: BS.SHARE_CAPITAL | B55: Modal saham | C55: 1200070544500 | D55: 1200070544500 | E55: 1200070544500 | F55: 1200071000000 | G55: 1200071000000 | H55: 1223896000000 | I55: kunci JSON: modal_saham
A56: BS.APIC | B56: Tambahan modal disetor | C56: 1124816856453 | D56: 1124816856453 | E56: 1124816856453 | F56: 1124817000000 | G56: 1124817000000 | H56: 806384000000 | I56: kunci JSON: tambahan_modal
A57: BS.NCI_TXN_DIFF | B57: Selisih transaksi dengan kepentingan nonpengendali | G57: -1480000000 | H57: -1346000000 | I57: kunci JSON: selisih_nci
A58: BS.OCI_RES | B58: Penghasilan komprehensif lain | C58: 29748911906 | D58: 36805871185 | E58: 48720849663 | F58: 49353000000 | G58: 48543000000 | H58: 44355000000 | I58: kunci JSON: oci_ekuitas
A59: BS.RETAINED_EARN | B59: Saldo laba (defisit) (ditentukan + belum ditentukan penggunaannya) | C59: -600688806428 | D59: -435380567809 | E59: -479695516834 | F59: -518186000000 | G59: -541699000000 | H59: -740699000000 | I59: kunci JSON: saldo_laba
A60: BS.EQUITY_PARENT | B60: Ekuitas pemilik entitas induk | C60: =C55+C56+C57+C58+C59 -> 1753947506431 | D60: =D55+D56+D57+D58+D59 -> 1926312704329 | E60: =E55+E56+E57+E58+E59 -> 1893912733782 | F60: =F55+F56+F57+F58+F59 -> 1856055000000 | G60: =G55+G56+G57+G58+G59 -> 1830252000000 | H60: =H55+H56+H57+H58+H59 -> 1332590000000
A61: BS.NCI | B61: Kepentingan nonpengendali | C61: 788766333 | D61: 1089841354 | E61: 1225387334 | F61: 1402000000 | G61: 3052000000 | H61: 3135000000 | I61: kunci JSON: nci
A62: BS.TOTAL_EQUITY | B62: JUMLAH EKUITAS | C62: =C60+C61 -> 1754736272764 | D62: =D60+D61 -> 1927402545683 | E62: =E60+E61 -> 1895138121116 | F62: =F60+F61 -> 1857457000000 | G62: =G60+G61 -> 1833304000000 | H62: =H60+H61 -> 1335725000000
A63: BS.TOTAL_LIAB_EQUITY | B63: JUMLAH LIABILITAS DAN EKUITAS | C63: =C53+C62 -> 4346329088006 | D63: =D53+D62 -> 4871806608361 | E63: =E53+E62 -> 5749599247752 | F63: =F53+F62 -> 5606291000000 | G63: =G53+G62 -> 5683022000000 | H63: =H53+H62 -> 7623910000000
B64: MEMO (tidak dijumlahkan)
A65: BS.RE_APPROP_MEMO | B65: Memo: saldo laba ditentukan penggunaannya (tercetak) | C65: 2000000000 | D65: 2000000000 | E65: 7000000000 | F65: 7000000000 | G65: 7000000000 | H65: 7000000000 | I65: kunci JSON: saldo_laba_ditentukan
A66: BS.RE_UNAPPROP_MEMO | B66: Memo: saldo laba (defisit) belum ditentukan penggunaannya (tercetak) | C66: -602688806428 | D66: -437380567809 | E66: -486695516834 | F66: -525186000000 | G66: -548699000000 | H66: -747699000000 | I66: kunci JSON: saldo_laba_belum
B67: MEMO: SUBTOTAL TERCETAK DI LK
A68: BS.TOTAL_CA_PRINTED | B68: Jumlah aset lancar (tercetak) | C68: 939835506742 | D68: 1021454537372 | E68: 1445613598592 | F68: 998249000000 | G68: 832802000000 | H68: 2527917000000 | I68: kunci JSON: TOTAL_ASET_LANCAR
A69: BS.TOTAL_NCA_PRINTED | B69: Jumlah aset tidak lancar (tercetak) | C69: 3406493581264 | D69: 3850352070989 | E69: 4303985649160 | F69: 4608042000000 | G69: 4850220000000 | H69: 5095993000000 | I69: kunci JSON: TOTAL_ASET_TIDAK_LANCAR
A70: BS.TOTAL_ASSETS_PRINTED | B70: Jumlah aset (tercetak) | C70: 4346329088006 | D70: 4871806608361 | E70: 5749599247752 | F70: 5606291000000 | G70: 5683022000000 | H70: 7623910000000 | I70: kunci JSON: TOTAL_ASET
A71: BS.TOTAL_CL_PRINTED | B71: Liabilitas jangka pendek (tercetak) | C71: 1740988511325 | D71: 2659180898777 | E71: 2602765426046 | F71: 2105526000000 | G71: 2597046000000 | H71: 1610030000000 | I71: kunci JSON: TOTAL_LIAB_PENDEK
A72: BS.TOTAL_NCL_PRINTED | B72: Liabilitas jangka panjang (tercetak) | C72: 850604303917 | D72: 285223163901 | E72: 1251695700590 | F72: 1643308000000 | G72: 1252672000000 | H72: 4678155000000 | I72: kunci JSON: TOTAL_LIAB_PANJANG
A73: BS.TOTAL_LIAB_PRINTED | B73: Jumlah liabilitas (tercetak) | C73: 2591592815242 | D73: 2944404062678 | E73: 3854461126636 | F73: 3748834000000 | G73: 3849718000000 | H73: 6288185000000 | I73: kunci JSON: TOTAL_LIABILITAS
A74: BS.EQUITY_PARENT_PRINTED | B74: Ekuitas induk (tercetak) | C74: 1753947506431 | D74: 1926312704329 | E74: 1893912733782 | F74: 1856055000000 | G74: 1830252000000 | H74: 1332590000000 | I74: kunci JSON: EKUITAS_INDUK
A75: BS.TOTAL_EQUITY_PRINTED | B75: Jumlah ekuitas (tercetak) | C75: 1754736272764 | D75: 1927402545683 | E75: 1895138121116 | F75: 1857457000000 | G75: 1833304000000 | H75: 1335725000000 | I75: kunci JSON: TOTAL_EKUITAS
A76: BS.TOTAL_LIAB_EQUITY_PRINTED | B76: Jumlah liabilitas & ekuitas (tercetak) | C76: 4346329088006 | D76: 4871806608361 | E76: 5749599247752 | F76: 5606291000000 | G76: 5683022000000 | H76: 7623910000000 | I76: kunci JSON: TOTAL_LIAB_EKUITAS
B77: CEK
A78: BS.CHECK | B78: Aset - (liabilitas + ekuitas) = 0 | C78: =C27-C63 -> 0 | D78: =D27-D63 -> 0 | E78: =E27-E63 -> 0 | F78: =F27-F63 -> 0 | G78: =G27-G63 -> 0 | H78: =H27-H63 -> 0

Sheet CF
A1: Laporan Arus Kas - historis FY2021A-FY2025A
A2: Rp penuh. Biru = input dari SRAJ_seri_2020_2025.json (LK audited; 2023-2025 dari Rp juta), hitam = rumus. Tiap kolom dari LK tahun itu (dasar asli), kecuali 2024 = komparatif LK FY2025 disajikan kembali (Temuan S1-S2).
B3: Sumber kolom | C3: LK FY2020 (audit, Rp penuh) | D3: LK FY2021 (audit, Rp penuh) | E3: LK FY2022 (audit, Rp penuh) | F3: LK FY2023 (audit, Rp juta) | G3: LK FY2025 (komparatif disajikan kembali, Rp juta) | H3: LK FY2025 (audit, Rp juta) | I3: Catatan sumber: SRAJ (PT Sejahteraraya Anugrahjaya Tbk / Mayapada Hospital). Histori FY2020-FY2025 dari LK audit masing-masing tahun (dasar asli), kecuali 2024 dari komparatif LK FY2025
A4: Kode | B4: Akun | C4: FY2020A | D4: FY2021A | E4: FY2022A | F4: FY2023A | G4: FY2024A | H4: FY2025A | I4: Catatan / sumber
B5: ARUS KAS OPERASI
A6: CF.CASH_FROM_CUSTOMERS | B6: Penerimaan kas dari pelanggan | C6: 1206282381896 | D6: 1917035104557 | E6: 1932446236358 | F6: 2365859000000 | G6: 2274208000000 | H6: 2460965000000 | I6: kunci JSON: terima_pelanggan
A7: CF.CASH_TO_EMPLOYEES | B7: Pembayaran kas kepada karyawan | C7: -518122857052 | D7: -700717424697 | E7: -858868120858 | F7: -1126223000000 | G7: -556717000000 | H7: -669878000000 | I7: kunci JSON: bayar_karyawan
A8: CF.CASH_TO_SUPPLIERS | B8: Pembayaran kas kepada pemasok & lainnya | C8: -518399717152 | D8: -782054151603 | E8: -789221263965 | F8: -1058144000000 | G8: -1316325000000 | H8: -1506034000000 | I8: kunci JSON: bayar_pemasok
A9: CF.CASH_GEN | B9: Kas dari pelanggan dikurangi pembayaran operasi (subtotal model; tidak tercetak) | C9: =C6+C7+C8 -> 169759807692 | D9: =D6+D7+D8 -> 434263528257 | E9: =E6+E7+E8 -> 284356851535 | F9: =F6+F7+F8 -> 181492000000 | G9: =G6+G7+G8 -> 401166000000 | H9: =H6+H7+H8 -> 285053000000
A10: CF.FIN_INCOME_RECEIVED | B10: Penerimaan bunga | C10: 26470099827 | D10: 23940936423 | E10: 19404583424 | F10: 29050000000 | G10: 13483000000 | H10: 66897000000 | I10: kunci JSON: terima_bunga
A11: CF.FIN_COST_PAID | B11: Pembayaran bunga & beban keuangan | C11: -100262493441 | D11: -115124935079 | E11: -80404699161 | F11: -145447000000 | G11: -120996000000 | H11: -180398000000 | I11: kunci JSON: bayar_bunga
A12: CF.TAX_PAID | B12: Pembayaran pajak penghasilan | C12: -2085522676 | D12: -6292866811 | E12: -12881913537 | F12: -9178000000 | G12: -20405000000 | H12: -41882000000 | I12: kunci JSON: bayar_pajak
A13: CF.CFO | B13: Kas neto dari aktivitas operasi | C13: =C9+C10+C11+C12 -> 93881891402 | D13: =D9+D10+D11+D12 -> 336786662790 | E13: =E9+E10+E11+E12 -> 210474822261 | F13: =F9+F10+F11+F12 -> 55917000000 | G13: =G9+G10+G11+G12 -> 273248000000 | H13: =H9+H10+H11+H12 -> 129670000000
B14: ARUS KAS INVESTASI
A15: CF.CAPEX_PPE | B15: Perolehan aset tetap | C15: -544122343656 | D15: -464023277324 | E15: -569712834234 | F15: -570699000000 | G15: -525029000000 | H15: -579605000000 | I15: kunci JSON: perolehan_aset_tetap
A16: CF.PPE_ADVANCES | B16: Uang muka pembelian aset tetap | E16: -85833683046 | F16: -12833000000 | I16: kunci JSON: uang_muka_aset_tetap
A17: CF.CAPEX_INTANG | B17: Perolehan aset takberwujud | C17: -6697340640 | D17: -3165516135 | E17: -4343974611 | F17: -5066000000 | G17: -7568000000 | H17: -28217000000 | I17: kunci JSON: perolehan_atb
A18: CF.CAPEX_INVPROP | B18: Perolehan properti investasi | H18: -4685000000 | I18: kunci JSON: perolehan_properti
A19: CF.PPE_DISPOSAL_PROCEEDS | B19: Hasil penjualan aset tetap | C19: 108657000 | D19: 313000000 | E19: 294685224 | F19: 3208000000 | G19: 280000000 | H19: 357000000 | I19: kunci JSON: jual_aset_tetap
A20: CF.RP_REC_NET | B20: Piutang pihak berelasi - neto | D20: -1404495936 | E20: -18626561484 | I20: kunci JSON: piutang_rp_neto
A21: CF.CFI | B21: Kas neto untuk aktivitas investasi | C21: =C15+C16+C17+C18+C19+C20 -> -550711027296 | D21: =D15+D16+D17+D18+D19+D20 -> -468280289395 | E21: =E15+E16+E17+E18+E19+E20 -> -678222368151 | F21: =F15+F16+F17+F18+F19+F20 -> -585390000000 | G21: =G15+G16+G17+G18+G19+G20 -> -532317000000 | H21: =H15+H16+H17+H18+H19+H20 -> -612150000000
B22: ARUS KAS PENDANAAN
A23: CF.ST_BANK_DRAW | B23: Penerimaan pinjaman bank jangka pendek | C23: 171000000000 | D23: 390000000000 | E23: 36827459956 | F23: 11525000000 | I23: kunci JSON: bank_st_draw
A24: CF.ST_BANK_REPAY | B24: Pembayaran pinjaman bank jangka pendek | C24: -24678569749 | D24: -20000000000 | E24: -142490111313 | F24: -477247000000 | I24: kunci JSON: bank_st_repay
A25: CF.LT_BANK_DRAW | B25: Penerimaan utang bank jangka panjang | C25: 830000000000 | D25: 220000000000 | E25: 100000000000 | G25: 288607000000 | H25: 136758000000 | I25: kunci JSON: bank_lt_draw
A26: CF.LT_BANK_REPAY | B26: Pembayaran utang bank jangka panjang | C26: -134309028160 | D26: -839428499944 | E26: -57661026547 | F26: -80956000000 | G26: -251795000000 | H26: -83663000000 | I26: kunci JSON: bank_lt_repay
A27: CF.LOAN_DRAW | B27: Penerimaan pinjaman lembaga keuangan non-bank | F27: 481631000000 | H27: 407900000000 | I27: kunci JSON: pinjaman_draw
A28: CF.LOAN_REPAY | B28: Pembayaran pinjaman lembaga keuangan non-bank | F28: -6021000000 | G28: -24083000000 | H28: -42998000000 | I28: kunci JSON: pinjaman_repay
A29: CF.BOND_DRAW | B29: Penerbitan surat utang / obligasi | E29: 950000000000 | H29: 1947031000000 | I29: kunci JSON: obligasi_draw
A30: CF.BOND_REPAY | B30: Pelunasan surat utang / obligasi | H30: -407900000000 | I30: kunci JSON: obligasi_repay
A31: CF.FIN_LEASE_PAID | B31: Pembayaran utang pembiayaan | D31: -174990000 | E31: -1596885161 | F31: -1821000000 | G31: -2284000000 | H31: -431000000 | I31: kunci JSON: bayar_sewa_pemb
A32: CF.OTHER_PAY_PAID | B32: Penerimaan (pembayaran) utang lain-lain pihak berelasi | C32: 342308233436 | D32: 428841753085 | H32: -435044000000 | I32: kunci JSON: bayar_utang_lain
A33: CF.SHARE_ISSUE | B33: Penerbitan saham (2025) | H33: 521696000000 | I33: kunci JSON: terbit_saham
A34: CF.RESTRICTED_CASH | B34: Dana yang dibatasi penggunaannya | H34: -18310000000 | I34: kunci JSON: dana_dibatasi
A35: CF.LEASE_PAID | B35: Pembayaran liabilitas sewa | C35: -330000000000 | F35: -707000000 | G35: -708000000 | H35: -1599000000 | I35: kunci JSON: bayar_sewa
A36: CF.DIVIDENDS_PAID | B36: Pembayaran dividen tunai (pemilik entitas induk; tidak ada) | I36: kunci JSON: -
A37: CF.CFF | B37: Kas neto dari (untuk) aktivitas pendanaan | C37: =C23+C24+C25+C26+C27+C28+C29+C30+C31+C32+C33+C34+C35+C36 -> 854320635527 | D37: =D23+D24+D25+D26+D27+D28+D29+D30+D31+D32+D33+D34+D35+D36 -> 179238263141 | E37: =E23+E24+E25+E26+E27+E28+E29+E30+E31+E32+E33+E34+E35+E36 -> 885079436935 | F37: =F23+F24+F25+F26+F27+F28+F29+F30+F31+F32+F33+F34+F35+F36 -> -73596000000 | G37: =G23+G24+G25+G26+G27+G28+G29+G30+G31+G32+G33+G34+G35+G36 -> 9737000000 | H37: =H23+H24+H25+H26+H27+H28+H29+H30+H31+H32+H33+H34+H35+H36 -> 2023440000000
A38: CF.NET_CHANGE | B38: Kenaikan (penurunan) neto kas | C38: =C13+C21+C37 -> 397491499633 | D38: =D13+D21+D37 -> 47744636536 | E38: =E13+E21+E37 -> 417331891045 | F38: =F13+F21+F37 -> -603069000000 | G38: =G13+G21+G37 -> -249332000000 | H38: =H13+H21+H37 -> 1540960000000
A39: CF.FX | B39: Efek perubahan kurs pada kas | H39: 37264000000 | I39: kunci JSON: efek_kurs
A40: CF.CASH_BEGIN | B40: Kas awal tahun (definisi LAK) | C40: 232117189241 | D40: 653177723083 | E40: 700922359619 | F40: 1118254000000 | G40: 497371000000 | H40: 248039000000 | I40: kunci JSON: KAS_AWAL
A41: CF.CASH_END | B41: Kas akhir tahun (definisi LAK) | C41: =C38+C39+C40 -> 629608688874 | D41: =D38+D39+D40 -> 700922359619 | E41: =E38+E39+E40 -> 1118254250664 | F41: =F38+F39+F40 -> 515185000000 | G41: =G38+G39+G40 -> 248039000000 | H41: =H38+H39+H40 -> 1826263000000
B42: MEMO: REKONSILIASI DEFINISI KAS (tidak dijumlahkan; Temuan S5)
A43: CF.RECON_BEGIN_MEMO | B43: Memo: kas awal LAK -> kas neraca akhir tahun lalu (selisih definisi/penyajian kembali) | D43: -23569034209 | G43: 17814000000 | H43: 29169000000 | I43: kunci JSON: rekon_kas_awal
A44: CF.RECON_END_MEMO | B44: Memo: kas akhir LAK -> kas neraca (cerukan / pinjaman bank jangka pendek di kas LAK) | G44: 29169000000 | I44: kunci JSON: rekon_kas_akhir
B45: MEMO: SUBTOTAL TERCETAK DI LK
A46: CF.CFO_PRINTED | B46: Kas neto operasi (tercetak) | C46: 93881891402 | D46: 336786662790 | E46: 210474822261 | F46: 55917000000 | G46: 273248000000 | H46: 129670000000 | I46: kunci JSON: NET_OPERASI
A47: CF.CFI_PRINTED | B47: Kas neto investasi (tercetak) | C47: -550711027296 | D47: -468280289395 | E47: -678222368151 | F47: -585390000000 | G47: -532317000000 | H47: -612150000000 | I47: kunci JSON: NET_INVESTASI
A48: CF.CFF_PRINTED | B48: Kas neto pendanaan (tercetak) | C48: 854320635527 | D48: 179238263141 | E48: 885079436934 | F48: -73596000000 | G48: 9737000000 | H48: 2023440000000 | I48: kunci JSON: NET_PENDANAAN
A49: CF.NET_CHANGE_PRINTED | B49: Kenaikan neto kas (tercetak) | C49: 397491499633 | D49: 47744636536 | E49: 417331891045 | F49: -603069000000 | G49: -249332000000 | H49: 1540960000000 | I49: kunci JSON: KENAIKAN_NETO
A50: CF.CASH_END_PRINTED | B50: Kas akhir (tercetak) | C50: 629608688874 | D50: 700922359619 | E50: 1118254250664 | F50: 515185000000 | G50: 248039000000 | H50: 1826263000000 | I50: kunci JSON: KAS_AKHIR

Sheet Schedules
A1: Schedules CALK FY2020A-FY2025A
A2: Rincian catatan atas LK (tahapD per tahun, Rp penuh). Bagian A = ringkasan yang dipakai Rasio/Asumsi; bagian B-C = rincian lengkap. Kosong = tidak diungkap tahun itu; FY2020-2025 dari CALK LK tahun itu sendiri (2024 dari LK FY2025 bila diungkap). Nomor catatan LK SRAJ: aset tetap Cat aset tetap, pendapatan Cat 26, beban pokok 27, beban usaha 28, pendapatan lain-lain neto 30. Akumulasi penyusutan dicatat bertanda negatif.
B3: Sumber kolom | C3: LK FY2020 (audit, Rp penuh) | D3: LK FY2021 (audit, Rp penuh) | E3: LK FY2022 (audit, Rp penuh) | F3: LK FY2023 (audit, Rp juta) | G3: LK FY2025 (komparatif disajikan kembali, Rp juta) | H3: LK FY2025 (audit, Rp juta)
A4: Kode | B4: Akun | C4: FY2020A | D4: FY2021A | E4: FY2022A | F4: FY2023A | G4: FY2024A | H4: FY2025A | I4: Catatan / sumber
B5: A. RINGKASAN UNTUK MODEL (rumus dari bagian B-C)
A6: REV.MED | B6: Pendapatan - obat & perlengkapan medis (rawat inap + rawat jalan) | C6: =N(C60)+N(C48)+N(C53) -> 253936863405 | D6: =N(D60)+N(D48)+N(D53) -> 417781280603 | E6: =N(E60)+N(E48)+N(E53) -> 431771186720 | F6: =N(F60)+N(F48)+N(F53) -> 754584000000 | G6: =N(G60)+N(G48)+N(G53) -> 1164022000000 | H6: =N(H60)+N(H48)+N(H53) -> 1291720000000 | I6: Cat 26
A7: REV.INPAT | B7: Pendapatan - rawat inap (jasa, penunjang, kamar & ruang operasi, administrasi) | C7: =N(C59)+N(C49)+N(C50)+N(C51)+N(C52) -> 467640506965 | D7: =N(D59)+N(D49)+N(D50)+N(D51)+N(D52) -> 753471843387 | E7: =N(E59)+N(E49)+N(E50)+N(E51)+N(E52) -> 817003131432 | F7: =N(F59)+N(F49)+N(F50)+N(F51)+N(F52) -> 1065433000000 | G7: =N(G59)+N(G49)+N(G50)+N(G51)+N(G52) -> 1332597000000 | H7: =N(H59)+N(H49)+N(H50)+N(H51)+N(H52) -> 1400293000000 | I7: Cat 26
A8: REV.OUTPAT | B8: Pendapatan - rawat jalan & penunjang (poliklinik, laboratorium, radiologi, pemeriksaan, hemodialisa) | C8: =N(C61)+N(C62)+N(C63)+N(C64)+N(C65)+N(C54)+N(C55)+N(C56) -> 596525411320 | D8: =N(D61)+N(D62)+N(D63)+N(D64)+N(D65)+N(D54)+N(D55)+N(D56) -> 788732235692 | E8: =N(E61)+N(E62)+N(E63)+N(E64)+N(E65)+N(E54)+N(E55)+N(E56) -> 704457503479 | F8: =N(F61)+N(F62)+N(F63)+N(F64)+N(F65)+N(F54)+N(F55)+N(F56) -> 683157000000 | G8: =N(G61)+N(G62)+N(G63)+N(G64)+N(G65)+N(G54)+N(G55)+N(G56) -> 651726000000 | H8: =N(H61)+N(H62)+N(H63)+N(H64)+N(H65)+N(H54)+N(H55)+N(H56) -> 809565000000 | I8: Cat 26
A9: REV.OTHER | B9: Lainnya: diskon pasien / pengurang jasa tenaga ahli (agen, PSAK 115; 2024-25) = jumlah tercetak - 3 kelompok | C9: =N(C58)-C6-C7-C8 -> -34304172516 | D9: =N(D58)-D6-D7-D8 -> -35532218704 | E9: =N(E58)-E6-E7-E8 -> -19068140667 | F9: =N(F58)-F6-F7-F8 -> 0 | G9: =N(G58)-G6-G7-G8 -> -807914000000 | H9: =N(H58)-H6-H7-H8 -> -912138000000 | I9: Cat 26; diturunkan
A10: REV.NET | B10: Pendapatan (rumus) | C10: =C6+C7+C8+C9 -> 1283798609174 | D10: =D6+D7+D8+D9 -> 1924453140978 | E10: =E6+E7+E8+E9 -> 1934163680964 | F10: =F6+F7+F8+F9 -> 2503174000000 | G10: =G6+G7+G8+G9 -> 2340431000000 | H10: =H6+H7+H8+H9 -> 2589440000000
A11: REV.MED_SH | B11: Porsi obat & perlengkapan medis % pendapatan | C11: =IFERROR(C6/C10,0) -> 0.19780117 | D11: =IFERROR(D6/D10,0) -> 0.21709091 | E11: =IFERROR(E6/E10,0) -> 0.22323405 | F11: =IFERROR(F6/F10,0) -> 0.30145088 | G11: =IFERROR(G6/G10,0) -> 0.49735369 | H11: =IFERROR(H6/H10,0) -> 0.49884145
A12: DA.DEP_IN_COGS | B12: Penyusutan aset tetap di beban pokok (Cat 27) | C12: =N(C71) -> 84019999072 | D12: =N(D71) -> 111052598370 | E12: =N(E71) -> 149028787879 | F12: =N(F71) -> 193944000000 | G12: =N(G71) -> 225642000000 | H12: =N(H71) -> 261685000000 | I12: Cat 27
A13: DA.IN_OPEX | B13: Penyusutan aset tetap di beban usaha (Cat 28) | C13: =N(C89) -> 18983030015 | D13: =N(D89) -> 38462510464 | E13: =N(E89) -> 51029747812 | F13: =N(F89) -> 61901000000 | G13: =N(G89) -> 65940000000 | H13: =N(H89) -> 76121000000 | I13: Cat 28
A14: DA.PPE | B14: Penyusutan aset tetap (Cat 27 + 28) | C14: =C12+C13 -> 103003029087 | D14: =D12+D13 -> 149515108834 | E14: =E12+E13 -> 200058535691 | F14: =F12+F13 -> 255845000000 | G14: =G12+G13 -> 291582000000 | H14: =H12+H13 -> 337806000000
A15: DA.MUT | B15: Penyusutan menurut mutasi Cat aset tetap (-akumulasi: penambahan) | C15: =-C39 -> 103003029087 | D15: =-D39 -> 149515108834 | E15: =-E39 -> 200058535691 | F15: =-F39 -> 255845000000 | G15: =-G39 -> 291582000000 | H15: =-H39 -> 337806000000
A16: DA.ROU | B16: Penyusutan aset hak guna (Cat 27 + 28) | C16: =N(C75)+N(C103) -> 27179061135 | D16: =N(D75)+N(D103) -> 27179061135 | E16: =N(E75)+N(E103) -> 27179061135 | F16: =N(F75)+N(F103) -> 27450000000 | G16: =N(G75)+N(G103) -> 27395000000 | H16: =N(H75)+N(H103) -> 28058000000 | I16: Cat 27-28
A17: DA.AMORT_COGS | B17: Amortisasi aset takberwujud di beban pokok (tidak ada) | C17: =0 -> 0 | D17: =0 -> 0 | E17: =0 -> 0 | F17: =0 -> 0 | G17: =0 -> 0 | H17: =0 -> 0 | I17: tidak ada
A18: DA.AMORT_OPEX | B18: Amortisasi aset takberwujud di beban usaha (Cat 28) | C18: =N(C98) -> 2375476567 | D18: =N(D98) -> 4496436472 | E18: =N(E98) -> 6296293019 | F18: =N(F98) -> 5982000000 | G18: =N(G98) -> 7725000000 | H18: =N(H98) -> 15387000000 | I18: Cat 28
A19: DA.SOFTWARE | B19: Amortisasi aset takberwujud (Cat 27 + 28) | C19: =C17+C18 -> 2375476567 | D19: =D17+D18 -> 4496436472 | E19: =E17+E18 -> 6296293019 | F19: =F17+F18 -> 5982000000 | G19: =G17+G18 -> 7725000000 | H19: =H17+H18 -> 15387000000 | I19: Cat 28
A20: DA.TOTAL | B20: Total D&A (untuk EBITDA) | C20: =C14+C16+C19 -> 132557566789 | D20: =D14+D16+D19 -> 181190606441 | E20: =E14+E16+E19 -> 233533889845 | F20: =F14+F16+F19 -> 289277000000 | G20: =G14+G16+G19 -> 326702000000 | H20: =H14+H16+H19 -> 381251000000
A21: PPE.ADDITIONS | B21: Penambahan aset tetap (biaya perolehan, kas + nonkas) | C21: =C31 -> 694049164865 | D21: =D31 -> 601679274728 | E21: =E31 -> 640084702166 | F21: =F31 -> 601110000000 | G21: =G31 -> 510170000000 | H21: =H31 -> 509834000000
A22: EPS.WSH | B22: Rata-rata tertimbang saham beredar - dasar (lembar) | C22: =C150 -> 12000705445 | D22: =D150 -> 12000705445 | E22: =E150 -> 12000705445 | F22: =F150 -> 12000705445 | G22: =G150 -> 12000705445 | H22: =H150 -> 12202405868 | I22: Cat laba per saham
B27: B. MUTASI ASET TETAP (Cat aset tetap, baris JUMLAH tabel mutasi; model biaya; aset hak guna disajikan terpisah)
B28: Cat aset tetap Aset tetap - biaya perolehan (JUMLAH)
A29: MUT.COST_T.saldo_awal | B29: Saldo awal | C29: 2685348464215 | D29: 3448224531705 | E29: 4045883925132 | F29: 4679439000000 | G29: 5275928000000 | H29: 5763879000000 | I29: mutasi_aset (biaya perolehan)
A30: MUT.COST_T.akuisisi | B30: Akuisisi entitas anak | C30: 0 | D30: 0 | E30: 0 | F30: 0 | G30: 0 | H30: 0
A31: MUT.COST_T.penambahan | B31: Penambahan | C31: 694049164865 | D31: 601679274728 | E31: 640084702166 | F31: 601110000000 | G31: 510170000000 | H31: 509834000000
A32: MUT.COST_T.pengurangan | B32: Pengurangan | C32: -7574885290 | D32: -4019881301 | E32: -6528886382 | F32: -9829000000 | G32: -22219000000 | H32: -67349000000
A33: MUT.COST_T.reklasifikasi | B33: Reklasifikasi | C33: 0 | D33: 0 | E33: 0 | F33: 5208000000 | G33: 0 | H33: 0
A34: MUT.COST_T.saldo_akhir | B34: Saldo akhir (tercetak) | C34: 3371822743790 | D34: 4045883925132 | E34: 4679439740916 | F34: 5275928000000 | G34: 5763879000000 | H34: 6206364000000
A35: MUT.COST_T.END | B35: Saldo akhir (rumus: awal + akuisisi + penambahan + pengurangan + reklas) | C35: =C29+N(C30)+C31+C32+C33 -> 3371822743790 | D35: =D29+N(D30)+D31+D32+D33 -> 4045883925132 | E35: =E29+N(E30)+E31+E32+E33 -> 4679439740916 | F35: =F29+N(F30)+F31+F32+F33 -> 5275928000000 | G35: =G29+N(G30)+G31+G32+G33 -> 5763879000000 | H35: =H29+N(H30)+H31+H32+H33 -> 6206364000000
B36: Cat aset tetap Aset tetap - akumulasi penyusutan (JUMLAH; bertanda negatif)
A37: MUT.AD_T.saldo_awal | B37: Saldo awal | C37: -629006272888 | D37: -730207203768 | E37: -876108331302 | F37: -1072297000000 | G37: -1323616000000 | H37: -1599739000000 | I37: mutasi_aset (akumulasi penyusutan)
A38: MUT.AD_T.akuisisi | B38: Akuisisi entitas anak | C38: 0 | D38: 0 | E38: 0 | F38: 0 | G38: 0 | H38: 0
A39: MUT.AD_T.penambahan | B39: Penambahan | C39: -103003029087 | D39: -149515108834 | E39: -200058535691 | F39: -255845000000 | G39: -291582000000 | H39: -337806000000
A40: MUT.AD_T.pengurangan | B40: Pengurangan | C40: 1800014874 | D40: 3613981300 | E40: 3869290067 | F40: 6215000000 | G40: 15459000000 | H40: 17508000000
A41: MUT.AD_T.reklasifikasi | B41: Reklasifikasi | C41: 0 | D41: 0 | E41: 0 | F41: -1689000000 | G41: 0 | H41: 0
A42: MUT.AD_T.saldo_akhir | B42: Saldo akhir (tercetak) | C42: -730209287101 | D42: -876108331302 | E42: -1072297576926 | F42: -1323616000000 | G42: -1599739000000 | H42: -1920037000000
A43: MUT.AD_T.END | B43: Saldo akhir (rumus: awal + akuisisi + penambahan + pengurangan + reklas) | C43: =C37+N(C38)+C39+C40+C41 -> -730209287101 | D43: =D37+N(D38)+D39+D40+D41 -> -876108331302 | E43: =E37+N(E38)+E39+E40+E41 -> -1072297576926 | F43: =F37+N(F38)+F39+F40+F41 -> -1323616000000 | G43: =G37+N(G38)+G39+G40+G41 -> -1599739000000 | H43: =H37+N(H38)+H39+H40+H41 -> -1920037000000
A44: PPE.NBV | B44: Nilai tercatat aset tetap (biaya + akumulasi bertanda negatif) | C44: =C34+C42 -> 2641613456689 | D44: =D34+D42 -> 3169775593830 | E44: =E34+E42 -> 3607142163990 | F44: =F34+F42 -> 3952312000000 | G44: =G34+G42 -> 4164140000000 | H44: =H34+H42 -> 4286327000000
B46: C. RINCIAN CATATAN (urut catatan LK)
B47: Cat 26 - Pendapatan
A48: CK001 | B48: Rawat inap - Obat dan perlengkapan medis | F48: 494344000000 | G48: 627524000000 | H48: 682662000000 | I48: hal PDF None
A49: CK002 | B49: Rawat inap - Jasa tenaga ahli | F49: 480804000000 | G49: 591952000000 | H49: 646735000000 | I49: hal PDF None
A50: CK003 | B50: Rawat inap - Layanan penunjang medis | F50: 312261000000 | G50: 365347000000 | H50: 381421000000 | I50: hal PDF None
A51: CK004 | B51: Rawat inap - Kamar rawat inap dan ruang operasi | F51: 226561000000 | G51: 320854000000 | H51: 289631000000 | I51: hal PDF None
A52: CK005 | B52: Rawat inap - Administrasi | F52: 45807000000 | G52: 54444000000 | H52: 82506000000 | I52: hal PDF None
A53: CK006 | B53: Rawat jalan - Obat dan perlengkapan medis | F53: 260240000000 | G53: 536498000000 | H53: 609058000000 | I53: hal PDF None
A54: CK007 | B54: Rawat jalan - Jasa tenaga ahli | F54: 389546000000 | G54: 338776000000 | H54: 431289000000 | I54: hal PDF None
A55: CK008 | B55: Rawat jalan - Layanan penunjang medis | F55: 264539000000 | G55: 275330000000 | H55: 333142000000 | I55: hal PDF None
A56: CK009 | B56: Rawat jalan - Administrasi | F56: 29072000000 | G56: 37620000000 | H56: 45134000000 | I56: hal PDF None
A57: CK010 | B57: Dikurangi: biaya jasa tenaga ahli (agen, PSAK 115) | G57: -807914000000 | H57: -912138000000 | I57: hal PDF None
A58: CK011 | B58: JUMLAH (lapor) | C58: 1283798609174 | D58: 1924453140978 | E58: 1934163680964 | F58: 2503174000000 | G58: 2340431000000 | H58: 2589440000000 | I58: hal PDF None
A59: CK012 | B59: Rawat inap | C59: 467640506965 | D59: 753471843387 | E59: 817003131432 | I59: hal PDF None
A60: CK013 | B60: Obat-obatan | C60: 253936863405 | D60: 417781280603 | E60: 431771186720 | I60: hal PDF None
A61: CK014 | B61: Poliklinik | C61: 202306035034 | D61: 264925183181 | E61: 274869160543 | I61: hal PDF None
A62: CK015 | B62: Laboratorium | C62: 277355030730 | D62: 375603580623 | E62: 255930627005 | I62: hal PDF None
A63: CK016 | B63: Radiologi | C63: 65311157335 | D63: 99318704278 | E63: 116524563580 | I63: hal PDF None
A64: CK017 | B64: Pemeriksaan medis | C64: 31961173808 | D64: 24610350166 | E64: 29019651480 | I64: hal PDF None
A65: CK018 | B65: Hemodialisa | C65: 19592014413 | D65: 24274417444 | E65: 28113500871 | I65: hal PDF None
A66: CK019 | B66: Diskon pasien | C66: -34304172516 | D66: -35532218704 | E66: -19068140667 | I66: hal PDF None
A67: SK001 | B67: Σ rincian (rumus) | C67: =N(C48)+N(C49)+N(C50)+N(C51)+N(C52)+N(C53)+N(C54)+N(C55)+N(C56)+N(C57)+N(C59)+N(C60)+N(C61)+N(C62)+N(C63)+N(C64)+N(C65)+N(C66) -> 1283798609174 | D67: =N(D48)+N(D49)+N(D50)+N(D51)+N(D52)+N(D53)+N(D54)+N(D55)+N(D56)+N(D57)+N(D59)+N(D60)+N(D61)+N(D62)+N(D63)+N(D64)+N(D65)+N(D66) -> 1924453140978 | E67: =N(E48)+N(E49)+N(E50)+N(E51)+N(E52)+N(E53)+N(E54)+N(E55)+N(E56)+N(E57)+N(E59)+N(E60)+N(E61)+N(E62)+N(E63)+N(E64)+N(E65)+N(E66) -> 1934163680964 | F67: =N(F48)+N(F49)+N(F50)+N(F51)+N(F52)+N(F53)+N(F54)+N(F55)+N(F56)+N(F57)+N(F59)+N(F60)+N(F61)+N(F62)+N(F63)+N(F64)+N(F65)+N(F66) -> 2503174000000 | G67: =N(G48)+N(G49)+N(G50)+N(G51)+N(G52)+N(G53)+N(G54)+N(G55)+N(G56)+N(G57)+N(G59)+N(G60)+N(G61)+N(G62)+N(G63)+N(G64)+N(G65)+N(G66) -> 2340431000000 | H67: =N(H48)+N(H49)+N(H50)+N(H51)+N(H52)+N(H53)+N(H54)+N(H55)+N(H56)+N(H57)+N(H59)+N(H60)+N(H61)+N(H62)+N(H63)+N(H64)+N(H65)+N(H66) -> 2589440000000
B68: Cat 27 - Beban pokok pendapatan
A69: CK020 | B69: Obat dan perlengkapan medis | G69: 632856000000 | H69: 730391000000 | I69: hal PDF None
A70: CK021 | B70: Gaji dan tunjangan | C70: 94151640132 | D70: 139434588806 | E70: 178767908884 | F70: 228430000000 | G70: 278152000000 | H70: 277365000000 | I70: hal PDF None
A71: CK022 | B71: Penyusutan | C71: 84019999072 | D71: 111052598370 | E71: 149028787879 | F71: 193944000000 | G71: 225642000000 | H71: 261685000000 | I71: hal PDF None
A72: CK023 | B72: Kamar rawat inap | F72: 96494000000 | G72: 118922000000 | H72: 85142000000 | I72: hal PDF None
A73: CK024 | B73: Layanan penunjang medis | F73: 49998000000 | G73: 63386000000 | H73: 69869000000 | I73: hal PDF None
A74: CK025 | B74: Pasien rawat jalan | F74: 34788000000 | G74: 69964000000 | H74: 80306000000 | I74: hal PDF None
A75: CK026 | B75: Penyusutan aset hak guna | C75: 18378409513 | D75: 18378409513 | E75: 18378409513 | F75: 18378000000 | G75: 18525000000 | H75: 18973000000 | I75: hal PDF None
A76: CK027 | B76: Jasa tenaga ahli | G76: 16541000000 | H76: 6833000000 | I76: hal PDF None
A77: CK028 | B77: JUMLAH (lapor) | C77: 864698280519 | D77: 1219420404326 | E77: 1377109387379 | F77: 1785154000000 | G77: 1423988000000 | H77: 1530564000000 | I77: hal PDF None
A78: CK029 | B78: Jasa dokter | C78: 255673214045 | D78: 365894592513 | E78: 481880938211 | F78: 672126000000 | I78: hal PDF None
A79: CK030 | B79: Obat-obatan | C79: 107522125465 | D79: 189986508260 | E79: 183278794685 | F79: 490996000000 | I79: hal PDF None
A80: CK031 | B80: Beban pasien rawat inap | C80: 115642159760 | D80: 132129711402 | E80: 160368000858 | I80: hal PDF None
A81: CK032 | B81: Poliklinik | C81: 75567244808 | D81: 118194588834 | E81: 104817649529 | I81: hal PDF None
A82: CK033 | B82: Laboratorium | C82: 107641067638 | D82: 124437522136 | E82: 79199047177 | I82: hal PDF None
A83: CK034 | B83: Hemodialisa | C83: 1782870474 | D83: 11915524107 | E83: 15919398340 | I83: hal PDF None
A84: CK035 | B84: Radiologi | C84: 4319549612 | D84: 7996360385 | E84: 5470452303 | I84: hal PDF None
A85: SK002 | B85: Σ rincian (rumus) | C85: =N(C69)+N(C70)+N(C71)+N(C72)+N(C73)+N(C74)+N(C75)+N(C76)+N(C78)+N(C79)+N(C80)+N(C81)+N(C82)+N(C83)+N(C84) -> 864698280519 | D85: =N(D69)+N(D70)+N(D71)+N(D72)+N(D73)+N(D74)+N(D75)+N(D76)+N(D78)+N(D79)+N(D80)+N(D81)+N(D82)+N(D83)+N(D84) -> 1219420404326 | E85: =N(E69)+N(E70)+N(E71)+N(E72)+N(E73)+N(E74)+N(E75)+N(E76)+N(E78)+N(E79)+N(E80)+N(E81)+N(E82)+N(E83)+N(E84) -> 1377109387379 | F85: =N(F69)+N(F70)+N(F71)+N(F72)+N(F73)+N(F74)+N(F75)+N(F76)+N(F78)+N(F79)+N(F80)+N(F81)+N(F82)+N(F83)+N(F84) -> 1785154000000 | G85: =N(G69)+N(G70)+N(G71)+N(G72)+N(G73)+N(G74)+N(G75)+N(G76)+N(G78)+N(G79)+N(G80)+N(G81)+N(G82)+N(G83)+N(G84) -> 1423988000000 | H85: =N(H69)+N(H70)+N(H71)+N(H72)+N(H73)+N(H74)+N(H75)+N(H76)+N(H78)+N(H79)+N(H80)+N(H81)+N(H82)+N(H83)+N(H84) -> 1530564000000
B86: Cat 28 - Beban usaha
A87: CK036 | B87: Gaji dan tunjangan | C87: 164719380302 | D87: 192508348302 | E87: 198219273763 | F87: 219840000000 | G87: 257565000000 | H87: 380930000000 | I87: hal PDF None
A88: CK037 | B88: Jasa profesional | C88: 17520329209 | D88: 29331860054 | E88: 33119976143 | F88: 34372000000 | G88: 40273000000 | H88: 89043000000 | I88: hal PDF None
A89: CK038 | B89: Penyusutan | C89: 18983030015 | D89: 38462510464 | E89: 51029747812 | F89: 61901000000 | G89: 65940000000 | H89: 76121000000 | I89: hal PDF None
A90: CK039 | B90: Keamanan dan kebersihan | C90: 30690974480 | D90: 30618359408 | E90: 38144930006 | F90: 53224000000 | G90: 60698000000 | H90: 68667000000 | I90: hal PDF None
A91: CK040 | B91: Utilitas | D91: 32653358800 | E91: 38556418849 | F91: 45760000000 | G91: 49664000000 | H91: 52139000000 | I91: hal PDF None
A92: CK041 | B92: Perbaikan dan pemeliharaan | C92: 20905888279 | D92: 23689258082 | E92: 25042880282 | F92: 27572000000 | G92: 37415000000 | H92: 50290000000 | I92: hal PDF None
A93: CK042 | B93: Imbalan kerja | C93: 28565266736 | D93: 21831554389 | E93: 10903101831 | G93: 25951000000 | H93: 41051000000 | I93: hal PDF None
A94: CK043 | B94: Jamsostek | C94: 9283706794 | D94: 14500539037 | E94: 18229759864 | F94: 21196000000 | G94: 24203000000 | H94: 24748000000 | I94: hal PDF None
A95: CK044 | B95: Keperluan kantor | C95: 2454488872 | D95: 3087370579 | E95: 3409417356 | F95: 6601000000 | G95: 18627000000 | H95: 19408000000 | I95: hal PDF None
A96: CK045 | B96: Konsumsi | C96: 9928330977 | D96: 11066788766 | E96: 10588480914 | F96: 12119000000 | G96: 16247000000 | H96: 17081000000 | I96: hal PDF None
A97: CK046 | B97: Pengobatan | C97: 20456817125 | D97: 21471023128 | E97: 19272568449 | F97: 15434000000 | G97: 21901000000 | H97: 16555000000 | I97: hal PDF None
A98: CK047 | B98: Amortisasi aset tak berwujud | C98: 2375476567 | D98: 4496436472 | E98: 6296293019 | F98: 5982000000 | G98: 7725000000 | H98: 15387000000 | I98: hal PDF None
A99: CK048 | B99: Asuransi | C99: 5348628251 | D99: 5805588885 | E99: 7272991554 | F99: 8296000000 | G99: 9661000000 | H99: 13067000000 | I99: hal PDF None
A100: CK049 | B100: Pelatihan | C100: 2061009985 | D100: 2623400230 | E100: 3904332786 | F100: 6389000000 | G100: 10141000000 | H100: 11206000000 | I100: hal PDF None
A101: CK050 | B101: Perizinan dan pajak | G101: 11607000000 | H101: 11192000000 | I101: hal PDF None
A102: CK051 | B102: Transportasi dan perjalanan dinas | G102: 6908000000 | H102: 9826000000 | I102: hal PDF None
A103: CK052 | B103: Penyusutan aset hak guna | C103: 8800651622 | D103: 8800651622 | E103: 8800651622 | F103: 9072000000 | G103: 8870000000 | H103: 9085000000 | I103: hal PDF None
A104: CK053 | B104: Beban bank | C104: 3609618368 | D104: 4410794478 | E104: 4531517063 | F104: 5557000000 | G104: 7318000000 | H104: 7375000000 | I104: hal PDF None
A105: CK054 | B105: Lain-lain (dibawah Rp2.000) | G105: 8433000000 | H105: 9161000000 | I105: hal PDF None
...

Sheet Rasio
A1: Rasio keuangan FY2021A-FY2025A
A2: Rumus dari IS/BS/CF/Schedules. Rata-rata saldo & pertumbuhan mulai 2021; rasio berbasis CALK (EBITDA, D&A) kosong untuk 2020. Kolom rata-rata = FY2022-FY2025.
A4: Kode | B4: Akun | C4: FY2020A | D4: FY2021A | E4: FY2022A | F4: FY2023A | G4: FY2024A | H4: FY2025A | I4: Rata-rata FY2022-25 | J4: Definisi / catatan
B5: PERTUMBUHAN (yoy)
A6: R.G_REV | B6: Pendapatan | D6: =IFERROR(IS!D6/IS!C6-1,0) -> 0.4990304 | E6: =IFERROR(IS!E6/IS!D6-1,0) -> 0.0050458698 | F6: =IFERROR(IS!F6/IS!E6-1,0) -> 0.29418933 | G6: =IFERROR(IS!G6/IS!F6-1,0) -> -0.065014657 | H6: =IFERROR(IS!H6/IS!G6-1,0) -> 0.10639451 | I6: =AVERAGE(E6:H6) -> 0.085153762
A7: R.G_MED | B7: Obat & perlengkapan medis | D7: =IFERROR(Schedules!D6/Schedules!C6-1,0) -> 0.64521714 | E7: =IFERROR(Schedules!E6/Schedules!D6-1,0) -> 0.033486197 | F7: =IFERROR(Schedules!F6/Schedules!E6-1,0) -> 0.74764788 | G7: =IFERROR(Schedules!G6/Schedules!F6-1,0) -> 0.54260096 | H7: =IFERROR(Schedules!H6/Schedules!G6-1,0) -> 0.10970411 | I7: =AVERAGE(E7:H7) -> 0.35835979
A8: R.G_INPAT | B8: Rawat inap (jasa, kamar, penunjang) | D8: =IFERROR(Schedules!D7/Schedules!C7-1,0) -> 0.61122023 | E8: =IFERROR(Schedules!E7/Schedules!D7-1,0) -> 0.084318065 | F8: =IFERROR(Schedules!F7/Schedules!E7-1,0) -> 0.30407456 | G8: =IFERROR(Schedules!G7/Schedules!F7-1,0) -> 0.25075627 | H8: =IFERROR(Schedules!H7/Schedules!G7-1,0) -> 0.050800054 | I8: =AVERAGE(E8:H8) -> 0.17248724
A9: R.G_OUTPAT | B9: Rawat jalan & penunjang | D9: =IFERROR(Schedules!D8/Schedules!C8-1,0) -> 0.32221062 | E9: =IFERROR(Schedules!E8/Schedules!D8-1,0) -> -0.10684834 | F9: =IFERROR(Schedules!F8/Schedules!E8-1,0) -> -0.030236747 | G9: =IFERROR(Schedules!G8/Schedules!F8-1,0) -> -0.046008458 | H9: =IFERROR(Schedules!H8/Schedules!G8-1,0) -> 0.24218613 | I9: =AVERAGE(E9:H9) -> 0.014773146
A10: R.G_EBITDA | B10: EBITDA | D10: =IFERROR((IS!D14+Schedules!D20)/(IS!C14+Schedules!C20)-1,0) -> 1.4412024 | E10: =IFERROR((IS!E14+Schedules!E20)/(IS!D14+Schedules!D20)-1,0) -> -0.37756421 | F10: =IFERROR((IS!F14+Schedules!F20)/(IS!E14+Schedules!E20)-1,0) -> 0.49810459 | G10: =IFERROR((IS!G14+Schedules!G20)/(IS!F14+Schedules!F20)-1,0) -> 0.20342713 | H10: =IFERROR((IS!H14+Schedules!H20)/(IS!G14+Schedules!G20)-1,0) -> -0.036545139 | I10: =AVERAGE(E10:H10) -> 0.071855593
A11: R.G_NI | B11: Laba tahun berjalan | D11: =IFERROR(IS!D19/IS!C19-1,0) -> -12.422499 | E11: =IFERROR(IS!E19/IS!D19-1,0) -> -1.2668246 | F11: =IFERROR(IS!F19/IS!E19-1,0) -> -0.13293955 | G11: =IFERROR(IS!G19/IS!F19-1,0) -> -0.39070289 | H11: =IFERROR(IS!H19/IS!G19-1,0) -> 7.5156785 | I11: =AVERAGE(E11:H11) -> 1.4313029
A12: R.G_NIP | B12: Laba pemilik entitas induk | D12: =IFERROR(IS!D26/IS!C26-1,0) -> -12.495204 | E12: =IFERROR(IS!E26/IS!D26-1,0) -> -1.2680747 | F12: =IFERROR(IS!F26/IS!E26-1,0) -> -0.13144434 | G12: =IFERROR(IS!G26/IS!F26-1,0) -> -0.38911406 | H12: =IFERROR(IS!H26/IS!G26-1,0) -> 7.4634032 | I12: =AVERAGE(E12:H12) -> 1.4186925
B13: PROFITABILITAS
A14: R.GM | B14: Margin laba bruto | C14: =IFERROR(IS!C8/IS!C6,0) -> 0.32645333 | D14: =IFERROR(IS!D8/IS!D6,0) -> 0.36635485 | E14: =IFERROR(IS!E8/IS!E6,0) -> 0.28800783 | F14: =IFERROR(IS!F8/IS!F6,0) -> 0.28684382 | G14: =IFERROR(IS!G8/IS!G6,0) -> 0.39157019 | H14: =IFERROR(IS!H8/IS!H6,0) -> 0.40892085 | I14: =AVERAGE(E14:H14) -> 0.34383567
A15: R.OPM | B15: Margin laba usaha | C15: =IFERROR(IS!C14/IS!C6,0) -> 0.034493603 | D15: =IFERROR(IS!D14/IS!D6,0) -> 0.13017341 | E15: =IFERROR(IS!E14/IS!E6,0) -> 0.018185457 | F15: =IFERROR(IS!F14/IS!F6,0) -> 0.045252547 | G15: =IFERROR(IS!G14/IS!G6,0) -> 0.067397843 | H15: =IFERROR(IS!H14/IS!H6,0) -> 0.033013702 | I15: =AVERAGE(E15:H15) -> 0.040962387
A16: R.EBITDA | B16: EBITDA (Rp) | C16: =(IS!C14+Schedules!C20) -> 176840406802 | D16: =(IS!D14+Schedules!D20) -> 431703230988 | E16: =(IS!E14+Schedules!E20) -> 268707541015 | F16: =(IS!F14+Schedules!F20) -> 402552000000 | G16: =(IS!G14+Schedules!G20) -> 484442000000 | H16: =(IS!H14+Schedules!H20) -> 466738000000 | I16: =AVERAGE(E16:H16) -> 4.0560989e+11 | J16: laba usaha dihitung (termasuk pendapatan lain neto Cat 30) + penyusutan aset tetap (Cat 27+28) + penyusutan aset hak guna + amortisasi (Cat 28)
A17: R.EBITDA_M | B17: Margin EBITDA | C17: =IFERROR((IS!C14+Schedules!C20)/IS!C6,0) -> 0.13774778 | D17: =IFERROR((IS!D14+Schedules!D20)/IS!D6,0) -> 0.22432515 | E17: =IFERROR((IS!E14+Schedules!E20)/IS!E6,0) -> 0.13892699 | F17: =IFERROR((IS!F14+Schedules!F20)/IS!F6,0) -> 0.16081663 | G17: =IFERROR((IS!G14+Schedules!G20)/IS!G6,0) -> 0.20698837 | H17: =IFERROR((IS!H14+Schedules!H20)/IS!H6,0) -> 0.18024669 | I17: =AVERAGE(E17:H17) -> 0.17174467
A18: R.NM | B18: Margin laba bersih | C18: =IFERROR(IS!C19/IS!C6,0) -> -0.011293094 | D18: =IFERROR(IS!D19/IS!D6,0) -> 0.086052522 | E18: =IFERROR(IS!E19/IS!E6,0) -> -0.022845652 | F18: =IFERROR(IS!F19/IS!F6,0) -> -0.015305768 | G18: =IFERROR(IS!G19/IS!G6,0) -> -0.0099742312 | H18: =IFERROR(IS!H19/IS!H6,0) -> -0.076769495 | I18: =AVERAGE(E18:H18) -> -0.031223786
A19: R.NMP | B19: Margin laba induk | C19: =IFERROR(IS!C26/IS!C6,0) -> -0.011201622 | D19: =IFERROR(IS!D26/IS!D6,0) -> 0.085898812 | E19: =IFERROR(IS!E26/IS!E6,0) -> -0.022911685 | F19: =IFERROR(IS!F26/IS!F6,0) -> -0.015376478 | G19: =IFERROR(IS!G26/IS!G6,0) -> -0.01004644 | H19: =IFERROR(IS!H26/IS!H6,0) -> -0.076850593 | I19: =AVERAGE(E19:H19) -> -0.031296299
A20: R.ROE | B20: ROE (laba induk / rata-rata ekuitas induk) | D20: =IFERROR(IS!D26/((BS!D60+BS!C60)/2),0) -> 0.089835082 | E20: =IFERROR(IS!E26/((BS!E60+BS!D60)/2),0) -> -0.023200175 | F20: =IFERROR(IS!F26/((BS!F60+BS!E60)/2),0) -> -0.020528177 | G20: =IFERROR(IS!G26/((BS!G60+BS!F60)/2),0) -> -0.012756941 | H20: =IFERROR(IS!H26/((BS!H60+BS!G60)/2),0) -> -0.12583619 | I20: =AVERAGE(E20:H20) -> -0.045580372
A21: R.ROA | B21: ROA (laba / rata-rata aset) | D21: =IFERROR(IS!D19/((BS!D27+BS!C27)/2),0) -> 0.035930052 | E21: =IFERROR(IS!E19/((BS!E27+BS!D27)/2),0) -> -0.0083204109 | F21: =IFERROR(IS!F19/((BS!F27+BS!E27)/2),0) -> -0.0067476876 | G21: =IFERROR(IS!G19/((BS!G27+BS!F27)/2),0) -> -0.0041355927 | H21: =IFERROR(IS!H19/((BS!H27+BS!G27)/2),0) -> -0.029877661 | I21: =AVERAGE(E21:H21) -> -0.012270338
A22: R.ETR | B22: Tarif pajak efektif | C22: =IFERROR(-IS!C18/IS!C17,0) -> 76.751242 | D22: =IFERROR(-IS!D18/IS!D17,0) -> -0.058717335 | E22: =IFERROR(-IS!E18/IS!E17,0) -> -0.049904963 | F22: =IFERROR(-IS!F18/IS!F17,0) -> -0.22440957 | G22: =IFERROR(-IS!G18/IS!G17,0) -> -7.8424242 | H22: =IFERROR(-IS!H18/IS!H17,0) -> 0.1546966 | I22: =AVERAGE(E22:H22) -> -1.9905105
A23: R.NCI_SH | B23: Porsi laba ke NCI | C23: =IFERROR(IS!C27/IS!C19,0) -> 0.0080997698 | D23: =IFERROR(IS!D27/IS!D19,0) -> 0.0017862363 | E23: =IFERROR(IS!E27/IS!E19,0) -> -0.0028903894 | F23: =IFERROR(IS!F27/IS!F19,0) -> -0.0046198418 | G23: =IFERROR(IS!G27/IS!G19,0) -> -0.0072395476 | H23: =IFERROR(IS!H27/IS!H19,0) -> -0.0010563912 | I23: =AVERAGE(E23:H23) -> -0.0039515425
A24: R.OTH | B24: Pendapatan (beban) lain neto % pendapatan | C24: =IFERROR(IS!C13/IS!C6,0) -> 0.022144854 | D24: =IFERROR(IS!D13/IS!D6,0) -> 0.012485705 | E24: =IFERROR(IS!E13/IS!E6,0) -> 0.0021507288 | F24: =IFERROR(IS!F13/IS!F6,0) -> 0.0028020425 | G24: =IFERROR(IS!G13/IS!G6,0) -> -0.010586512 | H24: =IFERROR(IS!H13/IS!H6,0) -> 0.0011133681 | I24: =AVERAGE(E24:H24) -> -0.0011300931 | J24: Cat 30 (di atas laba usaha; termasuk penurunan nilai piutang & selisih kurs)
B25: PENDAPATAN
A26: R.SH_MED | B26: Porsi obat & perlengkapan medis (% pendapatan) | C26: =Schedules!C11 -> 0.19780117 | D26: =Schedules!D11 -> 0.21709091 | E26: =Schedules!E11 -> 0.22323405 | F26: =Schedules!F11 -> 0.30145088 | G26: =Schedules!G11 -> 0.49735369 | H26: =Schedules!H11 -> 0.49884145 | I26: =AVERAGE(E26:H26) -> 0.38022002
B27: MODAL KERJA (hari, saldo akhir)
A28: R.DSO | B28: DSO piutang usaha (hari) | C28: =IFERROR((BS!C8+BS!C9)/IS!C6*365,0) -> 64.090527 | D28: =IFERROR((BS!D8+BS!D9)/IS!D6*365,0) -> 44.362731 | E28: =IFERROR((BS!E8+BS!E9)/IS!E6*365,0) -> 45.853511 | F28: =IFERROR((BS!F8+BS!F9)/IS!F6*365,0) -> 57.643682 | G28: =IFERROR((BS!G8+BS!G9)/IS!G6*365,0) -> 66.171047 | H28: =IFERROR((BS!H8+BS!H9)/IS!H6*365,0) -> 78.644628 | I28: =AVERAGE(E28:H28) -> 62.078217
A29: R.DIO | B29: DIO persediaan (hari, atas beban pokok) | C29: =IFERROR(BS!C12/-IS!C7*365,0) -> 31.528102 | D29: =IFERROR(BS!D12/-IS!D7*365,0) -> 21.075025 | E29: =IFERROR(BS!E12/-IS!E7*365,0) -> 13.152174 | F29: =IFERROR(BS!F12/-IS!F7*365,0) -> 10.006476 | G29: =IFERROR(BS!G12/-IS!G7*365,0) -> 15.716663 | H29: =IFERROR(BS!H12/-IS!H7*365,0) -> 17.485643 | I29: =AVERAGE(E29:H29) -> 14.090239
A30: R.DPO | B30: DPO utang usaha (hari, atas beban pokok) | C30: =IFERROR((BS!C30+BS!C31)/-IS!C7*365,0) -> 73.956904 | D30: =IFERROR((BS!D30+BS!D31)/-IS!D7*365,0) -> 57.560031 | E30: =IFERROR((BS!E30+BS!E31)/-IS!E7*365,0) -> 42.935444 | F30: =IFERROR((BS!F30+BS!F31)/-IS!F7*365,0) -> 28.768515 | G30: =IFERROR((BS!G30+BS!G31)/-IS!G7*365,0) -> 40.036019 | H30: =IFERROR((BS!H30+BS!H31)/-IS!H7*365,0) -> 27.147901 | I30: =AVERAGE(E30:H30) -> 34.72197
B31: LIKUIDITAS & SOLVABILITAS
A32: R.CR | B32: Current ratio | C32: =IFERROR(BS!C16/BS!C43,0) -> 0.53982867 | D32: =IFERROR(BS!D16/BS!D43,0) -> 0.38412375 | E32: =IFERROR(BS!E16/BS!E43,0) -> 0.55541448 | F32: =IFERROR(BS!F16/BS!F43,0) -> 0.47410908 | G32: =IFERROR(BS!G16/BS!G43,0) -> 0.3206728 | H32: =IFERROR(BS!H16/BS!H43,0) -> 1.5701055 | I32: =AVERAGE(E32:H32) -> 0.73007547
A33: R.DEBT | B33: Utang berbunga: bank + pinjaman non-bank + surat utang + utang pembiayaan (Rp) | C33: =(BS!C29+BS!C38+BS!C45+BS!C39+BS!C46+BS!C40+BS!C47+BS!C41+BS!C48) -> 1072251221694 | D33: =(BS!D29+BS!D38+BS!D45+BS!D39+BS!D46+BS!D40+BS!D47+BS!D41+BS!D48) -> 846194719314 | E33: =(BS!E29+BS!E38+BS!E45+BS!E39+BS!E46+BS!E40+BS!E47+BS!E41+BS!E48) -> 1725310890922 | F33: =(BS!F29+BS!F38+BS!F45+BS!F39+BS!F46+BS!F40+BS!F47+BS!F41+BS!F48) -> 1646343000000 | G33: =(BS!G29+BS!G38+BS!G45+BS!G39+BS!G46+BS!G40+BS!G47+BS!G41+BS!G48) -> 1665866000000 | H33: =(BS!H29+BS!H38+BS!H45+BS!H39+BS!H46+BS!H40+BS!H47+BS!H41+BS!H48) -> 4684415000000 | I33: =AVERAGE(E33:H33) -> 2.4304837e+12 | J33: Temuan S6
A34: R.LEASE | B34: Liabilitas sewa (Rp) | C34: =(BS!C42+BS!C49) -> 0 | D34: =(BS!D42+BS!D49) -> 0 | E34: =(BS!E42+BS!E49) -> 0 | F34: =(BS!F42+BS!F49) -> 3891000000 | G34: =(BS!G42+BS!G49) -> 3276000000 | H34: =(BS!H42+BS!H49) -> 7677000000 | I34: =AVERAGE(E34:H34) -> 3711000000
A35: R.CASHINV | B35: Kas dan setara kas (Rp) | C35: =(BS!C6) -> 629608688874 | D35: =(BS!D6) -> 700922359619 | E35: =(BS!E6) -> 1118254250664 | F35: =(BS!F6) -> 515185000000 | G35: =(BS!G6) -> 277208000000 | H35: =(BS!H6) -> 1826263000000 | I35: =AVERAGE(E35:H35) -> 934227562666
A36: R.ND | B36: Utang neto (utang + sewa - kas) (Rp) | C36: =(BS!C29+BS!C38+BS!C45+BS!C39+BS!C46+BS!C40+BS!C47+BS!C41+BS!C48)+(BS!C42+BS!C49)-BS!C6 -> 442642532820 | D36: =(BS!D29+BS!D38+BS!D45+BS!D39+BS!D46+BS!D40+BS!D47+BS!D41+BS!D48)+(BS!D42+BS!D49)-BS!D6 -> 145272359695 | E36: =(BS!E29+BS!E38+BS!E45+BS!E39+BS!E46+BS!E40+BS!E47+BS!E41+BS!E48)+(BS!E42+BS!E49)-BS!E6 -> 607056640258 | F36: =(BS!F29+BS!F38+BS!F45+BS!F39+BS!F46+BS!F40+BS!F47+BS!F41+BS!F48)+(BS!F42+BS!F49)-BS!F6 -> 1135049000000 | G36: =(BS!G29+BS!G38+BS!G45+BS!G39+BS!G46+BS!G40+BS!G47+BS!G41+BS!G48)+(BS!G42+BS!G49)-BS!G6 -> 1391934000000 | H36: =(BS!H29+BS!H38+BS!H45+BS!H39+BS!H46+BS!H40+BS!H47+BS!H41+BS!H48)+(BS!H42+BS!H49)-BS!H6 -> 2865829000000 | I36: =AVERAGE(E36:H36) -> 1.4999672e+12 | J36: negatif = kas neto
A37: R.DE | B37: Utang / ekuitas | C37: =IFERROR((BS!C29+BS!C38+BS!C45+BS!C39+BS!C46+BS!C40+BS!C47+BS!C41+BS!C48)/BS!C62,0) -> 0.61106118 | D37: =IFERROR((BS!D29+BS!D38+BS!D45+BS!D39+BS!D46+BS!D40+BS!D47+BS!D41+BS!D48)/BS!D62,0) -> 0.43903373 | E37: =IFERROR((BS!E29+BS!E38+BS!E45+BS!E39+BS!E46+BS!E40+BS!E47+BS!E41+BS!E48)/BS!E62,0) -> 0.91038794 | F37: =IFERROR((BS!F29+BS!F38+BS!F45+BS!F39+BS!F46+BS!F40+BS!F47+BS!F41+BS!F48)/BS!F62,0) -> 0.88634246 | G37: =IFERROR((BS!G29+BS!G38+BS!G45+BS!G39+BS!G46+BS!G40+BS!G47+BS!G41+BS!G48)/BS!G62,0) -> 0.90866872 | H37: =IFERROR((BS!H29+BS!H38+BS!H45+BS!H39+BS!H46+BS!H40+BS!H47+BS!H41+BS!H48)/BS!H62,0) -> 3.5070205 | I37: =AVERAGE(E37:H37) -> 1.5531049
A38: R.NDE | B38: Utang neto / EBITDA | C38: =IFERROR(((BS!C29+BS!C38+BS!C45+BS!C39+BS!C46+BS!C40+BS!C47+BS!C41+BS!C48)+(BS!C42+BS!C49)-BS!C6)/(IS!C14+Schedules!C20),0) -> 2.5030622 | D38: =IFERROR(((BS!D29+BS!D38+BS!D45+BS!D39+BS!D46+BS!D40+BS!D47+BS!D41+BS!D48)+(BS!D42+BS!D49)-BS!D6)/(IS!D14+Schedules!D20),0) -> 0.33650978 | E38: =IFERROR(((BS!E29+BS!E38+BS!E45+BS!E39+BS!E46+BS!E40+BS!E47+BS!E41+BS!E48)+(BS!E42+BS!E49)-BS!E6)/(IS!E14+Schedules!E20),0) -> 2.2591723 | F38: =IFERROR(((BS!F29+BS!F38+BS!F45+BS!F39+BS!F46+BS!F40+BS!F47+BS!F41+BS!F48)+(BS!F42+BS!F49)-BS!F6)/(IS!F14+Schedules!F20),0) -> 2.8196332 | G38: =IFERROR(((BS!G29+BS!G38+BS!G45+BS!G39+BS!G46+BS!G40+BS!G47+BS!G41+BS!G48)+(BS!G42+BS!G49)-BS!G6)/(IS!G14+Schedules!G20),0) -> 2.8732728 | H38: =IFERROR(((BS!H29+BS!H38+BS!H45+BS!H39+BS!H46+BS!H40+BS!H47+BS!H41+BS!H48)+(BS!H42+BS!H49)-BS!H6)/(IS!H14+Schedules!H20),0) -> 6.1401236 | I38: =AVERAGE(E38:H38) -> 3.5230505
A39: R.ICR | B39: EBITDA / beban keuangan | C39: =IFERROR((IS!C14+Schedules!C20)/-IS!C15,0) -> 2.5061866 | D39: =IFERROR((IS!D14+Schedules!D20)/-IS!D15,0) -> 3.6574465 | E39: =IFERROR((IS!E14+Schedules!E20)/-IS!E15,0) -> 2.7797776 | F39: =IFERROR((IS!F14+Schedules!F20)/-IS!F15,0) -> 2.3177131 | G39: =IFERROR((IS!G14+Schedules!G20)/-IS!G15,0) -> 2.7863433 | H39: =IFERROR((IS!H14+Schedules!H20)/-IS!H15,0) -> 1.2043173 | I39: =AVERAGE(E39:H39) -> 2.2720378
B40: ARUS KAS
A41: R.CAPEX | B41: Capex (perolehan aset tetap + uang muka aset tetap) (Rp) | C41: =-(CF!C15+CF!C16) -> 544122343656 | D41: =-(CF!D15+CF!D16) -> 464023277324 | E41: =-(CF!E15+CF!E16) -> 655546517280 | F41: =-(CF!F15+CF!F16) -> 583532000000 | G41: =-(CF!G15+CF!G16) -> 525029000000 | H41: =-(CF!H15+CF!H16) -> 579605000000 | I41: =AVERAGE(E41:H41) -> 585928129320
A42: R.CAPEX_R | B42: Capex % pendapatan | C42: =IFERROR(-(CF!C15+CF!C16)/IS!C6,0) -> 0.42383777 | D42: =IFERROR(-(CF!D15+CF!D16)/IS!D6,0) -> 0.24111955 | E42: =IFERROR(-(CF!E15+CF!E16)/IS!E6,0) -> 0.33893022 | F42: =IFERROR(-(CF!F15+CF!F16)/IS!F6,0) -> 0.23311683 | G42: =IFERROR(-(CF!G15+CF!G16)/IS!G6,0) -> 0.22433005 | H42: =IFERROR(-(CF!H15+CF!H16)/IS!H6,0) -> 0.22383411 | I42: =AVERAGE(E42:H42) -> 0.2550528
A43: R.LEASE_R | B43: Pembayaran sewa % pendapatan | C43: =IFERROR(-CF!C35/IS!C6,0) -> 0.25704966 | D43: =IFERROR(-CF!D35/IS!D6,0) -> 0 | E43: =IFERROR(-CF!E35/IS!E6,0) -> 0 | F43: =IFERROR(-CF!F35/IS!F6,0) -> 0.00028244141 | G43: =IFERROR(-CF!G35/IS!G6,0) -> 0.00030250838 | H43: =IFERROR(-CF!H35/IS!H6,0) -> 0.00061750803 | I43: =AVERAGE(E43:H43) -> 0.00030061446
A44: R.FCF | B44: Arus kas bebas sederhana (CFO - capex + sewa dibayar) (Rp) | C44: =CF!C13--(CF!C15+CF!C16)+CF!C35 -> -780240452254 | D44: =CF!D13--(CF!D15+CF!D16)+CF!D35 -> -127236614534 | E44: =CF!E13--(CF!E15+CF!E16)+CF!E35 -> -445071695019 | F44: =CF!F13--(CF!F15+CF!F16)+CF!F35 -> -528322000000 | G44: =CF!G13--(CF!G15+CF!G16)+CF!G35 -> -252489000000 | H44: =CF!H13--(CF!H15+CF!H16)+CF!H35 -> -451534000000 | I44: =AVERAGE(E44:H44) -> -4.1935417e+11
A45: R.CCONV | B45: CFO / laba tahun berjalan | C45: =IFERROR(CF!C13/IS!C19,0) -> -6.4754805 | D45: =IFERROR(CF!D13/IS!D19,0) -> 2.0336862 | E45: =IFERROR(CF!E13/IS!E19,0) -> -4.7632499 | F45: =IFERROR(CF!F13/IS!F19,0) -> -1.4594785 | G45: =IFERROR(CF!G13/IS!G19,0) -> -11.705278 | H45: =IFERROR(CF!H13/IS!H19,0) -> -0.65229639 | I45: =AVERAGE(E45:H45) -> -4.6450756
B46: PER SAHAM (informasi, bukan penilaian)
A47: R.EPS | B47: Laba induk / 12,238,959,990 saham tercatat (Rp) | C47: =IFERROR(IS!C26/12238959990,0) -> -1.1749877 | D47: =IFERROR(IS!D26/12238959990,0) -> 13.506723 | E47: =IFERROR(IS!E26/12238959990,0) -> -3.62081 | F47: =IFERROR(IS!F26/12238959990,0) -> -3.1448751 | G47: =IFERROR(IS!G26/12238959990,0) -> -1.92116 | H47: =IFERROR(IS!H26/12238959990,0) -> -16.259551 | I47: =AVERAGE(E47:H47) -> -6.2365991 | J47: saham tercatat akhir 2025
A48: R.EPS_W | B48: Laba induk / saham rata-rata tertimbang CALK (Rp) | C48: =IFERROR(IS!C26/Schedules!C22,0) -> -1.1983151 | D48: =IFERROR(IS!D26/Schedules!D22,0) -> 13.774877 | E48: =IFERROR(IS!E26/Schedules!E22,0) -> -3.6926953 | F48: =IFERROR(IS!F26/Schedules!F22,0) -> -3.2073115 | G48: =IFERROR(IS!G26/Schedules!G22,0) -> -1.9593015 | H48: =IFERROR(IS!H26/Schedules!H22,0) -> -16.308259 | I48: =AVERAGE(E48:H48) -> -6.2918919
A49: R.EPS_P | B49: EPS dasar tercetak (Rp) | C49: =IS!C30 -> -1.2 | D49: =IS!D30 -> 13.77 | E49: =IS!E30 -> -3.69 | F49: =IS!F30 -> -3.21 | G49: =IS!G30 -> -1.96 | H49: =IS!H30 -> -16.31 | I49: =AVERAGE(E49:H49) -> -6.2925 | J49: Temuan S9
A50: R.BVPS | B50: Ekuitas induk per saham (Rp) | C50: =IFERROR(BS!C60/12238959990,0) -> 143.30854 | D50: =IFERROR(BS!D60/12238959990,0) -> 157.39186 | E50: =IFERROR(BS!E60/12238959990,0) -> 154.74458 | F50: =IFERROR(BS!F60/12238959990,0) -> 151.65137 | G50: =IFERROR(BS!G60/12238959990,0) -> 149.5431 | H50: =IFERROR(BS!H60/12238959990,0) -> 108.88098 | I50: =AVERAGE(E50:H50) -> 141.20501
A51: R.DIV | B51: Dividen tunai dibayar (Rp) | C51: =-CF!C36 -> 0 | D51: =-CF!D36 -> 0 | E51: =-CF!E36 -> 0 | F51: =-CF!F36 -> 0 | G51: =-CF!G36 -> 0 | H51: =-CF!H36 -> 0 | J51: dividen ke pemilik induk

Sheet Rekonsiliasi
A1: Rekonsiliasi & cek integritas (330 cek)
A2: Status = hasil rumus saat ini; Ekspektasi = hasil yang diharapkan dari data sumber (dihitung saat build). Semua ❌ yang diharapkan dijelaskan dan ditautkan ke Temuan.
B3: Ringkasan | C3: =IF(COUNTIF(K7:K336,"✖*")=0,"SEMUA 330 CEK SESUAI EKSPEKTASI","ADA "&COUNTIF(K7:K336,"✖*")&" CEK TIDAK SESUAI EKSPEKTASI") -> SEMUA 330 CEK SESUAI EKSPEKTASI
C4: ="OK: "&COUNTIF(I7:I336,"OK")&" | ❌ (diharapkan, dijelaskan di Temuan): "&COUNTIF(I7:I336,"❌")&" | N/A/INFO: "&(COUNTIF(I7:I336,"N/A")+COUNTIF(I7:I336,"INFO")) -> OK: 325 | ❌ (diharapkan, dijelaskan di Temuan): 5 | N/A/INFO: 0
A6: No | B6: Kategori | C6: Cek | D6: Tahun | E6: Nilai A | F6: Nilai B | G6: Selisih A-B | H6: Toleransi | I6: Status | J6: Ekspektasi | K6: Sesuai ekspektasi? | L6: Penjelasan / Temuan
A7: 1 | B7: Subtotal rumus vs tercetak | C7: IS: GROSS_PROFIT rumus = tercetak | D7: 2020 | E7: =IS!C8 -> 419100328655 | F7: =IS!C32 -> 419100328655 | G7: =IF(COUNT(E7:F7)=2,E7-F7,"") -> 0 | H7: 1 | I7: =IF(COUNT(E7:F7)<2,"N/A",IF(ABS(G7)<=H7,"OK","❌")) -> OK | J7: OK | K7: =IF(I7=J7,"✔ sesuai","✖ TIDAK sesuai") -> ✔ sesuai
A8: 2 | B8: Subtotal rumus vs tercetak | C8: IS: PBT rumus = tercetak | D8: 2020 | E8: =IS!C17 -> 191390366 | F8: =IS!C33 -> 191390366 | G8: =IF(COUNT(E8:F8)=2,E8-F8,"") -> 0 | H8: 1 | I8: =IF(COUNT(E8:F8)<2,"N/A",IF(ABS(G8)<=H8,"OK","❌")) -> OK | J8: OK | K8: =IF(I8=J8,"✔ sesuai","✖ TIDAK sesuai") -> ✔ sesuai
A9: 3 | B9: Subtotal rumus vs tercetak | C9: IS: NET_INCOME rumus = tercetak | D9: 2020 | E9: =IS!C19 -> -14498057988 | F9: =IS!C34 -> -14498057988 | G9: =IF(COUNT(E9:F9)=2,E9-F9,"") -> 0 | H9: 1 | I9: =IF(COUNT(E9:F9)<2,"N/A",IF(ABS(G9)<=H9,"OK","❌")) -> OK | J9: OK | K9: =IF(I9=J9,"✔ sesuai","✖ TIDAK sesuai") -> ✔ sesuai
A10: 4 | B10: Subtotal rumus vs tercetak | C10: IS: OCI_TOTAL rumus = tercetak | D10: 2020 | E10: =IS!C23 -> 4996817740 | F10: =IS!C35 -> 4996817740 | G10: =IF(COUNT(E10:F10)=2,E10-F10,"") -> 0 | H10: 1 | I10: =IF(COUNT(E10:F10)<2,"N/A",IF(ABS(G10)<=H10,"OK","❌")) -> OK | J10: OK | K10: =IF(I10=J10,"✔ sesuai","✖ TIDAK sesuai") -> ✔ sesuai
A11: 5 | B11: Subtotal rumus vs tercetak | C11: IS: TCI rumus = tercetak | D11: 2020 | E11: =IS!C24 -> -9501240248 | F11: =IS!C36 -> -9501240248 | G11: =IF(COUNT(E11:F11)=2,E11-F11,"") -> 0 | H11: 1 | I11: =IF(COUNT(E11:F11)<2,"N/A",IF(ABS(G11)<=H11,"OK","❌")) -> OK | J11: OK | K11: =IF(I11=J11,"✔ sesuai","✖ TIDAK sesuai") -> ✔ sesuai
A12: 6 | B12: Subtotal rumus vs tercetak | C12: BS: TOTAL_CA rumus = tercetak | D12: 2020 | E12: =BS!C16 -> 939835506742 | F12: =BS!C68 -> 939835506742 | G12: =IF(COUNT(E12:F12)=2,E12-F12,"") -> 0 | H12: 1 | I12: =IF(COUNT(E12:F12)<2,"N/A",IF(ABS(G12)<=H12,"OK","❌")) -> OK | J12: OK | K12: =IF(I12=J12,"✔ sesuai","✖ TIDAK sesuai") -> ✔ sesuai
A13: 7 | B13: Subtotal rumus vs tercetak | C13: BS: TOTAL_NCA rumus = tercetak | D13: 2020 | E13: =BS!C26 -> 3406493581264 | F13: =BS!C69 -> 3406493581264 | G13: =IF(COUNT(E13:F13)=2,E13-F13,"") -> 0 | H13: 1 | I13: =IF(COUNT(E13:F13)<2,"N/A",IF(ABS(G13)<=H13,"OK","❌")) -> OK | J13: OK | K13: =IF(I13=J13,"✔ sesuai","✖ TIDAK sesuai") -> ✔ sesuai
A14: 8 | B14: Subtotal rumus vs tercetak | C14: BS: TOTAL_ASSETS rumus = tercetak | D14: 2020 | E14: =BS!C27 -> 4346329088006 | F14: =BS!C70 -> 4346329088006 | G14: =IF(COUNT(E14:F14)=2,E14-F14,"") -> 0 | H14: 1 | I14: =IF(COUNT(E14:F14)<2,"N/A",IF(ABS(G14)<=H14,"OK","❌")) -> OK | J14: OK | K14: =IF(I14=J14,"✔ sesuai","✖ TIDAK sesuai") -> ✔ sesuai
A15: 9 | B15: Subtotal rumus vs tercetak | C15: BS: TOTAL_CL rumus = tercetak | D15: 2020 | E15: =BS!C43 -> 1740988511325 | F15: =BS!C71 -> 1740988511325 | G15: =IF(COUNT(E15:F15)=2,E15-F15,"") -> 0 | H15: 1 | I15: =IF(COUNT(E15:F15)<2,"N/A",IF(ABS(G15)<=H15,"OK","❌")) -> OK | J15: OK | K15: =IF(I15=J15,"✔ sesuai","✖ TIDAK sesuai") -> ✔ sesuai
A16: 10 | B16: Subtotal rumus vs tercetak | C16: BS: TOTAL_NCL rumus = tercetak | D16: 2020 | E16: =BS!C52 -> 850604303917 | F16: =BS!C72 -> 850604303917 | G16: =IF(COUNT(E16:F16)=2,E16-F16,"") -> 0 | H16: 1 | I16: =IF(COUNT(E16:F16)<2,"N/A",IF(ABS(G16)<=H16,"OK","❌")) -> OK | J16: OK | K16: =IF(I16=J16,"✔ sesuai","✖ TIDAK sesuai") -> ✔ sesuai
A17: 11 | B17: Subtotal rumus vs tercetak | C17: BS: TOTAL_LIAB rumus = tercetak | D17: 2020 | E17: =BS!C53 -> 2591592815242 | F17: =BS!C73 -> 2591592815242 | G17: =IF(COUNT(E17:F17)=2,E17-F17,"") -> 0 | H17: 1 | I17: =IF(COUNT(E17:F17)<2,"N/A",IF(ABS(G17)<=H17,"OK","❌")) -> OK | J17: OK | K17: =IF(I17=J17,"✔ sesuai","✖ TIDAK sesuai") -> ✔ sesuai
A18: 12 | B18: Subtotal rumus vs tercetak | C18: BS: EQUITY_PARENT rumus = tercetak | D18: 2020 | E18: =BS!C60 -> 1753947506431 | F18: =BS!C74 -> 1753947506431 | G18: =IF(COUNT(E18:F18)=2,E18-F18,"") -> 0 | H18: 1 | I18: =IF(COUNT(E18:F18)<2,"N/A",IF(ABS(G18)<=H18,"OK","❌")) -> OK | J18: OK | K18: =IF(I18=J18,"✔ sesuai","✖ TIDAK sesuai") -> ✔ sesuai
A19: 13 | B19: Subtotal rumus vs tercetak | C19: BS: TOTAL_EQUITY rumus = tercetak | D19: 2020 | E19: =BS!C62 -> 1754736272764 | F19: =BS!C75 -> 1754736272764 | G19: =IF(COUNT(E19:F19)=2,E19-F19,"") -> 0 | H19: 1 | I19: =IF(COUNT(E19:F19)<2,"N/A",IF(ABS(G19)<=H19,"OK","❌")) -> OK | J19: OK | K19: =IF(I19=J19,"✔ sesuai","✖ TIDAK sesuai") -> ✔ sesuai
A20: 14 | B20: Subtotal rumus vs tercetak | C20: BS: TOTAL_LIAB_EQUITY rumus = tercetak | D20: 2020 | E20: =BS!C63 -> 4346329088006 | F20: =BS!C76 -> 4346329088006 | G20: =IF(COUNT(E20:F20)=2,E20-F20,"") -> 0 | H20: 1 | I20: =IF(COUNT(E20:F20)<2,"N/A",IF(ABS(G20)<=H20,"OK","❌")) -> OK | J20: OK | K20: =IF(I20=J20,"✔ sesuai","✖ TIDAK sesuai") -> ✔ sesuai
A21: 15 | B21: Subtotal rumus vs tercetak | C21: CF: CFO rumus = tercetak | D21: 2020 | E21: =CF!C13 -> 93881891402 | F21: =CF!C46 -> 93881891402 | G21: =IF(COUNT(E21:F21)=2,E21-F21,"") -> 0 | H21: 1 | I21: =IF(COUNT(E21:F21)<2,"N/A",IF(ABS(G21)<=H21,"OK","❌")) -> OK | J21: OK | K21: =IF(I21=J21,"✔ sesuai","✖ TIDAK sesuai") -> ✔ sesuai
A22: 16 | B22: Subtotal rumus vs tercetak | C22: CF: CFI rumus = tercetak | D22: 2020 | E22: =CF!C21 -> -550711027296 | F22: =CF!C47 -> -550711027296 | G22: =IF(COUNT(E22:F22)=2,E22-F22,"") -> 0 | H22: 1 | I22: =IF(COUNT(E22:F22)<2,"N/A",IF(ABS(G22)<=H22,"OK","❌")) -> OK | J22: OK | K22: =IF(I22=J22,"✔ sesuai","✖ TIDAK sesuai") -> ✔ sesuai
A23: 17 | B23: Subtotal rumus vs tercetak | C23: CF: CFF rumus = tercetak | D23: 2020 | E23: =CF!C37 -> 854320635527 | F23: =CF!C48 -> 854320635527 | G23: =IF(COUNT(E23:F23)=2,E23-F23,"") -> 0 | H23: 1 | I23: =IF(COUNT(E23:F23)<2,"N/A",IF(ABS(G23)<=H23,"OK","❌")) -> OK | J23: OK | K23: =IF(I23=J23,"✔ sesuai","✖ TIDAK sesuai") -> ✔ sesuai
A24: 18 | B24: Subtotal rumus vs tercetak | C24: CF: NET_CHANGE rumus = tercetak | D24: 2020 | E24: =CF!C38 -> 397491499633 | F24: =CF!C49 -> 397491499633 | G24: =IF(COUNT(E24:F24)=2,E24-F24,"") -> 0 | H24: 1 | I24: =IF(COUNT(E24:F24)<2,"N/A",IF(ABS(G24)<=H24,"OK","❌")) -> OK | J24: OK | K24: =IF(I24=J24,"✔ sesuai","✖ TIDAK sesuai") -> ✔ sesuai
A25: 19 | B25: Subtotal rumus vs tercetak | C25: CF: CASH_END rumus = tercetak | D25: 2020 | E25: =CF!C41 -> 629608688874 | F25: =CF!C50 -> 629608688874 | G25: =IF(COUNT(E25:F25)=2,E25-F25,"") -> 0 | H25: 1 | I25: =IF(COUNT(E25:F25)<2,"N/A",IF(ABS(G25)<=H25,"OK","❌")) -> OK | J25: OK | K25: =IF(I25=J25,"✔ sesuai","✖ TIDAK sesuai") -> ✔ sesuai
A26: 20 | B26: Integritas laporan | C26: BS: aset = liabilitas + ekuitas | D26: 2020 | E26: =BS!C27 -> 4346329088006 | F26: =BS!C63 -> 4346329088006 | G26: =IF(COUNT(E26:F26)=2,E26-F26,"") -> 0 | H26: 1 | I26: =IF(COUNT(E26:F26)<2,"N/A",IF(ABS(G26)<=H26,"OK","❌")) -> OK | J26: OK | K26: =IF(I26=J26,"✔ sesuai","✖ TIDAK sesuai") -> ✔ sesuai
A27: 21 | B27: Integritas laporan | C27: IS: laba = induk + NCI | D27: 2020 | E27: =IS!C19 -> -14498057988 | F27: =IS!C26+IS!C27 -> -14498057988 | G27: =IF(COUNT(E27:F27)=2,E27-F27,"") -> 0 | H27: 1 | I27: =IF(COUNT(E27:F27)<2,"N/A",IF(ABS(G27)<=H27,"OK","❌")) -> OK | J27: OK | K27: =IF(I27=J27,"✔ sesuai","✖ TIDAK sesuai") -> ✔ sesuai
A28: 22 | B28: Integritas laporan | C28: IS: laba komprehensif = induk + NCI | D28: 2020 | E28: =IS!C24 -> -9501240248 | F28: =IS!C28+IS!C29 -> -9501240248 | G28: =IF(COUNT(E28:F28)=2,E28-F28,"") -> 0 | H28: 1 | I28: =IF(COUNT(E28:F28)<2,"N/A",IF(ABS(G28)<=H28,"OK","❌")) -> OK | J28: OK | K28: =IF(I28=J28,"✔ sesuai","✖ TIDAK sesuai") -> ✔ sesuai
A29: 23 | B29: Integritas laporan | C29: CF: kas akhir LAK + rekonsiliasi definisi kas (memo) = kas neraca | D29: 2020 | E29: =CF!C41+N(CF!C44) -> 629608688874 | F29: =BS!C6 -> 629608688874 | G29: =IF(COUNT(E29:F29)=2,E29-F29,"") -> 0 | H29: 1 | I29: =IF(COUNT(E29:F29)<2,"N/A",IF(ABS(G29)<=H29,"OK","❌")) -> OK | J29: OK | K29: =IF(I29=J29,"✔ sesuai","✖ TIDAK sesuai") -> ✔ sesuai
A30: 24 | B30: Integritas laporan | C30: LPE: dividen ke pemilik induk = dividen dibayar (CF) | D30: 2020 | E30: 0 | F30: =CF!C36 -> 0 | G30: =IF(COUNT(E30:F30)=2,E30-F30,"") -> 0 | H30: 1 | I30: =IF(COUNT(E30:F30)<2,"N/A",IF(ABS(G30)<=H30,"OK","❌")) -> OK | J30: OK | K30: =IF(I30=J30,"✔ sesuai","✖ TIDAK sesuai") -> ✔ sesuai | L30: LPE: 2020: awal periode model
A31: 25 | B31: CALK vs laporan | C31: Cat 26: obat + rawat inap + rawat jalan & penunjang + lainnya/diskon = pendapatan IS | D31: 2020 | E31: =Schedules!C10 -> 1283798609174 | F31: =IS!C6 -> 1283798609174 | G31: =IF(COUNT(E31:F31)=2,E31-F31,"") -> 0 | H31: 1 | I31: =IF(COUNT(E31:F31)<2,"N/A",IF(ABS(G31)<=H31,"OK","❌")) -> OK | J31: OK | K31: =IF(I31=J31,"✔ sesuai","✖ TIDAK sesuai") -> ✔ sesuai
A32: 26 | B32: CALK vs laporan | C32: Cat 26: jumlah pendapatan tercetak = IS | D32: 2020 | E32: =Schedules!C58 -> 1283798609174 | F32: =IS!C6 -> 1283798609174 | G32: =IF(COUNT(E32:F32)=2,E32-F32,"") -> 0 | H32: 1 | I32: =IF(COUNT(E32:F32)<2,"N/A",IF(ABS(G32)<=H32,"OK","❌")) -> OK | J32: OK | K32: =IF(I32=J32,"✔ sesuai","✖ TIDAK sesuai") -> ✔ sesuai
A33: 27 | B33: CALK vs laporan | C33: Cat 27: jumlah beban pokok tercetak = IS | D33: 2020 | E33: =Schedules!C77 -> 864698280519 | F33: =-IS!C7 -> 864698280519 | G33: =IF(COUNT(E33:F33)=2,E33-F33,"") -> 0 | H33: 1 | I33: =IF(COUNT(E33:F33)<2,"N/A",IF(ABS(G33)<=H33,"OK","❌")) -> OK | J33: OK | K33: =IF(I33=J33,"✔ sesuai","✖ TIDAK sesuai") -> ✔ sesuai
A34: 28 | B34: CALK vs laporan | C34: Cat 28: jumlah beban umum & administrasi tercetak = IS | D34: 2020 | E34: =Schedules!C106 -> 392704802139 | F34: =-IS!C10 -> 392704802139 | G34: =IF(COUNT(E34:F34)=2,E34-F34,"") -> 0 | H34: 1 | I34: =IF(COUNT(E34:F34)<2,"N/A",IF(ABS(G34)<=H34,"OK","❌")) -> OK | J34: OK | K34: =IF(I34=J34,"✔ sesuai","✖ TIDAK sesuai") -> ✔ sesuai
A35: 29 | B35: CALK vs laporan | C35: Cat 30: jumlah pendapatan lain-lain neto tercetak = IS | D35: 2020 | E35: =Schedules!C130 -> 28429533228 | F35: =IS!C12 -> 28429533228 | G35: =IF(COUNT(E35:F35)=2,E35-F35,"") -> 0 | H35: 1 | I35: =IF(COUNT(E35:F35)<2,"N/A",IF(ABS(G35)<=H35,"OK","❌")) -> OK | J35: OK | K35: =IF(I35=J35,"✔ sesuai","✖ TIDAK sesuai") -> ✔ sesuai
A36: 30 | B36: CALK vs laporan | C36: Cat aset tetap: nilai tercatat aset tetap (biaya + akumulasi) = BS | D36: 2020 | E36: =Schedules!C44 -> 2641613456689 | F36: =BS!C19 -> 2641613456689 | G36: =IF(COUNT(E36:F36)=2,E36-F36,"") -> 0 | H36: 1 | I36: =IF(COUNT(E36:F36)<2,"N/A",IF(ABS(G36)<=H36,"OK","❌")) -> OK | J36: OK | K36: =IF(I36=J36,"✔ sesuai","✖ TIDAK sesuai") -> ✔ sesuai
A37: 31 | B37: CALK internal | C37: Cat 27+28: penyusutan aset tetap di laba rugi = penambahan akumulasi Cat aset tetap | D37: 2020 | E37: =Schedules!C14 -> 103003029087 | F37: =Schedules!C15 -> 103003029087 | G37: =IF(COUNT(E37:F37)=2,E37-F37,"") -> 0 | H37: 1 | I37: =IF(COUNT(E37:F37)<2,"N/A",IF(ABS(G37)<=H37,"OK","❌")) -> OK | J37: OK | K37: =IF(I37=J37,"✔ sesuai","✖ TIDAK sesuai") -> ✔ sesuai
A38: 32 | B38: CALK internal | C38: Cat aset tetap Aset tetap - biaya perolehan: awal + mutasi = akhir | D38: 2020 | E38: =Schedules!C35 -> 3371822743790 | F38: =Schedules!C34 -> 3371822743790 | G38: =IF(COUNT(E38:F38)=2,E38-F38,"") -> 0 | H38: 1 | I38: =IF(COUNT(E38:F38)<2,"N/A",IF(ABS(G38)<=H38,"OK","❌")) -> OK | J38: OK | K38: =IF(I38=J38,"✔ sesuai","✖ TIDAK sesuai") -> ✔ sesuai
A39: 33 | B39: CALK internal | C39: Cat aset tetap Aset tetap - akumulasi penyusutan: awal + mutasi = akhir | D39: 2020 | E39: =Schedules!C43 -> -730209287101 | F39: =Schedules!C42 -> -730209287101 | G39: =IF(COUNT(E39:F39)=2,E39-F39,"") -> 0 | H39: 1 | I39: =IF(COUNT(E39:F39)<2,"N/A",IF(ABS(G39)<=H39,"OK","❌")) -> OK | J39: OK | K39: =IF(I39=J39,"✔ sesuai","✖ TIDAK sesuai") -> ✔ sesuai
A40: 34 | B40: CALK internal | C40: Cat 26: Σ rincian = Jumlah tercetak | D40: 2020 | E40: =Schedules!C67 -> 1283798609174 | F40: =Schedules!C58 -> 1283798609174 | G40: =IF(COUNT(E40:F40)=2,E40-F40,"") -> 0 | H40: 1 | I40: =IF(COUNT(E40:F40)<2,"N/A",IF(ABS(G40)<=H40,"OK","❌")) -> OK | J40: OK | K40: =IF(I40=J40,"✔ sesuai","✖ TIDAK sesuai") -> ✔ sesuai
A41: 35 | B41: CALK internal | C41: Cat 27: Σ rincian = Jumlah tercetak | D41: 2020 | E41: =Schedules!C85 -> 864698280519 | F41: =Schedules!C77 -> 864698280519 | G41: =IF(COUNT(E41:F41)=2,E41-F41,"") -> 0 | H41: 1 | I41: =IF(COUNT(E41:F41)<2,"N/A",IF(ABS(G41)<=H41,"OK","❌")) -> OK | J41: OK | K41: =IF(I41=J41,"✔ sesuai","✖ TIDAK sesuai") -> ✔ sesuai
A42: 36 | B42: CALK internal | C42: Cat 28: Σ rincian = Jumlah tercetak | D42: 2020 | E42: =Schedules!C120 -> 392704802139 | F42: =Schedules!C106 -> 392704802139 | G42: =IF(COUNT(E42:F42)=2,E42-F42,"") -> 0 | H42: 1 | I42: =IF(COUNT(E42:F42)<2,"N/A",IF(ABS(G42)<=H42,"OK","❌")) -> OK | J42: OK | K42: =IF(I42=J42,"✔ sesuai","✖ TIDAK sesuai") -> ✔ sesuai
A43: 37 | B43: CALK internal | C43: Cat 30: Σ rincian = Jumlah tercetak | D43: 2020 | E43: =Schedules!C148 -> 28429533228 | F43: =Schedules!C130 -> 28429533228 | G43: =IF(COUNT(E43:F43)=2,E43-F43,"") -> 0 | H43: 1 | I43: =IF(COUNT(E43:F43)<2,"N/A",IF(ABS(G43)<=H43,"OK","❌")) -> OK | J43: OK | K43: =IF(I43=J43,"✔ sesuai","✖ TIDAK sesuai") -> ✔ sesuai
A44: 38 | B44: Per saham | C44: EPS tercetak vs laba induk / saham rata-rata tertimbang CALK (toleransi Rp1) | D44: 2020 | E44: =IS!C30 -> -1.2 | F44: =ROUND(IS!C26/Schedules!C22,2) -> -1.2 | G44: =IF(COUNT(E44:F44)=2,E44-F44,"") -> 0 | H44: 1 | I44: =IF(COUNT(E44:F44)<2,"N/A",IF(ABS(G44)<=H44,"OK","❌")) -> OK | J44: OK | K44: =IF(I44=J44,"✔ sesuai","✖ TIDAK sesuai") -> ✔ sesuai
A45: 39 | B45: Subtotal rumus vs tercetak | C45: IS: GROSS_PROFIT rumus = tercetak | D45: 2021 | E45: =IS!D8 -> 705032736652 | F45: =IS!D32 -> 705032736652 | G45: =IF(COUNT(E45:F45)=2,E45-F45,"") -> 0 | H45: 1 | I45: =IF(COUNT(E45:F45)<2,"N/A",IF(ABS(G45)<=H45,"OK","❌")) -> OK | J45: OK | K45: =IF(I45=J45,"✔ sesuai","✖ TIDAK sesuai") -> ✔ sesuai
A46: 40 | B46: Subtotal rumus vs tercetak | C46: IS: PBT rumus = tercetak | D46: 2021 | E46: =IS!D17 -> 156419509835 | F46: =IS!D33 -> 156419509835 | G46: =IF(COUNT(E46:F46)=2,E46-F46,"") -> 0 | H46: 1 | I46: =IF(COUNT(E46:F46)<2,"N/A",IF(ABS(G46)<=H46,"OK","❌")) -> OK | J46: OK | K46: =IF(I46=J46,"✔ sesuai","✖ TIDAK sesuai") -> ✔ sesuai
A47: 41 | B47: Subtotal rumus vs tercetak | C47: IS: NET_INCOME rumus = tercetak | D47: 2021 | E47: =IS!D19 -> 165604046574 | F47: =IS!D34 -> 165604046574 | G47: =IF(COUNT(E47:F47)=2,E47-F47,"") -> 0 | H47: 1 | I47: =IF(COUNT(E47:F47)<2,"N/A",IF(ABS(G47)<=H47,"OK","❌")) -> OK | J47: OK | K47: =IF(I47=J47,"✔ sesuai","✖ TIDAK sesuai") -> ✔ sesuai
A48: 42 | B48: Subtotal rumus vs tercetak | C48: IS: OCI_TOTAL rumus = tercetak | D48: 2021 | E48: =IS!D23 -> 7062226345 | F48: =IS!D35 -> 7062226345 | G48: =IF(COUNT(E48:F48)=2,E48-F48,"") -> 0 | H48: 1 | I48: =IF(COUNT(E48:F48)<2,"N/A",IF(ABS(G48)<=H48,"OK","❌")) -> OK | J48: OK | K48: =IF(I48=J48,"✔ sesuai","✖ TIDAK sesuai") -> ✔ sesuai
A49: 43 | B49: Subtotal rumus vs tercetak | C49: IS: TCI rumus = tercetak | D49: 2021 | E49: =IS!D24 -> 172666272919 | F49: =IS!D36 -> 172666272919 | G49: =IF(COUNT(E49:F49)=2,E49-F49,"") -> 0 | H49: 1 | I49: =IF(COUNT(E49:F49)<2,"N/A",IF(ABS(G49)<=H49,"OK","❌")) -> OK | J49: OK | K49: =IF(I49=J49,"✔ sesuai","✖ TIDAK sesuai") -> ✔ sesuai
A50: 44 | B50: Subtotal rumus vs tercetak | C50: BS: TOTAL_CA rumus = tercetak | D50: 2021 | E50: =BS!D16 -> 1021454537372 | F50: =BS!D68 -> 1021454537372 | G50: =IF(COUNT(E50:F50)=2,E50-F50,"") -> 0 | H50: 1 | I50: =IF(COUNT(E50:F50)<2,"N/A",IF(ABS(G50)<=H50,"OK","❌")) -> OK | J50: OK | K50: =IF(I50=J50,"✔ sesuai","✖ TIDAK sesuai") -> ✔ sesuai
A51: 45 | B51: Subtotal rumus vs tercetak | C51: BS: TOTAL_NCA rumus = tercetak | D51: 2021 | E51: =BS!D26 -> 3850352070989 | F51: =BS!D69 -> 3850352070989 | G51: =IF(COUNT(E51:F51)=2,E51-F51,"") -> 0 | H51: 1 | I51: =IF(COUNT(E51:F51)<2,"N/A",IF(ABS(G51)<=H51,"OK","❌")) -> OK | J51: OK | K51: =IF(I51=J51,"✔ sesuai","✖ TIDAK sesuai") -> ✔ sesuai
A52: 46 | B52: Subtotal rumus vs tercetak | C52: BS: TOTAL_ASSETS rumus = tercetak | D52: 2021 | E52: =BS!D27 -> 4871806608361 | F52: =BS!D70 -> 4871806608361 | G52: =IF(COUNT(E52:F52)=2,E52-F52,"") -> 0 | H52: 1 | I52: =IF(COUNT(E52:F52)<2,"N/A",IF(ABS(G52)<=H52,"OK","❌")) -> OK | J52: OK | K52: =IF(I52=J52,"✔ sesuai","✖ TIDAK sesuai") -> ✔ sesuai
A53: 47 | B53: Subtotal rumus vs tercetak | C53: BS: TOTAL_CL rumus = tercetak | D53: 2021 | E53: =BS!D43 -> 2659180898777 | F53: =BS!D71 -> 2659180898777 | G53: =IF(COUNT(E53:F53)=2,E53-F53,"") -> 0 | H53: 1 | I53: =IF(COUNT(E53:F53)<2,"N/A",IF(ABS(G53)<=H53,"OK","❌")) -> OK | J53: OK | K53: =IF(I53=J53,"✔ sesuai","✖ TIDAK sesuai") -> ✔ sesuai
A54: 48 | B54: Subtotal rumus vs tercetak | C54: BS: TOTAL_NCL rumus = tercetak | D54: 2021 | E54: =BS!D52 -> 285223163901 | F54: =BS!D72 -> 285223163901 | G54: =IF(COUNT(E54:F54)=2,E54-F54,"") -> 0 | H54: 1 | I54: =IF(COUNT(E54:F54)<2,"N/A",IF(ABS(G54)<=H54,"OK","❌")) -> OK | J54: OK | K54: =IF(I54=J54,"✔ sesuai","✖ TIDAK sesuai") -> ✔ sesuai
A55: 49 | B55: Subtotal rumus vs tercetak | C55: BS: TOTAL_LIAB rumus = tercetak | D55: 2021 | E55: =BS!D53 -> 2944404062678 | F55: =BS!D73 -> 2944404062678 | G55: =IF(COUNT(E55:F55)=2,E55-F55,"") -> 0 | H55: 1 | I55: =IF(COUNT(E55:F55)<2,"N/A",IF(ABS(G55)<=H55,"OK","❌")) -> OK | J55: OK | K55: =IF(I55=J55,"✔ sesuai","✖ TIDAK sesuai") -> ✔ sesuai
A56: 50 | B56: Subtotal rumus vs tercetak | C56: BS: EQUITY_PARENT rumus = tercetak | D56: 2021 | E56: =BS!D60 -> 1926312704329 | F56: =BS!D74 -> 1926312704329 | G56: =IF(COUNT(E56:F56)=2,E56-F56,"") -> 0 | H56: 1 | I56: =IF(COUNT(E56:F56)<2,"N/A",IF(ABS(G56)<=H56,"OK","❌")) -> OK | J56: OK | K56: =IF(I56=J56,"✔ sesuai","✖ TIDAK sesuai") -> ✔ sesuai
A57: 51 | B57: Subtotal rumus vs tercetak | C57: BS: TOTAL_EQUITY rumus = tercetak | D57: 2021 | E57: =BS!D62 -> 1927402545683 | F57: =BS!D75 -> 1927402545683 | G57: =IF(COUNT(E57:F57)=2,E57-F57,"") -> 0 | H57: 1 | I57: =IF(COUNT(E57:F57)<2,"N/A",IF(ABS(G57)<=H57,"OK","❌")) -> OK | J57: OK | K57: =IF(I57=J57,"✔ sesuai","✖ TIDAK sesuai") -> ✔ sesuai
A58: 52 | B58: Subtotal rumus vs tercetak | C58: BS: TOTAL_LIAB_EQUITY rumus = tercetak | D58: 2021 | E58: =BS!D63 -> 4871806608361 | F58: =BS!D76 -> 4871806608361 | G58: =IF(COUNT(E58:F58)=2,E58-F58,"") -> 0 | H58: 1 | I58: =IF(COUNT(E58:F58)<2,"N/A",IF(ABS(G58)<=H58,"OK","❌")) -> OK | J58: OK | K58: =IF(I58=J58,"✔ sesuai","✖ TIDAK sesuai") -> ✔ sesuai
A59: 53 | B59: Subtotal rumus vs tercetak | C59: CF: CFO rumus = tercetak | D59: 2021 | E59: =CF!D13 -> 336786662790 | F59: =CF!D46 -> 336786662790 | G59: =IF(COUNT(E59:F59)=2,E59-F59,"") -> 0 | H59: 1 | I59: =IF(COUNT(E59:F59)<2,"N/A",IF(ABS(G59)<=H59,"OK","❌")) -> OK | J59: OK | K59: =IF(I59=J59,"✔ sesuai","✖ TIDAK sesuai") -> ✔ sesuai
A60: 54 | B60: Subtotal rumus vs tercetak | C60: CF: CFI rumus = tercetak | D60: 2021 | E60: =CF!D21 -> -468280289395 | F60: =CF!D47 -> -468280289395 | G60: =IF(COUNT(E60:F60)=2,E60-F60,"") -> 0 | H60: 1 | I60: =IF(COUNT(E60:F60)<2,"N/A",IF(ABS(G60)<=H60,"OK","❌")) -> OK | J60: OK | K60: =IF(I60=J60,"✔ sesuai","✖ TIDAK sesuai") -> ✔ sesuai
A61: 55 | B61: Subtotal rumus vs tercetak | C61: CF: CFF rumus = tercetak | D61: 2021 | E61: =CF!D37 -> 179238263141 | F61: =CF!D48 -> 179238263141 | G61: =IF(COUNT(E61:F61)=2,E61-F61,"") -> 0 | H61: 1 | I61: =IF(COUNT(E61:F61)<2,"N/A",IF(ABS(G61)<=H61,"OK","❌")) -> OK | J61: OK | K61: =IF(I61=J61,"✔ sesuai","✖ TIDAK sesuai") -> ✔ sesuai
A62: 56 | B62: Subtotal rumus vs tercetak | C62: CF: NET_CHANGE rumus = tercetak | D62: 2021 | E62: =CF!D38 -> 47744636536 | F62: =CF!D49 -> 47744636536 | G62: =IF(COUNT(E62:F62)=2,E62-F62,"") -> 0 | H62: 1 | I62: =IF(COUNT(E62:F62)<2,"N/A",IF(ABS(G62)<=H62,"OK","❌")) -> OK | J62: OK | K62: =IF(I62=J62,"✔ sesuai","✖ TIDAK sesuai") -> ✔ sesuai
A63: 57 | B63: Subtotal rumus vs tercetak | C63: CF: CASH_END rumus = tercetak | D63: 2021 | E63: =CF!D41 -> 700922359619 | F63: =CF!D50 -> 700922359619 | G63: =IF(COUNT(E63:F63)=2,E63-F63,"") -> 0 | H63: 1 | I63: =IF(COUNT(E63:F63)<2,"N/A",IF(ABS(G63)<=H63,"OK","❌")) -> OK | J63: OK | K63: =IF(I63=J63,"✔ sesuai","✖ TIDAK sesuai") -> ✔ sesuai
A64: 58 | B64: Integritas laporan | C64: BS: aset = liabilitas + ekuitas | D64: 2021 | E64: =BS!D27 -> 4871806608361 | F64: =BS!D63 -> 4871806608361 | G64: =IF(COUNT(E64:F64)=2,E64-F64,"") -> 0 | H64: 1 | I64: =IF(COUNT(E64:F64)<2,"N/A",IF(ABS(G64)<=H64,"OK","❌")) -> OK | J64: OK | K64: =IF(I64=J64,"✔ sesuai","✖ TIDAK sesuai") -> ✔ sesuai
A65: 59 | B65: Integritas laporan | C65: IS: laba = induk + NCI | D65: 2021 | E65: =IS!D19 -> 165604046574 | F65: =IS!D26+IS!D27 -> 165604046574 | G65: =IF(COUNT(E65:F65)=2,E65-F65,"") -> 0 | H65: 1 | I65: =IF(COUNT(E65:F65)<2,"N/A",IF(ABS(G65)<=H65,"OK","❌")) -> OK | J65: OK | K65: =IF(I65=J65,"✔ sesuai","✖ TIDAK sesuai") -> ✔ sesuai
A66: 60 | B66: Integritas laporan | C66: IS: laba komprehensif = induk + NCI | D66: 2021 | E66: =IS!D24 -> 172666272919 | F66: =IS!D28+IS!D29 -> 172666272919 | G66: =IF(COUNT(E66:F66)=2,E66-F66,"") -> 0 | H66: 1 | I66: =IF(COUNT(E66:F66)<2,"N/A",IF(ABS(G66)<=H66,"OK","❌")) -> OK | J66: OK | K66: =IF(I66=J66,"✔ sesuai","✖ TIDAK sesuai") -> ✔ sesuai
A67: 61 | B67: Integritas laporan | C67: CF: kas akhir LAK + rekonsiliasi definisi kas (memo) = kas neraca | D67: 2021 | E67: =CF!D41+N(CF!D44) -> 700922359619 | F67: =BS!D6 -> 700922359619 | G67: =IF(COUNT(E67:F67)=2,E67-F67,"") -> 0 | H67: 1 | I67: =IF(COUNT(E67:F67)<2,"N/A",IF(ABS(G67)<=H67,"OK","❌")) -> OK | J67: OK | K67: =IF(I67=J67,"✔ sesuai","✖ TIDAK sesuai") -> ✔ sesuai
A68: 62 | B68: Integritas laporan | C68: LPE: dividen ke pemilik induk = dividen dibayar (CF) | D68: 2021 | E68: 0 | F68: =CF!D36 -> 0 | G68: =IF(COUNT(E68:F68)=2,E68-F68,"") -> 0 | H68: 1 | I68: =IF(COUNT(E68:F68)<2,"N/A",IF(ABS(G68)<=H68,"OK","❌")) -> OK | J68: OK | K68: =IF(I68=J68,"✔ sesuai","✖ TIDAK sesuai") -> ✔ sesuai | L68: LPE: LPE LK FY2021: rugi/laba induk ke saldo laba; tanpa dividen
A69: 63 | B69: Antar tahun | C69: CF: kas awal LAK + rekonsiliasi definisi kas (memo) = kas neraca tahun lalu | D69: 2021 | E69: =CF!D40+N(CF!D43) -> 629608688874 | F69: =BS!C6 -> 629608688874 | G69: =IF(COUNT(E69:F69)=2,E69-F69,"") -> 0 | H69: 1 | I69: =IF(COUNT(E69:F69)<2,"N/A",IF(ABS(G69)<=H69,"OK","❌")) -> OK | J69: OK | K69: =IF(I69=J69,"✔ sesuai","✖ TIDAK sesuai") -> ✔ sesuai | L69: selisih definisi kas / penyajian kembali (Temuan S5)
A70: 64 | B70: Antar tahun | C70: Saldo laba: awal + laba komprehensif ke saldo laba (LPE) + dividen (CF) + lainnya (LPE) = akhir | D70: 2021 | E70: =BS!C59+165308238619+CF!D36+0 -> -435380567809 | F70: =BS!D59 -> -435380567809 | G70: =IF(COUNT(E70:F70)=2,E70-F70,"") -> 0 | H70: 1 | I70: =IF(COUNT(E70:F70)<2,"N/A",IF(ABS(G70)<=H70,"OK","❌")) -> OK | J70: OK | K70: =IF(I70=J70,"✔ sesuai","✖ TIDAK sesuai") -> ✔ sesuai | L70: saldo laba = ditentukan + belum ditentukan penggunaannya; OCI (pengukuran kembali imbalan kerja) di kolom terpisah; lainnya = pos LPE lain (lihat SRAJ_cek_silang.json; 2023 = pembulatan Rp juta). Angka statis LPE dari SRAJ_cek_silang.json
A71: 65 | B71: Antar tahun | C71: Mutasi aset tetap: saldo awal biaya = saldo akhir tahun lalu | D71: 2021 | E71: =Schedules!D29 -> 3448224531705 | F71: =Schedules!C34 -> 3371822743790 | G71: =IF(COUNT(E71:F71)=2,E71-F71,"") -> 76401787915 | H71: 1 | I71: =IF(COUNT(E71:F71)<2,"N/A",IF(ABS(G71)<=H71,"OK","❌")) -> ❌ | J71: ❌ | K71: =IF(I71=J71,"✔ sesuai","✖ TIDAK sesuai") -> ✔ sesuai | L71: Temuan S8: LK FY2021 menyajikan saldo awal biaya perolehan 3.448.224.531.705 vs saldo akhir LK FY2020 3.371.822.743.790 (reklasifikasi 76.403.871.248 dari aset tidak lancar lain ke aset tetap di LK FY2021).
A72: 66 | B72: Antar tahun | C72: Mutasi aset tetap: saldo awal akumulasi = saldo akhir tahun lalu | D72: 2021 | E72: =Schedules!D37 -> -730207203768 | F72: =Schedules!C42 -> -730209287101 | G72: =IF(COUNT(E72:F72)=2,E72-F72,"") -> 2083333 | H72: 1 | I72: =IF(COUNT(E72:F72)<2,"N/A",IF(ABS(G72)<=H72,"OK","❌")) -> ❌ | J72: ❌ | K72: =IF(I72=J72,"✔ sesuai","✖ TIDAK sesuai") -> ✔ sesuai | L72: Temuan S8: saldo awal akumulasi LK FY2021 -730.207.203.768 vs saldo akhir LK FY2020 -730.209.287.101 (selisih 2.083.333 dari reklasifikasi yang sama).
A73: 67 | B73: CALK vs laporan | C73: Cat 26: obat + rawat inap + rawat jalan & penunjang + lainnya/diskon = pendapatan IS | D73: 2021 | E73: =Schedules!D10 -> 1924453140978 | F73: =IS!D6 -> 1924453140978 | G73: =IF(COUNT(E73:F73)=2,E73-F73,"") -> 0 | H73: 1 | I73: =IF(COUNT(E73:F73)<2,"N/A",IF(ABS(G73)<=H73,"OK","❌")) -> OK | J73: OK | K73: =IF(I73=J73,"✔ sesuai","✖ TIDAK sesuai") -> ✔ sesuai
A74: 68 | B74: CALK vs laporan | C74: Cat 26: jumlah pendapatan tercetak = IS | D74: 2021 | E74: =Schedules!D58 -> 1924453140978 | F74: =IS!D6 -> 1924453140978 | G74: =IF(COUNT(E74:F74)=2,E74-F74,"") -> 0 | H74: 1 | I74: =IF(COUNT(E74:F74)<2,"N/A",IF(ABS(G74)<=H74,"OK","❌")) -> OK | J74: OK | K74: =IF(I74=J74,"✔ sesuai","✖ TIDAK sesuai") -> ✔ sesuai
A75: 69 | B75: CALK vs laporan | C75: Cat 27: jumlah beban pokok tercetak = IS | D75: 2021 | E75: =Schedules!D77 -> 1219420404326 | F75: =-IS!D7 -> 1219420404326 | G75: =IF(COUNT(E75:F75)=2,E75-F75,"") -> 0 | H75: 1 | I75: =IF(COUNT(E75:F75)<2,"N/A",IF(ABS(G75)<=H75,"OK","❌")) -> OK | J75: OK | K75: =IF(I75=J75,"✔ sesuai","✖ TIDAK sesuai") -> ✔ sesuai
A76: 70 | B76: CALK vs laporan | C76: Cat 28: jumlah beban umum & administrasi tercetak = IS | D76: 2021 | E76: =Schedules!D106 -> 462409623024 | F76: =-IS!D10 -> 462409623024 | G76: =IF(COUNT(E76:F76)=2,E76-F76,"") -> 0 | H76: 1 | I76: =IF(COUNT(E76:F76)<2,"N/A",IF(ABS(G76)<=H76,"OK","❌")) -> OK | J76: OK | K76: =IF(I76=J76,"✔ sesuai","✖ TIDAK sesuai") -> ✔ sesuai
A77: 71 | B77: CALK vs laporan | C77: Cat 30: jumlah pendapatan lain-lain neto tercetak = IS | D77: 2021 | E77: =Schedules!D130 -> 24028154926 | F77: =IS!D12 -> 24028154926 | G77: =IF(COUNT(E77:F77)=2,E77-F77,"") -> 0 | H77: 1 | I77: =IF(COUNT(E77:F77)<2,"N/A",IF(ABS(G77)<=H77,"OK","❌")) -> OK | J77: OK | K77: =IF(I77=J77,"✔ sesuai","✖ TIDAK sesuai") -> ✔ sesuai
A78: 72 | B78: CALK vs laporan | C78: Cat aset tetap: nilai tercatat aset tetap (biaya + akumulasi) = BS | D78: 2021 | E78: =Schedules!D44 -> 3169775593830 | F78: =BS!D19 -> 3169775593830 | G78: =IF(COUNT(E78:F78)=2,E78-F78,"") -> 0 | H78: 1 | I78: =IF(COUNT(E78:F78)<2,"N/A",IF(ABS(G78)<=H78,"OK","❌")) -> OK | J78: OK | K78: =IF(I78=J78,"✔ sesuai","✖ TIDAK sesuai") -> ✔ sesuai
A79: 73 | B79: CALK internal | C79: Cat 27+28: penyusutan aset tetap di laba rugi = penambahan akumulasi Cat aset tetap | D79: 2021 | E79: =Schedules!D14 -> 149515108834 | F79: =Schedules!D15 -> 149515108834 | G79: =IF(COUNT(E79:F79)=2,E79-F79,"") -> 0 | H79: 1 | I79: =IF(COUNT(E79:F79)<2,"N/A",IF(ABS(G79)<=H79,"OK","❌")) -> OK | J79: OK | K79: =IF(I79=J79,"✔ sesuai","✖ TIDAK sesuai") -> ✔ sesuai
A80: 74 | B80: CALK internal | C80: Cat aset tetap Aset tetap - biaya perolehan: awal + mutasi = akhir | D80: 2021 | E80: =Schedules!D35 -> 4045883925132 | F80: =Schedules!D34 -> 4045883925132 | G80: =IF(COUNT(E80:F80)=2,E80-F80,"") -> 0 | H80: 1 | I80: =IF(COUNT(E80:F80)<2,"N/A",IF(ABS(G80)<=H80,"OK","❌")) -> OK | J80: OK | K80: =IF(I80=J80,"✔ sesuai","✖ TIDAK sesuai") -> ✔ sesuai
A81: 75 | B81: CALK internal | C81: Cat aset tetap Aset tetap - akumulasi penyusutan: awal + mutasi = akhir | D81: 2021 | E81: =Schedules!D43 -> -876108331302 | F81: =Schedules!D42 -> -876108331302 | G81: =IF(COUNT(E81:F81)=2,E81-F81,"") -> 0 | H81: 1 | I81: =IF(COUNT(E81:F81)<2,"N/A",IF(ABS(G81)<=H81,"OK","❌")) -> OK | J81: OK | K81: =IF(I81=J81,"✔ sesuai","✖ TIDAK sesuai") -> ✔ sesuai
A82: 76 | B82: CALK internal | C82: Cat 26: Σ rincian = Jumlah tercetak | D82: 2021 | E82: =Schedules!D67 -> 1924453140978 | F82: =Schedules!D58 -> 1924453140978 | G82: =IF(COUNT(E82:F82)=2,E82-F82,"") -> 0 | H82: 1 | I82: =IF(COUNT(E82:F82)<2,"N/A",IF(ABS(G82)<=H82,"OK","❌")) -> OK | J82: OK | K82: =IF(I82=J82,"✔ sesuai","✖ TIDAK sesuai") -> ✔ sesuai
A83: 77 | B83: CALK internal | C83: Cat 27: Σ rincian = Jumlah tercetak | D83: 2021 | E83: =Schedules!D85 -> 1219420404326 | F83: =Schedules!D77 -> 1219420404326 | G83: =IF(COUNT(E83:F83)=2,E83-F83,"") -> 0 | H83: 1 | I83: =IF(COUNT(E83:F83)<2,"N/A",IF(ABS(G83)<=H83,"OK","❌")) -> OK | J83: OK | K83: =IF(I83=J83,"✔ sesuai","✖ TIDAK sesuai") -> ✔ sesuai
A84: 78 | B84: CALK internal | C84: Cat 28: Σ rincian = Jumlah tercetak | D84: 2021 | E84: =Schedules!D120 -> 462409623024 | F84: =Schedules!D106 -> 462409623024 | G84: =IF(COUNT(E84:F84)=2,E84-F84,"") -> 0 | H84: 1 | I84: =IF(COUNT(E84:F84)<2,"N/A",IF(ABS(G84)<=H84,"OK","❌")) -> OK | J84: OK | K84: =IF(I84=J84,"✔ sesuai","✖ TIDAK sesuai") -> ✔ sesuai
